{
  "type": "Feature",
  "properties": {
    "iso:country":"US",
    "sg:address":"830 N Spruce St",
    "sg:city":"Wilmington",
    "sg:classifiers":[
        {
            "category":"Organizations",
            "subcategory":"Non-profit Organization",
            "type":"Services"
        }
    ],
    "sg:phone":"+1 302 652 8947",
    "sg:postcode":"19801",
    "sg:province":"DE",
    "sg:tags":[
        "social"
    ],
    "wof:name":"Pierre Toussanit Dental Inc",
    "wof:placetype":"venue"
},
  "geometry": {"coordinates":[-75.54104100000001,39.74164],"type":"Point"}
}