{
  "type": "Feature",
  "properties": {
    "addr:full":"38223 Dupont Blvd Selbyville DE 19975",
    "addr:housenumber":"38223",
    "addr:postcode":"19975",
    "addr:street":"Dupont Blvd",
    "iso:country":"US",
    "sg:address":"38223 Dupont Blvd",
    "sg:city":"Selbyville",
    "sg:classifiers":[
        {
            "category":"Banks & Credit Unions",
            "subcategory":"Financial Services",
            "type":"Services"
        }
    ],
    "sg:phone":"+1 302 436 9831",
    "sg:postcode":"19975",
    "sg:province":"DE",
    "sg:tags":[
        "cashing",
        "loan",
        "payday",
        "alternative",
        "check"
    ],
    "sg:website":"http://www.acecashexpress.com",
    "wof:name":"ACE Cash Express",
    "wof:placetype":"venue"
},
  "geometry": {"coordinates":[-75.233374,38.458969],"type":"Point"}
}