{
  "type": "Feature",
  "properties": {
    "iso:country":"US",
    "sg:address":"5 April Ln",
    "sg:city":"Wilmington",
    "sg:classifiers":[
        {
            "category":"Health Services",
            "subcategory":"Health Practitioner",
            "type":"Services"
        }
    ],
    "sg:phone":"+1 302 475 5216",
    "sg:postcode":"19810",
    "sg:province":"DE",
    "wof:name":"Psychological",
    "wof:placetype":"venue"
},
  "geometry": {"coordinates":[-75.48800799999999,39.806329],"type":"Point"}
}