{
  "type": "Feature",
  "properties": {
    "addr:full":"230 Executive Dr Newark DE 19702",
    "addr:housenumber":"230",
    "addr:postcode":"19702",
    "addr:street":"Executive Dr",
    "iso:country":"US",
    "sg:address":"230 Executive Dr",
    "sg:city":"Newark",
    "sg:classifiers":[
        {
            "category":"Home & Garden",
            "subcategory":"Furniture",
            "type":"Retail Goods"
        },
        {
            "category":"Building & Trades",
            "subcategory":"Construction",
            "type":"Services"
        }
    ],
    "sg:phone":"+1 302 738 2737",
    "sg:postcode":"19702",
    "sg:province":"DE",
    "sg:tags":[
        "builder",
        "custom",
        "contractor"
    ],
    "wof:name":"Furniture Solutions",
    "wof:placetype":"venue"
},
  "geometry": {"coordinates":[-75.74957000000001,39.613562],"type":"Point"}
}