{
  "type": "Feature",
  "properties": {
    "iso:country":"US",
    "sg:address":"1585 McKee Rd",
    "sg:city":"Dover",
    "sg:classifiers":[
        {
            "category":"Manufacturing",
            "subcategory":"Apparel",
            "type":"Manufacturing & Wholesale Goods"
        }
    ],
    "sg:phone":"+1 302 735 7600",
    "sg:postcode":"19904",
    "sg:province":"DE",
    "sg:tags":[
        "flag",
        "banner"
    ],
    "sg:website":"www.customdecornet.com",
    "wof:name":"Custom Decor Inc",
    "wof:placetype":"venue"
},
  "geometry": {"coordinates":[-75.564768,39.186293],"type":"Point"}
}