{
  "type": "Feature",
  "properties": {
    "addr:full":"1708 Newport Gap Pike Wilmington DE 19808",
    "addr:housenumber":"1708",
    "addr:postcode":"19808",
    "addr:street":"Newport Gap Pike",
    "iso:country":"US",
    "sg:address":"1708 Newport Gap Pike",
    "sg:city":"Wilmington",
    "sg:classifiers":[
        {
            "category":"Utilities",
            "subcategory":"Mobile Phone",
            "type":"Services"
        }
    ],
    "sg:phone":"+1 302 636 7108",
    "sg:postcode":"19808",
    "sg:province":"DE",
    "sg:tags":[
        "communication",
        "radiotelephone"
    ],
    "wof:name":"Ansercomm",
    "wof:placetype":"venue"
},
  "geometry": {"coordinates":[-75.627831,39.733523],"type":"Point"}
}