{
  "type": "Feature",
  "properties": {
    "iso:country":"US",
    "sg:address":"92 Atlantic Ave",
    "sg:city":"Ocean View",
    "sg:classifiers":[
        {
            "category":"Insurance",
            "subcategory":"Title Insurance",
            "type":"Services"
        },
        {
            "category":"Real Estate",
            "subcategory":"Real Estate Services",
            "type":"Services"
        }
    ],
    "sg:phone":"+1 302 541 0400",
    "sg:postcode":"19970",
    "sg:province":"DE",
    "sg:tags":[
        "company",
        "carrier"
    ],
    "wof:name":"Brennan Title Company",
    "wof:placetype":"venue"
},
  "geometry": {"coordinates":[-75.081056,38.542598],"type":"Point"}
}