{
  "type": "Feature",
  "properties": {
    "iso:country":"US",
    "sg:address":"768 Townsend Blvd",
    "sg:city":"Dover",
    "sg:classifiers":[
        {
            "category":"Real Estate",
            "subcategory":"Real Estate Agent",
            "type":"Services"
        }
    ],
    "sg:phone":"+1 302 734 0800",
    "sg:postcode":"19901",
    "sg:province":"DE",
    "wof:name":"RE Max Avenues Real Estate LLC",
    "wof:placetype":"venue"
},
  "geometry": {"coordinates":[-75.52099200000001,39.175283],"type":"Point"}
}