{
  "type": "Feature",
  "properties": {
    "iso:country":"US",
    "sg:address":"713 S Washington St",
    "sg:city":"Milford",
    "sg:classifiers":[
        {
            "category":"Retail",
            "subcategory":"Laundry & Dry Cleaning",
            "type":"Services"
        }
    ],
    "sg:phone":"+1 302 430 0851",
    "sg:postcode":"19963",
    "sg:province":"DE",
    "sg:tags":[
        "commercial"
    ],
    "wof:name":"A P Linen Service",
    "wof:placetype":"venue"
},
  "geometry": {"coordinates":[-75.42630800000001,38.900875],"type":"Point"}
}