{
  "type": "Feature",
  "properties": {
    "addr:full":"600 N Dupont Hwy New Castle DE 19720",
    "addr:housenumber":"600",
    "addr:postcode":"19720",
    "addr:street":"N Dupont Hwy",
    "iso:country":"US",
    "sg:address":"600 N Dupont Hwy",
    "sg:city":"New Castle",
    "sg:classifiers":[
        {
            "category":"Retail",
            "subcategory":"Auto Repair",
            "type":"Services"
        }
    ],
    "sg:phone":"+1 302 328 5390",
    "sg:postcode":"19720",
    "sg:province":"DE",
    "sg:tags":[
        "wrecker"
    ],
    "wof:name":"Jim & Harold's Garage",
    "wof:placetype":"venue"
},
  "geometry": {"coordinates":[-75.586102,39.684906],"type":"Point"}
}