{
  "type": "Feature",
  "properties": {
    "iso:country":"US",
    "sg:address":"3204 Fordham Rd",
    "sg:city":"Wilmington",
    "sg:classifiers":[
        {
            "category":"Professional",
            "subcategory":"Management & Consulting",
            "type":"Services"
        }
    ],
    "sg:phone":"+1 302 655 3205",
    "sg:postcode":"19807",
    "sg:province":"DE",
    "wof:name":"Next Generation Radio",
    "wof:placetype":"venue"
},
  "geometry": {"coordinates":[-75.587113,39.756223],"type":"Point"}
}