{
  "type": "Feature",
  "properties": {
    "addr:full":"3 Toronto Cir Newark DE 19702",
    "addr:housenumber":"3",
    "addr:postcode":"19702",
    "addr:street":"Toronto Cir",
    "iso:country":"US",
    "sg:address":"3 Toronto Cir",
    "sg:city":"Newark",
    "sg:classifiers":[
        {
            "category":"Retail",
            "subcategory":"Repair Shop",
            "type":"Services"
        }
    ],
    "sg:phone":"+1 302 366 1370",
    "sg:postcode":"19702",
    "sg:province":"DE",
    "wof:name":"Commercial Marine Service",
    "wof:placetype":"venue"
},
  "geometry": {"coordinates":[-75.70786699999999,39.645368],"type":"Point"}
}