{
  "type": "Feature",
  "properties": {
    "iso:country":"US",
    "sg:address":"750 Kings Hwy",
    "sg:city":"Lewes",
    "sg:classifiers":[
        {
            "category":"Health Services",
            "subcategory":"Doctor",
            "type":"Services"
        }
    ],
    "sg:phone":"+1 302 644 4171",
    "sg:postcode":"19958",
    "sg:province":"DE",
    "wof:name":"Michael L Cahoon Dr",
    "wof:placetype":"venue"
},
  "geometry": {"coordinates":[-75.14475899999999,38.762708],"type":"Point"}
}