{
  "type": "Feature",
  "properties": {
    "addr:full":"1603 W Newport Pike Wilmington DE 19804",
    "addr:housenumber":"1603",
    "addr:postcode":"19804",
    "addr:street":"W Newport Pike",
    "iso:country":"US",
    "sg:address":"1603 W Newport Pike",
    "sg:city":"Wilmington",
    "sg:classifiers":[
        {
            "category":"Building & Trades",
            "subcategory":"Construction",
            "type":"Services"
        }
    ],
    "sg:phone":"+1 302 983 7991",
    "sg:postcode":"19804",
    "sg:province":"DE",
    "sg:tags":[
        "house"
    ],
    "wof:name":"Genos Construction",
    "wof:placetype":"venue"
},
  "geometry": {"coordinates":[-75.629074,39.715762],"type":"Point"}
}