{
  "type": "Feature",
  "properties": {
    "iso:country":"US",
    "sg:address":"18 W Periwinkle Ln",
    "sg:city":"Newark",
    "sg:classifiers":[
        {
            "category":"Government",
            "subcategory":"Office",
            "type":"Public Place"
        }
    ],
    "sg:phone":"+1 302 235 7156",
    "sg:postcode":"19711",
    "sg:province":"DE",
    "sg:tags":[
        "consultant"
    ],
    "wof:name":"David T Mage",
    "wof:placetype":"venue"
},
  "geometry": {"coordinates":[-75.73436700000001,39.767005],"type":"Point"}
}