{
  "type": "Feature",
  "properties": {
    "iso:country":"US",
    "sg:address":"925 S Broom St",
    "sg:city":"Wilmington",
    "sg:classifiers":[
        {
            "category":"Professional",
            "subcategory":"Computer Services",
            "type":"Services"
        }
    ],
    "sg:phone":"+1 302 421 9084",
    "sg:postcode":"19805",
    "sg:province":"DE",
    "wof:name":"Fv Technologies",
    "wof:placetype":"venue"
},
  "geometry": {"coordinates":[-75.57205500000001,39.737215],"type":"Point"}
}