{
  "type": "Feature",
  "properties": {
    "iso:country":"US",
    "sg:address":"724 Yorklyn Rd",
    "sg:city":"Hockessin",
    "sg:classifiers":[
        {
            "category":"Professional",
            "subcategory":"Art Services",
            "type":"Services"
        }
    ],
    "sg:phone":"+1 302 234 7410",
    "sg:postcode":"19707",
    "sg:province":"DE",
    "sg:tags":[
        "company",
        "integrated",
        "holding"
    ],
    "wof:name":"Creative Solutions Intl",
    "wof:placetype":"venue"
},
  "geometry": {"coordinates":[-75.692168,39.789692],"type":"Point"}
}