{
  "type": "Feature",
  "properties": {
    "addr:full":"425 Stanton Christiana Rd Newark DE 19713",
    "addr:housenumber":"425",
    "addr:postcode":"19713",
    "addr:street":"Stanton Christiana Rd",
    "iso:country":"US",
    "sg:address":"425 Stanton Christiana Rd",
    "sg:city":"Newark",
    "sg:classifiers":[
        {
            "category":"Restaurant",
            "type":"Food & Drink"
        }
    ],
    "sg:menulink":"http://www.allmenus.com/de/upper-christiana/110001-chilis/menu/",
    "sg:phone":"+1 302 273 8635",
    "sg:postcode":"19713",
    "sg:province":"DE",
    "sg:tags":[
        "burger",
        "american",
        "sandwich",
        "tex-mex",
        "soup"
    ],
    "wof:name":"Chili's",
    "wof:placetype":"venue"
},
  "geometry": {"coordinates":[-75.65367000000001,39.691947],"type":"Point"}
}