{
  "type": "Feature",
  "properties": {
    "iso:country":"US",
    "sg:address":"22804 Gravel Hill Rd",
    "sg:city":"Georgetown",
    "sg:classifiers":[
        {
            "category":"Building & Trades",
            "subcategory":"Electrical",
            "type":"Services"
        }
    ],
    "sg:phone":"+1 302 856 4035",
    "sg:postcode":"19947",
    "sg:province":"DE",
    "sg:tags":[
        "industrial",
        "electrician",
        "contractors-commercial",
        "electric"
    ],
    "wof:name":"Integrity Electric",
    "wof:placetype":"venue"
},
  "geometry": {"coordinates":[-75.300665,38.665157],"type":"Point"}
}