{
  "type": "Feature",
  "properties": {
    "iso:country":"US",
    "sg:address":"6 Albe Dr",
    "sg:city":"Newark",
    "sg:classifiers":[
        {
            "category":"Manufacturing",
            "subcategory":"Rubber & Plastics",
            "type":"Manufacturing & Wholesale Goods"
        }
    ],
    "sg:phone":"+1 302 737 1977",
    "sg:postcode":"19702",
    "sg:province":"DE",
    "sg:tags":[
        "pallet",
        "mfg"
    ],
    "wof:name":"Plasti Pallets Corp",
    "wof:placetype":"venue"
},
  "geometry": {"coordinates":[-75.715035,39.646519],"type":"Point"}
}