{
  "type": "Feature",
  "properties": {
    "iso:country":"US",
    "sg:address":"103 E Hazeldell Ave",
    "sg:city":"New Castle",
    "sg:classifiers":[
        {
            "category":"Shopping",
            "subcategory":"Tobacco",
            "type":"Retail Goods"
        }
    ],
    "sg:phone":"+1 302 655 6002",
    "sg:postcode":"19720",
    "sg:province":"DE",
    "sg:tags":[
        "cigarette",
        "cigar",
        "dealer"
    ],
    "wof:name":"Butts & Bets",
    "wof:placetype":"venue"
},
  "geometry": {"coordinates":[-75.56388699999999,39.706112],"type":"Point"}
}