{
  "type": "Feature",
  "properties": {
    "addr:full":"4752 Weatherhill Dr Wilmington DE 19808",
    "addr:housenumber":"4752",
    "addr:postcode":"19808",
    "addr:street":"Weatherhill Dr",
    "iso:country":"US",
    "sg:address":"4752 Weatherhill Dr",
    "sg:city":"Wilmington",
    "sg:classifiers":[
        {
            "category":"Professional",
            "type":"Services"
        }
    ],
    "sg:phone":"+1 302 239 8410",
    "sg:postcode":"19808",
    "sg:province":"DE",
    "wof:name":"Roy W Hanson",
    "wof:placetype":"venue"
},
  "geometry": {"coordinates":[-75.689745,39.743804],"type":"Point"}
}