{
  "type": "Feature",
  "properties": {
    "iso:country":"US",
    "sg:address":"177 Old Camden Rd",
    "sg:city":"Camden Wyoming",
    "sg:classifiers":[
        {
            "category":"Education",
            "subcategory":"Dance Studio",
            "type":"Public Place"
        }
    ],
    "sg:phone":"+1 302 697 2218",
    "sg:postcode":"19934",
    "sg:province":"DE",
    "sg:tags":[
        "performing",
        "art"
    ],
    "wof:name":"Central Delaware Dance Academy Inc",
    "wof:placetype":"venue"
},
  "geometry": {"coordinates":[-75.53630099999999,39.119301],"type":"Point"}
}