{
  "type": "Feature",
  "properties": {
    "iso:country":"US",
    "sg:address":"12 E Shetland Ct",
    "sg:city":"Newark",
    "sg:classifiers":[
        {
            "category":"Professional",
            "type":"Services"
        }
    ],
    "sg:phone":"+1 302 432 4712",
    "sg:postcode":"19711",
    "sg:province":"DE",
    "wof:name":"MBNA Employee",
    "wof:placetype":"venue"
},
  "geometry": {"coordinates":[-75.784184,39.675146],"type":"Point"}
}