{
  "type": "Feature",
  "properties": {
    "iso:country":"US",
    "sg:address":"1979 S State St Ste 30253",
    "sg:city":"Dover",
    "sg:classifiers":[
        {
            "category":"Insurance",
            "subcategory":"Hazard Insurance",
            "type":"Services"
        }
    ],
    "sg:phone":"+1 302 531 0293",
    "sg:postcode":"19901",
    "sg:province":"DE",
    "sg:tags":[
        "commercial",
        "business"
    ],
    "wof:name":"Speller Insurance Group",
    "wof:placetype":"venue"
},
  "geometry": {"coordinates":[-75.51581400000001,39.119991],"type":"Point"}
}