{
  "type": "Feature",
  "properties": {
    "addr:full":"128 S Dupont Hwy New Castle DE 19720",
    "addr:housenumber":"128",
    "addr:postcode":"19720",
    "addr:street":"S Dupont Hwy",
    "iso:country":"US",
    "sg:address":"128 S Dupont Hwy",
    "sg:city":"New Castle",
    "sg:classifiers":[
        {
            "category":"Restaurant",
            "type":"Food & Drink"
        }
    ],
    "sg:menulink":"http://www.allmenus.com/de/new-castle/75345-tgi-fridays/menu/",
    "sg:phone":"+1 302 325 6622",
    "sg:postcode":"19720",
    "sg:province":"DE",
    "sg:tags":[
        "american"
    ],
    "wof:name":"T.G.I. Friday's",
    "wof:placetype":"venue"
},
  "geometry": {"coordinates":[-75.59967399999999,39.670106],"type":"Point"}
}