{
  "type": "Feature",
  "properties": {
    "addr:full":"662 S Dual Hwy Seaford DE 19973",
    "addr:housenumber":"662",
    "addr:postcode":"19973",
    "addr:street":"S Dual Hwy",
    "iso:country":"US",
    "sg:address":"662 S Dual Hwy",
    "sg:city":"Seaford",
    "sg:classifiers":[
        {
            "category":"Health Services",
            "subcategory":"Doctor",
            "type":"Services"
        }
    ],
    "sg:phone":"+1 302 629 2333",
    "sg:postcode":"19973",
    "sg:province":"DE",
    "sg:tags":[
        "medical"
    ],
    "wof:name":"Fichter Amanda Do",
    "wof:placetype":"venue"
},
  "geometry": {"coordinates":[-75.592842,38.635432],"type":"Point"}
}