{
  "type": "Feature",
  "properties": {
    "iso:country":"US",
    "sg:address":"204 Southern Blvd",
    "sg:city":"Camden Wyoming",
    "sg:classifiers":[
        {
            "category":"Manufacturing",
            "subcategory":"Food",
            "type":"Manufacturing & Wholesale Goods"
        }
    ],
    "sg:phone":"+1 302 697 3118",
    "sg:postcode":"19934",
    "sg:province":"DE",
    "sg:tags":[
        "frozen",
        "mfg"
    ],
    "wof:name":"Quality Kitchen Corp",
    "wof:placetype":"venue"
},
  "geometry": {"coordinates":[-75.561773,39.115936],"type":"Point"}
}