{
  "type": "Feature",
  "properties": {
    "iso:country":"US",
    "sg:address":"203 Blue Rock Rd",
    "sg:city":"Wilmington",
    "sg:classifiers":[
        {
            "category":"Real Estate",
            "subcategory":"Real Estate Agent",
            "type":"Services"
        }
    ],
    "sg:phone":"+1 302 762 8761",
    "sg:postcode":"19809",
    "sg:province":"DE",
    "wof:name":"Sunset Mortgage Company",
    "wof:placetype":"venue"
},
  "geometry": {"coordinates":[-75.506754,39.76134],"type":"Point"}
}