{
  "type": "Feature",
  "properties": {
    "iso:country":"US",
    "sg:address":"1056 Church Hill Rd",
    "sg:city":"Milford",
    "sg:classifiers":[
        {
            "category":"Retail",
            "subcategory":"Auto Repair",
            "type":"Services"
        }
    ],
    "sg:phone":"+1 302 422 8596",
    "sg:postcode":"19963",
    "sg:province":"DE",
    "sg:tags":[
        "automotive",
        "wrecker",
        "towing"
    ],
    "wof:name":"Roger Minner Wrecker Service",
    "wof:placetype":"venue"
},
  "geometry": {"coordinates":[-75.457899,38.939717],"type":"Point"}
}