{
  "type": "Feature",
  "properties": {
    "addr:full":"910 Marion Ave Wilmington DE 19809",
    "addr:housenumber":"910",
    "addr:postcode":"19809",
    "addr:street":"Marion Ave",
    "iso:country":"US",
    "sg:address":"910 Marion Ave",
    "sg:city":"Wilmington",
    "sg:classifiers":[
        {
            "category":"Manufacturing",
            "subcategory":"Chemicals & Compounds",
            "type":"Manufacturing & Wholesale Goods"
        }
    ],
    "sg:phone":"+1 302 764 7964",
    "sg:postcode":"19809",
    "sg:province":"DE",
    "sg:tags":[
        "mfg"
    ],
    "wof:name":"A Kleensweep",
    "wof:placetype":"venue"
},
  "geometry": {"coordinates":[-75.497128,39.764612],"type":"Point"}
}