{
  "type": "Feature",
  "properties": {
    "iso:country":"US",
    "sg:address":"7190 Marshall St",
    "sg:city":"Lincoln",
    "sg:classifiers":[
        {
            "category":"Freight",
            "type":"Transportation"
        }
    ],
    "sg:phone":"+1 302 422 7721",
    "sg:postcode":"19960",
    "sg:province":"DE",
    "sg:tags":[
        "trucking"
    ],
    "wof:name":"Off Brothers Trucking Inc",
    "wof:placetype":"venue"
},
  "geometry": {"coordinates":[-75.41900099999999,38.880732],"type":"Point"}
}