{
  "type": "Feature",
  "properties": {
    "iso:country":"US",
    "sg:address":"1888 E Denneys Rd",
    "sg:city":"Dover",
    "sg:classifiers":[
        {
            "category":"Retail",
            "subcategory":"Repair Shop",
            "type":"Services"
        }
    ],
    "sg:phone":"+1 302 736 1352",
    "sg:postcode":"19901",
    "sg:province":"DE",
    "sg:tags":[
        "welding"
    ],
    "wof:name":"Allens Diving & Welding",
    "wof:placetype":"venue"
},
  "geometry": {"coordinates":[-75.54586399999999,39.226233],"type":"Point"}
}