{
  "type": "Feature",
  "properties": {
    "addr:full":"704 Gateway Rd Hockessin DE 19707",
    "addr:housenumber":"704",
    "addr:postcode":"19707",
    "addr:street":"Gateway Rd",
    "iso:country":"US",
    "sg:address":"704 Gateway Rd",
    "sg:city":"Hockessin",
    "sg:classifiers":[
        {
            "category":"Building & Trades",
            "subcategory":"Construction",
            "type":"Services"
        }
    ],
    "sg:phone":"+1 302 239 7474",
    "sg:postcode":"19707",
    "sg:province":"DE",
    "sg:tags":[
        "residential",
        "commercial",
        "remodeling",
        "renovation"
    ],
    "wof:name":"J J Wncius Imprvs Off Rnvtions",
    "wof:placetype":"venue"
},
  "geometry": {"coordinates":[-75.68682200000001,39.778911],"type":"Point"}
}