{
  "type": "Feature",
  "properties": {
    "iso:country":"US",
    "sg:address":"4029 New Castle Ave",
    "sg:city":"New Castle",
    "sg:classifiers":[
        {
            "category":"Retail",
            "subcategory":"Auto Repair",
            "type":"Services"
        }
    ],
    "sg:phone":"+1 302 428 1421",
    "sg:postcode":"19720",
    "sg:province":"DE",
    "sg:tags":[
        "general"
    ],
    "wof:name":"Terminal Truck & Trailer Repr",
    "wof:placetype":"venue"
},
  "geometry": {"coordinates":[-75.547349,39.714582],"type":"Point"}
}