{
  "type": "Feature",
  "properties": {
    "iso:country":"US",
    "sg:address":"345 New London Rd",
    "sg:city":"Newark",
    "sg:classifiers":[
        {
            "category":"Organizations",
            "subcategory":"Membership Organization",
            "type":"Services"
        }
    ],
    "sg:phone":"+1 302 737 4055",
    "sg:postcode":"19711",
    "sg:province":"DE",
    "wof:name":"Bandak Arab African Foundation",
    "wof:placetype":"venue"
},
  "geometry": {"coordinates":[-75.763784,39.693632],"type":"Point"}
}