{
  "type": "Feature",
  "properties": {
    "addr:full":"6902 Milford Harrington Hwy Harrington DE 19952",
    "addr:housenumber":"6902",
    "addr:postcode":"19952",
    "addr:street":"Milford Harrington Hwy",
    "iso:country":"US",
    "sg:address":"6902 Milford Harrington Hwy",
    "sg:city":"Harrington",
    "sg:classifiers":[
        {
            "category":"Retail",
            "subcategory":"Veterinary Services",
            "type":"Services"
        }
    ],
    "sg:phone":"+1 302 398 3367",
    "sg:postcode":"19952",
    "sg:province":"DE",
    "sg:tags":[
        "veterinarian",
        "specialty"
    ],
    "wof:name":"A Little Vet Clinic",
    "wof:placetype":"venue"
},
  "geometry": {"coordinates":[-75.561291,38.923793],"type":"Point"}
}