{
  "type": "Feature",
  "properties": {
    "addr:full":"502 First State Blvd Newport DE 19804",
    "addr:housenumber":"502",
    "addr:postcode":"19804",
    "addr:street":"First State Blvd",
    "iso:country":"US",
    "sg:address":"502 First State Blvd",
    "sg:city":"Newport",
    "sg:classifiers":[
        {
            "category":"Utilities",
            "subcategory":"Mobile Phone",
            "type":"Services"
        }
    ],
    "sg:phone":"+1 302 993 3250",
    "sg:postcode":"19804",
    "sg:province":"DE",
    "sg:tags":[
        "telephone",
        "cellular"
    ],
    "wof:name":"Verizon Wireless",
    "wof:placetype":"venue"
},
  "geometry": {"coordinates":[-75.633593,39.713916],"type":"Point"}
}