{
  "type": "Feature",
  "properties": {
    "addr:full":"2824 Tatnall St Wilmington DE 19802",
    "addr:housenumber":"2824",
    "addr:postcode":"19802",
    "addr:street":"Tatnall St",
    "iso:country":"US",
    "sg:address":"2824 Tatnall St",
    "sg:city":"Wilmington",
    "sg:classifiers":[
        {
            "category":"Organizations",
            "subcategory":"Religious Organization",
            "type":"Services"
        }
    ],
    "sg:phone":"+1 302 764 0427",
    "sg:postcode":"19802",
    "sg:province":"DE",
    "sg:tags":[
        "church"
    ],
    "wof:name":"Faith Tabernacle Church-Living",
    "wof:placetype":"venue"
},
  "geometry": {"coordinates":[-75.534035,39.756427],"type":"Point"}
}