{
  "type": "Feature",
  "properties": {
    "addr:full":"1308 Grinnel Rd Wilmington DE 19803",
    "addr:housenumber":"1308",
    "addr:postcode":"19803",
    "addr:street":"Grinnel Rd",
    "iso:country":"US",
    "sg:address":"1308 Grinnel Rd",
    "sg:city":"Wilmington",
    "sg:classifiers":[
        {
            "category":"Wholesale",
            "subcategory":"Chemicals & Plastics",
            "type":"Manufacturing & Wholesale Goods"
        }
    ],
    "sg:phone":"+1 302 478 9495",
    "sg:postcode":"19803",
    "sg:province":"DE",
    "wof:name":"Zeptocon Scientific Corp",
    "wof:placetype":"venue"
},
  "geometry": {"coordinates":[-75.498463,39.795888],"type":"Point"}
}