{
  "type": "Feature",
  "properties": {
    "iso:country":"US",
    "sg:address":"702 Wilmington Ave",
    "sg:city":"Wilmington",
    "sg:classifiers":[
        {
            "category":"Building & Trades",
            "subcategory":"Construction",
            "type":"Services"
        }
    ],
    "sg:phone":"+1 302 995 6561",
    "sg:postcode":"19805",
    "sg:province":"DE",
    "sg:tags":[
        "general",
        "contractor"
    ],
    "wof:name":"Oak Grove Estates Inc",
    "wof:placetype":"venue"
},
  "geometry": {"coordinates":[-75.58241,39.741223],"type":"Point"}
}