{
  "type": "Feature",
  "properties": {
    "iso:country":"US",
    "sg:address":"115 Lincoln Ave",
    "sg:city":"New Castle",
    "sg:classifiers":[
        {
            "category":"Building & Trades",
            "subcategory":"Electrical",
            "type":"Services"
        }
    ],
    "sg:phone":"+1 302 322 8529",
    "sg:postcode":"19720",
    "sg:province":"DE",
    "sg:tags":[
        "work",
        "electrical"
    ],
    "wof:name":"Jones Electrical Services",
    "wof:placetype":"venue"
},
  "geometry": {"coordinates":[-75.58952499999999,39.684062],"type":"Point"}
}