{
  "type": "Feature",
  "properties": {
    "addr:full":"216 Market St Frederica DE 19946",
    "addr:housenumber":"216",
    "addr:postcode":"19946",
    "addr:street":"Market St",
    "iso:country":"US",
    "sg:address":"216 Market St",
    "sg:city":"Frederica",
    "sg:classifiers":[
        {
            "category":"Social Services",
            "subcategory":"Adult Care",
            "type":"Services"
        }
    ],
    "sg:phone":"+1 302 335 4555",
    "sg:postcode":"19946",
    "sg:province":"DE",
    "sg:tags":[
        "organization",
        "senior",
        "citizen"
    ],
    "wof:name":"Frederica Senior Ctr Inc",
    "wof:placetype":"venue"
},
  "geometry": {"coordinates":[-75.465858,39.005392],"type":"Point"}
}