{
  "type": "Feature",
  "properties": {
    "addr:full":"858 Monroe Ter Dover DE 19904",
    "addr:housenumber":"858",
    "addr:postcode":"19904",
    "addr:street":"Monroe Ter",
    "iso:country":"US",
    "sg:address":"858 Monroe Ter",
    "sg:city":"Dover",
    "sg:classifiers":[
        {
            "category":"Restaurant",
            "type":"Food & Drink"
        }
    ],
    "sg:phone":"+1 302 734 9192",
    "sg:postcode":"19904",
    "sg:province":"DE",
    "sg:tags":[
        "eating"
    ],
    "wof:name":"J and B Wholesale Inc",
    "wof:placetype":"venue"
},
  "geometry": {"coordinates":[-75.526445,39.147474],"type":"Point"}
}