{
  "type": "Feature",
  "properties": {
    "iso:country":"US",
    "sg:address":"36 General Torbert Dr",
    "sg:city":"Milford",
    "sg:classifiers":[
        {
            "category":"Organizations",
            "subcategory":"Religious Organization",
            "type":"Services"
        }
    ],
    "sg:phone":"+1 302 424 6818",
    "sg:postcode":"19963",
    "sg:province":"DE",
    "sg:tags":[
        "clergy"
    ],
    "wof:name":"Priscilla Maxham",
    "wof:placetype":"venue"
},
  "geometry": {"coordinates":[-75.42662300000001,38.923156],"type":"Point"}
}