{
  "type": "Feature",
  "properties": {
    "addr:full":"119 Washington St Delaware City DE 19706",
    "addr:housenumber":"119",
    "addr:postcode":"19706",
    "addr:street":"Washington St",
    "iso:country":"US",
    "sg:address":"119 Washington St",
    "sg:city":"Delaware City",
    "sg:classifiers":[
        {
            "category":"Real Estate",
            "subcategory":"Real Estate Agent",
            "type":"Services"
        }
    ],
    "sg:phone":"+1 302 834 1233",
    "sg:postcode":"19706",
    "sg:province":"DE",
    "wof:name":"Nickle Real Estate",
    "wof:placetype":"venue"
},
  "geometry": {"coordinates":[-75.590902,39.577666],"type":"Point"}
}