{
  "type": "Feature",
  "properties": {
    "iso:country":"US",
    "sg:address":"950 Ridge Rd",
    "sg:city":"Claymont",
    "sg:classifiers":[
        {
            "category":"Retail",
            "subcategory":"Laundry & Dry Cleaning",
            "type":"Services"
        }
    ],
    "sg:phone":"+1 302 792 1778",
    "sg:postcode":"19703",
    "sg:province":"DE",
    "wof:name":"Quality Clene",
    "wof:placetype":"venue"
},
  "geometry": {"coordinates":[-75.440569,39.814835],"type":"Point"}
}