{
  "type": "Feature",
  "properties": {
    "addr:full":"107 Barksdale Professional Center Newark DE 19711",
    "addr:housenumber":"107",
    "addr:postcode":"19711",
    "addr:street":"Barksdale Professional Center",
    "iso:country":"US",
    "sg:address":"107 Barksdale Professional Center",
    "sg:city":"Newark",
    "sg:classifiers":[
        {
            "category":"Professional",
            "subcategory":"Accounting & Tax Preparation",
            "type":"Services"
        }
    ],
    "sg:phone":"+1 302 453 8161",
    "sg:postcode":"19711",
    "sg:province":"DE",
    "wof:name":"Ross W Burnam CPA PA",
    "wof:placetype":"venue"
},
  "geometry": {"coordinates":[-75.766265,39.678807],"type":"Point"}
}