{
  "type": "Feature",
  "properties": {
    "iso:country":"US",
    "sg:address":"938 S Bradford St",
    "sg:city":"Dover",
    "sg:classifiers":[
        {
            "category":"Health Services",
            "subcategory":"Doctor",
            "type":"Services"
        }
    ],
    "sg:phone":"+1 302 674 7155",
    "sg:postcode":"19904",
    "sg:province":"DE",
    "wof:name":"Kent Pulmonary Associates",
    "wof:placetype":"venue"
},
  "geometry": {"coordinates":[-75.52407700000001,39.148235],"type":"Point"}
}