{
  "type": "Feature",
  "properties": {
    "addr:full":"16 Roselle Ave Wilmington DE 19805",
    "addr:housenumber":"16",
    "addr:postcode":"19805",
    "addr:street":"Roselle Ave",
    "iso:country":"US",
    "sg:address":"16 Roselle Ave",
    "sg:city":"Wilmington",
    "sg:classifiers":[
        {
            "category":"Personal",
            "subcategory":"Beauty Salon",
            "type":"Services"
        }
    ],
    "sg:phone":"+1 302 571 8601",
    "sg:postcode":"19805",
    "sg:province":"DE",
    "sg:tags":[
        "shop"
    ],
    "wof:name":"Glorified Images",
    "wof:placetype":"venue"
},
  "geometry": {"coordinates":[-75.614288,39.739254],"type":"Point"}
}