{
  "type": "Feature",
  "properties": {
    "iso:country":"US",
    "sg:address":"500 Stanton Christiana Rd",
    "sg:city":"Newark",
    "sg:classifiers":[
        {
            "category":"Banks & Credit Unions",
            "subcategory":"Investment Brokerage",
            "type":"Services"
        }
    ],
    "sg:phone":"+1 302 634 1000",
    "sg:postcode":"19702",
    "sg:province":"DE",
    "sg:tags":[
        "security"
    ],
    "wof:name":"Morgan Guaranty",
    "wof:placetype":"venue"
},
  "geometry": {"coordinates":[-75.652587,39.693637],"type":"Point"}
}