{
  "type": "Feature",
  "properties": {
    "addr:full":"2 Festival Ct Newark DE 19702",
    "addr:housenumber":"2",
    "addr:postcode":"19702",
    "addr:street":"Festival Ct",
    "iso:country":"US",
    "sg:address":"2 Festival Ct",
    "sg:city":"Newark",
    "sg:classifiers":[
        {
            "category":"Building & Trades",
            "subcategory":"Plumbing",
            "type":"Services"
        }
    ],
    "sg:phone":"+1 302 368 8101",
    "sg:postcode":"19702",
    "sg:province":"DE",
    "sg:tags":[
        "contractor"
    ],
    "wof:name":"R C Wahl Heating & AC Co",
    "wof:placetype":"venue"
},
  "geometry": {"coordinates":[-75.75488199999999,39.628049],"type":"Point"}
}