{
  "type": "Feature",
  "properties": {
    "addr:full":"43 River Breeze Dr Millsboro DE 19966",
    "addr:housenumber":"43",
    "addr:postcode":"19966",
    "addr:street":"River Breeze Dr",
    "iso:country":"US",
    "sg:address":"43 River Breeze Dr",
    "sg:city":"Millsboro",
    "sg:classifiers":[
        {
            "category":"Professional",
            "type":"Services"
        }
    ],
    "sg:phone":"+1 302 945 8380",
    "sg:postcode":"19966",
    "sg:province":"DE",
    "wof:name":"Shirleys Shades",
    "wof:placetype":"venue"
},
  "geometry": {"coordinates":[-75.19049800000001,38.624396],"type":"Point"}
}