{
  "type": "Feature",
  "properties": {
    "iso:country":"US",
    "sg:address":"89 Kings Hwy",
    "sg:city":"Dover",
    "sg:classifiers":[
        {
            "category":"Government",
            "subcategory":"Office",
            "type":"Public Place"
        }
    ],
    "sg:phone":"+1 302 739 5295",
    "sg:postcode":"19901",
    "sg:province":"DE",
    "wof:name":"Mosquito Control Section",
    "wof:placetype":"venue"
},
  "geometry": {"coordinates":[-75.51833499999999,39.163473],"type":"Point"}
}