{
  "type": "Feature",
  "properties": {
    "iso:country":"US",
    "sg:address":"944 McDowell Dr",
    "sg:city":"Dover",
    "sg:classifiers":[
        {
            "category":"Airline",
            "type":"Transportation"
        }
    ],
    "sg:phone":"+1 302 734 9622",
    "sg:postcode":"19901",
    "sg:province":"DE",
    "sg:tags":[
        "scheduled",
        "air"
    ],
    "wof:name":"East West Airlines",
    "wof:placetype":"venue"
},
  "geometry": {"coordinates":[-75.515298,39.175489],"type":"Point"}
}