{
  "type": "Feature",
  "properties": {
    "iso:country":"US",
    "sg:address":"1007 N Tatnall St",
    "sg:city":"Wilmington",
    "sg:classifiers":[
        {
            "category":"Real Estate",
            "subcategory":"Real Estate Operator",
            "type":"Services"
        }
    ],
    "sg:phone":"+1 302 774 5440",
    "sg:postcode":"19801",
    "sg:province":"DE",
    "sg:tags":[
        "building",
        "nonresidential"
    ],
    "wof:name":"Dupont",
    "wof:placetype":"venue"
},
  "geometry": {"coordinates":[-75.54996800000001,39.746543],"type":"Point"}
}