{
  "type": "Feature",
  "properties": {
    "addr:full":"1401 E Newport Pike Wilmington DE 19804",
    "addr:housenumber":"1401",
    "addr:postcode":"19804",
    "addr:street":"E Newport Pike",
    "iso:country":"US",
    "sg:address":"1401 E Newport Pike",
    "sg:city":"Wilmington",
    "sg:classifiers":[
        {
            "category":"Building & Trades",
            "subcategory":"Construction",
            "type":"Services"
        }
    ],
    "sg:phone":"+1 302 999 7565",
    "sg:postcode":"19804",
    "sg:province":"DE",
    "sg:tags":[
        "general",
        "contractor"
    ],
    "wof:name":"Casella Contracting Inc",
    "wof:placetype":"venue"
},
  "geometry": {"coordinates":[-75.60134600000001,39.717777],"type":"Point"}
}