{
  "type": "Feature",
  "properties": {
    "iso:country":"US",
    "sg:address":"1915 Capitol Trl",
    "sg:city":"Newark",
    "sg:classifiers":[
        {
            "category":"Professional",
            "type":"Services"
        }
    ],
    "sg:phone":"+1 302 737 2910",
    "sg:postcode":"19711",
    "sg:province":"DE",
    "wof:name":"Dale E Walters",
    "wof:placetype":"venue"
},
  "geometry": {"coordinates":[-75.697835,39.701662],"type":"Point"}
}