{
  "type": "Feature",
  "properties": {
    "iso:country":"US",
    "sg:address":"17 Atlantic Ave",
    "sg:city":"Ocean View",
    "sg:classifiers":[
        {
            "category":"Health Services",
            "subcategory":"Health Practitioner",
            "type":"Services"
        },
        {
            "category":"Health Services",
            "subcategory":"Doctor",
            "type":"Services"
        }
    ],
    "sg:phone":"+1 302 539 6641",
    "sg:postcode":"19970",
    "sg:province":"DE",
    "sg:tags":[
        "physician",
        "surgeon"
    ],
    "wof:name":"Associates In Medicine PA",
    "wof:placetype":"venue"
},
  "geometry": {"coordinates":[-75.08119600000001,38.542789],"type":"Point"}
}