{
  "type": "Feature",
  "properties": {
    "iso:country":"US",
    "sg:address":"502 Lambson Ln",
    "sg:city":"New Castle",
    "sg:classifiers":[
        {
            "category":"Building & Trades",
            "subcategory":"Plumbing",
            "type":"Services"
        }
    ],
    "sg:phone":"+1 302 656 6054",
    "sg:postcode":"19720",
    "sg:province":"DE",
    "sg:tags":[
        "plumbing",
        "air",
        "heating",
        "conditioning",
        "contractor"
    ],
    "wof:name":"Thomas A Cochran & Sons Inc",
    "wof:placetype":"venue"
},
  "geometry": {"coordinates":[-75.540378,39.705221],"type":"Point"}
}