{
  "type": "Feature",
  "properties": {
    "iso:country":"US",
    "sg:address":"1220 Bennetts Pier Rd",
    "sg:city":"Milford",
    "sg:classifiers":[
        {
            "category":"Professional",
            "type":"Services"
        }
    ],
    "sg:phone":"+1 302 424 4465",
    "sg:postcode":"19963",
    "sg:province":"DE",
    "wof:name":"John H French",
    "wof:placetype":"venue"
},
  "geometry": {"coordinates":[-75.37312300000001,39.005352],"type":"Point"}
}