{
  "type": "Feature",
  "properties": {
    "iso:country":"US",
    "sg:address":"212 Marabou Dr",
    "sg:city":"Newark",
    "sg:classifiers":[
        {
            "category":"Professional",
            "subcategory":"Computer Services",
            "type":"Services"
        }
    ],
    "sg:phone":"+1 302 832 1307",
    "sg:postcode":"19702",
    "sg:province":"DE",
    "sg:tags":[
        "repair",
        "monitor"
    ],
    "wof:name":"Tek Enterprises",
    "wof:placetype":"venue"
},
  "geometry": {"coordinates":[-75.75709500000001,39.590439],"type":"Point"}
}