{
  "type": "Feature",
  "properties": {
    "addr:full":"2405 Duncan Rd Wilmington DE 19808",
    "addr:housenumber":"2405",
    "addr:postcode":"19808",
    "addr:street":"Duncan Rd",
    "iso:country":"US",
    "sg:address":"2405 Duncan Rd",
    "sg:city":"Wilmington",
    "sg:classifiers":[
        {
            "category":"Professional",
            "subcategory":"Business Services",
            "type":"Services"
        }
    ],
    "sg:phone":"+1 302 633 6184",
    "sg:postcode":"19808",
    "sg:province":"DE",
    "wof:name":"In Global Education Enterprise",
    "wof:placetype":"venue"
},
  "geometry": {"coordinates":[-75.64263099999999,39.737782],"type":"Point"}
}