{
  "type": "Feature",
  "properties": {
    "addr:full":"4921 Governor Printz Blvd Wilmington DE 19809",
    "addr:housenumber":"4921",
    "addr:postcode":"19809",
    "addr:street":"Governor Printz Blvd",
    "iso:country":"US",
    "sg:address":"4921 Governor Printz Blvd",
    "sg:city":"Wilmington",
    "sg:classifiers":[
        {
            "category":"Retail",
            "subcategory":"Auto Repair",
            "type":"Services"
        }
    ],
    "sg:phone":"+1 302 762 2301",
    "sg:postcode":"19809",
    "sg:province":"DE",
    "sg:tags":[
        "body"
    ],
    "wof:name":"Smith Auto Body Repair",
    "wof:placetype":"venue"
},
  "geometry": {"coordinates":[-75.496273,39.755877],"type":"Point"}
}