{
  "type": "Feature",
  "properties": {
    "iso:country":"US",
    "sg:address":"746 N Dupont Hwy",
    "sg:city":"Dover",
    "sg:classifiers":[
        {
            "category":"Autos & Motor Vehicles",
            "subcategory":"Auto Supplies",
            "type":"Retail Goods"
        }
    ],
    "sg:phone":"+1 302 678 3284",
    "sg:postcode":"19901",
    "sg:province":"DE",
    "sg:tags":[
        "glass"
    ],
    "sg:website":"www.safelite.com",
    "wof:name":"Safelite Auto Glass",
    "wof:placetype":"venue"
},
  "geometry": {"coordinates":[-75.5326,39.183498],"type":"Point"}
}