{
  "type": "Feature",
  "properties": {
    "iso:country":"US",
    "sg:address":"20 Shea Way",
    "sg:city":"Newark",
    "sg:classifiers":[
        {
            "category":"Manufacturing",
            "subcategory":"Printing",
            "type":"Manufacturing & Wholesale Goods"
        }
    ],
    "sg:phone":"+1 302 731 9750",
    "sg:postcode":"19713",
    "sg:province":"DE",
    "sg:tags":[
        "publisher"
    ],
    "wof:name":"Mitchell Lane Publishers Inc",
    "wof:placetype":"venue"
},
  "geometry": {"coordinates":[-75.727599,39.653934],"type":"Point"}
}