{
  "type": "Feature",
  "properties": {
    "addr:full":"40 Polly Drummond Hill Rd Newark DE 19711",
    "addr:housenumber":"40",
    "addr:postcode":"19711",
    "addr:street":"Polly Drummond Hill Rd",
    "iso:country":"US",
    "sg:address":"40 Polly Drummond Hill Rd",
    "sg:city":"Newark",
    "sg:classifiers":[
        {
            "category":"Health Services",
            "subcategory":"Medical Lab",
            "type":"Services"
        }
    ],
    "sg:phone":"+1 302 737 6038",
    "sg:postcode":"19711",
    "sg:province":"DE",
    "sg:tags":[
        "laboratory"
    ],
    "wof:name":"Medical Laboratories",
    "wof:placetype":"venue"
},
  "geometry": {"coordinates":[-75.709991,39.706542],"type":"Point"}
}