{
  "type": "Feature",
  "properties": {
    "addr:full":"3100 Swarthmore Rd Wilmington DE 19807",
    "addr:housenumber":"3100",
    "addr:postcode":"19807",
    "addr:street":"Swarthmore Rd",
    "iso:country":"US",
    "sg:address":"3100 Swarthmore Rd",
    "sg:city":"Wilmington",
    "sg:classifiers":[
        {
            "category":"Professional",
            "subcategory":"Computer Services",
            "type":"Services"
        }
    ],
    "sg:phone":"+1 609 405 0519",
    "sg:postcode":"19807",
    "sg:province":"DE",
    "sg:tags":[
        "consulting"
    ],
    "wof:name":"D2 Technology Inc",
    "wof:placetype":"venue"
},
  "geometry": {"coordinates":[-75.584113,39.756043],"type":"Point"}
}