{
  "type": "Feature",
  "properties": {
    "addr:full":"2815 Philadelphia Pike Claymont DE 19703",
    "addr:housenumber":"2815",
    "addr:postcode":"19703",
    "addr:street":"Philadelphia Pike",
    "iso:country":"US",
    "sg:address":"2815 Philadelphia Pike",
    "sg:city":"Claymont",
    "sg:classifiers":[
        {
            "category":"Restaurant",
            "type":"Food & Drink"
        }
    ],
    "sg:phone":"+1 302 798 0142",
    "sg:postcode":"19703",
    "sg:province":"DE",
    "wof:name":"Shang Hai",
    "wof:placetype":"venue"
},
  "geometry": {"coordinates":[-75.46603399999999,39.795869],"type":"Point"}
}