{
  "type": "Feature",
  "properties": {
    "iso:country":"US",
    "sg:address":"1803 Township Rd",
    "sg:city":"Wilmington",
    "sg:classifiers":[
        {
            "category":"Social Services",
            "subcategory":"Child Care",
            "type":"Services"
        }
    ],
    "sg:phone":"+1 302 999 1816",
    "sg:postcode":"19804",
    "sg:province":"DE",
    "sg:tags":[
        "day"
    ],
    "wof:name":"Knotts Julia Day Care",
    "wof:placetype":"venue"
},
  "geometry": {"coordinates":[-75.64732600000001,39.718001],"type":"Point"}
}