{
  "type": "Feature",
  "properties": {
    "iso:country":"US",
    "sg:address":"678 N Broad St",
    "sg:city":"Middletown",
    "sg:classifiers":[
        {
            "category":"Autos & Motor Vehicles",
            "subcategory":"Auto Supplies",
            "type":"Retail Goods"
        }
    ],
    "sg:phone":"+1 302 378 9583",
    "sg:postcode":"19709",
    "sg:province":"DE",
    "sg:tags":[
        "automobile",
        "parts"
    ],
    "wof:name":"Middletown NAPA Auto Parts",
    "wof:placetype":"venue"
},
  "geometry": {"coordinates":[-75.71938,39.457648],"type":"Point"}
}