{
  "type": "Feature",
  "properties": {
    "iso:country":"US",
    "sg:address":"600 Industrial Dr",
    "sg:city":"Middletown",
    "sg:classifiers":[
        {
            "category":"Manufacturing",
            "subcategory":"Glass & Minerals",
            "type":"Manufacturing & Wholesale Goods"
        },
        {
            "category":"Building & Trades",
            "subcategory":"Construction",
            "type":"Services"
        }
    ],
    "sg:phone":"+1 302 376 5280",
    "sg:postcode":"19709",
    "sg:province":"DE",
    "sg:tags":[
        "ready",
        "concrete",
        "contractor",
        "mfg"
    ],
    "wof:name":"South Gate Concrete Inc",
    "wof:placetype":"venue"
},
  "geometry": {"coordinates":[-75.720367,39.443191],"type":"Point"}
}