{
  "type": "Feature",
  "properties": {
    "iso:country":"US",
    "sg:address":"3415 N Market St",
    "sg:city":"Wilmington",
    "sg:classifiers":[
        {
            "category":"Autos & Motor Vehicles",
            "subcategory":"Auto Supplies",
            "type":"Retail Goods"
        },
        {
            "category":"Retail",
            "subcategory":"Auto Repair",
            "type":"Services"
        }
    ],
    "sg:phone":"+1 302 764 8900",
    "sg:postcode":"19802",
    "sg:province":"DE",
    "sg:tags":[
        "repairing",
        "automobile",
        "tire"
    ],
    "wof:name":"Bargain Tire & Service Inc",
    "wof:placetype":"venue"
},
  "geometry": {"coordinates":[-75.527073,39.758536],"type":"Point"}
}