{
  "type": "Feature",
  "properties": {
    "iso:country":"US",
    "sg:address":"710 Greenbank Rd Ste A",
    "sg:city":"Wilmington",
    "sg:classifiers":[
        {
            "category":"Health Services",
            "subcategory":"Dentist",
            "type":"Services"
        }
    ],
    "sg:phone":"+1 302 994 2582",
    "sg:postcode":"19808",
    "sg:province":"DE",
    "sg:tags":[
        "dentists-cosmetic",
        "dentists-pediatric",
        "dentists-endodontists",
        "dentistry",
        "implant",
        "dentists-implantology"
    ],
    "sg:website":"http://www.kdental.com",
    "wof:name":"Kirkwood Dental Associates P A",
    "wof:placetype":"venue"
},
  "geometry": {"coordinates":[-75.63580399999999,39.735964],"type":"Point"}
}