{
  "type": "Feature",
  "properties": {
    "addr:full":"550 S College Ave Newark DE 19713",
    "addr:housenumber":"550",
    "addr:postcode":"19713",
    "addr:street":"S College Ave",
    "iso:country":"US",
    "sg:address":"550 S College Ave",
    "sg:city":"Newark",
    "sg:classifiers":[
        {
            "category":"Building & Trades",
            "subcategory":"Construction",
            "type":"Services"
        }
    ],
    "sg:phone":"+1 302 292 8735",
    "sg:postcode":"19713",
    "sg:province":"DE",
    "sg:tags":[
        "contractor"
    ],
    "wof:name":"Commercial Contracting",
    "wof:placetype":"venue"
},
  "geometry": {"coordinates":[-75.752837,39.666922],"type":"Point"}
}