{
  "type": "Feature",
  "properties": {
    "addr:full":"5 Penny Lane Ct Wilmington DE 19803",
    "addr:housenumber":"5",
    "addr:postcode":"19803",
    "addr:street":"Penny Lane Ct",
    "iso:country":"US",
    "sg:address":"5 Penny Lane Ct",
    "sg:city":"Wilmington",
    "sg:classifiers":[
        {
            "category":"Professional",
            "subcategory":"Art Services",
            "type":"Services"
        }
    ],
    "sg:phone":"+1 302 654 3905",
    "sg:postcode":"19803",
    "sg:province":"DE",
    "sg:tags":[
        "photo",
        "photography",
        "commercial",
        "studio",
        "portrait"
    ],
    "wof:name":"Carson T Zullinger",
    "wof:placetype":"venue"
},
  "geometry": {"coordinates":[-75.514546,39.791464],"type":"Point"}
}