{
  "type": "Feature",
  "properties": {
    "addr:full":"10 Sumac Ct Newark DE 19702",
    "addr:housenumber":"10",
    "addr:postcode":"19702",
    "addr:street":"Sumac Ct",
    "iso:country":"US",
    "sg:address":"10 Sumac Ct",
    "sg:city":"Newark",
    "sg:classifiers":[
        {
            "category":"Social Services",
            "subcategory":"Child Care",
            "type":"Services"
        }
    ],
    "sg:phone":"+1 302 292 0205",
    "sg:postcode":"19702",
    "sg:province":"DE",
    "sg:tags":[
        "day"
    ],
    "wof:name":"Frances Gilmore",
    "wof:placetype":"venue"
},
  "geometry": {"coordinates":[-75.691824,39.64489],"type":"Point"}
}