{
  "type": "Feature",
  "properties": {
    "iso:country":"US",
    "sg:address":"530 School House Rd",
    "sg:city":"Hockessin",
    "sg:classifiers":[
        {
            "category":"Shopping",
            "subcategory":"Catalog Store",
            "type":"Retail Goods"
        }
    ],
    "sg:phone":"+1 484 701 3439",
    "sg:postcode":"19707",
    "sg:province":"DE",
    "sg:tags":[
        "mail",
        "house"
    ],
    "wof:name":"Asm",
    "wof:placetype":"venue"
},
  "geometry": {"coordinates":[-75.687358,39.785407],"type":"Point"}
}