{
  "type": "Feature",
  "properties": {
    "addr:full":"666 S Bay Rd Dover DE 19901",
    "addr:housenumber":"666",
    "addr:postcode":"19901",
    "addr:street":"S Bay Rd",
    "iso:country":"US",
    "sg:address":"666 S Bay Rd",
    "sg:city":"Dover",
    "sg:classifiers":[
        {
            "category":"Cinema",
            "subcategory":"Movie Rental",
            "type":"Entertainment"
        }
    ],
    "sg:phone":"+1 302 674 1502",
    "sg:postcode":"19901",
    "sg:province":"DE",
    "sg:tags":[
        "game",
        "video"
    ],
    "sg:website":"www.moviegallery.com",
    "wof:name":"Movie Gallery",
    "wof:placetype":"venue"
},
  "geometry": {"coordinates":[-75.505697,39.151782],"type":"Point"}
}