{
  "type": "Feature",
  "properties": {
    "iso:country":"US",
    "sg:address":"1900 N Van Buren St",
    "sg:city":"Wilmington",
    "sg:classifiers":[
        {
            "category":"Professional",
            "subcategory":"Art Services",
            "type":"Services"
        }
    ],
    "sg:phone":"+1 302 655 9450",
    "sg:postcode":"19802",
    "sg:province":"DE",
    "sg:tags":[
        "commercial",
        "design"
    ],
    "wof:name":"Thomas Richards & Harris Inc",
    "wof:placetype":"venue"
},
  "geometry": {"coordinates":[-75.546702,39.758159],"type":"Point"}
}