{
  "type": "Feature",
  "properties": {
    "addr:full":"1021 Park Pl Wilmington DE 19806",
    "addr:housenumber":"1021",
    "addr:postcode":"19806",
    "addr:street":"Park Pl",
    "iso:country":"US",
    "sg:address":"1021 Park Pl",
    "sg:city":"Wilmington",
    "sg:classifiers":[
        {
            "category":"Health Services",
            "subcategory":"Health Practitioner",
            "type":"Services"
        }
    ],
    "sg:phone":"+1 302 426 0348",
    "sg:postcode":"19806",
    "sg:province":"DE",
    "wof:name":"Barbara A Dambach",
    "wof:placetype":"venue"
},
  "geometry": {"coordinates":[-75.55695299999999,39.75158],"type":"Point"}
}