{
  "type": "Feature",
  "properties": {
    "iso:country":"US",
    "sg:address":"270 University Dr",
    "sg:city":"Newark",
    "sg:classifiers":[
        {
            "category":"Restaurant",
            "type":"Food & Drink"
        }
    ],
    "sg:phone":"+1 302 738 6810",
    "sg:postcode":"19702",
    "sg:province":"DE",
    "sg:tags":[
        "pizza"
    ],
    "wof:name":"Ciao's Pizza & Pasta",
    "wof:placetype":"venue"
},
  "geometry": {"coordinates":[-75.668976,39.667546],"type":"Point"}
}