{
  "type": "Feature",
  "properties": {
    "iso:country":"US",
    "sg:address":"415 Brookfield Dr",
    "sg:city":"Dover",
    "sg:classifiers":[
        {
            "category":"Home & Garden",
            "subcategory":"Furniture",
            "type":"Retail Goods"
        }
    ],
    "sg:phone":"+1 302 653 5186",
    "sg:postcode":"19901",
    "sg:province":"DE",
    "sg:tags":[
        "store"
    ],
    "wof:name":"Clocks Counrty Furniture",
    "wof:placetype":"venue"
},
  "geometry": {"coordinates":[-75.53478800000001,39.092522],"type":"Point"}
}