{
  "type": "Feature",
  "properties": {
    "iso:country":"US",
    "sg:address":"10414 Blacksmith Shop Rd",
    "sg:city":"Greenwood",
    "sg:classifiers":[
        {
            "category":"Retail",
            "subcategory":"Auto Repair",
            "type":"Services"
        }
    ],
    "sg:phone":"+1 302 424 6809",
    "sg:postcode":"19950",
    "sg:province":"DE",
    "sg:tags":[
        "body"
    ],
    "wof:name":"Todays Kustoms",
    "wof:placetype":"venue"
},
  "geometry": {"coordinates":[-75.50433099999999,38.83963],"type":"Point"}
}