{
  "type": "Feature",
  "properties": {
    "iso:country":"US",
    "sg:address":"308 Elkton Rd",
    "sg:city":"Newark",
    "sg:classifiers":[
        {
            "category":"Personal",
            "subcategory":"Shoe Repair & Shine",
            "type":"Services"
        }
    ],
    "sg:phone":"+1 302 292 1122",
    "sg:postcode":"19711",
    "sg:province":"DE",
    "sg:tags":[
        "drycleaning",
        "plant",
        "parlor"
    ],
    "wof:name":"Parkway Cleaners",
    "wof:placetype":"venue"
},
  "geometry": {"coordinates":[-75.765517,39.67515],"type":"Point"}
}