{
  "type": "Feature",
  "properties": {
    "iso:country":"US",
    "sg:address":"100 Wilton Blvd",
    "sg:city":"New Castle",
    "sg:classifiers":[
        {
            "category":"Professional",
            "type":"Services"
        },
        {
            "category":"Social Services",
            "subcategory":"Child Care",
            "type":"Services"
        }
    ],
    "sg:phone":"+1 302 324 5418",
    "sg:postcode":"19720",
    "sg:province":"DE",
    "sg:tags":[
        "establishment",
        "day"
    ],
    "wof:name":"Victoryville Child Learning Ce",
    "wof:placetype":"venue"
},
  "geometry": {"coordinates":[-75.62843599999999,39.656714],"type":"Point"}
}