{
  "type": "Feature",
  "properties": {
    "addr:full":"510 Smith Ave Harrington DE 19952",
    "addr:housenumber":"510",
    "addr:postcode":"19952",
    "addr:street":"Smith Ave",
    "iso:country":"US",
    "sg:address":"510 Smith Ave",
    "sg:city":"Harrington",
    "sg:classifiers":[
        {
            "category":"Sports & Exercise",
            "subcategory":"Gym",
            "type":"Entertainment"
        }
    ],
    "sg:phone":"+1 302 398 6000",
    "sg:postcode":"19952",
    "sg:province":"DE",
    "sg:tags":[
        "club",
        "health",
        "studio",
        "gymnasium"
    ],
    "wof:name":"Curves For Women",
    "wof:placetype":"venue"
},
  "geometry": {"coordinates":[-75.567054,38.929566],"type":"Point"}
}