{
  "type": "Feature",
  "properties": {
    "addr:full":"950 Ridge Rd Claymont DE 19703",
    "addr:housenumber":"950",
    "addr:postcode":"19703",
    "addr:street":"Ridge Rd",
    "iso:country":"US",
    "sg:address":"950 Ridge Rd",
    "sg:city":"Claymont",
    "sg:classifiers":[
        {
            "category":"Retail",
            "subcategory":"Animal Services",
            "type":"Services"
        }
    ],
    "sg:phone":"+1 302 798 1810",
    "sg:postcode":"19703",
    "sg:province":"DE",
    "sg:tags":[
        "pet",
        "grooming",
        "washing"
    ],
    "wof:name":"Doggie Style Grooming",
    "wof:placetype":"venue"
},
  "geometry": {"coordinates":[-75.440569,39.814835],"type":"Point"}
}