{
  "type": "Feature",
  "properties": {
    "iso:country":"US",
    "sg:address":"203 Presidential Dr",
    "sg:city":"Wilmington",
    "sg:classifiers":[
        {
            "category":"Professional",
            "type":"Services"
        }
    ],
    "sg:phone":"+1 302 777 2219",
    "sg:postcode":"19807",
    "sg:province":"DE",
    "wof:name":"Sophie Deudon",
    "wof:placetype":"venue"
},
  "geometry": {"coordinates":[-75.596638,39.774277],"type":"Point"}
}