{
  "type": "Feature",
  "properties": {
    "addr:full":"18 Hickory St Frankford DE 19945",
    "addr:housenumber":"18",
    "addr:postcode":"19945",
    "addr:street":"Hickory St",
    "iso:country":"US",
    "sg:address":"18 Hickory St",
    "sg:city":"Frankford",
    "sg:classifiers":[
        {
            "category":"Insurance",
            "subcategory":"Hazard Insurance",
            "type":"Services"
        },
        {
            "category":"Insurance",
            "subcategory":"Insurance Agent",
            "type":"Services"
        },
        {
            "category":"Insurance",
            "subcategory":"Life Insurance",
            "type":"Services"
        },
        {
            "category":"Insurance",
            "subcategory":"Title Insurance",
            "type":"Services"
        }
    ],
    "sg:phone":"+1 302 732 9505",
    "sg:postcode":"19945",
    "sg:province":"DE",
    "sg:tags":[
        "auto",
        "homeowner"
    ],
    "sg:website":"http://www.nationwide.com/agent/Frankford-DELAWARE-insurance-agent/cynthia-hoban/office.html",
    "wof:name":"Cynthia C Hoban - Nationwide Insurance",
    "wof:placetype":"venue"
},
  "geometry": {"coordinates":[-75.240133,38.52133],"type":"Point"}
}