{
  "type": "Feature",
  "properties": {
    "iso:country":"US",
    "sg:address":"352 Trillium Dr",
    "sg:city":"Magnolia",
    "sg:classifiers":[
        {
            "category":"Personal",
            "subcategory":"Beauty Salon",
            "type":"Services"
        }
    ],
    "sg:phone":"+1 302 698 3451",
    "sg:postcode":"19962",
    "sg:province":"DE",
    "wof:name":"Pam's Hair Design",
    "wof:placetype":"venue"
},
  "geometry": {"coordinates":[-75.505528,39.058962],"type":"Point"}
}