{
  "type": "Feature",
  "properties": {
    "iso:country":"US",
    "sg:address":"4 Dansfield Dr",
    "sg:city":"Wilmington",
    "sg:classifiers":[
        {
            "category":"Real Estate",
            "subcategory":"Real Estate Agent",
            "type":"Services"
        }
    ],
    "sg:phone":"+1 302 764 0737",
    "sg:postcode":"19803",
    "sg:province":"DE",
    "wof:name":"Anna R Dostillio",
    "wof:placetype":"venue"
},
  "geometry": {"coordinates":[-75.52419399999999,39.776356],"type":"Point"}
}