{
  "type": "Feature",
  "properties": {
    "iso:country":"US",
    "sg:address":"102 Sunset Dr",
    "sg:city":"Wilmington",
    "sg:classifiers":[
        {
            "category":"Professional",
            "subcategory":"Research",
            "type":"Services"
        }
    ],
    "sg:phone":"+1 302 792 2463",
    "sg:postcode":"19809",
    "sg:province":"DE",
    "sg:tags":[
        "peer",
        "reviewer"
    ],
    "wof:name":"James McNair",
    "wof:placetype":"venue"
},
  "geometry": {"coordinates":[-75.48263799999999,39.778377],"type":"Point"}
}