{
  "type": "Feature",
  "properties": {
    "iso:country":"US",
    "sg:address":"714 Gallo Rd",
    "sg:city":"Harrington",
    "sg:classifiers":[
        {
            "category":"Building & Trades",
            "subcategory":"Construction",
            "type":"Services"
        }
    ],
    "sg:phone":"+1 302 398 9704",
    "sg:postcode":"19952",
    "sg:province":"DE",
    "sg:tags":[
        "equipment",
        "station",
        "contractor"
    ],
    "wof:name":"First State Petroleum Services",
    "wof:placetype":"venue"
},
  "geometry": {"coordinates":[-75.65665799999999,38.868917],"type":"Point"}
}