{
  "type": "Feature",
  "properties": {
    "addr:full":"220 Elkton Rd Newark DE 19711",
    "addr:housenumber":"220",
    "addr:postcode":"19711",
    "addr:street":"Elkton Rd",
    "iso:country":"US",
    "sg:address":"220 Elkton Rd",
    "sg:city":"Newark",
    "sg:classifiers":[
        {
            "category":"Government",
            "subcategory":"Police Station",
            "type":"Public Place"
        }
    ],
    "sg:phone":"+1 302 366 7142",
    "sg:postcode":"19711",
    "sg:province":"DE",
    "sg:tags":[
        "department"
    ],
    "wof:name":"Newark Police-Traffic Div",
    "wof:placetype":"venue"
},
  "geometry": {"coordinates":[-75.76304399999999,39.677174],"type":"Point"}
}