{
  "type": "Feature",
  "properties": {
    "iso:country":"US",
    "sg:address":"19930 Coastal Hwy",
    "sg:city":"Rehoboth Beach",
    "sg:classifiers":[
        {
            "category":"Home & Garden",
            "subcategory":"Building Materials",
            "type":"Retail Goods"
        }
    ],
    "sg:phone":"+1 302 226 2449",
    "sg:postcode":"19971",
    "sg:province":"DE",
    "sg:tags":[
        "paint"
    ],
    "wof:name":"Sherwin-Williams Paints",
    "wof:placetype":"venue"
},
  "geometry": {"coordinates":[-75.10447000000001,38.713286],"type":"Point"}
}