{
  "type": "Feature",
  "properties": {
    "iso:country":"US",
    "sg:address":"8 Club Ln",
    "sg:city":"Wilmington",
    "sg:classifiers":[
        {
            "category":"Building & Trades",
            "subcategory":"Cleaning & Sanitation",
            "type":"Services"
        }
    ],
    "sg:phone":"+1 302 504 8419",
    "sg:postcode":"19810",
    "sg:province":"DE",
    "sg:website":"www.wilmingtoncleaningservice.com/",
    "wof:name":"Crossover Janitorial Service",
    "wof:placetype":"venue"
},
  "geometry": {"coordinates":[-75.540556,39.813881],"type":"Point"}
}