{
  "type": "Feature",
  "properties": {
    "iso:country":"US",
    "sg:address":"1035 Philadelphia Pike",
    "sg:city":"Wilmington",
    "sg:classifiers":[
        {
            "category":"Wholesale",
            "subcategory":"Office Equipment",
            "type":"Manufacturing & Wholesale Goods"
        }
    ],
    "sg:phone":"+1 302 798 5589",
    "sg:postcode":"19809",
    "sg:province":"DE",
    "sg:tags":[
        "machine",
        "business"
    ],
    "wof:name":"Eastern States Business Eqp Co",
    "wof:placetype":"venue"
},
  "geometry": {"coordinates":[-75.484685,39.78053],"type":"Point"}
}