{
  "type": "Feature",
  "properties": {
    "iso:country":"US",
    "sg:address":"200 Banning St Ste 350",
    "sg:city":"Dover",
    "sg:classifiers":[
        {
            "category":"Health Services",
            "subcategory":"Chiropractor",
            "type":"Services"
        }
    ],
    "sg:phone":"+1 302 730 8848",
    "sg:postcode":"19904",
    "sg:province":"DE",
    "sg:tags":[
        "chiropractic"
    ],
    "wof:name":"Delaware Back Pain",
    "wof:placetype":"venue"
},
  "geometry": {"coordinates":[-75.53375200000001,39.155182],"type":"Point"}
}