{
  "type": "Feature",
  "properties": {
    "addr:full":"404 Harvey Dr Newport DE 19804",
    "addr:housenumber":"404",
    "addr:postcode":"19804",
    "addr:street":"Harvey Dr",
    "iso:country":"US",
    "sg:address":"404 Harvey Dr",
    "sg:city":"Newport",
    "sg:classifiers":[
        {
            "category":"Home & Garden",
            "subcategory":"Carpets & Floor Coverings",
            "type":"Retail Goods"
        },
        {
            "category":"Building & Trades",
            "subcategory":"Construction",
            "type":"Services"
        }
    ],
    "sg:phone":"+1 302 999 7780",
    "sg:postcode":"19804",
    "sg:province":"DE",
    "sg:tags":[
        "rug",
        "installation",
        "dealer",
        "contractor"
    ],
    "wof:name":"Garr-Wood Carpet",
    "wof:placetype":"venue"
},
  "geometry": {"coordinates":[-75.59652199999999,39.712891],"type":"Point"}
}