{
  "type": "Feature",
  "properties": {
    "iso:country":"US",
    "sg:address":"621 Delaware St",
    "sg:city":"New Castle",
    "sg:classifiers":[
        {
            "category":"Banks & Credit Unions",
            "subcategory":"Bank",
            "type":"Services"
        }
    ],
    "sg:phone":"+1 302 322 7015",
    "sg:postcode":"19720",
    "sg:province":"DE",
    "sg:tags":[
        "loan",
        "real estate"
    ],
    "wof:name":"Mc Nally Mortgage",
    "wof:placetype":"venue"
},
  "geometry": {"coordinates":[-75.567814,39.662653],"type":"Point"}
}