{
  "type": "Feature",
  "properties": {
    "iso:country":"US",
    "sg:address":"212 New Castle Ave",
    "sg:city":"New Castle",
    "sg:classifiers":[
        {
            "category":"Restaurant",
            "type":"Food & Drink"
        }
    ],
    "sg:phone":"+1 302 888 1660",
    "sg:postcode":"19720",
    "sg:province":"DE",
    "sg:tags":[
        "shop",
        "sub",
        "pizza"
    ],
    "wof:name":"Pizza Couriers & Express Wings",
    "wof:placetype":"venue"
},
  "geometry": {"coordinates":[-75.556405,39.687836],"type":"Point"}
}