{
  "type": "Feature",
  "properties": {
    "iso:country":"US",
    "sg:address":"5616 Kirkwood Hwy",
    "sg:city":"Wilmington",
    "sg:classifiers":[
        {
            "category":"Professional",
            "subcategory":"Business Services",
            "type":"Services"
        }
    ],
    "sg:phone":"+1 302 994 2000",
    "sg:postcode":"19808",
    "sg:province":"DE",
    "wof:name":"Comprehensive Business Svcs",
    "wof:placetype":"venue"
},
  "geometry": {"coordinates":[-75.67489399999999,39.714234],"type":"Point"}
}