{
  "type": "Feature",
  "properties": {
    "addr:full":"2076 Limestone Rd Wilmington DE 19808",
    "addr:housenumber":"2076",
    "addr:postcode":"19808",
    "addr:street":"Limestone Rd",
    "iso:country":"US",
    "sg:address":"2076 Limestone Rd",
    "sg:city":"Wilmington",
    "sg:classifiers":[
        {
            "category":"Restaurant",
            "type":"Food & Drink"
        }
    ],
    "sg:phone":"+1 302 998 0096",
    "sg:postcode":"19808",
    "sg:province":"DE",
    "sg:tags":[
        "shop",
        "sandwich"
    ],
    "wof:name":"Capriotti's Sandwich Shop",
    "wof:placetype":"venue"
},
  "geometry": {"coordinates":[-75.657066,39.722588],"type":"Point"}
}