{
  "type": "Feature",
  "properties": {
    "iso:country":"US",
    "sg:address":"907 McDowell Dr",
    "sg:city":"Dover",
    "sg:classifiers":[
        {
            "category":"Insurance",
            "subcategory":"Insurance Agent",
            "type":"Services"
        }
    ],
    "sg:phone":"+1 302 736 1822",
    "sg:postcode":"19901",
    "sg:province":"DE",
    "sg:tags":[
        "professional"
    ],
    "wof:name":"Aspire People Services",
    "wof:placetype":"venue"
},
  "geometry": {"coordinates":[-75.514157,39.176633],"type":"Point"}
}