{
  "type": "Feature",
  "properties": {
    "iso:country":"US",
    "sg:address":"5 Meadow Ln",
    "sg:city":"Ocean View",
    "sg:classifiers":[
        {
            "category":"Real Estate",
            "subcategory":"Real Estate Agent",
            "type":"Services"
        }
    ],
    "sg:phone":"+1 302 539 4940",
    "sg:postcode":"19970",
    "sg:province":"DE",
    "wof:name":"Domani Consulting",
    "wof:placetype":"venue"
},
  "geometry": {"coordinates":[-75.108604,38.539359],"type":"Point"}
}