{
  "type": "Feature",
  "properties": {
    "addr:full":"222 S Chapel St Newark DE 19711",
    "addr:housenumber":"222",
    "addr:postcode":"19711",
    "addr:street":"S Chapel St",
    "iso:country":"US",
    "sg:address":"222 S Chapel St",
    "sg:city":"Newark",
    "sg:classifiers":[
        {
            "category":"Personal",
            "type":"Services"
        }
    ],
    "sg:phone":"+1 302 831 1461",
    "sg:postcode":"19711",
    "sg:province":"DE",
    "wof:name":"Protermant Services",
    "wof:placetype":"venue"
},
  "geometry": {"coordinates":[-75.743503,39.676114],"type":"Point"}
}