{
  "type": "Feature",
  "properties": {
    "iso:country":"US",
    "sg:address":"5321 N Dupont Hwy",
    "sg:city":"Dover",
    "sg:classifiers":[
        {
            "category":"Home & Garden",
            "subcategory":"Furniture",
            "type":"Retail Goods"
        }
    ],
    "sg:phone":"+1 302 653 2411",
    "sg:postcode":"19901",
    "sg:province":"DE",
    "sg:tags":[
        "store"
    ],
    "wof:name":"American Heirlooms by Kenton Chair Shop",
    "wof:placetype":"venue"
},
  "geometry": {"coordinates":[-75.57567,39.221569],"type":"Point"}
}