{
  "type": "Feature",
  "properties": {
    "iso:country":"US",
    "sg:address":"127 Wembley Rd",
    "sg:city":"Wilmington",
    "sg:classifiers":[
        {
            "category":"Wholesale",
            "subcategory":"Machinery & Supplies",
            "type":"Manufacturing & Wholesale Goods"
        }
    ],
    "sg:phone":"+1 302 234 4414",
    "sg:postcode":"19808",
    "sg:province":"DE",
    "sg:tags":[
        "packaging"
    ],
    "wof:name":"Active Perforated Films",
    "wof:placetype":"venue"
},
  "geometry": {"coordinates":[-75.663571,39.768161],"type":"Point"}
}