{
  "type": "Feature",
  "properties": {
    "iso:country":"US",
    "sg:address":"1176 Pulaski Hwy",
    "sg:city":"Bear",
    "sg:classifiers":[
        {
            "category":"Travel",
            "subcategory":"Hotels & Motels",
            "type":"Entertainment"
        }
    ],
    "sg:phone":"+1 302 834 9812",
    "sg:postcode":"19701",
    "sg:province":"DE",
    "sg:tags":[
        "operation"
    ],
    "wof:name":"Glen Efficiencies & Motel",
    "wof:placetype":"venue"
},
  "geometry": {"coordinates":[-75.669721,39.628115],"type":"Point"}
}