{
  "type": "Feature",
  "properties": {
    "iso:country":"US",
    "sg:address":"4565 Hwy One",
    "sg:city":"Rehoboth Beach",
    "sg:classifiers":[
        {
            "category":"Shopping",
            "subcategory":"Clothing, Apparel, & Fashions",
            "type":"Retail Goods"
        }
    ],
    "sg:phone":"+1 302 644 2560",
    "sg:postcode":"19971",
    "sg:province":"DE",
    "sg:tags":[
        "sporting",
        "factory",
        "store"
    ],
    "wof:name":"L L Bean Rehoboth Bch Outl Ctr",
    "wof:placetype":"venue"
},
  "geometry": {"coordinates":[-75.137908,38.734708],"type":"Point"}
}