{
  "type": "Feature",
  "properties": {
    "iso:country":"US",
    "sg:address":"10797 Iron Hill Rd",
    "sg:city":"Delmar",
    "sg:classifiers":[
        {
            "category":"Home & Garden",
            "subcategory":"Mobile Homes",
            "type":"Retail Goods"
        }
    ],
    "sg:phone":"+1 302 846 9735",
    "sg:postcode":"19940",
    "sg:province":"DE",
    "sg:website":"www.atlantishomesllc.com",
    "wof:name":"Atlantis Homes",
    "wof:placetype":"venue"
},
  "geometry": {"coordinates":[-75.55184,38.477819],"type":"Point"}
}