{
  "type": "Feature",
  "properties": {
    "iso:country":"US",
    "sg:address":"5161 W Woodmill Dr",
    "sg:city":"Wilmington",
    "sg:classifiers":[
        {
            "category":"Autos & Motor Vehicles",
            "subcategory":"Auto Supplies",
            "type":"Retail Goods"
        }
    ],
    "sg:phone":"+1 302 892 3400",
    "sg:postcode":"19808",
    "sg:province":"DE",
    "sg:tags":[
        "automobile",
        "parts"
    ],
    "wof:name":"Sport Compact Pro",
    "wof:placetype":"venue"
},
  "geometry": {"coordinates":[-75.671986,39.717597],"type":"Point"}
}