{
  "type": "Feature",
  "properties": {
    "addr:full":"5714 Kennett Pike Wilmington DE 19807",
    "addr:housenumber":"5714",
    "addr:postcode":"19807",
    "addr:street":"Kennett Pike",
    "iso:country":"US",
    "sg:address":"5714 Kennett Pike",
    "sg:city":"Wilmington",
    "sg:classifiers":[
        {
            "category":"Manufacturing",
            "subcategory":"Printing",
            "type":"Manufacturing & Wholesale Goods"
        }
    ],
    "sg:phone":"+1 302 656 4868",
    "sg:postcode":"19807",
    "sg:province":"DE",
    "sg:tags":[
        "magazine",
        "publishing"
    ],
    "wof:name":"The Hunt Magazine",
    "wof:placetype":"venue"
},
  "geometry": {"coordinates":[-75.61639099999999,39.820712],"type":"Point"}
}