{
  "type": "Feature",
  "properties": {
    "iso:country":"US",
    "sg:address":"1911 N Market St",
    "sg:city":"Wilmington",
    "sg:classifiers":[
        {
            "category":"Personal",
            "subcategory":"Beauty Salon",
            "type":"Services"
        },
        {
            "category":"Personal",
            "subcategory":"Barber",
            "type":"Services"
        }
    ],
    "sg:phone":"+1 302 777 7855",
    "sg:postcode":"19802",
    "sg:province":"DE",
    "sg:tags":[
        "shop"
    ],
    "wof:name":"Made For Women Hair Studio",
    "wof:placetype":"venue"
},
  "geometry": {"coordinates":[-75.542,39.751805],"type":"Point"}
}