{
  "type": "Feature",
  "properties": {
    "iso:country":"US",
    "sg:address":"1302 Hillside Ave",
    "sg:city":"Wilmington",
    "sg:classifiers":[
        {
            "category":"Professional",
            "subcategory":"Management & Consulting",
            "type":"Services"
        }
    ],
    "sg:phone":"+1 302 798 7970",
    "sg:postcode":"19809",
    "sg:province":"DE",
    "sg:tags":[
        "business"
    ],
    "wof:name":"Joseph Kosloski",
    "wof:placetype":"venue"
},
  "geometry": {"coordinates":[-75.48688199999999,39.785656],"type":"Point"}
}