{
  "type": "Feature",
  "properties": {
    "iso:country":"US",
    "sg:address":"1003 Walker Rd",
    "sg:city":"Dover",
    "sg:classifiers":[
        {
            "category":"Shopping",
            "subcategory":"Department Store",
            "type":"Retail Goods"
        }
    ],
    "sg:phone":"+1 302 734 2228",
    "sg:postcode":"19904",
    "sg:province":"DE",
    "sg:tags":[
        "shop"
    ],
    "wof:name":"Dollar Discount 9274",
    "wof:placetype":"venue"
},
  "geometry": {"coordinates":[-75.546536,39.169444],"type":"Point"}
}