{
  "type": "Feature",
  "properties": {
    "addr:full":"200 Christiana Farms Pl Newark DE 19702",
    "addr:housenumber":"200",
    "addr:postcode":"19702",
    "addr:street":"Christiana Farms Pl",
    "iso:country":"US",
    "sg:address":"200 Christiana Farms Pl",
    "sg:city":"Newark",
    "sg:classifiers":[
        {
            "category":"Social Services",
            "type":"Services"
        }
    ],
    "sg:phone":"+1 302 368 1100",
    "sg:postcode":"19702",
    "sg:province":"DE",
    "wof:name":"Pdms Inc",
    "wof:placetype":"venue"
},
  "geometry": {"coordinates":[-75.713948,39.64418],"type":"Point"}
}