{
  "type": "Feature",
  "properties": {
    "iso:country":"US",
    "sg:address":"126 Main St",
    "sg:city":"Townsend",
    "sg:classifiers":[
        {
            "category":"Education",
            "subcategory":"School",
            "type":"Public Place"
        }
    ],
    "sg:phone":"+1 302 378 5020",
    "sg:postcode":"19734",
    "sg:province":"DE",
    "wof:name":"Townsend Elementary School",
    "wof:placetype":"venue"
},
  "geometry": {"coordinates":[-75.689351,39.39598],"type":"Point"}
}