{
  "type": "Feature",
  "properties": {
    "addr:full":"2628 Newell Dr Wilmington DE 19808",
    "addr:housenumber":"2628",
    "addr:postcode":"19808",
    "addr:street":"Newell Dr",
    "iso:country":"US",
    "sg:address":"2628 Newell Dr",
    "sg:city":"Wilmington",
    "sg:classifiers":[
        {
            "category":"Shopping",
            "type":"Retail Goods"
        },
        {
            "category":"Manufacturing",
            "subcategory":"Food",
            "type":"Manufacturing & Wholesale Goods"
        }
    ],
    "sg:phone":"+1 302 998 1763",
    "sg:postcode":"19808",
    "sg:province":"DE",
    "sg:tags":[
        "mfg",
        "merchandise",
        "miscellaneous",
        "ice",
        "relations",
        "public",
        "store"
    ],
    "wof:name":"Kimos Real Hawaiian Shave Ice",
    "wof:placetype":"venue"
},
  "geometry": {"coordinates":[-75.632152,39.74421],"type":"Point"}
}