{
  "type": "Feature",
  "properties": {
    "addr:full":"1409 N Dupont Hwy New Castle DE 19720",
    "addr:housenumber":"1409",
    "addr:postcode":"19720",
    "addr:street":"N Dupont Hwy",
    "iso:country":"US",
    "sg:address":"1409 N Dupont Hwy",
    "sg:city":"New Castle",
    "sg:classifiers":[
        {
            "category":"Restaurant",
            "type":"Food & Drink"
        }
    ],
    "sg:menulink":"http://www.allmenus.com/de/new-castle/109719-subway/menu/",
    "sg:phone":"+1 302 328 9257",
    "sg:postcode":"19720",
    "sg:province":"DE",
    "sg:tags":[
        "american",
        "sandwich"
    ],
    "wof:name":"Subway",
    "wof:placetype":"venue"
},
  "geometry": {"coordinates":[-75.58291,39.690072],"type":"Point"}
}