{
  "type": "Feature",
  "properties": {
    "iso:country":"US",
    "sg:address":"3120 Naamans Rd",
    "sg:city":"Wilmington",
    "sg:classifiers":[
        {
            "category":"Recreation",
            "type":"Entertainment"
        }
    ],
    "sg:phone":"+1 302 478 7590",
    "sg:postcode":"19810",
    "sg:province":"DE",
    "wof:name":"Archangel Psychic Network",
    "wof:placetype":"venue"
},
  "geometry": {"coordinates":[-75.539293,39.829184],"type":"Point"}
}