{
  "type": "Feature",
  "properties": {
    "iso:country":"US",
    "sg:address":"756 Long Point Rd",
    "sg:city":"Dover",
    "sg:classifiers":[
        {
            "category":"Freight",
            "type":"Transportation"
        }
    ],
    "sg:phone":"+1 302 734 7376",
    "sg:postcode":"19901",
    "sg:province":"DE",
    "sg:tags":[
        "trucking"
    ],
    "wof:name":"Quicksilver Trucking",
    "wof:placetype":"venue"
},
  "geometry": {"coordinates":[-75.478618,39.172911],"type":"Point"}
}