{
  "type": "Feature",
  "properties": {
    "iso:country":"US",
    "sg:address":"7 W Commons Blvd",
    "sg:city":"New Castle",
    "sg:classifiers":[
        {
            "category":"Wholesale",
            "subcategory":"Machinery & Supplies",
            "type":"Manufacturing & Wholesale Goods"
        }
    ],
    "sg:phone":"+1 302 322 5411",
    "sg:postcode":"19720",
    "sg:province":"DE",
    "sg:tags":[
        "pipe",
        "fitting"
    ],
    "wof:name":"Deacon Industrial Supply Co",
    "wof:placetype":"venue"
},
  "geometry": {"coordinates":[-75.61458500000001,39.6853],"type":"Point"}
}