{
  "type": "Feature",
  "properties": {
    "iso:country":"US",
    "sg:address":"9 Mason Dr",
    "sg:city":"Selbyville",
    "sg:classifiers":[
        {
            "category":"Wholesale",
            "subcategory":"Machinery & Supplies",
            "type":"Manufacturing & Wholesale Goods"
        }
    ],
    "sg:phone":"+1 302 436 4070",
    "sg:postcode":"19975",
    "sg:province":"DE",
    "sg:tags":[
        "equipment",
        "industrial"
    ],
    "wof:name":"Fastenal Co",
    "wof:placetype":"venue"
},
  "geometry": {"coordinates":[-75.22942999999999,38.451439],"type":"Point"}
}