{
  "type": "Feature",
  "properties": {
    "iso:country":"US",
    "sg:address":"320 Water St",
    "sg:city":"Wilmington",
    "sg:classifiers":[
        {
            "category":"Building & Trades",
            "subcategory":"Electrical",
            "type":"Services"
        }
    ],
    "sg:phone":"+1 302 998 2989",
    "sg:postcode":"19804",
    "sg:province":"DE",
    "sg:tags":[
        "electrical",
        "contractor"
    ],
    "wof:name":"Flash Electric",
    "wof:placetype":"venue"
},
  "geometry": {"coordinates":[-75.599532,39.713091],"type":"Point"}
}