{
  "type": "Feature",
  "properties": {
    "iso:country":"US",
    "sg:address":"520 Copper Dr",
    "sg:city":"Newport",
    "sg:classifiers":[
        {
            "category":"Building & Trades",
            "subcategory":"Construction",
            "type":"Services"
        }
    ],
    "sg:phone":"+1 302 225 2311",
    "sg:postcode":"19804",
    "sg:province":"DE",
    "sg:tags":[
        "resurfacing",
        "laying",
        "refinishing",
        "floor"
    ],
    "wof:name":"Longest Yard Inc",
    "wof:placetype":"venue"
},
  "geometry": {"coordinates":[-75.59848700000001,39.711498],"type":"Point"}
}