{
  "type": "Feature",
  "properties": {
    "addr:full":"78 Albe Dr Newark DE 19702",
    "addr:housenumber":"78",
    "addr:postcode":"19702",
    "addr:street":"Albe Dr",
    "iso:country":"US",
    "sg:address":"78 Albe Dr",
    "sg:city":"Newark",
    "sg:classifiers":[
        {
            "category":"Retail",
            "subcategory":"Auto Repair",
            "type":"Services"
        }
    ],
    "sg:phone":"+1 302 368 3469",
    "sg:postcode":"19702",
    "sg:province":"DE",
    "sg:tags":[
        "repairing",
        "automobile",
        "automotive",
        "general"
    ],
    "wof:name":"Reeder's Auto",
    "wof:placetype":"venue"
},
  "geometry": {"coordinates":[-75.715101,39.650324],"type":"Point"}
}