{
  "type": "Feature",
  "properties": {
    "iso:country":"US",
    "sg:address":"21 NW Front St",
    "sg:city":"Milford",
    "sg:classifiers":[
        {
            "category":"Social Services",
            "type":"Services"
        }
    ],
    "sg:phone":"+1 302 424 4121",
    "sg:postcode":"19963",
    "sg:province":"DE",
    "sg:tags":[
        "counseling"
    ],
    "wof:name":"Community Counseling Assoc",
    "wof:placetype":"venue"
},
  "geometry": {"coordinates":[-75.428472,38.91459],"type":"Point"}
}