{
  "type": "Feature",
  "properties": {
    "iso:country":"US",
    "sg:address":"6 Windward Dr",
    "sg:city":"Felton",
    "sg:classifiers":[
        {
            "category":"Building & Trades",
            "subcategory":"Landscaping Services",
            "type":"Services"
        }
    ],
    "sg:phone":"+1 302 335 5433",
    "sg:postcode":"19943",
    "sg:province":"DE",
    "sg:tags":[
        "installation",
        "sprinkler"
    ],
    "wof:name":"Mary Annes Landscaping Inc",
    "wof:placetype":"venue"
},
  "geometry": {"coordinates":[-75.51334799999999,39.03127],"type":"Point"}
}