{
  "type": "Feature",
  "properties": {
    "addr:full":"100 S Lincoln St Wilmington DE 19805",
    "addr:housenumber":"100",
    "addr:postcode":"19805",
    "addr:street":"S Lincoln St",
    "iso:country":"US",
    "sg:address":"100 S Lincoln St",
    "sg:city":"Wilmington",
    "sg:classifiers":[
        {
            "category":"Real Estate",
            "subcategory":"Real Estate Agent",
            "type":"Services"
        }
    ],
    "sg:phone":"+1 302 777 3399",
    "sg:postcode":"19805",
    "sg:province":"DE",
    "wof:name":"Eurocar 2000 Inc",
    "wof:placetype":"venue"
},
  "geometry": {"coordinates":[-75.574117,39.745447],"type":"Point"}
}