{
  "type": "Feature",
  "properties": {
    "iso:country":"US",
    "sg:address":"249 Appleby Rd",
    "sg:city":"New Castle",
    "sg:classifiers":[
        {
            "category":"Building & Trades",
            "subcategory":"Cleaning & Sanitation",
            "type":"Services"
        }
    ],
    "sg:phone":"+1 302 325 2900",
    "sg:postcode":"19720",
    "sg:province":"DE",
    "sg:tags":[
        "janitor"
    ],
    "wof:name":"Global USA Cleaning Systems",
    "wof:placetype":"venue"
},
  "geometry": {"coordinates":[-75.631967,39.65039],"type":"Point"}
}