{
  "type": "Feature",
  "properties": {
    "iso:country":"US",
    "sg:address":"209 W 4th St",
    "sg:city":"Wilmington",
    "sg:classifiers":[
        {
            "category":"Health Services",
            "subcategory":"Health Practitioner",
            "type":"Services"
        }
    ],
    "sg:phone":"+1 302 777 3910",
    "sg:postcode":"19801",
    "sg:province":"DE",
    "wof:name":"4th St Chropractic",
    "wof:placetype":"venue"
},
  "geometry": {"coordinates":[-75.55347,39.741383],"type":"Point"}
}