{
  "type": "Feature",
  "properties": {
    "iso:country":"US",
    "sg:address":"2713 Tanager Dr",
    "sg:city":"Wilmington",
    "sg:classifiers":[
        {
            "category":"Building & Trades",
            "subcategory":"Construction",
            "type":"Services"
        }
    ],
    "sg:phone":"+1 302 994 8929",
    "sg:postcode":"19808",
    "sg:province":"DE",
    "sg:tags":[
        "hanging",
        "contractor"
    ],
    "wof:name":"M & N Painting Co",
    "wof:placetype":"venue"
},
  "geometry": {"coordinates":[-75.62938200000001,39.749729],"type":"Point"}
}