{
  "type": "Feature",
  "properties": {
    "iso:country":"US",
    "sg:address":"806 W Newport Pike",
    "sg:city":"Newport",
    "sg:classifiers":[
        {
            "category":"Retail",
            "subcategory":"Auto Repair",
            "type":"Services"
        }
    ],
    "sg:phone":"+1 302 994 1617",
    "sg:postcode":"19804",
    "sg:province":"DE",
    "sg:tags":[
        "repairing",
        "automobile",
        "general"
    ],
    "wof:name":"Silview Auto Care",
    "wof:placetype":"venue"
},
  "geometry": {"coordinates":[-75.617582,39.713917],"type":"Point"}
}