{
  "type": "Feature",
  "properties": {
    "addr:full":"314 E Main St Newark DE 19711",
    "addr:housenumber":"314",
    "addr:postcode":"19711",
    "addr:street":"E Main St",
    "iso:country":"US",
    "sg:address":"314 E Main St",
    "sg:city":"Newark",
    "sg:classifiers":[
        {
            "category":"Health Services",
            "subcategory":"Medical Lab",
            "type":"Services"
        }
    ],
    "sg:phone":"+1 302 455 0775",
    "sg:postcode":"19711",
    "sg:province":"DE",
    "sg:tags":[
        "laboratory"
    ],
    "wof:name":"Radiology Associates",
    "wof:placetype":"venue"
},
  "geometry": {"coordinates":[-75.739555,39.684214],"type":"Point"}
}