{
  "type": "Feature",
  "properties": {
    "addr:full":"4100 N Market St Wilmington DE 19802",
    "addr:housenumber":"4100",
    "addr:postcode":"19802",
    "addr:street":"N Market St",
    "iso:country":"US",
    "sg:address":"4100 N Market St",
    "sg:city":"Wilmington",
    "sg:classifiers":[
        {
            "category":"Restaurant",
            "type":"Food & Drink"
        }
    ],
    "sg:phone":"+1 302 764 9953",
    "sg:postcode":"19802",
    "sg:province":"DE",
    "wof:name":"Steak N Eggs",
    "wof:placetype":"venue"
},
  "geometry": {"coordinates":[-75.521416,39.76105],"type":"Point"}
}