{
  "type": "Feature",
  "properties": {
    "iso:country":"US",
    "sg:address":"19 Pine St",
    "sg:city":"Ocean View",
    "sg:classifiers":[
        {
            "category":"Professional",
            "subcategory":"Detective & Security Services",
            "type":"Services"
        }
    ],
    "sg:phone":"+1 302 539 5808",
    "sg:postcode":"19970",
    "sg:province":"DE",
    "sg:tags":[
        "guard",
        "patrol"
    ],
    "wof:name":"Resort Investigations & Patrol",
    "wof:placetype":"venue"
},
  "geometry": {"coordinates":[-75.109109,38.557419],"type":"Point"}
}