{
  "type": "Feature",
  "properties": {
    "addr:full":"300 Virginia Ave Seaford DE 19973",
    "addr:housenumber":"300",
    "addr:postcode":"19973",
    "addr:street":"Virginia Ave",
    "iso:country":"US",
    "sg:address":"300 Virginia Ave",
    "sg:city":"Seaford",
    "sg:classifiers":[
        {
            "category":"Government",
            "subcategory":"Police Station",
            "type":"Public Place"
        }
    ],
    "sg:phone":"+1 302 629 6644",
    "sg:postcode":"19973",
    "sg:province":"DE",
    "sg:tags":[
        "department"
    ],
    "wof:name":"Police Dept",
    "wof:placetype":"venue"
},
  "geometry": {"coordinates":[-75.614351,38.652912],"type":"Point"}
}