{
  "type": "Feature",
  "properties": {
    "iso:country":"US",
    "sg:address":"76 Creek Dr",
    "sg:city":"Millsboro",
    "sg:classifiers":[
        {
            "category":"Shopping",
            "subcategory":"Gifts & Souvenirs",
            "type":"Retail Goods"
        }
    ],
    "sg:phone":"+1 302 947 9820",
    "sg:postcode":"19966",
    "sg:province":"DE",
    "wof:name":"D K Designs",
    "wof:placetype":"venue"
},
  "geometry": {"coordinates":[-75.153328,38.646015],"type":"Point"}
}