{
  "type": "Feature",
  "properties": {
    "addr:full":"4520 Kirkwood Hwy Wilmington DE 19808",
    "addr:housenumber":"4520",
    "addr:postcode":"19808",
    "addr:street":"Kirkwood Hwy",
    "iso:country":"US",
    "sg:address":"4520 Kirkwood Hwy",
    "sg:city":"Wilmington",
    "sg:classifiers":[
        {
            "category":"Shopping",
            "subcategory":"Optical Goods",
            "type":"Retail Goods"
        }
    ],
    "sg:phone":"+1 302 998 4500",
    "sg:postcode":"19808",
    "sg:province":"DE",
    "wof:name":"Sterling Optical",
    "wof:placetype":"venue"
},
  "geometry": {"coordinates":[-75.657532,39.724064],"type":"Point"}
}