{
  "type": "Feature",
  "properties": {
    "iso:country":"US",
    "sg:address":"232 W Ayre St",
    "sg:city":"Newport",
    "sg:classifiers":[
        {
            "category":"Building & Trades",
            "subcategory":"Construction",
            "type":"Services"
        }
    ],
    "sg:phone":"+1 302 994 6461",
    "sg:postcode":"19804",
    "sg:province":"DE",
    "sg:tags":[
        "concrete",
        "contractor"
    ],
    "wof:name":"Chambers & Sons General Constr",
    "wof:placetype":"venue"
},
  "geometry": {"coordinates":[-75.613164,39.712174],"type":"Point"}
}