{
  "type": "Feature",
  "properties": {
    "iso:country":"US",
    "sg:address":"870 Bayview Rd",
    "sg:city":"Middletown",
    "sg:classifiers":[
        {
            "category":"Shopping",
            "type":"Retail Goods"
        }
    ],
    "sg:phone":"+1 302 378 8829",
    "sg:postcode":"19709",
    "sg:province":"DE",
    "sg:tags":[
        "merchandise",
        "supply"
    ],
    "wof:name":"Agway",
    "wof:placetype":"venue"
},
  "geometry": {"coordinates":[-75.63293400000001,39.492396],"type":"Point"}
}