{
  "type": "Feature",
  "properties": {
    "iso:country":"US",
    "sg:address":"1047 Dexter Corner Rd",
    "sg:city":"Townsend",
    "sg:classifiers":[
        {
            "category":"Building & Trades",
            "subcategory":"Construction",
            "type":"Services"
        }
    ],
    "sg:phone":"+1 302 378 4904",
    "sg:postcode":"19734",
    "sg:province":"DE",
    "sg:tags":[
        "house",
        "contractor"
    ],
    "wof:name":"Estepp Construction Company",
    "wof:placetype":"venue"
},
  "geometry": {"coordinates":[-75.697804,39.372044],"type":"Point"}
}