{
  "type": "Feature",
  "properties": {
    "iso:country":"US",
    "sg:address":"18276 Dupont Blvd",
    "sg:city":"Georgetown",
    "sg:classifiers":[
        {
            "category":"Autos & Motor Vehicles",
            "subcategory":"Automobile Sales",
            "type":"Retail Goods"
        }
    ],
    "sg:phone":"+1 302 856 1491",
    "sg:postcode":"19947",
    "sg:province":"DE",
    "sg:tags":[
        "car",
        "used",
        "dealer"
    ],
    "wof:name":"Daisey's Used Cars Inc",
    "wof:placetype":"venue"
},
  "geometry": {"coordinates":[-75.42020599999999,38.734258],"type":"Point"}
}