{
  "type": "Feature",
  "properties": {
    "addr:full":"400 David Hollowell Dr Newark DE 19716",
    "addr:housenumber":"400",
    "addr:postcode":"19716",
    "addr:street":"David Hollowell Dr",
    "iso:country":"US",
    "sg:address":"400 David Hollowell Dr",
    "sg:city":"Newark",
    "sg:classifiers":[
        {
            "category":"Travel",
            "subcategory":"Hotels & Motels",
            "type":"Entertainment"
        }
    ],
    "sg:phone":"+1 302 737 0900",
    "sg:postcode":"19716",
    "sg:province":"DE",
    "sg:tags":[
        "lodging"
    ],
    "wof:name":"Courtyard by Marriott Newark - University of Delaware",
    "wof:placetype":"venue"
},
  "geometry": {"coordinates":[-75.75702800000001,39.687904],"type":"Point"}
}