{
  "type": "Feature",
  "properties": {
    "iso:country":"US",
    "sg:address":"208 N Connell St",
    "sg:city":"Wilmington",
    "sg:classifiers":[
        {
            "category":"Freight",
            "type":"Transportation"
        }
    ],
    "sg:phone":"+1 302 395 1801",
    "sg:postcode":"19805",
    "sg:province":"DE",
    "wof:name":"Weepak Moving & Storage",
    "wof:placetype":"venue"
},
  "geometry": {"coordinates":[-75.565324,39.745255],"type":"Point"}
}