{
  "type": "Feature",
  "properties": {
    "iso:country":"US",
    "sg:address":"153 E Chestnut Hill Rd",
    "sg:city":"Newark",
    "sg:classifiers":[
        {
            "category":"Professional",
            "subcategory":"Computer Services",
            "type":"Services"
        }
    ],
    "sg:phone":"+1 302 369 6250",
    "sg:postcode":"19713",
    "sg:province":"DE",
    "wof:name":"Delcom Computers",
    "wof:placetype":"venue"
},
  "geometry": {"coordinates":[-75.741803,39.659584],"type":"Point"}
}