{
  "type": "Feature",
  "properties": {
    "iso:country":"US",
    "sg:address":"22062 Mill Park Dr",
    "sg:city":"Bridgeville",
    "sg:classifiers":[
        {
            "category":"Organizations",
            "subcategory":"Religious Organization",
            "type":"Services"
        }
    ],
    "sg:phone":"+1 302 337 7111",
    "sg:postcode":"19933",
    "sg:province":"DE",
    "sg:tags":[
        "church"
    ],
    "wof:name":"Victory Temple Treasure",
    "wof:placetype":"venue"
},
  "geometry": {"coordinates":[-75.54922000000001,38.693552],"type":"Point"}
}