{
  "type": "Feature",
  "properties": {
    "iso:country":"US",
    "sg:address":"642 S Queen St",
    "sg:city":"Dover",
    "sg:classifiers":[
        {
            "category":"Manufacturing",
            "subcategory":"Tools & Machinery",
            "type":"Manufacturing & Wholesale Goods"
        }
    ],
    "sg:phone":"+1 302 678 8311",
    "sg:postcode":"19904",
    "sg:province":"DE",
    "sg:tags":[
        "surgical",
        "mfg"
    ],
    "wof:name":"Delmarva Orthotics Prosthetics",
    "wof:placetype":"venue"
},
  "geometry": {"coordinates":[-75.528003,39.151931],"type":"Point"}
}