{
  "type": "Feature",
  "properties": {
    "addr:full":"2 Higgins Rd Newark DE 19711",
    "addr:housenumber":"2",
    "addr:postcode":"19711",
    "addr:street":"Higgins Rd",
    "iso:country":"US",
    "sg:address":"2 Higgins Rd",
    "sg:city":"Newark",
    "sg:classifiers":[
        {
            "category":"Social Services",
            "subcategory":"Child Care",
            "type":"Services"
        }
    ],
    "sg:phone":"+1 302 738 3633",
    "sg:postcode":"19711",
    "sg:province":"DE",
    "sg:tags":[
        "day"
    ],
    "wof:name":"Eastmans Kristine Day Care",
    "wof:placetype":"venue"
},
  "geometry": {"coordinates":[-75.708935,39.726179],"type":"Point"}
}