{
  "type": "Feature",
  "properties": {
    "iso:country":"US",
    "sg:address":"2702 Kirkwood Hwy",
    "sg:city":"Wilmington",
    "sg:classifiers":[
        {
            "category":"Organizations",
            "subcategory":"Religious Organization",
            "type":"Services"
        }
    ],
    "sg:phone":"+1 302 999 7713",
    "sg:postcode":"19805",
    "sg:province":"DE",
    "wof:name":"Church Of The Nazarene",
    "wof:placetype":"venue"
},
  "geometry": {"coordinates":[-75.615921,39.737634],"type":"Point"}
}