{
  "type": "Feature",
  "properties": {
    "iso:country":"US",
    "sg:address":"3310 Wrangle Hill Rd",
    "sg:city":"Bear",
    "sg:classifiers":[
        {
            "category":"Retail",
            "subcategory":"Auto Repair",
            "type":"Services"
        }
    ],
    "sg:phone":"+1 302 838 7040",
    "sg:postcode":"19701",
    "sg:province":"DE",
    "sg:tags":[
        "general"
    ],
    "wof:name":"Expert Mufflers & Brakes",
    "wof:placetype":"venue"
},
  "geometry": {"coordinates":[-75.69116200000001,39.588529],"type":"Point"}
}