{
  "type": "Feature",
  "properties": {
    "iso:country":"US",
    "sg:address":"901 N Washington St",
    "sg:city":"Wilmington",
    "sg:classifiers":[
        {
            "category":"Professional",
            "subcategory":"Computer Services",
            "type":"Services"
        }
    ],
    "sg:phone":"+1 302 777 2163",
    "sg:postcode":"19801",
    "sg:province":"DE",
    "sg:tags":[
        "consultant",
        "designer"
    ],
    "wof:name":"Nile Systems Inc",
    "wof:placetype":"venue"
},
  "geometry": {"coordinates":[-75.551799,39.74717],"type":"Point"}
}