{
  "type": "Feature",
  "properties": {
    "iso:country":"US",
    "sg:address":"32 Honeysuckle Dr",
    "sg:city":"Wilmington",
    "sg:classifiers":[
        {
            "category":"School Buses",
            "type":"Transportation"
        }
    ],
    "sg:phone":"+1 302 998 5463",
    "sg:postcode":"19804",
    "sg:province":"DE",
    "wof:name":"Boulden Buses Inc",
    "wof:placetype":"venue"
},
  "geometry": {"coordinates":[-75.648582,39.710644],"type":"Point"}
}