{
  "type": "Feature",
  "properties": {
    "iso:country":"US",
    "sg:address":"3411 Silverside Rd",
    "sg:city":"Wilmington",
    "sg:classifiers":[
        {
            "category":"Building & Trades",
            "subcategory":"Construction",
            "type":"Services"
        }
    ],
    "sg:phone":"+1 302 478 6030",
    "sg:postcode":"19810",
    "sg:province":"DE",
    "sg:tags":[
        "general",
        "contractor"
    ],
    "sg:website":"www.scaconstructs.com",
    "wof:name":"Snyder Crompton & Assoc Inc",
    "wof:placetype":"venue"
},
  "geometry": {"coordinates":[-75.549054,39.80927],"type":"Point"}
}