{
  "type": "Feature",
  "properties": {
    "iso:country":"US",
    "sg:address":"2718 Naamans Rd",
    "sg:city":"Wilmington",
    "sg:classifiers":[
        {
            "category":"Food & Beverages",
            "subcategory":"Liquor & Beverages",
            "type":"Retail Goods"
        }
    ],
    "sg:phone":"+1 302 475 9420",
    "sg:postcode":"19810",
    "sg:province":"DE",
    "sg:tags":[
        "beer",
        "spirit",
        "wine"
    ],
    "wof:name":"Brandywine Liquors",
    "wof:placetype":"venue"
},
  "geometry": {"coordinates":[-75.52359800000001,39.828499],"type":"Point"}
}