{
  "type": "Feature",
  "properties": {
    "iso:country":"US",
    "sg:address":"5700 Kirkwood Hwy Ste 204",
    "sg:city":"Wilmington",
    "sg:classifiers":[
        {
            "category":"Health Services",
            "subcategory":"Doctor",
            "type":"Services"
        }
    ],
    "sg:phone":"+1 302 992 9990",
    "sg:postcode":"19808",
    "sg:province":"DE",
    "sg:tags":[
        "physician",
        "oncology",
        "surgeons",
        "surgeon",
        "gynecologic"
    ],
    "wof:name":"Promila Suri Md",
    "wof:placetype":"venue"
},
  "geometry": {"coordinates":[-75.67434,39.714731],"type":"Point"}
}