{
  "type": "Feature",
  "properties": {
    "addr:full":"5 Essex Dr Bear DE 19701",
    "addr:housenumber":"5",
    "addr:postcode":"19701",
    "addr:street":"Essex Dr",
    "iso:country":"US",
    "sg:address":"5 Essex Dr",
    "sg:city":"Bear",
    "sg:classifiers":[
        {
            "category":"Social Services",
            "subcategory":"Job Training",
            "type":"Services"
        }
    ],
    "sg:phone":"+1 302 834 1369",
    "sg:postcode":"19701",
    "sg:province":"DE",
    "wof:name":"Delaware Aerospace Ed Fndtion",
    "wof:placetype":"venue"
},
  "geometry": {"coordinates":[-75.72772399999999,39.597931],"type":"Point"}
}