{
  "type": "Feature",
  "properties": {
    "iso:country":"US",
    "sg:address":"161 Sugarberry Dr",
    "sg:city":"New Castle",
    "sg:classifiers":[
        {
            "category":"Autos & Motor Vehicles",
            "subcategory":"Automobile Sales",
            "type":"Retail Goods"
        }
    ],
    "sg:phone":"+1 302 834 4373",
    "sg:postcode":"19720",
    "sg:province":"DE",
    "sg:tags":[
        "car",
        "dealer"
    ],
    "wof:name":"Cars R Us Autoworld Inc",
    "wof:placetype":"venue"
},
  "geometry": {"coordinates":[-75.647158,39.619864],"type":"Point"}
}