{
  "type": "Feature",
  "properties": {
    "iso:country":"US",
    "sg:address":"2700 Silverside Rd Ste 2",
    "sg:city":"Wilmington",
    "sg:classifiers":[
        {
            "category":"Health Services",
            "subcategory":"Doctor",
            "type":"Services"
        }
    ],
    "sg:phone":"+1 302 478 8421",
    "sg:postcode":"19810",
    "sg:province":"DE",
    "sg:tags":[
        "practice",
        "family"
    ],
    "wof:name":"Diehl Kristine MD",
    "wof:placetype":"venue"
},
  "geometry": {"coordinates":[-75.519096,39.8106],"type":"Point"}
}