{
  "type": "Feature",
  "properties": {
    "addr:full":"469 Old Airport Rd New Castle DE 19720",
    "addr:housenumber":"469",
    "addr:postcode":"19720",
    "addr:street":"Old Airport Rd New",
    "iso:country":"US",
    "sg:address":"469 Old Airport Rd",
    "sg:city":"New Castle",
    "sg:classifiers":[
        {
            "category":"Building & Trades",
            "subcategory":"Plumbing",
            "type":"Services"
        }
    ],
    "sg:phone":"+1 302 322 5220",
    "sg:postcode":"19720",
    "sg:province":"DE",
    "sg:tags":[
        "mechanical",
        "contractor"
    ],
    "wof:name":"American Mechanical Inc",
    "wof:placetype":"venue"
},
  "geometry": {"coordinates":[-75.615585,39.697988],"type":"Point"}
}