{
  "type": "Feature",
  "properties": {
    "iso:country":"US",
    "sg:address":"49 Primrose Dr",
    "sg:city":"Bear",
    "sg:classifiers":[
        {
            "category":"Professional",
            "subcategory":"Detective & Security Services",
            "type":"Services"
        }
    ],
    "sg:phone":"+1 302 832 8110",
    "sg:postcode":"19701",
    "sg:province":"DE",
    "sg:tags":[
        "system"
    ],
    "wof:name":"Security Plus",
    "wof:placetype":"venue"
},
  "geometry": {"coordinates":[-75.73922399999999,39.566376],"type":"Point"}
}