{
  "type": "Feature",
  "properties": {
    "addr:full":"30 Spruce Ave Wilmington DE 19805",
    "addr:housenumber":"30",
    "addr:postcode":"19805",
    "addr:street":"Spruce Ave",
    "iso:country":"US",
    "sg:address":"30 Spruce Ave",
    "sg:city":"Wilmington",
    "sg:classifiers":[
        {
            "category":"Education",
            "subcategory":"Library",
            "type":"Public Place"
        }
    ],
    "sg:phone":"+1 302 892 9814",
    "sg:postcode":"19805",
    "sg:province":"DE",
    "wof:name":"Elsmere Library",
    "wof:placetype":"venue"
},
  "geometry": {"coordinates":[-75.60300100000001,39.73962],"type":"Point"}
}