{
  "type": "Feature",
  "properties": {
    "addr:full":"3910 Concord Pike Wilmington DE 19803",
    "addr:housenumber":"3910",
    "addr:postcode":"19803",
    "addr:street":"Concord Pike",
    "iso:country":"US",
    "sg:address":"3910 Concord Pike",
    "sg:city":"Wilmington",
    "sg:classifiers":[
        {
            "category":"Restaurant",
            "type":"Food & Drink"
        }
    ],
    "sg:menulink":"http://www.allmenus.com/de/brandywine/207430-taco-bell/menu/",
    "sg:phone":"+1 302 478 8993",
    "sg:postcode":"19803",
    "sg:province":"DE",
    "sg:tags":[
        "mexican"
    ],
    "wof:name":"Taco Bell",
    "wof:placetype":"venue"
},
  "geometry": {"coordinates":[-75.54969800000001,39.807153],"type":"Point"}
}