{
  "type": "Feature",
  "properties": {
    "iso:country":"US",
    "sg:address":"2106 Silverside Rd",
    "sg:city":"Wilmington",
    "sg:classifiers":[
        {
            "category":"Health Services",
            "subcategory":"Podiatrist",
            "type":"Services"
        }
    ],
    "sg:phone":"+1 302 478 8099",
    "sg:postcode":"19810",
    "sg:province":"DE",
    "wof:name":"Brandywine Foot Care",
    "wof:placetype":"venue"
},
  "geometry": {"coordinates":[-75.50340300000001,39.801201],"type":"Point"}
}