{
  "type": "Feature",
  "properties": {
    "iso:country":"US",
    "sg:address":"699 Jimmy Dr Ste 1",
    "sg:city":"Smyrna",
    "sg:classifiers":[
        {
            "category":"Personal",
            "subcategory":"Beauty Salon",
            "type":"Services"
        },
        {
            "category":"Personal",
            "subcategory":"Barber",
            "type":"Services"
        }
    ],
    "sg:phone":"+1 302 659 3810",
    "sg:postcode":"19977",
    "sg:province":"DE",
    "wof:name":"Us Male Modern Barber Shop",
    "wof:placetype":"venue"
},
  "geometry": {"coordinates":[-75.594268,39.280857],"type":"Point"}
}