{
  "type": "Feature",
  "properties": {
    "iso:country":"US",
    "sg:address":"304 Savannah Rd",
    "sg:city":"Lewes",
    "sg:classifiers":[
        {
            "category":"Professional",
            "subcategory":"Management & Consulting",
            "type":"Services"
        }
    ],
    "sg:phone":"+1 302 645 0284",
    "sg:postcode":"19958",
    "sg:province":"DE",
    "sg:tags":[
        "consultant",
        "business"
    ],
    "wof:name":"A J Bennett & Assocs",
    "wof:placetype":"venue"
},
  "geometry": {"coordinates":[-75.139396,38.774164],"type":"Point"}
}