{
  "type": "Feature",
  "properties": {
    "addr:full":"813 N Market St Wilmington DE 19801",
    "addr:housenumber":"813",
    "addr:postcode":"19801",
    "addr:street":"N Market St",
    "iso:country":"US",
    "sg:address":"813 N Market St",
    "sg:city":"Wilmington",
    "sg:classifiers":[
        {
            "category":"Professional",
            "type":"Services"
        }
    ],
    "sg:phone":"+1 302 234 0767",
    "sg:postcode":"19801",
    "sg:province":"DE",
    "wof:name":"Progressive Digital Imaging In",
    "wof:placetype":"venue"
},
  "geometry": {"coordinates":[-75.54855499999999,39.744552],"type":"Point"}
}