{
  "type": "Feature",
  "properties": {
    "addr:full":"15 Dickinson St Rehoboth Beach DE 19971",
    "addr:housenumber":"15",
    "addr:postcode":"19971",
    "addr:street":"Dickinson St",
    "iso:country":"US",
    "sg:address":"15 Dickinson St",
    "sg:city":"Rehoboth Beach",
    "sg:classifiers":[
        {
            "category":"Health Services",
            "subcategory":"Doctor",
            "type":"Services"
        }
    ],
    "sg:phone":"+1 302 226 4940",
    "sg:postcode":"19971",
    "sg:province":"DE",
    "sg:tags":[
        "medical"
    ],
    "wof:name":"Arnold Sussman Dr",
    "wof:placetype":"venue"
},
  "geometry": {"coordinates":[-75.074404,38.689831],"type":"Point"}
}