{
  "type": "Feature",
  "properties": {
    "iso:country":"US",
    "sg:address":"2903 Bodine Dr",
    "sg:city":"Wilmington",
    "sg:classifiers":[
        {
            "category":"Real Estate",
            "subcategory":"Real Estate Services",
            "type":"Services"
        }
    ],
    "sg:phone":"+1 302 479 5010",
    "sg:postcode":"19810",
    "sg:province":"DE",
    "wof:name":"Moran Shawn Real Estate",
    "wof:placetype":"venue"
},
  "geometry": {"coordinates":[-75.53130299999999,39.8241],"type":"Point"}
}