{
  "type": "Feature",
  "properties": {
    "addr:full":"715 N Tatnall St Wilmington DE 19801",
    "addr:housenumber":"715",
    "addr:postcode":"19801",
    "addr:street":"N Tatnall St",
    "iso:country":"US",
    "sg:address":"715 N Tatnall St",
    "sg:city":"Wilmington",
    "sg:classifiers":[
        {
            "category":"Organizations",
            "subcategory":"Non-profit Organization",
            "type":"Services"
        }
    ],
    "sg:phone":"+1 302 654 1088",
    "sg:postcode":"19801",
    "sg:province":"DE",
    "wof:name":"Children & Family Frist",
    "wof:placetype":"venue"
},
  "geometry": {"coordinates":[-75.551666,39.744259],"type":"Point"}
}