{
  "type": "Feature",
  "properties": {
    "addr:full":"3601 Miller Rd Wilmington DE 19802",
    "addr:housenumber":"3601",
    "addr:postcode":"19802",
    "addr:street":"Miller Rd",
    "iso:country":"US",
    "sg:address":"3601 Miller Rd",
    "sg:city":"Wilmington",
    "sg:classifiers":[
        {
            "category":"Retail",
            "subcategory":"Auto Repair",
            "type":"Services"
        }
    ],
    "sg:phone":"+1 302 764 7300",
    "sg:postcode":"19802",
    "sg:province":"DE",
    "sg:tags":[
        "muffler",
        "exhaust",
        "system"
    ],
    "wof:name":"Midas Auto Svc Experts",
    "wof:placetype":"venue"
},
  "geometry": {"coordinates":[-75.534825,39.767821],"type":"Point"}
}