{
  "type": "Feature",
  "properties": {
    "addr:full":"1 Martine Ct Newark DE 19711",
    "addr:housenumber":"1",
    "addr:postcode":"19711",
    "addr:street":"Martine Ct",
    "iso:country":"US",
    "sg:address":"1 Martine Ct",
    "sg:city":"Newark",
    "sg:classifiers":[
        {
            "category":"Professional",
            "subcategory":"Detective & Security Services",
            "type":"Services"
        }
    ],
    "sg:phone":"+1 302 492 1099",
    "sg:postcode":"19711",
    "sg:province":"DE",
    "sg:tags":[
        "consulting"
    ],
    "wof:name":"Security Services Intl",
    "wof:placetype":"venue"
},
  "geometry": {"coordinates":[-75.705049,39.719035],"type":"Point"}
}