{
  "type": "Feature",
  "properties": {
    "iso:country":"US",
    "sg:address":"148 Willis Rd Apt F",
    "sg:city":"Dover",
    "sg:classifiers":[
        {
            "category":"Building & Trades",
            "subcategory":"Cleaning & Sanitation",
            "type":"Services"
        }
    ],
    "sg:phone":"+1 302 678 2578",
    "sg:postcode":"19901",
    "sg:province":"DE",
    "sg:tags":[
        "home",
        "carpet"
    ],
    "wof:name":"Nu-World Building Service",
    "wof:placetype":"venue"
},
  "geometry": {"coordinates":[-75.5093,39.1707],"type":"Point"}
}