{
  "type": "Feature",
  "properties": {
    "addr:full":"864 Valley Rd Hockessin DE 19707",
    "addr:housenumber":"864",
    "addr:postcode":"19707",
    "addr:street":"Valley Rd",
    "iso:country":"US",
    "sg:address":"864 Valley Rd",
    "sg:city":"Hockessin",
    "sg:classifiers":[
        {
            "category":"Building & Trades",
            "subcategory":"Landscaping Services",
            "type":"Services"
        }
    ],
    "sg:phone":"+1 302 239 0714",
    "sg:postcode":"19707",
    "sg:province":"DE",
    "sg:tags":[
        "sod",
        "sodding"
    ],
    "wof:name":"Orsini's Topsoil Hauling Inc",
    "wof:placetype":"venue"
},
  "geometry": {"coordinates":[-75.705715,39.784448],"type":"Point"}
}