{
  "type": "Feature",
  "properties": {
    "iso:country":"US",
    "sg:address":"324 5th Ave",
    "sg:city":"Wilmington",
    "sg:classifiers":[
        {
            "category":"Government",
            "subcategory":"Police Station",
            "type":"Public Place"
        }
    ],
    "sg:phone":"+1 302 655 6628",
    "sg:postcode":"19805",
    "sg:province":"DE",
    "sg:tags":[
        "protection"
    ],
    "wof:name":"Faternal Order Police Wilmi",
    "wof:placetype":"venue"
},
  "geometry": {"coordinates":[-75.567987,39.732905],"type":"Point"}
}