{
  "type": "Feature",
  "properties": {
    "iso:country":"US",
    "sg:address":"700 Otis Dr",
    "sg:city":"Dover",
    "sg:classifiers":[
        {
            "category":"Sports & Exercise",
            "subcategory":"Gym",
            "type":"Entertainment"
        }
    ],
    "sg:phone":"+1 302 674 4766",
    "sg:postcode":"19901",
    "sg:province":"DE",
    "wof:name":"Yph Consultants",
    "wof:placetype":"venue"
},
  "geometry": {"coordinates":[-75.496759,39.154035],"type":"Point"}
}