{
  "type": "Feature",
  "properties": {
    "iso:country":"US",
    "sg:address":"228 E Roosevelt Ave",
    "sg:city":"New Castle",
    "sg:classifiers":[
        {
            "category":"Organizations",
            "subcategory":"Professional Association",
            "type":"Services"
        }
    ],
    "sg:phone":"+1 302 328 2137",
    "sg:postcode":"19720",
    "sg:province":"DE",
    "sg:tags":[
        "business"
    ],
    "wof:name":"Bad 2 Association",
    "wof:placetype":"venue"
},
  "geometry": {"coordinates":[-75.58095400000001,39.682323],"type":"Point"}
}