{
  "type": "Feature",
  "properties": {
    "iso:country":"US",
    "sg:address":"226 N Walnut St",
    "sg:city":"Wilmington",
    "sg:classifiers":[
        {
            "category":"Social Services",
            "type":"Services"
        }
    ],
    "sg:phone":"+1 302 652 8278",
    "sg:postcode":"19801",
    "sg:province":"DE",
    "sg:tags":[
        "organization",
        "welfare"
    ],
    "sg:website":"www.friendship-house.org",
    "wof:name":"Friendship House",
    "wof:placetype":"venue"
},
  "geometry": {"coordinates":[-75.54900000000001,39.738707],"type":"Point"}
}