{
  "type": "Feature",
  "properties": {
    "iso:country":"US",
    "sg:address":"5 Jaymar Blvd",
    "sg:city":"Newark",
    "sg:classifiers":[
        {
            "category":"Building & Trades",
            "subcategory":"Construction",
            "type":"Services"
        }
    ],
    "sg:phone":"+1 302 738 2835",
    "sg:postcode":"19702",
    "sg:province":"DE",
    "sg:tags":[
        "hanging",
        "contractor"
    ],
    "wof:name":"J&C Painting",
    "wof:placetype":"venue"
},
  "geometry": {"coordinates":[-75.693917,39.646824],"type":"Point"}
}