{
  "type": "Feature",
  "properties": {
    "addr:full":"1214 Oak St Wilmington DE 19805",
    "addr:housenumber":"1214",
    "addr:postcode":"19805",
    "addr:street":"Oak St",
    "iso:country":"US",
    "sg:address":"1214 Oak St",
    "sg:city":"Wilmington",
    "sg:classifiers":[
        {
            "category":"Building & Trades",
            "subcategory":"Cleaning & Sanitation",
            "type":"Services"
        }
    ],
    "sg:phone":"+1 302 652 6368",
    "sg:postcode":"19805",
    "sg:province":"DE",
    "sg:tags":[
        "window"
    ],
    "wof:name":"David's Residential Window",
    "wof:placetype":"venue"
},
  "geometry": {"coordinates":[-75.568556,39.7376],"type":"Point"}
}