{
  "type": "Feature",
  "properties": {
    "iso:country":"US",
    "sg:address":"45 Germay Dr",
    "sg:city":"Wilmington",
    "sg:classifiers":[
        {
            "category":"Manufacturing",
            "subcategory":"Tools & Machinery",
            "type":"Manufacturing & Wholesale Goods"
        }
    ],
    "sg:phone":"+1 302 656 9406",
    "sg:postcode":"19804",
    "sg:province":"DE",
    "sg:tags":[
        "machine",
        "shop"
    ],
    "wof:name":"T & C Grinding Svc",
    "wof:placetype":"venue"
},
  "geometry": {"coordinates":[-75.577866,39.725194],"type":"Point"}
}