{
  "type": "Feature",
  "properties": {
    "iso:country":"US",
    "sg:address":"110 N Dupont Hwy",
    "sg:city":"New Castle",
    "sg:classifiers":[
        {
            "category":"Shopping",
            "subcategory":"Musical Instruments",
            "type":"Retail Goods"
        }
    ],
    "sg:phone":"+1 302 324 8867",
    "sg:postcode":"19720",
    "sg:province":"DE",
    "sg:tags":[
        "music",
        "dealer"
    ],
    "wof:name":"New Castle Music",
    "wof:placetype":"venue"
},
  "geometry": {"coordinates":[-75.59318,39.677097],"type":"Point"}
}