{
  "type": "Feature",
  "properties": {
    "iso:country":"US",
    "sg:address":"2901 Crossfork Dr",
    "sg:city":"Wilmington",
    "sg:classifiers":[
        {
            "category":"Real Estate",
            "subcategory":"Real Estate Operator",
            "type":"Services"
        }
    ],
    "sg:phone":"+1 302 994 1004",
    "sg:postcode":"19808",
    "sg:province":"DE",
    "sg:tags":[
        "building",
        "apartment"
    ],
    "wof:name":"Arundel Apartments",
    "wof:placetype":"venue"
},
  "geometry": {"coordinates":[-75.671852,39.736941],"type":"Point"}
}