{
  "type": "Feature",
  "properties": {
    "iso:country":"US",
    "sg:address":"670 Peoples Plz",
    "sg:city":"Newark",
    "sg:classifiers":[
        {
            "category":"Personal",
            "type":"Services"
        }
    ],
    "sg:phone":"+1 302 832 5515",
    "sg:postcode":"19702",
    "sg:province":"DE",
    "wof:name":"California Sun",
    "wof:placetype":"venue"
},
  "geometry": {"coordinates":[-75.745853,39.602967],"type":"Point"}
}