{
  "type": "Feature",
  "properties": {
    "addr:full":"1106 Berkeley Rd Wilmington DE 19807",
    "addr:housenumber":"1106",
    "addr:postcode":"19807",
    "addr:street":"Berkeley Rd",
    "iso:country":"US",
    "sg:address":"1106 Berkeley Rd",
    "sg:city":"Wilmington",
    "sg:classifiers":[
        {
            "category":"Organizations",
            "subcategory":"Non-profit Organization",
            "type":"Services"
        }
    ],
    "sg:phone":"+1 302 571 1217",
    "sg:postcode":"19807",
    "sg:province":"DE",
    "sg:tags":[
        "social"
    ],
    "wof:name":"Homes For Life Foundation",
    "wof:placetype":"venue"
},
  "geometry": {"coordinates":[-75.58726799999999,39.768547],"type":"Point"}
}