{
  "type": "Feature",
  "properties": {
    "addr:full":"115 E 14th St Wilmington DE 19801",
    "addr:housenumber":"115",
    "addr:postcode":"19801",
    "addr:street":"E 14Th St",
    "iso:country":"US",
    "sg:address":"115 E 14th St",
    "sg:city":"Wilmington",
    "sg:classifiers":[
        {
            "category":"Social Services",
            "subcategory":"Adult Care",
            "type":"Services"
        }
    ],
    "sg:phone":"+1 302 654 6908",
    "sg:postcode":"19801",
    "sg:province":"DE",
    "sg:tags":[
        "home",
        "group"
    ],
    "wof:name":"St Patrick' House Inc",
    "wof:placetype":"venue"
},
  "geometry": {"coordinates":[-75.543693,39.748497],"type":"Point"}
}