{
  "type": "Feature",
  "properties": {
    "addr:full":"18 N Purdue Ave New Castle DE 19720",
    "addr:housenumber":"18",
    "addr:postcode":"19720",
    "addr:street":"N Purdue Ave",
    "iso:country":"US",
    "sg:address":"18 N Purdue Ave",
    "sg:city":"New Castle",
    "sg:classifiers":[
        {
            "category":"Building & Trades",
            "subcategory":"Plumbing",
            "type":"Services"
        }
    ],
    "sg:phone":"+1 302 328 0243",
    "sg:postcode":"19720",
    "sg:province":"DE",
    "sg:tags":[
        "contractor"
    ],
    "wof:name":"Sheehans Consolidated Services",
    "wof:placetype":"venue"
},
  "geometry": {"coordinates":[-75.576854,39.675789],"type":"Point"}
}