{
  "type": "Feature",
  "properties": {
    "iso:country":"US",
    "sg:address":"1812 Marsh Rd",
    "sg:city":"Wilmington",
    "sg:classifiers":[
        {
            "category":"Banks & Credit Unions",
            "subcategory":"Investment Brokerage",
            "type":"Services"
        },
        {
            "category":"Banks & Credit Unions",
            "subcategory":"Bank",
            "type":"Services"
        }
    ],
    "sg:phone":"+1 302 651 1802",
    "sg:postcode":"19810",
    "sg:province":"DE",
    "sg:tags":[
        "commercial",
        "security",
        "trust",
        "saving"
    ],
    "sg:website":"http://www.wilmingtontrust.com",
    "wof:name":"Wilmington Trust",
    "wof:placetype":"venue"
},
  "geometry": {"coordinates":[-75.503899,39.803501],"type":"Point"}
}