{
  "type": "Feature",
  "properties": {
    "addr:full":"1643 E Ayre St Wilmington DE 19804",
    "addr:housenumber":"1643",
    "addr:postcode":"19804",
    "addr:street":"E Ayre St",
    "iso:country":"US",
    "sg:address":"1643 E Ayre St",
    "sg:city":"Wilmington",
    "sg:classifiers":[
        {
            "category":"Wholesale",
            "subcategory":"Hardware",
            "type":"Manufacturing & Wholesale Goods"
        }
    ],
    "sg:phone":"+1 302 995 0849",
    "sg:postcode":"19804",
    "sg:province":"DE",
    "wof:name":"Anchor Bolts Inc",
    "wof:placetype":"venue"
},
  "geometry": {"coordinates":[-75.602159,39.713642],"type":"Point"}
}