{
  "type": "Feature",
  "properties": {
    "iso:country":"US",
    "sg:address":"11209 Raven Ct",
    "sg:city":"Lincoln",
    "sg:classifiers":[
        {
            "category":"Building & Trades",
            "subcategory":"Electrical",
            "type":"Services"
        }
    ],
    "sg:phone":"+1 302 684 4041",
    "sg:postcode":"19960",
    "sg:province":"DE",
    "sg:tags":[
        "electrical",
        "contractor"
    ],
    "wof:name":"Jonathan Jones Electric",
    "wof:placetype":"venue"
},
  "geometry": {"coordinates":[-75.363861,38.83506],"type":"Point"}
}