{
  "type": "Feature",
  "properties": {
    "iso:country":"US",
    "sg:address":"50 S Meadowood Dr",
    "sg:city":"Newark",
    "sg:classifiers":[
        {
            "category":"Social Services",
            "subcategory":"Child Care",
            "type":"Services"
        },
        {
            "category":"Education",
            "subcategory":"Preschool",
            "type":"Public Place"
        }
    ],
    "sg:phone":"+1 302 453 8090",
    "sg:postcode":"19711",
    "sg:province":"DE",
    "sg:tags":[
        "kindergarten",
        "nursery",
        "day"
    ],
    "sg:website":"http://www.kindercare.com/our-centers/center-details/301158/?cid=YP_KC301158",
    "wof:name":"Meadowood KinderCare",
    "wof:placetype":"venue"
},
  "geometry": {"coordinates":[-75.68563,39.708018],"type":"Point"}
}