{
  "type": "Feature",
  "properties": {
    "iso:country":"US",
    "sg:address":"126 S Gray Ave",
    "sg:city":"Wilmington",
    "sg:classifiers":[
        {
            "category":"Shopping",
            "type":"Retail Goods"
        }
    ],
    "sg:phone":"+1 302 888 2880",
    "sg:postcode":"19805",
    "sg:province":"DE",
    "sg:tags":[
        "wedding",
        "supply"
    ],
    "wof:name":"Autoexec",
    "wof:placetype":"venue"
},
  "geometry": {"coordinates":[-75.585532,39.748191],"type":"Point"}
}