{
  "type": "Feature",
  "properties": {
    "iso:country":"US",
    "sg:address":"4 N Penbrook Dr",
    "sg:city":"Middletown",
    "sg:classifiers":[
        {
            "category":"Professional",
            "type":"Services"
        }
    ],
    "sg:phone":"+1 302 376 1178",
    "sg:postcode":"19709",
    "sg:province":"DE",
    "wof:name":"William Holley",
    "wof:placetype":"venue"
},
  "geometry": {"coordinates":[-75.6914,39.469769],"type":"Point"}
}