{
  "type": "Feature",
  "properties": {
    "iso:country":"US",
    "sg:address":"3542 Foxcroft Dr",
    "sg:city":"Wilmington",
    "sg:classifiers":[
        {
            "category":"Bars & Pubs",
            "type":"Food & Drink"
        }
    ],
    "sg:phone":"+1 302 455 9655",
    "sg:postcode":"19808",
    "sg:province":"DE",
    "sg:tags":[
        "personal",
        "drinking",
        "eating"
    ],
    "wof:name":"Duffers Den Bar & Grill",
    "wof:placetype":"venue"
},
  "geometry": {"coordinates":[-75.696414,39.735437],"type":"Point"}
}