{
  "type": "Feature",
  "properties": {
    "iso:country":"US",
    "sg:address":"28 Old Rudnick Ln",
    "sg:city":"Dover",
    "sg:classifiers":[
        {
            "category":"Professional",
            "subcategory":"Lawyer & Legal Services",
            "type":"Services"
        }
    ],
    "sg:phone":"+1 302 736 3466",
    "sg:postcode":"19901",
    "sg:province":"DE",
    "sg:tags":[
        "company",
        "incorporating"
    ],
    "wof:name":"Del Corp America",
    "wof:placetype":"venue"
},
  "geometry": {"coordinates":[-75.52218499999999,39.13481],"type":"Point"}
}