{
  "type": "Feature",
  "properties": {
    "iso:country":"US",
    "sg:address":"2207 Baynard Blvd",
    "sg:city":"Wilmington",
    "sg:classifiers":[
        {
            "category":"Building & Trades",
            "subcategory":"Plumbing",
            "type":"Services"
        }
    ],
    "sg:phone":"+1 302 652 4923",
    "sg:postcode":"19802",
    "sg:province":"DE",
    "sg:tags":[
        "contractor"
    ],
    "wof:name":"John E Bullock Jr",
    "wof:placetype":"venue"
},
  "geometry": {"coordinates":[-75.543964,39.758715],"type":"Point"}
}