{
  "type": "Feature",
  "properties": {
    "iso:country":"US",
    "sg:address":"1250 Norman Eskridge Hwy",
    "sg:city":"Seaford",
    "sg:classifiers":[
        {
            "category":"Ice Cream",
            "type":"Food & Drink"
        }
    ],
    "sg:menulink":"http://www.allmenus.com/de/seaford/234503-ritas-ice-custard-happiness/menu/",
    "sg:phone":"+1 302 628 4294",
    "sg:postcode":"19973",
    "sg:province":"DE",
    "sg:tags":[
        "american"
    ],
    "wof:name":"Rita's Ice Custard Happiness",
    "wof:placetype":"venue"
},
  "geometry": {"coordinates":[-75.595558,38.652741],"type":"Point"}
}