{
  "type": "Feature",
  "properties": {
    "addr:full":"31 Fairway Rd Newark DE 19711",
    "addr:housenumber":"31",
    "addr:postcode":"19711",
    "addr:street":"Fairway Rd",
    "iso:country":"US",
    "sg:address":"31 Fairway Rd",
    "sg:city":"Newark",
    "sg:classifiers":[
        {
            "category":"Professional",
            "type":"Services"
        }
    ],
    "sg:phone":"+1 302 369 4124",
    "sg:postcode":"19711",
    "sg:province":"DE",
    "wof:name":"J Cannon",
    "wof:placetype":"venue"
},
  "geometry": {"coordinates":[-75.715181,39.694366],"type":"Point"}
}