{
  "type": "Feature",
  "properties": {
    "iso:country":"US",
    "sg:address":"104 Quigley Blvd",
    "sg:city":"New Castle",
    "sg:classifiers":[
        {
            "category":"Professional",
            "subcategory":"Business Services",
            "type":"Services"
        }
    ],
    "sg:phone":"+1 302 326 3950",
    "sg:postcode":"19720",
    "sg:province":"DE",
    "sg:tags":[
        "water",
        "treatment"
    ],
    "wof:name":"Delaware Filter Corp",
    "wof:placetype":"venue"
},
  "geometry": {"coordinates":[-75.60352899999999,39.661449],"type":"Point"}
}