{
  "type": "Feature",
  "properties": {
    "iso:country":"US",
    "sg:address":"15 Omega Dr",
    "sg:city":"Newark",
    "sg:classifiers":[
        {
            "category":"Health Services",
            "subcategory":"Doctor",
            "type":"Services"
        }
    ],
    "sg:phone":"+1 302 888 1980",
    "sg:postcode":"19713",
    "sg:province":"DE",
    "sg:tags":[
        "physician",
        "surgeon"
    ],
    "wof:name":"De Ear Nose & Throat Head",
    "wof:placetype":"venue"
},
  "geometry": {"coordinates":[-75.67555400000001,39.690852],"type":"Point"}
}