{
  "type": "Feature",
  "properties": {
    "iso:country":"US",
    "sg:address":"3408 Old Capitol Trl",
    "sg:city":"Wilmington",
    "sg:classifiers":[
        {
            "category":"Retail",
            "subcategory":"Auto Repair",
            "type":"Services"
        }
    ],
    "sg:phone":"+1 302 998 3556",
    "sg:postcode":"19808",
    "sg:province":"DE",
    "sg:tags":[
        "repairing",
        "automobile"
    ],
    "wof:name":"Shelway Auto Svc",
    "wof:placetype":"venue"
},
  "geometry": {"coordinates":[-75.630117,39.731025],"type":"Point"}
}