{
  "type": "Feature",
  "properties": {
    "addr:full":"1423 S Dupont Hwy Bear DE 19720",
    "addr:housenumber":"1423",
    "addr:postcode":"19720",
    "addr:street":"S Dupont Hwy",
    "iso:country":"US",
    "sg:address":"1423 S Dupont Hwy",
    "sg:city":"Bear",
    "sg:classifiers":[
        {
            "category":"Building & Trades",
            "subcategory":"Construction",
            "type":"Services"
        }
    ],
    "sg:phone":"+1 302 834 5044",
    "sg:postcode":"19720",
    "sg:province":"DE",
    "sg:tags":[
        "general",
        "contractor"
    ],
    "wof:name":"Daisy Construction Co",
    "wof:placetype":"venue"
},
  "geometry": {"coordinates":[-75.655512,39.571062],"type":"Point"}
}