{
  "type": "Feature",
  "properties": {
    "iso:country":"US",
    "sg:address":"232 N Governor Blvd",
    "sg:city":"Dover",
    "sg:classifiers":[
        {
            "category":"Social Services",
            "subcategory":"Child Care",
            "type":"Services"
        }
    ],
    "sg:phone":"+1 302 736 6251",
    "sg:postcode":"19901",
    "sg:province":"DE",
    "sg:tags":[
        "day"
    ],
    "wof:name":"Gibbs Daycare",
    "wof:placetype":"venue"
},
  "geometry": {"coordinates":[-75.50693099999999,39.141351],"type":"Point"}
}