{
  "type": "Feature",
  "properties": {
    "iso:country":"US",
    "sg:address":"2318 N Jefferson St",
    "sg:city":"Wilmington",
    "sg:classifiers":[
        {
            "category":"Personal",
            "subcategory":"Barber",
            "type":"Services"
        }
    ],
    "sg:phone":"+1 302 654 9962",
    "sg:postcode":"19802",
    "sg:province":"DE",
    "sg:tags":[
        "shop"
    ],
    "wof:name":"Perks Hair Cutting Unlimited",
    "wof:placetype":"venue"
},
  "geometry": {"coordinates":[-75.54060800000001,39.757154],"type":"Point"}
}