{
  "type": "Feature",
  "properties": {
    "iso:country":"US",
    "sg:address":"4 Pollari Cir",
    "sg:city":"Newark",
    "sg:classifiers":[
        {
            "category":"Professional",
            "type":"Services"
        }
    ],
    "sg:phone":"+1 302 453 0496",
    "sg:postcode":"19713",
    "sg:province":"DE",
    "wof:name":"K&S Sandman Services",
    "wof:placetype":"venue"
},
  "geometry": {"coordinates":[-75.768869,39.631913],"type":"Point"}
}