{
  "type": "Feature",
  "properties": {
    "iso:country":"US",
    "sg:address":"2207 Concord Pike",
    "sg:city":"Wilmington",
    "sg:classifiers":[
        {
            "category":"Insurance",
            "subcategory":"Insurance Agent",
            "type":"Services"
        }
    ],
    "sg:phone":"+1 302 477 9830",
    "sg:postcode":"19803",
    "sg:province":"DE",
    "wof:name":"Anthony P Sagredo Insurance",
    "wof:placetype":"venue"
},
  "geometry": {"coordinates":[-75.545925,39.786699],"type":"Point"}
}