{
  "type": "Feature",
  "properties": {
    "addr:full":"4569 New Linden Hill Rd Wilmington DE 19808",
    "addr:housenumber":"4569",
    "addr:postcode":"19808",
    "addr:street":"New Linden Hill Rd",
    "iso:country":"US",
    "sg:address":"4569 New Linden Hill Rd",
    "sg:city":"Wilmington",
    "sg:classifiers":[
        {
            "category":"Restaurant",
            "type":"Food & Drink"
        }
    ],
    "sg:phone":"+1 302 731 8200",
    "sg:postcode":"19808",
    "sg:province":"DE",
    "sg:tags":[
        "eating"
    ],
    "wof:name":"Pietros Pizza & Sub Shop",
    "wof:placetype":"venue"
},
  "geometry": {"coordinates":[-75.689972,39.734663],"type":"Point"}
}