{
  "type": "Feature",
  "properties": {
    "iso:country":"US",
    "sg:address":"16 Cherry Rd",
    "sg:city":"New Castle",
    "sg:classifiers":[
        {
            "category":"Building & Trades",
            "subcategory":"Electrical",
            "type":"Services"
        }
    ],
    "sg:phone":"+1 302 328 6593",
    "sg:postcode":"19720",
    "sg:province":"DE",
    "sg:tags":[
        "electrical",
        "contractor"
    ],
    "wof:name":"Don Stillwater & Son",
    "wof:placetype":"venue"
},
  "geometry": {"coordinates":[-75.631141,39.674019],"type":"Point"}
}