{
  "type": "Feature",
  "properties": {
    "iso:country":"US",
    "sg:address":"7244 S Dupont Hwy",
    "sg:city":"Felton",
    "sg:classifiers":[
        {
            "category":"Building & Trades",
            "subcategory":"Plumbing",
            "type":"Services"
        }
    ],
    "sg:phone":"+1 302 697 2100",
    "sg:postcode":"19943",
    "sg:province":"DE",
    "wof:name":"Rays and Sons",
    "wof:placetype":"venue"
},
  "geometry": {"coordinates":[-75.555801,39.057899],"type":"Point"}
}