{
  "type": "Feature",
  "properties": {
    "iso:country":"US",
    "sg:address":"530 S Bay Rd",
    "sg:city":"Dover",
    "sg:classifiers":[
        {
            "category":"Restaurant",
            "type":"Food & Drink"
        }
    ],
    "sg:phone":"+1 302 674 8410",
    "sg:postcode":"19901",
    "sg:province":"DE",
    "sg:tags":[
        "seafood",
        "asian",
        "pan",
        "chinese"
    ],
    "wof:name":"Orient Express",
    "wof:placetype":"venue"
},
  "geometry": {"coordinates":[-75.509579,39.156697],"type":"Point"}
}