{
  "type": "Feature",
  "properties": {
    "iso:country":"US",
    "sg:address":"1326 S Governors Ave Ste B",
    "sg:city":"Dover",
    "sg:classifiers":[
        {
            "category":"Health Services",
            "subcategory":"Doctor",
            "type":"Services"
        }
    ],
    "sg:phone":"+1 302 678 3338",
    "sg:postcode":"19904",
    "sg:province":"DE",
    "sg:tags":[
        "podiatrist"
    ],
    "wof:name":"Central Delaware Family Footcare Associates PA",
    "wof:placetype":"venue"
},
  "geometry": {"coordinates":[-75.52950300000001,39.135201],"type":"Point"}
}