{
  "type": "Feature",
  "properties": {
    "iso:country":"US",
    "sg:address":"3629 Silverside Rd",
    "sg:city":"Wilmington",
    "sg:classifiers":[
        {
            "category":"Personal",
            "subcategory":"Beauty Salon",
            "type":"Services"
        },
        {
            "category":"Personal",
            "subcategory":"Nail Salon",
            "type":"Services"
        }
    ],
    "sg:phone":"+1 302 475 7530",
    "sg:postcode":"19810",
    "sg:province":"DE",
    "sg:tags":[
        "hair"
    ],
    "sg:website":"www.georgemarcussalon.com",
    "wof:name":"George Marcus Salon",
    "wof:placetype":"venue"
},
  "geometry": {"coordinates":[-75.547096,39.8092],"type":"Point"}
}