{
  "type": "Feature",
  "properties": {
    "iso:country":"US",
    "sg:address":"2320 S Dupont Hwy",
    "sg:city":"Dover",
    "sg:classifiers":[
        {
            "category":"Farming",
            "subcategory":"Livestock Farm",
            "type":"Manufacturing & Wholesale Goods"
        }
    ],
    "sg:phone":"+1 302 698 4561",
    "sg:postcode":"19901",
    "sg:province":"DE",
    "sg:tags":[
        "poultry",
        "health",
        "animal"
    ],
    "wof:name":"Poultry & Animal Health",
    "wof:placetype":"venue"
},
  "geometry": {"coordinates":[-75.53657200000001,39.11521],"type":"Point"}
}