{
  "type": "Feature",
  "properties": {
    "iso:country":"US",
    "sg:address":"807 Pulaski Hwy",
    "sg:city":"Bear",
    "sg:classifiers":[
        {
            "category":"Retail",
            "subcategory":"Auto Repair",
            "type":"Services"
        }
    ],
    "sg:phone":"+1 302 328 1550",
    "sg:postcode":"19701",
    "sg:province":"DE",
    "sg:tags":[
        "repairing",
        "automobile",
        "transmission"
    ],
    "wof:name":"Pro Trans Inc",
    "wof:placetype":"venue"
},
  "geometry": {"coordinates":[-75.646513,39.640813],"type":"Point"}
}