{
  "type": "Feature",
  "properties": {
    "iso:country":"US",
    "sg:address":"909 Clifford Brown Walk",
    "sg:city":"Wilmington",
    "sg:classifiers":[
        {
            "category":"Retail",
            "subcategory":"Funeral Services",
            "type":"Services"
        }
    ],
    "sg:phone":"+1 302 658 1555",
    "sg:postcode":"19801",
    "sg:province":"DE",
    "wof:name":"Edward R Bell",
    "wof:placetype":"venue"
},
  "geometry": {"coordinates":[-75.543958,39.743878],"type":"Point"}
}