{
  "type": "Feature",
  "properties": {
    "addr:full":"97 Jackson Ave New Castle DE 19720",
    "addr:housenumber":"97",
    "addr:postcode":"19720",
    "addr:street":"Jackson Ave",
    "iso:country":"US",
    "sg:address":"97 Jackson Ave",
    "sg:city":"New Castle",
    "sg:classifiers":[
        {
            "category":"Shopping",
            "subcategory":"Bicycles & Sporting Goods",
            "type":"Retail Goods"
        }
    ],
    "sg:phone":"+1 302 328 9747",
    "sg:postcode":"19720",
    "sg:province":"DE",
    "sg:tags":[
        "gun",
        "gunsmith"
    ],
    "wof:name":"Miller's Gun Ctr Inc",
    "wof:placetype":"venue"
},
  "geometry": {"coordinates":[-75.58793900000001,39.68489],"type":"Point"}
}