{
  "type": "Feature",
  "properties": {
    "iso:country":"US",
    "sg:address":"36474 Seaside Outlet Dr",
    "sg:city":"Rehoboth Beach",
    "sg:classifiers":[
        {
            "category":"Shopping",
            "subcategory":"Shoes",
            "type":"Retail Goods"
        }
    ],
    "sg:phone":"+1 302 226 0111",
    "sg:postcode":"19971",
    "sg:province":"DE",
    "wof:name":"S A S",
    "wof:placetype":"venue"
},
  "geometry": {"coordinates":[-75.113337,38.718754],"type":"Point"}
}