{
  "type": "Feature",
  "properties": {
    "addr:full":"200 Continental Dr Newark DE 19713",
    "addr:housenumber":"200",
    "addr:postcode":"19713",
    "addr:street":"Continental Dr",
    "iso:country":"US",
    "sg:address":"200 Continental Dr",
    "sg:city":"Newark",
    "sg:classifiers":[
        {
            "category":"Organizations",
            "subcategory":"Professional Association",
            "type":"Services"
        },
        {
            "category":"Social Services",
            "type":"Services"
        }
    ],
    "sg:phone":"+1 302 283 1466",
    "sg:postcode":"19713",
    "sg:province":"DE",
    "sg:tags":[
        "welfare"
    ],
    "wof:name":"Delaware State Dental Society",
    "wof:placetype":"venue"
},
  "geometry": {"coordinates":[-75.660782,39.685627],"type":"Point"}
}