{
  "type": "Feature",
  "properties": {
    "iso:country":"US",
    "sg:address":"611 Parkridge Dr",
    "sg:city":"Hockessin",
    "sg:classifiers":[
        {
            "category":"Building & Trades",
            "subcategory":"Construction",
            "type":"Services"
        }
    ],
    "sg:phone":"+1 302 234 6572",
    "sg:postcode":"19707",
    "sg:province":"DE",
    "sg:tags":[
        "house",
        "contractor"
    ],
    "wof:name":"Pedano & Sons LLC",
    "wof:placetype":"venue"
},
  "geometry": {"coordinates":[-75.69923199999999,39.797836],"type":"Point"}
}