{
  "type": "Feature",
  "properties": {
    "iso:country":"US",
    "sg:address":"608 E Basin Rd",
    "sg:city":"New Castle",
    "sg:classifiers":[
        {
            "category":"Shopping",
            "subcategory":"Computers & Home Electronics",
            "type":"Retail Goods"
        }
    ],
    "sg:phone":"+1 302 328 0221",
    "sg:postcode":"19720",
    "sg:province":"DE",
    "sg:tags":[
        "television",
        "stereo",
        "video",
        "cassette",
        "radio",
        "recorder"
    ],
    "wof:name":"Romano Electronics Inc",
    "wof:placetype":"venue"
},
  "geometry": {"coordinates":[-75.583668,39.67109],"type":"Point"}
}