{
  "type": "Feature",
  "properties": {
    "iso:country":"US",
    "sg:address":"18717 Seashore Hwy",
    "sg:city":"Georgetown",
    "sg:classifiers":[
        {
            "category":"Professional",
            "type":"Services"
        }
    ],
    "sg:phone":"+1 302 855 9115",
    "sg:postcode":"19947",
    "sg:province":"DE",
    "wof:name":"Kc Layout Services Inc",
    "wof:placetype":"venue"
},
  "geometry": {"coordinates":[-75.41112800000001,38.697735],"type":"Point"}
}