{
  "type": "Feature",
  "properties": {
    "addr:full":"17 W Main St Newark DE 19716",
    "addr:housenumber":"17",
    "addr:postcode":"19716",
    "addr:street":"W Main St",
    "iso:country":"US",
    "sg:address":"17 W Main St",
    "sg:city":"Newark",
    "sg:classifiers":[
        {
            "category":"Fast Food",
            "type":"Food & Drink"
        },
        {
            "category":"Restaurant",
            "type":"Food & Drink"
        }
    ],
    "sg:phone":"+1 302 831 6761",
    "sg:postcode":"19716",
    "sg:province":"DE",
    "sg:tags":[
        "chicken"
    ],
    "sg:website":"http://www.chick-fil-a.com",
    "wof:name":"Chick-Fil-A",
    "wof:placetype":"venue"
},
  "geometry": {"coordinates":[-75.754254,39.682994],"type":"Point"}
}