{
  "type": "Feature",
  "properties": {
    "addr:full":"1200 Peoples Plz Newark DE 19702",
    "addr:housenumber":"1200",
    "addr:postcode":"19702",
    "addr:street":"Peoples Plz",
    "iso:country":"US",
    "sg:address":"1200 Peoples Plz",
    "sg:city":"Newark",
    "sg:classifiers":[
        {
            "category":"Professional",
            "type":"Services"
        }
    ],
    "sg:phone":"+1 302 838 8775",
    "sg:postcode":"19702",
    "sg:province":"DE",
    "wof:name":"Craig Azevedo",
    "wof:placetype":"venue"
},
  "geometry": {"coordinates":[-75.746887,39.602882],"type":"Point"}
}