{
  "type": "Feature",
  "properties": {
    "addr:full":"112 N Dupont Hwy New Castle DE 19720",
    "addr:housenumber":"112",
    "addr:postcode":"19720",
    "addr:street":"N Dupont Hwy",
    "iso:country":"US",
    "sg:address":"112 N Dupont Hwy",
    "sg:city":"New Castle",
    "sg:classifiers":[
        {
            "category":"Restaurant",
            "type":"Food & Drink"
        }
    ],
    "sg:menulink":"http://www.allmenus.com/de/new-castle/189531-kfc---kentucky-fried-chicken/menu/",
    "sg:phone":"+1 302 322 8075",
    "sg:postcode":"19720",
    "sg:province":"DE",
    "sg:tags":[
        "american",
        "chicken"
    ],
    "wof:name":"KFC - Kentucky Fried Chicken",
    "wof:placetype":"venue"
},
  "geometry": {"coordinates":[-75.601889,39.667712],"type":"Point"}
}