{
  "type": "Feature",
  "properties": {
    "addr:full":"5504 S Dupont Hwy Dover DE 19901",
    "addr:housenumber":"5504",
    "addr:postcode":"19901",
    "addr:street":"S Dupont Hwy",
    "iso:country":"US",
    "sg:address":"5504 S Dupont Hwy",
    "sg:city":"Dover",
    "sg:classifiers":[
        {
            "category":"Shopping",
            "subcategory":"Music",
            "type":"Retail Goods"
        }
    ],
    "sg:phone":"+1 302 697 7333",
    "sg:postcode":"19901",
    "sg:province":"DE",
    "sg:tags":[
        "video",
        "disc",
        "tape",
        "cassette"
    ],
    "wof:name":"Movie Gallery",
    "wof:placetype":"venue"
},
  "geometry": {"coordinates":[-75.551165,39.084036],"type":"Point"}
}