{
  "type": "Feature",
  "properties": {
    "iso:country":"US",
    "sg:address":"520 Terminal Ave",
    "sg:city":"New Castle",
    "sg:classifiers":[
        {
            "category":"Professional",
            "subcategory":"Detective & Security Services",
            "type":"Services"
        }
    ],
    "sg:phone":"+1 302 655 9399",
    "sg:postcode":"19720",
    "sg:province":"DE",
    "sg:tags":[
        "car"
    ],
    "wof:name":"Master Security",
    "wof:placetype":"venue"
},
  "geometry": {"coordinates":[-75.53556500000001,39.717771],"type":"Point"}
}