{
  "type": "Feature",
  "properties": {
    "addr:full":"250 N Rehoboth Blvd Milford DE 19963",
    "addr:housenumber":"250",
    "addr:postcode":"19963",
    "addr:street":"N Rehoboth Blvd",
    "iso:country":"US",
    "sg:address":"250 N Rehoboth Blvd",
    "sg:city":"Milford",
    "sg:classifiers":[
        {
            "category":"Manufacturing",
            "subcategory":"Chemicals & Compounds",
            "type":"Manufacturing & Wholesale Goods"
        }
    ],
    "sg:phone":"+1 302 422 3570",
    "sg:postcode":"19963",
    "sg:province":"DE",
    "sg:tags":[
        "fertilizer",
        "pesticide",
        "mfg",
        "insecticide"
    ],
    "sg:website":"www.roysterclark.com",
    "wof:name":"Royster-Clark Inc",
    "wof:placetype":"venue"
},
  "geometry": {"coordinates":[-75.424284,38.922929],"type":"Point"}
}