{
  "type": "Feature",
  "properties": {
    "iso:country":"US",
    "sg:address":"3501 Silverside Rd Naamans Bldg, Ste 206",
    "sg:city":"Wilmington",
    "sg:classifiers":[
        {
            "category":"Shopping",
            "subcategory":"Florist",
            "type":"Retail Goods"
        }
    ],
    "sg:phone":"+1 866 337 9947",
    "sg:postcode":"19810",
    "sg:province":"DE",
    "sg:website":"www.amazonflowers.us/",
    "wof:name":"Amazon Flowers",
    "wof:placetype":"venue"
},
  "geometry": {"coordinates":[-75.543356,39.808915],"type":"Point"}
}