{
  "type": "Feature",
  "properties": {
    "iso:country":"US",
    "sg:address":"102 Sussex Ave",
    "sg:city":"Bridgeville",
    "sg:classifiers":[
        {
            "category":"Building & Trades",
            "subcategory":"Plumbing",
            "type":"Services"
        }
    ],
    "sg:phone":"+1 302 337 7082",
    "sg:postcode":"19933",
    "sg:province":"DE",
    "sg:tags":[
        "conditioning",
        "air",
        "system",
        "contractor"
    ],
    "wof:name":"Moyer's Heating & Air",
    "wof:placetype":"venue"
},
  "geometry": {"coordinates":[-75.598056,38.738786],"type":"Point"}
}