{
  "type": "Feature",
  "properties": {
    "addr:full":"2811 Bodine Dr Wilmington DE 19810",
    "addr:housenumber":"2811",
    "addr:postcode":"19810",
    "addr:street":"Bodine Dr",
    "iso:country":"US",
    "sg:address":"2811 Bodine Dr",
    "sg:city":"Wilmington",
    "sg:classifiers":[
        {
            "category":"Personal",
            "subcategory":"Skin Care",
            "type":"Services"
        },
        {
            "category":"Personal",
            "subcategory":"Day Spa",
            "type":"Services"
        }
    ],
    "sg:phone":"+1 302 478 0182",
    "sg:postcode":"19810",
    "sg:province":"DE",
    "wof:name":"Iglay Brigitte",
    "wof:placetype":"venue"
},
  "geometry": {"coordinates":[-75.52990200000001,39.822927],"type":"Point"}
}