{
  "type": "Feature",
  "properties": {
    "iso:country":"US",
    "sg:address":"410 S Bedford St",
    "sg:city":"Georgetown",
    "sg:classifiers":[
        {
            "category":"Health Services",
            "subcategory":"Hospital",
            "type":"Services"
        }
    ],
    "sg:phone":"+1 302 856 2388",
    "sg:postcode":"19947",
    "sg:province":"DE",
    "sg:tags":[
        "specialty"
    ],
    "wof:name":"Children and Fmly First of Del",
    "wof:placetype":"venue"
},
  "geometry": {"coordinates":[-75.379132,38.678453],"type":"Point"}
}