{
  "type": "Feature",
  "properties": {
    "iso:country":"US",
    "sg:address":"122 W Monroe St",
    "sg:city":"Millsboro",
    "sg:classifiers":[
        {
            "category":"Wholesale",
            "subcategory":"Farm Supplies",
            "type":"Manufacturing & Wholesale Goods"
        }
    ],
    "sg:phone":"+1 302 934 7042",
    "sg:postcode":"19966",
    "sg:province":"DE",
    "sg:tags":[
        "grain"
    ],
    "wof:name":"Collins' Grain & Storage",
    "wof:placetype":"venue"
},
  "geometry": {"coordinates":[-75.294431,38.589026],"type":"Point"}
}