{
  "type": "Feature",
  "properties": {
    "addr:full":"827 N Market St Wilmington DE 19801",
    "addr:housenumber":"827",
    "addr:postcode":"19801",
    "addr:street":"N Market St",
    "iso:country":"US",
    "sg:address":"827 N Market St",
    "sg:city":"Wilmington",
    "sg:classifiers":[
        {
            "category":"Shopping",
            "subcategory":"Clothing, Apparel, & Fashions",
            "type":"Retail Goods"
        }
    ],
    "sg:phone":"+1 302 656 1223",
    "sg:postcode":"19801",
    "sg:province":"DE",
    "sg:tags":[
        "item",
        "boutique"
    ],
    "wof:name":"Jay's Family Fashion",
    "wof:placetype":"venue"
},
  "geometry": {"coordinates":[-75.548689,39.74437],"type":"Point"}
}