{
  "type": "Feature",
  "properties": {
    "addr:full":"721 Philadelphia Pike Wilmington DE 19809",
    "addr:housenumber":"721",
    "addr:postcode":"19809",
    "addr:street":"Philadelphia Pike",
    "iso:country":"US",
    "sg:address":"721 Philadelphia Pike",
    "sg:city":"Wilmington",
    "sg:classifiers":[
        {
            "category":"Health Services",
            "subcategory":"Chiropractor",
            "type":"Services"
        }
    ],
    "sg:phone":"+1 302 764 5668",
    "sg:postcode":"19809",
    "sg:province":"DE",
    "wof:name":"Ashe Chiropractic Offices",
    "wof:placetype":"venue"
},
  "geometry": {"coordinates":[-75.501822,39.77006],"type":"Point"}
}