{
  "type": "Feature",
  "properties": {
    "iso:country":"US",
    "sg:address":"3725 Washington Ave",
    "sg:city":"Wilmington",
    "sg:classifiers":[
        {
            "category":"Building & Trades",
            "subcategory":"Construction",
            "type":"Services"
        }
    ],
    "sg:phone":"+1 302 994 1060",
    "sg:postcode":"19808",
    "sg:province":"DE",
    "sg:tags":[
        "truck",
        "rental",
        "contractor"
    ],
    "wof:name":"D E Leager Construction",
    "wof:placetype":"venue"
},
  "geometry": {"coordinates":[-75.635668,39.728274],"type":"Point"}
}