{
  "type": "Feature",
  "properties": {
    "iso:country":"US",
    "sg:address":"349 E Main St",
    "sg:city":"Newark",
    "sg:classifiers":[
        {
            "category":"Autos & Motor Vehicles",
            "subcategory":"Fuel & Gas Station",
            "type":"Retail Goods"
        }
    ],
    "sg:phone":"+1 302 737 1745",
    "sg:postcode":"19711",
    "sg:province":"DE",
    "sg:tags":[
        "station",
        "gasoline"
    ],
    "wof:name":"Hockessin Gulf",
    "wof:placetype":"venue"
},
  "geometry": {"coordinates":[-75.73915599999999,39.68411],"type":"Point"}
}