{
  "type": "Feature",
  "properties": {
    "iso:country":"US",
    "sg:address":"507 Wisseman Ave",
    "sg:city":"Milford",
    "sg:classifiers":[
        {
            "category":"Building & Trades",
            "subcategory":"Construction",
            "type":"Services"
        }
    ],
    "sg:phone":"+1 302 422 9270",
    "sg:postcode":"19963",
    "sg:province":"DE",
    "sg:tags":[
        "water",
        "well",
        "drilling"
    ],
    "wof:name":"Harry Donovan",
    "wof:placetype":"venue"
},
  "geometry": {"coordinates":[-75.455505,38.904559],"type":"Point"}
}