{
  "type": "Feature",
  "properties": {
    "iso:country":"US",
    "sg:address":"12605 S Dupont Hwy",
    "sg:city":"Felton",
    "sg:classifiers":[
        {
            "category":"Home & Garden",
            "subcategory":"Building Materials",
            "type":"Retail Goods"
        }
    ],
    "sg:phone":"+1 302 284 0444",
    "sg:postcode":"19943",
    "sg:province":"DE",
    "sg:tags":[
        "door"
    ],
    "wof:name":"Britt's Overhead Doors",
    "wof:placetype":"venue"
},
  "geometry": {"coordinates":[-75.567516,38.987088],"type":"Point"}
}