{
  "type": "Feature",
  "properties": {
    "iso:country":"US",
    "sg:address":"406 S Bedford St",
    "sg:city":"Georgetown",
    "sg:classifiers":[
        {
            "category":"Social Services",
            "type":"Services"
        }
    ],
    "sg:phone":"+1 302 856 9578",
    "sg:postcode":"19947",
    "sg:province":"DE",
    "sg:tags":[
        "organization",
        "welfare"
    ],
    "wof:name":"Catholic Charities",
    "wof:placetype":"venue"
},
  "geometry": {"coordinates":[-75.37921,38.678901],"type":"Point"}
}