{
  "type": "Feature",
  "properties": {
    "addr:full":"623 Parkridge Dr Hockessin DE 19707",
    "addr:housenumber":"623",
    "addr:postcode":"19707",
    "addr:street":"Parkridge Dr",
    "iso:country":"US",
    "sg:address":"623 Parkridge Dr",
    "sg:city":"Hockessin",
    "sg:classifiers":[
        {
            "category":"Health Services",
            "subcategory":"Doctor",
            "type":"Services"
        }
    ],
    "sg:phone":"+1 302 234 1758",
    "sg:postcode":"19707",
    "sg:province":"DE",
    "sg:tags":[
        "medical"
    ],
    "wof:name":"Mark T Lounsbury",
    "wof:placetype":"venue"
},
  "geometry": {"coordinates":[-75.69864699999999,39.797704],"type":"Point"}
}