{
  "type": "Feature",
  "properties": {
    "addr:full":"110 W 6th St Wilmington DE 19801",
    "addr:housenumber":"110",
    "addr:postcode":"19801",
    "addr:street":"W 6Th St",
    "iso:country":"US",
    "sg:address":"110 W 6th St",
    "sg:city":"Wilmington",
    "sg:classifiers":[
        {
            "category":"Professional",
            "subcategory":"Computer Services",
            "type":"Services"
        }
    ],
    "sg:phone":"+1 425 673 5484",
    "sg:postcode":"19801",
    "sg:province":"DE",
    "wof:name":"Donorware LLC",
    "wof:placetype":"venue"
},
  "geometry": {"coordinates":[-75.551557,39.742326],"type":"Point"}
}