{
  "type": "Feature",
  "properties": {
    "addr:full":"608 N Bedford St Georgetown DE 19947",
    "addr:housenumber":"608",
    "addr:postcode":"19947",
    "addr:street":"N Bedford St",
    "iso:country":"US",
    "sg:address":"608 N Bedford St",
    "sg:city":"Georgetown",
    "sg:classifiers":[
        {
            "category":"Building & Trades",
            "subcategory":"Construction",
            "type":"Services"
        }
    ],
    "sg:phone":"+1 302 853 0019",
    "sg:postcode":"19947",
    "sg:province":"DE",
    "sg:tags":[
        "contractor"
    ],
    "wof:name":"Tj Depalma Contracting",
    "wof:placetype":"venue"
},
  "geometry": {"coordinates":[-75.391581,38.695144],"type":"Point"}
}