{
  "type": "Feature",
  "properties": {
    "iso:country":"US",
    "sg:address":"21 Mercer Dr",
    "sg:city":"Newark",
    "sg:classifiers":[
        {
            "category":"Manufacturing",
            "subcategory":"Signs",
            "type":"Manufacturing & Wholesale Goods"
        }
    ],
    "sg:phone":"+1 302 456 1266",
    "sg:postcode":"19713",
    "sg:province":"DE",
    "sg:tags":[
        "specialty",
        "mfg"
    ],
    "wof:name":"Signs & Wonders Corp",
    "wof:placetype":"venue"
},
  "geometry": {"coordinates":[-75.728416,39.66775],"type":"Point"}
}