{
  "type": "Feature",
  "properties": {
    "iso:country":"US",
    "sg:address":"1505 E Newport Pike",
    "sg:city":"Wilmington",
    "sg:classifiers":[
        {
            "category":"Personal",
            "subcategory":"Barber",
            "type":"Services"
        }
    ],
    "sg:phone":"+1 302 995 1251",
    "sg:postcode":"19804",
    "sg:province":"DE",
    "sg:tags":[
        "shop"
    ],
    "wof:name":"Prado Barber Shop",
    "wof:placetype":"venue"
},
  "geometry": {"coordinates":[-75.60200500000001,39.717398],"type":"Point"}
}