{
  "type": "Feature",
  "properties": {
    "addr:full":"132 Broadkill Rd Milton DE 19968",
    "addr:housenumber":"132",
    "addr:postcode":"19968",
    "addr:street":"Broadkill Rd",
    "iso:country":"US",
    "sg:address":"132 Broadkill Rd",
    "sg:city":"Milton",
    "sg:classifiers":[
        {
            "category":"Restaurant",
            "type":"Food & Drink"
        }
    ],
    "sg:menulink":"http://www.allmenus.com/de/milton/67324-dominos-pizza/menu/",
    "sg:phone":"+1 302 684 5000",
    "sg:postcode":"19968",
    "sg:province":"DE",
    "sg:tags":[
        "american",
        "wing",
        "pizza"
    ],
    "wof:name":"Domino's Pizza",
    "wof:placetype":"venue"
},
  "geometry": {"coordinates":[-75.31366800000001,38.788121],"type":"Point"}
}