{
  "type": "Feature",
  "properties": {
    "iso:country":"US",
    "sg:address":"3155 Hourglass Rd",
    "sg:city":"Hartly",
    "sg:classifiers":[
        {
            "category":"Building & Trades",
            "subcategory":"Construction",
            "type":"Services"
        }
    ],
    "sg:phone":"+1 302 492 3307",
    "sg:postcode":"19953",
    "sg:province":"DE",
    "sg:tags":[
        "system",
        "specialty",
        "heating",
        "contractor",
        "air conditioning"
    ],
    "wof:name":"Glenn Martin",
    "wof:placetype":"venue"
},
  "geometry": {"coordinates":[-75.684174,39.12895],"type":"Point"}
}