{
  "type": "Feature",
  "properties": {
    "iso:country":"US",
    "sg:address":"587 Union Church Rd",
    "sg:city":"Townsend",
    "sg:classifiers":[
        {
            "category":"Building & Trades",
            "subcategory":"Construction",
            "type":"Services"
        }
    ],
    "sg:phone":"+1 302 378 7430",
    "sg:postcode":"19734",
    "sg:province":"DE",
    "sg:tags":[
        "system",
        "specialty",
        "heating",
        "contractor",
        "air conditioning"
    ],
    "wof:name":"Mike's Plumbing & Heating",
    "wof:placetype":"venue"
},
  "geometry": {"coordinates":[-75.650402,39.387123],"type":"Point"}
}