{
  "type": "Feature",
  "properties": {
    "addr:full":"181 Lake Arrowhead Cir Bear DE 19701",
    "addr:housenumber":"181",
    "addr:postcode":"19701",
    "addr:street":"Lake Arrowhead Cir",
    "iso:country":"US",
    "sg:address":"181 Lake Arrowhead Cir",
    "sg:city":"Bear",
    "sg:classifiers":[
        {
            "category":"Professional",
            "type":"Services"
        }
    ],
    "sg:phone":"+1 302 836 0182",
    "sg:postcode":"19701",
    "sg:province":"DE",
    "wof:name":"Urban Bankers of Delaware",
    "wof:placetype":"venue"
},
  "geometry": {"coordinates":[-75.70281799999999,39.617259],"type":"Point"}
}