{
  "type": "Feature",
  "properties": {
    "iso:country":"US",
    "sg:address":"4707 Kirkwood Hwy",
    "sg:city":"Wilmington",
    "sg:classifiers":[
        {
            "category":"Shopping",
            "subcategory":"Musical Instruments",
            "type":"Retail Goods"
        }
    ],
    "sg:phone":"+1 302 633 0600",
    "sg:postcode":"19808",
    "sg:province":"DE",
    "wof:name":"Music & Arts Center Inc",
    "wof:placetype":"venue"
},
  "geometry": {"coordinates":[-75.66289500000001,39.7212],"type":"Point"}
}