{
  "type": "Feature",
  "properties": {
    "addr:full":"103 3rd St Lincoln DE 19960",
    "addr:housenumber":"103",
    "addr:postcode":"19960",
    "addr:street":"3Rd St",
    "iso:country":"US",
    "sg:address":"103 3rd St",
    "sg:city":"Lincoln",
    "sg:classifiers":[
        {
            "category":"Education",
            "subcategory":"School",
            "type":"Public Place"
        }
    ],
    "sg:phone":"+1 302 422 1650",
    "sg:postcode":"19960",
    "sg:province":"DE",
    "wof:name":"Evelyn I Morris Early Childhd",
    "wof:placetype":"venue"
},
  "geometry": {"coordinates":[-75.418932,38.87089],"type":"Point"}
}