{
  "type": "Feature",
  "properties": {
    "iso:country":"US",
    "sg:address":"2710 Centerville Rd Suite 210",
    "sg:city":"Wilmington",
    "sg:classifiers":[
        {
            "category":"Professional",
            "subcategory":"Lawyer & Legal Services",
            "type":"Services"
        }
    ],
    "sg:phone":"+1 302 655 9200",
    "sg:postcode":"19808",
    "sg:province":"DE",
    "sg:tags":[
        "attorney",
        "injury",
        "natural",
        "business",
        "personal",
        "tax",
        "environment",
        "governmental",
        "planning",
        "real estate",
        "resource",
        "law",
        "administrative",
        "bankruptcy"
    ],
    "wof:name":"Taylor & Mc New",
    "wof:placetype":"venue"
},
  "geometry": {"coordinates":[-75.624576,39.753236],"type":"Point"}
}