{
  "type": "Feature",
  "properties": {
    "iso:country":"US",
    "sg:address":"1225 N King St",
    "sg:city":"Wilmington",
    "sg:classifiers":[
        {
            "category":"Social Services",
            "subcategory":"Child Care",
            "type":"Services"
        }
    ],
    "sg:phone":"+1 302 661 0690",
    "sg:postcode":"19801",
    "sg:province":"DE",
    "sg:tags":[
        "day"
    ],
    "wof:name":"Folks Little II",
    "wof:placetype":"venue"
},
  "geometry": {"coordinates":[-75.54538700000001,39.747631],"type":"Point"}
}