{
  "type": "Feature",
  "properties": {
    "iso:country":"US",
    "sg:address":"506 Jefferic Blvd",
    "sg:city":"Dover",
    "sg:classifiers":[
        {
            "category":"Wholesale",
            "subcategory":"Painting Supplies",
            "type":"Manufacturing & Wholesale Goods"
        }
    ],
    "sg:phone":"+1 302 730 9130",
    "sg:postcode":"19901",
    "sg:province":"DE",
    "sg:tags":[
        "paint",
        "varnish",
        "related",
        "sup"
    ],
    "wof:name":"Duron Pints Wallcoverings 194",
    "wof:placetype":"venue"
},
  "geometry": {"coordinates":[-75.52617600000001,39.178036],"type":"Point"}
}