{
  "type": "Feature",
  "properties": {
    "addr:full":"2546 S Dupont Blvd Smyrna DE 19977",
    "addr:housenumber":"2546",
    "addr:postcode":"19977",
    "addr:street":"S Dupont Blvd",
    "iso:country":"US",
    "sg:address":"2546 S Dupont Blvd",
    "sg:city":"Smyrna",
    "sg:classifiers":[
        {
            "category":"Autos & Motor Vehicles",
            "subcategory":"Automobile Sales",
            "type":"Retail Goods"
        },
        {
            "category":"Autos & Motor Vehicles",
            "subcategory":"Auto Supplies",
            "type":"Retail Goods"
        }
    ],
    "sg:phone":"+1 302 659 1119",
    "sg:postcode":"19977",
    "sg:province":"DE",
    "sg:tags":[
        "car",
        "dealer"
    ],
    "wof:name":"Philiz Fountainrock Auto Sales",
    "wof:placetype":"venue"
},
  "geometry": {"coordinates":[-75.588319,39.267922],"type":"Point"}
}