{
  "type": "Feature",
  "properties": {
    "iso:country":"US",
    "sg:address":"1 Main Ave",
    "sg:city":"Wilmington",
    "sg:classifiers":[
        {
            "category":"Real Estate",
            "subcategory":"Real Estate Services",
            "type":"Services"
        }
    ],
    "sg:phone":"+1 302 633 4436",
    "sg:postcode":"19804",
    "sg:province":"DE",
    "wof:name":"Stan Flowers",
    "wof:placetype":"venue"
},
  "geometry": {"coordinates":[-75.598153,39.726134],"type":"Point"}
}