{
  "type": "Feature",
  "properties": {
    "iso:country":"US",
    "sg:address":"9410 Canterbury Rd",
    "sg:city":"Felton",
    "sg:classifiers":[
        {
            "category":"Retail",
            "subcategory":"Repair Shop",
            "type":"Services"
        }
    ],
    "sg:phone":"+1 302 284 0190",
    "sg:postcode":"19943",
    "sg:province":"DE",
    "sg:tags":[
        "electronic"
    ],
    "wof:name":"Mission Electronics",
    "wof:placetype":"venue"
},
  "geometry": {"coordinates":[-75.551835,39.037486],"type":"Point"}
}