{
  "type": "Feature",
  "properties": {
    "iso:country":"US",
    "sg:address":"200 Beau Tree Dr",
    "sg:city":"Wilmington",
    "sg:classifiers":[
        {
            "category":"Retail",
            "subcategory":"Repair Shop",
            "type":"Services"
        }
    ],
    "sg:phone":"+1 302 475 4005",
    "sg:postcode":"19810",
    "sg:province":"DE",
    "sg:tags":[
        "lock",
        "key",
        "locksmith"
    ],
    "wof:name":"A-Abacus Locksmith",
    "wof:placetype":"venue"
},
  "geometry": {"coordinates":[-75.516977,39.836152],"type":"Point"}
}