{
  "type": "Feature",
  "properties": {
    "addr:full":"177 Rickey Blvd Bear DE 19701",
    "addr:housenumber":"177",
    "addr:postcode":"19701",
    "addr:street":"Rickey Blvd",
    "iso:country":"US",
    "sg:address":"177 Rickey Blvd",
    "sg:city":"Bear",
    "sg:classifiers":[
        {
            "category":"Manufacturing",
            "subcategory":"Toys & Sporting Goods",
            "type":"Manufacturing & Wholesale Goods"
        }
    ],
    "sg:phone":"+1 302 836 1175",
    "sg:postcode":"19701",
    "sg:province":"DE",
    "sg:tags":[
        "gym",
        "mat",
        "mfg"
    ],
    "wof:name":"Athletic Gym Mats",
    "wof:placetype":"venue"
},
  "geometry": {"coordinates":[-75.710718,39.608284],"type":"Point"}
}