{
  "type": "Feature",
  "properties": {
    "iso:country":"US",
    "sg:address":"2625 Concord Pike",
    "sg:city":"Wilmington",
    "sg:classifiers":[
        {
            "category":"Health Services",
            "subcategory":"Optometrist",
            "type":"Services"
        }
    ],
    "sg:phone":"+1 302 477 9681",
    "sg:postcode":"19803",
    "sg:province":"DE",
    "wof:name":"Simon Eye Assoc",
    "wof:placetype":"venue"
},
  "geometry": {"coordinates":[-75.547056,39.795111],"type":"Point"}
}