{
  "type": "Feature",
  "properties": {
    "addr:full":"8 Dawn Meadow Ln Newark DE 19711",
    "addr:housenumber":"8",
    "addr:postcode":"19711",
    "addr:street":"Dawn Meadow Ln",
    "iso:country":"US",
    "sg:address":"8 Dawn Meadow Ln",
    "sg:city":"Newark",
    "sg:classifiers":[
        {
            "category":"Professional",
            "subcategory":"Accounting & Tax Preparation",
            "type":"Services"
        }
    ],
    "sg:phone":"+1 302 234 7744",
    "sg:postcode":"19711",
    "sg:province":"DE",
    "sg:tags":[
        "public",
        "accountants-certified"
    ],
    "wof:name":"Phillip & Terry Saccomanno",
    "wof:placetype":"venue"
},
  "geometry": {"coordinates":[-75.74544,39.74428],"type":"Point"}
}