{
  "type": "Feature",
  "properties": {
    "addr:full":"430 Christiana Medical Center Newark DE 19702",
    "addr:housenumber":"430",
    "addr:postcode":"19702",
    "iso:country":"US",
    "sg:address":"430 Christiana Medical Center",
    "sg:city":"Newark",
    "sg:classifiers":[
        {
            "category":"Health Services",
            "subcategory":"Doctor",
            "type":"Services"
        }
    ],
    "sg:phone":"+1 302 368 5500",
    "sg:postcode":"19702",
    "sg:province":"DE",
    "sg:tags":[
        "physician",
        "surgeon",
        "medical"
    ],
    "wof:name":"Jerry L Case MD",
    "wof:placetype":"venue"
},
  "geometry": {"coordinates":[-75.658478,39.676878],"type":"Point"}
}