{
  "type": "Feature",
  "properties": {
    "iso:country":"US",
    "sg:address":"200 E Dickerson Ln",
    "sg:city":"Middletown",
    "sg:classifiers":[
        {
            "category":"Building & Trades",
            "subcategory":"Construction",
            "type":"Services"
        }
    ],
    "sg:phone":"+1 302 376 7082",
    "sg:postcode":"19709",
    "sg:province":"DE",
    "sg:tags":[
        "home",
        "builder"
    ],
    "wof:name":"Ryan Homes",
    "wof:placetype":"venue"
},
  "geometry": {"coordinates":[-75.727625,39.514573],"type":"Point"}
}