{
  "type": "Feature",
  "properties": {
    "addr:full":"103 Balmore Ln Wilmington DE 19808",
    "addr:housenumber":"103",
    "addr:postcode":"19808",
    "addr:street":"Balmore Ln",
    "iso:country":"US",
    "sg:address":"103 Balmore Ln",
    "sg:city":"Wilmington",
    "sg:classifiers":[
        {
            "category":"Organizations",
            "subcategory":"Professional Association",
            "type":"Services"
        }
    ],
    "sg:phone":"+1 302 998 4276",
    "sg:postcode":"19808",
    "sg:province":"DE",
    "wof:name":"Marine Corps League",
    "wof:placetype":"venue"
},
  "geometry": {"coordinates":[-75.662543,39.753442],"type":"Point"}
}