{
  "type": "Feature",
  "properties": {
    "iso:country":"US",
    "sg:address":"900 NE Front St",
    "sg:city":"Milford",
    "sg:classifiers":[
        {
            "category":"Building & Trades",
            "subcategory":"Plumbing",
            "type":"Services"
        }
    ],
    "sg:phone":"+1 302 422 5677",
    "sg:postcode":"19963",
    "sg:province":"DE",
    "sg:tags":[
        "sheet",
        "work",
        "metal",
        "contractor"
    ],
    "wof:name":"Airtech Sheet Metal",
    "wof:placetype":"venue"
},
  "geometry": {"coordinates":[-75.415542,38.923008],"type":"Point"}
}