{
  "type": "Feature",
  "properties": {
    "iso:country":"US",
    "sg:address":"2412 W Newport Pike",
    "sg:city":"Wilmington",
    "sg:classifiers":[
        {
            "category":"Autos & Motor Vehicles",
            "subcategory":"Automobile Sales",
            "type":"Retail Goods"
        }
    ],
    "sg:phone":"+1 302 421 9005",
    "sg:postcode":"19804",
    "sg:province":"DE",
    "sg:tags":[
        "used"
    ],
    "wof:name":"Auto Sports",
    "wof:placetype":"venue"
},
  "geometry": {"coordinates":[-75.640683,39.715578],"type":"Point"}
}