{
  "type": "Feature",
  "properties": {
    "iso:country":"US",
    "sg:address":"1872 Pulaski Hwy",
    "sg:city":"Bear",
    "sg:classifiers":[
        {
            "category":"Retail",
            "subcategory":"Auto Repair",
            "type":"Services"
        }
    ],
    "sg:phone":"+1 302 633 6865",
    "sg:postcode":"19701",
    "sg:province":"DE",
    "sg:tags":[
        "body",
        "automobile",
        "painting"
    ],
    "wof:name":"Bayshore Body Shop",
    "wof:placetype":"venue"
},
  "geometry": {"coordinates":[-75.70583999999999,39.61033],"type":"Point"}
}