{
  "type": "Feature",
  "properties": {
    "iso:country":"US",
    "sg:address":"318 Main St",
    "sg:city":"Townsend",
    "sg:classifiers":[
        {
            "category":"Restaurant",
            "type":"Food & Drink"
        }
    ],
    "sg:phone":"+1 302 378 2946",
    "sg:postcode":"19734",
    "sg:province":"DE",
    "sg:tags":[
        "pizza",
        "italian"
    ],
    "wof:name":"La Matesina Pizza Pasta",
    "wof:placetype":"venue"
},
  "geometry": {"coordinates":[-75.692294,39.395128],"type":"Point"}
}