{
  "type": "Feature",
  "properties": {
    "iso:country":"US",
    "sg:address":"33 Duke St Ofc A",
    "sg:city":"Newark",
    "sg:classifiers":[
        {
            "category":"Real Estate",
            "subcategory":"Real Estate Operator",
            "type":"Services"
        }
    ],
    "sg:phone":"+1 302 328 6251",
    "sg:postcode":"19711",
    "sg:province":"DE",
    "sg:tags":[
        "apartment"
    ],
    "wof:name":"Fusco Enterprises",
    "wof:placetype":"venue"
},
  "geometry": {"coordinates":[-75.73848599999999,39.678294],"type":"Point"}
}