{
  "type": "Feature",
  "properties": {
    "iso:country":"US",
    "sg:address":"22556 Bridgeville Hwy",
    "sg:city":"Seaford",
    "sg:classifiers":[
        {
            "category":"Restaurant",
            "type":"Food & Drink"
        }
    ],
    "sg:phone":"+1 302 629 8788",
    "sg:postcode":"19973",
    "sg:province":"DE",
    "wof:name":"Market Street Pub",
    "wof:placetype":"venue"
},
  "geometry": {"coordinates":[-75.595286,38.671282],"type":"Point"}
}