{
  "type": "Feature",
  "properties": {
    "iso:country":"US",
    "sg:address":"2203 Kirkwood Hwy",
    "sg:city":"Wilmington",
    "sg:classifiers":[
        {
            "category":"Banks & Credit Unions",
            "subcategory":"Bank",
            "type":"Services"
        }
    ],
    "sg:phone":"+1 302 993 3000",
    "sg:postcode":"19805",
    "sg:province":"DE",
    "sg:tags":[
        "state",
        "commercial"
    ],
    "wof:name":"PNC",
    "wof:placetype":"venue"
},
  "geometry": {"coordinates":[-75.611197,39.737996],"type":"Point"}
}