{
  "type": "Feature",
  "properties": {
    "iso:country":"US",
    "sg:address":"4830 Kennett Pike",
    "sg:city":"Wilmington",
    "sg:classifiers":[
        {
            "category":"Professional",
            "type":"Services"
        }
    ],
    "sg:phone":"+1 302 426 8366",
    "sg:postcode":"19807",
    "sg:province":"DE",
    "wof:name":"Eleanor Stirling Anderson",
    "wof:placetype":"venue"
},
  "geometry": {"coordinates":[-75.608661,39.798237],"type":"Point"}
}