{
  "type": "Feature",
  "properties": {
    "iso:country":"US",
    "sg:address":"1001 Middleford Rd",
    "sg:city":"Seaford",
    "sg:classifiers":[
        {
            "category":"Social Services",
            "subcategory":"Adult Care",
            "type":"Services"
        }
    ],
    "sg:phone":"+1 302 629 4593",
    "sg:postcode":"19973",
    "sg:province":"DE",
    "sg:tags":[
        "home",
        "residential",
        "skilled",
        "nursing",
        "facility"
    ],
    "wof:name":"Methodist Manor House",
    "wof:placetype":"venue"
},
  "geometry": {"coordinates":[-75.60243800000001,38.643112],"type":"Point"}
}