{
  "type": "Feature",
  "properties": {
    "iso:country":"US",
    "sg:address":"160 Greentree Dr Ste 203",
    "sg:city":"Dover",
    "sg:classifiers":[
        {
            "category":"Professional",
            "subcategory":"Accounting & Tax Preparation",
            "type":"Services"
        }
    ],
    "sg:phone":"+1 302 674 4305",
    "sg:postcode":"19904",
    "sg:province":"DE",
    "sg:tags":[
        "accountant"
    ],
    "sg:website":"www.fawcasson.com",
    "wof:name":"Hastings Jennings P CPA Abv",
    "wof:placetype":"venue"
},
  "geometry": {"coordinates":[-75.55639600000001,39.1609],"type":"Point"}
}