{
  "type": "Feature",
  "properties": {
    "iso:country":"US",
    "sg:address":"8 E Aldine Dr",
    "sg:city":"Hockessin",
    "sg:classifiers":[
        {
            "category":"Communications",
            "subcategory":"Film & Video Production",
            "type":"Services"
        }
    ],
    "sg:phone":"+1 302 234 9577",
    "sg:postcode":"19707",
    "sg:province":"DE",
    "sg:tags":[
        "audio"
    ],
    "wof:name":"AOV Productions",
    "wof:placetype":"venue"
},
  "geometry": {"coordinates":[-75.67080199999999,39.785248],"type":"Point"}
}