{
  "type": "Feature",
  "properties": {
    "iso:country":"US",
    "sg:address":"313 Forest Dr",
    "sg:city":"Wilmington",
    "sg:classifiers":[
        {
            "category":"Communications",
            "subcategory":"Film & Video Production",
            "type":"Services"
        },
        {
            "category":"Professional",
            "subcategory":"Art Services",
            "type":"Services"
        },
        {
            "category":"Professional",
            "subcategory":"Computer Services",
            "type":"Services"
        }
    ],
    "sg:phone":"+1 302 528 7813",
    "sg:postcode":"19804",
    "sg:province":"DE",
    "sg:tags":[
        "web",
        "graphic",
        "site",
        "designer",
        "design",
        "online",
        "medium",
        "interactive"
    ],
    "sg:website":"http://www.digitalantelope.com",
    "wof:name":"Digital Antelpe",
    "wof:placetype":"venue"
},
  "geometry": {"coordinates":[-75.598517,39.716757],"type":"Point"}
}