{
  "type": "Feature",
  "properties": {
    "iso:country":"US",
    "sg:address":"424 N Front St",
    "sg:city":"Seaford",
    "sg:classifiers":[
        {
            "category":"Autos & Motor Vehicles",
            "subcategory":"Auto Supplies",
            "type":"Retail Goods"
        }
    ],
    "sg:phone":"+1 302 629 9185",
    "sg:postcode":"19973",
    "sg:province":"DE",
    "wof:name":"Manlove Auto Parts",
    "wof:placetype":"venue"
},
  "geometry": {"coordinates":[-75.609179,38.646376],"type":"Point"}
}