{
  "type": "Feature",
  "properties": {
    "iso:country":"US",
    "sg:address":"189 N Scott St",
    "sg:city":"Wilmington",
    "sg:classifiers":[
        {
            "category":"Utilities",
            "subcategory":"Telephone",
            "type":"Services"
        }
    ],
    "sg:phone":"+1 302 654 8866",
    "sg:postcode":"19805",
    "sg:province":"DE",
    "sg:tags":[
        "communications"
    ],
    "wof:name":"Modern Technologys Intl",
    "wof:placetype":"venue"
},
  "geometry": {"coordinates":[-75.572328,39.746022],"type":"Point"}
}