{
  "type": "Feature",
  "properties": {
    "iso:country":"US",
    "sg:address":"2 Reads Way",
    "sg:city":"New Castle",
    "sg:classifiers":[
        {
            "category":"Professional",
            "subcategory":"Employment Agencies",
            "type":"Services"
        }
    ],
    "sg:phone":"+1 302 326 9073",
    "sg:postcode":"19720",
    "sg:province":"DE",
    "sg:tags":[
        "help",
        "contractor"
    ],
    "wof:name":"Olsten Staffing Svc",
    "wof:placetype":"venue"
},
  "geometry": {"coordinates":[-75.609111,39.688378],"type":"Point"}
}