{
  "type": "Feature",
  "properties": {
    "iso:country":"US",
    "sg:address":"623 N King St",
    "sg:city":"Wilmington",
    "sg:classifiers":[
        {
            "category":"Insurance",
            "subcategory":"Hazard Insurance",
            "type":"Services"
        }
    ],
    "sg:phone":"+1 302 777 7982",
    "sg:postcode":"19801",
    "sg:province":"DE",
    "sg:tags":[
        "bond"
    ],
    "wof:name":"T & H Bail Bonds",
    "wof:placetype":"venue"
},
  "geometry": {"coordinates":[-75.54936600000001,39.741716],"type":"Point"}
}