{
  "type": "Feature",
  "properties": {
    "iso:country":"US",
    "sg:address":"5183 Vernon Rd",
    "sg:city":"Harrington",
    "sg:classifiers":[
        {
            "category":"Organizations",
            "subcategory":"Religious Organization",
            "type":"Services"
        }
    ],
    "sg:phone":"+1 302 398 9415",
    "sg:postcode":"19952",
    "sg:province":"DE",
    "sg:tags":[
        "church"
    ],
    "wof:name":"Prospect United Methodist Chr",
    "wof:placetype":"venue"
},
  "geometry": {"coordinates":[-75.63808899999999,38.894229],"type":"Point"}
}