{
  "type": "Feature",
  "properties": {
    "iso:country":"US",
    "sg:address":"21 Red Mill Rd",
    "sg:city":"Newark",
    "sg:classifiers":[
        {
            "category":"Building & Trades",
            "subcategory":"Electrical",
            "type":"Services"
        }
    ],
    "sg:phone":"+1 302 737 0223",
    "sg:postcode":"19711",
    "sg:province":"DE",
    "sg:tags":[
        "electrical",
        "contractor"
    ],
    "wof:name":"CT Crossan Elec Cantract Inc",
    "wof:placetype":"venue"
},
  "geometry": {"coordinates":[-75.70885699999999,39.694221],"type":"Point"}
}