{
  "type": "Feature",
  "properties": {
    "iso:country":"US",
    "sg:address":"20622 Camp Rd",
    "sg:city":"Bridgeville",
    "sg:classifiers":[
        {
            "category":"Personal",
            "subcategory":"Beauty Salon",
            "type":"Services"
        }
    ],
    "sg:phone":"+1 302 337 0130",
    "sg:postcode":"19933",
    "sg:province":"DE",
    "wof:name":"Especially Yours Hair Salon",
    "wof:placetype":"venue"
},
  "geometry": {"coordinates":[-75.58385800000001,38.700237],"type":"Point"}
}