{
  "type": "Feature",
  "properties": {
    "iso:country":"US",
    "sg:address":"1 Woodcroft Ln",
    "sg:city":"Wilmington",
    "sg:classifiers":[
        {
            "category":"Real Estate",
            "subcategory":"Real Estate Agent",
            "type":"Services"
        }
    ],
    "sg:phone":"+1 302 475 6822",
    "sg:postcode":"19810",
    "sg:province":"DE",
    "wof:name":"Brandy Edgington",
    "wof:placetype":"venue"
},
  "geometry": {"coordinates":[-75.491832,39.814906],"type":"Point"}
}