{
  "type": "Feature",
  "properties": {
    "iso:country":"US",
    "sg:address":"7 Nicole Ct",
    "sg:city":"New Castle",
    "sg:classifiers":[
        {
            "category":"Government",
            "subcategory":"Office",
            "type":"Public Place"
        }
    ],
    "sg:phone":"+1 302 322 6100",
    "sg:postcode":"19720",
    "sg:province":"DE",
    "sg:tags":[
        "legislative",
        "body"
    ],
    "wof:name":"David B McBride Senator",
    "wof:placetype":"venue"
},
  "geometry": {"coordinates":[-75.646979,39.660086],"type":"Point"}
}