{
  "type": "Feature",
  "properties": {
    "addr:full":"521 Langwater Dr Newark DE 19711",
    "addr:housenumber":"521",
    "addr:postcode":"19711",
    "addr:street":"Langwater Dr",
    "iso:country":"US",
    "sg:address":"521 Langwater Dr",
    "sg:city":"Newark",
    "sg:classifiers":[
        {
            "category":"Organizations",
            "subcategory":"Religious Organization",
            "type":"Services"
        }
    ],
    "sg:phone":"+1 302 235 7020",
    "sg:postcode":"19711",
    "sg:province":"DE",
    "wof:name":"Hindu Temple Assoc Inc",
    "wof:placetype":"venue"
},
  "geometry": {"coordinates":[-75.736222,39.76544],"type":"Point"}
}