{
  "type": "Feature",
  "properties": {
    "addr:full":"20 Brendle Ln Wilmington DE 19807",
    "addr:housenumber":"20",
    "addr:postcode":"19807",
    "addr:street":"Brendle Ln",
    "iso:country":"US",
    "sg:address":"20 Brendle Ln",
    "sg:city":"Wilmington",
    "sg:classifiers":[
        {
            "category":"Professional",
            "subcategory":"Management & Consulting",
            "type":"Services"
        }
    ],
    "sg:phone":"+1 302 428 0350",
    "sg:postcode":"19807",
    "sg:province":"DE",
    "sg:tags":[
        "financial"
    ],
    "wof:name":"Philadelphia Venture Mgt",
    "wof:placetype":"venue"
},
  "geometry": {"coordinates":[-75.58482600000001,39.822307],"type":"Point"}
}