{
  "type": "Feature",
  "properties": {
    "iso:country":"US",
    "sg:address":"1403 Foulk Rd Ste 102",
    "sg:city":"Wilmington",
    "sg:classifiers":[
        {
            "category":"Banks & Credit Unions",
            "subcategory":"Investment Brokerage",
            "type":"Services"
        }
    ],
    "sg:phone":"+1 302 479 5936",
    "sg:postcode":"19803",
    "sg:province":"DE",
    "sg:tags":[
        "investing"
    ],
    "wof:name":"S B Portfolio Management Corporation",
    "wof:placetype":"venue"
},
  "geometry": {"coordinates":[-75.521698,39.8013],"type":"Point"}
}