{
  "type": "Feature",
  "properties": {
    "iso:country":"US",
    "sg:address":"1306 Holletts Corner Rd",
    "sg:city":"Clayton",
    "sg:classifiers":[
        {
            "category":"Building & Trades",
            "subcategory":"Landscaping Services",
            "type":"Services"
        }
    ],
    "sg:phone":"+1 302 653 4667",
    "sg:postcode":"19938",
    "sg:province":"DE",
    "wof:name":"All State Tree Service",
    "wof:placetype":"venue"
},
  "geometry": {"coordinates":[-75.742108,39.283229],"type":"Point"}
}