{
  "type": "Feature",
  "properties": {
    "addr:full":"2002 W Newport Pike Wilmington DE 19804",
    "addr:housenumber":"2002",
    "addr:postcode":"19804",
    "addr:street":"W Newport Pike",
    "iso:country":"US",
    "sg:address":"2002 W Newport Pike",
    "sg:city":"Wilmington",
    "sg:classifiers":[
        {
            "category":"Personal",
            "subcategory":"Beauty Salon",
            "type":"Services"
        }
    ],
    "sg:phone":"+1 302 994 3031",
    "sg:postcode":"19804",
    "sg:province":"DE",
    "sg:tags":[
        "shop"
    ],
    "wof:name":"Christine's Creations",
    "wof:placetype":"venue"
},
  "geometry": {"coordinates":[-75.636314,39.715765],"type":"Point"}
}