{
  "type": "Feature",
  "properties": {
    "addr:full":"1 Tammie Dr Bear DE 19701",
    "addr:housenumber":"1",
    "addr:postcode":"19701",
    "addr:street":"Tammie Dr",
    "iso:country":"US",
    "sg:address":"1 Tammie Dr",
    "sg:city":"Bear",
    "sg:classifiers":[
        {
            "category":"Building & Trades",
            "subcategory":"Construction",
            "type":"Services"
        }
    ],
    "sg:phone":"+1 302 836 8031",
    "sg:postcode":"19701",
    "sg:province":"DE",
    "sg:tags":[
        "concrete",
        "contractor"
    ],
    "wof:name":"Bradley & Sons Designer Con",
    "wof:placetype":"venue"
},
  "geometry": {"coordinates":[-75.70753999999999,39.593841],"type":"Point"}
}