{
  "type": "Feature",
  "properties": {
    "addr:full":"190 Brecks Ln Wilmington DE 19807",
    "addr:housenumber":"190",
    "addr:postcode":"19807",
    "addr:street":"Brecks Ln",
    "iso:country":"US",
    "sg:address":"190 Brecks Ln",
    "sg:city":"Wilmington",
    "sg:classifiers":[
        {
            "category":"Professional",
            "type":"Services"
        }
    ],
    "sg:phone":"+1 302 652 4855",
    "sg:postcode":"19807",
    "sg:province":"DE",
    "wof:name":"Net Result Inc",
    "wof:placetype":"venue"
},
  "geometry": {"coordinates":[-75.583626,39.769616],"type":"Point"}
}