{
  "type": "Feature",
  "properties": {
    "addr:full":"345 Tamara Cir Newark DE 19711",
    "addr:housenumber":"345",
    "addr:postcode":"19711",
    "addr:street":"Tamara Cir",
    "iso:country":"US",
    "sg:address":"345 Tamara Cir",
    "sg:city":"Newark",
    "sg:classifiers":[
        {
            "category":"Building & Trades",
            "subcategory":"Construction",
            "type":"Services"
        }
    ],
    "sg:phone":"+1 302 731 2516",
    "sg:postcode":"19711",
    "sg:province":"DE",
    "sg:tags":[
        "house"
    ],
    "wof:name":"Dean Groud Const",
    "wof:placetype":"venue"
},
  "geometry": {"coordinates":[-75.68065,39.696555],"type":"Point"}
}