{
  "type": "Feature",
  "properties": {
    "addr:full":"820 N Buttonwood St Wilmington DE 19801",
    "addr:housenumber":"820",
    "addr:postcode":"19801",
    "addr:street":"N Buttonwood St",
    "iso:country":"US",
    "sg:address":"820 N Buttonwood St",
    "sg:city":"Wilmington",
    "sg:classifiers":[
        {
            "category":"Recreation",
            "type":"Entertainment"
        }
    ],
    "sg:phone":"+1 302 655 2028",
    "sg:postcode":"19801",
    "sg:province":"DE",
    "wof:name":"Konica Roller Exchange",
    "wof:placetype":"venue"
},
  "geometry": {"coordinates":[-75.53868,39.739723],"type":"Point"}
}