{
  "type": "Feature",
  "properties": {
    "iso:country":"US",
    "sg:address":"100 W 10th St",
    "sg:city":"Wilmington",
    "sg:classifiers":[
        {
            "category":"Social Services",
            "subcategory":"Job Training",
            "type":"Services"
        }
    ],
    "sg:phone":"+1 302 622 9177",
    "sg:postcode":"19801",
    "sg:province":"DE",
    "sg:tags":[
        "rehabilitation"
    ],
    "wof:name":"Delaware Association-Rhb Fclts",
    "wof:placetype":"venue"
},
  "geometry": {"coordinates":[-75.54907300000001,39.74608],"type":"Point"}
}