{
  "type": "Feature",
  "properties": {
    "addr:full":"33 Central Ave Ocean View DE 19970",
    "addr:housenumber":"33",
    "addr:postcode":"19970",
    "addr:street":"Central Ave",
    "iso:country":"US",
    "sg:address":"33 Central Ave",
    "sg:city":"Ocean View",
    "sg:classifiers":[
        {
            "category":"Home & Garden",
            "subcategory":"Carpets & Floor Coverings",
            "type":"Retail Goods"
        }
    ],
    "sg:phone":"+1 302 537 2480",
    "sg:postcode":"19970",
    "sg:province":"DE",
    "sg:tags":[
        "window",
        "installation",
        "rug",
        "dealer"
    ],
    "wof:name":"Interiors By Kim Inc",
    "wof:placetype":"venue"
},
  "geometry": {"coordinates":[-75.088825,38.548616],"type":"Point"}
}