{
  "type": "Feature",
  "properties": {
    "iso:country":"US",
    "sg:address":"117 New Rd",
    "sg:city":"Wilmington",
    "sg:classifiers":[
        {
            "category":"Wholesale",
            "subcategory":"Auto Parts",
            "type":"Manufacturing & Wholesale Goods"
        }
    ],
    "sg:phone":"+1 302 658 4070",
    "sg:postcode":"19805",
    "sg:province":"DE",
    "sg:tags":[
        "automotive",
        "supply"
    ],
    "wof:name":"Finishmaster Paint Stores",
    "wof:placetype":"venue"
},
  "geometry": {"coordinates":[-75.582832,39.741384],"type":"Point"}
}