{
  "type": "Feature",
  "properties": {
    "iso:country":"US",
    "sg:address":"222 Philadelphia Pike",
    "sg:city":"Wilmington",
    "sg:classifiers":[
        {
            "category":"Professional",
            "subcategory":"Management & Consulting",
            "type":"Services"
        }
    ],
    "sg:phone":"+1 302 761 9300",
    "sg:postcode":"19809",
    "sg:province":"DE",
    "sg:tags":[
        "business"
    ],
    "wof:name":"High Achvers Mtvtional Academy",
    "wof:placetype":"venue"
},
  "geometry": {"coordinates":[-75.513884,39.764395],"type":"Point"}
}