{
  "type": "Feature",
  "properties": {
    "iso:country":"US",
    "sg:address":"812 Interchange Blvd",
    "sg:city":"Newark",
    "sg:classifiers":[
        {
            "category":"Professional",
            "type":"Services"
        }
    ],
    "sg:phone":"+1 302 455 0102",
    "sg:postcode":"19711",
    "sg:province":"DE",
    "wof:name":"Intelligent Systems",
    "wof:placetype":"venue"
},
  "geometry": {"coordinates":[-75.778155,39.66196],"type":"Point"}
}