{
  "type": "Feature",
  "properties": {
    "iso:country":"US",
    "sg:address":"101 N Union St",
    "sg:city":"Wilmington",
    "sg:classifiers":[
        {
            "category":"Autos & Motor Vehicles",
            "subcategory":"Automobile Sales",
            "type":"Retail Goods"
        }
    ],
    "sg:phone":"+1 302 652 3590",
    "sg:postcode":"19805",
    "sg:province":"DE",
    "wof:name":"Rylin Motors",
    "wof:placetype":"venue"
},
  "geometry": {"coordinates":[-75.57413099999999,39.747614],"type":"Point"}
}