{
  "type": "Feature",
  "properties": {
    "iso:country":"US",
    "sg:address":"2700 Hwy One",
    "sg:city":"Rehoboth Beach",
    "sg:classifiers":[
        {
            "category":"Food & Beverages",
            "subcategory":"Groceries & Convenience Stores",
            "type":"Retail Goods"
        }
    ],
    "sg:phone":"+1 302 227 4486",
    "sg:postcode":"19971",
    "sg:province":"DE",
    "sg:tags":[
        "grocer"
    ],
    "wof:name":"De-Lux Dairy Market",
    "wof:placetype":"venue"
},
  "geometry": {"coordinates":[-75.079441,38.7004],"type":"Point"}
}