{
  "type": "Feature",
  "properties": {
    "iso:country":"US",
    "sg:address":"104 Main St",
    "sg:city":"Millsboro",
    "sg:classifiers":[
        {
            "category":"Banks & Credit Unions",
            "subcategory":"Bank",
            "type":"Services"
        }
    ],
    "sg:phone":"+1 302 934 3106",
    "sg:postcode":"19966",
    "sg:province":"DE",
    "wof:name":"Pnc Bank",
    "wof:placetype":"venue"
},
  "geometry": {"coordinates":[-75.29380399999999,38.588257],"type":"Point"}
}