{
  "type": "Feature",
  "properties": {
    "addr:full":"235 Pinehurst Rd Wilmington DE 19803",
    "addr:housenumber":"235",
    "addr:postcode":"19803",
    "addr:street":"Pinehurst Rd",
    "iso:country":"US",
    "sg:address":"235 Pinehurst Rd",
    "sg:city":"Wilmington",
    "sg:classifiers":[
        {
            "category":"Organizations",
            "subcategory":"Membership Organization",
            "type":"Services"
        }
    ],
    "sg:phone":"+1 302 652 5976",
    "sg:postcode":"19803",
    "sg:province":"DE",
    "wof:name":"Northern Delaware Soccer Leag",
    "wof:placetype":"venue"
},
  "geometry": {"coordinates":[-75.53786100000001,39.792193],"type":"Point"}
}