{
  "type": "Feature",
  "properties": {
    "iso:country":"US",
    "sg:address":"10667 Dupont Blvd",
    "sg:city":"Lincoln",
    "sg:classifiers":[
        {
            "category":"Freight",
            "type":"Transportation"
        }
    ],
    "sg:phone":"+1 302 422 0441",
    "sg:postcode":"19960",
    "sg:province":"DE",
    "sg:tags":[
        "truck",
        "broker"
    ],
    "wof:name":"R & M Trucking",
    "wof:placetype":"venue"
},
  "geometry": {"coordinates":[-75.43874099999999,38.833575],"type":"Point"}
}