{
  "type": "Feature",
  "properties": {
    "iso:country":"US",
    "sg:address":"700 White Clay Center Dr",
    "sg:city":"Newark",
    "sg:classifiers":[
        {
            "category":"Banks & Credit Unions",
            "subcategory":"Bank",
            "type":"Services"
        }
    ],
    "sg:phone":"+1 302 451 2500",
    "sg:postcode":"19711",
    "sg:province":"DE",
    "sg:tags":[
        "a",
        "it",
        "operates",
        "state",
        "through",
        "subsidiary",
        "as"
    ],
    "wof:name":"Bank of NY",
    "wof:placetype":"venue"
},
  "geometry": {"coordinates":[-75.723862,39.6844],"type":"Point"}
}