{
  "type": "Feature",
  "properties": {
    "iso:country":"US",
    "sg:address":"758 Christiana Pkwy",
    "sg:city":"Newark",
    "sg:classifiers":[
        {
            "category":"Real Estate",
            "subcategory":"Real Estate Operator",
            "type":"Services"
        }
    ],
    "sg:phone":"+1 302 738 0200",
    "sg:postcode":"19713",
    "sg:province":"DE",
    "sg:tags":[
        "apartment"
    ],
    "wof:name":"Cedar Wood Apartments",
    "wof:placetype":"venue"
},
  "geometry": {"coordinates":[-75.70256999999999,39.675059],"type":"Point"}
}