{
  "type": "Feature",
  "properties": {
    "iso:country":"US",
    "sg:address":"3 E Hawthorne Ct",
    "sg:city":"Newark",
    "sg:classifiers":[
        {
            "category":"Wholesale",
            "subcategory":"Electrical",
            "type":"Manufacturing & Wholesale Goods"
        }
    ],
    "sg:phone":"+1 302 834 5231",
    "sg:postcode":"19702",
    "sg:province":"DE",
    "sg:tags":[
        "installation",
        "telecommunication",
        "sales"
    ],
    "sg:website":"www.cabletechde.com",
    "wof:name":"Cable Technologies Inc",
    "wof:placetype":"venue"
},
  "geometry": {"coordinates":[-75.759872,39.599534],"type":"Point"}
}