{
  "type": "Feature",
  "properties": {
    "iso:country":"US",
    "sg:address":"326 W Dupont Hwy",
    "sg:city":"Millsboro",
    "sg:classifiers":[
        {
            "category":"Insurance",
            "subcategory":"Insurance Agent",
            "type":"Services"
        }
    ],
    "sg:phone":"+1 302 934 9235",
    "sg:postcode":"19966",
    "sg:province":"DE",
    "wof:name":"Brittingham & Williams",
    "wof:placetype":"venue"
},
  "geometry": {"coordinates":[-75.301782,38.589069],"type":"Point"}
}