{
  "type": "Feature",
  "properties": {
    "iso:country":"US",
    "sg:address":"151 Fairhill Dr",
    "sg:city":"Wilmington",
    "sg:classifiers":[
        {
            "category":"Building & Trades",
            "subcategory":"Plumbing",
            "type":"Services"
        }
    ],
    "sg:phone":"+1 302 239 9572",
    "sg:postcode":"19808",
    "sg:province":"DE",
    "sg:tags":[
        "contractor"
    ],
    "wof:name":"Cooling III Frederick",
    "wof:placetype":"venue"
},
  "geometry": {"coordinates":[-75.682507,39.754552],"type":"Point"}
}