{
  "type": "Feature",
  "properties": {
    "iso:country":"US",
    "sg:address":"220 Johnson Way",
    "sg:city":"New Castle",
    "sg:classifiers":[
        {
            "category":"Real Estate",
            "subcategory":"Real Estate Agent",
            "type":"Services"
        }
    ],
    "sg:phone":"+1 302 326 9917",
    "sg:postcode":"19720",
    "sg:province":"DE",
    "sg:tags":[
        "commercial"
    ],
    "wof:name":"Center Point 2000",
    "wof:placetype":"venue"
},
  "geometry": {"coordinates":[-75.588145,39.662749],"type":"Point"}
}