{
  "type": "Feature",
  "properties": {
    "iso:country":"US",
    "sg:address":"304 N Union St",
    "sg:city":"Wilmington",
    "sg:classifiers":[
        {
            "category":"Wholesale",
            "subcategory":"Hardware",
            "type":"Manufacturing & Wholesale Goods"
        }
    ],
    "sg:phone":"+1 302 655 0709",
    "sg:postcode":"19805",
    "sg:province":"DE",
    "wof:name":"Sister Team African Braiding",
    "wof:placetype":"venue"
},
  "geometry": {"coordinates":[-75.57295000000001,39.74921],"type":"Point"}
}