{
  "type": "Feature",
  "properties": {
    "iso:country":"US",
    "sg:address":"1901 N Dupont Hwy",
    "sg:city":"New Castle",
    "sg:classifiers":[
        {
            "category":"Professional",
            "subcategory":"Accounting & Tax Preparation",
            "type":"Services"
        }
    ],
    "sg:phone":"+1 302 577 4564",
    "sg:postcode":"19720",
    "sg:province":"DE",
    "wof:name":"Audit and Recovery MGT Svcs",
    "wof:placetype":"venue"
},
  "geometry": {"coordinates":[-75.575073,39.697753],"type":"Point"}
}