{
  "type": "Feature",
  "properties": {
    "iso:country":"US",
    "sg:address":"426 Christina Mill Dr",
    "sg:city":"Newark",
    "sg:classifiers":[
        {
            "category":"Professional",
            "type":"Services"
        }
    ],
    "sg:phone":"+1 302 229 4856",
    "sg:postcode":"19711",
    "sg:province":"DE",
    "wof:name":"Tri State Data Network",
    "wof:placetype":"venue"
},
  "geometry": {"coordinates":[-75.77447600000001,39.670302],"type":"Point"}
}