{
  "type": "Feature",
  "properties": {
    "iso:country":"US",
    "sg:address":"64 Omega Dr",
    "sg:city":"Newark",
    "sg:classifiers":[
        {
            "category":"Health Services",
            "subcategory":"Doctor",
            "type":"Services"
        }
    ],
    "sg:phone":"+1 302 368 8850",
    "sg:postcode":"19713",
    "sg:province":"DE",
    "sg:tags":[
        "medical"
    ],
    "wof:name":"Christiana Obgyn",
    "wof:placetype":"venue"
},
  "geometry": {"coordinates":[-75.67588600000001,39.691419],"type":"Point"}
}