{
  "type": "Feature",
  "properties": {
    "iso:country":"US",
    "sg:address":"53 Cape Henlopen Dr",
    "sg:city":"Lewes",
    "sg:classifiers":[
        {
            "category":"Professional",
            "subcategory":"Business Services",
            "type":"Services"
        }
    ],
    "sg:phone":"+1 302 645 6110",
    "sg:postcode":"19958",
    "sg:province":"DE",
    "wof:name":"Port Lewes Assoc Unit Owner",
    "wof:placetype":"venue"
},
  "geometry": {"coordinates":[-75.127753,38.780267],"type":"Point"}
}