{
  "type": "Feature",
  "properties": {
    "iso:country":"US",
    "sg:address":"2912 Mendenhall Ave",
    "sg:city":"Wilmington",
    "sg:classifiers":[
        {
            "category":"Professional",
            "type":"Services"
        }
    ],
    "sg:phone":"+1 302 762 7976",
    "sg:postcode":"19802",
    "sg:province":"DE",
    "wof:name":"Kenmart Inc",
    "wof:placetype":"venue"
},
  "geometry": {"coordinates":[-75.523628,39.751185],"type":"Point"}
}