{
  "type": "Feature",
  "properties": {
    "iso:country":"US",
    "sg:address":"516 Riga Dr",
    "sg:city":"Ocean View",
    "sg:classifiers":[
        {
            "category":"Building & Trades",
            "subcategory":"Construction",
            "type":"Services"
        }
    ],
    "sg:phone":"+1 302 541 9293",
    "sg:postcode":"19970",
    "sg:province":"DE",
    "sg:tags":[
        "window",
        "replacement"
    ],
    "wof:name":"Superior Screen & Glass",
    "wof:placetype":"venue"
},
  "geometry": {"coordinates":[-75.08088499999999,38.539021],"type":"Point"}
}