{
  "type": "Feature",
  "properties": {
    "iso:country":"US",
    "sg:address":"14 Hidden Valley Dr",
    "sg:city":"Newark",
    "sg:classifiers":[
        {
            "category":"Professional",
            "subcategory":"Business Services",
            "type":"Services"
        }
    ],
    "sg:phone":"+1 302 369 8837",
    "sg:postcode":"19711",
    "sg:province":"DE",
    "sg:tags":[
        "holding"
    ],
    "wof:name":"Spurgeon Holdings",
    "wof:placetype":"venue"
},
  "geometry": {"coordinates":[-75.778488,39.693724],"type":"Point"}
}