{
  "type": "Feature",
  "properties": {
    "iso:country":"US",
    "sg:address":"2651 Kirkwood Hwy",
    "sg:city":"Newark",
    "sg:classifiers":[
        {
            "category":"Home & Garden",
            "subcategory":"Furniture",
            "type":"Retail Goods"
        }
    ],
    "sg:phone":"+1 302 322 2311",
    "sg:postcode":"19711",
    "sg:province":"DE",
    "wof:name":"Newark Home Furnishings Inc",
    "wof:placetype":"venue"
},
  "geometry": {"coordinates":[-75.684923,39.706929],"type":"Point"}
}