{
  "type": "Feature",
  "properties": {
    "iso:country":"US",
    "sg:address":"1901 N Dupont Hwy",
    "sg:city":"New Castle",
    "sg:classifiers":[
        {
            "category":"Government",
            "subcategory":"Office",
            "type":"Public Place"
        }
    ],
    "sg:phone":"+1 302 577 4461",
    "sg:postcode":"19720",
    "sg:province":"DE",
    "sg:tags":[
        "state",
        "program",
        "health"
    ],
    "wof:name":"Alcoholism & Drug Abuse Bureau",
    "wof:placetype":"venue"
},
  "geometry": {"coordinates":[-75.575073,39.697753],"type":"Point"}
}