{
  "type": "Feature",
  "properties": {
    "iso:country":"US",
    "sg:address":"135 Cornwell Dr",
    "sg:city":"Bear",
    "sg:classifiers":[
        {
            "category":"Manufacturing",
            "subcategory":"Food",
            "type":"Manufacturing & Wholesale Goods"
        }
    ],
    "sg:phone":"+1 302 834 6862",
    "sg:postcode":"19701",
    "sg:province":"DE",
    "sg:tags":[
        "preparation",
        "mfg"
    ],
    "wof:name":"Ten Percent Club Inc",
    "wof:placetype":"venue"
},
  "geometry": {"coordinates":[-75.687146,39.567105],"type":"Point"}
}