{
  "type": "Feature",
  "properties": {
    "addr:full":"23490 Sussex Hwy Seaford DE 19973",
    "addr:housenumber":"23490",
    "addr:postcode":"19973",
    "addr:street":"Sussex Hwy",
    "iso:country":"US",
    "sg:address":"23490 Sussex Hwy",
    "sg:city":"Seaford",
    "sg:classifiers":[
        {
            "category":"Shopping",
            "subcategory":"Department Store",
            "type":"Retail Goods"
        }
    ],
    "sg:phone":"+1 302 628 1477",
    "sg:postcode":"19973",
    "sg:province":"DE",
    "wof:name":"W&C Clothing Outlet",
    "wof:placetype":"venue"
},
  "geometry": {"coordinates":[-75.59467100000001,38.655084],"type":"Point"}
}