{
  "type": "Feature",
  "properties": {
    "addr:full":"500 Denny St Dover DE 19901",
    "addr:housenumber":"500",
    "addr:postcode":"19901",
    "addr:street":"Denny St",
    "iso:country":"US",
    "sg:address":"500 Denny St",
    "sg:city":"Dover",
    "sg:classifiers":[
        {
            "category":"Shopping",
            "subcategory":"Bicycles & Sporting Goods",
            "type":"Retail Goods"
        }
    ],
    "sg:phone":"+1 302 744 9140",
    "sg:postcode":"19901",
    "sg:province":"DE",
    "sg:tags":[
        "bait",
        "fishing"
    ],
    "wof:name":"Smiths Bait Shop",
    "wof:placetype":"venue"
},
  "geometry": {"coordinates":[-75.517533,39.244266],"type":"Point"}
}