{
  "type": "Feature",
  "properties": {
    "addr:full":"311 Holly Ct Bethany Beach DE 19930",
    "addr:housenumber":"311",
    "addr:postcode":"19930",
    "addr:street":"Holly Ct",
    "iso:country":"US",
    "sg:address":"311 Holly Ct",
    "sg:city":"Bethany Beach",
    "sg:classifiers":[
        {
            "category":"Health Services",
            "subcategory":"Doctor",
            "type":"Services"
        }
    ],
    "sg:phone":"+1 302 539 1176",
    "sg:postcode":"19930",
    "sg:province":"DE",
    "sg:tags":[
        "medical"
    ],
    "wof:name":"Michael Balenson Dr",
    "wof:placetype":"venue"
},
  "geometry": {"coordinates":[-75.060309,38.533889],"type":"Point"}
}