{
  "type": "Feature",
  "properties": {
    "iso:country":"US",
    "sg:address":"500 S Dupont Hwy",
    "sg:city":"New Castle",
    "sg:classifiers":[
        {
            "category":"Real Estate",
            "subcategory":"Real Estate Operator",
            "type":"Services"
        }
    ],
    "sg:phone":"+1 302 328 7679",
    "sg:postcode":"19720",
    "sg:province":"DE",
    "sg:tags":[
        "apartment"
    ],
    "wof:name":"Pine Woods Village",
    "wof:placetype":"venue"
},
  "geometry": {"coordinates":[-75.624842,39.6442],"type":"Point"}
}