{
  "type": "Feature",
  "properties": {
    "iso:country":"US",
    "sg:address":"77 McCullough Dr",
    "sg:city":"New Castle",
    "sg:classifiers":[
        {
            "category":"Local Transit",
            "type":"Transportation"
        }
    ],
    "sg:phone":"+1 302 325 4200",
    "sg:postcode":"19720",
    "sg:province":"DE",
    "sg:tags":[
        "limousine"
    ],
    "wof:name":"Eagle Limousine & Motorcoach",
    "wof:placetype":"venue"
},
  "geometry": {"coordinates":[-75.56947,39.690937],"type":"Point"}
}