{
  "type": "Feature",
  "properties": {
    "iso:country":"US",
    "sg:address":"2711 Centerville Rd",
    "sg:city":"Wilmington",
    "sg:classifiers":[
        {
            "category":"Real Estate",
            "subcategory":"Real Estate Agent",
            "type":"Services"
        }
    ],
    "sg:phone":"+1 719 683 2731",
    "sg:postcode":"19808",
    "sg:province":"DE",
    "sg:tags":[
        "business",
        "holding"
    ],
    "wof:name":"Malachi Enterprises Inc",
    "wof:placetype":"venue"
},
  "geometry": {"coordinates":[-75.62527799999999,39.756113],"type":"Point"}
}