{
  "type": "Feature",
  "properties": {
    "addr:full":"804 Maryland Ave Wilmington DE 19805",
    "addr:housenumber":"804",
    "addr:postcode":"19805",
    "addr:street":"Maryland Ave",
    "iso:country":"US",
    "sg:address":"804 Maryland Ave",
    "sg:city":"Wilmington",
    "sg:classifiers":[
        {
            "category":"Organizations",
            "subcategory":"Professional Association",
            "type":"Services"
        }
    ],
    "sg:phone":"+1 302 652 5317",
    "sg:postcode":"19805",
    "sg:province":"DE",
    "wof:name":"Wilmington Fire Fighters Assn",
    "wof:placetype":"venue"
},
  "geometry": {"coordinates":[-75.567274,39.737243],"type":"Point"}
}