{
  "type": "Feature",
  "properties": {
    "iso:country":"US",
    "sg:address":"111 Wallasey Rd",
    "sg:city":"Wilmington",
    "sg:classifiers":[
        {
            "category":"Real Estate",
            "subcategory":"Surveying",
            "type":"Services"
        }
    ],
    "sg:phone":"+1 302 683 9220",
    "sg:postcode":"19808",
    "sg:province":"DE",
    "wof:name":"Midatlantic Surveying Assoc LL",
    "wof:placetype":"venue"
},
  "geometry": {"coordinates":[-75.657788,39.764641],"type":"Point"}
}