{
  "type": "Feature",
  "properties": {
    "iso:country":"US",
    "sg:address":"4 Mason Dr",
    "sg:city":"Selbyville",
    "sg:classifiers":[
        {
            "category":"Wholesale",
            "subcategory":"Construction Materials",
            "type":"Manufacturing & Wholesale Goods"
        }
    ],
    "sg:phone":"+1 302 436 9520",
    "sg:postcode":"19975",
    "sg:province":"DE",
    "sg:tags":[
        "fence"
    ],
    "sg:website":"www.esvinylproducts.com",
    "wof:name":"Eastern Shore Porch & Patio",
    "wof:placetype":"venue"
},
  "geometry": {"coordinates":[-75.229173,38.451292],"type":"Point"}
}