{
  "type": "Feature",
  "properties": {
    "addr:full":"20639 Fleatown Rd Lincoln DE 19960",
    "addr:postcode":"20639;19960",
    "addr:street":"Fleatown Rd",
    "iso:country":"US",
    "sg:address":"20639 Fleatown Rd",
    "sg:city":"Lincoln",
    "sg:classifiers":[
        {
            "category":"Food & Beverages",
            "subcategory":"Groceries & Convenience Stores",
            "type":"Retail Goods"
        }
    ],
    "sg:phone":"+1 302 422 5044",
    "sg:postcode":"19960",
    "sg:province":"DE",
    "wof:name":"King's Market",
    "wof:placetype":"venue"
},
  "geometry": {"coordinates":[-75.38825,38.861533],"type":"Point"}
}