{
  "type": "Feature",
  "properties": {
    "iso:country":"US",
    "sg:address":"11 Windsor Rd",
    "sg:city":"Wilmington",
    "sg:classifiers":[
        {
            "category":"Professional",
            "subcategory":"Management & Consulting",
            "type":"Services"
        }
    ],
    "sg:phone":"+1 302 762 2858",
    "sg:postcode":"19809",
    "sg:province":"DE",
    "wof:name":"Worldwide Corprte Cnsltnt",
    "wof:placetype":"venue"
},
  "geometry": {"coordinates":[-75.507175,39.769679],"type":"Point"}
}