{
  "type": "Feature",
  "properties": {
    "iso:country":"US",
    "sg:address":"222 S Jackson St",
    "sg:city":"Wilmington",
    "sg:classifiers":[
        {
            "category":"Food & Beverages",
            "subcategory":"Liquor & Beverages",
            "type":"Retail Goods"
        }
    ],
    "sg:phone":"+1 302 651 9716",
    "sg:postcode":"19805",
    "sg:province":"DE",
    "sg:tags":[
        "alcoholic"
    ],
    "wof:name":"Jackson Street Liquors",
    "wof:placetype":"venue"
},
  "geometry": {"coordinates":[-75.563293,39.740435],"type":"Point"}
}