{
  "type": "Feature",
  "properties": {
    "iso:country":"US",
    "sg:address":"943 N Dupont Blvd",
    "sg:city":"Milford",
    "sg:classifiers":[
        {
            "category":"Restaurant",
            "type":"Food & Drink"
        }
    ],
    "sg:menulink":"http://www.allmenus.com/de/milford-north/166901-burger-king/menu/",
    "sg:phone":"+1 302 424 2272",
    "sg:postcode":"19963",
    "sg:province":"DE",
    "sg:tags":[
        "burger",
        "american"
    ],
    "wof:name":"Burger King",
    "wof:placetype":"venue"
},
  "geometry": {"coordinates":[-75.431535,38.92997],"type":"Point"}
}