{
  "type": "Feature",
  "properties": {
    "iso:country":"US",
    "sg:address":"432 Bay Rd",
    "sg:city":"Milford",
    "sg:classifiers":[
        {
            "category":"Food & Beverages",
            "subcategory":"Groceries & Convenience Stores",
            "type":"Retail Goods"
        }
    ],
    "sg:phone":"+1 302 422 2700",
    "sg:postcode":"19963",
    "sg:province":"DE",
    "wof:name":"Shore Stop",
    "wof:placetype":"venue"
},
  "geometry": {"coordinates":[-75.42554800000001,38.949853],"type":"Point"}
}