{
  "type": "Feature",
  "properties": {
    "iso:country":"US",
    "sg:address":"221 Greenbank Rd",
    "sg:city":"Wilmington",
    "sg:classifiers":[
        {
            "category":"Real Estate",
            "subcategory":"Real Estate Operator",
            "type":"Services"
        }
    ],
    "sg:phone":"+1 302 998 4644",
    "sg:postcode":"19808",
    "sg:province":"DE",
    "sg:tags":[
        "building",
        "apartment"
    ],
    "wof:name":"Greenbank Manor Apartments",
    "wof:placetype":"venue"
},
  "geometry": {"coordinates":[-75.63086800000001,39.739277],"type":"Point"}
}