{
  "type": "Feature",
  "properties": {
    "addr:full":"168 E Main St Newark DE 19711",
    "addr:housenumber":"168",
    "addr:postcode":"19711",
    "addr:street":"E Main St",
    "iso:country":"US",
    "sg:address":"168 E Main St",
    "sg:city":"Newark",
    "sg:classifiers":[
        {
            "category":"Restaurant",
            "type":"Food & Drink"
        }
    ],
    "sg:phone":"+1 302 731 1746",
    "sg:postcode":"19711",
    "sg:province":"DE",
    "sg:tags":[
        "parlor",
        "ice",
        "cream"
    ],
    "wof:name":"Cold Stone Creamery",
    "wof:placetype":"venue"
},
  "geometry": {"coordinates":[-75.74572000000001,39.683691],"type":"Point"}
}