{
  "type": "Feature",
  "properties": {
    "addr:full":"350 New Churchmans Rd New Castle DE 19720",
    "addr:housenumber":"350",
    "addr:postcode":"19720",
    "addr:street":"New Churchmans Rd New",
    "iso:country":"US",
    "sg:address":"350 New Churchmans Rd",
    "sg:city":"New Castle",
    "sg:classifiers":[
        {
            "category":"Insurance",
            "subcategory":"Insurance Agent",
            "type":"Services"
        }
    ],
    "sg:phone":"+1 302 322 9090",
    "sg:postcode":"19720",
    "sg:province":"DE",
    "sg:tags":[
        "adjuster"
    ],
    "wof:name":"GAB Robins",
    "wof:placetype":"venue"
},
  "geometry": {"coordinates":[-75.61780400000001,39.671999],"type":"Point"}
}