{
  "type": "Feature",
  "properties": {
    "iso:country":"US",
    "sg:address":"917 Janice Dr",
    "sg:city":"Newark",
    "sg:classifiers":[
        {
            "category":"Building & Trades",
            "subcategory":"Equipment Rental",
            "type":"Services"
        }
    ],
    "sg:phone":"+1 302 452 0502",
    "sg:postcode":"19713",
    "sg:province":"DE",
    "wof:name":"A Card In Yard With Stcks More",
    "wof:placetype":"venue"
},
  "geometry": {"coordinates":[-75.74740799999999,39.653974],"type":"Point"}
}