{
  "type": "Feature",
  "properties": {
    "addr:full":"3459 Harris Rd Townsend DE 19734",
    "addr:housenumber":"3459",
    "addr:postcode":"19734",
    "addr:street":"Harris Rd",
    "iso:country":"US",
    "sg:address":"3459 Harris Rd",
    "sg:city":"Townsend",
    "sg:classifiers":[
        {
            "category":"Home & Garden",
            "subcategory":"Building Materials",
            "type":"Retail Goods"
        }
    ],
    "sg:phone":"+1 302 834 1158",
    "sg:postcode":"19734",
    "sg:province":"DE",
    "sg:tags":[
        "glass",
        "window",
        "plate"
    ],
    "wof:name":"Newark Glass & Mirror",
    "wof:placetype":"venue"
},
  "geometry": {"coordinates":[-75.660006,39.433751],"type":"Point"}
}