{
  "type": "Feature",
  "properties": {
    "addr:full":"256 E Camden Wyoming Ave Camden Wyoming DE 19934",
    "addr:housenumber":"256",
    "addr:postcode":"19934",
    "addr:street":"E Camden Wyoming Ave",
    "iso:country":"US",
    "sg:address":"256 E Camden Wyoming Ave",
    "sg:city":"Camden Wyoming",
    "sg:classifiers":[
        {
            "category":"Personal",
            "subcategory":"Beauty Salon",
            "type":"Services"
        }
    ],
    "sg:phone":"+1 302 697 9066",
    "sg:postcode":"19934",
    "sg:province":"DE",
    "sg:tags":[
        "shop"
    ],
    "wof:name":"Looks Hair-Arts Studio",
    "wof:placetype":"venue"
},
  "geometry": {"coordinates":[-75.543987,39.11378],"type":"Point"}
}