{
  "type": "Feature",
  "properties": {
    "iso:country":"US",
    "sg:address":"126 Quigley Blvd",
    "sg:city":"New Castle",
    "sg:classifiers":[
        {
            "category":"Retail",
            "subcategory":"Repair Shop",
            "type":"Services"
        }
    ],
    "sg:phone":"+1 302 322 8870",
    "sg:postcode":"19720",
    "sg:province":"DE",
    "sg:tags":[
        "equipment",
        "conditioning",
        "air"
    ],
    "sg:website":"www.carrier.com",
    "wof:name":"Carrier Building Systems & Svc",
    "wof:placetype":"venue"
},
  "geometry": {"coordinates":[-75.603452,39.660613],"type":"Point"}
}