{
  "type": "Feature",
  "properties": {
    "iso:country":"US",
    "sg:address":"36 Glenrich Ave",
    "sg:city":"Wilmington",
    "sg:classifiers":[
        {
            "category":"Building & Trades",
            "subcategory":"Construction",
            "type":"Services"
        }
    ],
    "sg:phone":"+1 302 778 4415",
    "sg:postcode":"19804",
    "sg:province":"DE",
    "sg:tags":[
        "resurfacing",
        "laying",
        "refinishing",
        "floor"
    ],
    "wof:name":"B & S Flooring Inc",
    "wof:placetype":"venue"
},
  "geometry": {"coordinates":[-75.585776,39.731832],"type":"Point"}
}