{
  "type": "Feature",
  "properties": {
    "addr:full":"1093 S Governors Ave Dover DE 19904",
    "addr:housenumber":"1093",
    "addr:postcode":"19904",
    "addr:street":"S Governors Ave",
    "iso:country":"US",
    "sg:address":"1093 S Governors Ave",
    "sg:city":"Dover",
    "sg:classifiers":[
        {
            "category":"Health Services",
            "subcategory":"Doctor",
            "type":"Services"
        }
    ],
    "sg:phone":"+1 302 734 5600",
    "sg:postcode":"19904",
    "sg:province":"DE",
    "sg:tags":[
        "physician",
        "surgeon"
    ],
    "wof:name":"Pain Treatment Ctr Of Dover",
    "wof:placetype":"venue"
},
  "geometry": {"coordinates":[-75.525615,39.140633],"type":"Point"}
}