{
  "type": "Feature",
  "properties": {
    "addr:full":"3113 High St Dover DE 19901",
    "addr:housenumber":"3113",
    "addr:postcode":"19901",
    "addr:street":"High St",
    "iso:country":"US",
    "sg:address":"3113 High St",
    "sg:city":"Dover",
    "sg:classifiers":[
        {
            "category":"Government",
            "subcategory":"Office",
            "type":"Public Place"
        }
    ],
    "sg:phone":"+1 302 730 8572",
    "sg:postcode":"19901",
    "sg:province":"DE",
    "sg:tags":[
        "test",
        "administrator"
    ],
    "wof:name":"June Haylock",
    "wof:placetype":"venue"
},
  "geometry": {"coordinates":[-75.487618,39.12129],"type":"Point"}
}