{
  "type": "Feature",
  "properties": {
    "iso:country":"US",
    "sg:address":"701 McColley St",
    "sg:city":"Milford",
    "sg:classifiers":[
        {
            "category":"Home & Garden",
            "subcategory":"Building Materials",
            "type":"Retail Goods"
        }
    ],
    "sg:phone":"+1 302 424 3650",
    "sg:postcode":"19963",
    "sg:province":"DE",
    "wof:name":"Key Builders Supply Co",
    "wof:placetype":"venue"
},
  "geometry": {"coordinates":[-75.42432700000001,38.903043],"type":"Point"}
}