{
  "type": "Feature",
  "properties": {
    "iso:country":"US",
    "sg:address":"2210 Amhurst Rd",
    "sg:city":"Wilmington",
    "sg:classifiers":[
        {
            "category":"Professional",
            "type":"Services"
        }
    ],
    "sg:phone":"+1 302 655 1155",
    "sg:postcode":"19803",
    "sg:province":"DE",
    "wof:name":"Gary Del Matto",
    "wof:placetype":"venue"
},
  "geometry": {"coordinates":[-75.543781,39.79336],"type":"Point"}
}