{
  "type": "Feature",
  "properties": {
    "iso:country":"US",
    "sg:address":"5000 Limestone Rd",
    "sg:city":"Wilmington",
    "sg:classifiers":[
        {
            "category":"Building & Trades",
            "subcategory":"Plumbing",
            "type":"Services"
        },
        {
            "category":"Building & Trades",
            "subcategory":"Construction",
            "type":"Services"
        }
    ],
    "sg:phone":"+1 302 234 8020",
    "sg:postcode":"19808",
    "sg:province":"DE",
    "sg:tags":[
        "plumber",
        "industrial",
        "system",
        "specialty",
        "heating",
        "contractors-commercial",
        "contractor",
        "air conditioning"
    ],
    "wof:name":"James Scalia Plumbing & Htg",
    "wof:placetype":"venue"
},
  "geometry": {"coordinates":[-75.693793,39.742662],"type":"Point"}
}