{
  "type": "Feature",
  "properties": {
    "iso:country":"US",
    "sg:address":"1401 N Clayton St",
    "sg:city":"Wilmington",
    "sg:classifiers":[
        {
            "category":"Building & Trades",
            "subcategory":"Landscaping Services",
            "type":"Services"
        }
    ],
    "sg:phone":"+1 302 777 7118",
    "sg:postcode":"19806",
    "sg:province":"DE",
    "sg:tags":[
        "landscape"
    ],
    "wof:name":"Greens In Regulation",
    "wof:placetype":"venue"
},
  "geometry": {"coordinates":[-75.56156300000001,39.756956],"type":"Point"}
}