{
  "type": "Feature",
  "properties": {
    "addr:full":"838 E Loockerman St Dover DE 19901",
    "addr:housenumber":"838",
    "addr:postcode":"19901",
    "addr:street":"E Loockerman St",
    "iso:country":"US",
    "sg:address":"838 E Loockerman St",
    "sg:city":"Dover",
    "sg:classifiers":[
        {
            "category":"Transit Center",
            "subcategory":"Freight",
            "type":"Transportation"
        },
        {
            "category":"Freight",
            "type":"Transportation"
        }
    ],
    "sg:phone":"+1 302 724 4254",
    "sg:postcode":"19901",
    "sg:province":"DE",
    "sg:tags":[
        "trucking-motor",
        "trucking"
    ],
    "wof:name":"Diamond Transport Incorporated",
    "wof:placetype":"venue"
},
  "geometry": {"coordinates":[-75.50814099999999,39.165054],"type":"Point"}
}