{
  "type": "Feature",
  "properties": {
    "addr:full":"12 W Rivers End Dr Claymont DE 19703",
    "addr:housenumber":"12",
    "addr:postcode":"19703",
    "addr:street":"W Rivers End Dr",
    "iso:country":"US",
    "sg:address":"12 W Rivers End Dr",
    "sg:city":"Claymont",
    "sg:classifiers":[
        {
            "category":"Social Services",
            "subcategory":"Child Care",
            "type":"Services"
        }
    ],
    "sg:phone":"+1 302 792 0542",
    "sg:postcode":"19703",
    "sg:province":"DE",
    "sg:tags":[
        "day"
    ],
    "wof:name":"Mrs TS Pre-Sch and Day Care",
    "wof:placetype":"venue"
},
  "geometry": {"coordinates":[-75.46647299999999,39.793631],"type":"Point"}
}