{
  "type": "Feature",
  "properties": {
    "iso:country":"US",
    "sg:address":"1116 Creekside Dr",
    "sg:city":"Wilmington",
    "sg:classifiers":[
        {
            "category":"Real Estate",
            "subcategory":"Real Estate Operator",
            "type":"Services"
        }
    ],
    "sg:phone":"+1 302 994 6182",
    "sg:postcode":"19804",
    "sg:province":"DE",
    "sg:tags":[
        "apartment"
    ],
    "wof:name":"Arbor Pointe Apartments",
    "wof:placetype":"venue"
},
  "geometry": {"coordinates":[-75.64527200000001,39.710195],"type":"Point"}
}