{
  "type": "Feature",
  "properties": {
    "iso:country":"US",
    "sg:address":"44 Spruance Rd",
    "sg:city":"Dover",
    "sg:classifiers":[
        {
            "category":"Real Estate",
            "subcategory":"Real Estate Services",
            "type":"Services"
        }
    ],
    "sg:phone":"+1 302 678 5203",
    "sg:postcode":"19901",
    "sg:province":"DE",
    "sg:tags":[
        "buyer",
        "broker"
    ],
    "wof:name":"Petersons Rl Enterprises",
    "wof:placetype":"venue"
},
  "geometry": {"coordinates":[-75.507757,39.166886],"type":"Point"}
}