{
  "type": "Feature",
  "properties": {
    "iso:country":"US",
    "sg:address":"9 E Aldine Dr",
    "sg:city":"Hockessin",
    "sg:classifiers":[
        {
            "category":"Professional",
            "subcategory":"Management & Consulting",
            "type":"Services"
        }
    ],
    "sg:phone":"+1 302 234 0723",
    "sg:postcode":"19707",
    "sg:province":"DE",
    "sg:tags":[
        "business"
    ],
    "wof:name":"System Strategies",
    "wof:placetype":"venue"
},
  "geometry": {"coordinates":[-75.67092,39.785348],"type":"Point"}
}