{
  "type": "Feature",
  "properties": {
    "iso:country":"US",
    "sg:address":"1035 Philadelphia Pike",
    "sg:city":"Wilmington",
    "sg:classifiers":[
        {
            "category":"Professional",
            "subcategory":"Management & Consulting",
            "type":"Services"
        }
    ],
    "sg:phone":"+1 302 798 9404",
    "sg:postcode":"19809",
    "sg:province":"DE",
    "sg:tags":[
        "contracting"
    ],
    "wof:name":"Tsi Compliance Services Inc",
    "wof:placetype":"venue"
},
  "geometry": {"coordinates":[-75.484685,39.78053],"type":"Point"}
}