{
  "type": "Feature",
  "properties": {
    "iso:country":"US",
    "sg:address":"1910 Limestone Rd",
    "sg:city":"Wilmington",
    "sg:classifiers":[
        {
            "category":"Shopping",
            "subcategory":"Hobbies, Toys, & Games",
            "type":"Retail Goods"
        }
    ],
    "sg:phone":"+1 302 993 1140",
    "sg:postcode":"19804",
    "sg:province":"DE",
    "wof:name":"Mary's Secret Garden",
    "wof:placetype":"venue"
},
  "geometry": {"coordinates":[-75.65281899999999,39.718318],"type":"Point"}
}