{
  "type": "Feature",
  "properties": {
    "addr:full":"102 Delaware Ave Bridgeville DE 19933",
    "addr:housenumber":"102",
    "addr:postcode":"19933",
    "addr:street":"Delaware Ave",
    "iso:country":"US",
    "sg:address":"102 Delaware Ave",
    "sg:city":"Bridgeville",
    "sg:classifiers":[
        {
            "category":"Professional",
            "subcategory":"Computer Services",
            "type":"Services"
        }
    ],
    "sg:phone":"+1 302 337 0319",
    "sg:postcode":"19933",
    "sg:province":"DE",
    "sg:tags":[
        "related"
    ],
    "wof:name":"P C Team",
    "wof:placetype":"venue"
},
  "geometry": {"coordinates":[-75.59908900000001,38.742993],"type":"Point"}
}