{
  "type": "Feature",
  "properties": {
    "addr:full":"410 Junction St Wilmington DE 19805",
    "addr:housenumber":"410",
    "addr:postcode":"19805",
    "addr:street":"Junction St",
    "iso:country":"US",
    "sg:address":"410 Junction St",
    "sg:city":"Wilmington",
    "sg:classifiers":[
        {
            "category":"Restaurant",
            "type":"Food & Drink"
        }
    ],
    "sg:phone":"+1 302 633 4862",
    "sg:postcode":"19805",
    "sg:province":"DE",
    "sg:tags":[
        "eating"
    ],
    "wof:name":"Rockys Place",
    "wof:placetype":"venue"
},
  "geometry": {"coordinates":[-75.59111799999999,39.740843],"type":"Point"}
}