{
  "type": "Feature",
  "properties": {
    "iso:country":"US",
    "sg:address":"145 S Dual Hwy",
    "sg:city":"Laurel",
    "sg:classifiers":[
        {
            "category":"Retail",
            "subcategory":"Auto Repair",
            "type":"Services"
        }
    ],
    "sg:phone":"+1 302 875 1223",
    "sg:postcode":"19956",
    "sg:province":"DE",
    "sg:tags":[
        "repairing",
        "automobile"
    ],
    "wof:name":"Xpert Performance LTD",
    "wof:placetype":"venue"
},
  "geometry": {"coordinates":[-75.557799,38.562633],"type":"Point"}
}