{
  "type": "Feature",
  "properties": {
    "iso:country":"US",
    "sg:address":"741 S Market St",
    "sg:city":"Wilmington",
    "sg:classifiers":[
        {
            "category":"Wholesale",
            "subcategory":"Auto Parts",
            "type":"Manufacturing & Wholesale Goods"
        }
    ],
    "sg:phone":"+1 302 658 4697",
    "sg:postcode":"19801",
    "sg:province":"DE",
    "sg:tags":[
        "automobile",
        "rebuilt"
    ],
    "wof:name":"Casper's Auto Parts",
    "wof:placetype":"venue"
},
  "geometry": {"coordinates":[-75.55615299999999,39.731796],"type":"Point"}
}