{
  "type": "Feature",
  "properties": {
    "addr:full":"1207 E State St Delmar DE 21875",
    "addr:housenumber":"1207",
    "addr:postcode":"21875",
    "addr:street":"E State St",
    "iso:country":"US",
    "sg:address":"1207 E State St",
    "sg:city":"Delmar",
    "sg:classifiers":[
        {
            "category":"Organizations",
            "subcategory":"Religious Organization",
            "type":"Services"
        }
    ],
    "sg:phone":"+1 410 896 9162",
    "sg:postcode":"21875",
    "sg:province":"DE",
    "sg:tags":[
        "church"
    ],
    "wof:name":"Faith Baptist Church",
    "wof:placetype":"venue"
},
  "geometry": {"coordinates":[-75.561351,38.455535],"type":"Point"}
}