{
  "type": "Feature",
  "properties": {
    "addr:full":"26 Montvale Rd Newark DE 19713",
    "addr:housenumber":"26",
    "addr:postcode":"19713",
    "addr:street":"Montvale Rd",
    "iso:country":"US",
    "sg:address":"26 Montvale Rd",
    "sg:city":"Newark",
    "sg:classifiers":[
        {
            "category":"Professional",
            "type":"Services"
        }
    ],
    "sg:phone":"+1 302 369 8584",
    "sg:postcode":"19713",
    "sg:province":"DE",
    "wof:name":"Leonard Love Facsimile",
    "wof:placetype":"venue"
},
  "geometry": {"coordinates":[-75.72995400000001,39.66557],"type":"Point"}
}