{
  "type": "Feature",
  "properties": {
    "addr:full":"20735 Coastal Hwy Rehoboth Beach DE 19971",
    "addr:housenumber":"20735",
    "addr:postcode":"19971",
    "addr:street":"Coastal Hwy",
    "iso:country":"US",
    "sg:address":"20735 Coastal Hwy",
    "sg:city":"Rehoboth Beach",
    "sg:classifiers":[
        {
            "category":"Personal",
            "subcategory":"Beauty Salon",
            "type":"Services"
        }
    ],
    "sg:phone":"+1 302 227 3861",
    "sg:postcode":"19971",
    "sg:province":"DE",
    "sg:tags":[
        "shop"
    ],
    "wof:name":"Boires Hair Design",
    "wof:placetype":"venue"
},
  "geometry": {"coordinates":[-75.08387999999999,38.703289],"type":"Point"}
}