{
  "type": "Feature",
  "properties": {
    "iso:country":"US",
    "sg:address":"307 N Bedford St",
    "sg:city":"Georgetown",
    "sg:classifiers":[
        {
            "category":"Retail",
            "subcategory":"Funeral Services",
            "type":"Services"
        }
    ],
    "sg:phone":"+1 302 856 2880",
    "sg:postcode":"19947",
    "sg:province":"DE",
    "wof:name":"Parsell Dodd & Carey Funeral",
    "wof:placetype":"venue"
},
  "geometry": {"coordinates":[-75.38963,38.69318],"type":"Point"}
}