{
  "type": "Feature",
  "properties": {
    "iso:country":"US",
    "sg:address":"347 State Rd 24",
    "sg:city":"Lewes",
    "sg:classifiers":[
        {
            "category":"Travel",
            "subcategory":"Hotels & Motels",
            "type":"Entertainment"
        }
    ],
    "sg:phone":"+1 302 945 7462",
    "sg:postcode":"19958",
    "sg:province":"DE",
    "sg:tags":[
        "operation"
    ],
    "wof:name":"Boat Hole Cottages",
    "wof:placetype":"venue"
},
  "geometry": {"coordinates":[-75.17487800000001,38.692567],"type":"Point"}
}