{
  "type": "Feature",
  "properties": {
    "iso:country":"US",
    "sg:address":"215 W Loockerman St",
    "sg:city":"Dover",
    "sg:classifiers":[
        {
            "category":"Shopping",
            "subcategory":"Clothing, Apparel, & Fashions",
            "type":"Retail Goods"
        }
    ],
    "sg:phone":"+1 302 678 8160",
    "sg:postcode":"19904",
    "sg:province":"DE",
    "sg:tags":[
        "shop",
        "bridal"
    ],
    "sg:website":"www.simonsbridal.com",
    "wof:name":"Simon's Bridal Shoppe",
    "wof:placetype":"venue"
},
  "geometry": {"coordinates":[-75.527298,39.157501],"type":"Point"}
}