{
  "type": "Feature",
  "properties": {
    "iso:country":"US",
    "sg:address":"5 W Main St",
    "sg:city":"Newark",
    "sg:classifiers":[
        {
            "category":"Retail",
            "subcategory":"Repair Shop",
            "type":"Services"
        }
    ],
    "sg:phone":"+1 302 738 1212",
    "sg:postcode":"19702",
    "sg:province":"DE",
    "wof:name":"Lindells Grandfather Cloc",
    "wof:placetype":"venue"
},
  "geometry": {"coordinates":[-75.66035100000001,39.665548],"type":"Point"}
}