{
  "type": "Feature",
  "properties": {
    "iso:country":"US",
    "sg:address":"2414 Grubb Rd",
    "sg:city":"Edgemoor",
    "sg:classifiers":[
        {
            "category":"Building & Trades",
            "subcategory":"Construction",
            "type":"Services"
        }
    ],
    "sg:phone":"+1 302 475 9544",
    "sg:postcode":"19810",
    "sg:province":"DE",
    "sg:tags":[
        "general",
        "contractor"
    ],
    "wof:name":"Matruder Construction Inc",
    "wof:placetype":"venue"
},
  "geometry": {"coordinates":[-75.503912,39.815673],"type":"Point"}
}