{
  "type": "Feature",
  "properties": {
    "addr:full":"44 Hidden Valley Dr Newark DE 19711",
    "addr:housenumber":"44",
    "addr:postcode":"19711",
    "addr:street":"Hidden Valley Dr",
    "iso:country":"US",
    "sg:address":"44 Hidden Valley Dr",
    "sg:city":"Newark",
    "sg:classifiers":[
        {
            "category":"Shopping",
            "subcategory":"Tobacco",
            "type":"Retail Goods"
        }
    ],
    "sg:phone":"+1 302 366 8934",
    "sg:postcode":"19711",
    "sg:province":"DE",
    "sg:tags":[
        "product"
    ],
    "wof:name":"News Basket",
    "wof:placetype":"venue"
},
  "geometry": {"coordinates":[-75.778792,39.694248],"type":"Point"}
}