{
  "type": "Feature",
  "properties": {
    "iso:country":"US",
    "sg:address":"3707 N Market St",
    "sg:city":"Wilmington",
    "sg:classifiers":[
        {
            "category":"Organizations",
            "subcategory":"Membership Organization",
            "type":"Services"
        }
    ],
    "sg:phone":"+1 302 764 6170",
    "sg:postcode":"19802",
    "sg:province":"DE",
    "sg:tags":[
        "athletic"
    ],
    "wof:name":"Police Athletic League-Wlmngtn",
    "wof:placetype":"venue"
},
  "geometry": {"coordinates":[-75.524711,39.759622],"type":"Point"}
}