{
  "type": "Feature",
  "properties": {
    "addr:full":"52 W Commerce St Smyrna DE 19977",
    "addr:housenumber":"52",
    "addr:postcode":"19977",
    "addr:street":"W Commerce St",
    "iso:country":"US",
    "sg:address":"52 W Commerce St",
    "sg:city":"Smyrna",
    "sg:classifiers":[
        {
            "category":"Personal",
            "subcategory":"Beauty Salon",
            "type":"Services"
        }
    ],
    "sg:phone":"+1 302 653 4559",
    "sg:postcode":"19977",
    "sg:province":"DE",
    "sg:tags":[
        "shop"
    ],
    "wof:name":"Miss Shirley's",
    "wof:placetype":"venue"
},
  "geometry": {"coordinates":[-75.607568,39.29998],"type":"Point"}
}