{
  "type": "Feature",
  "properties": {
    "iso:country":"US",
    "sg:address":"112 Cheltenham Rd",
    "sg:city":"Newark",
    "sg:classifiers":[
        {
            "category":"Professional",
            "subcategory":"Accounting & Tax Preparation",
            "type":"Services"
        }
    ],
    "sg:phone":"+1 302 731 4427",
    "sg:postcode":"19711",
    "sg:province":"DE",
    "wof:name":"Alma Company",
    "wof:placetype":"venue"
},
  "geometry": {"coordinates":[-75.76303299999999,39.682429],"type":"Point"}
}