{
  "type": "Feature",
  "properties": {
    "iso:country":"US",
    "sg:address":"1412 Kirkwood Hwy",
    "sg:city":"Wilmington",
    "sg:classifiers":[
        {
            "category":"Manufacturing",
            "subcategory":"Apparel",
            "type":"Manufacturing & Wholesale Goods"
        }
    ],
    "sg:phone":"+1 302 999 0562",
    "sg:postcode":"19805",
    "sg:province":"DE",
    "sg:tags":[
        "embroidery",
        "custom"
    ],
    "wof:name":"Initially Yours Inc",
    "wof:placetype":"venue"
},
  "geometry": {"coordinates":[-75.60338900000001,39.738777],"type":"Point"}
}