{
  "type": "Feature",
  "properties": {
    "addr:full":"148 Sunset Blvd New Castle DE 19720",
    "addr:housenumber":"148",
    "addr:postcode":"19720",
    "addr:street":"Sunset Blvd",
    "iso:country":"US",
    "sg:address":"148 Sunset Blvd",
    "sg:city":"New Castle",
    "sg:classifiers":[
        {
            "category":"Restaurant",
            "type":"Food & Drink"
        }
    ],
    "sg:menulink":"http://www.allmenus.com/de/new-castle/107332-soup-man/menu/",
    "sg:phone":"+1 302 323 9610",
    "sg:postcode":"19720",
    "sg:province":"DE",
    "sg:tags":[
        "soup",
        "american",
        "salad"
    ],
    "wof:name":"Soup Man",
    "wof:placetype":"venue"
},
  "geometry": {"coordinates":[-75.59753499999999,39.671117],"type":"Point"}
}