{
  "type": "Feature",
  "properties": {
    "addr:full":"1012 Wilmington Ave Wilmington DE 19805",
    "addr:housenumber":"1012",
    "addr:postcode":"19805",
    "addr:street":"Wilmington Ave",
    "iso:country":"US",
    "sg:address":"1012 Wilmington Ave",
    "sg:city":"Wilmington",
    "sg:classifiers":[
        {
            "category":"Restaurant",
            "type":"Food & Drink"
        }
    ],
    "sg:menulink":"http://www.allmenus.com/de/lower-christiana/109729-subway/menu/",
    "sg:phone":"+1 302 993 9060",
    "sg:postcode":"19805",
    "sg:province":"DE",
    "sg:tags":[
        "american",
        "sandwich"
    ],
    "wof:name":"Subway",
    "wof:placetype":"venue"
},
  "geometry": {"coordinates":[-75.598079,39.739173],"type":"Point"}
}