{
  "type": "Feature",
  "properties": {
    "iso:country":"US",
    "sg:address":"913 Constance Ct",
    "sg:city":"Wilmington",
    "sg:classifiers":[
        {
            "category":"Professional",
            "subcategory":"Management & Consulting",
            "type":"Services"
        }
    ],
    "sg:phone":"+1 302 994 5744",
    "sg:postcode":"19808",
    "sg:province":"DE",
    "sg:tags":[
        "marketing"
    ],
    "wof:name":"Futura Marketing Inc",
    "wof:placetype":"venue"
},
  "geometry": {"coordinates":[-75.651437,39.755968],"type":"Point"}
}