{
  "type": "Feature",
  "properties": {
    "iso:country":"US",
    "sg:address":"2000 Baynard Blvd",
    "sg:city":"Wilmington",
    "sg:classifiers":[
        {
            "category":"Health Services",
            "subcategory":"Doctor",
            "type":"Services"
        }
    ],
    "sg:phone":"+1 302 654 1200",
    "sg:postcode":"19802",
    "sg:province":"DE",
    "sg:tags":[
        "medical"
    ],
    "wof:name":"Harold Friedman DPM",
    "wof:placetype":"venue"
},
  "geometry": {"coordinates":[-75.54525099999999,39.756814],"type":"Point"}
}