{
  "type": "Feature",
  "properties": {
    "iso:country":"US",
    "sg:address":"35 Albe Dr",
    "sg:city":"Newark",
    "sg:classifiers":[
        {
            "category":"Building & Trades",
            "subcategory":"Construction",
            "type":"Services"
        }
    ],
    "sg:phone":"+1 302 283 0600",
    "sg:postcode":"19702",
    "sg:province":"DE",
    "sg:tags":[
        "contractor"
    ],
    "wof:name":"Thomas Building Group",
    "wof:placetype":"venue"
},
  "geometry": {"coordinates":[-75.71480099999999,39.648105],"type":"Point"}
}