{
  "type": "Feature",
  "properties": {
    "iso:country":"US",
    "sg:address":"101 School Rd",
    "sg:city":"Wilmington",
    "sg:classifiers":[
        {
            "category":"Education",
            "subcategory":"School",
            "type":"Public Place"
        }
    ],
    "sg:phone":"+1 302 576 2900",
    "sg:postcode":"19803",
    "sg:province":"DE",
    "sg:tags":[
        "organization",
        "religious"
    ],
    "sg:website":"www.wilmingtonfriends.org",
    "wof:name":"Wilmington Friends School Inc",
    "wof:placetype":"venue"
},
  "geometry": {"coordinates":[-75.549161,39.768772],"type":"Point"}
}