{
  "type": "Feature",
  "properties": {
    "iso:country":"US",
    "sg:address":"300 S New St",
    "sg:city":"Dover",
    "sg:classifiers":[
        {
            "category":"Government",
            "subcategory":"Office",
            "type":"Public Place"
        }
    ],
    "sg:phone":"+1 302 674 5162",
    "sg:postcode":"19904",
    "sg:province":"DE",
    "sg:tags":[
        "federal",
        "human"
    ],
    "wof:name":"US Social Security Adm",
    "wof:placetype":"venue"
},
  "geometry": {"coordinates":[-75.527805,39.1564],"type":"Point"}
}