{
  "type": "Feature",
  "properties": {
    "addr:full":"273 Chapman Rd Newark DE 19702",
    "addr:housenumber":"273",
    "addr:postcode":"19702",
    "addr:street":"Chapman Rd",
    "iso:country":"US",
    "sg:address":"273 Chapman Rd",
    "sg:city":"Newark",
    "sg:classifiers":[
        {
            "category":"Shopping",
            "subcategory":"Crafts & Fabrics",
            "type":"Retail Goods"
        }
    ],
    "sg:phone":"+1 302 737 2759",
    "sg:postcode":"19702",
    "sg:province":"DE",
    "sg:tags":[
        "sewing"
    ],
    "wof:name":"Jo-Ann Fabrics & Crafts",
    "wof:placetype":"venue"
},
  "geometry": {"coordinates":[-75.672876,39.667957],"type":"Point"}
}