{
  "type": "Feature",
  "properties": {
    "iso:country":"US",
    "sg:address":"2711 Centerville Rd",
    "sg:city":"Wilmington",
    "sg:classifiers":[
        {
            "category":"Professional",
            "subcategory":"Management & Consulting",
            "type":"Services"
        }
    ],
    "sg:phone":"+1 361 884 1961",
    "sg:postcode":"19808",
    "sg:province":"DE",
    "wof:name":"Right Away Management Corp",
    "wof:placetype":"venue"
},
  "geometry": {"coordinates":[-75.62527799999999,39.756113],"type":"Point"}
}