{
  "type": "Feature",
  "properties": {
    "addr:full":"4 Denny Rd Wilmington DE 19809",
    "addr:housenumber":"4",
    "addr:postcode":"19809",
    "addr:street":"Denny Rd",
    "iso:country":"US",
    "sg:address":"4 Denny Rd",
    "sg:city":"Wilmington",
    "sg:classifiers":[
        {
            "category":"Professional",
            "type":"Services"
        },
        {
            "category":"Professional",
            "subcategory":"Management & Consulting",
            "type":"Services"
        }
    ],
    "sg:phone":"+1 302 765 3630",
    "sg:postcode":"19809",
    "sg:province":"DE",
    "sg:tags":[
        "consultant"
    ],
    "wof:name":"Venturesoftnet Inc",
    "wof:placetype":"venue"
},
  "geometry": {"coordinates":[-75.50549100000001,39.755504],"type":"Point"}
}