{
  "type": "Feature",
  "properties": {
    "iso:country":"US",
    "sg:address":"600 Delaware Ave",
    "sg:city":"Wilmington",
    "sg:phone":"+1 302 575 0400",
    "sg:postcode":"19801",
    "sg:province":"DE",
    "sg:website":"http://www.cielo-ss.com",
    "wof:name":"Cielo Salon & Spa Inc",
    "wof:placetype":"venue"
},
  "geometry": {"coordinates":[-75.55220799999999,39.748581],"type":"Point"}
}