{
  "type": "Feature",
  "properties": {
    "addr:full":"230 Peoples Way Hockessin DE 19707",
    "addr:housenumber":"230",
    "addr:postcode":"19707",
    "addr:street":"Peoples Way",
    "iso:country":"US",
    "sg:address":"230 Peoples Way",
    "sg:city":"Hockessin",
    "sg:classifiers":[
        {
            "category":"Professional",
            "subcategory":"Management & Consulting",
            "type":"Services"
        }
    ],
    "sg:phone":"+1 302 239 1162",
    "sg:postcode":"19707",
    "sg:province":"DE",
    "sg:tags":[
        "brokerage",
        "financial",
        "mortgage"
    ],
    "wof:name":"Csi Financial Services",
    "wof:placetype":"venue"
},
  "geometry": {"coordinates":[-75.69883299999999,39.773385],"type":"Point"}
}