{
  "type": "Feature",
  "properties": {
    "addr:full":"16 Pleasant Pl New Castle DE 19720",
    "addr:housenumber":"16",
    "addr:postcode":"19720",
    "addr:street":"Pleasant Pl",
    "iso:country":"US",
    "sg:address":"16 Pleasant Pl",
    "sg:city":"New Castle",
    "sg:classifiers":[
        {
            "category":"Education",
            "subcategory":"School",
            "type":"Public Place"
        }
    ],
    "sg:phone":"+1 302 323 2935",
    "sg:postcode":"19720",
    "sg:province":"DE",
    "wof:name":"Pleasantville Elementary Schl",
    "wof:placetype":"venue"
},
  "geometry": {"coordinates":[-75.62501899999999,39.666468],"type":"Point"}
}