{
  "type": "Feature",
  "properties": {
    "addr:full":"4300 Lancaster Pike Wilmington DE 19805",
    "addr:housenumber":"4300",
    "addr:postcode":"19805",
    "addr:street":"Lancaster Pike",
    "iso:country":"US",
    "sg:address":"4300 Lancaster Pike",
    "sg:city":"Wilmington",
    "sg:classifiers":[
        {
            "category":"Personal",
            "subcategory":"Barber",
            "type":"Services"
        }
    ],
    "sg:phone":"+1 302 999 8059",
    "sg:postcode":"19805",
    "sg:province":"DE",
    "sg:tags":[
        "shop",
        "beauty"
    ],
    "wof:name":"Cuts & Styles Barley Mill Inc",
    "wof:placetype":"venue"
},
  "geometry": {"coordinates":[-75.60423,39.758694],"type":"Point"}
}