{
  "type": "Feature",
  "properties": {
    "addr:full":"511 Philadelphia Pike Wilmington DE 19809",
    "addr:housenumber":"511",
    "addr:postcode":"19809",
    "addr:street":"Philadelphia Pike",
    "iso:country":"US",
    "sg:address":"511 Philadelphia Pike",
    "sg:city":"Wilmington",
    "sg:classifiers":[
        {
            "category":"Personal",
            "subcategory":"Barber",
            "type":"Services"
        }
    ],
    "sg:phone":"+1 302 764 2744",
    "sg:postcode":"19809",
    "sg:province":"DE",
    "wof:name":"Ralph's Scissors Sensations",
    "wof:placetype":"venue"
},
  "geometry": {"coordinates":[-75.506721,39.767773],"type":"Point"}
}