{
  "type": "Feature",
  "properties": {
    "addr:full":"1415 N Clayton St Wilmington DE 19806",
    "addr:housenumber":"1415",
    "addr:postcode":"19806",
    "addr:street":"N Clayton St",
    "iso:country":"US",
    "sg:address":"1415 N Clayton St",
    "sg:city":"Wilmington",
    "sg:classifiers":[
        {
            "category":"Professional",
            "subcategory":"Computer Services",
            "type":"Services"
        }
    ],
    "sg:phone":"+1 302 658 3421",
    "sg:postcode":"19806",
    "sg:province":"DE",
    "sg:tags":[
        "development",
        "software"
    ],
    "wof:name":"Codrian Inc",
    "wof:placetype":"venue"
},
  "geometry": {"coordinates":[-75.561701,39.756853],"type":"Point"}
}