{
  "type": "Feature",
  "properties": {
    "addr:full":"1316 Shallcross Ave Wilmington DE 19806",
    "addr:housenumber":"1316",
    "addr:postcode":"19806",
    "addr:street":"Shallcross Ave",
    "iso:country":"US",
    "sg:address":"1316 Shallcross Ave",
    "sg:city":"Wilmington",
    "sg:classifiers":[
        {
            "category":"Professional",
            "subcategory":"Computer Services",
            "type":"Services"
        }
    ],
    "sg:phone":"+1 302 661 2557",
    "sg:postcode":"19806",
    "sg:province":"DE",
    "sg:tags":[
        "datum"
    ],
    "wof:name":"Intouch Design Communications",
    "wof:placetype":"venue"
},
  "geometry": {"coordinates":[-75.55765599999999,39.756589],"type":"Point"}
}