{
  "type": "Feature",
  "properties": {
    "addr:full":"1200 Willow Grove Rd Felton DE 19943",
    "addr:housenumber":"1200",
    "addr:postcode":"19943",
    "addr:street":"Willow Grove Rd",
    "iso:country":"US",
    "sg:address":"1200 Willow Grove Rd",
    "sg:city":"Felton",
    "sg:classifiers":[
        {
            "category":"Food & Beverages",
            "subcategory":"Groceries & Convenience Stores",
            "type":"Retail Goods"
        }
    ],
    "sg:phone":"+1 302 284 3866",
    "sg:postcode":"19943",
    "sg:province":"DE",
    "sg:tags":[
        "station",
        "gasoline"
    ],
    "wof:name":"Country Cupboard The",
    "wof:placetype":"venue"
},
  "geometry": {"coordinates":[-75.726632,39.032394],"type":"Point"}
}