{
  "type": "Feature",
  "properties": {
    "addr:full":"701 Bridgeville Hwy Seaford DE 19973",
    "addr:housenumber":"701",
    "addr:postcode":"19973",
    "addr:street":"Bridgeville Hwy",
    "iso:country":"US",
    "sg:address":"701 Bridgeville Hwy",
    "sg:city":"Seaford",
    "sg:classifiers":[
        {
            "category":"Organizations",
            "subcategory":"Religious Organization",
            "type":"Services"
        }
    ],
    "sg:phone":"+1 302 629 9077",
    "sg:postcode":"19973",
    "sg:province":"DE",
    "sg:tags":[
        "church"
    ],
    "wof:name":"Seaford Presbyterian Church",
    "wof:placetype":"venue"
},
  "geometry": {"coordinates":[-75.60604600000001,38.651095],"type":"Point"}
}