{
  "type": "Feature",
  "properties": {
    "addr:full":"1600 E Newport Pike Wilmington DE 19804",
    "addr:housenumber":"1600",
    "addr:postcode":"19804",
    "addr:street":"E Newport Pike",
    "iso:country":"US",
    "sg:address":"1600 E Newport Pike",
    "sg:city":"Wilmington",
    "sg:classifiers":[
        {
            "category":"Professional",
            "type":"Services"
        }
    ],
    "sg:phone":"+1 302 998 6300",
    "sg:postcode":"19804",
    "sg:province":"DE",
    "wof:name":"Wharton & Barnard Inc",
    "wof:placetype":"venue"
},
  "geometry": {"coordinates":[-75.603821,39.715944],"type":"Point"}
}