{
  "type": "Feature",
  "properties": {
    "addr:full":"1010 Wright St Wilmington DE 19805",
    "addr:housenumber":"1010",
    "addr:postcode":"19805",
    "addr:street":"Wright St",
    "iso:country":"US",
    "sg:address":"1010 Wright St",
    "sg:city":"Wilmington",
    "sg:classifiers":[
        {
            "category":"Wholesale",
            "subcategory":"Groceries",
            "type":"Manufacturing & Wholesale Goods"
        }
    ],
    "sg:phone":"+1 302 425 5453",
    "sg:postcode":"19805",
    "sg:province":"DE",
    "wof:name":"Italian Delights & More I",
    "wof:placetype":"venue"
},
  "geometry": {"coordinates":[-75.56859300000001,39.734048],"type":"Point"}
}