{
  "type": "Feature",
  "properties": {
    "iso:country":"US",
    "sg:address":"3847 Evelyn Dr",
    "sg:city":"Wilmington",
    "sg:classifiers":[
        {
            "category":"Organizations",
            "subcategory":"Labor Organization",
            "type":"Services"
        }
    ],
    "sg:phone":"+1 302 999 0412",
    "sg:postcode":"19808",
    "sg:province":"DE",
    "wof:name":"Uswa",
    "wof:placetype":"venue"
},
  "geometry": {"coordinates":[-75.644092,39.736214],"type":"Point"}
}