{
  "type": "Feature",
  "properties": {
    "iso:country":"US",
    "sg:address":"10 8th Ave",
    "sg:city":"Wilmington",
    "sg:classifiers":[
        {
            "category":"Insurance",
            "subcategory":"Hazard Insurance",
            "type":"Services"
        }
    ],
    "sg:phone":"+1 302 893 4220",
    "sg:postcode":"19805",
    "sg:province":"DE",
    "sg:tags":[
        "warranty",
        "automobile",
        "processing"
    ],
    "wof:name":"Mid Atlantic Warranty",
    "wof:placetype":"venue"
},
  "geometry": {"coordinates":[-75.571956,39.734571],"type":"Point"}
}