{
  "type": "Feature",
  "properties": {
    "iso:country":"US",
    "sg:address":"42 Rehoboth Ave",
    "sg:city":"Rehoboth Beach",
    "sg:classifiers":[
        {
            "category":"Restaurant",
            "type":"Food & Drink"
        }
    ],
    "sg:phone":"+1 302 296 0133",
    "sg:postcode":"19971",
    "sg:province":"DE",
    "sg:tags":[
        "parlor",
        "ice",
        "cream"
    ],
    "wof:name":"Nice Cream Day",
    "wof:placetype":"venue"
},
  "geometry": {"coordinates":[-75.077302,38.716401],"type":"Point"}
}