{
  "type": "Feature",
  "properties": {
    "addr:full":"501 Ogletown Rd Newark DE 19711",
    "addr:housenumber":"501",
    "addr:postcode":"19711",
    "addr:street":"Ogletown Rd",
    "iso:country":"US",
    "sg:address":"501 Ogletown Rd",
    "sg:city":"Newark",
    "sg:classifiers":[
        {
            "category":"Health Services",
            "subcategory":"Clinic",
            "type":"Services"
        }
    ],
    "sg:phone":"+1 302 368 6830",
    "sg:postcode":"19711",
    "sg:province":"DE",
    "sg:tags":[
        "specialty",
        "outpatient"
    ],
    "wof:name":"New Cstle Cmnty Mntal Hlth Ctr",
    "wof:placetype":"venue"
},
  "geometry": {"coordinates":[-75.734711,39.684798],"type":"Point"}
}