{
  "type": "Feature",
  "properties": {
    "iso:country":"US",
    "sg:address":"5317 Limestone Rd",
    "sg:city":"Wilmington",
    "sg:classifiers":[
        {
            "category":"Health Services",
            "subcategory":"Doctor",
            "type":"Services"
        }
    ],
    "sg:phone":"+1 302 239 6677",
    "sg:postcode":"19808",
    "sg:province":"DE",
    "wof:name":"Rohrbaugh and Thomas-Glavin PA",
    "wof:placetype":"venue"
},
  "geometry": {"coordinates":[-75.69756,39.744785],"type":"Point"}
}