{
  "type": "Feature",
  "properties": {
    "addr:full":"512 Lake Dr Frederica DE 19977",
    "addr:housenumber":"512",
    "addr:postcode":"19977",
    "addr:street":"Lake Dr Frederica",
    "iso:country":"US",
    "sg:address":"512 Lake Dr",
    "sg:city":"Frederica",
    "sg:classifiers":[
        {
            "category":"Professional",
            "type":"Services"
        }
    ],
    "sg:phone":"+1 302 335 4023",
    "sg:postcode":"19977",
    "sg:province":"DE",
    "wof:name":"Eliseo Valenzuela Jr",
    "wof:placetype":"venue"
},
  "geometry": {"coordinates":[-75.608465,39.293853],"type":"Point"}
}