{
  "type": "Feature",
  "properties": {
    "addr:full":"1408 Wilmington Rd New Castle DE 19720",
    "addr:housenumber":"1408",
    "addr:postcode":"19720",
    "addr:street":"Wilmington Rd New",
    "iso:country":"US",
    "sg:address":"1408 Wilmington Rd",
    "sg:city":"New Castle",
    "sg:classifiers":[
        {
            "category":"Professional",
            "type":"Services"
        }
    ],
    "sg:phone":"+1 302 328 0508",
    "sg:postcode":"19720",
    "sg:province":"DE",
    "wof:name":"Richard M Hayford Colonel",
    "wof:placetype":"venue"
},
  "geometry": {"coordinates":[-75.55949200000001,39.679086],"type":"Point"}
}