{
  "type": "Feature",
  "properties": {
    "iso:country":"US",
    "sg:address":"117 W North St",
    "sg:city":"Georgetown",
    "sg:classifiers":[
        {
            "category":"Professional",
            "subcategory":"Management & Consulting",
            "type":"Services"
        }
    ],
    "sg:phone":"+1 302 856 7771",
    "sg:postcode":"19947",
    "sg:province":"DE",
    "wof:name":"Howard C Richardson",
    "wof:placetype":"venue"
},
  "geometry": {"coordinates":[-75.395904,38.692819],"type":"Point"}
}