{
  "type": "Feature",
  "properties": {
    "iso:country":"US",
    "sg:address":"477 Fletcher Dr",
    "sg:city":"Smyrna",
    "sg:classifiers":[
        {
            "category":"Travel",
            "subcategory":"Travel Agent",
            "type":"Entertainment"
        }
    ],
    "sg:phone":"+1 302 227 9211",
    "sg:postcode":"19977",
    "sg:province":"DE",
    "sg:tags":[
        "agency",
        "bureau"
    ],
    "wof:name":"Caribbean Cruise Lines",
    "wof:placetype":"venue"
},
  "geometry": {"coordinates":[-75.598131,39.249776],"type":"Point"}
}