{
  "type": "Feature",
  "properties": {
    "addr:full":"3249 Frazer Rd Newark DE 19702",
    "addr:housenumber":"3249",
    "addr:postcode":"19702",
    "addr:street":"Frazer Rd",
    "iso:country":"US",
    "sg:address":"3249 Frazer Rd",
    "sg:city":"Newark",
    "sg:classifiers":[
        {
            "category":"Building & Trades",
            "subcategory":"Construction",
            "type":"Services"
        }
    ],
    "sg:phone":"+1 302 368 2886",
    "sg:postcode":"19702",
    "sg:province":"DE",
    "sg:tags":[
        "house"
    ],
    "wof:name":"Kevin Reed Construction",
    "wof:placetype":"venue"
},
  "geometry": {"coordinates":[-75.757819,39.552303],"type":"Point"}
}