{
  "type": "Feature",
  "properties": {
    "iso:country":"US",
    "sg:address":"607 S Harrison St",
    "sg:city":"Wilmington",
    "sg:classifiers":[
        {
            "category":"Retail",
            "subcategory":"Funeral Services",
            "type":"Services"
        }
    ],
    "sg:phone":"+1 302 652 5114",
    "sg:postcode":"19805",
    "sg:province":"DE",
    "sg:tags":[
        "director",
        "home"
    ],
    "wof:name":"Yasik John F & Son Inc",
    "wof:placetype":"venue"
},
  "geometry": {"coordinates":[-75.567482,39.73874],"type":"Point"}
}