{
  "type": "Feature",
  "properties": {
    "addr:full":"1998 Mitten St Dover DE 19901",
    "addr:housenumber":"1998",
    "addr:postcode":"19901",
    "addr:street":"Mitten St",
    "iso:country":"US",
    "sg:address":"1998 Mitten St",
    "sg:city":"Dover",
    "sg:classifiers":[
        {
            "category":"Building & Trades",
            "subcategory":"Construction",
            "type":"Services"
        },
        {
            "category":"Building & Trades",
            "subcategory":"Electrical",
            "type":"Services"
        }
    ],
    "sg:phone":"+1 302 697 1368",
    "sg:postcode":"19901",
    "sg:province":"DE",
    "sg:tags":[
        "electrician",
        "contractor"
    ],
    "wof:name":"Smith Mark A",
    "wof:placetype":"venue"
},
  "geometry": {"coordinates":[-75.517403,39.118198],"type":"Point"}
}