{
  "type": "Feature",
  "properties": {
    "iso:country":"US",
    "sg:address":"2002 Foulk Rd",
    "sg:city":"Wilmington",
    "sg:classifiers":[
        {
            "category":"Health Services",
            "subcategory":"Podiatrist",
            "type":"Services"
        }
    ],
    "sg:phone":"+1 302 765 2505",
    "sg:postcode":"19810",
    "sg:province":"DE",
    "wof:name":"Foot Healthcare Of Delaware",
    "wof:placetype":"venue"
},
  "geometry": {"coordinates":[-75.51094999999999,39.812717],"type":"Point"}
}