{
  "type": "Feature",
  "properties": {
    "iso:country":"US",
    "sg:address":"205 Winston Ave",
    "sg:city":"Wilmington",
    "sg:classifiers":[
        {
            "category":"Organizations",
            "subcategory":"Religious Organization",
            "type":"Services"
        }
    ],
    "sg:phone":"+1 302 683 0677",
    "sg:postcode":"19804",
    "sg:province":"DE",
    "wof:name":"Ruben Rodriguez Rev",
    "wof:placetype":"venue"
},
  "geometry": {"coordinates":[-75.593124,39.729132],"type":"Point"}
}