{
  "type": "Feature",
  "properties": {
    "addr:full":"217 W 25th St Wilmington DE 19802",
    "addr:housenumber":"217",
    "addr:postcode":"19802",
    "addr:street":"W 25Th St",
    "iso:country":"US",
    "sg:address":"217 W 25th St",
    "sg:city":"Wilmington",
    "sg:classifiers":[
        {
            "category":"Real Estate",
            "subcategory":"Real Estate Agent",
            "type":"Services"
        }
    ],
    "sg:phone":"+1 302 762 8600",
    "sg:postcode":"19802",
    "sg:province":"DE",
    "sg:tags":[
        "management"
    ],
    "wof:name":"Falkowski & Assoc Inc",
    "wof:placetype":"venue"
},
  "geometry": {"coordinates":[-75.538804,39.756736],"type":"Point"}
}