{
  "type": "Feature",
  "properties": {
    "iso:country":"US",
    "sg:address":"106 S Marshall St",
    "sg:city":"Wilmington",
    "sg:classifiers":[
        {
            "category":"Building & Trades",
            "subcategory":"Landscaping Services",
            "type":"Services"
        }
    ],
    "sg:phone":"+1 302 764 0804",
    "sg:postcode":"19804",
    "sg:province":"DE",
    "wof:name":"Forever Green Landscaping",
    "wof:placetype":"venue"
},
  "geometry": {"coordinates":[-75.608118,39.712325],"type":"Point"}
}