{
  "type": "Feature",
  "properties": {
    "iso:country":"US",
    "sg:address":"1521 Crittenden Rd",
    "sg:city":"Wilmington",
    "sg:classifiers":[
        {
            "category":"Building & Trades",
            "subcategory":"Construction",
            "type":"Services"
        }
    ],
    "sg:phone":"+1 302 892 2116",
    "sg:postcode":"19805",
    "sg:province":"DE",
    "sg:tags":[
        "house"
    ],
    "wof:name":"Paradise Group Inc",
    "wof:placetype":"venue"
},
  "geometry": {"coordinates":[-75.60648999999999,39.746728],"type":"Point"}
}