{
  "type": "Feature",
  "properties": {
    "addr:full":"300 Commercial Dr Wilmington DE 19805",
    "addr:housenumber":"300",
    "addr:postcode":"19805",
    "addr:street":"Commercial Dr",
    "iso:country":"US",
    "sg:address":"300 Commercial Dr",
    "sg:city":"Wilmington",
    "sg:classifiers":[
        {
            "category":"Building & Trades",
            "subcategory":"Electrical",
            "type":"Services"
        }
    ],
    "sg:phone":"+1 302 658 7260",
    "sg:postcode":"19805",
    "sg:province":"DE",
    "sg:tags":[
        "electrical",
        "contractor"
    ],
    "wof:name":"Progressive Services Inc",
    "wof:placetype":"venue"
},
  "geometry": {"coordinates":[-75.588917,39.74182],"type":"Point"}
}