{
  "type": "Feature",
  "properties": {
    "addr:full":"125 Churchill Ln Wilmington DE 19808",
    "addr:housenumber":"125",
    "addr:postcode":"19808",
    "addr:street":"Churchill Ln",
    "iso:country":"US",
    "sg:address":"125 Churchill Ln",
    "sg:city":"Wilmington",
    "sg:classifiers":[
        {
            "category":"Insurance",
            "subcategory":"Hazard Insurance",
            "type":"Services"
        }
    ],
    "sg:phone":"+1 302 239 4301",
    "sg:postcode":"19808",
    "sg:province":"DE",
    "wof:name":"Richard Colliss",
    "wof:placetype":"venue"
},
  "geometry": {"coordinates":[-75.69711,39.753223],"type":"Point"}
}