{
  "type": "Feature",
  "properties": {
    "iso:country":"US",
    "sg:address":"274 S Dupont Hwy",
    "sg:city":"Dover",
    "sg:classifiers":[
        {
            "category":"Personal",
            "subcategory":"Nail Salon",
            "type":"Services"
        }
    ],
    "sg:phone":"+1 302 677 1747",
    "sg:postcode":"19901",
    "sg:province":"DE",
    "wof:name":"La Nails",
    "wof:placetype":"venue"
},
  "geometry": {"coordinates":[-75.512398,39.1586],"type":"Point"}
}