{
  "type": "Feature",
  "properties": {
    "iso:country":"US",
    "sg:address":"125 Westgate Dr",
    "sg:city":"Wilmington",
    "sg:classifiers":[
        {
            "category":"Real Estate",
            "subcategory":"Real Estate Services",
            "type":"Services"
        },
        {
            "category":"Real Estate",
            "subcategory":"Real Estate Agent",
            "type":"Services"
        }
    ],
    "sg:phone":"+1 302 234 4433",
    "sg:postcode":"19808",
    "sg:province":"DE",
    "sg:tags":[
        "buyer",
        "broker"
    ],
    "wof:name":"Kelly Spinelli Real Estat",
    "wof:placetype":"venue"
},
  "geometry": {"coordinates":[-75.65997299999999,39.76593],"type":"Point"}
}