{
  "type": "Feature",
  "properties": {
    "addr:full":"126 N Broom St Wilmington DE 19805",
    "addr:housenumber":"126",
    "addr:postcode":"19805",
    "addr:street":"N Broom St",
    "iso:country":"US",
    "sg:address":"126 N Broom St",
    "sg:city":"Wilmington",
    "sg:classifiers":[
        {
            "category":"Building & Trades",
            "subcategory":"Construction",
            "type":"Services"
        }
    ],
    "sg:phone":"+1 302 655 2408",
    "sg:postcode":"19805",
    "sg:province":"DE",
    "sg:tags":[
        "altering",
        "remodeling",
        "contractor"
    ],
    "wof:name":"Garcia Construction Remodeling",
    "wof:placetype":"venue"
},
  "geometry": {"coordinates":[-75.567258,39.744121],"type":"Point"}
}