{
  "type": "Feature",
  "properties": {
    "iso:country":"US",
    "sg:address":"120 S Bedford St",
    "sg:city":"Georgetown",
    "sg:classifiers":[
        {
            "category":"Professional",
            "subcategory":"Lawyer & Legal Services",
            "type":"Services"
        }
    ],
    "sg:phone":"+1 302 855 0120",
    "sg:postcode":"19947",
    "sg:province":"DE",
    "sg:tags":[
        "attorney"
    ],
    "wof:name":"Robert V Witsil Jr Pa",
    "wof:placetype":"venue"
},
  "geometry": {"coordinates":[-75.383985,38.688638],"type":"Point"}
}