{
  "type": "Feature",
  "properties": {
    "iso:country":"US",
    "sg:address":"3512 Silverside Rd",
    "sg:city":"Wilmington",
    "sg:classifiers":[
        {
            "category":"Real Estate",
            "subcategory":"Real Estate Agent",
            "type":"Services"
        }
    ],
    "sg:phone":"+1 302 478 4780",
    "sg:postcode":"19810",
    "sg:province":"DE",
    "wof:name":"Richard Craig & Assoc",
    "wof:placetype":"venue"
},
  "geometry": {"coordinates":[-75.544541,39.808819],"type":"Point"}
}