{
  "type": "Feature",
  "properties": {
    "iso:country":"US",
    "sg:address":"111 Clover Dr",
    "sg:city":"Hockessin",
    "sg:classifiers":[
        {
            "category":"Real Estate",
            "subcategory":"Real Estate Services",
            "type":"Services"
        },
        {
            "category":"Real Estate",
            "subcategory":"Real Estate Agent",
            "type":"Services"
        }
    ],
    "sg:phone":"+1 302 239 6971",
    "sg:postcode":"19707",
    "sg:province":"DE",
    "sg:tags":[
        "buyer",
        "broker"
    ],
    "wof:name":"Nemeth Paul",
    "wof:placetype":"venue"
},
  "geometry": {"coordinates":[-75.66895700000001,39.779145],"type":"Point"}
}