{
  "type": "Feature",
  "properties": {
    "iso:country":"US",
    "sg:address":"590 Century Blvd",
    "sg:city":"Wilmington",
    "sg:classifiers":[
        {
            "category":"Wholesale",
            "subcategory":"Computers",
            "type":"Manufacturing & Wholesale Goods"
        }
    ],
    "sg:phone":"+1 302 633 9800",
    "sg:postcode":"19808",
    "sg:province":"DE",
    "sg:tags":[
        "hardware"
    ],
    "wof:name":"ISI Connect LLC",
    "wof:placetype":"venue"
},
  "geometry": {"coordinates":[-75.61922800000001,39.731375],"type":"Point"}
}