{
  "type": "Feature",
  "properties": {
    "iso:country":"US",
    "sg:address":"35 Rose Cir",
    "sg:city":"Newark",
    "sg:classifiers":[
        {
            "category":"Building & Trades",
            "subcategory":"Construction",
            "type":"Services"
        }
    ],
    "sg:phone":"+1 302 453 1385",
    "sg:postcode":"19711",
    "sg:province":"DE",
    "sg:tags":[
        "repair",
        "welding",
        "contractor"
    ],
    "wof:name":"R E Erickson & Son Welding",
    "wof:placetype":"venue"
},
  "geometry": {"coordinates":[-75.71237600000001,39.698786],"type":"Point"}
}