{
  "type": "Feature",
  "properties": {
    "addr:full":"221 N Marshall St Stanton DE 19804",
    "addr:housenumber":"221",
    "addr:postcode":"19804",
    "addr:street":"N Marshall St",
    "iso:country":"US",
    "sg:address":"221 N Marshall St",
    "sg:city":"Stanton",
    "sg:classifiers":[
        {
            "category":"Retail",
            "subcategory":"Repair Shop",
            "type":"Services"
        }
    ],
    "sg:phone":"+1 302 999 7242",
    "sg:postcode":"19804",
    "sg:province":"DE",
    "sg:tags":[
        "repairing",
        "piano",
        "refinishing"
    ],
    "wof:name":"A-440 Piano Svc",
    "wof:placetype":"venue"
},
  "geometry": {"coordinates":[-75.608949,39.716543],"type":"Point"}
}