{
  "type": "Feature",
  "properties": {
    "iso:country":"US",
    "sg:address":"1014 Elkton Rd",
    "sg:city":"Newark",
    "sg:classifiers":[
        {
            "category":"Home & Garden",
            "subcategory":"Building Materials",
            "type":"Retail Goods"
        }
    ],
    "sg:phone":"+1 302 366 1311",
    "sg:postcode":"19711",
    "sg:province":"DE",
    "sg:tags":[
        "prefabricated",
        "log"
    ],
    "wof:name":"Mayer Inc",
    "wof:placetype":"venue"
},
  "geometry": {"coordinates":[-75.78728099999999,39.655812],"type":"Point"}
}