{
  "type": "Feature",
  "properties": {
    "addr:full":"22 N Union St Smyrna DE 19977",
    "addr:housenumber":"22",
    "addr:postcode":"19977",
    "addr:street":"N Union St",
    "iso:country":"US",
    "sg:address":"22 N Union St",
    "sg:city":"Smyrna",
    "sg:classifiers":[
        {
            "category":"Social Services",
            "subcategory":"Child Care",
            "type":"Services"
        }
    ],
    "sg:phone":"+1 302 653 5690",
    "sg:postcode":"19977",
    "sg:province":"DE",
    "sg:tags":[
        "kindergarten",
        "academic",
        "school"
    ],
    "wof:name":"Saint Peter's Preschool",
    "wof:placetype":"venue"
},
  "geometry": {"coordinates":[-75.60977699999999,39.298947],"type":"Point"}
}