{
  "type": "Feature",
  "properties": {
    "iso:country":"US",
    "sg:address":"36505 Smith Mill Church Rd",
    "sg:city":"Delmar",
    "sg:classifiers":[
        {
            "category":"Farming",
            "subcategory":"Farm",
            "type":"Manufacturing & Wholesale Goods"
        }
    ],
    "sg:phone":"+1 302 846 2454",
    "sg:postcode":"19940",
    "sg:province":"DE",
    "wof:name":"Brumbley Farms",
    "wof:placetype":"venue"
},
  "geometry": {"coordinates":[-75.50932899999999,38.482139],"type":"Point"}
}