{
  "type": "Feature",
  "properties": {
    "iso:country":"US",
    "sg:address":"30 Watergate Cir",
    "sg:city":"Selbyville",
    "sg:classifiers":[
        {
            "category":"Professional",
            "type":"Services"
        }
    ],
    "sg:phone":"+1 302 436 9875",
    "sg:postcode":"19975",
    "sg:province":"DE",
    "wof:name":"TRC Inc",
    "wof:placetype":"venue"
},
  "geometry": {"coordinates":[-75.12943,38.452969],"type":"Point"}
}