{
  "type": "Feature",
  "properties": {
    "iso:country":"US",
    "sg:address":"216 Hitching Post Dr",
    "sg:city":"Wilmington",
    "sg:classifiers":[
        {
            "category":"Professional",
            "subcategory":"Management & Consulting",
            "type":"Services"
        }
    ],
    "sg:phone":"+1 302 479 0339",
    "sg:postcode":"19803",
    "sg:province":"DE",
    "wof:name":"Fpg Financonsult Inc",
    "wof:placetype":"venue"
},
  "geometry": {"coordinates":[-75.531327,39.803876],"type":"Point"}
}