{
  "type": "Feature",
  "properties": {
    "addr:full":"22 Old Rudnick Ln Dover DE 19901",
    "addr:housenumber":"22",
    "addr:postcode":"19901",
    "addr:street":"Old Rudnick Ln",
    "iso:country":"US",
    "sg:address":"22 Old Rudnick Ln",
    "sg:city":"Dover",
    "sg:classifiers":[
        {
            "category":"Professional",
            "type":"Services"
        }
    ],
    "sg:phone":"+1 302 674 3964",
    "sg:postcode":"19901",
    "sg:province":"DE",
    "wof:name":"LCAI",
    "wof:placetype":"venue"
},
  "geometry": {"coordinates":[-75.52225300000001,39.134789],"type":"Point"}
}