{
  "type": "Feature",
  "properties": {
    "iso:country":"US",
    "sg:address":"904 Myers Dr",
    "sg:city":"Hartly",
    "sg:classifiers":[
        {
            "category":"Building & Trades",
            "subcategory":"Construction",
            "type":"Services"
        }
    ],
    "sg:phone":"+1 302 492 3651",
    "sg:postcode":"19953",
    "sg:province":"DE",
    "sg:tags":[
        "general",
        "contractor"
    ],
    "wof:name":"Gateway Construction Inc",
    "wof:placetype":"venue"
},
  "geometry": {"coordinates":[-75.682833,39.18239],"type":"Point"}
}