{
  "type": "Feature",
  "properties": {
    "iso:country":"US",
    "sg:address":"1907 Brian Ct",
    "sg:city":"Bear",
    "sg:classifiers":[
        {
            "category":"Building & Trades",
            "subcategory":"Construction",
            "type":"Services"
        }
    ],
    "sg:phone":"+1 302 834 4526",
    "sg:postcode":"19701",
    "sg:province":"DE",
    "sg:tags":[
        "steel",
        "erection",
        "structural"
    ],
    "wof:name":"Jat Industrial Inc",
    "wof:placetype":"venue"
},
  "geometry": {"coordinates":[-75.68563,39.617392],"type":"Point"}
}