{
  "type": "Feature",
  "properties": {
    "iso:country":"US",
    "sg:address":"2000 W Newport Pike",
    "sg:city":"Wilmington",
    "sg:classifiers":[
        {
            "category":"Wholesale",
            "subcategory":"Hardware",
            "type":"Manufacturing & Wholesale Goods"
        },
        {
            "category":"Home & Garden",
            "subcategory":"Garden Supply",
            "type":"Retail Goods"
        },
        {
            "category":"Retail",
            "subcategory":"Repair Shop",
            "type":"Services"
        }
    ],
    "sg:phone":"+1 302 998 7700",
    "sg:postcode":"19804",
    "sg:province":"DE",
    "sg:tags":[
        "renting",
        "lawn",
        "outdoor",
        "power",
        "landscaping",
        "equipment-sales",
        "equipment",
        "saw"
    ],
    "sg:website":"http://www.stihldealer.net/default-dealer-012195.aspx",
    "wof:name":"Suburban Lawn Equipment Inc.",
    "wof:placetype":"venue"
},
  "geometry": {"coordinates":[-75.635406,39.715939],"type":"Point"}
}