{
  "type": "Feature",
  "properties": {
    "addr:full":"10 Summerknoll Cir Newark DE 19711",
    "addr:housenumber":"10",
    "addr:postcode":"19711",
    "addr:street":"Summerknoll Cir",
    "iso:country":"US",
    "sg:address":"10 Summerknoll Cir",
    "sg:city":"Newark",
    "sg:classifiers":[
        {
            "category":"Manufacturing",
            "subcategory":"Printing",
            "type":"Manufacturing & Wholesale Goods"
        }
    ],
    "sg:phone":"+1 302 225 3030",
    "sg:postcode":"19711",
    "sg:province":"DE",
    "sg:tags":[
        "newspaper"
    ],
    "wof:name":"Delaware Fire Svc News",
    "wof:placetype":"venue"
},
  "geometry": {"coordinates":[-75.727887,39.773514],"type":"Point"}
}