{
  "type": "Feature",
  "properties": {
    "addr:full":"18 Harbor Rd Rehoboth Beach DE 19971",
    "addr:housenumber":"18",
    "addr:postcode":"19971",
    "addr:street":"Harbor Rd",
    "iso:country":"US",
    "sg:address":"18 Harbor Rd",
    "sg:city":"Rehoboth Beach",
    "sg:classifiers":[
        {
            "category":"Professional",
            "type":"Services"
        }
    ],
    "sg:phone":"+1 302 227 1343",
    "sg:postcode":"19971",
    "sg:province":"DE",
    "wof:name":"Robert N Adrian Capt",
    "wof:placetype":"venue"
},
  "geometry": {"coordinates":[-75.081276,38.733019],"type":"Point"}
}