{
  "type": "Feature",
  "properties": {
    "iso:country":"US",
    "sg:address":"42 Kings Hwy",
    "sg:city":"Dover",
    "sg:classifiers":[
        {
            "category":"Social Services",
            "subcategory":"Child Care",
            "type":"Services"
        }
    ],
    "sg:phone":"+1 302 734 2870",
    "sg:postcode":"19901",
    "sg:province":"DE",
    "wof:name":"Sanford S Murphey Day Care Ctr",
    "wof:placetype":"venue"
},
  "geometry": {"coordinates":[-75.523115,39.162209],"type":"Point"}
}