{
  "type": "Feature",
  "properties": {
    "iso:country":"US",
    "sg:address":"209 S Dillwyn Rd",
    "sg:city":"Newark",
    "sg:classifiers":[
        {
            "category":"Professional",
            "subcategory":"Business Services",
            "type":"Services"
        }
    ],
    "sg:phone":"+1 302 368 0261",
    "sg:postcode":"19711",
    "sg:province":"DE",
    "sg:tags":[
        "auctioneer"
    ],
    "wof:name":"Evard B Hall Auctioneers",
    "wof:placetype":"venue"
},
  "geometry": {"coordinates":[-75.718997,39.688279],"type":"Point"}
}