{
  "type": "Feature",
  "properties": {
    "iso:country":"US",
    "sg:address":"2300 W Huntington Dr",
    "sg:city":"Wilmington",
    "sg:classifiers":[
        {
            "category":"Organizations",
            "subcategory":"Religious Organization",
            "type":"Services"
        }
    ],
    "sg:phone":"+1 302 998 1747",
    "sg:postcode":"19808",
    "sg:province":"DE",
    "sg:tags":[
        "church"
    ],
    "wof:name":"St Michael's-Orthodox Church",
    "wof:placetype":"venue"
},
  "geometry": {"coordinates":[-75.672167,39.716353],"type":"Point"}
}