{
  "type": "Feature",
  "properties": {
    "iso:country":"US",
    "sg:address":"3411 Silverside Rd",
    "sg:city":"Wilmington",
    "sg:classifiers":[
        {
            "category":"Manufacturing",
            "subcategory":"Chemicals & Compounds",
            "type":"Manufacturing & Wholesale Goods"
        }
    ],
    "sg:phone":"+1 302 478 0825",
    "sg:postcode":"19810",
    "sg:province":"DE",
    "sg:tags":[
        "preparation",
        "pharmaceutical",
        "mfg"
    ],
    "wof:name":"Clariant Lsm (america) Inc",
    "wof:placetype":"venue"
},
  "geometry": {"coordinates":[-75.549054,39.80927],"type":"Point"}
}