{
  "type": "Feature",
  "properties": {
    "addr:full":"306 Bayview Ave Rehoboth Beach DE 19971",
    "addr:housenumber":"306",
    "addr:postcode":"19971",
    "addr:street":"Bayview Ave",
    "iso:country":"US",
    "sg:address":"306 Bayview Ave",
    "sg:city":"Rehoboth Beach",
    "sg:classifiers":[
        {
            "category":"Professional",
            "type":"Services"
        }
    ],
    "sg:phone":"+1 302 227 2757",
    "sg:postcode":"19971",
    "sg:province":"DE",
    "wof:name":"Write Expression",
    "wof:placetype":"venue"
},
  "geometry": {"coordinates":[-75.082982,38.697074],"type":"Point"}
}