{
  "type": "Feature",
  "properties": {
    "iso:country":"US",
    "sg:address":"308 West Ave",
    "sg:city":"New Castle",
    "sg:classifiers":[
        {
            "category":"Organizations",
            "subcategory":"Religious Organization",
            "type":"Services"
        }
    ],
    "sg:phone":"+1 302 654 1710",
    "sg:postcode":"19720",
    "sg:province":"DE",
    "sg:tags":[
        "church"
    ],
    "wof:name":"First Baptist Church",
    "wof:placetype":"venue"
},
  "geometry": {"coordinates":[-75.54561099999999,39.702627],"type":"Point"}
}