{
  "type": "Feature",
  "properties": {
    "iso:country":"US",
    "sg:address":"1141 N Dupont Hwy",
    "sg:city":"Dover",
    "sg:classifiers":[
        {
            "category":"Restaurant",
            "type":"Food & Drink"
        }
    ],
    "sg:phone":"+1 302 678 5012",
    "sg:postcode":"19901",
    "sg:province":"DE",
    "sg:tags":[
        "grill",
        "bar"
    ],
    "wof:name":"Chipotle Mexican Grill, Inc.",
    "wof:placetype":"venue"
},
  "geometry": {"coordinates":[-75.53756,39.187199],"type":"Point"}
}