{
  "type": "Feature",
  "properties": {
    "iso:country":"US",
    "sg:address":"5905 Kennett Pike",
    "sg:city":"Wilmington",
    "sg:classifiers":[
        {
            "category":"Banks & Credit Unions",
            "subcategory":"Investment Brokerage",
            "type":"Services"
        }
    ],
    "sg:phone":"+1 302 655 6207",
    "sg:postcode":"19807",
    "sg:province":"DE",
    "sg:tags":[
        "advisory"
    ],
    "wof:name":"Privilege Capital Management",
    "wof:placetype":"venue"
},
  "geometry": {"coordinates":[-75.618995,39.82513],"type":"Point"}
}