{
  "type": "Feature",
  "properties": {
    "iso:country":"US",
    "sg:address":"2915 Newport Gap Pike",
    "sg:city":"Wilmington",
    "sg:classifiers":[
        {
            "category":"Travel",
            "subcategory":"Campground",
            "type":"Entertainment"
        }
    ],
    "sg:phone":"+1 302 655 2111",
    "sg:postcode":"19808",
    "sg:province":"DE",
    "sg:tags":[
        "camp"
    ],
    "wof:name":"Delaware Association For Blind",
    "wof:placetype":"venue"
},
  "geometry": {"coordinates":[-75.65204799999999,39.752476],"type":"Point"}
}