{
  "type": "Feature",
  "properties": {
    "iso:country":"US",
    "sg:address":"451 Bellevue Rd",
    "sg:city":"Newark",
    "sg:classifiers":[
        {
            "category":"Manufacturing",
            "subcategory":"Chemicals & Compounds",
            "type":"Manufacturing & Wholesale Goods"
        }
    ],
    "sg:phone":"+1 302 366 0500",
    "sg:postcode":"19713",
    "sg:province":"DE",
    "sg:tags":[
        "ab",
        "fabric",
        "mfg"
    ],
    "wof:name":"Rohm Haas Electronic Mtls Cmp",
    "wof:placetype":"venue"
},
  "geometry": {"coordinates":[-75.74356,39.64919],"type":"Point"}
}