{
  "type": "Feature",
  "properties": {
    "iso:country":"US",
    "sg:address":"52 Carey Ln",
    "sg:city":"Smyrna",
    "sg:classifiers":[
        {
            "category":"Freight",
            "type":"Transportation"
        }
    ],
    "sg:phone":"+1 302 389 3077",
    "sg:postcode":"19958",
    "sg:province":"DE",
    "sg:tags":[
        "special"
    ],
    "wof:name":"Sentinel Self Storage LLC",
    "wof:placetype":"venue"
},
  "geometry": {"coordinates":[-75.152995,38.780585],"type":"Point"}
}