{
  "type": "Feature",
  "properties": {
    "iso:country":"US",
    "sg:address":"207 E Market St",
    "sg:city":"Georgetown",
    "sg:classifiers":[
        {
            "category":"Health Services",
            "subcategory":"Clinic",
            "type":"Services"
        }
    ],
    "sg:phone":"+1 302 856 4700",
    "sg:postcode":"19947",
    "sg:province":"DE",
    "sg:tags":[
        "specialty",
        "outpatient"
    ],
    "wof:name":"Brandywine Counseling",
    "wof:placetype":"venue"
},
  "geometry": {"coordinates":[-75.38414400000001,38.691326],"type":"Point"}
}