{
  "type": "Feature",
  "properties": {
    "iso:country":"US",
    "sg:address":"1403 Silverside Rd",
    "sg:city":"Wilmington",
    "sg:classifiers":[
        {
            "category":"Insurance",
            "subcategory":"Hazard Insurance",
            "type":"Services"
        },
        {
            "category":"Insurance",
            "subcategory":"Insurance Agent",
            "type":"Services"
        },
        {
            "category":"Insurance",
            "subcategory":"Life Insurance",
            "type":"Services"
        },
        {
            "category":"Insurance",
            "subcategory":"Title Insurance",
            "type":"Services"
        }
    ],
    "sg:phone":"+1 302 478 6400",
    "sg:postcode":"19810",
    "sg:province":"DE",
    "sg:tags":[
        "auto",
        "homeowner"
    ],
    "sg:website":"http://www.nationwide.com/agent/Wilmington-DELAWARE-insurance-agent/terry-gouert/office.html",
    "wof:name":"Terry B Gouert Ins Inc - Nationwide Insurance",
    "wof:placetype":"venue"
},
  "geometry": {"coordinates":[-75.490511,39.793195],"type":"Point"}
}