{
  "type": "Feature",
  "properties": {
    "iso:country":"US",
    "sg:address":"3079 New Castle Ave",
    "sg:city":"New Castle",
    "sg:classifiers":[
        {
            "category":"Organizations",
            "subcategory":"Religious Organization",
            "type":"Services"
        }
    ],
    "sg:phone":"+1 302 654 2302",
    "sg:postcode":"19720",
    "sg:province":"DE",
    "sg:tags":[
        "church"
    ],
    "wof:name":"Mount Sinai Baptist Church",
    "wof:placetype":"venue"
},
  "geometry": {"coordinates":[-75.55028299999999,39.706264],"type":"Point"}
}