{
  "type": "Feature",
  "properties": {
    "iso:country":"US",
    "sg:address":"259 Elkton Rd",
    "sg:city":"Newark",
    "sg:classifiers":[
        {
            "category":"Deli",
            "type":"Food & Drink"
        }
    ],
    "sg:menulink":"http://www.allmenus.com/de/greater-newark/18116-bills-park-deli/menu/",
    "sg:phone":"+1 302 368 0149",
    "sg:postcode":"19711",
    "sg:province":"DE",
    "sg:tags":[
        "american"
    ],
    "wof:name":"Bill's Park Deli",
    "wof:placetype":"venue"
},
  "geometry": {"coordinates":[-75.762936,39.676969],"type":"Point"}
}