{
  "type": "Feature",
  "properties": {
    "iso:country":"US",
    "sg:address":"14 Kings Hwy",
    "sg:city":"Dover",
    "sg:classifiers":[
        {
            "category":"Organizations",
            "subcategory":"Non-profit Organization",
            "type":"Services"
        }
    ],
    "sg:phone":"+1 800 660 6602",
    "sg:postcode":"19901",
    "sg:province":"DE",
    "sg:tags":[
        "service/non-profit",
        "community"
    ],
    "sg:website":"www.familyandworkplace.org",
    "wof:name":"Family & Workplace Connection the",
    "wof:placetype":"venue"
},
  "geometry": {"coordinates":[-75.52171,39.162438],"type":"Point"}
}