{
  "type": "Feature",
  "properties": {
    "iso:country":"US",
    "sg:address":"878 Garfield Pkwy",
    "sg:city":"Bethany Beach",
    "sg:classifiers":[
        {
            "category":"Building & Trades",
            "subcategory":"Cleaning & Sanitation",
            "type":"Services"
        }
    ],
    "sg:phone":"+1 302 537 2230",
    "sg:postcode":"19930",
    "sg:province":"DE",
    "sg:tags":[
        "maintenance",
        "landscape"
    ],
    "wof:name":"P&P Enterprises",
    "wof:placetype":"venue"
},
  "geometry": {"coordinates":[-75.078334,38.542106],"type":"Point"}
}