{
  "type": "Feature",
  "properties": {
    "iso:country":"US",
    "sg:address":"111 E Market St",
    "sg:city":"Georgetown",
    "sg:classifiers":[
        {
            "category":"Food & Beverages",
            "subcategory":"Groceries & Convenience Stores",
            "type":"Retail Goods"
        }
    ],
    "sg:phone":"+1 302 855 9779",
    "sg:postcode":"19947",
    "sg:province":"DE",
    "sg:tags":[
        "machine",
        "operator",
        "vending"
    ],
    "wof:name":"Georgetown Deli",
    "wof:placetype":"venue"
},
  "geometry": {"coordinates":[-75.38476300000001,38.690833],"type":"Point"}
}