{
  "type": "Feature",
  "properties": {
    "addr:full":"14813 Oak Rd Greenwood DE 19950",
    "addr:housenumber":"14813",
    "addr:postcode":"19950",
    "addr:street":"Oak Rd",
    "iso:country":"US",
    "sg:address":"14813 Oak Rd",
    "sg:city":"Greenwood",
    "sg:classifiers":[
        {
            "category":"Personal",
            "subcategory":"Beauty Salon",
            "type":"Services"
        }
    ],
    "sg:phone":"+1 302 349 5454",
    "sg:postcode":"19950",
    "sg:province":"DE",
    "wof:name":"2 Handy Gals",
    "wof:placetype":"venue"
},
  "geometry": {"coordinates":[-75.516195,38.770425],"type":"Point"}
}