{
  "type": "Feature",
  "properties": {
    "iso:country":"US",
    "sg:address":"860 Silver Lake Blvd # 1",
    "sg:city":"Dover",
    "sg:classifiers":[
        {
            "category":"Structure",
            "subcategory":"Office Building",
            "type":"Public Place"
        }
    ],
    "sg:phone":"+1 302 739 4208",
    "sg:postcode":"19904",
    "sg:province":"DE",
    "sg:tags":[
        "park"
    ],
    "sg:website":"http://www.delawarepensions.com",
    "wof:name":"State Pensions Office",
    "wof:placetype":"venue"
},
  "geometry": {"coordinates":[-75.536652,39.174313],"type":"Point"}
}