{
  "type": "Feature",
  "properties": {
    "iso:country":"US",
    "sg:address":"120 Old Churchmans Rd",
    "sg:city":"New Castle",
    "sg:classifiers":[
        {
            "category":"Freight",
            "type":"Transportation"
        }
    ],
    "sg:phone":"+1 302 322 4529",
    "sg:postcode":"19720",
    "sg:province":"DE",
    "sg:website":"www.imports.com",
    "wof:name":"Fbo Avcenter",
    "wof:placetype":"venue"
},
  "geometry": {"coordinates":[-75.61485,39.674132],"type":"Point"}
}