{
  "type": "Feature",
  "properties": {
    "addr:full":"200 Wilkerdean Dr W Newark DE 19711",
    "addr:housenumber":"200",
    "addr:postcode":"19711",
    "addr:street":"Wilkerdean Dr W",
    "iso:country":"US",
    "sg:address":"200 Wilkerdean Dr W",
    "sg:city":"Newark",
    "sg:classifiers":[
        {
            "category":"Shopping",
            "subcategory":"Gifts & Souvenirs",
            "type":"Retail Goods"
        }
    ],
    "sg:phone":"+1 302 456 9655",
    "sg:postcode":"19711",
    "sg:province":"DE",
    "wof:name":"Dreamline Collectibles Inc",
    "wof:placetype":"venue"
},
  "geometry": {"coordinates":[-75.7406,39.693178],"type":"Point"}
}