{
  "type": "Feature",
  "properties": {
    "addr:full":"301 N Maryland Ave Wilmington DE 19804",
    "addr:housenumber":"301",
    "addr:postcode":"19804",
    "addr:street":"N Maryland Ave",
    "iso:country":"US",
    "sg:address":"301 N Maryland Ave",
    "sg:city":"Wilmington",
    "sg:classifiers":[
        {
            "category":"Bagels",
            "type":"Food & Drink"
        },
        {
            "category":"Coffee & Tea",
            "type":"Food & Drink"
        },
        {
            "category":"Food & Beverages",
            "subcategory":"Bakery",
            "type":"Retail Goods"
        },
        {
            "category":"Bakery",
            "type":"Food & Drink"
        },
        {
            "category":"Donuts",
            "type":"Food & Drink"
        }
    ],
    "sg:menulink":"http://www.allmenus.com/de/lower-christiana/130331-dunkin-donuts/menu/",
    "sg:phone":"+1 302 652 9328",
    "sg:postcode":"19804",
    "sg:province":"DE",
    "sg:tags":[
        "coffee",
        "diner",
        "tea",
        "bakery",
        "bagel",
        "american",
        "pastry"
    ],
    "wof:name":"Dunkin' Donuts",
    "wof:placetype":"venue"
},
  "geometry": {"coordinates":[-75.582196,39.731003],"type":"Point"}
}