{
  "type": "Feature",
  "properties": {
    "iso:country":"US",
    "sg:address":"57 Robinson Dr",
    "sg:city":"New Castle",
    "sg:classifiers":[
        {
            "category":"Professional",
            "type":"Services"
        }
    ],
    "sg:phone":"+1 302 328 7165",
    "sg:postcode":"19720",
    "sg:province":"DE",
    "wof:name":"Donald E Neil Sgt",
    "wof:placetype":"venue"
},
  "geometry": {"coordinates":[-75.58238,39.696221],"type":"Point"}
}