{
  "type": "Feature",
  "properties": {
    "iso:country":"US",
    "sg:address":"305 S West St",
    "sg:city":"Harrington",
    "sg:classifiers":[
        {
            "category":"Professional",
            "type":"Services"
        }
    ],
    "sg:phone":"+1 302 398 4038",
    "sg:postcode":"19952",
    "sg:province":"DE",
    "wof:name":"Alexander Mary L Bishop",
    "wof:placetype":"venue"
},
  "geometry": {"coordinates":[-75.582268,38.91879],"type":"Point"}
}