{
  "type": "Feature",
  "properties": {
    "iso:country":"US",
    "sg:address":"4720 S Dupont Hwy",
    "sg:city":"Dover",
    "sg:classifiers":[
        {
            "category":"Autos & Motor Vehicles",
            "subcategory":"Automobile Sales",
            "type":"Retail Goods"
        }
    ],
    "sg:phone":"+1 302 698 6370",
    "sg:postcode":"19901",
    "sg:province":"DE",
    "sg:tags":[
        "car",
        "dealer"
    ],
    "wof:name":"Colonial Motors Inc",
    "wof:placetype":"venue"
},
  "geometry": {"coordinates":[-75.54665,39.093848],"type":"Point"}
}