{
  "type": "Feature",
  "properties": {
    "iso:country":"US",
    "sg:address":"1 Capo Ln",
    "sg:city":"New Castle",
    "sg:classifiers":[
        {
            "category":"Local Transit",
            "type":"Transportation"
        }
    ],
    "sg:phone":"+1 302 836 2733",
    "sg:postcode":"19720",
    "sg:province":"DE",
    "sg:tags":[
        "limousine"
    ],
    "wof:name":"Supreme Limousine",
    "wof:placetype":"venue"
},
  "geometry": {"coordinates":[-75.65485700000001,39.615697],"type":"Point"}
}