{
  "type": "Feature",
  "properties": {
    "iso:country":"US",
    "sg:address":"1677 Pulaski Hwy",
    "sg:city":"Bear",
    "sg:classifiers":[
        {
            "category":"Professional",
            "subcategory":"Employment Agencies",
            "type":"Services"
        }
    ],
    "sg:phone":"+1 302 838 5602",
    "sg:postcode":"19701",
    "sg:province":"DE",
    "sg:tags":[
        "help",
        "supply"
    ],
    "wof:name":"Randstad",
    "wof:placetype":"venue"
},
  "geometry": {"coordinates":[-75.69357599999999,39.61924],"type":"Point"}
}