{
  "type": "Feature",
  "properties": {
    "iso:country":"US",
    "sg:address":"37600 Bearhole Rd",
    "sg:city":"Selbyville",
    "sg:classifiers":[
        {
            "category":"Health Services",
            "subcategory":"Doctor",
            "type":"Services"
        }
    ],
    "sg:phone":"+1 302 436 1803",
    "sg:postcode":"19975",
    "sg:province":"DE",
    "sg:tags":[
        "physician",
        "surgeon"
    ],
    "wof:name":"Elizabeth C Parberry Dr",
    "wof:placetype":"venue"
},
  "geometry": {"coordinates":[-75.156227,38.470009],"type":"Point"}
}