{
  "type": "Feature",
  "properties": {
    "iso:country":"US",
    "sg:address":"20644 Conrail Rd",
    "sg:city":"Bridgeville",
    "sg:classifiers":[
        {
            "category":"Food & Beverages",
            "subcategory":"Fruits & Vegetables",
            "type":"Retail Goods"
        }
    ],
    "sg:phone":"+1 302 629 5788",
    "sg:postcode":"19933",
    "sg:province":"DE",
    "sg:tags":[
        "produce"
    ],
    "wof:name":"Tran Produce",
    "wof:placetype":"venue"
},
  "geometry": {"coordinates":[-75.61572099999999,38.696564],"type":"Point"}
}