{
  "type": "Feature",
  "properties": {
    "iso:country":"US",
    "sg:address":"1 W Chestnut Hill Rd",
    "sg:city":"Newark",
    "sg:classifiers":[
        {
            "category":"Food & Beverages",
            "subcategory":"Groceries & Convenience Stores",
            "type":"Retail Goods"
        }
    ],
    "sg:phone":"+1 302 366 9475",
    "sg:postcode":"19713",
    "sg:province":"DE",
    "wof:name":"One Stop Shoppe",
    "wof:placetype":"venue"
},
  "geometry": {"coordinates":[-75.751435,39.655654],"type":"Point"}
}