{
  "type": "Feature",
  "properties": {
    "iso:country":"US",
    "sg:address":"223 N Market St",
    "sg:city":"Wilmington",
    "sg:classifiers":[
        {
            "category":"Professional",
            "type":"Services"
        }
    ],
    "sg:phone":"+1 302 777 4310",
    "sg:postcode":"19801",
    "sg:province":"DE",
    "wof:name":"Carlucci Atelier",
    "wof:placetype":"venue"
},
  "geometry": {"coordinates":[-75.551852,39.739729],"type":"Point"}
}