{
  "type": "Feature",
  "properties": {
    "iso:country":"US",
    "sg:address":"125 Rustic Ln",
    "sg:city":"Dover",
    "sg:classifiers":[
        {
            "category":"Building & Trades",
            "subcategory":"Construction",
            "type":"Services"
        }
    ],
    "sg:phone":"+1 302 736 1581",
    "sg:postcode":"19901",
    "sg:province":"DE",
    "sg:tags":[
        "carpentry",
        "contractor"
    ],
    "wof:name":"Kj Construction",
    "wof:placetype":"venue"
},
  "geometry": {"coordinates":[-75.54501,39.196059],"type":"Point"}
}