{
  "type": "Feature",
  "properties": {
    "iso:country":"US",
    "sg:address":"35 E Glenwood Ave",
    "sg:city":"Smyrna",
    "sg:classifiers":[
        {
            "category":"Shopping",
            "subcategory":"Tobacco",
            "type":"Retail Goods"
        }
    ],
    "sg:phone":"+1 302 653 3954",
    "sg:postcode":"19977",
    "sg:province":"DE",
    "sg:tags":[
        "cigarette",
        "cigar",
        "dealer"
    ],
    "wof:name":"Dot Discount",
    "wof:placetype":"venue"
},
  "geometry": {"coordinates":[-75.609606,39.303942],"type":"Point"}
}