{
  "type": "Feature",
  "properties": {
    "addr:full":"718 Stanton Christiana Rd Newark DE 19713",
    "addr:housenumber":"718",
    "addr:postcode":"19713",
    "addr:street":"Stanton Christiana Rd",
    "iso:country":"US",
    "sg:address":"718 Stanton Christiana Rd",
    "sg:city":"Newark",
    "sg:classifiers":[
        {
            "category":"Wholesale",
            "subcategory":"Construction Materials",
            "type":"Manufacturing & Wholesale Goods"
        },
        {
            "category":"Home & Garden",
            "subcategory":"Building Materials",
            "type":"Retail Goods"
        },
        {
            "category":"Building & Trades",
            "subcategory":"Construction",
            "type":"Services"
        }
    ],
    "sg:phone":"+1 302 998 0800",
    "sg:postcode":"19713",
    "sg:province":"DE",
    "sg:tags":[
        "bathroom",
        "supply",
        "cabinet",
        "planning",
        "plumbing",
        "part",
        "accessory",
        "remodeling",
        "fixtures",
        "kitchen"
    ],
    "sg:website":"http://www.bellsupply.com",
    "wof:name":"Bell's Supply CO Inc",
    "wof:placetype":"venue"
},
  "geometry": {"coordinates":[-75.652283,39.70551],"type":"Point"}
}