{
  "type": "Feature",
  "properties": {
    "addr:full":"1501 Casho Mill Rd Newark DE 19711",
    "addr:housenumber":"1501",
    "addr:postcode":"19711",
    "addr:street":"Casho Mill Rd",
    "iso:country":"US",
    "sg:address":"1501 Casho Mill Rd",
    "sg:city":"Newark",
    "sg:classifiers":[
        {
            "category":"Organizations",
            "subcategory":"Labor Organization",
            "type":"Services"
        }
    ],
    "sg:phone":"+1 302 292 6670",
    "sg:postcode":"19711",
    "sg:province":"DE",
    "wof:name":"United Food & Commercial Wrkrs",
    "wof:placetype":"venue"
},
  "geometry": {"coordinates":[-75.771299,39.670975],"type":"Point"}
}