{
  "type": "Feature",
  "properties": {
    "addr:full":"1158 Pulaski Hwy Bear DE 19701",
    "addr:housenumber":"1158",
    "addr:postcode":"19701",
    "addr:street":"Pulaski Hwy",
    "iso:country":"US",
    "sg:address":"1158 Pulaski Hwy",
    "sg:city":"Bear",
    "sg:classifiers":[
        {
            "category":"Health Services",
            "subcategory":"Chiropractor",
            "type":"Services"
        }
    ],
    "sg:phone":"+1 302 832 7000",
    "sg:postcode":"19701",
    "sg:province":"DE",
    "wof:name":"True Wellness Ctr",
    "wof:placetype":"venue"
},
  "geometry": {"coordinates":[-75.66734,39.629092],"type":"Point"}
}