{
  "type": "Feature",
  "properties": {
    "addr:full":"107 S Dupont Rd Wilmington DE 19805",
    "addr:housenumber":"107",
    "addr:postcode":"19805",
    "addr:street":"S Dupont Rd",
    "iso:country":"US",
    "sg:address":"107 S Dupont Rd",
    "sg:city":"Wilmington",
    "sg:classifiers":[
        {
            "category":"Retail",
            "subcategory":"Car Wash",
            "type":"Services"
        },
        {
            "category":"Retail",
            "subcategory":"Auto Repair",
            "type":"Services"
        }
    ],
    "sg:phone":"+1 302 633 1323",
    "sg:postcode":"19805",
    "sg:province":"DE",
    "sg:tags":[
        "body",
        "repairing",
        "automobile",
        "removal",
        "dent",
        "painting"
    ],
    "wof:name":"High Tech Auto Body",
    "wof:placetype":"venue"
},
  "geometry": {"coordinates":[-75.58860900000001,39.750411],"type":"Point"}
}