{
  "type": "Feature",
  "properties": {
    "iso:country":"US",
    "sg:address":"120 Silver Lake Rd",
    "sg:city":"Middletown",
    "sg:classifiers":[
        {
            "category":"Education",
            "subcategory":"School",
            "type":"Public Place"
        }
    ],
    "sg:phone":"+1 302 378 2757",
    "sg:postcode":"19709",
    "sg:province":"DE",
    "wof:name":"Appoquinimink Teacher Ctr",
    "wof:placetype":"venue"
},
  "geometry": {"coordinates":[-75.696416,39.449391],"type":"Point"}
}