{
  "type": "Feature",
  "properties": {
    "iso:country":"US",
    "sg:address":"88 Comanche Cir",
    "sg:city":"Millsboro",
    "sg:classifiers":[
        {
            "category":"Professional",
            "type":"Services"
        }
    ],
    "sg:phone":"+1 302 947 2572",
    "sg:postcode":"19966",
    "sg:province":"DE",
    "wof:name":"Ronald Sellers",
    "wof:placetype":"venue"
},
  "geometry": {"coordinates":[-75.206327,38.596914],"type":"Point"}
}