{
  "type": "Feature",
  "properties": {
    "iso:country":"US",
    "sg:address":"32791 Roy West Rd",
    "sg:city":"Delmar",
    "sg:classifiers":[
        {
            "category":"Freight",
            "type":"Transportation"
        }
    ],
    "sg:phone":"+1 410 546 3094",
    "sg:postcode":"21875",
    "sg:province":"DE",
    "sg:tags":[
        "operator",
        "local",
        "trucking"
    ],
    "wof:name":"Joseph Hull Trucking LLC",
    "wof:placetype":"venue"
},
  "geometry": {"coordinates":[-75.469009,38.444569],"type":"Point"}
}