{
  "type": "Feature",
  "properties": {
    "addr:full":"111 Alan Dr Newark DE 19711",
    "addr:housenumber":"111",
    "addr:postcode":"19711",
    "addr:street":"Alan Dr",
    "iso:country":"US",
    "sg:address":"111 Alan Dr",
    "sg:city":"Newark",
    "sg:classifiers":[
        {
            "category":"Manufacturing",
            "subcategory":"Rubber & Plastics",
            "type":"Manufacturing & Wholesale Goods"
        },
        {
            "category":"Manufacturing",
            "subcategory":"Chemicals & Compounds",
            "type":"Manufacturing & Wholesale Goods"
        }
    ],
    "sg:phone":"+1 302 731 8691",
    "sg:postcode":"19711",
    "sg:province":"DE",
    "sg:tags":[
        "product",
        "compounds",
        "materials-colorants",
        "powders",
        "plastics-raw",
        "resins",
        "liquids"
    ],
    "sg:website":"http://www.fpintl.com",
    "wof:name":"Fp International",
    "wof:placetype":"venue"
},
  "geometry": {"coordinates":[-75.690597,39.691525],"type":"Point"}
}