{
  "type": "Feature",
  "properties": {
    "iso:country":"US",
    "sg:address":"108 Buena Vista Dr",
    "sg:city":"New Castle",
    "sg:classifiers":[
        {
            "category":"Real Estate",
            "subcategory":"Real Estate Agent",
            "type":"Services"
        }
    ],
    "sg:phone":"+1 302 322 6649",
    "sg:postcode":"19720",
    "sg:province":"DE",
    "wof:name":"Community Management Services",
    "wof:placetype":"venue"
},
  "geometry": {"coordinates":[-75.635977,39.639561],"type":"Point"}
}