{
  "type": "Feature",
  "properties": {
    "iso:country":"US",
    "sg:address":"540 Greenhill Ave",
    "sg:city":"Wilmington",
    "sg:classifiers":[
        {
            "category":"Professional",
            "subcategory":"Employment Agencies",
            "type":"Services"
        }
    ],
    "sg:phone":"+1 302 655 4491",
    "sg:postcode":"19805",
    "sg:province":"DE",
    "sg:tags":[
        "opportunity"
    ],
    "wof:name":"Bernard Personnel Consultants",
    "wof:placetype":"venue"
},
  "geometry": {"coordinates":[-75.579207,39.753314],"type":"Point"}
}