{
  "type": "Feature",
  "properties": {
    "addr:full":"308 Llangollen Blvd New Castle DE 19720",
    "addr:housenumber":"308",
    "addr:postcode":"19720",
    "addr:street":"Llangollen Blvd",
    "iso:country":"US",
    "sg:address":"308 Llangollen Blvd",
    "sg:city":"New Castle",
    "sg:classifiers":[
        {
            "category":"Organizations",
            "subcategory":"Labor Organization",
            "type":"Services"
        }
    ],
    "sg:phone":"+1 302 325 9125",
    "sg:postcode":"19720",
    "sg:province":"DE",
    "wof:name":"Union of Utility Workers",
    "wof:placetype":"venue"
},
  "geometry": {"coordinates":[-75.611369,39.644593],"type":"Point"}
}