{
  "type": "Feature",
  "properties": {
    "iso:country":"US",
    "sg:address":"131 Landers Ln",
    "sg:city":"New Castle",
    "sg:classifiers":[
        {
            "category":"Personal",
            "type":"Services"
        }
    ],
    "sg:phone":"+1 302 652 7263",
    "sg:postcode":"19720",
    "sg:province":"DE",
    "wof:name":"Tm Repair",
    "wof:placetype":"venue"
},
  "geometry": {"coordinates":[-75.567105,39.69368],"type":"Point"}
}