{
  "type": "Feature",
  "properties": {
    "addr:full":"34 Blevins Dr New Castle DE 19720",
    "addr:housenumber":"34",
    "addr:postcode":"19720",
    "addr:street":"Blevins Dr",
    "iso:country":"US",
    "sg:address":"34 Blevins Dr",
    "sg:city":"New Castle",
    "sg:classifiers":[
        {
            "category":"Professional",
            "type":"Services"
        }
    ],
    "sg:phone":"+1 302 324 4460",
    "sg:postcode":"19720",
    "sg:province":"DE",
    "wof:name":"US Automated Proccessing De",
    "wof:placetype":"venue"
},
  "geometry": {"coordinates":[-75.600526,39.663756],"type":"Point"}
}