{
  "type": "Feature",
  "properties": {
    "iso:country":"US",
    "sg:address":"624 Main",
    "sg:city":"Cheswold",
    "sg:classifiers":[
        {
            "category":"Building & Trades",
            "subcategory":"Construction",
            "type":"Services"
        }
    ],
    "sg:phone":"+1 302 678 8466",
    "sg:postcode":"19936",
    "sg:province":"DE",
    "sg:tags":[
        "contractor"
    ],
    "wof:name":"Sinclair Construction",
    "wof:placetype":"venue"
},
  "geometry": {"coordinates":[-75.52330000000001,39.158001],"type":"Point"}
}