{
  "type": "Feature",
  "properties": {
    "iso:country":"US",
    "sg:address":"211 Murray Rd",
    "sg:city":"Newark",
    "sg:classifiers":[
        {
            "category":"Manufacturing",
            "subcategory":"Printing",
            "type":"Manufacturing & Wholesale Goods"
        }
    ],
    "sg:phone":"+1 302 368 4927",
    "sg:postcode":"19711",
    "sg:province":"DE",
    "sg:tags":[
        "book"
    ],
    "wof:name":"Red Dragon Press Inc",
    "wof:placetype":"venue"
},
  "geometry": {"coordinates":[-75.76420899999999,39.675624],"type":"Point"}
}