{
  "type": "Feature",
  "properties": {
    "iso:country":"US",
    "sg:address":"12 W Green St",
    "sg:city":"Middletown",
    "sg:classifiers":[
        {
            "category":"Professional",
            "type":"Services"
        }
    ],
    "sg:phone":"+1 302 378 8105",
    "sg:postcode":"19709",
    "sg:province":"DE",
    "wof:name":"Alfred V Dibiasoss",
    "wof:placetype":"venue"
},
  "geometry": {"coordinates":[-75.716668,39.448469],"type":"Point"}
}