{
  "type": "Feature",
  "properties": {
    "addr:full":"22730 Rum Bridge Rd Georgetown DE 19947",
    "addr:postcode":"22730;19947",
    "addr:street":"Bridge Rd",
    "iso:country":"US",
    "sg:address":"22730 Rum Bridge Rd",
    "sg:city":"Georgetown",
    "sg:classifiers":[
        {
            "category":"Building & Trades",
            "subcategory":"Landscaping Services",
            "type":"Services"
        }
    ],
    "sg:phone":"+1 302 855 0657",
    "sg:postcode":"19947",
    "sg:province":"DE",
    "sg:tags":[
        "landscape"
    ],
    "wof:name":"Creative Curbing LLC",
    "wof:placetype":"venue"
},
  "geometry": {"coordinates":[-75.473491,38.671056],"type":"Point"}
}