{
  "type": "Feature",
  "properties": {
    "addr:full":"5075 N Dupont Hwy Dover DE 19901",
    "addr:housenumber":"5075",
    "addr:postcode":"19901",
    "addr:street":"N Dupont Hwy",
    "iso:country":"US",
    "sg:address":"5075 N Dupont Hwy",
    "sg:city":"Dover",
    "sg:classifiers":[
        {
            "category":"Building & Trades",
            "subcategory":"Construction",
            "type":"Services"
        }
    ],
    "sg:phone":"+1 302 674 5466",
    "sg:postcode":"19901",
    "sg:province":"DE",
    "sg:tags":[
        "roofing",
        "contractor"
    ],
    "wof:name":"J & L Roofing Co",
    "wof:placetype":"venue"
},
  "geometry": {"coordinates":[-75.57114,39.212319],"type":"Point"}
}