{
  "type": "Feature",
  "properties": {
    "addr:full":"30 Old Rudnick Ln Dover DE 19901",
    "addr:housenumber":"30",
    "addr:postcode":"19901",
    "addr:street":"Old Rudnick Ln",
    "iso:country":"US",
    "sg:address":"30 Old Rudnick Ln",
    "sg:city":"Dover",
    "sg:classifiers":[
        {
            "category":"Professional",
            "subcategory":"Computer Services",
            "type":"Services"
        }
    ],
    "sg:phone":"+1 661 760 7662",
    "sg:postcode":"19901",
    "sg:province":"DE",
    "sg:tags":[
        "system",
        "integration"
    ],
    "wof:name":"Informaserv Inc",
    "wof:placetype":"venue"
},
  "geometry": {"coordinates":[-75.52216300000001,39.134817],"type":"Point"}
}