{
  "type": "Feature",
  "properties": {
    "iso:country":"US",
    "sg:address":"1050 Ridge Rd",
    "sg:city":"Claymont",
    "sg:classifiers":[
        {
            "category":"Freight",
            "type":"Transportation"
        }
    ],
    "sg:phone":"+1 302 798 3331",
    "sg:postcode":"19703",
    "sg:province":"DE",
    "sg:tags":[
        "commercial",
        "storage"
    ],
    "wof:name":"Tri-State Mini Storage",
    "wof:placetype":"venue"
},
  "geometry": {"coordinates":[-75.440451,39.814952],"type":"Point"}
}