{
  "type": "Feature",
  "properties": {
    "iso:country":"US",
    "sg:address":"127 Rehoboth Ave",
    "sg:city":"Rehoboth Beach",
    "sg:classifiers":[
        {
            "category":"Manufacturing",
            "subcategory":"Signs",
            "type":"Manufacturing & Wholesale Goods"
        }
    ],
    "sg:phone":"+1 609 522 6860",
    "sg:postcode":"19971",
    "sg:province":"DE",
    "sg:tags":[
        "specialty",
        "mfg"
    ],
    "wof:name":"Diversity",
    "wof:placetype":"venue"
},
  "geometry": {"coordinates":[-75.079933,38.71638],"type":"Point"}
}