{
  "type": "Feature",
  "properties": {
    "addr:full":"7234 Lancaster Pike Hockessin DE 19707",
    "addr:housenumber":"7234",
    "addr:postcode":"19707",
    "addr:street":"Lancaster Pike",
    "iso:country":"US",
    "sg:address":"7234 Lancaster Pike",
    "sg:city":"Hockessin",
    "sg:classifiers":[
        {
            "category":"Real Estate",
            "subcategory":"Real Estate Services",
            "type":"Services"
        },
        {
            "category":"Real Estate",
            "subcategory":"Real Estate Agent",
            "type":"Services"
        }
    ],
    "sg:phone":"+1 302 239 3022",
    "sg:postcode":"19707",
    "sg:province":"DE",
    "sg:tags":[
        "buyer",
        "broker"
    ],
    "wof:name":"Moryc Magge Real Estate",
    "wof:placetype":"venue"
},
  "geometry": {"coordinates":[-75.69122299999999,39.787319],"type":"Point"}
}