{
  "type": "Feature",
  "properties": {
    "iso:country":"US",
    "sg:address":"15 Clemson Ct",
    "sg:city":"Newark",
    "sg:classifiers":[
        {
            "category":"Professional",
            "type":"Services"
        }
    ],
    "sg:phone":"+1 302 738 6031",
    "sg:postcode":"19711",
    "sg:province":"DE",
    "wof:name":"James Crane",
    "wof:placetype":"venue"
},
  "geometry": {"coordinates":[-75.711187,39.728543],"type":"Point"}
}