{
  "type": "Feature",
  "properties": {
    "iso:country":"US",
    "sg:address":"666 1/2 S Bay Rd",
    "sg:city":"Dover",
    "sg:classifiers":[
        {
            "category":"Cinema",
            "subcategory":"Movie Rental",
            "type":"Entertainment"
        }
    ],
    "sg:phone":"+1 302 678 8526",
    "sg:postcode":"19901",
    "sg:province":"DE",
    "sg:tags":[
        "game",
        "video"
    ],
    "sg:website":"www.taninn.com",
    "wof:name":"Tan Inn",
    "wof:placetype":"venue"
},
  "geometry": {"coordinates":[-75.505697,39.151782],"type":"Point"}
}