{
  "type": "Feature",
  "properties": {
    "addr:full":"135 2nd St Lewes DE 19958",
    "addr:housenumber":"135",
    "addr:postcode":"19958",
    "addr:street":"2Nd St",
    "iso:country":"US",
    "sg:address":"135 2nd St",
    "sg:city":"Lewes",
    "sg:classifiers":[
        {
            "category":"Insurance",
            "subcategory":"Insurance Agent",
            "type":"Services"
        }
    ],
    "sg:phone":"+1 302 645 9344",
    "sg:postcode":"19958",
    "sg:province":"DE",
    "wof:name":"Progressive Insurance Co",
    "wof:placetype":"venue"
},
  "geometry": {"coordinates":[-75.13952999999999,38.77535],"type":"Point"}
}