{
  "type": "Feature",
  "properties": {
    "addr:full":"113 E Cochran St Middletown DE 19709",
    "addr:housenumber":"113",
    "addr:postcode":"19709",
    "addr:street":"E Cochran St",
    "iso:country":"US",
    "sg:address":"113 E Cochran St",
    "sg:city":"Middletown",
    "sg:classifiers":[
        {
            "category":"Recreation",
            "type":"Entertainment"
        }
    ],
    "sg:phone":"+1 302 378 4605",
    "sg:postcode":"19709",
    "sg:province":"DE",
    "sg:tags":[
        "club",
        "membership"
    ],
    "wof:name":"Little League Baseball In",
    "wof:placetype":"venue"
},
  "geometry": {"coordinates":[-75.71255600000001,39.44796],"type":"Point"}
}