{
  "type": "Feature",
  "properties": {
    "iso:country":"US",
    "sg:address":"118 Atlantic Ave",
    "sg:city":"Ocean View",
    "sg:classifiers":[
        {
            "category":"Health Services",
            "subcategory":"Doctor",
            "type":"Services"
        }
    ],
    "sg:phone":"+1 302 537 6110",
    "sg:postcode":"19970",
    "sg:province":"DE",
    "sg:tags":[
        "physician",
        "surgeon"
    ],
    "wof:name":"Bonnie L Burnquist MD",
    "wof:placetype":"venue"
},
  "geometry": {"coordinates":[-75.081,38.542581],"type":"Point"}
}