{
  "type": "Feature",
  "properties": {
    "addr:full":"504 Center Rd Magnolia DE 19962",
    "addr:housenumber":"504",
    "addr:postcode":"19962",
    "addr:street":"Center Rd",
    "iso:country":"US",
    "sg:address":"504 Center Rd",
    "sg:city":"Magnolia",
    "sg:classifiers":[
        {
            "category":"Retail",
            "subcategory":"Repair Shop",
            "type":"Services"
        }
    ],
    "sg:phone":"+1 302 399 7177",
    "sg:postcode":"19962",
    "sg:province":"DE",
    "sg:tags":[
        "cleaning"
    ],
    "wof:name":"D N B Cleaning",
    "wof:placetype":"venue"
},
  "geometry": {"coordinates":[-75.487832,39.098625],"type":"Point"}
}