{
  "type": "Feature",
  "properties": {
    "iso:country":"US",
    "sg:address":"28 Shady Rd",
    "sg:city":"Lewes",
    "sg:classifiers":[
        {
            "category":"Building & Trades",
            "subcategory":"Landscaping Services",
            "type":"Services"
        }
    ],
    "sg:phone":"+1 302 645 5330",
    "sg:postcode":"19958",
    "sg:province":"DE",
    "sg:tags":[
        "landscape",
        "contractor"
    ],
    "wof:name":"A American Tree Care",
    "wof:placetype":"venue"
},
  "geometry": {"coordinates":[-75.16980599999999,38.745252],"type":"Point"}
}