{
  "type": "Feature",
  "properties": {
    "iso:country":"US",
    "sg:address":"103 NE 6th St",
    "sg:city":"Milford",
    "sg:classifiers":[
        {
            "category":"Professional",
            "type":"Services"
        }
    ],
    "sg:phone":"+1 302 424 4050",
    "sg:postcode":"19963",
    "sg:province":"DE",
    "wof:name":"Russel Y Dolbeare Svc",
    "wof:placetype":"venue"
},
  "geometry": {"coordinates":[-75.427164,38.920029],"type":"Point"}
}