{
  "type": "Feature",
  "properties": {
    "iso:country":"US",
    "sg:address":"1910 Delaware Ave",
    "sg:city":"Wilmington",
    "sg:classifiers":[
        {
            "category":"Communications",
            "subcategory":"Film & Video Production",
            "type":"Services"
        }
    ],
    "sg:phone":"+1 302 427 2330",
    "sg:postcode":"19806",
    "sg:province":"DE",
    "sg:tags":[
        "taping"
    ],
    "wof:name":"Silver Hand Productions Inc",
    "wof:placetype":"venue"
},
  "geometry": {"coordinates":[-75.565299,39.760428],"type":"Point"}
}