{
  "type": "Feature",
  "properties": {
    "iso:country":"US",
    "sg:address":"111 Lake Dr",
    "sg:city":"Newark",
    "sg:classifiers":[
        {
            "category":"Wholesale",
            "subcategory":"Auto Parts",
            "type":"Manufacturing & Wholesale Goods"
        }
    ],
    "sg:phone":"+1 302 454 1417",
    "sg:postcode":"19702",
    "sg:province":"DE",
    "sg:tags":[
        "brakes"
    ],
    "wof:name":"Dana Brakes & Chassis",
    "wof:placetype":"venue"
},
  "geometry": {"coordinates":[-75.75251799999999,39.619174],"type":"Point"}
}