{
  "type": "Feature",
  "properties": {
    "iso:country":"US",
    "sg:address":"501 Silverside Rd",
    "sg:city":"Wilmington",
    "sg:classifiers":[
        {
            "category":"Professional",
            "subcategory":"Employment Agencies",
            "type":"Services"
        }
    ],
    "sg:phone":"+1 302 791 0213",
    "sg:postcode":"19809",
    "sg:province":"DE",
    "sg:tags":[
        "help",
        "supply"
    ],
    "wof:name":"Ado Staffing Inc",
    "wof:placetype":"venue"
},
  "geometry": {"coordinates":[-75.48805900000001,39.79023],"type":"Point"}
}