{
  "type": "Feature",
  "properties": {
    "iso:country":"US",
    "sg:address":"410 Foulk Rd",
    "sg:city":"Wilmington",
    "sg:classifiers":[
        {
            "category":"Health Services",
            "subcategory":"Medical Lab",
            "type":"Services"
        }
    ],
    "sg:phone":"+1 302 765 2334",
    "sg:postcode":"19803",
    "sg:province":"DE",
    "sg:tags":[
        "laboratory"
    ],
    "wof:name":"Omega Medical Laboratories",
    "wof:placetype":"venue"
},
  "geometry": {"coordinates":[-75.53994299999999,39.782164],"type":"Point"}
}