{
  "type": "Feature",
  "properties": {
    "iso:country":"US",
    "sg:address":"150 Clinton St",
    "sg:city":"Delaware City",
    "sg:classifiers":[
        {
            "category":"Organizations",
            "subcategory":"Non-profit Organization",
            "type":"Services"
        }
    ],
    "sg:phone":"+1 302 834 9336",
    "sg:postcode":"19706",
    "sg:province":"DE",
    "wof:name":"De City Fire Co",
    "wof:placetype":"venue"
},
  "geometry": {"coordinates":[-75.590523,39.576922],"type":"Point"}
}