{
  "type": "Feature",
  "properties": {
    "addr:full":"228 Hawkes Ct Hockessin DE 19707",
    "addr:housenumber":"228",
    "addr:postcode":"19707",
    "addr:street":"Hawkes Ct",
    "iso:country":"US",
    "sg:address":"228 Hawkes Ct",
    "sg:city":"Hockessin",
    "sg:classifiers":[
        {
            "category":"Social Services",
            "subcategory":"Child Care",
            "type":"Services"
        }
    ],
    "sg:phone":"+1 302 234 8052",
    "sg:postcode":"19707",
    "sg:province":"DE",
    "sg:tags":[
        "day"
    ],
    "wof:name":"Sheri Gebbia Day Care",
    "wof:placetype":"venue"
},
  "geometry": {"coordinates":[-75.678308,39.779723],"type":"Point"}
}