{
  "type": "Feature",
  "properties": {
    "addr:full":"16 S Poplar St Wilmington DE 19801",
    "addr:housenumber":"16",
    "addr:postcode":"19801",
    "addr:street":"S Poplar St",
    "iso:country":"US",
    "sg:address":"16 S Poplar St",
    "sg:city":"Wilmington",
    "sg:classifiers":[
        {
            "category":"Government",
            "subcategory":"Office",
            "type":"Public Place"
        }
    ],
    "sg:phone":"+1 302 429 2230",
    "sg:postcode":"19801",
    "sg:province":"DE",
    "sg:tags":[
        "government-united",
        "state"
    ],
    "sg:website":"http://www.amtrak.com",
    "wof:name":"Amtrak",
    "wof:placetype":"venue"
},
  "geometry": {"coordinates":[-75.548984,39.736316],"type":"Point"}
}