{
  "type": "Feature",
  "properties": {
    "iso:country":"US",
    "sg:address":"3102 Wilmont Dr",
    "sg:city":"Wilmington",
    "sg:classifiers":[
        {
            "category":"Professional",
            "subcategory":"Credit Reporting & Collection",
            "type":"Services"
        }
    ],
    "sg:phone":"+1 302 477 1869",
    "sg:postcode":"19810",
    "sg:province":"DE",
    "sg:tags":[
        "agency"
    ],
    "wof:name":"K-LAK Corp",
    "wof:placetype":"venue"
},
  "geometry": {"coordinates":[-75.535172,39.809639],"type":"Point"}
}