{
  "type": "Feature",
  "properties": {
    "addr:full":"102 Newton Dr Bear DE 19701",
    "addr:housenumber":"102",
    "addr:postcode":"19701",
    "addr:street":"Newton Dr",
    "iso:country":"US",
    "sg:address":"102 Newton Dr",
    "sg:city":"Bear",
    "sg:classifiers":[
        {
            "category":"Manufacturing",
            "subcategory":"Printing",
            "type":"Manufacturing & Wholesale Goods"
        }
    ],
    "sg:phone":"+1 302 325 3343",
    "sg:postcode":"19701",
    "sg:province":"DE",
    "sg:tags":[
        "firm",
        "marketing",
        "graphic",
        "design",
        "communications"
    ],
    "wof:name":"Bodyinblackcom Inc",
    "wof:placetype":"venue"
},
  "geometry": {"coordinates":[-75.663158,39.651416],"type":"Point"}
}