{
  "type": "Feature",
  "properties": {
    "iso:country":"US",
    "sg:address":"644 S Queen St",
    "sg:city":"Dover",
    "sg:classifiers":[
        {
            "category":"Health Services",
            "subcategory":"Doctor",
            "type":"Services"
        }
    ],
    "sg:phone":"+1 302 678 9002",
    "sg:postcode":"19904",
    "sg:province":"DE",
    "wof:name":"Kaplan William M MD",
    "wof:placetype":"venue"
},
  "geometry": {"coordinates":[-75.528835,39.151705],"type":"Point"}
}