{
  "type": "Feature",
  "properties": {
    "iso:country":"US",
    "sg:address":"3445 Harris Rd",
    "sg:city":"Townsend",
    "sg:classifiers":[
        {
            "category":"Retail",
            "subcategory":"Auto Repair",
            "type":"Services"
        }
    ],
    "sg:phone":"+1 302 378 1701",
    "sg:postcode":"19734",
    "sg:province":"DE",
    "sg:tags":[
        "body",
        "automobile",
        "customizing",
        "painting",
        "repairing"
    ],
    "sg:website":"http://www.rhodescustomauto.com",
    "wof:name":"Rhodes Custom Auto Works",
    "wof:placetype":"venue"
},
  "geometry": {"coordinates":[-75.65876799999999,39.425614],"type":"Point"}
}