{
  "type": "Feature",
  "properties": {
    "addr:full":"127 Garey Dr Felton DE 19943",
    "addr:housenumber":"127",
    "addr:postcode":"19943",
    "addr:street":"Garey Dr",
    "iso:country":"US",
    "sg:address":"127 Garey Dr",
    "sg:city":"Felton",
    "sg:classifiers":[
        {
            "category":"Real Estate",
            "subcategory":"Real Estate Agent",
            "type":"Services"
        }
    ],
    "sg:phone":"+1 302 284 4945",
    "sg:postcode":"19943",
    "sg:province":"DE",
    "wof:name":"John Schulties Real Estate",
    "wof:placetype":"venue"
},
  "geometry": {"coordinates":[-75.587833,39.013193],"type":"Point"}
}