{
  "type": "Feature",
  "properties": {
    "addr:full":"4437 Kirkwood Hwy Wilmington DE 19808",
    "addr:housenumber":"4437",
    "addr:postcode":"19808",
    "addr:street":"Kirkwood Hwy",
    "iso:country":"US",
    "sg:address":"4437 Kirkwood Hwy",
    "sg:city":"Wilmington",
    "sg:classifiers":[
        {
            "category":"Shopping",
            "subcategory":"Department Store",
            "type":"Retail Goods"
        }
    ],
    "sg:phone":"+1 302 633 9960",
    "sg:postcode":"19808",
    "sg:province":"DE",
    "wof:name":"Kohl's",
    "wof:placetype":"venue"
},
  "geometry": {"coordinates":[-75.652719,39.726744],"type":"Point"}
}