{
  "type": "Feature",
  "properties": {
    "iso:country":"US",
    "sg:address":"315 Airport Rd",
    "sg:city":"New Castle",
    "sg:classifiers":[
        {
            "category":"Building & Trades",
            "subcategory":"Construction",
            "type":"Services"
        }
    ],
    "sg:phone":"+1 302 633 6670",
    "sg:postcode":"19720",
    "sg:province":"DE",
    "sg:tags":[
        "paving",
        "contractor"
    ],
    "wof:name":"Concrete Work Unltd",
    "wof:placetype":"venue"
},
  "geometry": {"coordinates":[-75.616711,39.689956],"type":"Point"}
}