{
  "type": "Feature",
  "properties": {
    "iso:country":"US",
    "sg:address":"4 Copper Dr",
    "sg:city":"Wilmington",
    "sg:classifiers":[
        {
            "category":"Professional",
            "subcategory":"Art Services",
            "type":"Services"
        }
    ],
    "sg:phone":"+1 302 636 9193",
    "sg:postcode":"19804",
    "sg:province":"DE",
    "sg:tags":[
        "me",
        "design"
    ],
    "wof:name":"Comer Cory",
    "wof:placetype":"venue"
},
  "geometry": {"coordinates":[-75.599492,39.713193],"type":"Point"}
}