{
  "type": "Feature",
  "properties": {
    "addr:full":"609 Atlantic Ave Millville DE 19968",
    "addr:housenumber":"609",
    "addr:postcode":"19968",
    "addr:street":"Atlantic Ave",
    "iso:country":"US",
    "sg:address":"609 Atlantic Ave",
    "sg:city":"Millville",
    "sg:classifiers":[
        {
            "category":"Health Services",
            "subcategory":"Doctor",
            "type":"Services"
        }
    ],
    "sg:phone":"+1 302 541 8138",
    "sg:postcode":"19968",
    "sg:province":"DE",
    "sg:tags":[
        "physician",
        "surgeon"
    ],
    "wof:name":"Cardiology Consultants",
    "wof:placetype":"venue"
},
  "geometry": {"coordinates":[-75.307793,38.78374],"type":"Point"}
}