{
  "type": "Feature",
  "properties": {
    "addr:full":"737 S Queen St Ste 2 Dover DE 19904",
    "addr:housenumber":"737",
    "addr:postcode":"19904",
    "addr:street":"S Queen St Ste 2",
    "iso:country":"US",
    "sg:address":"737 S Queen St Ste 2",
    "sg:city":"Dover",
    "sg:classifiers":[
        {
            "category":"Health Services",
            "subcategory":"Doctor",
            "type":"Services"
        }
    ],
    "sg:phone":"+1 302 735 8850",
    "sg:postcode":"19904",
    "sg:province":"DE",
    "wof:name":"Glenn John F III MD",
    "wof:placetype":"venue"
},
  "geometry": {"coordinates":[-75.528999,39.149799],"type":"Point"}
}