{
  "type": "Feature",
  "properties": {
    "iso:country":"US",
    "sg:address":"2115 Hillside Rd",
    "sg:city":"Wilmington",
    "sg:classifiers":[
        {
            "category":"Retail",
            "subcategory":"Repair Shop",
            "type":"Services"
        }
    ],
    "sg:phone":"+1 302 475 3557",
    "sg:postcode":"19810",
    "sg:province":"DE",
    "sg:tags":[
        "plumbing"
    ],
    "wof:name":"City Plumbing & Heating Inc",
    "wof:placetype":"venue"
},
  "geometry": {"coordinates":[-75.492203,39.811298],"type":"Point"}
}