{
  "type": "Feature",
  "properties": {
    "iso:country":"US",
    "sg:address":"410 N Cass St",
    "sg:city":"Middletown",
    "sg:classifiers":[
        {
            "category":"Insurance",
            "subcategory":"Insurance Agent",
            "type":"Services"
        }
    ],
    "sg:phone":"+1 302 449 0306",
    "sg:postcode":"19709",
    "sg:province":"DE",
    "sg:tags":[
        "consultant"
    ],
    "wof:name":"Westfield Insurance",
    "wof:placetype":"venue"
},
  "geometry": {"coordinates":[-75.719993,39.453235],"type":"Point"}
}