{
  "type": "Feature",
  "properties": {
    "iso:country":"US",
    "sg:address":"2207 Naamans Rd",
    "sg:city":"Wilmington",
    "sg:classifiers":[
        {
            "category":"Home & Garden",
            "subcategory":"Household Appliances",
            "type":"Retail Goods"
        }
    ],
    "sg:phone":"+1 302 762 2969",
    "sg:postcode":"19810",
    "sg:province":"DE",
    "sg:tags":[
        "repair"
    ],
    "wof:name":"Vernon & Vernon Fuel Oil Service",
    "wof:placetype":"venue"
},
  "geometry": {"coordinates":[-75.505501,39.8256],"type":"Point"}
}