{
  "type": "Feature",
  "properties": {
    "iso:country":"US",
    "sg:address":"323 Barney Jenkins Rd",
    "sg:city":"Felton",
    "sg:classifiers":[
        {
            "category":"Organizations",
            "subcategory":"Religious Organization",
            "type":"Services"
        }
    ],
    "sg:phone":"+1 302 284 2449",
    "sg:postcode":"19943",
    "sg:province":"DE",
    "wof:name":"Aump Church",
    "wof:placetype":"venue"
},
  "geometry": {"coordinates":[-75.54925299999999,39.059775],"type":"Point"}
}