{
  "type": "Feature",
  "properties": {
    "iso:country":"US",
    "sg:address":"3511 Silverside Rd",
    "sg:city":"Wilmington",
    "sg:classifiers":[
        {
            "category":"Professional",
            "type":"Services"
        }
    ],
    "sg:phone":"+1 302 477 8913",
    "sg:postcode":"19810",
    "sg:province":"DE",
    "wof:name":"Comrec Services LP",
    "wof:placetype":"venue"
},
  "geometry": {"coordinates":[-75.548903,39.809257],"type":"Point"}
}