{
  "type": "Feature",
  "properties": {
    "addr:full":"1911 Foulk Rd Wilmington DE 19810",
    "addr:housenumber":"1911",
    "addr:postcode":"19810",
    "addr:street":"Foulk Rd",
    "iso:country":"US",
    "sg:address":"1911 Foulk Rd",
    "sg:city":"Wilmington",
    "sg:classifiers":[
        {
            "category":"Health Services",
            "subcategory":"Chiropractor",
            "type":"Services"
        }
    ],
    "sg:phone":"+1 610 485 9800",
    "sg:postcode":"19810",
    "sg:province":"DE",
    "wof:name":"Travis Arthur W DC",
    "wof:placetype":"venue"
},
  "geometry": {"coordinates":[-75.512199,39.811798],"type":"Point"}
}