{
  "type": "Feature",
  "properties": {
    "addr:full":"130 Copper Dr Newport DE 19804",
    "addr:housenumber":"130",
    "addr:postcode":"19804",
    "addr:street":"Copper Dr",
    "iso:country":"US",
    "sg:address":"130 Copper Dr",
    "sg:city":"Newport",
    "sg:classifiers":[
        {
            "category":"Autos & Motor Vehicles",
            "subcategory":"Automobile Sales",
            "type":"Retail Goods"
        }
    ],
    "sg:phone":"+1 302 996 9524",
    "sg:postcode":"19804",
    "sg:province":"DE",
    "sg:tags":[
        "car",
        "dealer"
    ],
    "wof:name":"Cheap & Charming Auto's",
    "wof:placetype":"venue"
},
  "geometry": {"coordinates":[-75.599304,39.712825],"type":"Point"}
}