{
  "type": "Feature",
  "properties": {
    "iso:country":"US",
    "sg:address":"204 S Park Dr",
    "sg:city":"Wilmington",
    "sg:classifiers":[
        {
            "category":"Building & Trades",
            "subcategory":"Construction",
            "type":"Services"
        }
    ],
    "sg:phone":"+1 302 791 0188",
    "sg:postcode":"19809",
    "sg:province":"DE",
    "sg:tags":[
        "general",
        "contractor"
    ],
    "wof:name":"Preferred Contractors Inc",
    "wof:placetype":"venue"
},
  "geometry": {"coordinates":[-75.481498,39.787998],"type":"Point"}
}