{
  "type": "Feature",
  "properties": {
    "iso:country":"US",
    "sg:address":"328 Delaware Cir",
    "sg:city":"Newark",
    "sg:classifiers":[
        {
            "category":"Arts & Performance",
            "subcategory":"Theater",
            "type":"Entertainment"
        }
    ],
    "sg:phone":"+1 302 368 1636",
    "sg:postcode":"19711",
    "sg:province":"DE",
    "sg:tags":[
        "musician"
    ],
    "wof:name":"Bips Egnor's Music",
    "wof:placetype":"venue"
},
  "geometry": {"coordinates":[-75.73809799999999,39.682163],"type":"Point"}
}