{
  "type": "Feature",
  "properties": {
    "addr:full":"110 N Dupont Hwy New Castle DE 19720",
    "addr:housenumber":"110",
    "addr:postcode":"19720",
    "addr:street":"N Dupont Hwy",
    "iso:country":"US",
    "sg:address":"110 N Dupont Hwy",
    "sg:city":"New Castle",
    "sg:classifiers":[
        {
            "category":"Manufacturing",
            "subcategory":"Apparel",
            "type":"Manufacturing & Wholesale Goods"
        },
        {
            "category":"Shopping",
            "subcategory":"Clothing, Apparel, & Fashions",
            "type":"Retail Goods"
        }
    ],
    "sg:phone":"+1 302 328 2256",
    "sg:postcode":"19720",
    "sg:province":"DE",
    "sg:tags":[
        "t"
    ],
    "wof:name":"Sketchery",
    "wof:placetype":"venue"
},
  "geometry": {"coordinates":[-75.59318,39.677097],"type":"Point"}
}