{
  "type": "Feature",
  "properties": {
    "addr:full":"412 E Ayre St Wilmington DE 19804",
    "addr:housenumber":"412",
    "addr:postcode":"19804",
    "addr:street":"E Ayre St",
    "iso:country":"US",
    "sg:address":"412 E Ayre St",
    "sg:city":"Wilmington",
    "sg:classifiers":[
        {
            "category":"Building & Trades",
            "subcategory":"Construction",
            "type":"Services"
        }
    ],
    "sg:phone":"+1 302 633 4332",
    "sg:postcode":"19804",
    "sg:province":"DE",
    "sg:tags":[
        "house"
    ],
    "wof:name":"Highland Construction Inc",
    "wof:placetype":"venue"
},
  "geometry": {"coordinates":[-75.602986,39.713338],"type":"Point"}
}