{
  "type": "Feature",
  "properties": {
    "addr:full":"26 Wyoming Ave Dover DE 19904",
    "addr:housenumber":"26",
    "addr:postcode":"19904",
    "addr:street":"Wyoming Ave",
    "iso:country":"US",
    "sg:address":"26 Wyoming Ave",
    "sg:city":"Dover",
    "sg:classifiers":[
        {
            "category":"Real Estate",
            "subcategory":"Real Estate Operator",
            "type":"Services"
        }
    ],
    "sg:phone":"+1 302 678 3652",
    "sg:postcode":"19904",
    "sg:province":"DE",
    "sg:tags":[
        "apartment"
    ],
    "wof:name":"Leonard Apartments",
    "wof:placetype":"venue"
},
  "geometry": {"coordinates":[-75.522918,39.143562],"type":"Point"}
}