{
  "type": "Feature",
  "properties": {
    "iso:country":"US",
    "sg:address":"1530 Butler Rd",
    "sg:city":"Harrington",
    "sg:phone":"+1 302 398 4696",
    "sg:postcode":"19952",
    "sg:province":"DE",
    "sg:tags":[
        "farm",
        "corn",
        "wheat",
        "soybean"
    ],
    "wof:name":"Charles Short",
    "wof:placetype":"venue"
},
  "geometry": {"coordinates":[-75.540432,38.923315],"type":"Point"}
}