{
  "type": "Feature",
  "properties": {
    "iso:country":"US",
    "sg:address":"295 S Dupont Hwy",
    "sg:city":"Dover",
    "sg:classifiers":[
        {
            "category":"Banks & Credit Unions",
            "subcategory":"Bank",
            "type":"Services"
        },
        {
            "category":"Banks & Credit Unions",
            "subcategory":"Financial Services",
            "type":"Services"
        }
    ],
    "sg:phone":"+1 800 432 1000",
    "sg:postcode":"19901",
    "sg:province":"DE",
    "sg:tags":[
        "broker",
        "mortgage"
    ],
    "sg:website":"Www.Bankofamerica.Com",
    "wof:name":"Bank of America Atm",
    "wof:placetype":"venue"
},
  "geometry": {"coordinates":[-75.51172099999999,39.157665],"type":"Point"}
}