{
  "type": "Feature",
  "properties": {
    "iso:country":"US",
    "sg:address":"107 S Maple Ave",
    "sg:city":"Milford",
    "sg:classifiers":[
        {
            "category":"Education",
            "subcategory":"Dance Studio",
            "type":"Public Place"
        }
    ],
    "sg:phone":"+1 302 422 2633",
    "sg:postcode":"19963",
    "sg:province":"DE",
    "wof:name":"Diamond Dance Co",
    "wof:placetype":"venue"
},
  "geometry": {"coordinates":[-75.43102399999999,38.910073],"type":"Point"}
}