{
  "type": "Feature",
  "properties": {
    "iso:country":"US",
    "sg:address":"206 Philadelphia St",
    "sg:city":"Rehoboth Beach",
    "sg:classifiers":[
        {
            "category":"Banks & Credit Unions",
            "subcategory":"Financial Services",
            "type":"Services"
        }
    ],
    "sg:phone":"+1 302 227 4207",
    "sg:postcode":"19971",
    "sg:province":"DE",
    "sg:tags":[
        "trust",
        "management"
    ],
    "wof:name":"International Assoc of LI",
    "wof:placetype":"venue"
},
  "geometry": {"coordinates":[-75.079854,38.713916],"type":"Point"}
}