{
  "type": "Feature",
  "properties": {
    "addr:full":"112 Senatorial Dr Wilmington DE 19807",
    "addr:housenumber":"112",
    "addr:postcode":"19807",
    "addr:street":"Senatorial Dr",
    "iso:country":"US",
    "sg:address":"112 Senatorial Dr",
    "sg:city":"Wilmington",
    "sg:classifiers":[
        {
            "category":"Health Services",
            "subcategory":"Doctor",
            "type":"Services"
        }
    ],
    "sg:phone":"+1 302 427 8092",
    "sg:postcode":"19807",
    "sg:province":"DE",
    "sg:tags":[
        "medical"
    ],
    "wof:name":"Gabriele Simonini Dr",
    "wof:placetype":"venue"
},
  "geometry": {"coordinates":[-75.596628,39.774371],"type":"Point"}
}