{
  "type": "Feature",
  "properties": {
    "iso:country":"US",
    "sg:address":"23 University Dr",
    "sg:city":"Newark",
    "sg:classifiers":[
        {
            "category":"Shopping",
            "subcategory":"Clothing, Apparel, & Fashions",
            "type":"Retail Goods"
        }
    ],
    "sg:phone":"+1 302 369 5639",
    "sg:postcode":"19702",
    "sg:province":"DE",
    "wof:name":"Rainbow 818",
    "wof:placetype":"venue"
},
  "geometry": {"coordinates":[-75.669279,39.666503],"type":"Point"}
}