{
  "type": "Feature",
  "properties": {
    "addr:full":"1812 Marsh Rd Ste 401 Wilmington DE 19810",
    "addr:housenumber":"1812",
    "addr:postcode":"19810",
    "addr:street":"Marsh Rd Ste 401",
    "iso:country":"US",
    "sg:address":"1812 Marsh Rd Ste 401",
    "sg:city":"Wilmington",
    "sg:classifiers":[
        {
            "category":"Banks & Credit Unions",
            "subcategory":"Bank",
            "type":"Services"
        }
    ],
    "sg:phone":"+1 302 475 8331",
    "sg:postcode":"19810",
    "sg:province":"DE",
    "sg:website":"www.delawarenational.com",
    "wof:name":"Delaware National Bank",
    "wof:placetype":"venue"
},
  "geometry": {"coordinates":[-75.503829,39.803819],"type":"Point"}
}