{
  "type": "Feature",
  "properties": {
    "addr:full":"12 Rehoboth Ave Rehoboth Beach DE 19971",
    "addr:housenumber":"12",
    "addr:postcode":"19971",
    "addr:street":"Rehoboth Ave",
    "iso:country":"US",
    "sg:address":"12 Rehoboth Ave",
    "sg:city":"Rehoboth Beach",
    "sg:classifiers":[
        {
            "category":"Shopping",
            "subcategory":"Jewelry",
            "type":"Retail Goods"
        }
    ],
    "sg:phone":"+1 302 227 6049",
    "sg:postcode":"19971",
    "sg:province":"DE",
    "sg:tags":[
        "jeweler"
    ],
    "wof:name":"Touch Of Class",
    "wof:placetype":"venue"
},
  "geometry": {"coordinates":[-75.076449,38.716417],"type":"Point"}
}