{
  "type": "Feature",
  "properties": {
    "iso:country":"US",
    "sg:address":"44 Pleasanton Dr",
    "sg:city":"Dover",
    "sg:classifiers":[
        {
            "category":"Shopping",
            "subcategory":"Discount & Variety Stores",
            "type":"Retail Goods"
        }
    ],
    "sg:phone":"+1 302 492 8091",
    "sg:postcode":"19901",
    "sg:province":"DE",
    "sg:tags":[
        "salvage",
        "surplus",
        "merchandise"
    ],
    "wof:name":"Cannon Iron & Metal Inc",
    "wof:placetype":"venue"
},
  "geometry": {"coordinates":[-75.50209,39.20126],"type":"Point"}
}