{
  "type": "Feature",
  "properties": {
    "addr:full":"18 Fox Hunt Dr Bear DE 19701",
    "addr:housenumber":"18",
    "addr:postcode":"19701",
    "addr:street":"Fox Hunt Dr",
    "iso:country":"US",
    "sg:address":"18 Fox Hunt Dr",
    "sg:city":"Bear",
    "sg:classifiers":[
        {
            "category":"Food & Beverages",
            "subcategory":"Specialty",
            "type":"Retail Goods"
        }
    ],
    "sg:phone":"+1 302 832 8484",
    "sg:postcode":"19701",
    "sg:province":"DE",
    "sg:tags":[
        "health",
        "diet"
    ],
    "wof:name":"General Nutrition Ctr",
    "wof:placetype":"venue"
},
  "geometry": {"coordinates":[-75.712295,39.608613],"type":"Point"}
}