{
  "type": "Feature",
  "properties": {
    "iso:country":"US",
    "sg:address":"7707 Lindale Rd",
    "sg:city":"Greenwood",
    "sg:classifiers":[
        {
            "category":"Manufacturing",
            "subcategory":"Tools & Machinery",
            "type":"Manufacturing & Wholesale Goods"
        }
    ],
    "sg:phone":"+1 302 424 0750",
    "sg:postcode":"19950",
    "sg:province":"DE",
    "sg:tags":[
        "machine",
        "shop"
    ],
    "wof:name":"Nanticoke Consulting and McHy",
    "wof:placetype":"venue"
},
  "geometry": {"coordinates":[-75.48938699999999,38.872541],"type":"Point"}
}