{
  "type": "Feature",
  "properties": {
    "addr:full":"443 Rose Dale Ln Dover DE 19904",
    "addr:housenumber":"443",
    "addr:postcode":"19904",
    "addr:street":"Rose Dale Ln",
    "iso:country":"US",
    "sg:address":"443 Rose Dale Ln",
    "sg:city":"Dover",
    "sg:classifiers":[
        {
            "category":"Building & Trades",
            "subcategory":"Construction",
            "type":"Services"
        }
    ],
    "sg:phone":"+1 302 222 6480",
    "sg:postcode":"19904",
    "sg:province":"DE",
    "sg:tags":[
        "deck",
        "altering",
        "consultant",
        "builder",
        "handyman",
        "contractor",
        "remodeling",
        "patio"
    ],
    "wof:name":"John Mast Construction",
    "wof:placetype":"venue"
},
  "geometry": {"coordinates":[-75.629977,39.202642],"type":"Point"}
}