{
  "type": "Feature",
  "properties": {
    "iso:country":"US",
    "sg:address":"2601 Pike Creek Rd",
    "sg:city":"Newark",
    "sg:classifiers":[
        {
            "category":"Real Estate",
            "subcategory":"Real Estate Operator",
            "type":"Services"
        }
    ],
    "sg:phone":"+1 302 738 7954",
    "sg:postcode":"19711",
    "sg:province":"DE",
    "sg:tags":[
        "apartment"
    ],
    "wof:name":"Hockessin",
    "wof:placetype":"venue"
},
  "geometry": {"coordinates":[-75.68180099999999,39.709511],"type":"Point"}
}