{
  "type": "Feature",
  "properties": {
    "iso:country":"US",
    "sg:address":"4016 Carpenter Bridge Rd",
    "sg:city":"Felton",
    "sg:classifiers":[
        {
            "category":"Farming",
            "subcategory":"Farm",
            "type":"Manufacturing & Wholesale Goods"
        }
    ],
    "sg:phone":"+1 302 335 3426",
    "sg:postcode":"19943",
    "sg:province":"DE",
    "sg:tags":[
        "crop",
        "general"
    ],
    "wof:name":"Louis Starkey",
    "wof:placetype":"venue"
},
  "geometry": {"coordinates":[-75.514974,38.969661],"type":"Point"}
}