{
  "type": "Feature",
  "properties": {
    "iso:country":"US",
    "sg:address":"2 Pennsylvania Ave",
    "sg:city":"Rehoboth Beach",
    "sg:classifiers":[
        {
            "category":"Banks & Credit Unions",
            "subcategory":"Bank",
            "type":"Services"
        }
    ],
    "sg:phone":"+1 302 537 4100",
    "sg:postcode":"19971",
    "sg:province":"DE",
    "sg:tags":[
        "loan",
        "real estate"
    ],
    "wof:name":"Mercantile Mortgage Corp",
    "wof:placetype":"venue"
},
  "geometry": {"coordinates":[-75.077513,38.723565],"type":"Point"}
}