{
  "type": "Feature",
  "properties": {
    "iso:country":"US",
    "sg:address":"605 N Market St",
    "sg:city":"Wilmington",
    "sg:classifiers":[
        {
            "category":"Arts & Performance",
            "subcategory":"Theater",
            "type":"Entertainment"
        }
    ],
    "sg:phone":"+1 302 661 2060",
    "sg:postcode":"19801",
    "sg:province":"DE",
    "sg:tags":[
        "bureau"
    ],
    "wof:name":"Get Rich Entertainment",
    "wof:placetype":"venue"
},
  "geometry": {"coordinates":[-75.549875,39.742651],"type":"Point"}
}