{
  "type": "Feature",
  "properties": {
    "iso:country":"US",
    "sg:address":"17295 Apple Tree Rd",
    "sg:city":"Bridgeville",
    "sg:classifiers":[
        {
            "category":"Building & Trades",
            "subcategory":"Electrical",
            "type":"Services"
        }
    ],
    "sg:phone":"+1 302 337 3850",
    "sg:postcode":"19933",
    "sg:province":"DE",
    "sg:tags":[
        "electric",
        "contractor"
    ],
    "wof:name":"Ray's Electrical Svc",
    "wof:placetype":"venue"
},
  "geometry": {"coordinates":[-75.551727,38.750865],"type":"Point"}
}