{
  "type": "Feature",
  "properties": {
    "addr:full":"19 Cinnamon Dr Hockessin DE 19707",
    "addr:housenumber":"19",
    "addr:postcode":"19707",
    "addr:street":"Cinnamon Dr",
    "iso:country":"US",
    "sg:address":"19 Cinnamon Dr",
    "sg:city":"Hockessin",
    "sg:classifiers":[
        {
            "category":"Shopping",
            "subcategory":"Musical Instruments",
            "type":"Retail Goods"
        }
    ],
    "sg:phone":"+1 302 239 9262",
    "sg:postcode":"19707",
    "sg:province":"DE",
    "wof:name":"Music On The Move Inc",
    "wof:placetype":"venue"
},
  "geometry": {"coordinates":[-75.671301,39.783139],"type":"Point"}
}