{
  "type": "Feature",
  "properties": {
    "addr:full":"122 Silver Lake Rd Middletown DE 19709",
    "addr:housenumber":"122",
    "addr:postcode":"19709",
    "addr:street":"Silver Lake Rd",
    "iso:country":"US",
    "sg:address":"122 Silver Lake Rd",
    "sg:city":"Middletown",
    "sg:classifiers":[
        {
            "category":"Government",
            "subcategory":"Office",
            "type":"Public Place"
        }
    ],
    "sg:phone":"+1 302 378 5779",
    "sg:postcode":"19709",
    "sg:province":"DE",
    "sg:tags":[
        "rehabilitation",
        "vocational"
    ],
    "wof:name":"Appoquinimink St Serv Ctr",
    "wof:placetype":"venue"
},
  "geometry": {"coordinates":[-75.696416,39.449391],"type":"Point"}
}