{
  "type": "Feature",
  "properties": {
    "iso:country":"US",
    "sg:address":"3220 Philadelphia Pike",
    "sg:city":"Claymont",
    "sg:classifiers":[
        {
            "category":"Bakery",
            "type":"Food & Drink"
        },
        {
            "category":"Coffee & Tea",
            "type":"Food & Drink"
        },
        {
            "category":"Bagels",
            "type":"Food & Drink"
        },
        {
            "category":"Donuts",
            "type":"Food & Drink"
        }
    ],
    "sg:menulink":"http://www.allmenus.com/de/brandywine/130265-dunkin-donuts/menu/",
    "sg:phone":"+1 302 793 1530",
    "sg:postcode":"19703",
    "sg:province":"DE",
    "sg:tags":[
        "american",
        "diner",
        "pastry"
    ],
    "wof:name":"Dunkin' Donuts",
    "wof:placetype":"venue"
},
  "geometry": {"coordinates":[-75.461799,39.7994],"type":"Point"}
}