{
  "type": "Feature",
  "properties": {
    "iso:country":"US",
    "sg:address":"120 W Water St",
    "sg:city":"Dover",
    "sg:classifiers":[
        {
            "category":"Shopping",
            "subcategory":"Clothing, Apparel, & Fashions",
            "type":"Retail Goods"
        }
    ],
    "sg:phone":"+1 302 730 8123",
    "sg:postcode":"19901",
    "sg:province":"DE",
    "sg:tags":[
        "t"
    ],
    "wof:name":"T Shirt Outlet",
    "wof:placetype":"venue"
},
  "geometry": {"coordinates":[-75.523644,39.154576],"type":"Point"}
}