{
  "type": "Feature",
  "properties": {
    "iso:country":"US",
    "sg:address":"117 New London Rd",
    "sg:city":"Newark",
    "sg:classifiers":[
        {
            "category":"Building & Trades",
            "subcategory":"Construction",
            "type":"Services"
        }
    ],
    "sg:phone":"+1 302 369 9361",
    "sg:postcode":"19711",
    "sg:province":"DE",
    "sg:tags":[
        "house"
    ],
    "wof:name":"Tands Construction",
    "wof:placetype":"venue"
},
  "geometry": {"coordinates":[-75.759534,39.687156],"type":"Point"}
}