{
  "type": "Feature",
  "properties": {
    "iso:country":"US",
    "sg:address":"2210 W 9th St",
    "sg:city":"Wilmington",
    "sg:classifiers":[
        {
            "category":"Building & Trades",
            "subcategory":"Construction",
            "type":"Services"
        }
    ],
    "sg:phone":"+1 302 656 9311",
    "sg:postcode":"19805",
    "sg:province":"DE",
    "sg:tags":[
        "wood",
        "installation",
        "refinishing",
        "floor"
    ],
    "wof:name":"Dominic A Di Febo & Sons",
    "wof:placetype":"venue"
},
  "geometry": {"coordinates":[-75.57276,39.754616],"type":"Point"}
}