{
  "type": "Feature",
  "properties": {
    "addr:full":"312 Lark Dr Newark DE 19713",
    "addr:housenumber":"312",
    "addr:postcode":"19713",
    "addr:street":"Lark Dr",
    "iso:country":"US",
    "sg:address":"312 Lark Dr",
    "sg:city":"Newark",
    "sg:classifiers":[
        {
            "category":"Professional",
            "type":"Services"
        }
    ],
    "sg:phone":"+1 302 368 5978",
    "sg:postcode":"19713",
    "sg:province":"DE",
    "sg:tags":[
        "engineering"
    ],
    "wof:name":"Rosenburg David and Assn",
    "wof:placetype":"venue"
},
  "geometry": {"coordinates":[-75.764144,39.655562],"type":"Point"}
}