{
  "type": "Feature",
  "properties": {
    "iso:country":"US",
    "sg:address":"1 Commerce St",
    "sg:city":"Wilmington",
    "sg:classifiers":[
        {
            "category":"Professional",
            "type":"Services"
        }
    ],
    "sg:phone":"+1 302 656 7712",
    "sg:postcode":"19801",
    "sg:province":"DE",
    "wof:name":"Whittington & Aulgur",
    "wof:placetype":"venue"
},
  "geometry": {"coordinates":[-75.536046,39.735161],"type":"Point"}
}