{
  "type": "Feature",
  "properties": {
    "iso:country":"US",
    "sg:address":"1115 S Governors Ave",
    "sg:city":"Dover",
    "sg:classifiers":[
        {
            "category":"Restaurant",
            "type":"Food & Drink"
        }
    ],
    "sg:phone":"+1 302 730 3551",
    "sg:postcode":"19904",
    "sg:province":"DE",
    "wof:name":"Nikos' Restaurant",
    "wof:placetype":"venue"
},
  "geometry": {"coordinates":[-75.525772,39.139871],"type":"Point"}
}