{
  "type": "Feature",
  "properties": {
    "iso:country":"US",
    "sg:address":"1315 Greenleaf Rd",
    "sg:city":"Wilmington",
    "sg:classifiers":[
        {
            "category":"Retail",
            "subcategory":"Repair Shop",
            "type":"Services"
        }
    ],
    "sg:phone":"+1 302 998 0139",
    "sg:postcode":"19805",
    "sg:province":"DE",
    "wof:name":"Starlights Cleaning",
    "wof:placetype":"venue"
},
  "geometry": {"coordinates":[-75.59433199999999,39.746422],"type":"Point"}
}