{
  "type": "Feature",
  "properties": {
    "addr:full":"604 Langwater Dr Newark DE 19711",
    "addr:housenumber":"604",
    "addr:postcode":"19711",
    "addr:street":"Langwater Dr",
    "iso:country":"US",
    "sg:address":"604 Langwater Dr",
    "sg:city":"Newark",
    "sg:classifiers":[
        {
            "category":"Insurance",
            "subcategory":"Hazard Insurance",
            "type":"Services"
        }
    ],
    "sg:phone":"+1 302 239 6160",
    "sg:postcode":"19711",
    "sg:province":"DE",
    "sg:tags":[
        "commercial",
        "business"
    ],
    "wof:name":"Harper Donald E Insurance Agency Inc",
    "wof:placetype":"venue"
},
  "geometry": {"coordinates":[-75.735293,39.763044],"type":"Point"}
}