{
  "type": "Feature",
  "properties": {
    "addr:full":"73 Rehoboth Ave Rehoboth Beach DE 19971",
    "addr:housenumber":"73",
    "addr:postcode":"19971",
    "addr:street":"Rehoboth Ave",
    "iso:country":"US",
    "sg:address":"73 Rehoboth Ave",
    "sg:city":"Rehoboth Beach",
    "sg:classifiers":[
        {
            "category":"Government",
            "subcategory":"Court House",
            "type":"Public Place"
        }
    ],
    "sg:phone":"+1 302 227 7917",
    "sg:postcode":"19971",
    "sg:province":"DE",
    "wof:name":"Alderman Court 37",
    "wof:placetype":"venue"
},
  "geometry": {"coordinates":[-75.07846600000001,38.716615],"type":"Point"}
}