{
  "type": "Feature",
  "properties": {
    "iso:country":"US",
    "sg:address":"2107 Wildwood Dr",
    "sg:city":"Wilmington",
    "sg:classifiers":[
        {
            "category":"Shopping",
            "subcategory":"Used Merchandise",
            "type":"Retail Goods"
        }
    ],
    "sg:phone":"+1 302 995 1992",
    "sg:postcode":"19805",
    "sg:province":"DE",
    "wof:name":"Danny & Janes Antique",
    "wof:placetype":"venue"
},
  "geometry": {"coordinates":[-75.620441,39.748325],"type":"Point"}
}