{
  "type": "Feature",
  "properties": {
    "iso:country":"US",
    "sg:address":"600 S Bay Rd",
    "sg:city":"Dover",
    "sg:classifiers":[
        {
            "category":"Autos & Motor Vehicles",
            "subcategory":"Automobile Sales",
            "type":"Retail Goods"
        }
    ],
    "sg:phone":"+1 302 736 8450",
    "sg:postcode":"19901",
    "sg:province":"DE",
    "wof:name":"Cruise In Auto Sales",
    "wof:placetype":"venue"
},
  "geometry": {"coordinates":[-75.508346,39.155579],"type":"Point"}
}