{
  "type": "Feature",
  "properties": {
    "iso:country":"US",
    "sg:address":"1505 Naamans Rd",
    "sg:city":"Wilmington",
    "sg:classifiers":[
        {
            "category":"Organizations",
            "subcategory":"Religious Organization",
            "type":"Services"
        }
    ],
    "sg:phone":"+1 302 475 5000",
    "sg:postcode":"19810",
    "sg:province":"DE",
    "wof:name":"Levinautics Transport Tech",
    "wof:placetype":"venue"
},
  "geometry": {"coordinates":[-75.480625,39.821606],"type":"Point"}
}