{
  "type": "Feature",
  "properties": {
    "addr:full":"105 Wilton Blvd New Castle DE 19720",
    "addr:housenumber":"105",
    "addr:postcode":"19720",
    "addr:street":"Wilton Blvd",
    "iso:country":"US",
    "sg:address":"105 Wilton Blvd",
    "sg:city":"New Castle",
    "sg:classifiers":[
        {
            "category":"Restaurant",
            "type":"Food & Drink"
        }
    ],
    "sg:menulink":"http://www.allmenus.com/de/new-castle/84619-applebees/menu/",
    "sg:phone":"+1 302 322 8202",
    "sg:postcode":"19720",
    "sg:province":"DE",
    "sg:tags":[
        "burger",
        "american",
        "sandwich",
        "soup"
    ],
    "wof:name":"Applebee's",
    "wof:placetype":"venue"
},
  "geometry": {"coordinates":[-75.623169,39.651878],"type":"Point"}
}