{
  "type": "Feature",
  "properties": {
    "addr:full":"71 Gainsborough Dr Lewes DE 19958",
    "addr:housenumber":"71",
    "addr:postcode":"19958",
    "addr:street":"Gainsborough Dr",
    "iso:country":"US",
    "sg:address":"71 Gainsborough Dr",
    "sg:city":"Lewes",
    "sg:classifiers":[
        {
            "category":"Professional",
            "type":"Services"
        }
    ],
    "sg:phone":"+1 302 644 1070",
    "sg:postcode":"19958",
    "sg:province":"DE",
    "wof:name":"Gibson William II",
    "wof:placetype":"venue"
},
  "geometry": {"coordinates":[-75.160668,38.740732],"type":"Point"}
}