{
  "type": "Feature",
  "properties": {
    "addr:full":"611 3rd St Seaford DE 19973",
    "addr:housenumber":"611",
    "addr:postcode":"19973",
    "addr:street":"3Rd St",
    "iso:country":"US",
    "sg:address":"611 3rd St",
    "sg:city":"Seaford",
    "sg:classifiers":[
        {
            "category":"Organizations",
            "subcategory":"Religious Organization",
            "type":"Services"
        }
    ],
    "sg:phone":"+1 302 629 2559",
    "sg:postcode":"19973",
    "sg:province":"DE",
    "wof:name":"Seaford Mission",
    "wof:placetype":"venue"
},
  "geometry": {"coordinates":[-75.609178,38.644762],"type":"Point"}
}