{
  "type": "Feature",
  "properties": {
    "iso:country":"US",
    "sg:address":"108 Cunard St",
    "sg:city":"Wilmington",
    "sg:classifiers":[
        {
            "category":"Social Services",
            "type":"Services"
        }
    ],
    "sg:phone":"+1 302 998 8387",
    "sg:postcode":"19804",
    "sg:province":"DE",
    "sg:tags":[
        "counseling"
    ],
    "wof:name":"Joshua Counseling Biblical Ctr",
    "wof:placetype":"venue"
},
  "geometry": {"coordinates":[-75.62199099999999,39.723533],"type":"Point"}
}