{
  "type": "Feature",
  "properties": {
    "iso:country":"US",
    "sg:address":"68 Church St",
    "sg:city":"Selbyville",
    "sg:classifiers":[
        {
            "category":"Government",
            "subcategory":"Police Station",
            "type":"Public Place"
        }
    ],
    "sg:phone":"+1 302 436 8334",
    "sg:postcode":"19975",
    "sg:province":"DE",
    "sg:tags":[
        "department"
    ],
    "wof:name":"Selbyville Police Dept",
    "wof:placetype":"venue"
},
  "geometry": {"coordinates":[-75.22763399999999,38.457322],"type":"Point"}
}