{
  "type": "Feature",
  "properties": {
    "iso:country":"US",
    "sg:address":"100 N Dupont Hwy",
    "sg:city":"Dover",
    "sg:classifiers":[
        {
            "category":"Banks & Credit Unions",
            "subcategory":"Bank",
            "type":"Services"
        }
    ],
    "sg:phone":"+1 302 736 2920",
    "sg:postcode":"19901",
    "sg:province":"DE",
    "wof:name":"First Union",
    "wof:placetype":"venue"
},
  "geometry": {"coordinates":[-75.516822,39.165459],"type":"Point"}
}