{
  "type": "Feature",
  "properties": {
    "iso:country":"US",
    "sg:address":"23 Sherin Dr",
    "sg:city":"Newark",
    "sg:classifiers":[
        {
            "category":"Building & Trades",
            "subcategory":"Cleaning & Sanitation",
            "type":"Services"
        }
    ],
    "sg:phone":"+1 302 738 1721",
    "sg:postcode":"19702",
    "sg:province":"DE",
    "sg:tags":[
        "maintenance"
    ],
    "wof:name":"M&K Cleaning Service",
    "wof:placetype":"venue"
},
  "geometry": {"coordinates":[-75.699366,39.637114],"type":"Point"}
}