{
  "type": "Feature",
  "properties": {
    "addr:full":"165 Commerce Way Dover DE 19904",
    "addr:housenumber":"165",
    "addr:postcode":"19904",
    "addr:street":"Commerce Way",
    "iso:country":"US",
    "sg:address":"165 Commerce Way",
    "sg:city":"Dover",
    "sg:classifiers":[
        {
            "category":"Professional",
            "type":"Services"
        }
    ],
    "sg:phone":"+1 302 735 9672",
    "sg:postcode":"19904",
    "sg:province":"DE",
    "wof:name":"Opportunity Center of Dover",
    "wof:placetype":"venue"
},
  "geometry": {"coordinates":[-75.55047999999999,39.15183],"type":"Point"}
}