{
  "type": "Feature",
  "properties": {
    "iso:country":"US",
    "sg:address":"1001 E Matson Run Pkwy",
    "sg:city":"Wilmington",
    "sg:classifiers":[
        {
            "category":"Shopping",
            "type":"Retail Goods"
        }
    ],
    "sg:phone":"+1 302 762 0322",
    "sg:postcode":"19802",
    "sg:province":"DE",
    "sg:tags":[
        "craft",
        "gallery",
        "dealer"
    ],
    "wof:name":"Artisans III",
    "wof:placetype":"venue"
},
  "geometry": {"coordinates":[-75.52855700000001,39.772124],"type":"Point"}
}