{
  "type": "Feature",
  "properties": {
    "iso:country":"US",
    "sg:address":"4272 Judith Rd",
    "sg:city":"Dover",
    "sg:classifiers":[
        {
            "category":"Building & Trades",
            "subcategory":"Construction",
            "type":"Services"
        }
    ],
    "sg:phone":"+1 302 492 8620",
    "sg:postcode":"19904",
    "sg:province":"DE",
    "sg:tags":[
        "painter"
    ],
    "wof:name":"Sammon's Painting",
    "wof:placetype":"venue"
},
  "geometry": {"coordinates":[-75.668684,39.189046],"type":"Point"}
}