{
  "type": "Feature",
  "properties": {
    "iso:country":"US",
    "sg:address":"151 Kings Hwy",
    "sg:city":"Lewes",
    "sg:classifiers":[
        {
            "category":"Travel",
            "subcategory":"Hotels & Motels",
            "type":"Entertainment"
        }
    ],
    "sg:phone":"+1 302 645 6438",
    "sg:postcode":"19958",
    "sg:province":"DE",
    "sg:tags":[
        "breakfast",
        "accommodation",
        "bed"
    ],
    "wof:name":"King's Inn",
    "wof:placetype":"venue"
},
  "geometry": {"coordinates":[-75.14005,38.771652],"type":"Point"}
}