{
  "type": "Feature",
  "properties": {
    "addr:full":"365 Savannah Rd Lewes DE 19958",
    "addr:housenumber":"365",
    "addr:postcode":"19958",
    "addr:street":"Savannah Rd",
    "iso:country":"US",
    "sg:address":"365 Savannah Rd",
    "sg:city":"Lewes",
    "sg:classifiers":[
        {
            "category":"Insurance",
            "subcategory":"Insurance Agent",
            "type":"Services"
        }
    ],
    "sg:phone":"+1 302 645 6459",
    "sg:postcode":"19958",
    "sg:province":"DE",
    "wof:name":"Truitt Insurance",
    "wof:placetype":"venue"
},
  "geometry": {"coordinates":[-75.14102699999999,38.77241],"type":"Point"}
}