{
  "type": "Feature",
  "properties": {
    "addr:full":"701 Foulk Rd Wilmington DE 19803",
    "addr:housenumber":"701",
    "addr:postcode":"19803",
    "addr:street":"Foulk Rd",
    "iso:country":"US",
    "sg:address":"701 Foulk Rd",
    "sg:city":"Wilmington",
    "sg:classifiers":[
        {
            "category":"Health Services",
            "subcategory":"Doctor",
            "type":"Services"
        }
    ],
    "sg:phone":"+1 302 655 1100",
    "sg:postcode":"19803",
    "sg:province":"DE",
    "sg:tags":[
        "medical"
    ],
    "wof:name":"Center For Change",
    "wof:placetype":"venue"
},
  "geometry": {"coordinates":[-75.535492,39.787012],"type":"Point"}
}