{
  "type": "Feature",
  "properties": {
    "iso:country":"US",
    "sg:address":"161 Hubbard Ave",
    "sg:city":"Frederica",
    "sg:classifiers":[
        {
            "category":"Recreation",
            "type":"Entertainment"
        }
    ],
    "sg:phone":"+1 302 335 3500",
    "sg:postcode":"19946",
    "sg:province":"DE",
    "sg:tags":[
        "party",
        "fishing"
    ],
    "wof:name":"Donovan's Dock",
    "wof:placetype":"venue"
},
  "geometry": {"coordinates":[-75.40004,39.058662],"type":"Point"}
}