{
  "type": "Feature",
  "properties": {
    "iso:country":"US",
    "sg:address":"2131 S Dupont Hwy",
    "sg:city":"Dover",
    "sg:classifiers":[
        {
            "category":"Social Services",
            "type":"Services"
        }
    ],
    "sg:phone":"+1 302 698 0747",
    "sg:postcode":"19901",
    "sg:province":"DE",
    "wof:name":"Creative Choices",
    "wof:placetype":"venue"
},
  "geometry": {"coordinates":[-75.534297,39.119288],"type":"Point"}
}