{
  "type": "Feature",
  "properties": {
    "iso:country":"US",
    "sg:address":"201 New St",
    "sg:city":"Middletown",
    "sg:classifiers":[
        {
            "category":"Education",
            "subcategory":"School",
            "type":"Public Place"
        }
    ],
    "sg:phone":"+1 302 378 5030",
    "sg:postcode":"19709",
    "sg:province":"DE",
    "wof:name":"Redding Middle School",
    "wof:placetype":"venue"
},
  "geometry": {"coordinates":[-75.70881799999999,39.454026],"type":"Point"}
}