{
  "type": "Feature",
  "properties": {
    "iso:country":"US",
    "sg:address":"105 Lincoln Ave",
    "sg:city":"Delmar",
    "sg:classifiers":[
        {
            "category":"Building & Trades",
            "subcategory":"Construction",
            "type":"Services"
        }
    ],
    "sg:phone":"+1 302 875 5017",
    "sg:postcode":"19940",
    "sg:province":"DE",
    "sg:tags":[
        "water",
        "well",
        "drilling"
    ],
    "wof:name":"Atlantic Well Drilling Inc",
    "wof:placetype":"venue"
},
  "geometry": {"coordinates":[-75.576218,38.459411],"type":"Point"}
}