{
  "type": "Feature",
  "properties": {
    "addr:full":"3511 Silverside Rd Wilmington DE 19810",
    "addr:housenumber":"3511",
    "addr:postcode":"19810",
    "addr:street":"Silverside Rd",
    "iso:country":"US",
    "sg:address":"3511 Silverside Rd",
    "sg:city":"Wilmington",
    "sg:classifiers":[
        {
            "category":"Professional",
            "subcategory":"Lawyer & Legal Services",
            "type":"Services"
        }
    ],
    "sg:phone":"+1 302 478 1070",
    "sg:postcode":"19810",
    "sg:province":"DE",
    "wof:name":"Spritz Gary R Esquire",
    "wof:placetype":"venue"
},
  "geometry": {"coordinates":[-75.54360200000001,39.808899],"type":"Point"}
}