{
  "type": "Feature",
  "properties": {
    "iso:country":"US",
    "sg:address":"507 S Maryland Ave",
    "sg:city":"Wilmington",
    "sg:classifiers":[
        {
            "category":"Personal",
            "type":"Services"
        }
    ],
    "sg:phone":"+1 302 999 1400",
    "sg:postcode":"19804",
    "sg:province":"DE",
    "sg:tags":[
        "control",
        "weight"
    ],
    "wof:name":"Delaware Hypnosis Partner",
    "wof:placetype":"venue"
},
  "geometry": {"coordinates":[-75.591821,39.72434],"type":"Point"}
}