{
  "type": "Feature",
  "properties": {
    "iso:country":"US",
    "sg:address":"17 Polly Drummond Shpg Center",
    "sg:city":"Newark",
    "sg:classifiers":[
        {
            "category":"Government",
            "subcategory":"Office",
            "type":"Public Place"
        }
    ],
    "sg:phone":"+1 302 368 6980",
    "sg:postcode":"19711",
    "sg:province":"DE",
    "sg:tags":[
        "rehabilitation",
        "vocational"
    ],
    "wof:name":"Vocatnal Rhabilitation Del Div",
    "wof:placetype":"venue"
},
  "geometry": {"coordinates":[-75.71137899999999,39.719191],"type":"Point"}
}