{
  "type": "Feature",
  "properties": {
    "iso:country":"US",
    "sg:address":"37 Stevens Dr",
    "sg:city":"New Castle",
    "sg:classifiers":[
        {
            "category":"Building & Trades",
            "subcategory":"Construction",
            "type":"Services"
        }
    ],
    "sg:phone":"+1 302 328 3046",
    "sg:postcode":"19720",
    "sg:province":"DE",
    "sg:tags":[
        "siding",
        "contractor"
    ],
    "wof:name":"Fox Siding Inc",
    "wof:placetype":"venue"
},
  "geometry": {"coordinates":[-75.619197,39.658622],"type":"Point"}
}