{
  "type": "Feature",
  "properties": {
    "iso:country":"US",
    "sg:address":"806 Port Penn Rd",
    "sg:city":"Middletown",
    "sg:classifiers":[
        {
            "category":"Building & Trades",
            "subcategory":"Construction",
            "type":"Services"
        }
    ],
    "sg:phone":"+1 302 834 6798",
    "sg:postcode":"19709",
    "sg:province":"DE",
    "sg:tags":[
        "concrete",
        "contractor"
    ],
    "wof:name":"David Wham General Contractor",
    "wof:placetype":"venue"
},
  "geometry": {"coordinates":[-75.598843,39.518887],"type":"Point"}
}