{
  "type": "Feature",
  "properties": {
    "iso:country":"US",
    "sg:address":"257 E Camden Wyoming Ave",
    "sg:city":"Camden Wyoming",
    "sg:classifiers":[
        {
            "category":"Professional",
            "subcategory":"Accounting & Tax Preparation",
            "type":"Services"
        }
    ],
    "sg:phone":"+1 302 697 0940",
    "sg:postcode":"19934",
    "sg:province":"DE",
    "sg:tags":[
        "accountant"
    ],
    "wof:name":"Terrell Eleanor Judith CPA",
    "wof:placetype":"venue"
},
  "geometry": {"coordinates":[-75.54409800000001,39.113899],"type":"Point"}
}