{
  "type": "Feature",
  "properties": {
    "addr:full":"1601 Ogletown Rd Newark DE 19711",
    "addr:housenumber":"1601",
    "addr:postcode":"19711",
    "addr:street":"Ogletown Rd",
    "iso:country":"US",
    "sg:address":"1601 Ogletown Rd",
    "sg:city":"Newark",
    "sg:classifiers":[
        {
            "category":"Manufacturing",
            "subcategory":"Rubber & Plastics",
            "type":"Manufacturing & Wholesale Goods"
        }
    ],
    "sg:phone":"+1 302 453 9464",
    "sg:postcode":"19711",
    "sg:province":"DE",
    "sg:tags":[
        "bottle",
        "mfg"
    ],
    "wof:name":"Liquid Container LP",
    "wof:placetype":"venue"
},
  "geometry": {"coordinates":[-75.718817,39.683988],"type":"Point"}
}