{
  "type": "Feature",
  "properties": {
    "iso:country":"US",
    "sg:address":"11444 S Dupont Hwy",
    "sg:city":"Felton",
    "sg:classifiers":[
        {
            "category":"Autos & Motor Vehicles",
            "subcategory":"Fuel & Gas Station",
            "type":"Retail Goods"
        }
    ],
    "sg:phone":"+1 302 284 3457",
    "sg:postcode":"19943",
    "sg:province":"DE",
    "sg:tags":[
        "convenience",
        "station",
        "gasoline",
        "store"
    ],
    "wof:name":"Mobil",
    "wof:placetype":"venue"
},
  "geometry": {"coordinates":[-75.568685,38.996462],"type":"Point"}
}