{
  "type": "Feature",
  "properties": {
    "iso:country":"US",
    "sg:address":"10 Possum Park Rd",
    "sg:city":"Newark",
    "sg:classifiers":[
        {
            "category":"Restaurant",
            "type":"Food & Drink"
        }
    ],
    "sg:menulink":"http://www.allmenus.com/de/greater-newark/169471-wendys/menu/",
    "sg:phone":"+1 302 368 5464",
    "sg:postcode":"19711",
    "sg:province":"DE",
    "sg:tags":[
        "burger",
        "american",
        "soup"
    ],
    "wof:name":"Wendy's",
    "wof:placetype":"venue"
},
  "geometry": {"coordinates":[-75.719802,39.695093],"type":"Point"}
}