{
  "type": "Feature",
  "properties": {
    "iso:country":"US",
    "sg:address":"35 Osprey Ln",
    "sg:city":"Ocean View",
    "sg:classifiers":[
        {
            "category":"Professional",
            "subcategory":"Business Services",
            "type":"Services"
        }
    ],
    "sg:phone":"+1 302 537 6309",
    "sg:postcode":"19970",
    "sg:province":"DE",
    "wof:name":"Sg Technology Enterprises Inc",
    "wof:placetype":"venue"
},
  "geometry": {"coordinates":[-75.084367,38.546929],"type":"Point"}
}