{
  "type": "Feature",
  "properties": {
    "addr:full":"135 Gordon Pl Dover DE 19901",
    "addr:housenumber":"135",
    "addr:postcode":"19901",
    "addr:street":"Gordon Pl",
    "iso:country":"US",
    "sg:address":"135 Gordon Pl",
    "sg:city":"Dover",
    "sg:classifiers":[
        {
            "category":"Building & Trades",
            "subcategory":"Construction",
            "type":"Services"
        }
    ],
    "sg:phone":"+1 302 734 9636",
    "sg:postcode":"19901",
    "sg:province":"DE",
    "sg:tags":[
        "wallcoverings-installation",
        "wallpaper"
    ],
    "wof:name":"Cms Painting",
    "wof:placetype":"venue"
},
  "geometry": {"coordinates":[-75.51811600000001,39.18789],"type":"Point"}
}