{
  "type": "Feature",
  "properties": {
    "iso:country":"US",
    "sg:address":"900 N King St",
    "sg:city":"Wilmington",
    "sg:classifiers":[
        {
            "category":"Government",
            "subcategory":"Court House",
            "type":"Public Place"
        }
    ],
    "sg:phone":"+1 302 571 2200",
    "sg:postcode":"19801",
    "sg:province":"DE",
    "wof:name":"Family Court of Delaware",
    "wof:placetype":"venue"
},
  "geometry": {"coordinates":[-75.54695100000001,39.745205],"type":"Point"}
}