{
  "type": "Feature",
  "properties": {
    "iso:country":"US",
    "sg:address":"210 Union Church Rd",
    "sg:city":"Townsend",
    "sg:classifiers":[
        {
            "category":"Building & Trades",
            "subcategory":"Landscaping Services",
            "type":"Services"
        }
    ],
    "sg:phone":"+1 302 378 0937",
    "sg:postcode":"19734",
    "sg:province":"DE",
    "sg:tags":[
        "landscape"
    ],
    "wof:name":"New Creation Landscaping",
    "wof:placetype":"venue"
},
  "geometry": {"coordinates":[-75.657464,39.384913],"type":"Point"}
}