{
  "type": "Feature",
  "properties": {
    "iso:country":"US",
    "sg:address":"7401 Society Dr",
    "sg:city":"Claymont",
    "sg:classifiers":[
        {
            "category":"Building & Trades",
            "subcategory":"Pest Control",
            "type":"Services"
        }
    ],
    "sg:phone":"+1 302 778 1447",
    "sg:postcode":"19703",
    "sg:province":"DE",
    "wof:name":"Target Pest Control",
    "wof:placetype":"venue"
},
  "geometry": {"coordinates":[-75.45894699999999,39.821509],"type":"Point"}
}