{
  "type": "Feature",
  "properties": {
    "iso:country":"US",
    "sg:address":"1220 N Market St",
    "sg:city":"Wilmington",
    "sg:classifiers":[
        {
            "category":"Professional",
            "subcategory":"Business Services",
            "type":"Services"
        }
    ],
    "sg:phone":"+1 866 856 1678",
    "sg:postcode":"19802",
    "sg:province":"DE",
    "sg:tags":[
        "financial"
    ],
    "wof:name":"Bloomfield Financial Svcs Corp",
    "wof:placetype":"venue"
},
  "geometry": {"coordinates":[-75.546111,39.747964],"type":"Point"}
}