{
  "type": "Feature",
  "properties": {
    "iso:country":"US",
    "sg:address":"1176 Elkton Rd",
    "sg:city":"Newark",
    "sg:classifiers":[
        {
            "category":"Recreation",
            "type":"Entertainment"
        }
    ],
    "sg:phone":"+1 302 737 8892",
    "sg:postcode":"19711",
    "sg:province":"DE",
    "wof:name":"Samantha Psychic",
    "wof:placetype":"venue"
},
  "geometry": {"coordinates":[-75.788318,39.654924],"type":"Point"}
}