{
  "type": "Feature",
  "properties": {
    "iso:country":"US",
    "sg:address":"1600 Chelmsford Cir",
    "sg:city":"Newark",
    "sg:classifiers":[
        {
            "category":"Retail",
            "subcategory":"Laundry & Dry Cleaning",
            "type":"Services"
        },
        {
            "category":"Building & Trades",
            "subcategory":"Cleaning & Sanitation",
            "type":"Services"
        },
        {
            "category":"Home & Garden",
            "subcategory":"Carpets & Floor Coverings",
            "type":"Retail Goods"
        }
    ],
    "sg:phone":"+1 302 368 2787",
    "sg:postcode":"19713",
    "sg:province":"DE",
    "sg:tags":[
        "cleaner",
        "upholstery",
        "rug"
    ],
    "wof:name":"Gross Carpet Cleaning Co",
    "wof:placetype":"venue"
},
  "geometry": {"coordinates":[-75.702163,39.666272],"type":"Point"}
}