{
  "type": "Feature",
  "properties": {
    "iso:country":"US",
    "sg:address":"327 Wyoming Rd",
    "sg:city":"Newark",
    "sg:classifiers":[
        {
            "category":"Organizations",
            "subcategory":"Community Association",
            "type":"Services"
        }
    ],
    "sg:phone":"+1 302 738 5197",
    "sg:postcode":"19711",
    "sg:province":"DE",
    "wof:name":"Alpha Sigma Alpha Sorority",
    "wof:placetype":"venue"
},
  "geometry": {"coordinates":[-75.744139,39.676201],"type":"Point"}
}