{
  "type": "Feature",
  "properties": {
    "iso:country":"US",
    "sg:address":"263 E Main St",
    "sg:city":"Newark",
    "sg:classifiers":[
        {
            "category":"Building & Trades",
            "subcategory":"Construction",
            "type":"Services"
        }
    ],
    "sg:phone":"+1 302 738 1990",
    "sg:postcode":"19711",
    "sg:province":"DE",
    "sg:tags":[
        "nonresidential",
        "general",
        "contractor"
    ],
    "wof:name":"J H Construction Inc",
    "wof:placetype":"venue"
},
  "geometry": {"coordinates":[-75.742574,39.683786],"type":"Point"}
}