{
  "type": "Feature",
  "properties": {
    "addr:full":"1280 Porter Rd Bear DE 19701",
    "addr:housenumber":"1280",
    "addr:postcode":"19701",
    "addr:street":"Porter Rd",
    "iso:country":"US",
    "sg:address":"1280 Porter Rd",
    "sg:city":"Bear",
    "sg:classifiers":[
        {
            "category":"Building & Trades",
            "subcategory":"Landscaping Services",
            "type":"Services"
        }
    ],
    "sg:phone":"+1 302 834 9100",
    "sg:postcode":"19701",
    "sg:province":"DE",
    "sg:tags":[
        "consultant",
        "designer",
        "landscape"
    ],
    "wof:name":"Priority Services",
    "wof:placetype":"venue"
},
  "geometry": {"coordinates":[-75.69016000000001,39.603457],"type":"Point"}
}