{
  "type": "Feature",
  "properties": {
    "iso:country":"US",
    "sg:address":"235 Hawkes Ct",
    "sg:city":"Hockessin",
    "sg:classifiers":[
        {
            "category":"Home & Garden",
            "subcategory":"Building Materials",
            "type":"Retail Goods"
        }
    ],
    "sg:phone":"+1 302 239 8449",
    "sg:postcode":"19707",
    "sg:province":"DE",
    "sg:tags":[
        "consulting",
        "manufacturing"
    ],
    "wof:name":"Greenbriar Group LLC",
    "wof:placetype":"venue"
},
  "geometry": {"coordinates":[-75.67806299999999,39.779812],"type":"Point"}
}