{
  "type": "Feature",
  "properties": {
    "addr:full":"22 Bethany Loop Bethany Beach DE 19930",
    "addr:housenumber":"22",
    "addr:postcode":"19930",
    "addr:street":"Bethany Loop",
    "iso:country":"US",
    "sg:address":"22 Bethany Loop",
    "sg:city":"Bethany Beach",
    "sg:classifiers":[
        {
            "category":"Real Estate",
            "subcategory":"Real Estate Agent",
            "type":"Services"
        }
    ],
    "sg:phone":"+1 302 539 4455",
    "sg:postcode":"19930",
    "sg:province":"DE",
    "wof:name":"Coldwell Banker",
    "wof:placetype":"venue"
},
  "geometry": {"coordinates":[-75.08142700000001,38.546695],"type":"Point"}
}