{
  "type": "Feature",
  "properties": {
    "iso:country":"US",
    "sg:address":"643 Yorklyn Rd",
    "sg:city":"Hockessin",
    "sg:classifiers":[
        {
            "category":"Retail",
            "subcategory":"Veterinary Services",
            "type":"Services"
        }
    ],
    "sg:phone":"+1 302 239 9464",
    "sg:postcode":"19707",
    "sg:province":"DE",
    "sg:tags":[
        "veterinarian"
    ],
    "wof:name":"Hockessin Animal Hospital",
    "wof:placetype":"venue"
},
  "geometry": {"coordinates":[-75.69363199999999,39.789393],"type":"Point"}
}