{
  "type": "Feature",
  "properties": {
    "iso:country":"US",
    "sg:address":"14 Rockford Xing",
    "sg:city":"Dover",
    "sg:classifiers":[
        {
            "category":"Real Estate",
            "subcategory":"Real Estate Operator",
            "type":"Services"
        }
    ],
    "sg:phone":"+1 302 674 2703",
    "sg:postcode":"19901",
    "sg:province":"DE",
    "sg:tags":[
        "apartment"
    ],
    "wof:name":"Laurels the",
    "wof:placetype":"venue"
},
  "geometry": {"coordinates":[-75.508301,39.171398],"type":"Point"}
}