{
  "type": "Feature",
  "properties": {
    "iso:country":"US",
    "sg:address":"2008 Pennsylvania Ave",
    "sg:city":"Wilmington",
    "sg:classifiers":[
        {
            "category":"Professional",
            "subcategory":"Business Services",
            "type":"Services"
        }
    ],
    "sg:phone":"+1 302 429 0652",
    "sg:postcode":"19806",
    "sg:province":"DE",
    "sg:tags":[
        "process",
        "server"
    ],
    "wof:name":"National Legal Process Servers",
    "wof:placetype":"venue"
},
  "geometry": {"coordinates":[-75.569091,39.75675],"type":"Point"}
}