{
  "type": "Feature",
  "properties": {
    "iso:country":"US",
    "sg:address":"3601 N Market St",
    "sg:city":"Wilmington",
    "sg:classifiers":[
        {
            "category":"Banks & Credit Unions",
            "subcategory":"Investment Brokerage",
            "type":"Services"
        }
    ],
    "sg:phone":"+1 302 762 6200",
    "sg:postcode":"19802",
    "sg:province":"DE",
    "sg:tags":[
        "security"
    ],
    "sg:website":"www.fidelitrade.net",
    "wof:name":"Fideli Trade",
    "wof:placetype":"venue"
},
  "geometry": {"coordinates":[-75.525487,39.759194],"type":"Point"}
}