{
  "type": "Feature",
  "properties": {
    "addr:full":"39 Basalt St Townsend DE 19734",
    "addr:housenumber":"39",
    "addr:postcode":"19734",
    "addr:street":"Basalt St",
    "iso:country":"US",
    "sg:address":"39 Basalt St",
    "sg:city":"Townsend",
    "sg:classifiers":[
        {
            "category":"Retail",
            "subcategory":"Repair Shop",
            "type":"Services"
        },
        {
            "category":"Professional",
            "subcategory":"Detective & Security Services",
            "type":"Services"
        }
    ],
    "sg:phone":"+1 302 584 6879",
    "sg:postcode":"19734",
    "sg:province":"DE",
    "sg:tags":[
        "skip",
        "tracing",
        "bail",
        "bond"
    ],
    "wof:name":"A-Z Bail Bonds",
    "wof:placetype":"venue"
},
  "geometry": {"coordinates":[-75.64577300000001,39.425254],"type":"Point"}
}