{
  "type": "Feature",
  "properties": {
    "iso:country":"US",
    "sg:address":"6 Hadco Rd",
    "sg:city":"Wilmington",
    "sg:classifiers":[
        {
            "category":"Manufacturing",
            "subcategory":"Tools & Machinery",
            "type":"Manufacturing & Wholesale Goods"
        }
    ],
    "sg:phone":"+1 302 999 0103",
    "sg:postcode":"19804",
    "sg:province":"DE",
    "sg:tags":[
        "machine",
        "shop",
        "job"
    ],
    "wof:name":"All Metals Fabricators Inc",
    "wof:placetype":"venue"
},
  "geometry": {"coordinates":[-75.58628899999999,39.739015],"type":"Point"}
}