{
  "type": "Feature",
  "properties": {
    "addr:full":"1702 Lovering Ave Wilmington DE 19806",
    "addr:housenumber":"1702",
    "addr:postcode":"19806",
    "addr:street":"Lovering Ave",
    "iso:country":"US",
    "sg:address":"1702 Lovering Ave",
    "sg:city":"Wilmington",
    "sg:classifiers":[
        {
            "category":"Banks & Credit Unions",
            "subcategory":"Investment Brokerage",
            "type":"Services"
        }
    ],
    "sg:phone":"+1 302 661 1627",
    "sg:postcode":"19806",
    "sg:province":"DE",
    "sg:tags":[
        "consultant",
        "planning",
        "financial"
    ],
    "wof:name":"S V Chantler & Co",
    "wof:placetype":"venue"
},
  "geometry": {"coordinates":[-75.5605,39.760798],"type":"Point"}
}