{
  "type": "Feature",
  "properties": {
    "iso:country":"US",
    "sg:address":"22730 Rum Bridge Rd",
    "sg:city":"Georgetown",
    "sg:classifiers":[
        {
            "category":"Professional",
            "type":"Services"
        }
    ],
    "sg:phone":"+1 302 855 0658",
    "sg:postcode":"19947",
    "sg:province":"DE",
    "wof:name":"James G Fox Fax",
    "wof:placetype":"venue"
},
  "geometry": {"coordinates":[-75.473491,38.671056],"type":"Point"}
}