{
  "type": "Feature",
  "properties": {
    "iso:country":"US",
    "sg:address":"2 E Bradys Ln",
    "sg:city":"Dover",
    "sg:classifiers":[
        {
            "category":"Manufacturing",
            "subcategory":"Signs",
            "type":"Manufacturing & Wholesale Goods"
        }
    ],
    "sg:phone":"+1 302 697 2181",
    "sg:postcode":"19901",
    "sg:province":"DE",
    "sg:tags":[
        "installs",
        "repair",
        "mfg"
    ],
    "wof:name":"Kent Sign Co Inc",
    "wof:placetype":"venue"
},
  "geometry": {"coordinates":[-75.51522199999999,39.114827],"type":"Point"}
}