{
  "type": "Feature",
  "properties": {
    "iso:country":"US",
    "sg:address":"162 E Green St",
    "sg:city":"Newark",
    "sg:classifiers":[
        {
            "category":"Professional",
            "subcategory":"Research",
            "type":"Services"
        }
    ],
    "sg:phone":"+1 302 831 2136",
    "sg:postcode":"19709",
    "sg:province":"DE",
    "sg:tags":[
        "nonphysical",
        "commercial"
    ],
    "wof:name":"Research Office- Vice Provost",
    "wof:placetype":"venue"
},
  "geometry": {"coordinates":[-75.713644,39.448659],"type":"Point"}
}