{
  "type": "Feature",
  "properties": {
    "addr:full":"160 E Main St Newark DE 19711",
    "addr:housenumber":"160",
    "addr:postcode":"19711",
    "addr:street":"E Main St",
    "iso:country":"US",
    "sg:address":"160 E Main St",
    "sg:city":"Newark",
    "sg:classifiers":[
        {
            "category":"Professional",
            "subcategory":"Computer Services",
            "type":"Services"
        }
    ],
    "sg:phone":"+1 302 453 8947",
    "sg:postcode":"19711",
    "sg:province":"DE",
    "sg:tags":[
        "programming"
    ],
    "sg:website":"www.bcs-inc.com",
    "wof:name":"Blair Computing Systems",
    "wof:placetype":"venue"
},
  "geometry": {"coordinates":[-75.747512,39.683483],"type":"Point"}
}