{
  "type": "Feature",
  "properties": {
    "addr:full":"1319 McKennans Church Rd Wilmington DE 19808",
    "addr:housenumber":"1319",
    "addr:postcode":"19808",
    "addr:street":"Mckennans Church Rd",
    "iso:country":"US",
    "sg:address":"1319 McKennans Church Rd",
    "sg:city":"Wilmington",
    "sg:classifiers":[
        {
            "category":"Cinema",
            "subcategory":"Movie Rental",
            "type":"Entertainment"
        }
    ],
    "sg:phone":"+1 302 994 1700",
    "sg:postcode":"19808",
    "sg:province":"DE",
    "sg:tags":[
        "leasing",
        "video",
        "disc",
        "tape"
    ],
    "wof:name":"Video Showplace",
    "wof:placetype":"venue"
},
  "geometry": {"coordinates":[-75.666191,39.731992],"type":"Point"}
}