{
  "type": "Feature",
  "properties": {
    "iso:country":"US",
    "sg:address":"18 Evans Rd",
    "sg:city":"Georgetown",
    "sg:classifiers":[
        {
            "category":"Building & Trades",
            "subcategory":"Construction",
            "type":"Services"
        }
    ],
    "sg:phone":"+1 302 854 9200",
    "sg:postcode":"19930",
    "sg:province":"DE",
    "sg:tags":[
        "paving",
        "contractor"
    ],
    "wof:name":"Black Rock Paving",
    "wof:placetype":"venue"
},
  "geometry": {"coordinates":[-75.05735900000001,38.549168],"type":"Point"}
}