{
  "type": "Feature",
  "properties": {
    "iso:country":"US",
    "sg:address":"5463 Pinehurst Dr",
    "sg:city":"Wilmington",
    "sg:classifiers":[
        {
            "category":"Personal",
            "subcategory":"Beauty Salon",
            "type":"Services"
        }
    ],
    "sg:phone":"+1 302 738 0753",
    "sg:postcode":"19808",
    "sg:province":"DE",
    "wof:name":"Lillies General Contracti",
    "wof:placetype":"venue"
},
  "geometry": {"coordinates":[-75.70038,39.731171],"type":"Point"}
}