{
  "type": "Feature",
  "properties": {
    "iso:country":"US",
    "sg:address":"20638 Cubbage Pond Rd",
    "sg:city":"Lincoln",
    "sg:classifiers":[
        {
            "category":"Organizations",
            "subcategory":"Labor Organization",
            "type":"Services"
        }
    ],
    "sg:phone":"+1 302 422 6245",
    "sg:postcode":"19960",
    "sg:province":"DE",
    "wof:name":"Laborers Intl Un N Amer",
    "wof:placetype":"venue"
},
  "geometry": {"coordinates":[-75.388952,38.863566],"type":"Point"}
}