{
  "type": "Feature",
  "properties": {
    "iso:country":"US",
    "sg:address":"118 Sassafras Dr",
    "sg:city":"Middletown",
    "sg:classifiers":[
        {
            "category":"Professional",
            "subcategory":"Computer Services",
            "type":"Services"
        }
    ],
    "sg:phone":"+1 302 218 7977",
    "sg:postcode":"19709",
    "sg:province":"DE",
    "sg:tags":[
        "consulting"
    ],
    "wof:name":"Fisher Tech Solutions",
    "wof:placetype":"venue"
},
  "geometry": {"coordinates":[-75.751366,39.458077],"type":"Point"}
}