{
  "type": "Feature",
  "properties": {
    "iso:country":"US",
    "sg:address":"329 E Camden Wyoming Ave",
    "sg:city":"Camden Wyoming",
    "sg:classifiers":[
        {
            "category":"Home & Garden",
            "subcategory":"Building Materials",
            "type":"Retail Goods"
        }
    ],
    "sg:phone":"+1 302 697 3281",
    "sg:postcode":"19934",
    "sg:province":"DE",
    "sg:tags":[
        "lumber"
    ],
    "wof:name":"Simpson Lumber Co",
    "wof:placetype":"venue"
},
  "geometry": {"coordinates":[-75.54136,39.113489],"type":"Point"}
}