{
  "type": "Feature",
  "properties": {
    "addr:full":"102 S Gerald Dr Newark DE 19713",
    "addr:housenumber":"102",
    "addr:postcode":"19713",
    "addr:street":"S Gerald Dr",
    "iso:country":"US",
    "sg:address":"102 S Gerald Dr",
    "sg:city":"Newark",
    "sg:classifiers":[
        {
            "category":"Building & Trades",
            "subcategory":"Landscaping Services",
            "type":"Services"
        }
    ],
    "sg:phone":"+1 302 753 4598",
    "sg:postcode":"19713",
    "sg:province":"DE",
    "sg:tags":[
        "landscape",
        "contractor"
    ],
    "wof:name":"Lester Lawn & Tree Co",
    "wof:placetype":"venue"
},
  "geometry": {"coordinates":[-75.680891,39.67436],"type":"Point"}
}