{
  "type": "Feature",
  "properties": {
    "addr:full":"14284 Whitesville Rd Delmar DE 19940",
    "addr:housenumber":"14284",
    "addr:postcode":"19940",
    "addr:street":"Whitesville Rd",
    "iso:country":"US",
    "sg:address":"14284 Whitesville Rd",
    "sg:city":"Delmar",
    "sg:classifiers":[
        {
            "category":"Retail",
            "subcategory":"Auto Repair",
            "type":"Services"
        }
    ],
    "sg:phone":"+1 302 875 4812",
    "sg:postcode":"19940",
    "sg:province":"DE",
    "sg:tags":[
        "automotive"
    ],
    "wof:name":"H & L Towing",
    "wof:placetype":"venue"
},
  "geometry": {"coordinates":[-75.493808,38.491202],"type":"Point"}
}