{
  "type": "Feature",
  "properties": {
    "iso:country":"US",
    "sg:address":"2500 Wrangle Hill Rd # 129",
    "sg:city":"Bear",
    "sg:classifiers":[
        {
            "category":"Professional",
            "subcategory":"Lawyer & Legal Services",
            "type":"Services"
        }
    ],
    "sg:phone":"+1 302 832 5600",
    "sg:postcode":"19701",
    "sg:province":"DE",
    "sg:tags":[
        "plan"
    ],
    "wof:name":"Sanclemente And Assoc",
    "wof:placetype":"venue"
},
  "geometry": {"coordinates":[-75.71528600000001,39.605991],"type":"Point"}
}