{
  "type": "Feature",
  "properties": {
    "iso:country":"US",
    "sg:address":"105 S New St",
    "sg:city":"Dover",
    "sg:classifiers":[
        {
            "category":"Organizations",
            "subcategory":"Non-profit Organization",
            "type":"Services"
        }
    ],
    "sg:phone":"+1 302 677 0116",
    "sg:postcode":"19904",
    "sg:province":"DE",
    "sg:tags":[
        "social"
    ],
    "wof:name":"House of Pride",
    "wof:placetype":"venue"
},
  "geometry": {"coordinates":[-75.528384,39.158115],"type":"Point"}
}