{
  "type": "Feature",
  "properties": {
    "addr:full":"1002 Society Dr Claymont DE 19703",
    "addr:housenumber":"1002",
    "addr:postcode":"19703",
    "addr:street":"Society Dr",
    "iso:country":"US",
    "sg:address":"1002 Society Dr",
    "sg:city":"Claymont",
    "sg:classifiers":[
        {
            "category":"Professional",
            "type":"Services"
        }
    ],
    "sg:phone":"+1 302 798 9677",
    "sg:postcode":"19703",
    "sg:province":"DE",
    "wof:name":"Wells Digital",
    "wof:placetype":"venue"
},
  "geometry": {"coordinates":[-75.461775,39.819203],"type":"Point"}
}