{
  "type": "Feature",
  "properties": {
    "iso:country":"US",
    "sg:address":"1661 S Dupont Hwy",
    "sg:city":"Dover",
    "sg:classifiers":[
        {
            "category":"Social Services",
            "type":"Services"
        }
    ],
    "sg:phone":"+1 302 735 9690",
    "sg:postcode":"19901",
    "sg:province":"DE",
    "sg:tags":[
        "center"
    ],
    "wof:name":"Bethany Christian Services",
    "wof:placetype":"venue"
},
  "geometry": {"coordinates":[-75.52936800000001,39.129729],"type":"Point"}
}