{
  "type": "Feature",
  "properties": {
    "iso:country":"US",
    "sg:address":"201 Dorman St",
    "sg:city":"Harrington",
    "sg:classifiers":[
        {
            "category":"Social Services",
            "type":"Services"
        }
    ],
    "sg:phone":"+1 302 398 8467",
    "sg:postcode":"19952",
    "sg:province":"DE",
    "wof:name":"Tony Perrone",
    "wof:placetype":"venue"
},
  "geometry": {"coordinates":[-75.58060500000001,38.927741],"type":"Point"}
}