{
  "type": "Feature",
  "properties": {
    "iso:country":"US",
    "sg:address":"149 Wiggins Mill Rd",
    "sg:city":"Townsend",
    "sg:classifiers":[
        {
            "category":"Building & Trades",
            "subcategory":"Landscaping Services",
            "type":"Services"
        }
    ],
    "sg:phone":"+1 302 378 1864",
    "sg:postcode":"19734",
    "sg:province":"DE",
    "wof:name":"Wright & Sons Lawn Service",
    "wof:placetype":"venue"
},
  "geometry": {"coordinates":[-75.72556299999999,39.421751],"type":"Point"}
}