{
  "type": "Feature",
  "properties": {
    "iso:country":"US",
    "sg:address":"200 S Claymont St",
    "sg:city":"Wilmington",
    "sg:classifiers":[
        {
            "category":"Organizations",
            "subcategory":"Professional Association",
            "type":"Services"
        }
    ],
    "sg:phone":"+1 302 655 6571",
    "sg:postcode":"19801",
    "sg:province":"DE",
    "wof:name":"Philadelphia Marine Trade Assn",
    "wof:placetype":"venue"
},
  "geometry": {"coordinates":[-75.54100099999999,39.730702],"type":"Point"}
}