{
  "type": "Feature",
  "properties": {
    "iso:country":"US",
    "sg:address":"1255 Quintilio Dr",
    "sg:city":"Bear",
    "sg:phone":"+1 302 838 1725",
    "sg:postcode":"19701",
    "sg:province":"DE",
    "wof:name":"Kennys Pan Asian Cuisine",
    "wof:placetype":"venue"
},
  "geometry": {"coordinates":[-75.669051,39.631215],"type":"Point"}
}