{
  "type": "Feature",
  "properties": {
    "iso:country":"US",
    "sg:address":"760 Pulaski Hwy",
    "sg:city":"Bear",
    "sg:classifiers":[
        {
            "category":"Autos & Motor Vehicles",
            "subcategory":"Auto Supplies",
            "type":"Retail Goods"
        }
    ],
    "sg:phone":"+1 302 322 9000",
    "sg:postcode":"19701",
    "sg:province":"DE",
    "sg:tags":[
        "tire"
    ],
    "wof:name":"Pete Farina's Discount Tire",
    "wof:placetype":"venue"
},
  "geometry": {"coordinates":[-75.633819,39.647449],"type":"Point"}
}