{
  "type": "Feature",
  "properties": {
    "iso:country":"US",
    "sg:address":"20 Rose Cir",
    "sg:city":"Newark",
    "sg:classifiers":[
        {
            "category":"Building & Trades",
            "subcategory":"Landscaping Services",
            "type":"Services"
        }
    ],
    "sg:phone":"+1 302 368 3747",
    "sg:postcode":"19711",
    "sg:province":"DE",
    "sg:tags":[
        "lawn",
        "garden"
    ],
    "wof:name":"Happy Lawn Care Inc",
    "wof:placetype":"venue"
},
  "geometry": {"coordinates":[-75.712322,39.6992],"type":"Point"}
}