{
  "type": "Feature",
  "properties": {
    "addr:full":"261 N Dupont Hwy Ste 3A Dover DE 19901",
    "addr:housenumber":"261",
    "addr:postcode":"19901",
    "addr:street":"N Dupont Hwy Ste 3A",
    "iso:country":"US",
    "sg:address":"261 N Dupont Hwy Ste 3A",
    "sg:city":"Dover",
    "sg:classifiers":[
        {
            "category":"Fast Food",
            "type":"Food & Drink"
        },
        {
            "category":"Restaurant",
            "type":"Food & Drink"
        },
        {
            "category":"Professional",
            "type":"Services"
        }
    ],
    "sg:phone":"+1 302 735 3333",
    "sg:postcode":"19901",
    "sg:province":"DE",
    "sg:tags":[
        "delivery",
        "pizza",
        "take",
        "italian"
    ],
    "sg:website":"www.dominos.com",
    "wof:name":"Domino's Pizza",
    "wof:placetype":"venue"
},
  "geometry": {"coordinates":[-75.518036,39.17042],"type":"Point"}
}