{
  "type": "Feature",
  "properties": {
    "iso:country":"US",
    "sg:address":"635 E 5th St",
    "sg:city":"Wilmington",
    "sg:classifiers":[
        {
            "category":"Shopping",
            "subcategory":"Clothing, Apparel, & Fashions",
            "type":"Retail Goods"
        }
    ],
    "sg:phone":"+1 302 571 9118",
    "sg:postcode":"19801",
    "sg:province":"DE",
    "wof:name":"Fashions By Denise",
    "wof:placetype":"venue"
},
  "geometry": {"coordinates":[-75.543762,39.738379],"type":"Point"}
}