{
  "type": "Feature",
  "properties": {
    "addr:full":"784 Nault Rd Dover DE 19904",
    "addr:housenumber":"784",
    "addr:postcode":"19904",
    "addr:street":"Nault Rd",
    "iso:country":"US",
    "sg:address":"784 Nault Rd",
    "sg:city":"Dover",
    "sg:classifiers":[
        {
            "category":"Building & Trades",
            "subcategory":"Construction",
            "type":"Services"
        }
    ],
    "sg:phone":"+1 302 670 7826",
    "sg:postcode":"19904",
    "sg:province":"DE",
    "sg:tags":[
        "contractor"
    ],
    "wof:name":"B & T Contracting",
    "wof:placetype":"venue"
},
  "geometry": {"coordinates":[-75.62434,39.13683],"type":"Point"}
}