{
  "type": "Feature",
  "properties": {
    "addr:full":"706 N Dupont Hwy Dover DE 19901",
    "addr:housenumber":"706",
    "addr:postcode":"19901",
    "addr:street":"N Dupont Hwy",
    "iso:country":"US",
    "sg:address":"706 N Dupont Hwy",
    "sg:city":"Dover",
    "sg:classifiers":[
        {
            "category":"Food & Beverages",
            "subcategory":"Groceries & Convenience Stores",
            "type":"Retail Goods"
        }
    ],
    "sg:phone":"+1 302 674 8360",
    "sg:postcode":"19901",
    "sg:province":"DE",
    "wof:name":"Uni-Mart",
    "wof:placetype":"venue"
},
  "geometry": {"coordinates":[-75.52746399999999,39.178874],"type":"Point"}
}