{
  "type": "Feature",
  "properties": {
    "addr:full":"107 Truitt Ave Rehoboth Beach DE 19971",
    "addr:housenumber":"107",
    "addr:postcode":"19971",
    "addr:street":"Truitt Ave",
    "iso:country":"US",
    "sg:address":"107 Truitt Ave",
    "sg:city":"Rehoboth Beach",
    "sg:classifiers":[
        {
            "category":"Professional",
            "type":"Services"
        }
    ],
    "sg:phone":"+1 302 645 0272",
    "sg:postcode":"19971",
    "sg:province":"DE",
    "wof:name":"Andrew Ludwig",
    "wof:placetype":"venue"
},
  "geometry": {"coordinates":[-75.133337,38.730092],"type":"Point"}
}