{
  "type": "Feature",
  "properties": {
    "addr:full":"2800 N Washington St Wilmington DE 19802",
    "addr:housenumber":"2800",
    "addr:postcode":"19802",
    "addr:street":"N Washington St",
    "iso:country":"US",
    "sg:address":"2800 N Washington St",
    "sg:city":"Wilmington",
    "sg:classifiers":[
        {
            "category":"Organizations",
            "subcategory":"Religious Organization",
            "type":"Services"
        }
    ],
    "sg:phone":"+1 302 764 7827",
    "sg:postcode":"19802",
    "sg:province":"DE",
    "sg:tags":[
        "church"
    ],
    "wof:name":"United Missionary Baptist Chr",
    "wof:placetype":"venue"
},
  "geometry": {"coordinates":[-75.535287,39.758514],"type":"Point"}
}