{
  "type": "Feature",
  "properties": {
    "iso:country":"US",
    "sg:address":"501 Silverside Rd",
    "sg:city":"Wilmington",
    "sg:classifiers":[
        {
            "category":"Wholesale",
            "subcategory":"Durable Goods & Equipment",
            "type":"Manufacturing & Wholesale Goods"
        }
    ],
    "sg:phone":"+1 302 798 8951",
    "sg:postcode":"19809",
    "sg:province":"DE",
    "sg:tags":[
        "representative",
        "manufacturer"
    ],
    "wof:name":"Lipton Investments",
    "wof:placetype":"venue"
},
  "geometry": {"coordinates":[-75.48805900000001,39.79023],"type":"Point"}
}