{
  "type": "Feature",
  "properties": {
    "addr:full":"112 E Glenwood Ave Smyrna DE 19977",
    "addr:housenumber":"112",
    "addr:postcode":"19977",
    "addr:street":"E Glenwood Ave",
    "iso:country":"US",
    "sg:address":"112 E Glenwood Ave",
    "sg:city":"Smyrna",
    "sg:classifiers":[
        {
            "category":"Shopping",
            "subcategory":"Computers & Home Electronics",
            "type":"Retail Goods"
        }
    ],
    "sg:phone":"+1 302 653 5645",
    "sg:postcode":"19977",
    "sg:province":"DE",
    "wof:name":"Radio Shack",
    "wof:placetype":"venue"
},
  "geometry": {"coordinates":[-75.608389,39.305166],"type":"Point"}
}