{
  "type": "Feature",
  "properties": {
    "iso:country":"US",
    "sg:address":"590 Naamans Rd",
    "sg:city":"Claymont",
    "sg:classifiers":[
        {
            "category":"Banks & Credit Unions",
            "subcategory":"Financial Services",
            "type":"Services"
        }
    ],
    "sg:phone":"+1 302 797 3469",
    "sg:postcode":"19703",
    "sg:province":"DE",
    "sg:tags":[
        "company",
        "holding"
    ],
    "wof:name":"Cigna",
    "wof:placetype":"venue"
},
  "geometry": {"coordinates":[-75.445954,39.813034],"type":"Point"}
}