{
  "type": "Feature",
  "properties": {
    "addr:full":"16 Duke Dr Bear DE 19701",
    "addr:housenumber":"16",
    "addr:postcode":"19701",
    "addr:street":"Duke Dr",
    "iso:country":"US",
    "sg:address":"16 Duke Dr",
    "sg:city":"Bear",
    "sg:classifiers":[
        {
            "category":"Professional",
            "type":"Services"
        }
    ],
    "sg:phone":"+1 302 832 2622",
    "sg:postcode":"19701",
    "sg:province":"DE",
    "wof:name":"R H Niggebrugge Fax",
    "wof:placetype":"venue"
},
  "geometry": {"coordinates":[-75.735445,39.577994],"type":"Point"}
}