{
  "type": "Feature",
  "properties": {
    "addr:full":"27129 Woodland Rd Seaford DE 19973",
    "addr:housenumber":"27129",
    "addr:postcode":"19973",
    "addr:street":"Woodland Rd",
    "iso:country":"US",
    "sg:address":"27129 Woodland Rd",
    "sg:city":"Seaford",
    "sg:classifiers":[
        {
            "category":"Building & Trades",
            "subcategory":"Construction",
            "type":"Services"
        }
    ],
    "sg:phone":"+1 302 629 9504",
    "sg:postcode":"19973",
    "sg:province":"DE",
    "sg:tags":[
        "equipment",
        "installation"
    ],
    "wof:name":"Harrold & Sons Incorporated",
    "wof:placetype":"venue"
},
  "geometry": {"coordinates":[-75.640771,38.621499],"type":"Point"}
}