{
  "type": "Feature",
  "properties": {
    "addr:full":"1909 Faulkland Rd Wilmington DE 19805",
    "addr:housenumber":"1909",
    "addr:postcode":"19805",
    "addr:street":"Faulkland Rd",
    "iso:country":"US",
    "sg:address":"1909 Faulkland Rd",
    "sg:city":"Wilmington",
    "sg:classifiers":[
        {
            "category":"Building & Trades",
            "subcategory":"Construction",
            "type":"Services"
        }
    ],
    "sg:phone":"+1 302 998 5966",
    "sg:postcode":"19805",
    "sg:province":"DE",
    "sg:tags":[
        "specializing",
        "home",
        "family",
        "contractor"
    ],
    "wof:name":"Myers Bill & Son Home Imprv",
    "wof:placetype":"venue"
},
  "geometry": {"coordinates":[-75.61833799999999,39.748039],"type":"Point"}
}