{
  "type": "Feature",
  "properties": {
    "addr:full":"44 W Main St Middletown DE 19709",
    "addr:housenumber":"44",
    "addr:postcode":"19709",
    "addr:street":"W Main St",
    "iso:country":"US",
    "sg:address":"44 W Main St",
    "sg:city":"Middletown",
    "sg:classifiers":[
        {
            "category":"Organizations",
            "subcategory":"Religious Organization",
            "type":"Services"
        }
    ],
    "sg:phone":"+1 302 376 5729",
    "sg:postcode":"19709",
    "sg:province":"DE",
    "sg:tags":[
        "church"
    ],
    "wof:name":"Forest Presbyterian Church",
    "wof:placetype":"venue"
},
  "geometry": {"coordinates":[-75.717562,39.449539],"type":"Point"}
}