{
  "type": "Feature",
  "properties": {
    "iso:country":"US",
    "sg:address":"17 Trolley Sq",
    "sg:city":"Wilmington",
    "sg:classifiers":[
        {
            "category":"Professional",
            "subcategory":"Employment Agencies",
            "type":"Services"
        }
    ],
    "sg:phone":"+1 302 655 5700",
    "sg:postcode":"19806",
    "sg:province":"DE",
    "sg:tags":[
        "help",
        "supply"
    ],
    "wof:name":"MPS Group Inc",
    "wof:placetype":"venue"
},
  "geometry": {"coordinates":[-75.561922,39.758143],"type":"Point"}
}