{
  "type": "Feature",
  "properties": {
    "iso:country":"US",
    "sg:address":"4 E Center St",
    "sg:city":"Harrington",
    "sg:classifiers":[
        {
            "category":"Food & Beverages",
            "subcategory":"Groceries & Convenience Stores",
            "type":"Retail Goods"
        }
    ],
    "sg:phone":"+1 302 234 7779",
    "sg:postcode":"19952",
    "sg:province":"DE",
    "wof:name":"Harrington Deli",
    "wof:placetype":"venue"
},
  "geometry": {"coordinates":[-75.576858,38.928441],"type":"Point"}
}