{
  "type": "Feature",
  "properties": {
    "iso:country":"US",
    "sg:address":"1124 E 7th St",
    "sg:city":"Wilmington",
    "sg:classifiers":[
        {
            "category":"Shopping",
            "subcategory":"Used Merchandise",
            "type":"Retail Goods"
        }
    ],
    "sg:phone":"+1 302 654 1390",
    "sg:postcode":"19801",
    "sg:province":"DE",
    "wof:name":"Clothing Bank of Delaware Inc",
    "wof:placetype":"venue"
},
  "geometry": {"coordinates":[-75.538568,39.738441],"type":"Point"}
}