{
  "type": "Feature",
  "properties": {
    "iso:country":"US",
    "sg:address":"832 Philadelphia Pike",
    "sg:city":"Wilmington",
    "sg:classifiers":[
        {
            "category":"Shopping",
            "subcategory":"Florist",
            "type":"Retail Goods"
        }
    ],
    "sg:phone":"+1 302 762 5000",
    "sg:postcode":"19809",
    "sg:province":"DE",
    "wof:name":"Belak Flowers",
    "wof:placetype":"venue"
},
  "geometry": {"coordinates":[-75.497105,39.772368],"type":"Point"}
}