{
  "type": "Feature",
  "properties": {
    "iso:country":"US",
    "sg:address":"4004 S Dupont Hwy",
    "sg:city":"Dover",
    "sg:classifiers":[
        {
            "category":"Shopping",
            "subcategory":"Bicycles & Sporting Goods",
            "type":"Retail Goods"
        }
    ],
    "sg:phone":"+1 302 697 2882",
    "sg:postcode":"19901",
    "sg:province":"DE",
    "sg:tags":[
        "co",
        "construction",
        "commercial",
        "nonresidential"
    ],
    "wof:name":"Commercial Residential Contrs",
    "wof:placetype":"venue"
},
  "geometry": {"coordinates":[-75.541254,39.105325],"type":"Point"}
}