{
  "type": "Feature",
  "properties": {
    "iso:country":"US",
    "sg:address":"7294 Whiteleysburg Rd",
    "sg:city":"Harrington",
    "sg:classifiers":[
        {
            "category":"Building & Trades",
            "subcategory":"Construction",
            "type":"Services"
        }
    ],
    "sg:phone":"+1 302 398 6281",
    "sg:postcode":"19952",
    "sg:province":"DE",
    "sg:tags":[
        "house"
    ],
    "wof:name":"Co Marks Construction",
    "wof:placetype":"venue"
},
  "geometry": {"coordinates":[-75.60998600000001,38.923415],"type":"Point"}
}