{
  "type": "Feature",
  "properties": {
    "iso:country":"US",
    "sg:address":"400 S Central Ave",
    "sg:city":"Laurel",
    "sg:classifiers":[
        {
            "category":"Professional",
            "subcategory":"Secretarial Services",
            "type":"Services"
        }
    ],
    "sg:phone":"+1 302 875 3711",
    "sg:postcode":"19956",
    "sg:province":"DE",
    "sg:tags":[
        "reporting",
        "court"
    ],
    "wof:name":"Landmark Svc Corp",
    "wof:placetype":"venue"
},
  "geometry": {"coordinates":[-75.57117599999999,38.556045],"type":"Point"}
}