{
  "type": "Feature",
  "properties": {
    "addr:full":"255 N Dupont Hwy Dover DE 19901",
    "addr:housenumber":"255",
    "addr:postcode":"19901",
    "addr:street":"N Dupont Hwy",
    "iso:country":"US",
    "sg:address":"255 N Dupont Hwy",
    "sg:city":"Dover",
    "sg:classifiers":[
        {
            "category":"Banks & Credit Unions",
            "subcategory":"Bank",
            "type":"Services"
        }
    ],
    "sg:phone":"+1 302 678 7200",
    "sg:postcode":"19901",
    "sg:province":"DE",
    "wof:name":"Dover Fcu",
    "wof:placetype":"venue"
},
  "geometry": {"coordinates":[-75.51786199999999,39.170205],"type":"Point"}
}