{
  "type": "Feature",
  "properties": {
    "addr:full":"4242 Horseshoe Rd Seaford DE 19973",
    "addr:housenumber":"4242",
    "addr:postcode":"19973",
    "addr:street":"Horseshoe Rd",
    "iso:country":"US",
    "sg:address":"4242 Horseshoe Rd",
    "sg:city":"Seaford",
    "sg:classifiers":[
        {
            "category":"Social Services",
            "subcategory":"Child Care",
            "type":"Services"
        }
    ],
    "sg:phone":"+1 302 628 9187",
    "sg:postcode":"19973",
    "sg:province":"DE",
    "sg:tags":[
        "day"
    ],
    "wof:name":"Robins Nest Daycare Preschool",
    "wof:placetype":"venue"
},
  "geometry": {"coordinates":[-75.67841,38.659266],"type":"Point"}
}