{
  "type": "Feature",
  "properties": {
    "iso:country":"US",
    "sg:address":"60 N College Ave",
    "sg:city":"Newark",
    "sg:classifiers":[
        {
            "category":"Wholesale",
            "subcategory":"Non-durable Goods",
            "type":"Manufacturing & Wholesale Goods"
        }
    ],
    "sg:phone":"+1 302 731 5917",
    "sg:postcode":"19711",
    "sg:province":"DE",
    "sg:tags":[
        "advertising"
    ],
    "wof:name":"Campus Loft Co Inc",
    "wof:placetype":"venue"
},
  "geometry": {"coordinates":[-75.754043,39.683117],"type":"Point"}
}