{
  "type": "Feature",
  "properties": {
    "iso:country":"US",
    "sg:address":"4877 Wheatleys Pond Rd",
    "sg:city":"Smyrna",
    "sg:classifiers":[
        {
            "category":"Professional",
            "subcategory":"Lawyer & Legal Services",
            "type":"Services"
        }
    ],
    "sg:phone":"+1 302 653 9132",
    "sg:postcode":"19977",
    "sg:province":"DE",
    "wof:name":"Stephen Nowak",
    "wof:placetype":"venue"
},
  "geometry": {"coordinates":[-75.62831199999999,39.287067],"type":"Point"}
}