{
  "type": "Feature",
  "properties": {
    "iso:country":"US",
    "sg:address":"115 Clear Brook Ct",
    "sg:city":"Claymont",
    "sg:classifiers":[
        {
            "category":"Health Services",
            "subcategory":"Doctor",
            "type":"Services"
        }
    ],
    "sg:phone":"+1 302 547 1930",
    "sg:postcode":"19703",
    "sg:province":"DE",
    "sg:tags":[
        "medical"
    ],
    "wof:name":"Helena Carter Dr Cellular",
    "wof:placetype":"venue"
},
  "geometry": {"coordinates":[-75.45944799999999,39.813796],"type":"Point"}
}