{
  "type": "Feature",
  "properties": {
    "iso:country":"US",
    "sg:address":"242 S Dupont Blvd",
    "sg:city":"Smyrna",
    "sg:classifiers":[
        {
            "category":"Professional",
            "subcategory":"Business Services",
            "type":"Services"
        }
    ],
    "sg:phone":"+1 302 659 5500",
    "sg:postcode":"19977",
    "sg:province":"DE",
    "sg:tags":[
        "repossessing"
    ],
    "wof:name":"Collateral Recovery Svc",
    "wof:placetype":"venue"
},
  "geometry": {"coordinates":[-75.60024199999999,39.297492],"type":"Point"}
}