{
  "type": "Feature",
  "properties": {
    "addr:full":"1020 Capitol Trl Newark DE 19711",
    "addr:housenumber":"1020",
    "addr:postcode":"19711",
    "addr:street":"Capitol Trl",
    "iso:country":"US",
    "sg:address":"1020 Capitol Trl",
    "sg:city":"Newark",
    "sg:classifiers":[
        {
            "category":"Restaurant",
            "type":"Food & Drink"
        }
    ],
    "sg:phone":"+1 302 366 7551",
    "sg:postcode":"19711",
    "sg:province":"DE",
    "sg:tags":[
        "eating"
    ],
    "wof:name":"Taco Bell",
    "wof:placetype":"venue"
},
  "geometry": {"coordinates":[-75.715256,39.695631],"type":"Point"}
}