{
  "type": "Feature",
  "properties": {
    "iso:country":"US",
    "sg:address":"2005 Concord Pike",
    "sg:city":"Wilmington",
    "sg:classifiers":[
        {
            "category":"Professional",
            "subcategory":"Engineering",
            "type":"Services"
        }
    ],
    "sg:phone":"+1 302 658 4281",
    "sg:postcode":"19803",
    "sg:province":"DE",
    "sg:tags":[
        "consulting",
        "engineer"
    ],
    "wof:name":"Carew Associates Inc",
    "wof:placetype":"venue"
},
  "geometry": {"coordinates":[-75.546255,39.78911],"type":"Point"}
}