{
  "type": "Feature",
  "properties": {
    "iso:country":"US",
    "sg:address":"536 N Bradford St",
    "sg:city":"Dover",
    "sg:classifiers":[
        {
            "category":"Organizations",
            "subcategory":"Religious Organization",
            "type":"Services"
        }
    ],
    "sg:phone":"+1 302 734 8705",
    "sg:postcode":"19904",
    "sg:province":"DE",
    "wof:name":"Epiphany Christian Entertainme",
    "wof:placetype":"venue"
},
  "geometry": {"coordinates":[-75.53022799999999,39.169536],"type":"Point"}
}