{
  "type": "Feature",
  "properties": {
    "addr:full":"502 E Market St Greenwood DE 19950",
    "addr:housenumber":"502",
    "addr:postcode":"19950",
    "addr:street":"E Market St",
    "iso:country":"US",
    "sg:address":"502 E Market St",
    "sg:city":"Greenwood",
    "sg:classifiers":[
        {
            "category":"Banks & Credit Unions",
            "subcategory":"Bank",
            "type":"Services"
        }
    ],
    "sg:phone":"+1 302 349 4512",
    "sg:postcode":"19950",
    "sg:province":"DE",
    "sg:tags":[
        "saving",
        "commercial"
    ],
    "sg:website":"http://www.discoverbank.com",
    "wof:name":"Discover Bank",
    "wof:placetype":"venue"
},
  "geometry": {"coordinates":[-75.585133,38.806169],"type":"Point"}
}