{
  "type": "Feature",
  "properties": {
    "iso:country":"US",
    "sg:address":"314 E Basin Rd",
    "sg:city":"New Castle",
    "sg:classifiers":[
        {
            "category":"Education",
            "subcategory":"School",
            "type":"Public Place"
        }
    ],
    "sg:phone":"+1 302 323 2760",
    "sg:postcode":"19720",
    "sg:province":"DE",
    "wof:name":"George Read Middle School",
    "wof:placetype":"venue"
},
  "geometry": {"coordinates":[-75.58696500000001,39.675744],"type":"Point"}
}