{
  "type": "Feature",
  "properties": {
    "iso:country":"US",
    "sg:address":"1305 N Dupont St",
    "sg:city":"Wilmington",
    "sg:classifiers":[
        {
            "category":"Manufacturing",
            "subcategory":"Lumber",
            "type":"Manufacturing & Wholesale Goods"
        }
    ],
    "sg:phone":"+1 302 655 8471",
    "sg:postcode":"19806",
    "sg:province":"DE",
    "sg:tags":[
        "logging"
    ],
    "wof:name":"J&J Quality Wood",
    "wof:placetype":"venue"
},
  "geometry": {"coordinates":[-75.563603,39.756525],"type":"Point"}
}