{
  "type": "Feature",
  "properties": {
    "addr:full":"1213 Lobdell St Wilmington DE 19801",
    "addr:housenumber":"1213",
    "addr:postcode":"19801",
    "addr:street":"Lobdell St",
    "iso:country":"US",
    "sg:address":"1213 Lobdell St",
    "sg:city":"Wilmington",
    "sg:classifiers":[
        {
            "category":"Freight",
            "type":"Transportation"
        }
    ],
    "sg:phone":"+1 302 652 2837",
    "sg:postcode":"19801",
    "sg:province":"DE",
    "sg:tags":[
        "operator",
        "local",
        "trucking"
    ],
    "wof:name":"Maddrey Trucking",
    "wof:placetype":"venue"
},
  "geometry": {"coordinates":[-75.54097899999999,39.730775],"type":"Point"}
}