{
  "type": "Feature",
  "properties": {
    "iso:country":"US",
    "sg:address":"2 Yorkshire Ct",
    "sg:city":"Bear",
    "sg:classifiers":[
        {
            "category":"Wholesale",
            "subcategory":"Auto Parts",
            "type":"Manufacturing & Wholesale Goods"
        }
    ],
    "sg:phone":"+1 302 838 5103",
    "sg:postcode":"19701",
    "sg:province":"DE",
    "sg:tags":[
        "automotive",
        "used",
        "supply"
    ],
    "wof:name":"Wyoming New Frontiers Intl",
    "wof:placetype":"venue"
},
  "geometry": {"coordinates":[-75.69306,39.57323],"type":"Point"}
}