{
  "type": "Feature",
  "properties": {
    "iso:country":"US",
    "sg:address":"800 Marrows Rd",
    "sg:city":"Newark",
    "sg:classifiers":[
        {
            "category":"Education",
            "subcategory":"School",
            "type":"Public Place"
        }
    ],
    "sg:phone":"+1 302 454 5454",
    "sg:postcode":"19713",
    "sg:province":"DE",
    "sg:tags":[
        "elementary"
    ],
    "wof:name":"Brookside Elementary School",
    "wof:placetype":"venue"
},
  "geometry": {"coordinates":[-75.727492,39.669268],"type":"Point"}
}