{
  "type": "Feature",
  "properties": {
    "iso:country":"US",
    "sg:address":"846 Walker Rd Ste 31-2",
    "sg:city":"Dover",
    "sg:classifiers":[
        {
            "category":"Health Services",
            "subcategory":"Doctor",
            "type":"Services"
        }
    ],
    "sg:phone":"+1 302 674 9188",
    "sg:postcode":"19904",
    "sg:province":"DE",
    "sg:tags":[
        "psychiatrist"
    ],
    "wof:name":"Kraman-Roach Lillian MD",
    "wof:placetype":"venue"
},
  "geometry": {"coordinates":[-75.54473400000001,39.169766],"type":"Point"}
}