{
  "type": "Feature",
  "properties": {
    "addr:full":"17378 S Dupont Hwy Harrington DE 19952",
    "addr:housenumber":"17378",
    "addr:postcode":"19952",
    "addr:street":"S Dupont Hwy",
    "iso:country":"US",
    "sg:address":"17378 S Dupont Hwy",
    "sg:city":"Harrington",
    "sg:classifiers":[
        {
            "category":"Retail",
            "subcategory":"Auto Repair",
            "type":"Services"
        }
    ],
    "sg:phone":"+1 302 398 8419",
    "sg:postcode":"19952",
    "sg:province":"DE",
    "sg:tags":[
        "general"
    ],
    "wof:name":"P & J Auto Repair & Towing",
    "wof:placetype":"venue"
},
  "geometry": {"coordinates":[-75.56814799999999,38.922486],"type":"Point"}
}