{
  "type": "Feature",
  "properties": {
    "iso:country":"US",
    "sg:address":"89 Blue Hen Dr",
    "sg:city":"Newark",
    "sg:classifiers":[
        {
            "category":"Building & Trades",
            "subcategory":"Cleaning & Sanitation",
            "type":"Services"
        }
    ],
    "sg:phone":"+1 302 731 9878",
    "sg:postcode":"19713",
    "sg:province":"DE",
    "sg:tags":[
        "maintenance"
    ],
    "wof:name":"All In One Cleaning Service",
    "wof:placetype":"venue"
},
  "geometry": {"coordinates":[-75.735032,39.655623],"type":"Point"}
}