{
  "type": "Feature",
  "properties": {
    "iso:country":"US",
    "sg:address":"1007 N Market St",
    "sg:city":"Wilmington",
    "sg:classifiers":[
        {
            "category":"Banks & Credit Unions",
            "subcategory":"Investment Brokerage",
            "type":"Services"
        },
        {
            "category":"Banks & Credit Unions",
            "subcategory":"Bank",
            "type":"Services"
        }
    ],
    "sg:phone":"+1 302 651 1401",
    "sg:postcode":"19801",
    "sg:province":"DE",
    "sg:tags":[
        "commercial",
        "trust",
        "saving"
    ],
    "sg:website":"http://www.binghamlegg.com",
    "wof:name":"Wilmington Trust Co",
    "wof:placetype":"venue"
},
  "geometry": {"coordinates":[-75.54769899999999,39.745596],"type":"Point"}
}