{
  "type": "Feature",
  "properties": {
    "iso:country":"US",
    "sg:address":"200 S Maryland Ave",
    "sg:city":"Wilmington",
    "sg:classifiers":[
        {
            "category":"Social Services",
            "type":"Services"
        }
    ],
    "sg:phone":"+1 302 247 1000",
    "sg:postcode":"19804",
    "sg:province":"DE",
    "sg:tags":[
        "counseling"
    ],
    "wof:name":"Tree House Wellness Center",
    "wof:placetype":"venue"
},
  "geometry": {"coordinates":[-75.587693,39.727239],"type":"Point"}
}