{
  "type": "Feature",
  "properties": {
    "iso:country":"US",
    "sg:address":"105 W 38th St",
    "sg:city":"Wilmington",
    "sg:classifiers":[
        {
            "category":"Social Services",
            "subcategory":"Child Care",
            "type":"Services"
        }
    ],
    "sg:phone":"+1 302 764 1524",
    "sg:postcode":"19802",
    "sg:province":"DE",
    "sg:tags":[
        "day"
    ],
    "wof:name":"Loving Child Nursery",
    "wof:placetype":"venue"
},
  "geometry": {"coordinates":[-75.52621000000001,39.761769],"type":"Point"}
}