{
  "type": "Feature",
  "properties": {
    "iso:country":"US",
    "sg:address":"4 Sea Chase Dr",
    "sg:city":"Rehoboth Beach",
    "sg:classifiers":[
        {
            "category":"Professional",
            "type":"Services"
        }
    ],
    "sg:phone":"+1 302 227 6740",
    "sg:postcode":"19971",
    "sg:province":"DE",
    "wof:name":"Charles Coale",
    "wof:placetype":"venue"
},
  "geometry": {"coordinates":[-75.13341,38.721903],"type":"Point"}
}