{
  "type": "Feature",
  "properties": {
    "iso:country":"US",
    "sg:address":"2319 Pennsylvania Ave",
    "sg:city":"Wilmington",
    "sg:classifiers":[
        {
            "category":"Health Services",
            "subcategory":"Doctor",
            "type":"Services"
        }
    ],
    "sg:phone":"+1 302 368 8900",
    "sg:postcode":"19806",
    "sg:province":"DE",
    "sg:tags":[
        "physician",
        "reconstructive",
        "surgeons",
        "cosmetic",
        "plastic",
        "surgeon",
        "surgery"
    ],
    "sg:website":"http://www.plasticsurgery.org/MD/MBALAKHANI.HTM",
    "wof:name":"Balakhani Mehdi MD",
    "wof:placetype":"venue"
},
  "geometry": {"coordinates":[-75.571746,39.758353],"type":"Point"}
}