{
  "type": "Feature",
  "properties": {
    "iso:country":"US",
    "sg:address":"2317 Pennsylvania Ave",
    "sg:city":"Wilmington",
    "sg:classifiers":[
        {
            "category":"Building & Trades",
            "subcategory":"Construction",
            "type":"Services"
        }
    ],
    "sg:phone":"+1 302 654 6611",
    "sg:postcode":"19806",
    "sg:province":"DE",
    "sg:tags":[
        "general",
        "contractor"
    ],
    "wof:name":"Commonwealth Construction",
    "wof:placetype":"venue"
},
  "geometry": {"coordinates":[-75.572885,39.759051],"type":"Point"}
}