{
  "type": "Feature",
  "properties": {
    "addr:full":"8 Sea Chase Dr Rehoboth Beach DE 19971",
    "addr:housenumber":"8",
    "addr:postcode":"19971",
    "addr:street":"Sea Chase Dr",
    "iso:country":"US",
    "sg:address":"8 Sea Chase Dr",
    "sg:city":"Rehoboth Beach",
    "sg:classifiers":[
        {
            "category":"Professional",
            "subcategory":"Management & Consulting",
            "type":"Services"
        }
    ],
    "sg:phone":"+1 302 226 0142",
    "sg:postcode":"19971",
    "sg:province":"DE",
    "sg:tags":[
        "public",
        "relations"
    ],
    "wof:name":"Early Light Communications",
    "wof:placetype":"venue"
},
  "geometry": {"coordinates":[-75.133487,38.721917],"type":"Point"}
}