{
  "type": "Feature",
  "properties": {
    "iso:country":"US",
    "sg:address":"3518 Silverside Rd",
    "sg:city":"Wilmington",
    "sg:classifiers":[
        {
            "category":"Restaurant",
            "type":"Food & Drink"
        }
    ],
    "sg:phone":"+1 302 478 3644",
    "sg:postcode":"19810",
    "sg:province":"DE",
    "sg:tags":[
        "fast"
    ],
    "wof:name":"Dog House The",
    "wof:placetype":"venue"
},
  "geometry": {"coordinates":[-75.54410799999999,39.808795],"type":"Point"}
}