{
  "type": "Feature",
  "properties": {
    "iso:country":"US",
    "sg:address":"40 E Division St Ste 1",
    "sg:city":"Dover",
    "sg:classifiers":[
        {
            "category":"Health Services",
            "subcategory":"Doctor",
            "type":"Services"
        }
    ],
    "sg:phone":"+1 302 734 9112",
    "sg:postcode":"19901",
    "sg:province":"DE",
    "wof:name":"Schlesinger Stephen MD",
    "wof:placetype":"venue"
},
  "geometry": {"coordinates":[-75.52449799999999,39.1619],"type":"Point"}
}