{
  "type": "Feature",
  "properties": {
    "iso:country":"US",
    "sg:address":"205 W 7th St",
    "sg:city":"Wilmington",
    "sg:classifiers":[
        {
            "category":"Restaurant",
            "type":"Food & Drink"
        }
    ],
    "sg:phone":"+1 302 429 0700",
    "sg:postcode":"19801",
    "sg:province":"DE",
    "sg:tags":[
        "eating"
    ],
    "wof:name":"Queen Bean Down Town",
    "wof:placetype":"venue"
},
  "geometry": {"coordinates":[-75.551986,39.74362],"type":"Point"}
}