{
  "type": "Feature",
  "properties": {
    "iso:country":"US",
    "sg:address":"3615 Miller Rd",
    "sg:city":"Wilmington",
    "sg:classifiers":[
        {
            "category":"Organizations",
            "subcategory":"Professional Association",
            "type":"Services"
        }
    ],
    "sg:phone":"+1 302 762 4800",
    "sg:postcode":"19802",
    "sg:province":"DE",
    "sg:tags":[
        "trade"
    ],
    "wof:name":"New Castle County Bd Realtors",
    "wof:placetype":"venue"
},
  "geometry": {"coordinates":[-75.534899,39.76775],"type":"Point"}
}