{
  "type": "Feature",
  "properties": {
    "addr:full":"9 Windmill Dr Ocean View DE 19970",
    "addr:housenumber":"9",
    "addr:postcode":"19970",
    "addr:street":"Windmill Dr",
    "iso:country":"US",
    "sg:address":"9 Windmill Dr",
    "sg:city":"Ocean View",
    "sg:classifiers":[
        {
            "category":"Wholesale",
            "subcategory":"Metals & Minerals",
            "type":"Manufacturing & Wholesale Goods"
        }
    ],
    "sg:phone":"+1 302 541 5320",
    "sg:postcode":"19970",
    "sg:province":"DE",
    "wof:name":"Centralia Coal Sales",
    "wof:placetype":"venue"
},
  "geometry": {"coordinates":[-75.11702200000001,38.54242],"type":"Point"}
}