{
  "type": "Feature",
  "properties": {
    "iso:country":"US",
    "sg:address":"111 Parrish Ln",
    "sg:city":"Wilmington",
    "sg:classifiers":[
        {
            "category":"Shopping",
            "subcategory":"Gifts & Souvenirs",
            "type":"Retail Goods"
        }
    ],
    "sg:phone":"+1 302 478 7619",
    "sg:postcode":"19810",
    "sg:province":"DE",
    "wof:name":"Painters Paradise",
    "wof:placetype":"venue"
},
  "geometry": {"coordinates":[-75.53225999999999,39.821258],"type":"Point"}
}