{
  "type": "Feature",
  "properties": {
    "iso:country":"US",
    "sg:address":"515 E Denneys Rd",
    "sg:city":"Dover",
    "sg:classifiers":[
        {
            "category":"Shopping",
            "subcategory":"Clothing, Apparel, & Fashions",
            "type":"Retail Goods"
        }
    ],
    "sg:phone":"+1 302 674 5968",
    "sg:postcode":"19901",
    "sg:province":"DE",
    "sg:tags":[
        "repair"
    ],
    "wof:name":"Debbees Place Inc",
    "wof:placetype":"venue"
},
  "geometry": {"coordinates":[-75.549294,39.221224],"type":"Point"}
}