{
  "type": "Feature",
  "properties": {
    "addr:full":"4270 Hwy One Rehoboth Beach DE 19971",
    "addr:housenumber":"4270",
    "addr:postcode":"19971",
    "addr:street":"Hwy One",
    "iso:country":"US",
    "sg:address":"4270 Hwy One",
    "sg:city":"Rehoboth Beach",
    "sg:classifiers":[
        {
            "category":"Building & Trades",
            "subcategory":"Cleaning & Sanitation",
            "type":"Services"
        }
    ],
    "sg:phone":"+1 302 226 2131",
    "sg:postcode":"19971",
    "sg:province":"DE",
    "sg:tags":[
        "janitor"
    ],
    "wof:name":"Sun Sational Cleaning Svc",
    "wof:placetype":"venue"
},
  "geometry": {"coordinates":[-75.103511,38.713309],"type":"Point"}
}