{
  "type": "Feature",
  "properties": {
    "iso:country":"US",
    "sg:address":"1000 Twin C Ln Ste 100",
    "sg:city":"Newark",
    "sg:classifiers":[
        {
            "category":"Health Services",
            "subcategory":"Doctor",
            "type":"Services"
        },
        {
            "category":"Health Services",
            "subcategory":"Clinic",
            "type":"Services"
        },
        {
            "category":"Community Center",
            "type":"Public Place"
        },
        {
            "category":"Health Services",
            "subcategory":"Dentist",
            "type":"Services"
        }
    ],
    "sg:phone":"+1 302 999 0774",
    "sg:postcode":"19713",
    "sg:province":"DE",
    "sg:tags":[
        "physician",
        "radiology",
        "laboratories-medical",
        "dental",
        "surgeons",
        "osteopathic",
        "mri",
        "resonance",
        "magnetic",
        "x-ray",
        "imaging"
    ],
    "sg:website":"http://www3.americanradiology.com",
    "wof:name":"American Radiology Services",
    "wof:placetype":"venue"
},
  "geometry": {"coordinates":[-75.651962,39.697208],"type":"Point"}
}