{
  "type": "Feature",
  "properties": {
    "iso:country":"US",
    "sg:address":"3911 N Washington St",
    "sg:city":"Wilmington",
    "sg:classifiers":[
        {
            "category":"Personal",
            "subcategory":"Beauty Salon",
            "type":"Services"
        }
    ],
    "sg:phone":"+1 302 762 6610",
    "sg:postcode":"19802",
    "sg:province":"DE",
    "sg:tags":[
        "shop"
    ],
    "wof:name":"Innovations Hair Design For Wo",
    "wof:placetype":"venue"
},
  "geometry": {"coordinates":[-75.525734,39.763391],"type":"Point"}
}