{
  "type": "Feature",
  "properties": {
    "addr:full":"205 Savannah Rd Lewes DE 19958",
    "addr:housenumber":"205",
    "addr:postcode":"19958",
    "addr:street":"Savannah Rd",
    "iso:country":"US",
    "sg:address":"205 Savannah Rd",
    "sg:city":"Lewes",
    "sg:classifiers":[
        {
            "category":"Travel",
            "subcategory":"Hotels & Motels",
            "type":"Entertainment"
        }
    ],
    "sg:phone":"+1 302 644 8878",
    "sg:postcode":"19958",
    "sg:province":"DE",
    "sg:tags":[
        "breakfast",
        "operation",
        "bed",
        "accommodation"
    ],
    "wof:name":"An Inn By The Bay",
    "wof:placetype":"venue"
},
  "geometry": {"coordinates":[-75.13856199999999,38.774784],"type":"Point"}
}