{
  "type": "Feature",
  "properties": {
    "iso:country":"US",
    "sg:address":"6 Village Dr",
    "sg:city":"Milton",
    "sg:classifiers":[
        {
            "category":"Manufacturing",
            "subcategory":"Food",
            "type":"Manufacturing & Wholesale Goods"
        }
    ],
    "sg:phone":"+1 302 684 1000",
    "sg:postcode":"19904",
    "sg:province":"DE",
    "sg:tags":[
        "malt",
        "beverage",
        "mfg"
    ],
    "wof:name":"Dogfish Head Craft Brewery",
    "wof:placetype":"venue"
},
  "geometry": {"coordinates":[-75.548421,39.169918],"type":"Point"}
}