{
  "type": "Feature",
  "properties": {
    "addr:full":"120 Central Blvd Bethany Beach DE 19930",
    "addr:housenumber":"120",
    "addr:postcode":"19930",
    "addr:street":"Central Blvd",
    "iso:country":"US",
    "sg:address":"120 Central Blvd",
    "sg:city":"Bethany Beach",
    "sg:classifiers":[
        {
            "category":"Professional",
            "type":"Services"
        }
    ],
    "sg:phone":"+1 302 539 8933",
    "sg:postcode":"19930",
    "sg:province":"DE",
    "wof:name":"Pelican Galleries",
    "wof:placetype":"venue"
},
  "geometry": {"coordinates":[-75.05706000000001,38.540099],"type":"Point"}
}