{
  "type": "Feature",
  "properties": {
    "iso:country":"US",
    "sg:address":"W North",
    "sg:city":"Dover",
    "sg:classifiers":[
        {
            "category":"Food & Beverages",
            "subcategory":"Specialty",
            "type":"Retail Goods"
        }
    ],
    "sg:phone":"+1 302 734 6100",
    "sg:postcode":"19901",
    "sg:province":"DE",
    "wof:name":"Kraft Foods Inc",
    "wof:placetype":"venue"
},
  "geometry": {"coordinates":[-75.515602,39.159901],"type":"Point"}
}