{
  "type": "Feature",
  "properties": {
    "iso:country":"US",
    "sg:address":"2115 Concord Pike",
    "sg:city":"Wilmington",
    "sg:classifiers":[
        {
            "category":"Shopping",
            "type":"Retail Goods"
        }
    ],
    "sg:phone":"+1 302 777 7894",
    "sg:postcode":"19803",
    "sg:province":"DE",
    "sg:tags":[
        "merchandise"
    ],
    "wof:name":"Hank Papula",
    "wof:placetype":"venue"
},
  "geometry": {"coordinates":[-75.546104,39.787797],"type":"Point"}
}