{
  "type": "Feature",
  "properties": {
    "addr:full":"717 Woodlawn Ave Seaford DE 19973",
    "addr:housenumber":"717",
    "addr:postcode":"19973",
    "addr:street":"Woodlawn Ave",
    "iso:country":"US",
    "sg:address":"717 Woodlawn Ave",
    "sg:city":"Seaford",
    "sg:classifiers":[
        {
            "category":"Organizations",
            "subcategory":"Religious Organization",
            "type":"Services"
        }
    ],
    "sg:phone":"+1 302 629 5600",
    "sg:postcode":"19973",
    "sg:province":"DE",
    "sg:tags":[
        "clergy"
    ],
    "wof:name":"Samuel W Mc Garvey",
    "wof:placetype":"venue"
},
  "geometry": {"coordinates":[-75.629159,38.647957],"type":"Point"}
}