{
  "type": "Feature",
  "properties": {
    "iso:country":"US",
    "sg:address":"3221 Naamans Rd",
    "sg:city":"Wilmington",
    "sg:classifiers":[
        {
            "category":"Retail",
            "subcategory":"Car Wash",
            "type":"Services"
        }
    ],
    "sg:phone":"+1 302 479 5911",
    "sg:postcode":"19810",
    "sg:province":"DE",
    "wof:name":"Magic Car Wash",
    "wof:placetype":"venue"
},
  "geometry": {"coordinates":[-75.54180100000001,39.828899],"type":"Point"}
}