{
  "type": "Feature",
  "properties": {
    "addr:full":"5729 W Denneys Rd Dover DE 19904",
    "addr:housenumber":"5729",
    "addr:postcode":"19904",
    "addr:street":"W Denneys Rd",
    "iso:country":"US",
    "sg:address":"5729 W Denneys Rd",
    "sg:city":"Dover",
    "sg:classifiers":[
        {
            "category":"Utilities",
            "subcategory":"Cable",
            "type":"Services"
        }
    ],
    "sg:phone":"+1 302 674 2494",
    "sg:postcode":"19904",
    "sg:province":"DE",
    "sg:tags":[
        "television"
    ],
    "wof:name":"Comcast",
    "wof:placetype":"venue"
},
  "geometry": {"coordinates":[-75.563069,39.199971],"type":"Point"}
}