{
  "type": "Feature",
  "properties": {
    "iso:country":"US",
    "sg:address":"29 Spruce Ave",
    "sg:city":"Elsmere",
    "sg:classifiers":[
        {
            "category":"Building & Trades",
            "subcategory":"Landscaping Services",
            "type":"Services"
        }
    ],
    "sg:phone":"+1 302 633 1189",
    "sg:postcode":"19805",
    "sg:province":"DE",
    "sg:tags":[
        "snow",
        "removal"
    ],
    "wof:name":"Gutter Solutions",
    "wof:placetype":"venue"
},
  "geometry": {"coordinates":[-75.602999,39.739609],"type":"Point"}
}