{
  "type": "Feature",
  "properties": {
    "iso:country":"US",
    "sg:address":"602 Fairview Ave",
    "sg:city":"Dover",
    "sg:classifiers":[
        {
            "category":"Personal",
            "subcategory":"Beauty Salon",
            "type":"Services"
        }
    ],
    "sg:phone":"+1 302 678 3003",
    "sg:postcode":"19904",
    "sg:province":"DE",
    "wof:name":"Fairview Avenue Shoppe",
    "wof:placetype":"venue"
},
  "geometry": {"coordinates":[-75.534603,39.170694],"type":"Point"}
}