{
  "type": "Feature",
  "properties": {
    "addr:full":"530 Jfk Memorial Hwy Newark DE 19702",
    "addr:housenumber":"530",
    "addr:postcode":"19702",
    "addr:street":"Jfk Memorial Hwy",
    "iso:country":"US",
    "sg:address":"530 Jfk Memorial Hwy",
    "sg:city":"Newark",
    "sg:classifiers":[
        {
            "category":"Travel",
            "subcategory":"Travel Agent",
            "type":"Entertainment"
        }
    ],
    "sg:phone":"+1 302 737 4059",
    "sg:postcode":"19702",
    "sg:province":"DE",
    "sg:tags":[
        "information",
        "tourist"
    ],
    "wof:name":"Brandywine Valley Tourism Info",
    "wof:placetype":"venue"
},
  "geometry": {"coordinates":[-75.694838,39.659266],"type":"Point"}
}