{
  "type": "Feature",
  "properties": {
    "addr:full":"3 Mill Rd Wilmington DE 19804",
    "addr:housenumber":"3",
    "addr:postcode":"19804",
    "addr:street":"Mill Rd",
    "iso:country":"US",
    "sg:address":"3 Mill Rd",
    "sg:city":"Wilmington",
    "sg:classifiers":[
        {
            "category":"Professional",
            "subcategory":"Engineering",
            "type":"Services"
        }
    ],
    "sg:phone":"+1 302 571 9001",
    "sg:postcode":"19804",
    "sg:province":"DE",
    "sg:tags":[
        "engineer"
    ],
    "sg:website":"www.wrallp.com",
    "wof:name":"Whitman Requardt & Assoc",
    "wof:placetype":"venue"
},
  "geometry": {"coordinates":[-75.646788,39.711061],"type":"Point"}
}