{
  "type": "Feature",
  "properties": {
    "iso:country":"US",
    "sg:address":"1705 Pulaski Hwy",
    "sg:city":"Bear",
    "sg:classifiers":[
        {
            "category":"Restaurant",
            "type":"Food & Drink"
        }
    ],
    "sg:phone":"+1 302 836 4936",
    "sg:postcode":"19701",
    "sg:province":"DE",
    "sg:tags":[
        "eating"
    ],
    "wof:name":"Charlies Restaurant & Diner",
    "wof:placetype":"venue"
},
  "geometry": {"coordinates":[-75.694999,39.618746],"type":"Point"}
}