{
  "type": "Feature",
  "properties": {
    "addr:full":"9 Andrew Ln Bear DE 19701",
    "addr:housenumber":"9",
    "addr:postcode":"19701",
    "addr:street":"Andrew Ln",
    "iso:country":"US",
    "sg:address":"9 Andrew Ln",
    "sg:city":"Bear",
    "sg:classifiers":[
        {
            "category":"Professional",
            "subcategory":"Business Services",
            "type":"Services"
        }
    ],
    "sg:phone":"+1 302 834 3463",
    "sg:postcode":"19701",
    "sg:province":"DE",
    "wof:name":"Construction Solutions Inc",
    "wof:placetype":"venue"
},
  "geometry": {"coordinates":[-75.65864999999999,39.615738],"type":"Point"}
}