{
  "type": "Feature",
  "properties": {
    "addr:full":"160 College Sq Newark DE 19711",
    "addr:housenumber":"160",
    "addr:postcode":"19711",
    "addr:street":"College Sq",
    "iso:country":"US",
    "sg:address":"160 College Sq",
    "sg:city":"Newark",
    "sg:classifiers":[
        {
            "category":"Shopping",
            "subcategory":"Clothing, Apparel, & Fashions",
            "type":"Retail Goods"
        }
    ],
    "sg:phone":"+1 302 368 7313",
    "sg:postcode":"19711",
    "sg:province":"DE",
    "wof:name":"Fashion Bug",
    "wof:placetype":"venue"
},
  "geometry": {"coordinates":[-75.732401,39.683744],"type":"Point"}
}