{
  "type": "Feature",
  "properties": {
    "iso:country":"US",
    "sg:address":"29346 Iron Branch Rd",
    "sg:city":"Millsboro",
    "sg:classifiers":[
        {
            "category":"Education",
            "subcategory":"School",
            "type":"Public Place"
        }
    ],
    "sg:phone":"+1 302 934 3222",
    "sg:postcode":"19966",
    "sg:province":"DE",
    "sg:website":"http://www.eastmillsboro.com",
    "wof:name":"East Millsboro Elem Sch",
    "wof:placetype":"venue"
},
  "geometry": {"coordinates":[-75.277844,38.585354],"type":"Point"}
}