{
  "type": "Feature",
  "properties": {
    "addr:full":"126 E Main St Newark DE 19711",
    "addr:housenumber":"126",
    "addr:postcode":"19711",
    "addr:street":"E Main St",
    "iso:country":"US",
    "sg:address":"126 E Main St",
    "sg:city":"Newark",
    "sg:classifiers":[
        {
            "category":"Banks & Credit Unions",
            "subcategory":"Bank",
            "type":"Services"
        }
    ],
    "sg:phone":"+1 302 429 4923",
    "sg:postcode":"19711",
    "sg:province":"DE",
    "sg:tags":[
        "national",
        "commercial"
    ],
    "wof:name":"Mellon",
    "wof:placetype":"venue"
},
  "geometry": {"coordinates":[-75.74810600000001,39.6835],"type":"Point"}
}