{
  "type": "Feature",
  "properties": {
    "iso:country":"US",
    "sg:address":"100 Troubador Way",
    "sg:city":"Newark",
    "sg:classifiers":[
        {
            "category":"Restaurant",
            "type":"Food & Drink"
        }
    ],
    "sg:phone":"+1 302 838 5930",
    "sg:postcode":"19702",
    "sg:province":"DE",
    "sg:tags":[
        "eating"
    ],
    "wof:name":"My Place",
    "wof:placetype":"venue"
},
  "geometry": {"coordinates":[-75.664186,39.64344],"type":"Point"}
}