{
  "type": "Feature",
  "properties": {
    "addr:full":"7 E Richards Ln Newark DE 19711",
    "addr:housenumber":"7",
    "addr:postcode":"19711",
    "addr:street":"E Richards Ln",
    "iso:country":"US",
    "sg:address":"7 E Richards Ln",
    "sg:city":"Newark",
    "sg:classifiers":[
        {
            "category":"Building & Trades",
            "subcategory":"Construction",
            "type":"Services"
        }
    ],
    "sg:phone":"+1 302 733 7528",
    "sg:postcode":"19711",
    "sg:province":"DE",
    "sg:tags":[
        "contractor"
    ],
    "wof:name":"Gary L Morris Siding Co",
    "wof:placetype":"venue"
},
  "geometry": {"coordinates":[-75.699083,39.703151],"type":"Point"}
}