{
  "type": "Feature",
  "properties": {
    "iso:country":"US",
    "sg:address":"1278 S Bay Rd",
    "sg:city":"Dover",
    "sg:classifiers":[
        {
            "category":"Home & Garden",
            "subcategory":"Furniture",
            "type":"Retail Goods"
        },
        {
            "category":"Shopping",
            "subcategory":"Gifts & Souvenirs",
            "type":"Retail Goods"
        }
    ],
    "sg:phone":"+1 302 734 4021",
    "sg:postcode":"19901",
    "sg:province":"DE",
    "sg:tags":[
        "collectible"
    ],
    "wof:name":"Cherished Treasures",
    "wof:placetype":"venue"
},
  "geometry": {"coordinates":[-75.49366999999999,39.13426],"type":"Point"}
}