{
  "type": "Feature",
  "properties": {
    "iso:country":"US",
    "sg:address":"35 Dorothy Cir",
    "sg:city":"Ocean View",
    "sg:classifiers":[
        {
            "category":"Building & Trades",
            "subcategory":"Construction",
            "type":"Services"
        }
    ],
    "sg:phone":"+1 302 537 6735",
    "sg:postcode":"19970",
    "sg:province":"DE",
    "sg:tags":[
        "house",
        "remodeling",
        "commercial",
        "residential",
        "contractor"
    ],
    "wof:name":"Bayland Renovators Inc",
    "wof:placetype":"venue"
},
  "geometry": {"coordinates":[-75.10563,38.556693],"type":"Point"}
}