{
  "type": "Feature",
  "properties": {
    "iso:country":"US",
    "sg:address":"3596 Concord Pike",
    "sg:city":"Wilmington",
    "sg:classifiers":[
        {
            "category":"Shopping",
            "type":"Retail Goods"
        }
    ],
    "sg:phone":"+1 302 479 9822",
    "sg:postcode":"19803",
    "sg:province":"DE",
    "sg:tags":[
        "merchandise"
    ],
    "wof:name":"Deck The Walls",
    "wof:placetype":"venue"
},
  "geometry": {"coordinates":[-75.548115,39.802553],"type":"Point"}
}