{
  "type": "Feature",
  "properties": {
    "addr:full":"26676 Centerview Dr Millsboro DE 19966",
    "addr:postcode":"26676;19966",
    "addr:street":"Centerview Dr",
    "iso:country":"US",
    "sg:address":"26676 Centerview Dr",
    "sg:city":"Millsboro",
    "sg:classifiers":[
        {
            "category":"Utilities",
            "subcategory":"Mobile Phone",
            "type":"Services"
        },
        {
            "category":"Shopping",
            "subcategory":"Mobile Phones",
            "type":"Retail Goods"
        }
    ],
    "sg:phone":"+1 302 933 0514",
    "sg:postcode":"19966",
    "sg:province":"DE",
    "sg:tags":[
        "supply",
        "communication",
        "telephone",
        "wireless",
        "equipment",
        "cellular"
    ],
    "wof:name":"Verizon Wireless",
    "wof:placetype":"venue"
},
  "geometry": {"coordinates":[-75.288577,38.573371],"type":"Point"}
}