{
  "type": "Feature",
  "properties": {
    "iso:country":"US",
    "sg:address":"15 Melody Dr",
    "sg:city":"Newark",
    "sg:classifiers":[
        {
            "category":"Food & Beverages",
            "subcategory":"Specialty",
            "type":"Retail Goods"
        }
    ],
    "sg:phone":"+1 302 836 1223",
    "sg:postcode":"19702",
    "sg:province":"DE",
    "sg:tags":[
        "vitamin"
    ],
    "wof:name":"Maria T Miller Hlth Supplement",
    "wof:placetype":"venue"
},
  "geometry": {"coordinates":[-75.751441,39.596345],"type":"Point"}
}