{
  "type": "Feature",
  "properties": {
    "iso:country":"US",
    "sg:address":"1714 Porter Rd",
    "sg:city":"Bear",
    "sg:classifiers":[
        {
            "category":"Government",
            "subcategory":"Fire Station",
            "type":"Public Place"
        }
    ],
    "sg:phone":"+1 302 834 2433",
    "sg:postcode":"19701",
    "sg:province":"DE",
    "sg:tags":[
        "department",
        "protection"
    ],
    "wof:name":"Christiana Fire Company",
    "wof:placetype":"venue"
},
  "geometry": {"coordinates":[-75.695579,39.595559],"type":"Point"}
}