{
  "type": "Feature",
  "properties": {
    "iso:country":"US",
    "sg:address":"100 W 10th St",
    "sg:city":"Wilmington",
    "sg:classifiers":[
        {
            "category":"Professional",
            "subcategory":"Research",
            "type":"Services"
        }
    ],
    "sg:phone":"+1 302 777 4711",
    "sg:postcode":"19801",
    "sg:province":"DE",
    "sg:tags":[
        "organization",
        "noncommercial"
    ],
    "wof:name":"Fair Play Foundation",
    "wof:placetype":"venue"
},
  "geometry": {"coordinates":[-75.54907300000001,39.74608],"type":"Point"}
}