{
  "type": "Feature",
  "properties": {
    "iso:country":"US",
    "sg:address":"206 Jestan Blvd",
    "sg:city":"Bear",
    "sg:classifiers":[
        {
            "category":"Banks & Credit Unions",
            "subcategory":"Bank",
            "type":"Services"
        }
    ],
    "sg:phone":"+1 302 838 4000",
    "sg:postcode":"19720",
    "sg:province":"DE",
    "sg:tags":[
        "loan",
        "mortgage",
        "real estate"
    ],
    "wof:name":"National Future Mortgage Inc",
    "wof:placetype":"venue"
},
  "geometry": {"coordinates":[-75.656373,39.612598],"type":"Point"}
}