{
  "type": "Feature",
  "properties": {
    "addr:full":"119 Ruthar Dr Newark DE 19711",
    "addr:housenumber":"119",
    "addr:postcode":"19711",
    "addr:street":"Ruthar Dr",
    "iso:country":"US",
    "sg:address":"119 Ruthar Dr",
    "sg:city":"Newark",
    "sg:classifiers":[
        {
            "category":"Wholesale",
            "subcategory":"Auto Parts",
            "type":"Manufacturing & Wholesale Goods"
        }
    ],
    "sg:phone":"+1 302 738 6684",
    "sg:postcode":"19711",
    "sg:province":"DE",
    "sg:tags":[
        "automotive"
    ],
    "wof:name":"Installers Express of Delaware",
    "wof:placetype":"venue"
},
  "geometry": {"coordinates":[-75.69031,39.691917],"type":"Point"}
}