{
  "type": "Feature",
  "properties": {
    "addr:full":"56 Britt Dr Magnolia DE 19962",
    "addr:housenumber":"56",
    "addr:postcode":"19962",
    "addr:street":"Britt Dr",
    "iso:country":"US",
    "sg:address":"56 Britt Dr",
    "sg:city":"Magnolia",
    "sg:classifiers":[
        {
            "category":"Restaurant",
            "type":"Food & Drink"
        }
    ],
    "sg:phone":"+1 302 698 5100",
    "sg:postcode":"19962",
    "sg:province":"DE",
    "wof:name":"LA Fontana Pizza & Restaurant",
    "wof:placetype":"venue"
},
  "geometry": {"coordinates":[-75.481701,39.077138],"type":"Point"}
}