{
  "type": "Feature",
  "properties": {
    "iso:country":"US",
    "sg:address":"307 S Laws St",
    "sg:city":"Bridgeville",
    "sg:classifiers":[
        {
            "category":"Professional",
            "subcategory":"Employment Agencies",
            "type":"Services"
        }
    ],
    "sg:phone":"+1 302 337 7801",
    "sg:postcode":"19933",
    "sg:province":"DE",
    "wof:name":"Jobs For Delaware Graduates",
    "wof:placetype":"venue"
},
  "geometry": {"coordinates":[-75.601282,38.739606],"type":"Point"}
}