{
  "type": "Feature",
  "properties": {
    "iso:country":"US",
    "sg:address":"6 Denny Rd",
    "sg:city":"Wilmington",
    "sg:classifiers":[
        {
            "category":"Insurance",
            "subcategory":"Insurance Agent",
            "type":"Services"
        }
    ],
    "sg:phone":"+1 302 762 9500",
    "sg:postcode":"19809",
    "sg:province":"DE",
    "wof:name":"Kc Financial Group Inc",
    "wof:placetype":"venue"
},
  "geometry": {"coordinates":[-75.505503,39.755448],"type":"Point"}
}