{
  "type": "Feature",
  "properties": {
    "iso:country":"US",
    "sg:address":"4 W 4th St",
    "sg:city":"Wilmington",
    "sg:classifiers":[
        {
            "category":"Organizations",
            "subcategory":"Religious Organization",
            "type":"Services"
        }
    ],
    "sg:phone":"+1 302 658 3511",
    "sg:postcode":"19801",
    "sg:province":"DE",
    "wof:name":"Worship and Praise Delvrnce",
    "wof:placetype":"venue"
},
  "geometry": {"coordinates":[-75.55188699999999,39.740578],"type":"Point"}
}