{
  "type": "Feature",
  "properties": {
    "iso:country":"US",
    "sg:address":"3505 Silverside Rd",
    "sg:city":"Wilmington",
    "sg:classifiers":[
        {
            "category":"Shopping",
            "type":"Retail Goods"
        }
    ],
    "sg:phone":"+1 302 737 0747",
    "sg:postcode":"19810",
    "sg:province":"DE",
    "sg:tags":[
        "hearing",
        "equipment",
        "supply",
        "impaired"
    ],
    "wof:name":"Beltone Hearing Aid Ctr",
    "wof:placetype":"venue"
},
  "geometry": {"coordinates":[-75.548912,39.809258],"type":"Point"}
}