{
  "type": "Feature",
  "properties": {
    "iso:country":"US",
    "sg:address":"1012 W State College Rd",
    "sg:city":"Dover",
    "sg:classifiers":[
        {
            "category":"Professional",
            "subcategory":"Management & Consulting",
            "type":"Services"
        },
        {
            "category":"Professional",
            "subcategory":"Credit Reporting & Collection",
            "type":"Services"
        }
    ],
    "sg:phone":"+1 302 730 4040",
    "sg:postcode":"19904",
    "sg:province":"DE",
    "sg:tags":[
        "consultant",
        "business"
    ],
    "wof:name":"Commercial Recovery Group Inc",
    "wof:placetype":"venue"
},
  "geometry": {"coordinates":[-75.55403099999999,39.175723],"type":"Point"}
}