{
  "type": "Feature",
  "properties": {
    "iso:country":"US",
    "sg:address":"520 Capitol Trl",
    "sg:city":"Newark",
    "sg:classifiers":[
        {
            "category":"Real Estate",
            "subcategory":"Real Estate Agent",
            "type":"Services"
        }
    ],
    "sg:phone":"+1 302 737 0365",
    "sg:postcode":"19711",
    "sg:province":"DE",
    "wof:name":"Marge Young Real Estate",
    "wof:placetype":"venue"
},
  "geometry": {"coordinates":[-75.72786600000001,39.690821],"type":"Point"}
}