{
  "type": "Feature",
  "properties": {
    "addr:full":"134 Brandywine Dr Bethany Beach DE 19930",
    "addr:housenumber":"134",
    "addr:postcode":"19930",
    "addr:street":"Brandywine Dr",
    "iso:country":"US",
    "sg:address":"134 Brandywine Dr",
    "sg:city":"Bethany Beach",
    "sg:classifiers":[
        {
            "category":"Professional",
            "subcategory":"Management & Consulting",
            "type":"Services"
        }
    ],
    "sg:phone":"+1 302 541 5361",
    "sg:postcode":"19930",
    "sg:province":"DE",
    "sg:tags":[
        "business"
    ],
    "wof:name":"William F Turner Consultants",
    "wof:placetype":"venue"
},
  "geometry": {"coordinates":[-75.057053,38.517693],"type":"Point"}
}