{
  "type": "Feature",
  "properties": {
    "iso:country":"US",
    "sg:address":"5402 Kennett Pike",
    "sg:city":"Wilmington",
    "sg:classifiers":[
        {
            "category":"Professional",
            "type":"Services"
        }
    ],
    "sg:phone":"+1 302 658 4545",
    "sg:postcode":"19807",
    "sg:province":"DE",
    "wof:name":"Luzerne Products Inc",
    "wof:placetype":"venue"
},
  "geometry": {"coordinates":[-75.614486,39.813371],"type":"Point"}
}