{
  "type": "Feature",
  "properties": {
    "addr:full":"2803 Philadelphia Pike Claymont DE 19703",
    "addr:housenumber":"2803",
    "addr:postcode":"19703",
    "addr:street":"Philadelphia Pike",
    "iso:country":"US",
    "sg:address":"2803 Philadelphia Pike",
    "sg:city":"Claymont",
    "sg:classifiers":[
        {
            "category":"Professional",
            "subcategory":"Computer Services",
            "type":"Services"
        }
    ],
    "sg:phone":"+1 302 322 3737",
    "sg:postcode":"19703",
    "sg:province":"DE",
    "sg:tags":[
        "datum"
    ],
    "wof:name":"Letskus Co",
    "wof:placetype":"venue"
},
  "geometry": {"coordinates":[-75.465951,39.79595],"type":"Point"}
}