{
  "type": "Feature",
  "properties": {
    "iso:country":"US",
    "sg:address":"1 S Heald St",
    "sg:city":"Wilmington",
    "sg:classifiers":[
        {
            "category":"Organizations",
            "subcategory":"Religious Organization",
            "type":"Services"
        }
    ],
    "sg:phone":"+1 302 654 0260",
    "sg:postcode":"19801",
    "sg:province":"DE",
    "sg:tags":[
        "church"
    ],
    "wof:name":"Agape Fellowship F W Baptist C",
    "wof:placetype":"venue"
},
  "geometry": {"coordinates":[-75.541776,39.732282],"type":"Point"}
}