{
  "type": "Feature",
  "properties": {
    "addr:full":"111 W Seneca Dr Newark DE 19702",
    "addr:housenumber":"111",
    "addr:postcode":"19702",
    "addr:street":"W Seneca Dr",
    "iso:country":"US",
    "sg:address":"111 W Seneca Dr",
    "sg:city":"Newark",
    "sg:classifiers":[
        {
            "category":"Professional",
            "subcategory":"Accounting & Tax Preparation",
            "type":"Services"
        }
    ],
    "sg:phone":"+1 302 368 0497",
    "sg:postcode":"19702",
    "sg:province":"DE",
    "sg:tags":[
        "bookkeeping",
        "payroll",
        "billing"
    ],
    "wof:name":"Bookkping For Small Businesses",
    "wof:placetype":"venue"
},
  "geometry": {"coordinates":[-75.64020600000001,39.686396],"type":"Point"}
}