{
  "type": "Feature",
  "properties": {
    "addr:full":"1401 Ridge Rd Wilmington DE 19809",
    "addr:housenumber":"1401",
    "addr:postcode":"19809",
    "addr:street":"Ridge Rd",
    "iso:country":"US",
    "sg:address":"1401 Ridge Rd",
    "sg:city":"Wilmington",
    "sg:classifiers":[
        {
            "category":"Professional",
            "subcategory":"Lawyer & Legal Services",
            "type":"Services"
        }
    ],
    "sg:phone":"+1 302 798 4822",
    "sg:postcode":"19809",
    "sg:province":"DE",
    "sg:tags":[
        "attorney"
    ],
    "wof:name":"Alfred J Lindh",
    "wof:placetype":"venue"
},
  "geometry": {"coordinates":[-75.478089,39.782177],"type":"Point"}
}