{
  "type": "Feature",
  "properties": {
    "iso:country":"US",
    "sg:address":"904 Cedartree Ln",
    "sg:city":"Claymont",
    "sg:classifiers":[
        {
            "category":"Health Services",
            "subcategory":"Doctor",
            "type":"Services"
        }
    ],
    "sg:phone":"+1 302 798 6690",
    "sg:postcode":"19703",
    "sg:province":"DE",
    "sg:tags":[
        "clinic"
    ],
    "wof:name":"International Behavioral Med",
    "wof:placetype":"venue"
},
  "geometry": {"coordinates":[-75.46370400000001,39.81643],"type":"Point"}
}