{
  "type": "Feature",
  "properties": {
    "iso:country":"US",
    "sg:address":"33116 Lighthouse Rd",
    "sg:city":"Selbyville",
    "sg:classifiers":[
        {
            "category":"Shopping",
            "subcategory":"Pets & Pet Supplies",
            "type":"Retail Goods"
        },
        {
            "category":"Retail",
            "subcategory":"Animal Services",
            "type":"Services"
        }
    ],
    "sg:phone":"+1 302 436 2008",
    "sg:postcode":"19975",
    "sg:province":"DE",
    "sg:tags":[
        "grooming",
        "dog",
        "cat"
    ],
    "sg:website":"http://www.washnwagspetgrooming.com",
    "wof:name":"Wash N Wag Pet Salon",
    "wof:placetype":"venue"
},
  "geometry": {"coordinates":[-75.136898,38.460885],"type":"Point"}
}