{
  "type": "Feature",
  "properties": {
    "iso:country":"US",
    "sg:address":"710 N Market St",
    "sg:city":"Wilmington",
    "sg:classifiers":[
        {
            "category":"Professional",
            "subcategory":"Art Services",
            "type":"Services"
        }
    ],
    "sg:phone":"+1 302 658 8984",
    "sg:postcode":"19802",
    "sg:province":"DE",
    "sg:tags":[
        "photographer"
    ],
    "wof:name":"Studio A Productions",
    "wof:placetype":"venue"
},
  "geometry": {"coordinates":[-75.549245,39.743286],"type":"Point"}
}