{
  "type": "Feature",
  "properties": {
    "iso:country":"US",
    "sg:address":"345 Bear Christiana Rd",
    "sg:city":"Bear",
    "sg:classifiers":[
        {
            "category":"Building & Trades",
            "subcategory":"Plumbing",
            "type":"Services"
        }
    ],
    "sg:phone":"+1 302 323 9719",
    "sg:postcode":"19701",
    "sg:province":"DE",
    "sg:tags":[
        "contractor"
    ],
    "wof:name":"F&G Mechanical Inc",
    "wof:placetype":"venue"
},
  "geometry": {"coordinates":[-75.654718,39.655313],"type":"Point"}
}