{
  "type": "Feature",
  "properties": {
    "iso:country":"US",
    "sg:address":"2062 New Castle Ave",
    "sg:city":"New Castle",
    "sg:classifiers":[
        {
            "category":"Home & Garden",
            "subcategory":"Household Appliances",
            "type":"Retail Goods"
        }
    ],
    "sg:phone":"+1 610 444 4208",
    "sg:postcode":"19720",
    "sg:province":"DE",
    "sg:tags":[
        "kirby",
        "cleaner",
        "retailer"
    ],
    "wof:name":"Kirby Company",
    "wof:placetype":"venue"
},
  "geometry": {"coordinates":[-75.554632,39.692724],"type":"Point"}
}