{
  "type": "Feature",
  "properties": {
    "iso:country":"US",
    "sg:address":"3631 Silverside Rd",
    "sg:city":"Wilmington",
    "sg:classifiers":[
        {
            "category":"Banks & Credit Unions",
            "subcategory":"Bank",
            "type":"Services"
        }
    ],
    "sg:phone":"+1 302 479 2553",
    "sg:postcode":"19810",
    "sg:province":"DE",
    "sg:tags":[
        "state",
        "savings"
    ],
    "wof:name":"Artisans Bank",
    "wof:placetype":"venue"
},
  "geometry": {"coordinates":[-75.54862300000001,39.809241],"type":"Point"}
}