{
  "type": "Feature",
  "properties": {
    "iso:country":"US",
    "sg:address":"501 Carr Rd",
    "sg:city":"Wilmington",
    "sg:classifiers":[
        {
            "category":"Real Estate",
            "subcategory":"Real Estate Operator",
            "type":"Services"
        }
    ],
    "sg:phone":"+1 302 764 5676",
    "sg:postcode":"19809",
    "sg:province":"DE",
    "sg:tags":[
        "building",
        "nonresidential"
    ],
    "wof:name":"Rockwood Office Park Assoc",
    "wof:placetype":"venue"
},
  "geometry": {"coordinates":[-75.494078,39.784186],"type":"Point"}
}