{
  "type": "Feature",
  "properties": {
    "addr:full":"600 N Lombard St Wilmington DE 19801",
    "addr:housenumber":"600",
    "addr:postcode":"19801",
    "addr:street":"N Lombard St",
    "iso:country":"US",
    "sg:address":"600 N Lombard St",
    "sg:city":"Wilmington",
    "sg:classifiers":[
        {
            "category":"Education",
            "subcategory":"School",
            "type":"Public Place"
        }
    ],
    "sg:phone":"+1 302 552 2600",
    "sg:postcode":"19801",
    "sg:province":"DE",
    "wof:name":"Christina School District",
    "wof:placetype":"venue"
},
  "geometry": {"coordinates":[-75.545158,39.739849],"type":"Point"}
}