{
  "type": "Feature",
  "properties": {
    "iso:country":"US",
    "sg:address":"107 N Broad St",
    "sg:city":"Middletown",
    "sg:classifiers":[
        {
            "category":"Professional",
            "type":"Services"
        }
    ],
    "sg:phone":"+1 302 449 0030",
    "sg:postcode":"19709",
    "sg:province":"DE",
    "wof:name":"Educaid",
    "wof:placetype":"venue"
},
  "geometry": {"coordinates":[-75.71704200000001,39.451127],"type":"Point"}
}