{
  "type": "Feature",
  "properties": {
    "addr:full":"89 Woods Dr Millsboro DE 19958",
    "addr:housenumber":"89",
    "addr:postcode":"19958",
    "addr:street":"Woods Dr",
    "iso:country":"US",
    "sg:address":"89 Woods Dr",
    "sg:city":"Millsboro",
    "sg:classifiers":[
        {
            "category":"Building & Trades",
            "subcategory":"Construction",
            "type":"Services"
        }
    ],
    "sg:phone":"+1 302 947 1731",
    "sg:postcode":"19958",
    "sg:province":"DE",
    "sg:tags":[
        "painter"
    ],
    "wof:name":"Robert S Sharp Painting Inc",
    "wof:placetype":"venue"
},
  "geometry": {"coordinates":[-75.148877,38.66683],"type":"Point"}
}