{
  "type": "Feature",
  "properties": {
    "iso:country":"US",
    "sg:address":"38 N Walnut St",
    "sg:city":"Milford",
    "sg:classifiers":[
        {
            "category":"Personal",
            "subcategory":"Barber",
            "type":"Services"
        }
    ],
    "sg:phone":"+1 302 422 7739",
    "sg:postcode":"19963",
    "sg:province":"DE",
    "sg:tags":[
        "shop"
    ],
    "wof:name":"Downtowne Barber Shop",
    "wof:placetype":"venue"
},
  "geometry": {"coordinates":[-75.42826700000001,38.9142],"type":"Point"}
}