{
  "type": "Feature",
  "properties": {
    "addr:full":"51 Valley Ct Wilmington DE 19810",
    "addr:housenumber":"51",
    "addr:postcode":"19810",
    "addr:street":"Valley Ct",
    "iso:country":"US",
    "sg:address":"51 Valley Ct",
    "sg:city":"Wilmington",
    "sg:classifiers":[
        {
            "category":"Freight",
            "type":"Transportation"
        }
    ],
    "sg:phone":"+1 302 475 6221",
    "sg:postcode":"19810",
    "sg:province":"DE",
    "sg:tags":[
        "operator",
        "local",
        "trucking"
    ],
    "wof:name":"Thomson Delivery Service",
    "wof:placetype":"venue"
},
  "geometry": {"coordinates":[-75.466739,39.824004],"type":"Point"}
}