{
  "type": "Feature",
  "properties": {
    "addr:full":"2234 Marsh Rd Wilmington DE 19810",
    "addr:housenumber":"2234",
    "addr:postcode":"19810",
    "addr:street":"Marsh Rd",
    "iso:country":"US",
    "sg:address":"2234 Marsh Rd",
    "sg:city":"Wilmington",
    "sg:classifiers":[
        {
            "category":"Real Estate",
            "subcategory":"Architect",
            "type":"Services"
        }
    ],
    "sg:phone":"+1 302 475 4805",
    "sg:postcode":"19810",
    "sg:province":"DE",
    "sg:tags":[
        "architectural"
    ],
    "wof:name":"Lee Smith Architects Inc",
    "wof:placetype":"venue"
},
  "geometry": {"coordinates":[-75.489569,39.815246],"type":"Point"}
}