{
  "type": "Feature",
  "properties": {
    "iso:country":"US",
    "sg:address":"1406 Bucknell Rd",
    "sg:city":"Wilmington",
    "sg:classifiers":[
        {
            "category":"Professional",
            "subcategory":"Management & Consulting",
            "type":"Services"
        }
    ],
    "sg:phone":"+1 302 478 7296",
    "sg:postcode":"19803",
    "sg:province":"DE",
    "sg:tags":[
        "business"
    ],
    "wof:name":"D Pulido",
    "wof:placetype":"venue"
},
  "geometry": {"coordinates":[-75.494704,39.795003],"type":"Point"}
}