{
  "type": "Feature",
  "properties": {
    "addr:full":"2217 Beaumont Rd Wilmington DE 19803",
    "addr:housenumber":"2217",
    "addr:postcode":"19803",
    "addr:street":"Beaumont Rd",
    "iso:country":"US",
    "sg:address":"2217 Beaumont Rd",
    "sg:city":"Wilmington",
    "sg:classifiers":[
        {
            "category":"Insurance",
            "subcategory":"Hazard Insurance",
            "type":"Services"
        }
    ],
    "sg:phone":"+1 302 658 3601",
    "sg:postcode":"19803",
    "sg:province":"DE",
    "sg:tags":[
        "commercial",
        "business"
    ],
    "wof:name":"Thomas P Delucia",
    "wof:placetype":"venue"
},
  "geometry": {"coordinates":[-75.541375,39.79232],"type":"Point"}
}