{
  "type": "Feature",
  "properties": {
    "iso:country":"US",
    "sg:address":"146 Fox Hunt Dr",
    "sg:city":"Bear",
    "sg:classifiers":[
        {
            "category":"Banks & Credit Unions",
            "subcategory":"Bank",
            "type":"Services"
        }
    ],
    "sg:phone":"+1 302 832 3800",
    "sg:postcode":"19701",
    "sg:province":"DE",
    "sg:tags":[
        "banking",
        "facility"
    ],
    "wof:name":"Mellon",
    "wof:placetype":"venue"
},
  "geometry": {"coordinates":[-75.712737,39.608144],"type":"Point"}
}