{
  "type": "Feature",
  "properties": {
    "addr:full":"3430 Philadelphia Pike Claymont DE 19703",
    "addr:housenumber":"3430",
    "addr:postcode":"19703",
    "addr:street":"Philadelphia Pike",
    "iso:country":"US",
    "sg:address":"3430 Philadelphia Pike",
    "sg:city":"Claymont",
    "sg:classifiers":[
        {
            "category":"Government",
            "subcategory":"Post Office",
            "type":"Public Place"
        }
    ],
    "sg:phone":"+1 302 798 6671",
    "sg:postcode":"19703",
    "sg:province":"DE",
    "sg:tags":[
        "postal",
        "us"
    ],
    "sg:website":"www.usps.com",
    "wof:name":"US Post Office",
    "wof:placetype":"venue"
},
  "geometry": {"coordinates":[-75.460083,39.80072],"type":"Point"}
}