{
  "type": "Feature",
  "properties": {
    "addr:full":"4013 Old Capitol Trl Wilmington DE 19808",
    "addr:housenumber":"4013",
    "addr:postcode":"19808",
    "addr:street":"Old Capitol Trl",
    "iso:country":"US",
    "sg:address":"4013 Old Capitol Trl",
    "sg:city":"Wilmington",
    "sg:classifiers":[
        {
            "category":"Personal",
            "subcategory":"Beauty Salon",
            "type":"Services"
        }
    ],
    "sg:phone":"+1 302 478 7080",
    "sg:postcode":"19808",
    "sg:province":"DE",
    "wof:name":"Rhonda Moore",
    "wof:placetype":"venue"
},
  "geometry": {"coordinates":[-75.64870999999999,39.726862],"type":"Point"}
}