{
  "type": "Feature",
  "properties": {
    "iso:country":"US",
    "sg:address":"34 Dryden Rd",
    "sg:city":"New Castle",
    "sg:classifiers":[
        {
            "category":"Professional",
            "subcategory":"Lawyer & Legal Services",
            "type":"Services"
        }
    ],
    "sg:phone":"+1 302 328 8768",
    "sg:postcode":"19720",
    "sg:province":"DE",
    "wof:name":"M & T Associates",
    "wof:placetype":"venue"
},
  "geometry": {"coordinates":[-75.636618,39.666914],"type":"Point"}
}