{
  "type": "Feature",
  "properties": {
    "iso:country":"US",
    "sg:address":"19 Davidson Ln",
    "sg:city":"New Castle",
    "sg:classifiers":[
        {
            "category":"Professional",
            "subcategory":"Research",
            "type":"Services"
        }
    ],
    "sg:phone":"+1 302 777 7403",
    "sg:postcode":"19720",
    "sg:province":"DE",
    "sg:tags":[
        "environmental",
        "ecological"
    ],
    "wof:name":"Hazardous Materials Handling",
    "wof:placetype":"venue"
},
  "geometry": {"coordinates":[-75.538636,39.702089],"type":"Point"}
}