{
  "type": "Feature",
  "properties": {
    "iso:country":"US",
    "sg:address":"1653 Van Dyke Greenspring Rd",
    "sg:city":"Smyrna",
    "sg:classifiers":[
        {
            "category":"Travel",
            "subcategory":"Hotels & Motels",
            "type":"Entertainment"
        }
    ],
    "sg:phone":"+1 302 653 1223",
    "sg:postcode":"19977",
    "sg:province":"DE",
    "sg:tags":[
        "breakfast",
        "accommodation",
        "bed"
    ],
    "wof:name":"Ramblin Rose Bed & Breakfast",
    "wof:placetype":"venue"
},
  "geometry": {"coordinates":[-75.653944,39.318413],"type":"Point"}
}