{
  "type": "Feature",
  "properties": {
    "iso:country":"US",
    "sg:address":"5 Baltimore Ave",
    "sg:city":"Georgetown",
    "sg:classifiers":[
        {
            "category":"Education",
            "subcategory":"School",
            "type":"Public Place"
        }
    ],
    "sg:phone":"+1 302 854 9323",
    "sg:postcode":"19947",
    "sg:province":"DE",
    "wof:name":"J Fran Dell Georgetown",
    "wof:placetype":"venue"
},
  "geometry": {"coordinates":[-75.34901000000001,38.693285],"type":"Point"}
}