{
  "type": "Feature",
  "properties": {
    "addr:full":"1621 N Heald St Wilmington DE 19802",
    "addr:housenumber":"1621",
    "addr:postcode":"19802",
    "addr:street":"N Heald St",
    "iso:country":"US",
    "sg:address":"1621 N Heald St",
    "sg:city":"Wilmington",
    "sg:classifiers":[
        {
            "category":"Social Services",
            "subcategory":"Child Care",
            "type":"Services"
        }
    ],
    "sg:phone":"+1 302 652 6892",
    "sg:postcode":"19802",
    "sg:province":"DE",
    "sg:tags":[
        "day"
    ],
    "wof:name":"Price Run Child Center",
    "wof:placetype":"venue"
},
  "geometry": {"coordinates":[-75.53235599999999,39.746224],"type":"Point"}
}