{
  "type": "Feature",
  "properties": {
    "iso:country":"US",
    "sg:address":"650 S Bay Rd",
    "sg:city":"Dover",
    "sg:classifiers":[
        {
            "category":"Shopping",
            "subcategory":"Discount & Variety Stores",
            "type":"Retail Goods"
        },
        {
            "category":"Shopping",
            "subcategory":"Department Store",
            "type":"Retail Goods"
        }
    ],
    "sg:phone":"+1 302 734 0902",
    "sg:postcode":"19901",
    "sg:province":"DE",
    "sg:tags":[
        "shop"
    ],
    "wof:name":"Family Dollar Stores",
    "wof:placetype":"venue"
},
  "geometry": {"coordinates":[-75.50773,39.154669],"type":"Point"}
}