{
  "type": "Feature",
  "properties": {
    "addr:full":"700 West St Laurel DE 19956",
    "addr:housenumber":"700",
    "addr:postcode":"19956",
    "addr:street":"West St",
    "iso:country":"US",
    "sg:address":"700 West St",
    "sg:city":"Laurel",
    "sg:classifiers":[
        {
            "category":"Retail",
            "subcategory":"Funeral Services",
            "type":"Services"
        }
    ],
    "sg:phone":"+1 302 875 3637",
    "sg:postcode":"19956",
    "sg:province":"DE",
    "sg:tags":[
        "plan",
        "merchandise"
    ],
    "wof:name":"Short Funeral Homes Inc",
    "wof:placetype":"venue"
},
  "geometry": {"coordinates":[-75.576168,38.553255],"type":"Point"}
}