{
  "type": "Feature",
  "properties": {
    "addr:full":"28 Colgate Dr Rehoboth Beach DE 19971",
    "addr:housenumber":"28",
    "addr:postcode":"19971",
    "addr:street":"Colgate Dr",
    "iso:country":"US",
    "sg:address":"28 Colgate Dr",
    "sg:city":"Rehoboth Beach",
    "sg:classifiers":[
        {
            "category":"Professional",
            "subcategory":"Business Services",
            "type":"Services"
        }
    ],
    "sg:phone":"+1 302 645 2044",
    "sg:postcode":"19971",
    "sg:province":"DE",
    "sg:tags":[
        "tile",
        "window",
        "painting",
        "treatment"
    ],
    "wof:name":"All Around Design",
    "wof:placetype":"venue"
},
  "geometry": {"coordinates":[-75.13852300000001,38.729001],"type":"Point"}
}