{
  "type": "Feature",
  "properties": {
    "iso:country":"US",
    "sg:address":"19 NW Front St",
    "sg:city":"Milford",
    "sg:classifiers":[
        {
            "category":"Retail",
            "subcategory":"Repair Shop",
            "type":"Services"
        }
    ],
    "sg:phone":"+1 302 422 0396",
    "sg:postcode":"19963",
    "sg:province":"DE",
    "wof:name":"Country Comfort Upholstering",
    "wof:placetype":"venue"
},
  "geometry": {"coordinates":[-75.428405,38.914592],"type":"Point"}
}