{
  "type": "Feature",
  "properties": {
    "addr:full":"503 Autumn Moon Ln Magnolia DE 19962",
    "addr:housenumber":"503",
    "addr:postcode":"19962",
    "addr:street":"Autumn Moon Ln",
    "iso:country":"US",
    "sg:address":"503 Autumn Moon Ln",
    "sg:city":"Magnolia",
    "sg:classifiers":[
        {
            "category":"Marine",
            "type":"Transportation"
        }
    ],
    "sg:phone":"+1 302 697 9133",
    "sg:postcode":"19962",
    "sg:province":"DE",
    "sg:tags":[
        "repair"
    ],
    "wof:name":"K & F Auto Repair & Towing LLC",
    "wof:placetype":"venue"
},
  "geometry": {"coordinates":[-75.51611800000001,39.067823],"type":"Point"}
}