{
  "type": "Feature",
  "properties": {
    "iso:country":"US",
    "sg:address":"1201 N Market St",
    "sg:city":"Wilmington",
    "sg:classifiers":[
        {
            "category":"Travel",
            "subcategory":"Travel Agent",
            "type":"Entertainment"
        }
    ],
    "sg:phone":"+1 302 427 9991",
    "sg:postcode":"19801",
    "sg:province":"DE",
    "sg:tags":[
        "agency"
    ],
    "wof:name":"Holiday Travel-Rosenbluth Vaca",
    "wof:placetype":"venue"
},
  "geometry": {"coordinates":[-75.54606699999999,39.748169],"type":"Point"}
}