{
  "type": "Feature",
  "properties": {
    "iso:country":"US",
    "sg:address":"39 Stuart Dr",
    "sg:city":"Dover",
    "sg:classifiers":[
        {
            "category":"Professional",
            "subcategory":"Management & Consulting",
            "type":"Services"
        }
    ],
    "sg:phone":"+1 302 697 0559",
    "sg:postcode":"19901",
    "sg:province":"DE",
    "sg:tags":[
        "public",
        "relations"
    ],
    "wof:name":"Sellabrate",
    "wof:placetype":"venue"
},
  "geometry": {"coordinates":[-75.511028,39.124933],"type":"Point"}
}