{
  "type": "Feature",
  "properties": {
    "iso:country":"US",
    "sg:address":"2605 Woodview Dr",
    "sg:city":"Wilmington",
    "sg:classifiers":[
        {
            "category":"Building & Trades",
            "subcategory":"Plumbing",
            "type":"Services"
        }
    ],
    "sg:phone":"+1 302 998 4027",
    "sg:postcode":"19808",
    "sg:province":"DE",
    "sg:tags":[
        "plumbing",
        "contractor"
    ],
    "wof:name":"William J Woodward Inc",
    "wof:placetype":"venue"
},
  "geometry": {"coordinates":[-75.630314,39.74745],"type":"Point"}
}