{
  "type": "Feature",
  "properties": {
    "iso:country":"US",
    "sg:address":"16 Cherry Dr W",
    "sg:city":"Magnolia",
    "sg:classifiers":[
        {
            "category":"Social Services",
            "subcategory":"Child Care",
            "type":"Services"
        }
    ],
    "sg:phone":"+1 302 698 3093",
    "sg:postcode":"19962",
    "sg:province":"DE",
    "sg:tags":[
        "day"
    ],
    "wof:name":"Debra Lamb Day Care",
    "wof:placetype":"venue"
},
  "geometry": {"coordinates":[-75.532659,39.065114],"type":"Point"}
}