{
  "type": "Feature",
  "properties": {
    "iso:country":"US",
    "sg:address":"344 Tyler Ln",
    "sg:city":"Smyrna",
    "sg:classifiers":[
        {
            "category":"Shopping",
            "subcategory":"Used Merchandise",
            "type":"Retail Goods"
        }
    ],
    "sg:phone":"+1 302 653 6237",
    "sg:postcode":"19977",
    "sg:province":"DE",
    "wof:name":"Jacobs Antiques",
    "wof:placetype":"venue"
},
  "geometry": {"coordinates":[-75.60537600000001,39.293037],"type":"Point"}
}