{
  "type": "Feature",
  "properties": {
    "iso:country":"US",
    "sg:address":"1301 Savannah Rd",
    "sg:city":"Lewes",
    "sg:classifiers":[
        {
            "category":"Personal",
            "subcategory":"Beauty Salon",
            "type":"Services"
        }
    ],
    "sg:phone":"+1 302 645 8164",
    "sg:postcode":"19958",
    "sg:province":"DE",
    "sg:tags":[
        "shop"
    ],
    "wof:name":"Bettys Hair Design",
    "wof:placetype":"venue"
},
  "geometry": {"coordinates":[-75.153521,38.760729],"type":"Point"}
}