{
  "type": "Feature",
  "properties": {
    "iso:country":"US",
    "sg:address":"10 Withers Way",
    "sg:city":"Hockessin",
    "sg:classifiers":[
        {
            "category":"Shopping",
            "subcategory":"Used Merchandise",
            "type":"Retail Goods"
        }
    ],
    "sg:phone":"+1 302 235 0708",
    "sg:postcode":"19707",
    "sg:province":"DE",
    "sg:tags":[
        "resale",
        "shop"
    ],
    "wof:name":"Southern Resale",
    "wof:placetype":"venue"
},
  "geometry": {"coordinates":[-75.681068,39.776001],"type":"Point"}
}