{
  "type": "Feature",
  "properties": {
    "iso:country":"US",
    "sg:address":"211 Shorewind Rd",
    "sg:city":"Bear",
    "sg:classifiers":[
        {
            "category":"Building & Trades",
            "subcategory":"Construction",
            "type":"Services"
        }
    ],
    "sg:phone":"+1 302 322 3358",
    "sg:postcode":"19701",
    "sg:province":"DE",
    "sg:tags":[
        "paving",
        "contractor"
    ],
    "wof:name":"William Mc Kenzie Paving",
    "wof:placetype":"venue"
},
  "geometry": {"coordinates":[-75.639832,39.644121],"type":"Point"}
}