{
  "type": "Feature",
  "properties": {
    "addr:full":"234 N Clayton St Wilmington DE 19805",
    "addr:housenumber":"234",
    "addr:postcode":"19805",
    "addr:street":"N Clayton St",
    "iso:country":"US",
    "sg:address":"234 N Clayton St",
    "sg:city":"Wilmington",
    "sg:classifiers":[
        {
            "category":"Organizations",
            "subcategory":"Religious Organization",
            "type":"Services"
        }
    ],
    "sg:phone":"+1 302 778 2847",
    "sg:postcode":"19805",
    "sg:province":"DE",
    "sg:tags":[
        "church"
    ],
    "wof:name":"New Life Christian Ctr",
    "wof:placetype":"venue"
},
  "geometry": {"coordinates":[-75.56871700000001,39.746275],"type":"Point"}
}