{
  "type": "Feature",
  "properties": {
    "addr:full":"24 Sanford Dr Newark DE 19713",
    "addr:housenumber":"24",
    "addr:postcode":"19713",
    "addr:street":"Sanford Dr",
    "iso:country":"US",
    "sg:address":"24 Sanford Dr",
    "sg:city":"Newark",
    "sg:classifiers":[
        {
            "category":"Shopping",
            "subcategory":"Gifts & Souvenirs",
            "type":"Retail Goods"
        }
    ],
    "sg:phone":"+1 302 427 9421",
    "sg:postcode":"19713",
    "sg:province":"DE",
    "wof:name":"Gift-A Day",
    "wof:placetype":"venue"
},
  "geometry": {"coordinates":[-75.740804,39.659774],"type":"Point"}
}