{
  "type": "Feature",
  "properties": {
    "addr:full":"54 Central Ave Ocean View DE 19970",
    "addr:housenumber":"54",
    "addr:postcode":"19970",
    "addr:street":"Central Ave",
    "iso:country":"US",
    "sg:address":"54 Central Ave",
    "sg:city":"Ocean View",
    "sg:classifiers":[
        {
            "category":"Building & Trades",
            "subcategory":"Construction",
            "type":"Services"
        }
    ],
    "sg:phone":"+1 302 537 1916",
    "sg:postcode":"19970",
    "sg:province":"DE",
    "sg:tags":[
        "contractor"
    ],
    "wof:name":"Benjamin B Smith Builders Inc",
    "wof:placetype":"venue"
},
  "geometry": {"coordinates":[-75.090333,38.545859],"type":"Point"}
}