{
  "type": "Feature",
  "properties": {
    "addr:full":"1411 Walnut Shade Rd Dover DE 19901",
    "addr:housenumber":"1411",
    "addr:postcode":"19901",
    "addr:street":"Walnut Shade Rd",
    "iso:country":"US",
    "sg:address":"1411 Walnut Shade Rd",
    "sg:city":"Dover",
    "sg:classifiers":[
        {
            "category":"Social Services",
            "subcategory":"Child Care",
            "type":"Services"
        }
    ],
    "sg:phone":"+1 302 697 1561",
    "sg:postcode":"19901",
    "sg:province":"DE",
    "sg:tags":[
        "day"
    ],
    "wof:name":"Theresa's Christian Home Day Care",
    "wof:placetype":"venue"
},
  "geometry": {"coordinates":[-75.53679700000001,39.074501],"type":"Point"}
}