{
  "type": "Feature",
  "properties": {
    "iso:country":"US",
    "sg:address":"1708 Naamans Rd",
    "sg:city":"Wilmington",
    "sg:classifiers":[
        {
            "category":"Recreation",
            "type":"Entertainment"
        }
    ],
    "sg:phone":"+1 302 529 0134",
    "sg:postcode":"19810",
    "sg:province":"DE",
    "sg:tags":[
        "karate",
        "judo",
        "instr"
    ],
    "wof:name":"Fraser's Karate",
    "wof:placetype":"venue"
},
  "geometry": {"coordinates":[-75.488556,39.82294],"type":"Point"}
}