{
  "type": "Feature",
  "properties": {
    "addr:full":"1818 Marsh Rd Wilmington DE 19810",
    "addr:housenumber":"1818",
    "addr:postcode":"19810",
    "addr:street":"Marsh Rd",
    "iso:country":"US",
    "sg:address":"1818 Marsh Rd",
    "sg:city":"Wilmington",
    "sg:classifiers":[
        {
            "category":"Building & Trades",
            "subcategory":"Plumbing",
            "type":"Services"
        }
    ],
    "sg:phone":"+1 302 529 1220",
    "sg:postcode":"19810",
    "sg:province":"DE",
    "sg:website":"Leaks'nheat.Com",
    "wof:name":"Stan Perkoski Plumbing & Heating Inc",
    "wof:placetype":"venue"
},
  "geometry": {"coordinates":[-75.50309799999999,39.8041],"type":"Point"}
}