{
  "type": "Feature",
  "properties": {
    "iso:country":"US",
    "sg:address":"3 S Main St",
    "sg:city":"Selbyville",
    "sg:classifiers":[
        {
            "category":"Shopping",
            "subcategory":"Used Merchandise",
            "type":"Retail Goods"
        }
    ],
    "sg:phone":"+1 302 436 9496",
    "sg:postcode":"19975",
    "sg:province":"DE",
    "sg:tags":[
        "antique"
    ],
    "wof:name":"Your Favorite Pl In Selbyville",
    "wof:placetype":"venue"
},
  "geometry": {"coordinates":[-75.220733,38.459683],"type":"Point"}
}