{
  "type": "Feature",
  "properties": {
    "iso:country":"US",
    "sg:address":"4 S Bancroft Pkwy",
    "sg:city":"Wilmington",
    "sg:classifiers":[
        {
            "category":"Organizations",
            "subcategory":"Religious Organization",
            "type":"Services"
        }
    ],
    "sg:phone":"+1 302 658 8633",
    "sg:postcode":"19805",
    "sg:province":"DE",
    "wof:name":"Saint Thomas Apostle RC Church",
    "wof:placetype":"venue"
},
  "geometry": {"coordinates":[-75.575878,39.746166],"type":"Point"}
}