{
  "type": "Feature",
  "properties": {
    "iso:country":"US",
    "sg:address":"1105 N Market St",
    "sg:city":"Wilmington",
    "sg:classifiers":[
        {
            "category":"Communications",
            "type":"Services"
        }
    ],
    "sg:phone":"+1 302 479 5416",
    "sg:postcode":"19801",
    "sg:province":"DE",
    "wof:name":"Rasor Communications Inc",
    "wof:placetype":"venue"
},
  "geometry": {"coordinates":[-75.54670400000001,39.747329],"type":"Point"}
}