{
  "type": "Feature",
  "properties": {
    "iso:country":"US",
    "sg:address":"1 Meco Cir",
    "sg:city":"Wilmington",
    "sg:classifiers":[
        {
            "category":"Manufacturing",
            "subcategory":"Printing",
            "type":"Manufacturing & Wholesale Goods"
        }
    ],
    "sg:phone":"+1 302 995 0820",
    "sg:postcode":"19804",
    "sg:province":"DE",
    "sg:tags":[
        "printer"
    ],
    "sg:website":"www.cannprinting.com",
    "wof:name":"William N Cann Inc",
    "wof:placetype":"venue"
},
  "geometry": {"coordinates":[-75.578676,39.722493],"type":"Point"}
}