{
  "type": "Feature",
  "properties": {
    "addr:full":"201 W 19th St Wilmington DE 19802",
    "addr:housenumber":"201",
    "addr:postcode":"19802",
    "addr:street":"W 19Th St",
    "iso:country":"US",
    "sg:address":"201 W 19th St",
    "sg:city":"Wilmington",
    "sg:classifiers":[
        {
            "category":"Professional",
            "type":"Services"
        }
    ],
    "sg:phone":"+1 302 652 8625",
    "sg:postcode":"19802",
    "sg:province":"DE",
    "wof:name":"P Gravitt",
    "wof:placetype":"venue"
},
  "geometry": {"coordinates":[-75.54476699999999,39.754266],"type":"Point"}
}