{
  "type": "Feature",
  "properties": {
    "iso:country":"US",
    "sg:address":"2110 N Market St",
    "sg:city":"Wilmington",
    "sg:classifiers":[
        {
            "category":"Food & Beverages",
            "subcategory":"Liquor & Beverages",
            "type":"Retail Goods"
        }
    ],
    "sg:phone":"+1 302 652 0401",
    "sg:postcode":"19802",
    "sg:province":"DE",
    "sg:tags":[
        "alcoholic"
    ],
    "wof:name":"Brandywine Village Liquors",
    "wof:placetype":"venue"
},
  "geometry": {"coordinates":[-75.53998799999999,39.75254],"type":"Point"}
}