{
  "type": "Feature",
  "properties": {
    "iso:country":"US",
    "sg:address":"32 Harris Cir",
    "sg:city":"Newark",
    "sg:classifiers":[
        {
            "category":"Professional",
            "type":"Services"
        },
        {
            "category":"Building & Trades",
            "subcategory":"Plumbing",
            "type":"Services"
        }
    ],
    "sg:phone":"+1 302 234 5330",
    "sg:postcode":"19711",
    "sg:province":"DE",
    "sg:tags":[
        "control",
        "air",
        "pollution"
    ],
    "wof:name":"Advanced Environmental Systems",
    "wof:placetype":"venue"
},
  "geometry": {"coordinates":[-75.73861100000001,39.765396],"type":"Point"}
}