{
  "type": "Feature",
  "properties": {
    "iso:country":"US",
    "sg:address":"4164 N Dupont Hwy",
    "sg:city":"Dover",
    "sg:classifiers":[
        {
            "category":"Professional",
            "subcategory":"Business Services",
            "type":"Services"
        }
    ],
    "sg:phone":"+1 302 346 2679",
    "sg:postcode":"19901",
    "sg:province":"DE",
    "wof:name":"Bechard Group",
    "wof:placetype":"venue"
},
  "geometry": {"coordinates":[-75.565538,39.206755],"type":"Point"}
}