{
  "type": "Feature",
  "properties": {
    "iso:country":"US",
    "sg:address":"300 Nicola Ln",
    "sg:city":"Hockessin",
    "sg:classifiers":[
        {
            "category":"Organizations",
            "subcategory":"Community Association",
            "type":"Services"
        }
    ],
    "sg:phone":"+1 302 234 4177",
    "sg:postcode":"19707",
    "sg:province":"DE",
    "wof:name":"Fraternal Ord of Police St Ldg",
    "wof:placetype":"venue"
},
  "geometry": {"coordinates":[-75.72337400000001,39.781608],"type":"Point"}
}