{
  "type": "Feature",
  "properties": {
    "iso:country":"US",
    "sg:address":"506 N Pine St",
    "sg:city":"Seaford",
    "sg:classifiers":[
        {
            "category":"Professional",
            "subcategory":"Computer Services",
            "type":"Services"
        }
    ],
    "sg:phone":"+1 302 628 0823",
    "sg:postcode":"19973",
    "sg:province":"DE",
    "wof:name":"Pentium Plus",
    "wof:placetype":"venue"
},
  "geometry": {"coordinates":[-75.615973,38.645558],"type":"Point"}
}