{
  "type": "Feature",
  "properties": {
    "iso:country":"US",
    "sg:address":"30 Baltimore Ave",
    "sg:city":"Rehoboth Beach",
    "sg:classifiers":[
        {
            "category":"Restaurant",
            "type":"Food & Drink"
        }
    ],
    "sg:menulink":"http://www.allmenus.com/de/lewes/236754-adriatico-italian-restaurant/menu/",
    "sg:phone":"+1 302 227 9255",
    "sg:postcode":"19971",
    "sg:province":"DE",
    "sg:tags":[
        "italian"
    ],
    "wof:name":"Adriatico Italian Restaurant",
    "wof:placetype":"venue"
},
  "geometry": {"coordinates":[-75.07942300000001,38.717031],"type":"Point"}
}