{
  "type": "Feature",
  "properties": {
    "iso:country":"US",
    "sg:address":"508 SE 2nd St",
    "sg:city":"Milford",
    "sg:classifiers":[
        {
            "category":"Food & Beverages",
            "subcategory":"Groceries & Convenience Stores",
            "type":"Retail Goods"
        }
    ],
    "sg:phone":"+1 302 422 6576",
    "sg:postcode":"19963",
    "sg:province":"DE",
    "sg:tags":[
        "grocer"
    ],
    "wof:name":"Mills Brothers Markets",
    "wof:placetype":"venue"
},
  "geometry": {"coordinates":[-75.42151,38.910348],"type":"Point"}
}