{
  "type": "Feature",
  "properties": {
    "iso:country":"US",
    "sg:address":"4 Hampton Ct",
    "sg:city":"Newark",
    "sg:classifiers":[
        {
            "category":"Professional",
            "subcategory":"Art Services",
            "type":"Services"
        }
    ],
    "sg:phone":"+1 302 834 4347",
    "sg:postcode":"19702",
    "sg:province":"DE",
    "sg:tags":[
        "calligrapher"
    ],
    "wof:name":"Curly Cues Calligraphy",
    "wof:placetype":"venue"
},
  "geometry": {"coordinates":[-75.685171,39.625227],"type":"Point"}
}