{
  "type": "Feature",
  "properties": {
    "iso:country":"US",
    "sg:address":"1005 W 27th St",
    "sg:city":"Wilmington",
    "sg:classifiers":[
        {
            "category":"Shopping",
            "subcategory":"Used Merchandise",
            "type":"Retail Goods"
        }
    ],
    "sg:phone":"+1 302 654 8255",
    "sg:postcode":"19802",
    "sg:province":"DE",
    "sg:tags":[
        "furniture"
    ],
    "wof:name":"Resettlers Inc",
    "wof:placetype":"venue"
},
  "geometry": {"coordinates":[-75.542141,39.764442],"type":"Point"}
}