{
  "type": "Feature",
  "properties": {
    "iso:country":"US",
    "sg:address":"3512 Silverside Rd",
    "sg:city":"Wilmington",
    "sg:classifiers":[
        {
            "category":"Professional",
            "subcategory":"Business Services",
            "type":"Services"
        }
    ],
    "sg:phone":"+1 302 478 0478",
    "sg:postcode":"19810",
    "sg:province":"DE",
    "sg:tags":[
        "appraiser"
    ],
    "wof:name":"Timothy J Smith & Assoc",
    "wof:placetype":"venue"
},
  "geometry": {"coordinates":[-75.544541,39.808819],"type":"Point"}
}