{
  "type": "Feature",
  "properties": {
    "iso:country":"US",
    "sg:address":"30 Fox Hunt Dr",
    "sg:city":"Bear",
    "sg:classifiers":[
        {
            "category":"Shopping",
            "subcategory":"Hobbies, Toys, & Games",
            "type":"Retail Goods"
        }
    ],
    "sg:phone":"+1 302 838 8404",
    "sg:postcode":"19701",
    "sg:province":"DE",
    "sg:tags":[
        "model",
        "supply"
    ],
    "wof:name":"Calling All Scrapbookers",
    "wof:placetype":"venue"
},
  "geometry": {"coordinates":[-75.712671,39.608333],"type":"Point"}
}