{
  "type": "Feature",
  "properties": {
    "addr:full":"620 N Market St Wilmington DE 19801",
    "addr:housenumber":"620",
    "addr:postcode":"19801",
    "addr:street":"N Market St",
    "iso:country":"US",
    "sg:address":"620 N Market St",
    "sg:city":"Wilmington",
    "sg:classifiers":[
        {
            "category":"Restaurant",
            "type":"Food & Drink"
        }
    ],
    "sg:menulink":"http://www.allmenus.com/de/wilmington/156741-kennedy-fried-chicken--pizza/menu/",
    "sg:phone":"+1 302 652 9495",
    "sg:postcode":"19801",
    "sg:province":"DE",
    "sg:tags":[
        "american",
        "pizza"
    ],
    "wof:name":"Kennedy Fried Chicken & Pizza",
    "wof:placetype":"venue"
},
  "geometry": {"coordinates":[-75.550175,39.742059],"type":"Point"}
}