{
  "type": "Feature",
  "properties": {
    "iso:country":"US",
    "sg:address":"29 S Main St",
    "sg:city":"Smyrna",
    "sg:classifiers":[
        {
            "category":"Retail",
            "subcategory":"Funeral Services",
            "type":"Services"
        }
    ],
    "sg:phone":"+1 302 653 8816",
    "sg:postcode":"19977",
    "sg:province":"DE",
    "sg:tags":[
        "director",
        "mortician",
        "supply"
    ],
    "sg:website":"http://www.fariesfuneralhomes.com",
    "wof:name":"Faries Funeral Directors Inc",
    "wof:placetype":"venue"
},
  "geometry": {"coordinates":[-75.605324,39.300121],"type":"Point"}
}