{
  "type": "Feature",
  "properties": {
    "iso:country":"US",
    "sg:address":"100 Naamans Rd",
    "sg:city":"Claymont",
    "sg:classifiers":[
        {
            "category":"Manufacturing",
            "subcategory":"Metals",
            "type":"Manufacturing & Wholesale Goods"
        },
        {
            "category":"Manufacturing",
            "subcategory":"Retail Goods",
            "type":"Manufacturing & Wholesale Goods"
        }
    ],
    "sg:phone":"+1 302 792 5920",
    "sg:postcode":"19703",
    "sg:province":"DE",
    "sg:tags":[
        "product",
        "mfg"
    ],
    "sg:website":"www.aurista.com",
    "wof:name":"Aurista",
    "wof:placetype":"venue"
},
  "geometry": {"coordinates":[-75.443096,39.810894],"type":"Point"}
}