{
  "type": "Feature",
  "properties": {
    "iso:country":"US",
    "sg:address":"100 Rockland Cir",
    "sg:city":"Wilmington",
    "sg:classifiers":[
        {
            "category":"Health Services",
            "subcategory":"Doctor",
            "type":"Services"
        }
    ],
    "sg:phone":"+1 302 654 1765",
    "sg:postcode":"19803",
    "sg:province":"DE",
    "sg:tags":[
        "dentist"
    ],
    "wof:name":"Garrett B Lyons Sr DDS",
    "wof:placetype":"venue"
},
  "geometry": {"coordinates":[-75.54944399999999,39.773275],"type":"Point"}
}