{
  "type": "Feature",
  "properties": {
    "iso:country":"US",
    "sg:address":"12 E Reamer Ave",
    "sg:city":"Wilmington",
    "sg:classifiers":[
        {
            "category":"Social Services",
            "subcategory":"Child Care",
            "type":"Services"
        }
    ],
    "sg:phone":"+1 302 995 6783",
    "sg:postcode":"19804",
    "sg:province":"DE",
    "sg:tags":[
        "day"
    ],
    "wof:name":"Joan Jones Day Care",
    "wof:placetype":"venue"
},
  "geometry": {"coordinates":[-75.586928,39.725546],"type":"Point"}
}