{
  "type": "Feature",
  "properties": {
    "iso:country":"US",
    "sg:address":"1232 N King St",
    "sg:city":"Wilmington",
    "sg:classifiers":[
        {
            "category":"Professional",
            "subcategory":"Lawyer & Legal Services",
            "type":"Services"
        }
    ],
    "sg:phone":"+1 302 652 4550",
    "sg:postcode":"19801",
    "sg:province":"DE",
    "wof:name":"Law Office of Tase Christopher",
    "wof:placetype":"venue"
},
  "geometry": {"coordinates":[-75.54528999999999,39.747494],"type":"Point"}
}