{
  "type": "Feature",
  "properties": {
    "iso:country":"US",
    "sg:address":"3128 New Castle Ave",
    "sg:city":"New Castle",
    "sg:classifiers":[
        {
            "category":"Building & Trades",
            "subcategory":"Construction",
            "type":"Services"
        }
    ],
    "sg:phone":"+1 302 658 4417",
    "sg:postcode":"19720",
    "sg:province":"DE",
    "sg:tags":[
        "heavy",
        "development"
    ],
    "wof:name":"Daisy Construction Company",
    "wof:placetype":"venue"
},
  "geometry": {"coordinates":[-75.54929799999999,39.708527],"type":"Point"}
}