{
  "type": "Feature",
  "properties": {
    "iso:country":"US",
    "sg:address":"110 Christiana Medical Center",
    "sg:city":"Newark",
    "sg:classifiers":[
        {
            "category":"Professional",
            "subcategory":"Lawyer & Legal Services",
            "type":"Services"
        }
    ],
    "sg:phone":"+1 302 836 3900",
    "sg:postcode":"19702",
    "sg:province":"DE",
    "sg:tags":[
        "attorney"
    ],
    "wof:name":"Schmidt Kirifides & Pearson",
    "wof:placetype":"venue"
},
  "geometry": {"coordinates":[-75.659148,39.676977],"type":"Point"}
}