{
  "type": "Feature",
  "properties": {
    "iso:country":"US",
    "sg:address":"130 Rothwell Rd",
    "sg:city":"Wilmington",
    "sg:classifiers":[
        {
            "category":"Organizations",
            "subcategory":"Labor Organization",
            "type":"Services"
        }
    ],
    "sg:phone":"+1 302 994 7672",
    "sg:postcode":"19805",
    "sg:province":"DE",
    "wof:name":"Amalgamated Transit Union Inc",
    "wof:placetype":"venue"
},
  "geometry": {"coordinates":[-75.624172,39.748345],"type":"Point"}
}