{
  "type": "Feature",
  "properties": {
    "iso:country":"US",
    "sg:address":"4430 Halltown Rd",
    "sg:city":"Hartly",
    "sg:classifiers":[
        {
            "category":"Freight",
            "type":"Transportation"
        }
    ],
    "sg:phone":"+1 302 492 3942",
    "sg:postcode":"19953",
    "sg:province":"DE",
    "sg:tags":[
        "trucking"
    ],
    "wof:name":"Patterson Trucking LLC",
    "wof:placetype":"venue"
},
  "geometry": {"coordinates":[-75.683423,39.141574],"type":"Point"}
}