{
  "type": "Feature",
  "properties": {
    "iso:country":"US",
    "sg:address":"1536 Brackenville Rd",
    "sg:city":"Hockessin",
    "sg:classifiers":[
        {
            "category":"Building & Trades",
            "subcategory":"Landscaping Services",
            "type":"Services"
        }
    ],
    "sg:phone":"+1 302 239 5556",
    "sg:postcode":"19707",
    "sg:province":"DE",
    "wof:name":"Gallo Tree Service Ryan",
    "wof:placetype":"venue"
},
  "geometry": {"coordinates":[-75.702507,39.769031],"type":"Point"}
}