{
  "type": "Feature",
  "properties": {
    "iso:country":"US",
    "sg:address":"4804 Mermaid Blvd",
    "sg:city":"Wilmington",
    "sg:classifiers":[
        {
            "category":"Professional",
            "subcategory":"Accounting & Tax Preparation",
            "type":"Services"
        }
    ],
    "sg:phone":"+1 302 239 4763",
    "sg:postcode":"19808",
    "sg:province":"DE",
    "sg:tags":[
        "accountant"
    ],
    "wof:name":"John J Gipprich",
    "wof:placetype":"venue"
},
  "geometry": {"coordinates":[-75.704797,39.736764],"type":"Point"}
}