{
  "type": "Feature",
  "properties": {
    "addr:full":"4805 Limestone Rd Wilmington DE 19808",
    "addr:housenumber":"4805",
    "addr:postcode":"19808",
    "addr:street":"Limestone Rd",
    "iso:country":"US",
    "sg:address":"4805 Limestone Rd",
    "sg:city":"Wilmington",
    "sg:classifiers":[
        {
            "category":"Shopping",
            "subcategory":"Clothing, Apparel, & Fashions",
            "type":"Retail Goods"
        }
    ],
    "sg:phone":"+1 302 239 6110",
    "sg:postcode":"19808",
    "sg:province":"DE",
    "sg:tags":[
        "apparel",
        "women's"
    ],
    "wof:name":"Marilyns Fashions",
    "wof:placetype":"venue"
},
  "geometry": {"coordinates":[-75.69271000000001,39.742184],"type":"Point"}
}