{
  "type": "Feature",
  "properties": {
    "iso:country":"US",
    "sg:address":"49 Deer Run Rd",
    "sg:city":"Townsend",
    "sg:phone":"+1 302 653 9141",
    "sg:postcode":"19734",
    "sg:province":"DE",
    "sg:tags":[
        "farm",
        "grain",
        "cash",
        "soybean"
    ],
    "wof:name":"Carlton Blendt",
    "wof:placetype":"venue"
},
  "geometry": {"coordinates":[-75.616758,39.37798],"type":"Point"}
}