{
  "type": "Feature",
  "properties": {
    "iso:country":"US",
    "sg:address":"4550 New Linden Hill Rd",
    "sg:city":"Wilmington",
    "sg:classifiers":[
        {
            "category":"Professional",
            "subcategory":"Management & Consulting",
            "type":"Services"
        }
    ],
    "sg:phone":"+1 302 993 2766",
    "sg:postcode":"19808",
    "sg:province":"DE",
    "sg:tags":[
        "construction"
    ],
    "wof:name":"Palmetto Management & Engrg",
    "wof:placetype":"venue"
},
  "geometry": {"coordinates":[-75.689616,39.734069],"type":"Point"}
}