{
  "type": "Feature",
  "properties": {
    "iso:country":"US",
    "sg:address":"528 N Franklin St",
    "sg:city":"Wilmington",
    "sg:classifiers":[
        {
            "category":"Food & Beverages",
            "subcategory":"Groceries & Convenience Stores",
            "type":"Retail Goods"
        }
    ],
    "sg:phone":"+1 302 656 3240",
    "sg:postcode":"19805",
    "sg:province":"DE",
    "sg:tags":[
        "grocer"
    ],
    "wof:name":"Min's Market",
    "wof:placetype":"venue"
},
  "geometry": {"coordinates":[-75.563326,39.746588],"type":"Point"}
}