{
  "type": "Feature",
  "properties": {
    "addr:full":"800 Sussex Ave Seaford DE 19973",
    "addr:housenumber":"800",
    "addr:postcode":"19973",
    "addr:street":"Sussex Ave",
    "iso:country":"US",
    "sg:address":"800 Sussex Ave",
    "sg:city":"Seaford",
    "sg:classifiers":[
        {
            "category":"Professional",
            "type":"Services"
        },
        {
            "category":"Organizations",
            "subcategory":"Religious Organization",
            "type":"Services"
        }
    ],
    "sg:phone":"+1 302 628 9270",
    "sg:postcode":"19973",
    "sg:province":"DE",
    "sg:tags":[
        "church"
    ],
    "wof:name":"Miracle Revival Center",
    "wof:placetype":"venue"
},
  "geometry": {"coordinates":[-75.633528,38.645815],"type":"Point"}
}