{
  "type": "Feature",
  "properties": {
    "iso:country":"US",
    "sg:address":"234 S Dupont Hwy",
    "sg:city":"New Castle",
    "sg:classifiers":[
        {
            "category":"Autos & Motor Vehicles",
            "subcategory":"Automobile Sales",
            "type":"Retail Goods"
        }
    ],
    "sg:phone":"+1 302 395 9330",
    "sg:postcode":"19720",
    "sg:province":"DE",
    "sg:tags":[
        "car",
        "used",
        "dealer"
    ],
    "wof:name":"New Castle Motors Inc",
    "wof:placetype":"venue"
},
  "geometry": {"coordinates":[-75.61302499999999,39.657391],"type":"Point"}
}