{
  "type": "Feature",
  "properties": {
    "addr:full":"1504 Bartleson Rd Wilmington DE 19805",
    "addr:housenumber":"1504",
    "addr:postcode":"19805",
    "addr:street":"Bartleson Rd",
    "iso:country":"US",
    "sg:address":"1504 Bartleson Rd",
    "sg:city":"Wilmington",
    "sg:classifiers":[
        {
            "category":"Building & Trades",
            "subcategory":"Equipment Rental",
            "type":"Services"
        }
    ],
    "sg:phone":"+1 302 996 9130",
    "sg:postcode":"19805",
    "sg:province":"DE",
    "wof:name":"Carlson Leasing",
    "wof:placetype":"venue"
},
  "geometry": {"coordinates":[-75.60709900000001,39.747308],"type":"Point"}
}