{
  "type": "Feature",
  "properties": {
    "addr:full":"100 Enterprise Pl Dover DE 19904",
    "addr:housenumber":"100",
    "addr:postcode":"19904",
    "addr:street":"Enterprise Pl",
    "iso:country":"US",
    "sg:address":"100 Enterprise Pl",
    "sg:city":"Dover",
    "sg:classifiers":[
        {
            "category":"Health Services",
            "subcategory":"Clinic",
            "type":"Services"
        }
    ],
    "sg:phone":"+1 302 678 3353",
    "sg:postcode":"19904",
    "sg:province":"DE",
    "sg:tags":[
        "specialty",
        "outpatient"
    ],
    "wof:name":"Easter Seals",
    "wof:placetype":"venue"
},
  "geometry": {"coordinates":[-75.547291,39.152204],"type":"Point"}
}