{
  "type": "Feature",
  "properties": {
    "iso:country":"US",
    "sg:address":"9156 Ocean Hwy",
    "sg:city":"Delmar",
    "sg:classifiers":[
        {
            "category":"Wholesale",
            "subcategory":"Machinery & Supplies",
            "type":"Manufacturing & Wholesale Goods"
        }
    ],
    "sg:phone":"+1 410 749 2106",
    "sg:postcode":"21875",
    "sg:province":"DE",
    "sg:tags":[
        "bearing"
    ],
    "wof:name":"Motion Industries Inc",
    "wof:placetype":"venue"
},
  "geometry": {"coordinates":[-75.56066199999999,38.443885],"type":"Point"}
}