{
  "type": "Feature",
  "properties": {
    "addr:full":"4201 Miller Rd Wilmington DE 19802",
    "addr:housenumber":"4201",
    "addr:postcode":"19802",
    "addr:street":"Miller Rd",
    "iso:country":"US",
    "sg:address":"4201 Miller Rd",
    "sg:city":"Wilmington",
    "sg:classifiers":[
        {
            "category":"Home & Garden",
            "subcategory":"Furniture",
            "type":"Retail Goods"
        }
    ],
    "sg:phone":"+1 302 656 2299",
    "sg:postcode":"19802",
    "sg:province":"DE",
    "wof:name":"Closic's Baby & Teen",
    "wof:placetype":"venue"
},
  "geometry": {"coordinates":[-75.532878,39.769402],"type":"Point"}
}