{
  "type": "Feature",
  "properties": {
    "iso:country":"US",
    "sg:address":"1461 Cedar Lane Rd",
    "sg:city":"Middletown",
    "sg:classifiers":[
        {
            "category":"Building & Trades",
            "subcategory":"Construction",
            "type":"Services"
        }
    ],
    "sg:phone":"+1 302 376 0742",
    "sg:postcode":"19709",
    "sg:province":"DE",
    "sg:tags":[
        "floor",
        "laying",
        "contractor"
    ],
    "wof:name":"Delawres Fnest Hardwood Floors",
    "wof:placetype":"venue"
},
  "geometry": {"coordinates":[-75.691643,39.491108],"type":"Point"}
}