{
  "type": "Feature",
  "properties": {
    "addr:full":"1006 E 28th St Wilmington DE 19802",
    "addr:housenumber":"1006",
    "addr:postcode":"19802",
    "addr:street":"E 28Th St",
    "iso:country":"US",
    "sg:address":"1006 E 28th St",
    "sg:city":"Wilmington",
    "sg:classifiers":[
        {
            "category":"Organizations",
            "subcategory":"Religious Organization",
            "type":"Services"
        }
    ],
    "sg:phone":"+1 302 764 8843",
    "sg:postcode":"19802",
    "sg:province":"DE",
    "sg:tags":[
        "church"
    ],
    "wof:name":"Presbyterian Church Our Savior",
    "wof:placetype":"venue"
},
  "geometry": {"coordinates":[-75.526771,39.75062],"type":"Point"}
}