{
  "type": "Feature",
  "properties": {
    "iso:country":"US",
    "sg:address":"280 Greenwood Rd",
    "sg:city":"Greenwood",
    "sg:classifiers":[
        {
            "category":"Farming",
            "subcategory":"Dairy Farm",
            "type":"Manufacturing & Wholesale Goods"
        }
    ],
    "sg:phone":"+1 302 349 4481",
    "sg:postcode":"19950",
    "sg:province":"DE",
    "wof:name":"Hope Fair Farms Inc",
    "wof:placetype":"venue"
},
  "geometry": {"coordinates":[-75.61654900000001,38.835854],"type":"Point"}
}