{
  "type": "Feature",
  "properties": {
    "iso:country":"US",
    "sg:address":"897 Woodcrest Dr",
    "sg:city":"Dover",
    "sg:classifiers":[
        {
            "category":"Banks & Credit Unions",
            "subcategory":"Financial Services",
            "type":"Services"
        }
    ],
    "sg:phone":"+1 302 734 1923",
    "sg:postcode":"19904",
    "sg:province":"DE",
    "sg:tags":[
        "trust",
        "management"
    ],
    "wof:name":"National Society of Daugh",
    "wof:placetype":"venue"
},
  "geometry": {"coordinates":[-75.54157499999999,39.172119],"type":"Point"}
}