{
  "type": "Feature",
  "properties": {
    "iso:country":"US",
    "sg:address":"619 Greylag Rd",
    "sg:city":"Middletown",
    "sg:classifiers":[
        {
            "category":"Building & Trades",
            "subcategory":"Construction",
            "type":"Services"
        }
    ],
    "sg:phone":"+1 302 378 7540",
    "sg:postcode":"19709",
    "sg:province":"DE",
    "sg:tags":[
        "general",
        "contractor"
    ],
    "wof:name":"Burns & Sons Millworks",
    "wof:placetype":"venue"
},
  "geometry": {"coordinates":[-75.651122,39.494654],"type":"Point"}
}