{
  "type": "Feature",
  "properties": {
    "iso:country":"US",
    "sg:address":"2505 W 6th St",
    "sg:city":"Wilmington",
    "sg:classifiers":[
        {
            "category":"Wholesale",
            "subcategory":"Drugs",
            "type":"Manufacturing & Wholesale Goods"
        }
    ],
    "sg:phone":"+1 302 571 8761",
    "sg:postcode":"19805",
    "sg:province":"DE",
    "sg:tags":[
        "pharmaceutical",
        "medical",
        "product",
        "supply"
    ],
    "wof:name":"Hanna Pharmaceutical Supply Co",
    "wof:placetype":"venue"
},
  "geometry": {"coordinates":[-75.57840299999999,39.753451],"type":"Point"}
}