{
  "type": "Feature",
  "properties": {
    "iso:country":"US",
    "sg:address":"311 Atkins St",
    "sg:city":"Millsboro",
    "sg:classifiers":[
        {
            "category":"Building & Trades",
            "subcategory":"Construction",
            "type":"Services"
        }
    ],
    "sg:phone":"+1 302 934 6063",
    "sg:postcode":"19966",
    "sg:province":"DE",
    "sg:tags":[
        "designer",
        "marine",
        "contractor"
    ],
    "wof:name":"Camelot Marine",
    "wof:placetype":"venue"
},
  "geometry": {"coordinates":[-75.28830499999999,38.591962],"type":"Point"}
}