{
  "type": "Feature",
  "properties": {
    "iso:country":"US",
    "sg:address":"619 New York Ave",
    "sg:city":"Claymont",
    "sg:classifiers":[
        {
            "category":"Professional",
            "subcategory":"Management & Consulting",
            "type":"Services"
        }
    ],
    "sg:phone":"+1 302 798 4859",
    "sg:postcode":"19703",
    "sg:province":"DE",
    "sg:tags":[
        "business"
    ],
    "wof:name":"Corparate Consulting",
    "wof:placetype":"venue"
},
  "geometry": {"coordinates":[-75.473623,39.800657],"type":"Point"}
}