{
  "type": "Feature",
  "properties": {
    "addr:full":"38235 N Spring Hill Rd Delmar DE 19940",
    "addr:housenumber":"38235",
    "addr:postcode":"19940",
    "addr:street":"N Spring Hill Rd",
    "iso:country":"US",
    "sg:address":"38235 N Spring Hill Rd",
    "sg:city":"Delmar",
    "sg:classifiers":[
        {
            "category":"Shopping",
            "subcategory":"Bicycles & Sporting Goods",
            "type":"Retail Goods"
        }
    ],
    "sg:phone":"+1 302 846 3811",
    "sg:postcode":"19940",
    "sg:province":"DE",
    "sg:tags":[
        "saddlery",
        "harness"
    ],
    "wof:name":"Tack Phillips & Gifts",
    "wof:placetype":"venue"
},
  "geometry": {"coordinates":[-75.659779,38.462664],"type":"Point"}
}