{
  "type": "Feature",
  "properties": {
    "iso:country":"US",
    "sg:address":"21064 Camp Rd",
    "sg:city":"Seaford",
    "sg:classifiers":[
        {
            "category":"Building & Trades",
            "subcategory":"Construction",
            "type":"Services"
        }
    ],
    "sg:phone":"+1 302 629 4767",
    "sg:postcode":"19973",
    "sg:province":"DE",
    "sg:tags":[
        "house"
    ],
    "wof:name":"Hollis Construction",
    "wof:placetype":"venue"
},
  "geometry": {"coordinates":[-75.584486,38.691326],"type":"Point"}
}