{
  "type": "Feature",
  "properties": {
    "addr:full":"15 Polly Drummond Hill Rd Newark DE 19711",
    "addr:housenumber":"15",
    "addr:postcode":"19711",
    "addr:street":"Polly Drummond Hill Rd",
    "iso:country":"US",
    "sg:address":"15 Polly Drummond Hill Rd",
    "sg:city":"Newark",
    "sg:classifiers":[
        {
            "category":"Organizations",
            "subcategory":"Religious Organization",
            "type":"Services"
        }
    ],
    "sg:phone":"+1 302 737 2100",
    "sg:postcode":"19711",
    "sg:province":"DE",
    "sg:tags":[
        "church"
    ],
    "sg:website":"www.wccpc.org",
    "wof:name":"White Clay Creek Presbyterian",
    "wof:placetype":"venue"
},
  "geometry": {"coordinates":[-75.70953299999999,39.698158],"type":"Point"}
}