{
  "type": "Feature",
  "properties": {
    "addr:full":"610 Market St Bridgeville DE 19933",
    "addr:housenumber":"610",
    "addr:postcode":"19933",
    "addr:street":"Market St",
    "iso:country":"US",
    "sg:address":"610 Market St",
    "sg:city":"Bridgeville",
    "sg:classifiers":[
        {
            "category":"Restaurant",
            "type":"Food & Drink"
        }
    ],
    "sg:phone":"+1 302 337 3222",
    "sg:postcode":"19933",
    "sg:province":"DE",
    "sg:tags":[
        "delicatessen"
    ],
    "wof:name":"Craft's Deli",
    "wof:placetype":"venue"
},
  "geometry": {"coordinates":[-75.605484,38.742463],"type":"Point"}
}