{
  "type": "Feature",
  "properties": {
    "addr:full":"1201 N Orange St Wilmington DE 19801",
    "addr:housenumber":"1201",
    "addr:postcode":"19801",
    "addr:street":"N Orange St",
    "iso:country":"US",
    "sg:address":"1201 N Orange St",
    "sg:city":"Wilmington",
    "sg:classifiers":[
        {
            "category":"Organizations",
            "subcategory":"Professional Association",
            "type":"Services"
        }
    ],
    "sg:phone":"+1 302 655 7221",
    "sg:postcode":"19801",
    "sg:province":"DE",
    "sg:website":"www.dscc.com",
    "wof:name":"De State Chamber Of Commerce",
    "wof:placetype":"venue"
},
  "geometry": {"coordinates":[-75.547316,39.748684],"type":"Point"}
}