{
  "type": "Feature",
  "properties": {
    "iso:country":"US",
    "sg:address":"105 Ruth Dr",
    "sg:city":"Middletown",
    "sg:classifiers":[
        {
            "category":"Retail",
            "subcategory":"Photofinishing",
            "type":"Services"
        }
    ],
    "sg:phone":"+1 302 378 1927",
    "sg:postcode":"19709",
    "sg:province":"DE",
    "sg:tags":[
        "album",
        "photo",
        "camera",
        "film",
        "developing"
    ],
    "wof:name":"Photo Express",
    "wof:placetype":"venue"
},
  "geometry": {"coordinates":[-75.670463,39.483139],"type":"Point"}
}