{
  "type": "Feature",
  "properties": {
    "iso:country":"US",
    "sg:address":"5 Hawkins Ct",
    "sg:city":"Bear",
    "sg:classifiers":[
        {
            "category":"Building & Trades",
            "subcategory":"Electrical",
            "type":"Services"
        }
    ],
    "sg:phone":"+1 302 838 4008",
    "sg:postcode":"19701",
    "sg:province":"DE",
    "sg:tags":[
        "electrical",
        "contractor"
    ],
    "wof:name":"Apex Electric",
    "wof:placetype":"venue"
},
  "geometry": {"coordinates":[-75.736676,39.592886],"type":"Point"}
}