{
  "type": "Feature",
  "properties": {
    "addr:full":"1941 Limestone Rd Wilmington DE 19808",
    "addr:housenumber":"1941",
    "addr:postcode":"19808",
    "addr:street":"Limestone Rd",
    "iso:country":"US",
    "sg:address":"1941 Limestone Rd",
    "sg:city":"Wilmington",
    "sg:classifiers":[
        {
            "category":"Health Services",
            "subcategory":"Doctor",
            "type":"Services"
        }
    ],
    "sg:phone":"+1 302 999 7898",
    "sg:postcode":"19808",
    "sg:province":"DE",
    "sg:tags":[
        "physician",
        "surgeon"
    ],
    "wof:name":"Clifton H Hunt MD",
    "wof:placetype":"venue"
},
  "geometry": {"coordinates":[-75.653458,39.71897],"type":"Point"}
}