{
  "type": "Feature",
  "properties": {
    "addr:full":"2741 Tanager Dr Wilmington DE 19808",
    "addr:housenumber":"2741",
    "addr:postcode":"19808",
    "addr:street":"Tanager Dr",
    "iso:country":"US",
    "sg:address":"2741 Tanager Dr",
    "sg:city":"Wilmington",
    "sg:classifiers":[
        {
            "category":"Building & Trades",
            "subcategory":"Construction",
            "type":"Services"
        }
    ],
    "sg:phone":"+1 302 996 0129",
    "sg:postcode":"19808",
    "sg:province":"DE",
    "sg:tags":[
        "contractor"
    ],
    "wof:name":"L C I",
    "wof:placetype":"venue"
},
  "geometry": {"coordinates":[-75.62938200000001,39.749729],"type":"Point"}
}