{
  "type": "Feature",
  "properties": {
    "iso:country":"US",
    "sg:address":"38472 Dupont Blvd 1",
    "sg:city":"Selbyville",
    "sg:classifiers":[
        {
            "category":"Banks & Credit Unions",
            "subcategory":"Financial Services",
            "type":"Services"
        }
    ],
    "sg:phone":"+1 302 436 9858",
    "sg:postcode":"19975",
    "sg:province":"DE",
    "sg:tags":[
        "cashing",
        "check"
    ],
    "wof:name":"Fast Cash",
    "wof:placetype":"venue"
},
  "geometry": {"coordinates":[-75.23336,38.454259],"type":"Point"}
}