{
  "type": "Feature",
  "properties": {
    "iso:country":"US",
    "sg:address":"3862 Deep Grass Ln",
    "sg:city":"Houston",
    "sg:classifiers":[
        {
            "category":"Organizations",
            "subcategory":"Religious Organization",
            "type":"Services"
        }
    ],
    "sg:phone":"+1 302 422 0832",
    "sg:postcode":"19954",
    "sg:province":"DE",
    "sg:tags":[
        "church"
    ],
    "wof:name":"Community Pentecostal Church",
    "wof:placetype":"venue"
},
  "geometry": {"coordinates":[-75.51538499999999,38.912588],"type":"Point"}
}