{
  "type": "Feature",
  "properties": {
    "addr:full":"3729 N Dupont Hwy Dover DE 19901",
    "addr:housenumber":"3729",
    "addr:postcode":"19901",
    "addr:street":"N Dupont Hwy",
    "iso:country":"US",
    "sg:address":"3729 N Dupont Hwy",
    "sg:city":"Dover",
    "sg:classifiers":[
        {
            "category":"Retail",
            "subcategory":"Auto Repair",
            "type":"Services"
        }
    ],
    "sg:phone":"+1 302 678 5660",
    "sg:postcode":"19901",
    "sg:province":"DE",
    "sg:tags":[
        "transmission"
    ],
    "wof:name":"AAMCO Transmissions",
    "wof:placetype":"venue"
},
  "geometry": {"coordinates":[-75.562747,39.205123],"type":"Point"}
}