{
  "type": "Feature",
  "properties": {
    "iso:country":"US",
    "sg:address":"1708 W 8th St",
    "sg:city":"Wilmington",
    "sg:classifiers":[
        {
            "category":"Bars & Pubs",
            "type":"Food & Drink"
        }
    ],
    "sg:phone":"+1 302 656 9917",
    "sg:postcode":"19805",
    "sg:province":"DE",
    "sg:tags":[
        "lounge",
        "drinking",
        "cocktail"
    ],
    "wof:name":"Green Gate Cafe",
    "wof:placetype":"venue"
},
  "geometry": {"coordinates":[-75.56797,39.751041],"type":"Point"}
}