{
  "type": "Feature",
  "properties": {
    "addr:full":"6392 Burnite Mill Rd Felton DE 19943",
    "addr:postcode":"6392;19943",
    "addr:street":"Burnite Mill Rd",
    "iso:country":"US",
    "sg:address":"6392 Burnite Mill Rd",
    "sg:city":"Felton",
    "sg:classifiers":[
        {
            "category":"Building & Trades",
            "subcategory":"Construction",
            "type":"Services"
        }
    ],
    "sg:phone":"+1 302 284 9076",
    "sg:postcode":"19943",
    "sg:province":"DE",
    "sg:tags":[
        "house"
    ],
    "wof:name":"J&B Improvements Inc",
    "wof:placetype":"venue"
},
  "geometry": {"coordinates":[-75.63161700000001,39.000829],"type":"Point"}
}