{
  "type": "Feature",
  "properties": {
    "addr:full":"8 Bridle Ln Ocean View DE 19970",
    "addr:housenumber":"8",
    "addr:postcode":"19970",
    "addr:street":"Bridle Ln",
    "iso:country":"US",
    "sg:address":"8 Bridle Ln",
    "sg:city":"Ocean View",
    "sg:classifiers":[
        {
            "category":"Building & Trades",
            "subcategory":"Construction",
            "type":"Services"
        }
    ],
    "sg:phone":"+1 302 541 5371",
    "sg:postcode":"19970",
    "sg:province":"DE",
    "sg:tags":[
        "operation",
        "contractor"
    ],
    "wof:name":"Resort Point Builders",
    "wof:placetype":"venue"
},
  "geometry": {"coordinates":[-75.108784,38.537515],"type":"Point"}
}