{
  "type": "Feature",
  "properties": {
    "iso:country":"US",
    "sg:address":"11 Mill St",
    "sg:city":"Camden Wyoming",
    "sg:classifiers":[
        {
            "category":"Professional",
            "type":"Services"
        }
    ],
    "sg:phone":"+1 302 697 7805",
    "sg:postcode":"19934",
    "sg:province":"DE",
    "wof:name":"Wyoming Milling Co",
    "wof:placetype":"venue"
},
  "geometry": {"coordinates":[-75.55671100000001,39.122267],"type":"Point"}
}