{
  "type": "Feature",
  "properties": {
    "iso:country":"US",
    "sg:address":"1524 E Lebanon Rd",
    "sg:city":"Dover",
    "sg:classifiers":[
        {
            "category":"Building & Trades",
            "subcategory":"Construction",
            "type":"Services"
        }
    ],
    "sg:phone":"+1 302 492 8662",
    "sg:postcode":"19901",
    "sg:province":"DE",
    "sg:tags":[
        "masonry",
        "contractor"
    ],
    "wof:name":"Gingerich Concrete & Masonry",
    "wof:placetype":"venue"
},
  "geometry": {"coordinates":[-75.499956,39.122904],"type":"Point"}
}