{
  "type": "Feature",
  "properties": {
    "iso:country":"US",
    "sg:address":"127 Parkway Dr",
    "sg:city":"Dover",
    "sg:classifiers":[
        {
            "category":"Professional",
            "type":"Services"
        }
    ],
    "sg:phone":"+1 302 678 2786",
    "sg:postcode":"19904",
    "sg:province":"DE",
    "wof:name":"India US Society of Delaw",
    "wof:placetype":"venue"
},
  "geometry": {"coordinates":[-75.582607,39.165619],"type":"Point"}
}