{
  "type": "Feature",
  "properties": {
    "iso:country":"US",
    "sg:address":"17 Salem Village Sq",
    "sg:city":"Newark",
    "sg:classifiers":[
        {
            "category":"Restaurant",
            "type":"Food & Drink"
        }
    ],
    "sg:phone":"+1 302 266 7012",
    "sg:postcode":"19713",
    "sg:province":"DE",
    "sg:tags":[
        "eating"
    ],
    "wof:name":"Ming Buffet",
    "wof:placetype":"venue"
},
  "geometry": {"coordinates":[-75.695515,39.667698],"type":"Point"}
}