{
  "type": "Feature",
  "properties": {
    "addr:full":"910 SE 2nd St Milford DE 19963",
    "addr:housenumber":"910",
    "addr:postcode":"19963",
    "addr:street":"Se 2Nd St",
    "iso:country":"US",
    "sg:address":"910 SE 2nd St",
    "sg:city":"Milford",
    "sg:classifiers":[
        {
            "category":"Professional",
            "subcategory":"Detective & Security Services",
            "type":"Services"
        }
    ],
    "sg:phone":"+1 302 422 5500",
    "sg:postcode":"19963",
    "sg:province":"DE",
    "sg:tags":[
        "guard",
        "patrol"
    ],
    "wof:name":"Travers Organization Inc",
    "wof:placetype":"venue"
},
  "geometry": {"coordinates":[-75.41655299999999,38.909567],"type":"Point"}
}