{
  "type": "Feature",
  "properties": {
    "iso:country":"US",
    "sg:address":"162 Dutton Dr",
    "sg:city":"Newark",
    "sg:classifiers":[
        {
            "category":"Organizations",
            "subcategory":"Religious Organization",
            "type":"Services"
        }
    ],
    "sg:phone":"+1 973 648 0861",
    "sg:postcode":"19720",
    "sg:province":"DE",
    "sg:tags":[
        "church"
    ],
    "wof:name":"Greater Little Rock Missionary",
    "wof:placetype":"venue"
},
  "geometry": {"coordinates":[-75.637998,39.65543],"type":"Point"}
}