{
  "type": "Feature",
  "properties": {
    "iso:country":"US",
    "sg:address":"5 Atlantic Ave",
    "sg:city":"Ocean View",
    "sg:classifiers":[
        {
            "category":"Home & Garden",
            "subcategory":"Carpets & Floor Coverings",
            "type":"Retail Goods"
        }
    ],
    "sg:phone":"+1 302 539 7322",
    "sg:postcode":"19970",
    "sg:province":"DE",
    "sg:tags":[
        "material"
    ],
    "sg:website":"www.morinsfloors.com",
    "wof:name":"Paul Morin Floor & Wall Design",
    "wof:placetype":"venue"
},
  "geometry": {"coordinates":[-75.081221,38.542797],"type":"Point"}
}