{
  "type": "Feature",
  "properties": {
    "addr:full":"326 Ruthar Dr Newark DE 19711",
    "addr:housenumber":"326",
    "addr:postcode":"19711",
    "addr:street":"Ruthar Dr",
    "iso:country":"US",
    "sg:address":"326 Ruthar Dr",
    "sg:city":"Newark",
    "sg:classifiers":[
        {
            "category":"Shopping",
            "subcategory":"Pharmacy",
            "type":"Retail Goods"
        }
    ],
    "sg:phone":"+1 302 366 0335",
    "sg:postcode":"19711",
    "sg:province":"DE",
    "sg:tags":[
        "drug",
        "store"
    ],
    "wof:name":"Happy Harrys Disc DRG Stores",
    "wof:placetype":"venue"
},
  "geometry": {"coordinates":[-75.698851,39.689463],"type":"Point"}
}