{
  "type": "Feature",
  "properties": {
    "addr:full":"136 Lantana Dr Hockessin DE 19707",
    "addr:housenumber":"136",
    "addr:postcode":"19707",
    "addr:street":"Lantana Dr",
    "iso:country":"US",
    "sg:address":"136 Lantana Dr",
    "sg:city":"Hockessin",
    "sg:classifiers":[
        {
            "category":"Restaurant",
            "type":"Food & Drink"
        }
    ],
    "sg:menulink":"http://www.allmenus.com/de/piedmont/107668-five-guys/menu/",
    "sg:phone":"+1 302 239 1250",
    "sg:postcode":"19707",
    "sg:province":"DE",
    "sg:tags":[
        "burger",
        "american",
        "hot",
        "dog"
    ],
    "wof:name":"Five Guys Burgers & Fries",
    "wof:placetype":"venue"
},
  "geometry": {"coordinates":[-75.71111399999999,39.774381],"type":"Point"}
}