{
  "type": "Feature",
  "properties": {
    "iso:country":"US",
    "sg:address":"4 W 5th St",
    "sg:city":"Wilmington",
    "sg:classifiers":[
        {
            "category":"Restaurant",
            "type":"Food & Drink"
        }
    ],
    "sg:phone":"+1 302 661 0100",
    "sg:postcode":"19801",
    "sg:province":"DE",
    "sg:tags":[
        "eating"
    ],
    "wof:name":"4w5 Cafe",
    "wof:placetype":"venue"
},
  "geometry": {"coordinates":[-75.551383,39.741312],"type":"Point"}
}