{
  "type": "Feature",
  "properties": {
    "addr:full":"779 S Dual Hwy Seaford DE 19973",
    "addr:housenumber":"779",
    "addr:postcode":"19973",
    "addr:street":"S Dual Hwy",
    "iso:country":"US",
    "sg:address":"779 S Dual Hwy",
    "sg:city":"Seaford",
    "sg:classifiers":[
        {
            "category":"Shopping",
            "subcategory":"Jewelry",
            "type":"Retail Goods"
        }
    ],
    "sg:phone":"+1 302 628 1124",
    "sg:postcode":"19973",
    "sg:province":"DE",
    "sg:tags":[
        "jeweler"
    ],
    "wof:name":"Friedman's Jewelers",
    "wof:placetype":"venue"
},
  "geometry": {"coordinates":[-75.592788,38.634946],"type":"Point"}
}