{
  "type": "Feature",
  "properties": {
    "iso:country":"US",
    "sg:address":"407 New London Rd",
    "sg:city":"Newark",
    "sg:classifiers":[
        {
            "category":"Shopping",
            "subcategory":"Computers & Home Electronics",
            "type":"Retail Goods"
        },
        {
            "category":"Cinema",
            "subcategory":"Movie Rental",
            "type":"Entertainment"
        }
    ],
    "sg:phone":"+1 302 266 6666",
    "sg:postcode":"19711",
    "sg:province":"DE",
    "sg:tags":[
        "leasing",
        "video",
        "disc",
        "tape"
    ],
    "wof:name":"California Video 1",
    "wof:placetype":"venue"
},
  "geometry": {"coordinates":[-75.765304,39.696342],"type":"Point"}
}