{
  "type": "Feature",
  "properties": {
    "addr:full":"30 Cragmere Rd Wilmington DE 19809",
    "addr:housenumber":"30",
    "addr:postcode":"19809",
    "addr:street":"Cragmere Rd",
    "iso:country":"US",
    "sg:address":"30 Cragmere Rd",
    "sg:city":"Wilmington",
    "sg:classifiers":[
        {
            "category":"Professional",
            "subcategory":"Research",
            "type":"Services"
        }
    ],
    "sg:phone":"+1 302 764 1363",
    "sg:postcode":"19809",
    "sg:province":"DE",
    "sg:tags":[
        "organization",
        "noncommercial"
    ],
    "wof:name":"National Coalition Buildi",
    "wof:placetype":"venue"
},
  "geometry": {"coordinates":[-75.491133,39.768983],"type":"Point"}
}