{
  "type": "Feature",
  "properties": {
    "iso:country":"US",
    "sg:address":"3705 Concord Pike",
    "sg:city":"Wilmington",
    "sg:classifiers":[
        {
            "category":"Health Services",
            "subcategory":"Clinic",
            "type":"Services"
        },
        {
            "category":"Professional",
            "subcategory":"Employment Agencies",
            "type":"Services"
        }
    ],
    "sg:phone":"+1 302 478 5011",
    "sg:postcode":"19803",
    "sg:province":"DE",
    "sg:tags":[
        "home",
        "care"
    ],
    "wof:name":"Perfect Care Nurses Inc",
    "wof:placetype":"venue"
},
  "geometry": {"coordinates":[-75.5493,39.806488],"type":"Point"}
}