{
  "type": "Feature",
  "properties": {
    "addr:full":"111 E 41st St Wilmington DE 19802",
    "addr:housenumber":"111",
    "addr:postcode":"19802",
    "addr:street":"E 41St St",
    "iso:country":"US",
    "sg:address":"111 E 41st St",
    "sg:city":"Wilmington",
    "sg:classifiers":[
        {
            "category":"Professional",
            "type":"Services"
        }
    ],
    "sg:phone":"+1 302 764 5179",
    "sg:postcode":"19802",
    "sg:province":"DE",
    "wof:name":"Howard E Spell",
    "wof:placetype":"venue"
},
  "geometry": {"coordinates":[-75.520915,39.759135],"type":"Point"}
}