{
  "type": "Feature",
  "properties": {
    "iso:country":"US",
    "sg:address":"612 Mulberry St",
    "sg:city":"Milton",
    "sg:classifiers":[
        {
            "category":"Health Services",
            "subcategory":"Health Practitioner",
            "type":"Services"
        }
    ],
    "sg:phone":"+1 302 684 2829",
    "sg:postcode":"19968",
    "sg:province":"DE",
    "sg:tags":[
        "therapist",
        "physical"
    ],
    "wof:name":"Tidewater Physical Therapy",
    "wof:placetype":"venue"
},
  "geometry": {"coordinates":[-75.318787,38.787555],"type":"Point"}
}