{
  "type": "Feature",
  "properties": {
    "iso:country":"US",
    "sg:address":"1301 N Dupont Hwy",
    "sg:city":"New Castle",
    "sg:classifiers":[
        {
            "category":"Food & Beverages",
            "subcategory":"Groceries & Convenience Stores",
            "type":"Retail Goods"
        }
    ],
    "sg:phone":"+1 302 328 9974",
    "sg:postcode":"19720",
    "sg:province":"DE",
    "sg:tags":[
        "grocer"
    ],
    "wof:name":"Save-A-Lot",
    "wof:placetype":"venue"
},
  "geometry": {"coordinates":[-75.582238,39.689688],"type":"Point"}
}