{
  "type": "Feature",
  "properties": {
    "addr:full":"6552 Cedar Neck Rd Milford DE 19963",
    "addr:housenumber":"6552",
    "addr:postcode":"19963",
    "addr:street":"Cedar Neck Rd",
    "iso:country":"US",
    "sg:address":"6552 Cedar Neck Rd",
    "sg:city":"Milford",
    "sg:classifiers":[
        {
            "category":"Building & Trades",
            "subcategory":"Construction",
            "type":"Services"
        }
    ],
    "sg:phone":"+1 302 422 0162",
    "sg:postcode":"19963",
    "sg:province":"DE",
    "sg:tags":[
        "house"
    ],
    "wof:name":"Triple X Construction",
    "wof:placetype":"venue"
},
  "geometry": {"coordinates":[-75.388076,38.891199],"type":"Point"}
}