{
  "type": "Feature",
  "properties": {
    "addr:full":"31 N Ocean Dr Bethany Beach DE 19930",
    "addr:housenumber":"31",
    "addr:postcode":"19930",
    "addr:street":"N Ocean Dr",
    "iso:country":"US",
    "sg:address":"31 N Ocean Dr",
    "sg:city":"Bethany Beach",
    "sg:classifiers":[
        {
            "category":"Real Estate",
            "subcategory":"Developer",
            "type":"Services"
        }
    ],
    "sg:phone":"+1 302 537 7917",
    "sg:postcode":"19930",
    "sg:province":"DE",
    "sg:tags":[
        "development"
    ],
    "wof:name":"L V M LP",
    "wof:placetype":"venue"
},
  "geometry": {"coordinates":[-75.053462,38.517177],"type":"Point"}
}