{
  "type": "Feature",
  "properties": {
    "iso:country":"US",
    "sg:address":"5801 Kennett Pike",
    "sg:city":"Wilmington",
    "sg:classifiers":[
        {
            "category":"Professional",
            "subcategory":"Business Services",
            "type":"Services"
        }
    ],
    "sg:phone":"+1 302 655 3410",
    "sg:postcode":"19807",
    "sg:province":"DE",
    "wof:name":"William Jones",
    "wof:placetype":"venue"
},
  "geometry": {"coordinates":[-75.61788799999999,39.823432],"type":"Point"}
}