{
  "type": "Feature",
  "properties": {
    "iso:country":"US",
    "sg:address":"2410 Twist Ln",
    "sg:city":"Wilmington",
    "sg:classifiers":[
        {
            "category":"Building & Trades",
            "subcategory":"Electrical",
            "type":"Services"
        }
    ],
    "sg:phone":"+1 302 651 0170",
    "sg:postcode":"19808",
    "sg:province":"DE",
    "sg:tags":[
        "electrical",
        "contractor"
    ],
    "wof:name":"Jove Electric",
    "wof:placetype":"venue"
},
  "geometry": {"coordinates":[-75.661626,39.729574],"type":"Point"}
}