{
  "type": "Feature",
  "properties": {
    "iso:country":"US",
    "sg:address":"1195 Corner Ketch Rd",
    "sg:city":"Newark",
    "sg:classifiers":[
        {
            "category":"Social Services",
            "subcategory":"Child Care",
            "type":"Services"
        }
    ],
    "sg:phone":"+1 302 235 1920",
    "sg:postcode":"19711",
    "sg:province":"DE",
    "sg:tags":[
        "nursery",
        "day"
    ],
    "wof:name":"Day Ken Fax",
    "wof:placetype":"venue"
},
  "geometry": {"coordinates":[-75.75514699999999,39.749252],"type":"Point"}
}