{
  "type": "Feature",
  "properties": {
    "iso:country":"US",
    "sg:address":"2601 Annand Dr",
    "sg:city":"Wilmington",
    "sg:classifiers":[
        {
            "category":"Wholesale",
            "subcategory":"Non-durable Goods",
            "type":"Manufacturing & Wholesale Goods"
        }
    ],
    "sg:phone":"+1 302 995 6887",
    "sg:postcode":"19808",
    "sg:province":"DE",
    "wof:name":"Lf Corporation",
    "wof:placetype":"venue"
},
  "geometry": {"coordinates":[-75.675416,39.715683],"type":"Point"}
}