{
  "type": "Feature",
  "properties": {
    "addr:full":"3700 Miller Rd Wilmington DE 19802",
    "addr:housenumber":"3700",
    "addr:postcode":"19802",
    "addr:street":"Miller Rd",
    "iso:country":"US",
    "sg:address":"3700 Miller Rd",
    "sg:city":"Wilmington",
    "sg:classifiers":[
        {
            "category":"Autos & Motor Vehicles",
            "subcategory":"Automobile Sales",
            "type":"Retail Goods"
        }
    ],
    "sg:phone":"+1 302 761 4300",
    "sg:postcode":"19802",
    "sg:province":"DE",
    "sg:tags":[
        "used"
    ],
    "wof:name":"Brandywine Motorcars",
    "wof:placetype":"venue"
},
  "geometry": {"coordinates":[-75.53314,39.76908],"type":"Point"}
}