{
  "type": "Feature",
  "properties": {
    "iso:country":"US",
    "sg:address":"250 Old Baltimore Pike",
    "sg:city":"Newark",
    "sg:classifiers":[
        {
            "category":"Wholesale",
            "subcategory":"Hardware",
            "type":"Manufacturing & Wholesale Goods"
        }
    ],
    "sg:phone":"+1 302 738 0228",
    "sg:postcode":"19702",
    "sg:province":"DE",
    "wof:name":"Jack Bailey",
    "wof:placetype":"venue"
},
  "geometry": {"coordinates":[-75.676196,39.656252],"type":"Point"}
}