{
  "type": "Feature",
  "properties": {
    "iso:country":"US",
    "sg:address":"200 Lake Dr",
    "sg:city":"Newark",
    "sg:classifiers":[
        {
            "category":"Manufacturing",
            "subcategory":"Tools & Machinery",
            "type":"Manufacturing & Wholesale Goods"
        }
    ],
    "sg:phone":"+1 302 731 1700",
    "sg:postcode":"19702",
    "sg:province":"DE",
    "sg:tags":[
        "paper",
        "mill",
        "industrial",
        "general",
        "mfg"
    ],
    "sg:website":"www.gravertechnologies.com",
    "wof:name":"Graver Technologies Inc",
    "wof:placetype":"venue"
},
  "geometry": {"coordinates":[-75.752971,39.616596],"type":"Point"}
}