{
  "type": "Feature",
  "properties": {
    "iso:country":"US",
    "sg:address":"3213 Kirkwood Hwy",
    "sg:city":"Wilmington",
    "sg:classifiers":[
        {
            "category":"Retail",
            "subcategory":"Car Wash",
            "type":"Services"
        }
    ],
    "sg:phone":"+1 302 994 7266",
    "sg:postcode":"19808",
    "sg:province":"DE",
    "sg:tags":[
        "carwash"
    ],
    "wof:name":"Greenbank Car Wash",
    "wof:placetype":"venue"
},
  "geometry": {"coordinates":[-75.62312900000001,39.737583],"type":"Point"}
}