{
  "type": "Feature",
  "properties": {
    "iso:country":"US",
    "sg:address":"1859 Slaughter Station Rd",
    "sg:city":"Hartly",
    "sg:classifiers":[
        {
            "category":"Professional",
            "subcategory":"Engineering",
            "type":"Services"
        }
    ],
    "sg:phone":"+1 302 492 1172",
    "sg:postcode":"19953",
    "sg:province":"DE",
    "wof:name":"Phillip Deitrich",
    "wof:placetype":"venue"
},
  "geometry": {"coordinates":[-75.715558,39.157933],"type":"Point"}
}