{
  "type": "Feature",
  "properties": {
    "iso:country":"US",
    "sg:address":"1915 Lancaster Ave",
    "sg:city":"Wilmington",
    "sg:classifiers":[
        {
            "category":"Professional",
            "subcategory":"Art Services",
            "type":"Services"
        }
    ],
    "sg:phone":"+1 302 654 1219",
    "sg:postcode":"19805",
    "sg:province":"DE",
    "sg:tags":[
        "photography",
        "commercial"
    ],
    "wof:name":"Reynolds J Studio-World Class",
    "wof:placetype":"venue"
},
  "geometry": {"coordinates":[-75.57447500000001,39.746864],"type":"Point"}
}