{
  "type": "Feature",
  "properties": {
    "iso:country":"US",
    "sg:address":"140 W Loockerman St",
    "sg:city":"Dover",
    "sg:classifiers":[
        {
            "category":"Shopping",
            "subcategory":"Shoes",
            "type":"Retail Goods"
        }
    ],
    "sg:phone":"+1 302 730 1773",
    "sg:postcode":"19904",
    "sg:province":"DE",
    "wof:name":"Bens Mens and Shoe Store",
    "wof:placetype":"venue"
},
  "geometry": {"coordinates":[-75.52614,39.157704],"type":"Point"}
}