{
  "type": "Feature",
  "properties": {
    "addr:full":"601 Clayton St Dagsboro DE 19939",
    "addr:housenumber":"601",
    "addr:postcode":"19939",
    "addr:street":"Clayton St",
    "iso:country":"US",
    "sg:address":"601 Clayton St",
    "sg:city":"Dagsboro",
    "sg:classifiers":[
        {
            "category":"Utilities",
            "subcategory":"Cable",
            "type":"Services"
        }
    ],
    "sg:phone":"+1 302 732 6600",
    "sg:postcode":"19939",
    "sg:province":"DE",
    "sg:tags":[
        "television"
    ],
    "wof:name":"Mediacom",
    "wof:placetype":"venue"
},
  "geometry": {"coordinates":[-75.25684200000001,38.543],"type":"Point"}
}