{
  "type": "Feature",
  "properties": {
    "addr:full":"1406 Forrest Ave Dover DE 19904",
    "addr:housenumber":"1406",
    "addr:postcode":"19904",
    "addr:street":"Forrest Ave",
    "iso:country":"US",
    "sg:address":"1406 Forrest Ave",
    "sg:city":"Dover",
    "sg:classifiers":[
        {
            "category":"Ice Cream",
            "type":"Food & Drink"
        }
    ],
    "sg:phone":"+1 302 730 0795",
    "sg:postcode":"19904",
    "sg:province":"DE",
    "sg:tags":[
        "frozen",
        "yogurt"
    ],
    "sg:website":"www.dairyqueen.com",
    "wof:name":"Dairy Queen",
    "wof:placetype":"venue"
},
  "geometry": {"coordinates":[-75.552803,39.158901],"type":"Point"}
}