{
  "type": "Feature",
  "properties": {
    "addr:full":"320 W Dupont Hwy Millsboro DE 19966",
    "addr:housenumber":"320",
    "addr:postcode":"19966",
    "addr:street":"W Dupont Hwy",
    "iso:country":"US",
    "sg:address":"320 W Dupont Hwy",
    "sg:city":"Millsboro",
    "sg:classifiers":[
        {
            "category":"Building & Trades",
            "subcategory":"Construction",
            "type":"Services"
        }
    ],
    "sg:phone":"+1 302 297 3600",
    "sg:postcode":"19966",
    "sg:province":"DE",
    "sg:tags":[
        "home",
        "builder"
    ],
    "wof:name":"Ryan Homes Inc",
    "wof:placetype":"venue"
},
  "geometry": {"coordinates":[-75.301952,38.589186],"type":"Point"}
}