{
  "type": "Feature",
  "properties": {
    "iso:country":"US",
    "sg:address":"636 Beechwood Ave",
    "sg:city":"Milford",
    "sg:classifiers":[
        {
            "category":"Arts & Performance",
            "subcategory":"Theater",
            "type":"Entertainment"
        }
    ],
    "sg:phone":"+1 302 430 0799",
    "sg:postcode":"19963",
    "sg:province":"DE",
    "sg:tags":[
        "group"
    ],
    "wof:name":"Martin KAThie& The Hot Rods",
    "wof:placetype":"venue"
},
  "geometry": {"coordinates":[-75.418519,38.90313],"type":"Point"}
}