{
  "type": "Feature",
  "properties": {
    "iso:country":"US",
    "sg:address":"317 Rehoboth Ave",
    "sg:city":"Rehoboth Beach",
    "sg:classifiers":[
        {
            "category":"Real Estate",
            "subcategory":"Real Estate Agent",
            "type":"Services"
        }
    ],
    "sg:phone":"+1 302 227 5030",
    "sg:postcode":"19971",
    "sg:province":"DE",
    "wof:name":"Remax Realtor Roger Smith",
    "wof:placetype":"venue"
},
  "geometry": {"coordinates":[-75.086519,38.715714],"type":"Point"}
}