{
  "type": "Feature",
  "properties": {
    "iso:country":"US",
    "sg:address":"8 Chippenham Dr",
    "sg:city":"Newark",
    "sg:classifiers":[
        {
            "category":"Professional",
            "subcategory":"Computer Services",
            "type":"Services"
        }
    ],
    "sg:phone":"+1 302 454 6401",
    "sg:postcode":"19711",
    "sg:province":"DE",
    "sg:tags":[
        "consultant",
        "designer"
    ],
    "sg:website":"www.blue-chip-computing.com",
    "wof:name":"Blue Chip Computing",
    "wof:placetype":"venue"
},
  "geometry": {"coordinates":[-75.78752900000001,39.705946],"type":"Point"}
}