{
  "type": "Feature",
  "properties": {
    "iso:country":"US",
    "sg:address":"59 Raven Turn",
    "sg:city":"Newark",
    "sg:classifiers":[
        {
            "category":"Health Services",
            "subcategory":"Chiropractor",
            "type":"Services"
        }
    ],
    "sg:phone":"+1 302 709 0182",
    "sg:postcode":"19702",
    "sg:province":"DE",
    "wof:name":"Craigg Chiropractic",
    "wof:placetype":"venue"
},
  "geometry": {"coordinates":[-75.68961400000001,39.625043],"type":"Point"}
}