{
  "type": "Feature",
  "properties": {
    "addr:full":"1713 Saint Mihiel Ave Wilmington DE 19804",
    "addr:housenumber":"1713",
    "addr:postcode":"19804",
    "addr:street":"Saint Mihiel Ave",
    "iso:country":"US",
    "sg:address":"1713 Saint Mihiel Ave",
    "sg:city":"Wilmington",
    "sg:classifiers":[
        {
            "category":"Professional",
            "type":"Services"
        }
    ],
    "sg:phone":"+1 302 996 9498",
    "sg:postcode":"19804",
    "sg:province":"DE",
    "wof:name":"Fly Away Decoy Inc",
    "wof:placetype":"venue"
},
  "geometry": {"coordinates":[-75.64722999999999,39.714985],"type":"Point"}
}