{
  "type": "Feature",
  "properties": {
    "addr:full":"9 Adelaide Ct Newark DE 19713",
    "addr:housenumber":"9",
    "addr:postcode":"19713",
    "addr:street":"Adelaide Ct",
    "iso:country":"US",
    "sg:address":"9 Adelaide Ct",
    "sg:city":"Newark",
    "sg:classifiers":[
        {
            "category":"Professional",
            "subcategory":"Engineering",
            "type":"Services"
        }
    ],
    "sg:phone":"+1 302 354 5571",
    "sg:postcode":"19713",
    "sg:province":"DE",
    "wof:name":"Case Engineering L L C",
    "wof:placetype":"venue"
},
  "geometry": {"coordinates":[-75.768451,39.632706],"type":"Point"}
}