{
  "type": "Feature",
  "properties": {
    "iso:country":"US",
    "sg:address":"37 Pierson Dr",
    "sg:city":"Hockessin",
    "sg:classifiers":[
        {
            "category":"Professional",
            "type":"Services"
        }
    ],
    "sg:phone":"+1 302 234 2275",
    "sg:postcode":"19707",
    "sg:province":"DE",
    "sg:tags":[
        "writer"
    ],
    "wof:name":"Wordwright Inc",
    "wof:placetype":"venue"
},
  "geometry": {"coordinates":[-75.716042,39.790051],"type":"Point"}
}