{
  "type": "Feature",
  "properties": {
    "addr:full":"2601 Annand Dr Wilmington DE 19808",
    "addr:housenumber":"2601",
    "addr:postcode":"19808",
    "addr:street":"Annand Dr",
    "iso:country":"US",
    "sg:address":"2601 Annand Dr",
    "sg:city":"Wilmington",
    "sg:classifiers":[
        {
            "category":"Health Services",
            "subcategory":"Doctor",
            "type":"Services"
        }
    ],
    "sg:phone":"+1 302 998 3334",
    "sg:postcode":"19808",
    "sg:province":"DE",
    "sg:tags":[
        "physician",
        "surgeon"
    ],
    "wof:name":"Manuel Amini MD",
    "wof:placetype":"venue"
},
  "geometry": {"coordinates":[-75.675416,39.715683],"type":"Point"}
}