{
  "type": "Feature",
  "properties": {
    "iso:country":"US",
    "sg:address":"1415 Foulk Rd",
    "sg:city":"Wilmington",
    "sg:classifiers":[
        {
            "category":"Health Services",
            "subcategory":"Dentist",
            "type":"Services"
        }
    ],
    "sg:phone":"+1 302 477 4900",
    "sg:postcode":"19803",
    "sg:province":"DE",
    "sg:website":"www.delawaresmiles.com",
    "wof:name":"Carroccia Richard J DMD",
    "wof:placetype":"venue"
},
  "geometry": {"coordinates":[-75.5215,39.801498],"type":"Point"}
}