{
  "type": "Feature",
  "properties": {
    "iso:country":"US",
    "sg:address":"405 Marsh Ln",
    "sg:city":"Wilmington",
    "sg:classifiers":[
        {
            "category":"Insurance",
            "subcategory":"Insurance Agent",
            "type":"Services"
        }
    ],
    "sg:phone":"+1 302 761 3000",
    "sg:postcode":"19804",
    "sg:province":"DE",
    "wof:name":"AIG",
    "wof:placetype":"venue"
},
  "geometry": {"coordinates":[-75.59416,39.712454],"type":"Point"}
}