{
  "type": "Feature",
  "properties": {
    "addr:full":"1 Sundew Rd Newark DE 19711",
    "addr:housenumber":"1",
    "addr:postcode":"19711",
    "addr:street":"Sundew Rd",
    "iso:country":"US",
    "sg:address":"1 Sundew Rd",
    "sg:city":"Newark",
    "sg:classifiers":[
        {
            "category":"Professional",
            "subcategory":"Management & Consulting",
            "type":"Services"
        }
    ],
    "sg:phone":"+1 302 622 4316",
    "sg:postcode":"19711",
    "sg:province":"DE",
    "sg:tags":[
        "development",
        "economic"
    ],
    "wof:name":"Dx-Ceeds Inc",
    "wof:placetype":"venue"
},
  "geometry": {"coordinates":[-75.685935,39.710401],"type":"Point"}
}