{
  "type": "Feature",
  "properties": {
    "iso:country":"US",
    "sg:address":"204 N Maryland Ave",
    "sg:city":"Wilmington",
    "sg:classifiers":[
        {
            "category":"Restaurant",
            "type":"Food & Drink"
        }
    ],
    "sg:phone":"+1 302 777 0900",
    "sg:postcode":"19804",
    "sg:province":"DE",
    "wof:name":"Mom's Pizza",
    "wof:placetype":"venue"
},
  "geometry": {"coordinates":[-75.584456,39.72951],"type":"Point"}
}