{
  "type": "Feature",
  "properties": {
    "iso:country":"US",
    "sg:address":"1233 N Dupont Hwy",
    "sg:city":"Dover",
    "sg:classifiers":[
        {
            "category":"Shopping",
            "subcategory":"Mobile Phones",
            "type":"Retail Goods"
        }
    ],
    "sg:phone":"+1 302 735 7912",
    "sg:postcode":"19901",
    "sg:province":"DE",
    "wof:name":"Hytech Wireless",
    "wof:placetype":"venue"
},
  "geometry": {"coordinates":[-75.539891,39.189035],"type":"Point"}
}