{
  "type": "Feature",
  "properties": {
    "iso:country":"US",
    "sg:address":"39 S Governors Ave",
    "sg:city":"Dover",
    "sg:classifiers":[
        {
            "category":"Local Transit",
            "type":"Transportation"
        }
    ],
    "sg:phone":"+1 302 677 4700",
    "sg:postcode":"19904",
    "sg:province":"DE",
    "sg:tags":[
        "ambulance"
    ],
    "wof:name":"Ambulance Service",
    "wof:placetype":"venue"
},
  "geometry": {"coordinates":[-75.527967,39.160469],"type":"Point"}
}