{
  "type": "Feature",
  "properties": {
    "iso:country":"US",
    "sg:address":"201 Delaware Ave",
    "sg:city":"Wilmington",
    "sg:classifiers":[
        {
            "category":"Building & Trades",
            "subcategory":"Construction",
            "type":"Services"
        }
    ],
    "sg:phone":"+1 302 995 6676",
    "sg:postcode":"19804",
    "sg:province":"DE",
    "sg:tags":[
        "house"
    ],
    "wof:name":"Free Style Builders Inc",
    "wof:placetype":"venue"
},
  "geometry": {"coordinates":[-75.61955399999999,39.716184],"type":"Point"}
}