{
  "type": "Feature",
  "properties": {
    "addr:full":"54 E Stoney Run Selbyville DE 19975",
    "addr:housenumber":"54",
    "addr:postcode":"19975",
    "addr:street":"E Stoney Run",
    "iso:country":"US",
    "sg:address":"54 E Stoney Run",
    "sg:city":"Selbyville",
    "sg:classifiers":[
        {
            "category":"Building & Trades",
            "subcategory":"Construction",
            "type":"Services"
        }
    ],
    "sg:phone":"+1 302 436 4113",
    "sg:postcode":"19975",
    "sg:province":"DE",
    "sg:tags":[
        "house"
    ],
    "wof:name":"Herbert B Kennell",
    "wof:placetype":"venue"
},
  "geometry": {"coordinates":[-75.107106,38.471464],"type":"Point"}
}