{
  "type": "Feature",
  "properties": {
    "iso:country":"US",
    "sg:address":"99 Naamans Rd",
    "sg:city":"Claymont",
    "sg:classifiers":[
        {
            "category":"Wholesale",
            "subcategory":"Electrical",
            "type":"Manufacturing & Wholesale Goods"
        }
    ],
    "sg:phone":"+1 302 798 2700",
    "sg:postcode":"19703",
    "sg:province":"DE",
    "sg:tags":[
        "equipment",
        "electric",
        "supply"
    ],
    "wof:name":"Tecot Electric Supply Co Inc",
    "wof:placetype":"venue"
},
  "geometry": {"coordinates":[-75.442121,39.809893],"type":"Point"}
}