{
  "type": "Feature",
  "properties": {
    "addr:full":"1516 Philadelphia Pike Wilmington DE 19809",
    "addr:housenumber":"1516",
    "addr:postcode":"19809",
    "addr:street":"Philadelphia Pike",
    "iso:country":"US",
    "sg:address":"1516 Philadelphia Pike",
    "sg:city":"Wilmington",
    "sg:classifiers":[
        {
            "category":"Retail",
            "subcategory":"Auto Repair",
            "type":"Services"
        }
    ],
    "sg:phone":"+1 302 792 1500",
    "sg:postcode":"19809",
    "sg:province":"DE",
    "sg:tags":[
        "garage",
        "towing"
    ],
    "wof:name":"Holly Oak Service Center",
    "wof:placetype":"venue"
},
  "geometry": {"coordinates":[-75.477929,39.784903],"type":"Point"}
}