{
  "type": "Feature",
  "properties": {
    "iso:country":"US",
    "sg:address":"2158 Lighthouse Rd",
    "sg:city":"Smyrna",
    "sg:classifiers":[
        {
            "category":"Farming",
            "subcategory":"Fish & Marine Products",
            "type":"Manufacturing & Wholesale Goods"
        }
    ],
    "sg:phone":"+1 302 653 8567",
    "sg:postcode":"19977",
    "sg:province":"DE",
    "sg:tags":[
        "preserves",
        "fishing",
        "hunting"
    ],
    "wof:name":"M & M Hunting Lodge",
    "wof:placetype":"venue"
},
  "geometry": {"coordinates":[-75.532945,39.323586],"type":"Point"}
}