{
  "type": "Feature",
  "properties": {
    "iso:country":"US",
    "sg:address":"2901 Green St",
    "sg:city":"Claymont",
    "sg:classifiers":[
        {
            "category":"Social Services",
            "subcategory":"Adult Care",
            "type":"Services"
        }
    ],
    "sg:phone":"+1 302 798 0601",
    "sg:postcode":"19703",
    "sg:province":"DE",
    "sg:tags":[
        "home",
        "for",
        "child"
    ],
    "wof:name":"Catholic Charity Childrens Hm",
    "wof:placetype":"venue"
},
  "geometry": {"coordinates":[-75.468535,39.798873],"type":"Point"}
}