{
  "type": "Feature",
  "properties": {
    "iso:country":"US",
    "sg:address":"421 Roseanna Dr",
    "sg:city":"Wilmington",
    "sg:classifiers":[
        {
            "category":"Building & Trades",
            "subcategory":"Construction",
            "type":"Services"
        }
    ],
    "sg:phone":"+1 302 477 0777",
    "sg:postcode":"19803",
    "sg:province":"DE",
    "sg:tags":[
        "general",
        "contractor"
    ],
    "wof:name":"G W Home Improvements",
    "wof:placetype":"venue"
},
  "geometry": {"coordinates":[-75.541381,39.806595],"type":"Point"}
}