{
  "type": "Feature",
  "properties": {
    "iso:country":"US",
    "sg:address":"410 Fulton St",
    "sg:city":"Dover",
    "sg:classifiers":[
        {
            "category":"Organizations",
            "subcategory":"Religious Organization",
            "type":"Services"
        }
    ],
    "sg:phone":"+1 302 736 6554",
    "sg:postcode":"19904",
    "sg:province":"DE",
    "sg:tags":[
        "church"
    ],
    "wof:name":"Calvary Baptist Church",
    "wof:placetype":"venue"
},
  "geometry": {"coordinates":[-75.53137,39.161775],"type":"Point"}
}