{
  "type": "Feature",
  "properties": {
    "addr:full":"107 W Cobblefield Ct Newark DE 19713",
    "addr:housenumber":"107",
    "addr:postcode":"19713",
    "addr:street":"W Cobblefield Ct",
    "iso:country":"US",
    "sg:address":"107 W Cobblefield Ct",
    "sg:city":"Newark",
    "sg:classifiers":[
        {
            "category":"Professional",
            "subcategory":"Management & Consulting",
            "type":"Services"
        }
    ],
    "sg:phone":"+1 302 738 8878",
    "sg:postcode":"19713",
    "sg:province":"DE",
    "sg:tags":[
        "development"
    ],
    "wof:name":"Dynamic Visions",
    "wof:placetype":"venue"
},
  "geometry": {"coordinates":[-75.76054600000001,39.650698],"type":"Point"}
}