{
  "type": "Feature",
  "properties": {
    "iso:country":"US",
    "sg:address":"211 Delaware St",
    "sg:city":"New Castle",
    "sg:classifiers":[
        {
            "category":"Shopping",
            "subcategory":"Crafts & Fabrics",
            "type":"Retail Goods"
        }
    ],
    "sg:phone":"+1 302 328 7888",
    "sg:postcode":"19720",
    "sg:province":"DE",
    "sg:tags":[
        "sewing"
    ],
    "wof:name":"Stitches That Count",
    "wof:placetype":"venue"
},
  "geometry": {"coordinates":[-75.563489,39.659423],"type":"Point"}
}