{
  "type": "Feature",
  "properties": {
    "iso:country":"US",
    "sg:address":"221 Laurel Rd",
    "sg:city":"Millsboro",
    "sg:classifiers":[
        {
            "category":"Social Services",
            "subcategory":"Child Care",
            "type":"Services"
        }
    ],
    "sg:phone":"+1 302 934 7594",
    "sg:postcode":"19966",
    "sg:province":"DE",
    "sg:tags":[
        "day"
    ],
    "wof:name":"Irelan Beverly Day Care",
    "wof:placetype":"venue"
},
  "geometry": {"coordinates":[-75.299504,38.584551],"type":"Point"}
}