{
  "type": "Feature",
  "properties": {
    "addr:full":"336 Bradley Rd Dover DE 19901",
    "addr:housenumber":"336",
    "addr:postcode":"19901",
    "addr:street":"Bradley Rd",
    "iso:country":"US",
    "sg:address":"336 Bradley Rd",
    "sg:city":"Dover",
    "sg:classifiers":[
        {
            "category":"Professional",
            "type":"Services"
        }
    ],
    "sg:phone":"+1 302 674 4188",
    "sg:postcode":"19901",
    "sg:province":"DE",
    "wof:name":"Daniel J Doyle Sgm",
    "wof:placetype":"venue"
},
  "geometry": {"coordinates":[-75.513711,39.174038],"type":"Point"}
}