{
  "type": "Feature",
  "properties": {
    "iso:country":"US",
    "sg:address":"2909 Cheshire Rd",
    "sg:city":"Wilmington",
    "sg:classifiers":[
        {
            "category":"Building & Trades",
            "subcategory":"Landscaping Services",
            "type":"Services"
        }
    ],
    "sg:phone":"+1 302 478 3243",
    "sg:postcode":"19810",
    "sg:province":"DE",
    "sg:tags":[
        "landscape"
    ],
    "wof:name":"Longs Landscaping Inc",
    "wof:placetype":"venue"
},
  "geometry": {"coordinates":[-75.542686,39.82079],"type":"Point"}
}