{
  "type": "Feature",
  "properties": {
    "iso:country":"US",
    "sg:address":"18 Wordsworth Dr",
    "sg:city":"Wilmington",
    "sg:classifiers":[
        {
            "category":"Building & Trades",
            "subcategory":"Landscaping Services",
            "type":"Services"
        }
    ],
    "sg:phone":"+1 302 998 4499",
    "sg:postcode":"19808",
    "sg:province":"DE",
    "wof:name":"Gallo Tree Serv",
    "wof:placetype":"venue"
},
  "geometry": {"coordinates":[-75.64867,39.747646],"type":"Point"}
}