{
  "type": "Feature",
  "properties": {
    "iso:country":"US",
    "sg:address":"3227 Horseshoe Rd",
    "sg:city":"Seaford",
    "sg:classifiers":[
        {
            "category":"Personal",
            "subcategory":"Beauty Salon",
            "type":"Services"
        }
    ],
    "sg:phone":"+1 302 629 0707",
    "sg:postcode":"19973",
    "sg:province":"DE",
    "wof:name":"Tnt Trenz Family Salon",
    "wof:placetype":"venue"
},
  "geometry": {"coordinates":[-75.69117900000001,38.657262],"type":"Point"}
}