{
  "type": "Feature",
  "properties": {
    "iso:country":"US",
    "sg:address":"283 N Dupont Hwy Ste E",
    "sg:city":"Dover",
    "sg:classifiers":[
        {
            "category":"Home & Garden",
            "subcategory":"Home Furnishings",
            "type":"Retail Goods"
        },
        {
            "category":"Home & Garden",
            "subcategory":"Carpets & Floor Coverings",
            "type":"Retail Goods"
        }
    ],
    "sg:phone":"+1 302 734 7735",
    "sg:postcode":"19901",
    "sg:province":"DE",
    "sg:tags":[
        "bedroom",
        "set",
        "bed",
        "mattress"
    ],
    "sg:website":"http://www.mattressgaint.com",
    "wof:name":"Mattress Giant",
    "wof:placetype":"venue"
},
  "geometry": {"coordinates":[-75.518665,39.170799],"type":"Point"}
}