{
  "type": "Feature",
  "properties": {
    "iso:country":"US",
    "sg:address":"505 White Clay Center Dr",
    "sg:city":"Newark",
    "sg:classifiers":[
        {
            "category":"Professional",
            "subcategory":"Management & Consulting",
            "type":"Services"
        }
    ],
    "sg:phone":"+1 302 376 6847",
    "sg:postcode":"19711",
    "sg:province":"DE",
    "sg:tags":[
        "marketing",
        "consultant"
    ],
    "wof:name":"Advanced Telemarketing Corp",
    "wof:placetype":"venue"
},
  "geometry": {"coordinates":[-75.72380699999999,39.682787],"type":"Point"}
}