{
  "type": "Feature",
  "properties": {
    "addr:full":"7852 S Dupont Hwy Felton DE 19943",
    "addr:housenumber":"7852",
    "addr:postcode":"19943",
    "addr:street":"S Dupont Hwy",
    "iso:country":"US",
    "sg:address":"7852 S Dupont Hwy",
    "sg:city":"Felton",
    "sg:classifiers":[
        {
            "category":"Shopping",
            "subcategory":"Used Merchandise",
            "type":"Retail Goods"
        },
        {
            "category":"Home & Garden",
            "subcategory":"Furniture",
            "type":"Retail Goods"
        }
    ],
    "sg:phone":"+1 302 284 3666",
    "sg:postcode":"19943",
    "sg:province":"DE",
    "wof:name":"Big Daddy's Baby & Hshld Furn",
    "wof:placetype":"venue"
},
  "geometry": {"coordinates":[-75.555819,39.057115],"type":"Point"}
}