{
  "type": "Feature",
  "properties": {
    "addr:full":"208 N Bedford St Georgetown DE 19947",
    "addr:housenumber":"208",
    "addr:postcode":"19947",
    "addr:street":"N Bedford St",
    "iso:country":"US",
    "sg:address":"208 N Bedford St",
    "sg:city":"Georgetown",
    "sg:classifiers":[
        {
            "category":"Health Services",
            "subcategory":"Clinic",
            "type":"Services"
        }
    ],
    "sg:phone":"+1 302 855 1220",
    "sg:postcode":"19947",
    "sg:province":"DE",
    "sg:tags":[
        "home"
    ],
    "wof:name":"Home Health Corp Of America",
    "wof:placetype":"venue"
},
  "geometry": {"coordinates":[-75.38825300000001,38.692194],"type":"Point"}
}