{
  "type": "Feature",
  "properties": {
    "addr:full":"2700 Silverside Rd Wilmington DE 19810",
    "addr:housenumber":"2700",
    "addr:postcode":"19810",
    "addr:street":"Silverside Rd",
    "iso:country":"US",
    "sg:address":"2700 Silverside Rd",
    "sg:city":"Wilmington",
    "sg:classifiers":[
        {
            "category":"Health Services",
            "subcategory":"Doctor",
            "type":"Services"
        }
    ],
    "sg:phone":"+1 302 478 5890",
    "sg:postcode":"19810",
    "sg:province":"DE",
    "wof:name":"Delaware Clinical Research",
    "wof:placetype":"venue"
},
  "geometry": {"coordinates":[-75.519096,39.8106],"type":"Point"}
}