{
  "type": "Feature",
  "properties": {
    "addr:full":"17099 County Seat Hwy Georgetown DE 19947",
    "addr:housenumber":"17099",
    "addr:postcode":"19947",
    "addr:street":"County Seat Hwy",
    "iso:country":"US",
    "sg:address":"17099 County Seat Hwy",
    "sg:city":"Georgetown",
    "sg:classifiers":[
        {
            "category":"Education",
            "subcategory":"School",
            "type":"Public Place"
        }
    ],
    "sg:phone":"+1 302 856 9035",
    "sg:postcode":"19947",
    "sg:province":"DE",
    "wof:name":"James Grove Adult Education",
    "wof:placetype":"venue"
},
  "geometry": {"coordinates":[-75.43124,38.651373],"type":"Point"}
}