{
  "type": "Feature",
  "properties": {
    "iso:country":"US",
    "sg:address":"407 Clinton St",
    "sg:city":"Delaware City",
    "sg:classifiers":[
        {
            "category":"Government",
            "subcategory":"Office",
            "type":"Public Place"
        }
    ],
    "sg:phone":"+1 302 834 4573",
    "sg:postcode":"19706",
    "sg:province":"DE",
    "sg:tags":[
        "city"
    ],
    "wof:name":"Delaware City Town Hall",
    "wof:placetype":"venue"
},
  "geometry": {"coordinates":[-75.59364600000001,39.573907],"type":"Point"}
}