{
  "type": "Feature",
  "properties": {
    "iso:country":"US",
    "sg:address":"115 W Market St",
    "sg:city":"Laurel",
    "sg:classifiers":[
        {
            "category":"Shopping",
            "type":"Retail Goods"
        }
    ],
    "sg:phone":"+1 302 875 4773",
    "sg:postcode":"19956",
    "sg:province":"DE",
    "sg:tags":[
        "merchandise"
    ],
    "wof:name":"E&L This & That Shop",
    "wof:placetype":"venue"
},
  "geometry": {"coordinates":[-75.571393,38.556858],"type":"Point"}
}