{
  "type": "Feature",
  "properties": {
    "iso:country":"US",
    "sg:address":"113 Fox Glove Dr",
    "sg:city":"Harrington",
    "sg:classifiers":[
        {
            "category":"Building & Trades",
            "subcategory":"Construction",
            "type":"Services"
        }
    ],
    "sg:phone":"+1 302 424 1167",
    "sg:postcode":"19952",
    "sg:province":"DE",
    "sg:tags":[
        "wallcoverings-installation",
        "wallpaper",
        "painting",
        "contractor"
    ],
    "wof:name":"Headly Brothers",
    "wof:placetype":"venue"
},
  "geometry": {"coordinates":[-75.50927799999999,38.945097],"type":"Point"}
}