{
  "type": "Feature",
  "properties": {
    "addr:full":"1011 Centre Rd Wilmington DE 19805",
    "addr:housenumber":"1011",
    "addr:postcode":"19805",
    "addr:street":"Centre Rd",
    "iso:country":"US",
    "sg:address":"1011 Centre Rd",
    "sg:city":"Wilmington",
    "sg:classifiers":[
        {
            "category":"Insurance",
            "subcategory":"Insurance Agent",
            "type":"Services"
        }
    ],
    "sg:phone":"+1 302 993 0500",
    "sg:postcode":"19805",
    "sg:province":"DE",
    "wof:name":"Liberty Mutual Insurance",
    "wof:placetype":"venue"
},
  "geometry": {"coordinates":[-75.60732400000001,39.75643],"type":"Point"}
}