{
  "type": "Feature",
  "properties": {
    "iso:country":"US",
    "sg:address":"1148 Pulaski Hwy",
    "sg:city":"Bear",
    "sg:classifiers":[
        {
            "category":"Building & Trades",
            "subcategory":"Cleaning & Sanitation",
            "type":"Services"
        }
    ],
    "sg:phone":"+1 302 345 7679",
    "sg:postcode":"19701",
    "sg:province":"DE",
    "wof:name":"JV Cleaning Service",
    "wof:placetype":"venue"
},
  "geometry": {"coordinates":[-75.665097,39.630034],"type":"Point"}
}