{
  "type": "Feature",
  "properties": {
    "iso:country":"US",
    "sg:address":"2658 Drayton Dr",
    "sg:city":"Wilmington",
    "sg:classifiers":[
        {
            "category":"Manufacturing",
            "subcategory":"Electronics",
            "type":"Manufacturing & Wholesale Goods"
        }
    ],
    "sg:phone":"+1 302 235 5988",
    "sg:postcode":"19808",
    "sg:province":"DE",
    "sg:tags":[
        "semiconductor",
        "devices"
    ],
    "wof:name":"Calico",
    "wof:placetype":"venue"
},
  "geometry": {"coordinates":[-75.678862,39.725328],"type":"Point"}
}