{
  "type": "Feature",
  "properties": {
    "iso:country":"US",
    "sg:address":"20 E Abbey Dr",
    "sg:city":"Townsend",
    "sg:classifiers":[
        {
            "category":"Real Estate",
            "subcategory":"Real Estate Services",
            "type":"Services"
        },
        {
            "category":"Real Estate",
            "subcategory":"Real Estate Agent",
            "type":"Services"
        }
    ],
    "sg:phone":"+1 302 449 2261",
    "sg:postcode":"19734",
    "sg:province":"DE",
    "sg:tags":[
        "management"
    ],
    "wof:name":"Five Star Properties Inc",
    "wof:placetype":"venue"
},
  "geometry": {"coordinates":[-75.653904,39.421351],"type":"Point"}
}