{
  "type": "Feature",
  "properties": {
    "iso:country":"US",
    "sg:address":"1 Thistle Ct",
    "sg:city":"Wilmington",
    "sg:classifiers":[
        {
            "category":"Building & Trades",
            "subcategory":"Construction",
            "type":"Services"
        }
    ],
    "sg:phone":"+1 302 529 7260",
    "sg:postcode":"19810",
    "sg:province":"DE",
    "sg:tags":[
        "hanging",
        "contractor"
    ],
    "wof:name":"Kirkwood Painting Co",
    "wof:placetype":"venue"
},
  "geometry": {"coordinates":[-75.472917,39.82522],"type":"Point"}
}