{
  "type": "Feature",
  "properties": {
    "addr:full":"4493 Hwy One Rehoboth Beach DE 19971",
    "addr:housenumber":"4493",
    "addr:postcode":"19971",
    "addr:street":"Hwy One",
    "iso:country":"US",
    "sg:address":"4493 Hwy One",
    "sg:city":"Rehoboth Beach",
    "sg:classifiers":[
        {
            "category":"Restaurant",
            "type":"Food & Drink"
        }
    ],
    "sg:phone":"+1 302 645 5433",
    "sg:postcode":"19971",
    "sg:province":"DE",
    "sg:website":"www.popeyes.com",
    "wof:name":"Popeyes Chicken & Biscuits",
    "wof:placetype":"venue"
},
  "geometry": {"coordinates":[-75.13051,38.729252],"type":"Point"}
}