{
  "type": "Feature",
  "properties": {
    "iso:country":"US",
    "sg:address":"1618 E Ayre St",
    "sg:city":"Newport",
    "sg:classifiers":[
        {
            "category":"Retail",
            "subcategory":"Car Wash",
            "type":"Services"
        }
    ],
    "sg:phone":"+1 302 633 1888",
    "sg:postcode":"19804",
    "sg:province":"DE",
    "sg:tags":[
        "polishing",
        "washing"
    ],
    "wof:name":"Perfect Custom Auto Detailing",
    "wof:placetype":"venue"
},
  "geometry": {"coordinates":[-75.602372,39.713455],"type":"Point"}
}