{
  "type": "Feature",
  "properties": {
    "iso:country":"US",
    "sg:address":"30 Adel Dr",
    "sg:city":"Newark",
    "sg:classifiers":[
        {
            "category":"Building & Trades",
            "subcategory":"Construction",
            "type":"Services"
        },
        {
            "category":"Building & Trades",
            "subcategory":"Plumbing",
            "type":"Services"
        }
    ],
    "sg:phone":"+1 302 453 0432",
    "sg:postcode":"19702",
    "sg:province":"DE",
    "sg:tags":[
        "excavation",
        "tank",
        "septic",
        "contractor"
    ],
    "wof:name":"Henry Miller & Son Inc",
    "wof:placetype":"venue"
},
  "geometry": {"coordinates":[-75.698579,39.655932],"type":"Point"}
}