{
  "type": "Feature",
  "properties": {
    "iso:country":"US",
    "sg:address":"110 Greenview Dr",
    "sg:city":"Dover",
    "sg:classifiers":[
        {
            "category":"Professional",
            "type":"Services"
        }
    ],
    "sg:phone":"+1 302 697 1091",
    "sg:postcode":"19901",
    "sg:province":"DE",
    "wof:name":"Thomas J Geist Ltcol",
    "wof:placetype":"venue"
},
  "geometry": {"coordinates":[-75.52365899999999,39.119076],"type":"Point"}
}