{
  "type": "Feature",
  "properties": {
    "addr:full":"2650 Westville Rd Marydel DE 19964",
    "addr:housenumber":"2650",
    "addr:postcode":"19964",
    "addr:street":"Westville Rd",
    "iso:country":"US",
    "sg:address":"2650 Westville Rd",
    "sg:city":"Marydel",
    "sg:classifiers":[
        {
            "category":"Professional",
            "type":"Services"
        }
    ],
    "sg:phone":"+1 302 492 3526",
    "sg:postcode":"19964",
    "sg:province":"DE",
    "wof:name":"Judith E French",
    "wof:placetype":"venue"
},
  "geometry": {"coordinates":[-75.70549800000001,39.098063],"type":"Point"}
}