{
  "type": "Feature",
  "properties": {
    "addr:full":"2223 Concord Pike Wilmington DE 19803",
    "addr:housenumber":"2223",
    "addr:postcode":"19803",
    "addr:street":"Concord Pike",
    "iso:country":"US",
    "sg:address":"2223 Concord Pike",
    "sg:city":"Wilmington",
    "sg:classifiers":[
        {
            "category":"Shopping",
            "subcategory":"Crafts & Fabrics",
            "type":"Retail Goods"
        }
    ],
    "sg:phone":"+1 302 655 6154",
    "sg:postcode":"19803",
    "sg:province":"DE",
    "sg:tags":[
        "sewing",
        "supply"
    ],
    "wof:name":"Calico Corners",
    "wof:placetype":"venue"
},
  "geometry": {"coordinates":[-75.54590899999999,39.786508],"type":"Point"}
}