{
  "type": "Feature",
  "properties": {
    "iso:country":"US",
    "sg:address":"4 Caponi Cir",
    "sg:city":"Middletown",
    "sg:classifiers":[
        {
            "category":"Shopping",
            "subcategory":"Bicycles & Sporting Goods",
            "type":"Retail Goods"
        }
    ],
    "sg:phone":"+1 302 376 8190",
    "sg:postcode":"19709",
    "sg:province":"DE",
    "sg:tags":[
        "equipment",
        "golf",
        "supply"
    ],
    "wof:name":"Better Game Golf Shoppe",
    "wof:placetype":"venue"
},
  "geometry": {"coordinates":[-75.706756,39.466074],"type":"Point"}
}