{
  "type": "Feature",
  "properties": {
    "iso:country":"US",
    "sg:address":"3 Winterbury Cir",
    "sg:city":"Wilmington",
    "sg:classifiers":[
        {
            "category":"Shopping",
            "type":"Retail Goods"
        }
    ],
    "sg:phone":"+1 302 994 2248",
    "sg:postcode":"19808",
    "sg:province":"DE",
    "sg:tags":[
        "merchandise"
    ],
    "wof:name":"Grace McFarren Art Studio",
    "wof:placetype":"venue"
},
  "geometry": {"coordinates":[-75.659783,39.76128],"type":"Point"}
}