{
  "type": "Feature",
  "properties": {
    "addr:full":"7 W Commerce St Smyrna DE 19977",
    "addr:housenumber":"7",
    "addr:postcode":"19977",
    "addr:street":"W Commerce St",
    "iso:country":"US",
    "sg:address":"7 W Commerce St",
    "sg:city":"Smyrna",
    "sg:classifiers":[
        {
            "category":"Personal",
            "subcategory":"Barber",
            "type":"Services"
        }
    ],
    "sg:phone":"+1 302 659 5477",
    "sg:postcode":"19977",
    "sg:province":"DE",
    "sg:tags":[
        "shop"
    ],
    "wof:name":"A Lil Off The Top Barber Shop",
    "wof:placetype":"venue"
},
  "geometry": {"coordinates":[-75.60646800000001,39.300674],"type":"Point"}
}