{
  "type": "Feature",
  "properties": {
    "iso:country":"US",
    "sg:address":"907 Kiamensi Rd",
    "sg:city":"Wilmington",
    "sg:classifiers":[
        {
            "category":"Social Services",
            "type":"Services"
        }
    ],
    "sg:phone":"+1 302 998 6439",
    "sg:postcode":"19804",
    "sg:province":"DE",
    "sg:tags":[
        "counseling"
    ],
    "wof:name":"Smith-Coleman Counseling Svc",
    "wof:placetype":"venue"
},
  "geometry": {"coordinates":[-75.636155,39.723824],"type":"Point"}
}