{
  "type": "Feature",
  "properties": {
    "iso:country":"US",
    "sg:address":"236 S Dupont Hwy",
    "sg:city":"New Castle",
    "sg:classifiers":[
        {
            "category":"Local Transit",
            "type":"Transportation"
        }
    ],
    "sg:phone":"+1 302 325 3222",
    "sg:postcode":"19720",
    "sg:province":"DE",
    "sg:tags":[
        "limousine"
    ],
    "wof:name":"Emerald Limousine Services",
    "wof:placetype":"venue"
},
  "geometry": {"coordinates":[-75.61629499999999,39.65456],"type":"Point"}
}