{
  "type": "Feature",
  "properties": {
    "iso:country":"US",
    "sg:address":"6 S Railroad Ave",
    "sg:city":"Wyoming",
    "sg:classifiers":[
        {
            "category":"Education",
            "subcategory":"Special Training",
            "type":"Public Place"
        }
    ],
    "sg:phone":"+1 302 697 2107",
    "sg:postcode":"19934",
    "sg:province":"DE",
    "sg:tags":[
        "educational"
    ],
    "wof:name":"Higher Education Referral",
    "wof:placetype":"venue"
},
  "geometry": {"coordinates":[-75.559695,39.118357],"type":"Point"}
}