{
  "type": "Feature",
  "properties": {
    "addr:full":"522 Otis Dr Dover DE 19901",
    "addr:housenumber":"522",
    "addr:postcode":"19901",
    "addr:street":"Otis Dr",
    "iso:country":"US",
    "sg:address":"522 Otis Dr",
    "sg:city":"Dover",
    "sg:classifiers":[
        {
            "category":"Education",
            "subcategory":"School",
            "type":"Public Place"
        }
    ],
    "sg:phone":"+1 302 734 9717",
    "sg:postcode":"19901",
    "sg:province":"DE",
    "sg:website":"www.dancebtd.com",
    "wof:name":"Dance Conservatory",
    "wof:placetype":"venue"
},
  "geometry": {"coordinates":[-75.498042,39.156613],"type":"Point"}
}