{
  "type": "Feature",
  "properties": {
    "iso:country":"US",
    "sg:address":"508 Philadelphia Pike",
    "sg:city":"Wilmington",
    "sg:classifiers":[
        {
            "category":"Insurance",
            "subcategory":"Insurance Agent",
            "type":"Services"
        }
    ],
    "sg:phone":"+1 302 764 6802",
    "sg:postcode":"19809",
    "sg:province":"DE",
    "wof:name":"State Farm Insurance",
    "wof:placetype":"venue"
},
  "geometry": {"coordinates":[-75.505213,39.768365],"type":"Point"}
}