{
  "type": "Feature",
  "properties": {
    "iso:country":"US",
    "sg:address":"4541 Kirkwood Hwy",
    "sg:city":"Wilmington",
    "sg:classifiers":[
        {
            "category":"Banks & Credit Unions",
            "subcategory":"Bank",
            "type":"Services"
        }
    ],
    "sg:phone":"+1 302 994 5721",
    "sg:postcode":"19808",
    "sg:province":"DE",
    "sg:tags":[
        "loan"
    ],
    "wof:name":"Citi Financial",
    "wof:placetype":"venue"
},
  "geometry": {"coordinates":[-75.655452,39.725338],"type":"Point"}
}