{
  "type": "Feature",
  "properties": {
    "iso:country":"US",
    "sg:address":"12 Ridon Dr",
    "sg:city":"Hockessin",
    "sg:classifiers":[
        {
            "category":"Building & Trades",
            "subcategory":"Construction",
            "type":"Services"
        }
    ],
    "sg:phone":"+1 302 239 2843",
    "sg:postcode":"19707",
    "sg:province":"DE",
    "sg:tags":[
        "dry wall",
        "contractor"
    ],
    "wof:name":"State Drywall Co",
    "wof:placetype":"venue"
},
  "geometry": {"coordinates":[-75.71189099999999,39.789547],"type":"Point"}
}