{
  "type": "Feature",
  "properties": {
    "iso:country":"US",
    "sg:address":"1713 Conrad St",
    "sg:city":"Wilmington",
    "sg:classifiers":[
        {
            "category":"Autos & Motor Vehicles",
            "subcategory":"Automobile Sales",
            "type":"Retail Goods"
        }
    ],
    "sg:phone":"+1 302 652 4160",
    "sg:postcode":"19805",
    "sg:province":"DE",
    "sg:tags":[
        "new",
        "car"
    ],
    "wof:name":"Road Master",
    "wof:placetype":"venue"
},
  "geometry": {"coordinates":[-75.57029199999999,39.746751],"type":"Point"}
}