{
  "type": "Feature",
  "properties": {
    "iso:country":"US",
    "sg:address":"44 Bancroft Mill Rd",
    "sg:city":"Wilmington",
    "sg:classifiers":[
        {
            "category":"Building & Trades",
            "subcategory":"Construction",
            "type":"Services"
        }
    ],
    "sg:phone":"+1 302 655 3434",
    "sg:postcode":"19806",
    "sg:province":"DE",
    "sg:tags":[
        "manager"
    ],
    "wof:name":"Bancroft Homes Inc",
    "wof:placetype":"venue"
},
  "geometry": {"coordinates":[-75.56455099999999,39.768705],"type":"Point"}
}