{
  "type": "Feature",
  "properties": {
    "iso:country":"US",
    "sg:address":"59 Baltimore Ave",
    "sg:city":"Rehoboth Beach",
    "sg:classifiers":[
        {
            "category":"Professional",
            "subcategory":"Business Services",
            "type":"Services"
        }
    ],
    "sg:phone":"+1 302 227 2272",
    "sg:postcode":"19971",
    "sg:province":"DE",
    "sg:tags":[
        "interior",
        "consultant",
        "design",
        "decorator"
    ],
    "wof:name":"Mark Showell Interiors Ltd",
    "wof:placetype":"venue"
},
  "geometry": {"coordinates":[-75.080224,38.717187],"type":"Point"}
}