{
  "type": "Feature",
  "properties": {
    "iso:country":"US",
    "sg:address":"4 Dogwood Ct",
    "sg:city":"Dover",
    "sg:classifiers":[
        {
            "category":"Professional",
            "type":"Services"
        }
    ],
    "sg:phone":"+1 302 674 1704",
    "sg:postcode":"19904",
    "sg:province":"DE",
    "wof:name":"Kenneth H Smith Ltcol",
    "wof:placetype":"venue"
},
  "geometry": {"coordinates":[-75.534492,39.137745],"type":"Point"}
}