{
  "type": "Feature",
  "properties": {
    "addr:full":"9 Cherry Rd New Castle DE 19720",
    "addr:housenumber":"9",
    "addr:postcode":"19720",
    "addr:street":"Cherry Rd",
    "iso:country":"US",
    "sg:address":"9 Cherry Rd",
    "sg:city":"New Castle",
    "sg:classifiers":[
        {
            "category":"Autos & Motor Vehicles",
            "subcategory":"Automobile Sales",
            "type":"Retail Goods"
        }
    ],
    "sg:phone":"+1 302 323 3012",
    "sg:postcode":"19720",
    "sg:province":"DE",
    "sg:tags":[
        "car",
        "dealer"
    ],
    "wof:name":"Gambacorta Used Cars",
    "wof:placetype":"venue"
},
  "geometry": {"coordinates":[-75.629428,39.67382],"type":"Point"}
}