{
  "type": "Feature",
  "properties": {
    "iso:country":"US",
    "sg:address":"408 N James St",
    "sg:city":"Wilmington",
    "sg:classifiers":[
        {
            "category":"Building & Trades",
            "subcategory":"Construction",
            "type":"Services"
        }
    ],
    "sg:phone":"+1 302 998 7385",
    "sg:postcode":"19804",
    "sg:province":"DE",
    "sg:tags":[
        "contractor"
    ],
    "wof:name":"S A Buell",
    "wof:placetype":"venue"
},
  "geometry": {"coordinates":[-75.60988399999999,39.715631],"type":"Point"}
}