{
  "type": "Feature",
  "properties": {
    "addr:full":"2706 Old Milltown Rd Wilmington DE 19808",
    "addr:housenumber":"2706",
    "addr:postcode":"19808",
    "addr:street":"Old Milltown Rd",
    "iso:country":"US",
    "sg:address":"2706 Old Milltown Rd",
    "sg:city":"Wilmington",
    "sg:classifiers":[
        {
            "category":"Professional",
            "type":"Services"
        }
    ],
    "sg:phone":"+1 302 995 1153",
    "sg:postcode":"19808",
    "sg:province":"DE",
    "wof:name":"Nancys Boat Services",
    "wof:placetype":"venue"
},
  "geometry": {"coordinates":[-75.675865,39.715535],"type":"Point"}
}