{
  "type": "Feature",
  "properties": {
    "iso:country":"US",
    "sg:address":"1373 N Little Creek Rd",
    "sg:city":"Dover",
    "sg:classifiers":[
        {
            "category":"Retail",
            "subcategory":"Car Wash",
            "type":"Services"
        },
        {
            "category":"Retail",
            "subcategory":"Auto Repair",
            "type":"Services"
        }
    ],
    "sg:phone":"+1 302 734 0161",
    "sg:postcode":"19901",
    "sg:province":"DE",
    "sg:tags":[
        "body",
        "painting",
        "repairing",
        "automobile"
    ],
    "wof:name":"The Number One Stop Shop Inc",
    "wof:placetype":"venue"
},
  "geometry": {"coordinates":[-75.502098,39.166882],"type":"Point"}
}