{
  "type": "Feature",
  "properties": {
    "iso:country":"US",
    "sg:address":"617 Market St",
    "sg:city":"Bridgeville",
    "sg:classifiers":[
        {
            "category":"Wholesale",
            "subcategory":"Construction Materials",
            "type":"Manufacturing & Wholesale Goods"
        },
        {
            "category":"Manufacturing",
            "subcategory":"Building Materials",
            "type":"Manufacturing & Wholesale Goods"
        }
    ],
    "sg:phone":"+1 302 337 0269",
    "sg:postcode":"19933",
    "sg:province":"DE",
    "wof:name":"Moulding & Millwork Inc",
    "wof:placetype":"venue"
},
  "geometry": {"coordinates":[-75.605458,38.742314],"type":"Point"}
}