{
  "type": "Feature",
  "properties": {
    "addr:full":"108 Olga Rd Wilmington DE 19805",
    "addr:housenumber":"108",
    "addr:postcode":"19805",
    "addr:street":"Olga Rd",
    "iso:country":"US",
    "sg:address":"108 Olga Rd",
    "sg:city":"Wilmington",
    "sg:classifiers":[
        {
            "category":"Building & Trades",
            "subcategory":"Plumbing",
            "type":"Services"
        }
    ],
    "sg:phone":"+1 302 654 9592",
    "sg:postcode":"19805",
    "sg:province":"DE",
    "sg:tags":[
        "contractor"
    ],
    "wof:name":"Kc Weaver Sons",
    "wof:placetype":"venue"
},
  "geometry": {"coordinates":[-75.597832,39.743326],"type":"Point"}
}