{
  "type": "Feature",
  "properties": {
    "iso:country":"US",
    "sg:address":"94 Albe Dr Ste 1",
    "sg:city":"Newark",
    "sg:classifiers":[
        {
            "category":"Landmark",
            "subcategory":"Monument",
            "type":"Public Place"
        }
    ],
    "sg:phone":"+1 302 738 0272",
    "sg:postcode":"19702",
    "sg:province":"DE",
    "wof:name":"Abba Monument Co Inc",
    "wof:placetype":"venue"
},
  "geometry": {"coordinates":[-75.71446899999999,39.650688],"type":"Point"}
}