{
  "type": "Feature",
  "properties": {
    "addr:full":"1151 S Governors Ave Dover DE 19904",
    "addr:housenumber":"1151",
    "addr:postcode":"19904",
    "addr:street":"S Governors Ave",
    "iso:country":"US",
    "sg:address":"1151 S Governors Ave",
    "sg:city":"Dover",
    "sg:classifiers":[
        {
            "category":"Retail",
            "subcategory":"Veterinary Services",
            "type":"Services"
        }
    ],
    "sg:phone":"+1 302 674 1515",
    "sg:postcode":"19904",
    "sg:province":"DE",
    "sg:tags":[
        "veterinarian"
    ],
    "wof:name":"Coon Chris E DVM",
    "wof:placetype":"venue"
},
  "geometry": {"coordinates":[-75.525803,39.139301],"type":"Point"}
}