{
  "type": "Feature",
  "properties": {
    "addr:full":"38325 Old Stage Rd Delmar DE 19940",
    "addr:housenumber":"38325",
    "addr:postcode":"19940",
    "addr:street":"Old Stage Rd",
    "iso:country":"US",
    "sg:address":"38325 Old Stage Rd",
    "sg:city":"Delmar",
    "sg:classifiers":[
        {
            "category":"Building & Trades",
            "subcategory":"Construction",
            "type":"Services"
        }
    ],
    "sg:phone":"+1 302 846 9873",
    "sg:postcode":"19940",
    "sg:province":"DE",
    "sg:tags":[
        "contractor"
    ],
    "wof:name":"Maur J Sheet Metal Co Inc",
    "wof:placetype":"venue"
},
  "geometry": {"coordinates":[-75.555361,38.455913],"type":"Point"}
}