{
  "type": "Feature",
  "properties": {
    "iso:country":"US",
    "sg:address":"1708 Foulk Rd",
    "sg:city":"Wilmington",
    "sg:classifiers":[
        {
            "category":"Shopping",
            "subcategory":"Crafts & Fabrics",
            "type":"Retail Goods"
        }
    ],
    "sg:phone":"+1 302 529 0553",
    "sg:postcode":"19803",
    "sg:province":"DE",
    "sg:tags":[
        "art"
    ],
    "sg:website":"www.grassrootshandcrafts.com",
    "wof:name":"Grassroots Handcrafts",
    "wof:placetype":"venue"
},
  "geometry": {"coordinates":[-75.515383,39.807431],"type":"Point"}
}