{
  "type": "Feature",
  "properties": {
    "iso:country":"US",
    "sg:address":"100 McIntosh Plz",
    "sg:city":"Newark",
    "sg:classifiers":[
        {
            "category":"Travel",
            "subcategory":"Hotels & Motels",
            "type":"Entertainment"
        }
    ],
    "sg:phone":"+1 302 453 9100",
    "sg:postcode":"19713",
    "sg:province":"DE",
    "sg:tags":[
        "operation"
    ],
    "wof:name":"Comfort Inn",
    "wof:placetype":"venue"
},
  "geometry": {"coordinates":[-75.681237,39.674549],"type":"Point"}
}