{
  "type": "Feature",
  "properties": {
    "iso:country":"US",
    "sg:address":"100 Saxton Rd",
    "sg:city":"Dover",
    "sg:classifiers":[
        {
            "category":"Wholesale",
            "subcategory":"Non-durable Goods",
            "type":"Manufacturing & Wholesale Goods"
        }
    ],
    "sg:phone":"+1 302 744 9775",
    "sg:postcode":"19901",
    "sg:province":"DE",
    "wof:name":"Diamond Aquarium Supply",
    "wof:placetype":"venue"
},
  "geometry": {"coordinates":[-75.524834,39.13254],"type":"Point"}
}