{
  "type": "Feature",
  "properties": {
    "iso:country":"US",
    "sg:address":"1403 Foulk Rd",
    "sg:city":"Wilmington",
    "sg:classifiers":[
        {
            "category":"Banks & Credit Unions",
            "subcategory":"Financial Services",
            "type":"Services"
        }
    ],
    "sg:phone":"+1 302 477 0877",
    "sg:postcode":"19803",
    "sg:province":"DE",
    "sg:tags":[
        "company",
        "holding"
    ],
    "wof:name":"Gamog Lease Inc",
    "wof:placetype":"venue"
},
  "geometry": {"coordinates":[-75.52063,39.802482],"type":"Point"}
}