{
  "type": "Feature",
  "properties": {
    "addr:full":"2115 N Washington St Wilmington DE 19802",
    "addr:housenumber":"2115",
    "addr:postcode":"19802",
    "addr:street":"N Washington St",
    "iso:country":"US",
    "sg:address":"2115 N Washington St",
    "sg:city":"Wilmington",
    "sg:classifiers":[
        {
            "category":"Professional",
            "subcategory":"Business Services",
            "type":"Services"
        }
    ],
    "sg:phone":"+1 302 254 3009",
    "sg:postcode":"19802",
    "sg:province":"DE",
    "wof:name":"Bold Enterprises Inc",
    "wof:placetype":"venue"
},
  "geometry": {"coordinates":[-75.542203,39.755469],"type":"Point"}
}