{
  "type": "Feature",
  "properties": {
    "iso:country":"US",
    "sg:address":"735 N Broad St",
    "sg:city":"Middletown",
    "sg:classifiers":[
        {
            "category":"Shopping",
            "type":"Retail Goods"
        }
    ],
    "sg:phone":"+1 302 376 1616",
    "sg:postcode":"19709",
    "sg:province":"DE",
    "sg:tags":[
        "pet",
        "food",
        "supply"
    ],
    "wof:name":"Concord Pet Foods & Supplies",
    "wof:placetype":"venue"
},
  "geometry": {"coordinates":[-75.719736,39.459118],"type":"Point"}
}