{
  "type": "Feature",
  "properties": {
    "iso:country":"US",
    "sg:address":"501 Christiana Mall",
    "sg:city":"Newark",
    "sg:classifiers":[
        {
            "category":"Shopping",
            "subcategory":"Department Store",
            "type":"Retail Goods"
        }
    ],
    "sg:phone":"+1 302 366 5800",
    "sg:postcode":"19702",
    "sg:province":"DE",
    "sg:website":"http://www.macys.com",
    "wof:name":"Macy's",
    "wof:placetype":"venue"
},
  "geometry": {"coordinates":[-75.64856399999999,39.679878],"type":"Point"}
}