{
  "type": "Feature",
  "properties": {
    "iso:country":"US",
    "sg:address":"19 Henry Ct",
    "sg:city":"Wilmington",
    "sg:classifiers":[
        {
            "category":"Shopping",
            "type":"Retail Goods"
        }
    ],
    "sg:phone":"+1 302 478 9081",
    "sg:postcode":"19808",
    "sg:province":"DE",
    "sg:tags":[
        "collectible"
    ],
    "wof:name":"Heroes & Legends",
    "wof:placetype":"venue"
},
  "geometry": {"coordinates":[-75.67599300000001,39.736592],"type":"Point"}
}