{
  "type": "Feature",
  "properties": {
    "iso:country":"US",
    "sg:address":"7 Marlin Ct",
    "sg:city":"New Castle",
    "sg:classifiers":[
        {
            "category":"Professional",
            "type":"Services"
        }
    ],
    "sg:phone":"+1 302 838 4009",
    "sg:postcode":"19720",
    "sg:province":"DE",
    "wof:name":"Robert A Pierce Mr",
    "wof:placetype":"venue"
},
  "geometry": {"coordinates":[-75.648533,39.616802],"type":"Point"}
}