{
  "type": "Feature",
  "properties": {
    "iso:country":"US",
    "sg:address":"314 E Main St",
    "sg:city":"Newark",
    "sg:classifiers":[
        {
            "category":"Wholesale",
            "subcategory":"Construction Materials",
            "type":"Manufacturing & Wholesale Goods"
        },
        {
            "category":"Wholesale",
            "subcategory":"Durable Goods & Equipment",
            "type":"Manufacturing & Wholesale Goods"
        }
    ],
    "sg:phone":"+1 302 454 0361",
    "sg:postcode":"19711",
    "sg:province":"DE",
    "sg:tags":[
        "representative",
        "manufacturer"
    ],
    "sg:website":"www.thomco1.com",
    "wof:name":"Thomco Inc",
    "wof:placetype":"venue"
},
  "geometry": {"coordinates":[-75.739555,39.684214],"type":"Point"}
}