{
  "type": "Feature",
  "properties": {
    "iso:country":"US",
    "sg:address":"501 Woodside Ave",
    "sg:city":"Wilmington",
    "sg:classifiers":[
        {
            "category":"Building & Trades",
            "subcategory":"Electrical",
            "type":"Services"
        }
    ],
    "sg:phone":"+1 302 798 5652",
    "sg:postcode":"19809",
    "sg:province":"DE",
    "sg:tags":[
        "house",
        "electrical",
        "contractor"
    ],
    "wof:name":"Pyramid Electric",
    "wof:placetype":"venue"
},
  "geometry": {"coordinates":[-75.490301,39.787584],"type":"Point"}
}