{
  "type": "Feature",
  "properties": {
    "iso:country":"US",
    "sg:address":"205 Philadelphia Pike",
    "sg:city":"Wilmington",
    "sg:classifiers":[
        {
            "category":"Banks & Credit Unions",
            "subcategory":"Investment Brokerage",
            "type":"Services"
        }
    ],
    "sg:phone":"+1 302 765 3500",
    "sg:postcode":"19809",
    "sg:province":"DE",
    "sg:tags":[
        "consultant",
        "planning",
        "financial",
        "advisory"
    ],
    "sg:website":"www.dfc-de.com",
    "wof:name":"Diversified Financial Cons",
    "wof:placetype":"venue"
},
  "geometry": {"coordinates":[-75.51209799999999,39.765392],"type":"Point"}
}