{
  "type": "Feature",
  "properties": {
    "iso:country":"US",
    "sg:address":"31 E Bellamy Dr",
    "sg:city":"New Castle",
    "sg:classifiers":[
        {
            "category":"Professional",
            "type":"Services"
        }
    ],
    "sg:phone":"+1 302 326 2286",
    "sg:postcode":"19720",
    "sg:province":"DE",
    "wof:name":"Gordon & Delores Holley",
    "wof:placetype":"venue"
},
  "geometry": {"coordinates":[-75.635997,39.664825],"type":"Point"}
}