{
  "type": "Feature",
  "properties": {
    "iso:country":"US",
    "sg:address":"10285 Redden Rd",
    "sg:city":"Bridgeville",
    "sg:classifiers":[
        {
            "category":"Shopping",
            "subcategory":"Beauty & Cosmetics",
            "type":"Retail Goods"
        }
    ],
    "sg:phone":"+1 302 337 8484",
    "sg:postcode":"19933",
    "sg:province":"DE",
    "wof:name":"Mary Kay Cosmetics",
    "wof:placetype":"venue"
},
  "geometry": {"coordinates":[-75.565766,38.747076],"type":"Point"}
}