{
  "type": "Feature",
  "properties": {
    "iso:country":"US",
    "sg:address":"3 Mill Park Ct",
    "sg:city":"Newark",
    "sg:classifiers":[
        {
            "category":"Professional",
            "subcategory":"Management & Consulting",
            "type":"Services"
        }
    ],
    "sg:phone":"+1 302 369 6901",
    "sg:postcode":"19713",
    "sg:province":"DE",
    "sg:tags":[
        "fire",
        "consultant",
        "protection"
    ],
    "wof:name":"HCC & Assoc",
    "wof:placetype":"venue"
},
  "geometry": {"coordinates":[-75.699026,39.685729],"type":"Point"}
}