{
  "type": "Feature",
  "properties": {
    "addr:full":"3130 Kennett Pike Greenville DE 19807",
    "addr:housenumber":"3130",
    "addr:postcode":"19807",
    "addr:street":"Kennett Pike",
    "iso:country":"US",
    "sg:address":"3130 Kennett Pike",
    "sg:city":"Greenville",
    "sg:classifiers":[
        {
            "category":"Education",
            "subcategory":"School",
            "type":"Public Place"
        }
    ],
    "sg:phone":"+1 302 651 2690",
    "sg:postcode":"19807",
    "sg:province":"DE",
    "wof:name":"Alexis I Du Pont Middle School",
    "wof:placetype":"venue"
},
  "geometry": {"coordinates":[-75.58448300000001,39.76669],"type":"Point"}
}