{
  "type": "Feature",
  "properties": {
    "iso:country":"US",
    "sg:address":"144 Kings Hwy",
    "sg:city":"Dover",
    "sg:classifiers":[
        {
            "category":"Building & Trades",
            "subcategory":"Landscaping Services",
            "type":"Services"
        }
    ],
    "sg:phone":"+1 302 678 3449",
    "sg:postcode":"19901",
    "sg:province":"DE",
    "sg:tags":[
        "landscape",
        "contractor"
    ],
    "wof:name":"R & L Landscaping LLC",
    "wof:placetype":"venue"
},
  "geometry": {"coordinates":[-75.524253,39.16015],"type":"Point"}
}