{
  "type": "Feature",
  "properties": {
    "iso:country":"US",
    "sg:address":"14 Degas Cir",
    "sg:city":"Wilmington",
    "sg:classifiers":[
        {
            "category":"Travel",
            "subcategory":"Travel Agent",
            "type":"Entertainment"
        }
    ],
    "sg:phone":"+1 302 235 1758",
    "sg:postcode":"19808",
    "sg:province":"DE",
    "sg:tags":[
        "operator",
        "tour",
        "group"
    ],
    "wof:name":"Footloose Tours Inc",
    "wof:placetype":"venue"
},
  "geometry": {"coordinates":[-75.707093,39.746803],"type":"Point"}
}