{
  "type": "Feature",
  "properties": {
    "iso:country":"US",
    "sg:address":"531 Cypress Dr",
    "sg:city":"Magnolia",
    "sg:classifiers":[
        {
            "category":"Professional",
            "subcategory":"Computer Services",
            "type":"Services"
        }
    ],
    "sg:phone":"+1 302 697 9400",
    "sg:postcode":"19962",
    "sg:province":"DE",
    "sg:website":"www.delnetexchange.com",
    "wof:name":"Delaware Internet Exchange",
    "wof:placetype":"venue"
},
  "geometry": {"coordinates":[-75.487754,39.097636],"type":"Point"}
}