{
  "type": "Feature",
  "properties": {
    "iso:country":"US",
    "sg:address":"625 N King St",
    "sg:city":"Wilmington",
    "sg:classifiers":[
        {
            "category":"Personal",
            "subcategory":"Beauty Salon",
            "type":"Services"
        }
    ],
    "sg:phone":"+1 302 778 2125",
    "sg:postcode":"19801",
    "sg:province":"DE",
    "wof:name":"Intou 2 Hair Studio",
    "wof:placetype":"venue"
},
  "geometry": {"coordinates":[-75.549374,39.741701],"type":"Point"}
}