{
  "type": "Feature",
  "properties": {
    "iso:country":"US",
    "sg:address":"405 Wisseman Ave",
    "sg:city":"Milford",
    "sg:classifiers":[
        {
            "category":"Building & Trades",
            "subcategory":"Construction",
            "type":"Services"
        }
    ],
    "sg:phone":"+1 302 430 0958",
    "sg:postcode":"19963",
    "sg:province":"DE",
    "sg:tags":[
        "painter"
    ],
    "wof:name":"Painters",
    "wof:placetype":"venue"
},
  "geometry": {"coordinates":[-75.45485600000001,38.905282],"type":"Point"}
}