{
  "type": "Feature",
  "properties": {
    "iso:country":"US",
    "sg:address":"20 Fairfield Rd",
    "sg:city":"Claymont",
    "sg:classifiers":[
        {
            "category":"Building & Trades",
            "subcategory":"Construction",
            "type":"Services"
        }
    ],
    "sg:phone":"+1 302 798 5430",
    "sg:postcode":"19703",
    "sg:province":"DE",
    "sg:tags":[
        "hanging",
        "contractor"
    ],
    "wof:name":"Jenkins Painting Co",
    "wof:placetype":"venue"
},
  "geometry": {"coordinates":[-75.468425,39.790415],"type":"Point"}
}