{
  "type": "Feature",
  "properties": {
    "iso:country":"US",
    "sg:address":"1600 Newport Gap Pike",
    "sg:city":"Wilmington",
    "sg:classifiers":[
        {
            "category":"Manufacturing",
            "subcategory":"Glass & Minerals",
            "type":"Manufacturing & Wholesale Goods"
        }
    ],
    "sg:phone":"+1 302 999 1886",
    "sg:postcode":"19808",
    "sg:province":"DE",
    "sg:tags":[
        "ready",
        "concrete",
        "mfg"
    ],
    "wof:name":"Material Supply Inc",
    "wof:placetype":"venue"
},
  "geometry": {"coordinates":[-75.624219,39.730273],"type":"Point"}
}