{
  "type": "Feature",
  "properties": {
    "iso:country":"US",
    "sg:address":"302 Atlantic Ave",
    "sg:city":"Millville",
    "sg:classifiers":[
        {
            "category":"Food & Beverages",
            "subcategory":"Liquor & Beverages",
            "type":"Retail Goods"
        }
    ],
    "sg:phone":"+1 302 537 8008",
    "sg:postcode":"19968",
    "sg:province":"DE",
    "wof:name":"Banks Wines & Spirits",
    "wof:placetype":"venue"
},
  "geometry": {"coordinates":[-75.309504,38.783287],"type":"Point"}
}