{
  "type": "Feature",
  "properties": {
    "addr:full":"360 E Harvest Ln Middletown DE 19709",
    "addr:housenumber":"360",
    "addr:postcode":"19709",
    "addr:street":"E Harvest Ln",
    "iso:country":"US",
    "sg:address":"360 E Harvest Ln",
    "sg:city":"Middletown",
    "sg:classifiers":[
        {
            "category":"Manufacturing",
            "subcategory":"Glass & Minerals",
            "type":"Manufacturing & Wholesale Goods"
        }
    ],
    "sg:phone":"+1 302 376 8640",
    "sg:postcode":"19709",
    "sg:province":"DE",
    "sg:tags":[
        "plate",
        "shape",
        "glass-wholesale",
        "window",
        "special",
        "circle",
        "glass-auto",
        "manufacturer"
    ],
    "wof:name":"Delmarva Auta Glass Inc",
    "wof:placetype":"venue"
},
  "geometry": {"coordinates":[-75.72802,39.459752],"type":"Point"}
}