{
  "type": "Feature",
  "properties": {
    "iso:country":"US",
    "sg:address":"2529 Lockwood Chapel Rd",
    "sg:city":"Dover",
    "sg:classifiers":[
        {
            "category":"Professional",
            "subcategory":"Business Services",
            "type":"Services"
        }
    ],
    "sg:phone":"+1 302 492 0137",
    "sg:postcode":"19904",
    "sg:province":"DE",
    "wof:name":"Richard Meyer",
    "wof:placetype":"venue"
},
  "geometry": {"coordinates":[-75.659009,39.17473],"type":"Point"}
}