{
  "type": "Feature",
  "properties": {
    "addr:full":"5301 Limestone Rd Ste 100 Wilmington DE 19808",
    "addr:housenumber":"5301",
    "addr:postcode":"19808",
    "addr:street":"Limestone Rd Ste 100",
    "iso:country":"US",
    "sg:address":"5301 Limestone Rd Ste 100",
    "sg:city":"Wilmington",
    "sg:classifiers":[
        {
            "category":"Banks & Credit Unions",
            "subcategory":"Investment Brokerage",
            "type":"Services"
        },
        {
            "category":"Insurance",
            "subcategory":"Hazard Insurance",
            "type":"Services"
        }
    ],
    "sg:phone":"+1 302 239 5500",
    "sg:postcode":"19808",
    "sg:province":"DE",
    "sg:tags":[
        "agent",
        "resume"
    ],
    "sg:website":"http://www.paulgallagher.com",
    "wof:name":"G N G Insurance",
    "wof:placetype":"venue"
},
  "geometry": {"coordinates":[-75.69596900000001,39.743919],"type":"Point"}
}