{
  "type": "Feature",
  "properties": {
    "addr:full":"1030 State Hwy 1 Lewes DE 19958",
    "addr:housenumber":"1030",
    "addr:postcode":"19958",
    "addr:street":"State Hwy 1",
    "iso:country":"US",
    "sg:address":"1030 State Hwy 1",
    "sg:city":"Lewes",
    "sg:classifiers":[
        {
            "category":"Food & Beverages",
            "subcategory":"Bakery",
            "type":"Retail Goods"
        }
    ],
    "sg:phone":"+1 302 644 1822",
    "sg:postcode":"19958",
    "sg:province":"DE",
    "sg:tags":[
        "bagel"
    ],
    "wof:name":"Surf Bagel & Deli",
    "wof:placetype":"venue"
},
  "geometry": {"coordinates":[-75.24747499999999,38.788561],"type":"Point"}
}