{
  "type": "Feature",
  "properties": {
    "iso:country":"US",
    "sg:address":"216 Delaware St",
    "sg:city":"New Castle",
    "sg:classifiers":[
        {
            "category":"Real Estate",
            "subcategory":"Real Estate Agent",
            "type":"Services"
        }
    ],
    "sg:phone":"+1 302 328 4113",
    "sg:postcode":"19720",
    "sg:province":"DE",
    "sg:tags":[
        "c",
        "apartment",
        "broker",
        "operates",
        "management",
        "an"
    ],
    "wof:name":"Coastal Funding Corporation",
    "wof:placetype":"venue"
},
  "geometry": {"coordinates":[-75.56424699999999,39.659893],"type":"Point"}
}