{
  "type": "Feature",
  "properties": {
    "iso:country":"US",
    "sg:address":"209 Clayton Manor Dr",
    "sg:city":"Middletown",
    "sg:classifiers":[
        {
            "category":"Building & Trades",
            "subcategory":"Construction",
            "type":"Services"
        }
    ],
    "sg:phone":"+1 302 378 8688",
    "sg:postcode":"19709",
    "sg:province":"DE",
    "sg:tags":[
        "concrete",
        "contractor"
    ],
    "wof:name":"J T Hoover Concrete",
    "wof:placetype":"venue"
},
  "geometry": {"coordinates":[-75.761027,39.50607],"type":"Point"}
}