{
  "type": "Feature",
  "properties": {
    "iso:country":"US",
    "sg:address":"42 Nassau Cmns",
    "sg:city":"Lewes",
    "sg:classifiers":[
        {
            "category":"Professional",
            "type":"Services"
        }
    ],
    "sg:phone":"+1 302 645 9075",
    "sg:postcode":"19958",
    "sg:province":"DE",
    "wof:name":"Visbal Fine Bronz Sculpture",
    "wof:placetype":"venue"
},
  "geometry": {"coordinates":[-75.149095,38.765712],"type":"Point"}
}