{
  "type": "Feature",
  "properties": {
    "addr:full":"137 S Bradford St Dover DE 19904",
    "addr:housenumber":"137",
    "addr:postcode":"19904",
    "addr:street":"S Bradford St",
    "iso:country":"US",
    "sg:address":"137 S Bradford St",
    "sg:city":"Dover",
    "sg:classifiers":[
        {
            "category":"Banks & Credit Unions",
            "subcategory":"Bank",
            "type":"Services"
        }
    ],
    "sg:phone":"+1 302 736 2910",
    "sg:postcode":"19904",
    "sg:province":"DE",
    "wof:name":"First Union",
    "wof:placetype":"venue"
},
  "geometry": {"coordinates":[-75.525873,39.158745],"type":"Point"}
}