{
  "type": "Feature",
  "properties": {
    "addr:full":"607 Bennett St Milton DE 19968",
    "addr:housenumber":"607",
    "addr:postcode":"19968",
    "addr:street":"Bennett St",
    "iso:country":"US",
    "sg:address":"607 Bennett St",
    "sg:city":"Milton",
    "sg:classifiers":[
        {
            "category":"Personal",
            "subcategory":"Beauty Salon",
            "type":"Services"
        }
    ],
    "sg:phone":"+1 302 684 8083",
    "sg:postcode":"19968",
    "sg:province":"DE",
    "sg:tags":[
        "shop"
    ],
    "wof:name":"Village Beauty Salon",
    "wof:placetype":"venue"
},
  "geometry": {"coordinates":[-75.311263,38.786771],"type":"Point"}
}