{
  "type": "Feature",
  "properties": {
    "addr:full":"501 E Dupont Hwy Millsboro DE 19966",
    "addr:housenumber":"501",
    "addr:postcode":"19966",
    "addr:street":"E Dupont Hwy",
    "iso:country":"US",
    "sg:address":"501 E Dupont Hwy",
    "sg:city":"Millsboro",
    "sg:classifiers":[
        {
            "category":"Home & Garden",
            "subcategory":"Mobile Homes",
            "type":"Retail Goods"
        }
    ],
    "sg:phone":"+1 302 934 6322",
    "sg:postcode":"19966",
    "sg:province":"DE",
    "wof:name":"CMH",
    "wof:placetype":"venue"
},
  "geometry": {"coordinates":[-75.284318,38.573215],"type":"Point"}
}