{
  "type": "Feature",
  "properties": {
    "iso:country":"US",
    "sg:address":"761 S Little Creek Rd",
    "sg:city":"Dover",
    "sg:classifiers":[
        {
            "category":"Organizations",
            "subcategory":"Religious Organization",
            "type":"Services"
        }
    ],
    "sg:phone":"+1 302 678 3130",
    "sg:postcode":"19901",
    "sg:province":"DE",
    "wof:name":"First Southern Baptist Church",
    "wof:placetype":"venue"
},
  "geometry": {"coordinates":[-75.507425,39.157366],"type":"Point"}
}