{
  "type": "Feature",
  "properties": {
    "iso:country":"US",
    "sg:address":"245 E Cleveland Ave",
    "sg:city":"Newark",
    "sg:classifiers":[
        {
            "category":"Retail",
            "subcategory":"Veterinary Services",
            "type":"Services"
        }
    ],
    "sg:phone":"+1 302 737 8100",
    "sg:postcode":"19711",
    "sg:province":"DE",
    "sg:tags":[
        "care"
    ],
    "wof:name":"VCA Hockessin Animal Hospital",
    "wof:placetype":"venue"
},
  "geometry": {"coordinates":[-75.743621,39.687086],"type":"Point"}
}