{
  "type": "Feature",
  "properties": {
    "iso:country":"US",
    "sg:address":"1614 Berrytown Rd",
    "sg:city":"Felton",
    "sg:classifiers":[
        {
            "category":"Building & Trades",
            "subcategory":"Plumbing",
            "type":"Services"
        }
    ],
    "sg:phone":"+1 302 284 8404",
    "sg:postcode":"19943",
    "sg:province":"DE",
    "sg:tags":[
        "contractor"
    ],
    "wof:name":"C & C Mechanical",
    "wof:placetype":"venue"
},
  "geometry": {"coordinates":[-75.605131,39.032134],"type":"Point"}
}