{
  "type": "Feature",
  "properties": {
    "iso:country":"US",
    "sg:address":"60 N College Ave",
    "sg:city":"Newark",
    "sg:phone":"+1 302 456 0900",
    "sg:postcode":"19711",
    "sg:province":"DE",
    "sg:website":"http://www.clarabellatanandhair.com",
    "wof:name":"Clara Bella Designs",
    "wof:placetype":"venue"
},
  "geometry": {"coordinates":[-75.754318,39.684761],"type":"Point"}
}