{
  "type": "Feature",
  "properties": {
    "iso:country":"US",
    "sg:address":"401 E Main St",
    "sg:city":"Middletown",
    "sg:phone":"+1 302 449 4269",
    "sg:postcode":"19709",
    "sg:province":"DE",
    "sg:website":"http://myromapizza.com",
    "wof:name":"Roma Pizza",
    "wof:placetype":"venue"
},
  "geometry": {"coordinates":[-75.70163700000001,39.45047],"type":"Point"}
}