{
  "type": "Feature",
  "properties": {
    "addr:full":"265 Lakeside Dr Lewes DE 19958",
    "addr:housenumber":"265",
    "addr:postcode":"19958",
    "addr:street":"Lakeside Dr",
    "iso:country":"US",
    "sg:address":"265 Lakeside Dr",
    "sg:city":"Lewes",
    "sg:classifiers":[
        {
            "category":"Professional",
            "subcategory":"Business Services",
            "type":"Services"
        }
    ],
    "sg:phone":"+1 302 645 5610",
    "sg:postcode":"19958",
    "sg:province":"DE",
    "wof:name":"Interior Outlook",
    "wof:placetype":"venue"
},
  "geometry": {"coordinates":[-75.16028799999999,38.738759],"type":"Point"}
}