{
  "type": "Feature",
  "properties": {
    "addr:full":"401 Brookside Ave Wilmington DE 19805",
    "addr:housenumber":"401",
    "addr:postcode":"19805",
    "addr:street":"Brookside Ave",
    "iso:country":"US",
    "sg:address":"401 Brookside Ave",
    "sg:city":"Wilmington",
    "sg:classifiers":[
        {
            "category":"Manufacturing",
            "subcategory":"Metals",
            "type":"Manufacturing & Wholesale Goods"
        }
    ],
    "sg:phone":"+1 302 994 8660",
    "sg:postcode":"19805",
    "sg:province":"DE",
    "sg:tags":[
        "steel"
    ],
    "wof:name":"Churchmen's Machine Co Inc",
    "wof:placetype":"venue"
},
  "geometry": {"coordinates":[-75.607542,39.733301],"type":"Point"}
}