{
  "type": "Feature",
  "properties": {
    "addr:full":"75 Marrows Rd Newark DE 19713",
    "addr:housenumber":"75",
    "addr:postcode":"19713",
    "addr:street":"Marrows Rd",
    "iso:country":"US",
    "sg:address":"75 Marrows Rd",
    "sg:city":"Newark",
    "sg:classifiers":[
        {
            "category":"Food & Beverages",
            "subcategory":"Liquor & Beverages",
            "type":"Retail Goods"
        }
    ],
    "sg:phone":"+1 302 737 9725",
    "sg:postcode":"19713",
    "sg:province":"DE",
    "sg:tags":[
        "alcoholic"
    ],
    "wof:name":"Brookside Liquor Mart",
    "wof:placetype":"venue"
},
  "geometry": {"coordinates":[-75.726783,39.663218],"type":"Point"}
}