{
  "type": "Feature",
  "properties": {
    "iso:country":"US",
    "sg:address":"5 Bunker Hill Rd",
    "sg:city":"New Castle",
    "sg:classifiers":[
        {
            "category":"Personal",
            "type":"Services"
        }
    ],
    "sg:phone":"+1 302 395 9488",
    "sg:postcode":"19720",
    "sg:province":"DE",
    "wof:name":"Ernest Kortvely",
    "wof:placetype":"venue"
},
  "geometry": {"coordinates":[-75.58999,39.674824],"type":"Point"}
}