{
  "type": "Feature",
  "properties": {
    "iso:country":"US",
    "sg:address":"650 Naamans Rd",
    "sg:city":"Claymont",
    "sg:classifiers":[
        {
            "category":"Real Estate",
            "subcategory":"Developer",
            "type":"Services"
        }
    ],
    "sg:phone":"+1 302 798 8300",
    "sg:postcode":"19703",
    "sg:province":"DE",
    "sg:tags":[
        "commercial"
    ],
    "wof:name":"Del Commons Assoc Ltd Partnr",
    "wof:placetype":"venue"
},
  "geometry": {"coordinates":[-75.45678100000001,39.816337],"type":"Point"}
}