{
  "type": "Feature",
  "properties": {
    "iso:country":"US",
    "sg:address":"811 Norman Eskridge Hwy",
    "sg:city":"Seaford",
    "sg:classifiers":[
        {
            "category":"Personal",
            "subcategory":"Beauty Salon",
            "type":"Services"
        }
    ],
    "sg:phone":"+1 302 628 2889",
    "sg:postcode":"19973",
    "sg:province":"DE",
    "sg:tags":[
        "manicuring"
    ],
    "wof:name":"Tori's Nail",
    "wof:placetype":"venue"
},
  "geometry": {"coordinates":[-75.601068,38.650681],"type":"Point"}
}