{
  "type": "Feature",
  "properties": {
    "iso:country":"US",
    "sg:address":"223 E Main St",
    "sg:city":"Newark",
    "sg:classifiers":[
        {
            "category":"Restaurant",
            "type":"Food & Drink"
        }
    ],
    "sg:menulink":"http://www.allmenus.com/de/greater-newark/20277-primos-hoagies/menu/",
    "sg:phone":"+1 302 368 7746",
    "sg:postcode":"19711",
    "sg:province":"DE",
    "sg:tags":[
        "american",
        "sandwich",
        "hoagy",
        "italian"
    ],
    "wof:name":"Primos Hoagies",
    "wof:placetype":"venue"
},
  "geometry": {"coordinates":[-75.744598,39.683699],"type":"Point"}
}