{
  "type": "Feature",
  "properties": {
    "addr:full":"824 N Market St Wilmington DE 19802",
    "addr:housenumber":"824",
    "addr:postcode":"19802",
    "addr:street":"N Market St",
    "iso:country":"US",
    "sg:address":"824 N Market St",
    "sg:city":"Wilmington",
    "sg:classifiers":[
        {
            "category":"Professional",
            "subcategory":"Lawyer & Legal Services",
            "type":"Services"
        }
    ],
    "sg:phone":"+1 302 654 7444",
    "sg:postcode":"19802",
    "sg:province":"DE",
    "wof:name":"Agostini Levitsky and Issacs",
    "wof:placetype":"venue"
},
  "geometry": {"coordinates":[-75.548543,39.744326],"type":"Point"}
}