{
  "type": "Feature",
  "properties": {
    "addr:full":"119 Dalwin Dr Dover DE 19901",
    "addr:housenumber":"119",
    "addr:postcode":"19901",
    "addr:street":"Dalwin Dr",
    "iso:country":"US",
    "sg:address":"119 Dalwin Dr",
    "sg:city":"Dover",
    "sg:classifiers":[
        {
            "category":"Professional",
            "subcategory":"Business Services",
            "type":"Services"
        }
    ],
    "sg:phone":"+1 302 697 9415",
    "sg:postcode":"19901",
    "sg:province":"DE",
    "wof:name":"Emerald Isle Entertainmen",
    "wof:placetype":"venue"
},
  "geometry": {"coordinates":[-75.523999,39.122787],"type":"Point"}
}