{
  "type": "Feature",
  "properties": {
    "addr:full":"2313 Ogletown Rd Newark DE 19711",
    "addr:housenumber":"2313",
    "addr:postcode":"19711",
    "addr:street":"Ogletown Rd",
    "iso:country":"US",
    "sg:address":"2313 Ogletown Rd",
    "sg:city":"Newark",
    "sg:classifiers":[
        {
            "category":"Professional",
            "type":"Services"
        }
    ],
    "sg:phone":"+1 302 731 9929",
    "sg:postcode":"19711",
    "sg:province":"DE",
    "wof:name":"First World Studios",
    "wof:placetype":"venue"
},
  "geometry": {"coordinates":[-75.723157,39.684946],"type":"Point"}
}