{
  "type": "Feature",
  "properties": {
    "addr:full":"29 Big Mill Branch Seaford DE 19973",
    "addr:housenumber":"29",
    "addr:postcode":"19973",
    "addr:street":"Big Mill Branch",
    "iso:country":"US",
    "sg:address":"29 Big Mill Branch",
    "sg:city":"Seaford",
    "sg:classifiers":[
        {
            "category":"Retail",
            "subcategory":"Car Wash",
            "type":"Services"
        }
    ],
    "sg:phone":"+1 302 632 8372",
    "sg:postcode":"19973",
    "sg:province":"DE",
    "sg:tags":[
        "carwash"
    ],
    "wof:name":"Jesus Washes Auto Detailing",
    "wof:placetype":"venue"
},
  "geometry": {"coordinates":[-75.543858,38.621206],"type":"Point"}
}