{
  "type": "Feature",
  "properties": {
    "addr:full":"1526 Savannah Rd Lewes DE 19958",
    "addr:housenumber":"1526",
    "addr:postcode":"19958",
    "addr:street":"Savannah Rd",
    "iso:country":"US",
    "sg:address":"1526 Savannah Rd",
    "sg:city":"Lewes",
    "sg:classifiers":[
        {
            "category":"Health Services",
            "subcategory":"Doctor",
            "type":"Services"
        }
    ],
    "sg:phone":"+1 302 645 1806",
    "sg:postcode":"19958",
    "sg:province":"DE",
    "sg:tags":[
        "medical"
    ],
    "wof:name":"Bhaskar S Palekar MD PA",
    "wof:placetype":"venue"
},
  "geometry": {"coordinates":[-75.158689,38.756062],"type":"Point"}
}