{
  "type": "Feature",
  "properties": {
    "iso:country":"US",
    "sg:address":"232 E Glenwood Ave",
    "sg:city":"Smyrna",
    "sg:classifiers":[
        {
            "category":"Wholesale",
            "subcategory":"Non-durable Goods",
            "type":"Manufacturing & Wholesale Goods"
        }
    ],
    "sg:phone":"+1 302 653 8384",
    "sg:postcode":"19977",
    "sg:province":"DE",
    "sg:tags":[
        "advertising"
    ],
    "wof:name":"RWM Promotional Advertising",
    "wof:placetype":"venue"
},
  "geometry": {"coordinates":[-75.60755399999999,39.30576],"type":"Point"}
}