{
  "type": "Feature",
  "properties": {
    "iso:country":"US",
    "sg:address":"480 Bank Ln",
    "sg:city":"Dover",
    "sg:classifiers":[
        {
            "category":"Government",
            "subcategory":"Court House",
            "type":"Public Place"
        }
    ],
    "sg:phone":"+1 302 739 4554",
    "sg:postcode":"19904",
    "sg:province":"DE",
    "sg:tags":[
        "state"
    ],
    "wof:name":"Justice Of The Peace Courts",
    "wof:placetype":"venue"
},
  "geometry": {"coordinates":[-75.530457,39.154563],"type":"Point"}
}