{
  "type": "Feature",
  "properties": {
    "addr:full":"212 S Woodward Ave Wilmington DE 19805",
    "addr:housenumber":"212",
    "addr:postcode":"19805",
    "addr:street":"S Woodward Ave",
    "iso:country":"US",
    "sg:address":"212 S Woodward Ave",
    "sg:city":"Wilmington",
    "sg:classifiers":[
        {
            "category":"Building & Trades",
            "subcategory":"Construction",
            "type":"Services"
        }
    ],
    "sg:phone":"+1 302 999 8235",
    "sg:postcode":"19805",
    "sg:province":"DE",
    "sg:tags":[
        "house"
    ],
    "wof:name":"Greenamoyer Construction Inc",
    "wof:placetype":"venue"
},
  "geometry": {"coordinates":[-75.614777,39.734335],"type":"Point"}
}