{
  "type": "Feature",
  "properties": {
    "addr:full":"820 N French St Ste 3 Wilmington DE 19801",
    "addr:housenumber":"820",
    "addr:postcode":"19801",
    "addr:street":"N French St Ste 3",
    "iso:country":"US",
    "sg:address":"820 N French St Ste 3",
    "sg:city":"Wilmington",
    "sg:classifiers":[
        {
            "category":"Professional",
            "subcategory":"Management & Consulting",
            "type":"Services"
        },
        {
            "category":"Government",
            "subcategory":"Office",
            "type":"Public Place"
        }
    ],
    "sg:phone":"+1 302 577 5210",
    "sg:postcode":"19801",
    "sg:province":"DE",
    "sg:tags":[
        "government-state",
        "beverage",
        "food",
        "consultant"
    ],
    "wof:name":"Safety And Homeland Security Department Of Delaware",
    "wof:placetype":"venue"
},
  "geometry": {"coordinates":[-75.546843,39.743603],"type":"Point"}
}