{
  "type": "Feature",
  "properties": {
    "iso:country":"US",
    "sg:address":"101 Boyer Dr",
    "sg:city":"Newark",
    "sg:classifiers":[
        {
            "category":"Professional",
            "type":"Services"
        }
    ],
    "sg:phone":"+1 302 266 9051",
    "sg:postcode":"19702",
    "sg:province":"DE",
    "wof:name":"Murray Jeannette Sister",
    "wof:placetype":"venue"
},
  "geometry": {"coordinates":[-75.701278,39.640783],"type":"Point"}
}