{
  "type": "Feature",
  "properties": {
    "iso:country":"US",
    "sg:address":"413 S Heald St",
    "sg:city":"Wilmington",
    "sg:classifiers":[
        {
            "category":"Organizations",
            "subcategory":"Religious Organization",
            "type":"Services"
        }
    ],
    "sg:phone":"+1 302 658 3997",
    "sg:postcode":"19801",
    "sg:province":"DE",
    "sg:tags":[
        "church"
    ],
    "wof:name":"Harrison Memorial Baptist Chr",
    "wof:placetype":"venue"
},
  "geometry": {"coordinates":[-75.543915,39.729305],"type":"Point"}
}