{
  "type": "Feature",
  "properties": {
    "iso:country":"US",
    "sg:address":"1815 W 13th St",
    "sg:city":"Wilmington",
    "sg:classifiers":[
        {
            "category":"Health Services",
            "subcategory":"Hospital",
            "type":"Services"
        },
        {
            "category":"Health Services",
            "subcategory":"Doctor",
            "type":"Services"
        }
    ],
    "sg:phone":"+1 302 892 2100",
    "sg:postcode":"19806",
    "sg:province":"DE",
    "sg:tags":[
        "physician",
        "surgeon",
        "general"
    ],
    "wof:name":"Delaware Surgical Group",
    "wof:placetype":"venue"
},
  "geometry": {"coordinates":[-75.566333,39.756519],"type":"Point"}
}