{
  "type": "Feature",
  "properties": {
    "iso:country":"US",
    "sg:address":"1416 Rising Sun Rd",
    "sg:city":"Camden Wyoming",
    "sg:classifiers":[
        {
            "category":"Shopping",
            "subcategory":"Bicycles & Sporting Goods",
            "type":"Retail Goods"
        }
    ],
    "sg:phone":"+1 302 698 1171",
    "sg:postcode":"19934",
    "sg:province":"DE",
    "sg:tags":[
        "equipment",
        "archery",
        "supply"
    ],
    "wof:name":"Eagle Eye Archery",
    "wof:placetype":"venue"
},
  "geometry": {"coordinates":[-75.514583,39.099428],"type":"Point"}
}