{
  "type": "Feature",
  "properties": {
    "addr:full":"16 Polly Drummond Shpg Center Newark DE 19711",
    "addr:housenumber":"16",
    "addr:postcode":"19711",
    "addr:street":"Polly Drummond Shpg Center",
    "iso:country":"US",
    "sg:address":"16 Polly Drummond Shpg Center",
    "sg:city":"Newark",
    "sg:classifiers":[
        {
            "category":"Manufacturing",
            "subcategory":"Textiles",
            "type":"Manufacturing & Wholesale Goods"
        }
    ],
    "sg:phone":"+1 302 453 8130",
    "sg:postcode":"19711",
    "sg:province":"DE",
    "sg:tags":[
        "knitting",
        "mills"
    ],
    "wof:name":"Stitches With Style",
    "wof:placetype":"venue"
},
  "geometry": {"coordinates":[-75.711313,39.719054],"type":"Point"}
}