{
  "type": "Feature",
  "properties": {
    "addr:full":"28 Lakewood Cir Newark DE 19711",
    "addr:housenumber":"28",
    "addr:postcode":"19711",
    "addr:street":"Lakewood Cir",
    "iso:country":"US",
    "sg:address":"28 Lakewood Cir",
    "sg:city":"Newark",
    "sg:classifiers":[
        {
            "category":"Restaurant",
            "type":"Food & Drink"
        }
    ],
    "sg:phone":"+1 302 234 3923",
    "sg:postcode":"19711",
    "sg:province":"DE",
    "wof:name":"Everyday Gourmet",
    "wof:placetype":"venue"
},
  "geometry": {"coordinates":[-75.74654,39.759541],"type":"Point"}
}