{
  "type": "Feature",
  "properties": {
    "iso:country":"US",
    "sg:address":"1010 Concord Ave",
    "sg:city":"Wilmington",
    "sg:classifiers":[
        {
            "category":"Building & Trades",
            "subcategory":"Construction",
            "type":"Services"
        }
    ],
    "sg:phone":"+1 302 888 2313",
    "sg:postcode":"19802",
    "sg:province":"DE",
    "sg:tags":[
        "general",
        "contractor"
    ],
    "wof:name":"Michael Marinelli Construction",
    "wof:placetype":"venue"
},
  "geometry": {"coordinates":[-75.542811,39.764476],"type":"Point"}
}