{
  "type": "Feature",
  "properties": {
    "iso:country":"US",
    "sg:address":"30986 Sussex Hwy",
    "sg:city":"Laurel",
    "sg:classifiers":[
        {
            "category":"Autos & Motor Vehicles",
            "subcategory":"Fuel & Gas Station",
            "type":"Retail Goods"
        },
        {
            "category":"Retail",
            "subcategory":"Auto Repair",
            "type":"Services"
        }
    ],
    "sg:phone":"+1 302 875 5674",
    "sg:postcode":"19956",
    "sg:province":"DE",
    "sg:tags":[
        "automotive",
        "tune"
    ],
    "sg:website":"http://www.napaautocare.com/",
    "wof:name":"Carey's Inc",
    "wof:placetype":"venue"
},
  "geometry": {"coordinates":[-75.556387,38.555452],"type":"Point"}
}