{
  "type": "Feature",
  "properties": {
    "iso:country":"US",
    "sg:address":"4 Meteor Ln",
    "sg:city":"Newark",
    "sg:classifiers":[
        {
            "category":"Building & Trades",
            "subcategory":"Construction",
            "type":"Services"
        }
    ],
    "sg:phone":"+1 302 239 1133",
    "sg:postcode":"19711",
    "sg:province":"DE",
    "sg:tags":[
        "excavation",
        "contractor"
    ],
    "wof:name":"Kevin Kelly Excavating",
    "wof:placetype":"venue"
},
  "geometry": {"coordinates":[-75.713455,39.757555],"type":"Point"}
}