{
  "type": "Feature",
  "properties": {
    "addr:full":"5701 Kirkwood Hwy Wilmington DE 19808",
    "addr:housenumber":"5701",
    "addr:postcode":"19808",
    "addr:street":"Kirkwood Hwy",
    "iso:country":"US",
    "sg:address":"5701 Kirkwood Hwy",
    "sg:city":"Wilmington",
    "sg:classifiers":[
        {
            "category":"Manufacturing",
            "subcategory":"Glass & Minerals",
            "type":"Manufacturing & Wholesale Goods"
        }
    ],
    "sg:phone":"+1 302 994 3806",
    "sg:postcode":"19808",
    "sg:province":"DE",
    "sg:tags":[
        "burial",
        "mfg",
        "cement",
        "concrete",
        "tombstone",
        "vault",
        "brick",
        "prod",
        "block"
    ],
    "wof:name":"Cecil Vault & Memorial Co Inc",
    "wof:placetype":"venue"
},
  "geometry": {"coordinates":[-75.67315600000001,39.71591],"type":"Point"}
}