{
  "type": "Feature",
  "properties": {
    "iso:country":"US",
    "sg:address":"2409 Silverside Rd",
    "sg:city":"Wilmington",
    "sg:classifiers":[
        {
            "category":"Building & Trades",
            "subcategory":"Electrical",
            "type":"Services"
        }
    ],
    "sg:phone":"+1 302 475 4859",
    "sg:postcode":"19810",
    "sg:province":"DE",
    "sg:tags":[
        "electrical",
        "contractor"
    ],
    "wof:name":"Wood Electric",
    "wof:placetype":"venue"
},
  "geometry": {"coordinates":[-75.51503,39.808193],"type":"Point"}
}