{
  "type": "Feature",
  "properties": {
    "iso:country":"US",
    "sg:address":"103 Foulk Rd Ste 202",
    "sg:city":"Wilmington",
    "sg:classifiers":[
        {
            "category":"Professional",
            "subcategory":"Business Services",
            "type":"Services"
        }
    ],
    "sg:phone":"+1 302 691 6091",
    "sg:postcode":"19803",
    "sg:province":"DE",
    "sg:tags":[
        "holding"
    ],
    "sg:website":"http://www.sca.com",
    "wof:name":"Dorma Group North America Inc",
    "wof:placetype":"venue"
},
  "geometry": {"coordinates":[-75.544777,39.780041],"type":"Point"}
}