{
  "type": "Feature",
  "properties": {
    "iso:country":"US",
    "sg:address":"838 Walker Rd",
    "sg:city":"Dover",
    "sg:classifiers":[
        {
            "category":"Professional",
            "subcategory":"Accounting & Tax Preparation",
            "type":"Services"
        }
    ],
    "sg:phone":"+1 302 734 1850",
    "sg:postcode":"19904",
    "sg:province":"DE",
    "sg:tags":[
        "return"
    ],
    "wof:name":"Slacum & Doyle Tax Service LLC",
    "wof:placetype":"venue"
},
  "geometry": {"coordinates":[-75.544571,39.169722],"type":"Point"}
}