{
  "type": "Feature",
  "properties": {
    "iso:country":"US",
    "sg:address":"7 Plover Ct",
    "sg:city":"Wilmington",
    "sg:classifiers":[
        {
            "category":"Organizations",
            "subcategory":"Religious Organization",
            "type":"Services"
        }
    ],
    "sg:phone":"+1 302 995 1561",
    "sg:postcode":"19808",
    "sg:province":"DE",
    "wof:name":"Carl N Kunz Jr Rev",
    "wof:placetype":"venue"
},
  "geometry": {"coordinates":[-75.628584,39.750358],"type":"Point"}
}