{
  "type": "Feature",
  "properties": {
    "iso:country":"US",
    "sg:address":"60 Leader Dr",
    "sg:city":"Newark",
    "sg:classifiers":[
        {
            "category":"Retail",
            "subcategory":"Repair Shop",
            "type":"Services"
        }
    ],
    "sg:phone":"+1 302 738 3440",
    "sg:postcode":"19713",
    "sg:province":"DE",
    "wof:name":"Salvatore Mannino Plumbing",
    "wof:placetype":"venue"
},
  "geometry": {"coordinates":[-75.719104,39.679908],"type":"Point"}
}