{
  "type": "Feature",
  "properties": {
    "iso:country":"US",
    "sg:address":"1601 Milltown Rd",
    "sg:city":"Wilmington",
    "sg:classifiers":[
        {
            "category":"Professional",
            "subcategory":"Lawyer & Legal Services",
            "type":"Services"
        }
    ],
    "sg:phone":"+1 302 998 9400",
    "sg:postcode":"19808",
    "sg:province":"DE",
    "sg:tags":[
        "attorney"
    ],
    "wof:name":"E Alan Uebler",
    "wof:placetype":"venue"
},
  "geometry": {"coordinates":[-75.669051,39.729147],"type":"Point"}
}