{
  "type": "Feature",
  "properties": {
    "iso:country":"US",
    "sg:address":"2601 Annand Dr",
    "sg:city":"Wilmington",
    "sg:classifiers":[
        {
            "category":"Health Services",
            "subcategory":"Doctor",
            "type":"Services"
        }
    ],
    "sg:phone":"+1 302 998 8283",
    "sg:postcode":"19808",
    "sg:province":"DE",
    "wof:name":"Jeanette Y Son Dentist",
    "wof:placetype":"venue"
},
  "geometry": {"coordinates":[-75.675416,39.715683],"type":"Point"}
}