{
  "type": "Feature",
  "properties": {
    "addr:full":"201 N Main St Smyrna DE 19977",
    "addr:housenumber":"201",
    "addr:postcode":"19977",
    "addr:street":"N Main St",
    "iso:country":"US",
    "sg:address":"201 N Main St",
    "sg:city":"Smyrna",
    "sg:classifiers":[
        {
            "category":"Health Services",
            "subcategory":"Health Practitioner",
            "type":"Services"
        }
    ],
    "sg:phone":"+1 302 659 2977",
    "sg:postcode":"19977",
    "sg:province":"DE",
    "sg:tags":[
        "therapist",
        "physical"
    ],
    "wof:name":"Excel Physical Therapy Smyrna",
    "wof:placetype":"venue"
},
  "geometry": {"coordinates":[-75.61027199999999,39.303513],"type":"Point"}
}