{
  "type": "Feature",
  "properties": {
    "iso:country":"US",
    "sg:address":"278 Sorghum Mill Rd",
    "sg:city":"Dover",
    "sg:classifiers":[
        {
            "category":"Building & Trades",
            "subcategory":"Construction",
            "type":"Services"
        }
    ],
    "sg:phone":"+1 302 698 1678",
    "sg:postcode":"19901",
    "sg:province":"DE",
    "sg:tags":[
        "general",
        "contractor"
    ],
    "wof:name":"BMC & Assoc LLC",
    "wof:placetype":"venue"
},
  "geometry": {"coordinates":[-75.512424,39.102222],"type":"Point"}
}