{
  "type": "Feature",
  "properties": {
    "addr:full":"1601 Milltown Rd Wilmington DE 19808",
    "addr:housenumber":"1601",
    "addr:postcode":"19808",
    "addr:street":"Milltown Rd",
    "iso:country":"US",
    "sg:address":"1601 Milltown Rd",
    "sg:city":"Wilmington",
    "sg:classifiers":[
        {
            "category":"Professional",
            "subcategory":"Credit Reporting & Collection",
            "type":"Services"
        }
    ],
    "sg:phone":"+1 302 992 9385",
    "sg:postcode":"19808",
    "sg:province":"DE",
    "wof:name":"Cachequest System",
    "wof:placetype":"venue"
},
  "geometry": {"coordinates":[-75.669051,39.729147],"type":"Point"}
}