{
  "type": "Feature",
  "properties": {
    "iso:country":"US",
    "sg:address":"4 River Woods Dr",
    "sg:city":"Wilmington",
    "sg:classifiers":[
        {
            "category":"Professional",
            "subcategory":"Management & Consulting",
            "type":"Services"
        }
    ],
    "sg:phone":"+1 302 275 3278",
    "sg:postcode":"19809",
    "sg:province":"DE",
    "sg:tags":[
        "business"
    ],
    "wof:name":"Protection Group LLC",
    "wof:placetype":"venue"
},
  "geometry": {"coordinates":[-75.489627,39.768273],"type":"Point"}
}