{
  "type": "Feature",
  "properties": {
    "iso:country":"US",
    "sg:address":"3301 Concord Pike",
    "sg:city":"Wilmington",
    "sg:classifiers":[
        {
            "category":"Wholesale",
            "subcategory":"Stationery",
            "type":"Manufacturing & Wholesale Goods"
        }
    ],
    "sg:phone":"+1 302 479 0877",
    "sg:postcode":"19803",
    "sg:province":"DE",
    "sg:tags":[
        "packaging",
        "material"
    ],
    "wof:name":"Concord Packaging Co",
    "wof:placetype":"venue"
},
  "geometry": {"coordinates":[-75.54807099999999,39.801826],"type":"Point"}
}