{
  "type": "Feature",
  "properties": {
    "iso:country":"US",
    "sg:address":"5931 W Denneys Rd",
    "sg:city":"Dover",
    "sg:classifiers":[
        {
            "category":"Autos & Motor Vehicles",
            "subcategory":"Auto Supplies",
            "type":"Retail Goods"
        }
    ],
    "sg:phone":"+1 302 734 8463",
    "sg:postcode":"19901",
    "sg:province":"DE",
    "sg:tags":[
        "alternator",
        "generator"
    ],
    "wof:name":"James Evans Svc",
    "wof:placetype":"venue"
},
  "geometry": {"coordinates":[-75.558688,39.202637],"type":"Point"}
}