{
  "type": "Feature",
  "properties": {
    "iso:country":"US",
    "sg:address":"3003 Silverside Rd",
    "sg:city":"Wilmington",
    "sg:classifiers":[
        {
            "category":"Education",
            "subcategory":"Preschool",
            "type":"Public Place"
        },
        {
            "category":"Education",
            "subcategory":"School",
            "type":"Public Place"
        }
    ],
    "sg:phone":"+1 302 478 3876",
    "sg:postcode":"19810",
    "sg:province":"DE",
    "sg:tags":[
        "elementary"
    ],
    "wof:name":"Concordia Preschool",
    "wof:placetype":"venue"
},
  "geometry": {"coordinates":[-75.526901,39.810699],"type":"Point"}
}