{
  "type": "Feature",
  "properties": {
    "iso:country":"US",
    "sg:address":"1420 Deer Antler Rd",
    "sg:city":"Clayton",
    "sg:classifiers":[
        {
            "category":"Social Services",
            "subcategory":"Child Care",
            "type":"Services"
        }
    ],
    "sg:phone":"+1 302 653 3666",
    "sg:postcode":"19938",
    "sg:province":"DE",
    "sg:tags":[
        "day"
    ],
    "wof:name":"Karens Daycare",
    "wof:placetype":"venue"
},
  "geometry": {"coordinates":[-75.692059,39.287606],"type":"Point"}
}