{
  "type": "Feature",
  "properties": {
    "iso:country":"US",
    "sg:address":"150 Saulsbury Rd",
    "sg:city":"Dover",
    "sg:classifiers":[
        {
            "category":"Social Services",
            "subcategory":"Job Training",
            "type":"Services"
        }
    ],
    "sg:phone":"+1 302 672 7732",
    "sg:postcode":"19904",
    "sg:province":"DE",
    "sg:tags":[
        "rehabilitation"
    ],
    "wof:name":"Weston Rehab Group",
    "wof:placetype":"venue"
},
  "geometry": {"coordinates":[-75.543814,39.161548],"type":"Point"}
}