{
  "type": "Feature",
  "properties": {
    "addr:full":"115 Warwick Dr Wilmington DE 19803",
    "addr:housenumber":"115",
    "addr:postcode":"19803",
    "addr:street":"Warwick Dr",
    "iso:country":"US",
    "sg:address":"115 Warwick Dr",
    "sg:city":"Wilmington",
    "sg:classifiers":[
        {
            "category":"Professional",
            "subcategory":"Management & Consulting",
            "type":"Services"
        }
    ],
    "sg:phone":"+1 302 479 7855",
    "sg:postcode":"19803",
    "sg:province":"DE",
    "sg:tags":[
        "business"
    ],
    "wof:name":"KAW Consulting",
    "wof:placetype":"venue"
},
  "geometry": {"coordinates":[-75.528199,39.801871],"type":"Point"}
}