{
  "type": "Feature",
  "properties": {
    "iso:country":"US",
    "sg:address":"10079 Middleford Rd",
    "sg:city":"Seaford",
    "sg:classifiers":[
        {
            "category":"Social Services",
            "subcategory":"Child Care",
            "type":"Services"
        }
    ],
    "sg:phone":"+1 302 628 1158",
    "sg:postcode":"19973",
    "sg:province":"DE",
    "sg:tags":[
        "day"
    ],
    "wof:name":"Bettys Day Care",
    "wof:placetype":"venue"
},
  "geometry": {"coordinates":[-75.569093,38.664622],"type":"Point"}
}