{
  "type": "Feature",
  "properties": {
    "iso:country":"US",
    "sg:address":"1010 N Bancroft Pkwy # 101",
    "sg:city":"Wilmington",
    "sg:classifiers":[
        {
            "category":"Health Services",
            "subcategory":"Doctor",
            "type":"Services"
        },
        {
            "category":"Health Services",
            "subcategory":"Dentist",
            "type":"Services"
        }
    ],
    "sg:phone":"+1 302 472 5555",
    "sg:postcode":"19805",
    "sg:province":"DE",
    "sg:tags":[
        "physician",
        "radiology",
        "laboratories-medical",
        "dental",
        "pediatrics-radiology",
        "surgeons",
        "x-ray"
    ],
    "sg:website":"http://www.mriandimaging.com",
    "wof:name":"Bancroft Pkwy Open Mri & Imgng",
    "wof:placetype":"venue"
},
  "geometry": {"coordinates":[-75.57138,39.755532],"type":"Point"}
}