{
  "type": "Feature",
  "properties": {
    "iso:country":"US",
    "sg:address":"18 Cunard St",
    "sg:city":"Wilmington",
    "sg:classifiers":[
        {
            "category":"Building & Trades",
            "subcategory":"Construction",
            "type":"Services"
        }
    ],
    "sg:phone":"+1 302 633 6595",
    "sg:postcode":"19804",
    "sg:province":"DE",
    "sg:tags":[
        "house"
    ],
    "wof:name":"All In One Construction Svc",
    "wof:placetype":"venue"
},
  "geometry": {"coordinates":[-75.62039300000001,39.724433],"type":"Point"}
}