{
  "type": "Feature",
  "properties": {
    "iso:country":"US",
    "sg:address":"410 Geddes St",
    "sg:city":"Wilmington",
    "sg:classifiers":[
        {
            "category":"Professional",
            "type":"Services"
        }
    ],
    "sg:phone":"+1 302 428 1316",
    "sg:postcode":"19805",
    "sg:province":"DE",
    "wof:name":"Data Bid Service",
    "wof:placetype":"venue"
},
  "geometry": {"coordinates":[-75.577787,39.743642],"type":"Point"}
}