{
  "type": "Feature",
  "properties": {
    "iso:country":"US",
    "sg:address":"3200 Limestone Rd",
    "sg:city":"Wilmington",
    "sg:classifiers":[
        {
            "category":"Retail",
            "subcategory":"Funeral Services",
            "type":"Services"
        }
    ],
    "sg:phone":"+1 302 999 8277",
    "sg:postcode":"19808",
    "sg:province":"DE",
    "sg:tags":[
        "director"
    ],
    "wof:name":"Doherty Funeral Homes",
    "wof:placetype":"venue"
},
  "geometry": {"coordinates":[-75.672787,39.733519],"type":"Point"}
}