{
  "type": "Feature",
  "properties": {
    "iso:country":"US",
    "sg:address":"1 Walnut Ln",
    "sg:city":"Selbyville",
    "sg:classifiers":[
        {
            "category":"Professional",
            "type":"Services"
        }
    ],
    "sg:phone":"+1 302 436 1718",
    "sg:postcode":"19975",
    "sg:province":"DE",
    "wof:name":"David Grant Ch Family",
    "wof:placetype":"venue"
},
  "geometry": {"coordinates":[-75.09014500000001,38.462368],"type":"Point"}
}