{
  "type": "Feature",
  "properties": {
    "iso:country":"US",
    "sg:address":"9126 Redden Rd",
    "sg:city":"Bridgeville",
    "sg:classifiers":[
        {
            "category":"Wholesale",
            "subcategory":"Motor Vehicles",
            "type":"Manufacturing & Wholesale Goods"
        }
    ],
    "sg:phone":"+1 302 337 7400",
    "sg:postcode":"19933",
    "sg:province":"DE",
    "sg:tags":[
        "trailer"
    ],
    "sg:website":"www.utilitykeystone.com",
    "wof:name":"Utility Eastern Shore Trailer",
    "wof:placetype":"venue"
},
  "geometry": {"coordinates":[-75.590046,38.748502],"type":"Point"}
}