{
  "type": "Feature",
  "properties": {
    "iso:country":"US",
    "sg:address":"2751 Centerville Rd",
    "sg:city":"Wilmington",
    "sg:classifiers":[
        {
            "category":"Professional",
            "subcategory":"Business Services",
            "type":"Services"
        }
    ],
    "sg:phone":"+1 302 504 0400",
    "sg:postcode":"19808",
    "sg:province":"DE",
    "sg:tags":[
        "marketing",
        "consulting",
        "program",
        "design"
    ],
    "wof:name":"Paragonrx LLC",
    "wof:placetype":"venue"
},
  "geometry": {"coordinates":[-75.624624,39.753755],"type":"Point"}
}