{
  "type": "Feature",
  "properties": {
    "iso:country":"US",
    "sg:address":"40 Atkins Ave",
    "sg:city":"Wilmington",
    "sg:classifiers":[
        {
            "category":"Professional",
            "subcategory":"Art Services",
            "type":"Services"
        }
    ],
    "sg:phone":"+1 302 425 5112",
    "sg:postcode":"19805",
    "sg:province":"DE",
    "sg:tags":[
        "commercial",
        "design"
    ],
    "wof:name":"F X Anim",
    "wof:placetype":"venue"
},
  "geometry": {"coordinates":[-75.587237,39.750697],"type":"Point"}
}