{
  "type": "Feature",
  "properties": {
    "iso:country":"US",
    "sg:address":"5136 S Dupont Pkwy",
    "sg:city":"Smyrna",
    "sg:classifiers":[
        {
            "category":"Autos & Motor Vehicles",
            "subcategory":"Recreational Vehicle Sales",
            "type":"Retail Goods"
        }
    ],
    "sg:phone":"+1 302 653 5804",
    "sg:postcode":"19977",
    "sg:province":"DE",
    "wof:name":"Parkview Rv Ctr North",
    "wof:placetype":"venue"
},
  "geometry": {"coordinates":[-75.63134700000001,39.337866],"type":"Point"}
}