{
  "type": "Feature",
  "properties": {
    "addr:full":"213 E 2nd St Seaford DE 19973",
    "addr:housenumber":"213",
    "addr:postcode":"19973",
    "addr:street":"E 2Nd St",
    "iso:country":"US",
    "sg:address":"213 E 2nd St",
    "sg:city":"Seaford",
    "sg:classifiers":[
        {
            "category":"Freight",
            "type":"Transportation"
        }
    ],
    "sg:phone":"+1 302 629 9399",
    "sg:postcode":"19973",
    "sg:province":"DE",
    "sg:tags":[
        "broker"
    ],
    "wof:name":"Frontier Transportation",
    "wof:placetype":"venue"
},
  "geometry": {"coordinates":[-75.603615,38.635793],"type":"Point"}
}