{
  "type": "Feature",
  "properties": {
    "addr:full":"502 Ivydale Rd Wilmington DE 19803",
    "addr:housenumber":"502",
    "addr:postcode":"19803",
    "addr:street":"Ivydale Rd",
    "iso:country":"US",
    "sg:address":"502 Ivydale Rd",
    "sg:city":"Wilmington",
    "sg:classifiers":[
        {
            "category":"Arts & Performance",
            "subcategory":"Theater",
            "type":"Entertainment"
        }
    ],
    "sg:phone":"+1 302 764 8477",
    "sg:postcode":"19803",
    "sg:province":"DE",
    "sg:tags":[
        "theatrical",
        "bureau"
    ],
    "wof:name":"Yankee Doodle Boys LLC",
    "wof:placetype":"venue"
},
  "geometry": {"coordinates":[-75.49999800000001,39.787006],"type":"Point"}
}