{
  "type": "Feature",
  "properties": {
    "iso:country":"US",
    "sg:address":"2523 Bona Rd",
    "sg:city":"Wilmington",
    "sg:classifiers":[
        {
            "category":"Professional",
            "subcategory":"Accounting & Tax Preparation",
            "type":"Services"
        }
    ],
    "sg:phone":"+1 302 478 4734",
    "sg:postcode":"19810",
    "sg:province":"DE",
    "sg:tags":[
        "auditing",
        "bookkeeping"
    ],
    "wof:name":"Martin Zukoff CPA",
    "wof:placetype":"venue"
},
  "geometry": {"coordinates":[-75.524461,39.82219],"type":"Point"}
}