{
  "type": "Feature",
  "properties": {
    "addr:full":"2214 Bear Corbitt Rd Bear DE 19701",
    "addr:housenumber":"2214",
    "addr:postcode":"19701",
    "addr:street":"Bear Corbitt Rd",
    "iso:country":"US",
    "sg:address":"2214 Bear Corbitt Rd",
    "sg:city":"Bear",
    "sg:classifiers":[
        {
            "category":"Autos & Motor Vehicles",
            "subcategory":"Automobile Sales",
            "type":"Retail Goods"
        }
    ],
    "sg:phone":"+1 302 834 4114",
    "sg:postcode":"19701",
    "sg:province":"DE",
    "sg:tags":[
        "used"
    ],
    "wof:name":"Bear Auto Sales",
    "wof:placetype":"venue"
},
  "geometry": {"coordinates":[-75.662481,39.596841],"type":"Point"}
}