{
  "type": "Feature",
  "properties": {
    "addr:full":"1300 Pennsylvania Ave Wilmington DE 19806",
    "addr:housenumber":"1300",
    "addr:postcode":"19806",
    "addr:street":"Pennsylvania Ave",
    "iso:country":"US",
    "sg:address":"1300 Pennsylvania Ave",
    "sg:city":"Wilmington",
    "sg:classifiers":[
        {
            "category":"Professional",
            "subcategory":"Advertising",
            "type":"Services"
        }
    ],
    "sg:phone":"+1 302 652 3051",
    "sg:postcode":"19806",
    "sg:province":"DE",
    "sg:tags":[
        "counselor"
    ],
    "sg:website":"www.shipleyassociates.com",
    "wof:name":"Shipley Associates Inc",
    "wof:placetype":"venue"
},
  "geometry": {"coordinates":[-75.559946,39.753401],"type":"Point"}
}