{
  "type": "Feature",
  "properties": {
    "addr:full":"1400 B St Wilmington DE 19801",
    "addr:housenumber":"1400",
    "addr:postcode":"19801",
    "addr:street":"B St",
    "iso:country":"US",
    "sg:address":"1400 B St",
    "sg:city":"Wilmington",
    "sg:classifiers":[
        {
            "category":"Professional",
            "subcategory":"Business Services",
            "type":"Services"
        }
    ],
    "sg:phone":"+1 302 326 1500",
    "sg:postcode":"19801",
    "sg:province":"DE",
    "sg:tags":[
        "packaging"
    ],
    "wof:name":"Pack & Process Inc",
    "wof:placetype":"venue"
},
  "geometry": {"coordinates":[-75.54118699999999,39.727931],"type":"Point"}
}