{
  "type": "Feature",
  "properties": {
    "iso:country":"US",
    "sg:address":"415 W Loockerman St",
    "sg:city":"Dover",
    "sg:classifiers":[
        {
            "category":"Restaurant",
            "type":"Food & Drink"
        }
    ],
    "sg:phone":"+1 302 736 1073",
    "sg:postcode":"19904",
    "sg:province":"DE",
    "sg:tags":[
        "pizza"
    ],
    "wof:name":"Simaron Pizza & Steak Shop",
    "wof:placetype":"venue"
},
  "geometry": {"coordinates":[-75.529594,39.15734],"type":"Point"}
}