{
  "type": "Feature",
  "properties": {
    "iso:country":"US",
    "sg:address":"3315 Coachman Rd",
    "sg:city":"Wilmington",
    "sg:classifiers":[
        {
            "category":"Building & Trades",
            "subcategory":"Construction",
            "type":"Services"
        }
    ],
    "sg:phone":"+1 302 479 5353",
    "sg:postcode":"19803",
    "sg:province":"DE",
    "sg:tags":[
        "house",
        "contractor"
    ],
    "wof:name":"Concrete Service Co",
    "wof:placetype":"venue"
},
  "geometry": {"coordinates":[-75.53209099999999,39.80291],"type":"Point"}
}