{
  "type": "Feature",
  "properties": {
    "iso:country":"US",
    "sg:address":"23 Possum Hollow Rd",
    "sg:city":"Newark",
    "sg:classifiers":[
        {
            "category":"Building & Trades",
            "subcategory":"Construction",
            "type":"Services"
        }
    ],
    "sg:phone":"+1 302 738 1891",
    "sg:postcode":"19711",
    "sg:province":"DE",
    "sg:tags":[
        "general",
        "contractor"
    ],
    "wof:name":"J A R Construction Inc",
    "wof:placetype":"venue"
},
  "geometry": {"coordinates":[-75.727583,39.71482],"type":"Point"}
}