{
  "type": "Feature",
  "properties": {
    "iso:country":"US",
    "sg:address":"1365 N Dupont Hwy",
    "sg:city":"Dover",
    "sg:classifiers":[
        {
            "category":"Shopping",
            "subcategory":"Jewelry",
            "type":"Retail Goods"
        }
    ],
    "sg:phone":"+1 302 857 3809",
    "sg:postcode":"19901",
    "sg:province":"DE",
    "sg:tags":[
        "jeweler"
    ],
    "wof:name":"Gordon's Jewelers",
    "wof:placetype":"venue"
},
  "geometry": {"coordinates":[-75.543187,39.191395],"type":"Point"}
}