{
  "type": "Feature",
  "properties": {
    "addr:full":"2413 N Broom St Wilmington DE 19802",
    "addr:housenumber":"2413",
    "addr:postcode":"19802",
    "addr:street":"N Broom St",
    "iso:country":"US",
    "sg:address":"2413 N Broom St",
    "sg:city":"Wilmington",
    "sg:classifiers":[
        {
            "category":"Professional",
            "type":"Services"
        }
    ],
    "sg:phone":"+1 302 656 7154",
    "sg:postcode":"19802",
    "sg:province":"DE",
    "wof:name":"Samuel Selma Barshay",
    "wof:placetype":"venue"
},
  "geometry": {"coordinates":[-75.543628,39.762943],"type":"Point"}
}