{
  "type": "Feature",
  "properties": {
    "iso:country":"US",
    "sg:address":"26 Parkway Cir",
    "sg:city":"New Castle",
    "sg:classifiers":[
        {
            "category":"Government",
            "subcategory":"Jail",
            "type":"Public Place"
        },
        {
            "category":"Social Services",
            "type":"Services"
        }
    ],
    "sg:phone":"+1 302 323 6050",
    "sg:postcode":"19720",
    "sg:province":"DE",
    "sg:tags":[
        "probation",
        "correctional",
        "institution"
    ],
    "wof:name":"Probation & Parole Dept",
    "wof:placetype":"venue"
},
  "geometry": {"coordinates":[-75.613343,39.662325],"type":"Point"}
}