{
  "type": "Feature",
  "properties": {
    "iso:country":"US",
    "sg:address":"115 5th St",
    "sg:city":"Delaware City",
    "sg:classifiers":[
        {
            "category":"Retail",
            "subcategory":"Auto Rental",
            "type":"Services"
        }
    ],
    "sg:phone":"+1 302 834 6902",
    "sg:postcode":"19706",
    "sg:province":"DE",
    "sg:tags":[
        "mobile",
        "home",
        "leasing"
    ],
    "wof:name":"Delaware City Mobile Home Park",
    "wof:placetype":"venue"
},
  "geometry": {"coordinates":[-75.590734,39.570353],"type":"Point"}
}