{
  "type": "Feature",
  "properties": {
    "iso:country":"US",
    "sg:address":"520 E Savannah Rd",
    "sg:city":"Lewes",
    "sg:classifiers":[
        {
            "category":"Manufacturing",
            "subcategory":"Wood Products",
            "type":"Manufacturing & Wholesale Goods"
        }
    ],
    "sg:phone":"+1 302 645 0551",
    "sg:postcode":"19958",
    "sg:province":"DE",
    "sg:tags":[
        "merchandise",
        "mfg"
    ],
    "wof:name":"Peninsula Gallery",
    "wof:placetype":"venue"
},
  "geometry": {"coordinates":[-75.137028,38.776432],"type":"Point"}
}