{
  "type": "Feature",
  "properties": {
    "iso:country":"US",
    "sg:address":"208 N Persimmon St",
    "sg:city":"Millsboro",
    "sg:classifiers":[
        {
            "category":"Wholesale",
            "subcategory":"Construction Materials",
            "type":"Manufacturing & Wholesale Goods"
        }
    ],
    "sg:phone":"+1 302 645 7420",
    "sg:postcode":"19966",
    "sg:province":"DE",
    "wof:name":"Edwards Mobile Home Service",
    "wof:placetype":"venue"
},
  "geometry": {"coordinates":[-75.129814,38.631921],"type":"Point"}
}