{
  "type": "Feature",
  "properties": {
    "iso:country":"US",
    "sg:address":"503 Lakewood Dr",
    "sg:city":"Milford",
    "sg:classifiers":[
        {
            "category":"Retail",
            "subcategory":"Car Wash",
            "type":"Services"
        }
    ],
    "sg:phone":"+1 302 270 8492",
    "sg:postcode":"19963",
    "sg:province":"DE",
    "sg:tags":[
        "automotive",
        "detailing"
    ],
    "wof:name":"Xtreme Graphix",
    "wof:placetype":"venue"
},
  "geometry": {"coordinates":[-75.455485,38.906518],"type":"Point"}
}