{
  "type": "Feature",
  "properties": {
    "iso:country":"US",
    "sg:address":"11 Sunnyside Rd",
    "sg:city":"Wilmington",
    "sg:classifiers":[
        {
            "category":"Building & Trades",
            "subcategory":"Construction",
            "type":"Services"
        }
    ],
    "sg:phone":"+1 302 656 1314",
    "sg:postcode":"19807",
    "sg:province":"DE",
    "sg:tags":[
        "home",
        "builder"
    ],
    "wof:name":"Homes By Cornerstone",
    "wof:placetype":"venue"
},
  "geometry": {"coordinates":[-75.597585,39.786099],"type":"Point"}
}