{
  "type": "Feature",
  "properties": {
    "iso:country":"US",
    "sg:address":"3 Arbor Dr",
    "sg:city":"Dover",
    "sg:classifiers":[
        {
            "category":"Organizations",
            "subcategory":"Religious Organization",
            "type":"Services"
        }
    ],
    "sg:phone":"+1 302 730 0773",
    "sg:postcode":"19904",
    "sg:province":"DE",
    "sg:tags":[
        "clergy"
    ],
    "wof:name":"Ralph A Ellis",
    "wof:placetype":"venue"
},
  "geometry": {"coordinates":[-75.56988800000001,39.166086],"type":"Point"}
}