{
  "type": "Feature",
  "properties": {
    "iso:country":"US",
    "sg:address":"5158 S Dupont Hwy",
    "sg:city":"Dover",
    "sg:classifiers":[
        {
            "category":"Insurance",
            "subcategory":"Insurance Agent",
            "type":"Services"
        }
    ],
    "sg:phone":"+1 302 698 4159",
    "sg:postcode":"19901",
    "sg:province":"DE",
    "wof:name":"Farm Family",
    "wof:placetype":"venue"
},
  "geometry": {"coordinates":[-75.550326,39.085993],"type":"Point"}
}