{
  "type": "Feature",
  "properties": {
    "iso:country":"US",
    "sg:address":"809 N Tatnall St",
    "sg:city":"Wilmington",
    "sg:classifiers":[
        {
            "category":"Retail",
            "subcategory":"Laundry & Dry Cleaning",
            "type":"Services"
        }
    ],
    "sg:phone":"+1 302 655 0673",
    "sg:postcode":"19801",
    "sg:province":"DE",
    "sg:tags":[
        "coin"
    ],
    "wof:name":"Paul Cheung Laundry",
    "wof:placetype":"venue"
},
  "geometry": {"coordinates":[-75.550777,39.745603],"type":"Point"}
}