{
  "type": "Feature",
  "properties": {
    "iso:country":"US",
    "sg:address":"703 E King St",
    "sg:city":"Seaford",
    "sg:classifiers":[
        {
            "category":"Social Services",
            "subcategory":"Child Care",
            "type":"Services"
        }
    ],
    "sg:phone":"+1 302 629 3225",
    "sg:postcode":"19973",
    "sg:province":"DE",
    "sg:tags":[
        "day"
    ],
    "wof:name":"Small Wonders Child Care Inc",
    "wof:placetype":"venue"
},
  "geometry": {"coordinates":[-75.607147,38.64334],"type":"Point"}
}