{
  "type": "Feature",
  "properties": {
    "addr:full":"1201 Savannah Rd Lewes DE 19958",
    "addr:housenumber":"1201",
    "addr:postcode":"19958",
    "addr:street":"Savannah Rd",
    "iso:country":"US",
    "sg:address":"1201 Savannah Rd",
    "sg:city":"Lewes",
    "sg:classifiers":[
        {
            "category":"Shopping",
            "subcategory":"Optical Goods",
            "type":"Retail Goods"
        }
    ],
    "sg:phone":"+1 302 945 1800",
    "sg:postcode":"19958",
    "sg:province":"DE",
    "wof:name":"Vision Centre Ltd",
    "wof:placetype":"venue"
},
  "geometry": {"coordinates":[-75.152788,38.761433],"type":"Point"}
}