{
  "type": "Feature",
  "properties": {
    "addr:full":"625 Smyrna Clayton Blvd Smyrna DE 19977",
    "addr:housenumber":"625",
    "addr:postcode":"19977",
    "addr:street":"Smyrna Clayton Blvd",
    "iso:country":"US",
    "sg:address":"625 Smyrna Clayton Blvd",
    "sg:city":"Smyrna",
    "sg:classifiers":[
        {
            "category":"Food & Beverages",
            "subcategory":"Liquor & Beverages",
            "type":"Retail Goods"
        }
    ],
    "sg:phone":"+1 302 653 6220",
    "sg:postcode":"19977",
    "sg:province":"DE",
    "wof:name":"Spruance City Liquors",
    "wof:placetype":"venue"
},
  "geometry": {"coordinates":[-75.616393,39.295674],"type":"Point"}
}