{
  "type": "Feature",
  "properties": {
    "iso:country":"US",
    "sg:address":"133 Westminster Dr",
    "sg:city":"Dover",
    "sg:classifiers":[
        {
            "category":"Professional",
            "type":"Services"
        }
    ],
    "sg:phone":"+1 302 736 1435",
    "sg:postcode":"19904",
    "sg:province":"DE",
    "wof:name":"Lloyd Witmer Col",
    "wof:placetype":"venue"
},
  "geometry": {"coordinates":[-75.55186500000001,39.176709],"type":"Point"}
}