{
  "type": "Feature",
  "properties": {
    "iso:country":"US",
    "sg:address":"2212 Lido Ln",
    "sg:city":"Wilmington",
    "sg:classifiers":[
        {
            "category":"Building & Trades",
            "subcategory":"Construction",
            "type":"Services"
        }
    ],
    "sg:phone":"+1 302 475 4762",
    "sg:postcode":"19810",
    "sg:province":"DE",
    "sg:tags":[
        "residential"
    ],
    "wof:name":"Ralph E Marcozzi",
    "wof:placetype":"venue"
},
  "geometry": {"coordinates":[-75.499869,39.811613],"type":"Point"}
}