{
  "type": "Feature",
  "properties": {
    "iso:country":"US",
    "sg:address":"734 Naamans Rd",
    "sg:city":"Claymont",
    "sg:classifiers":[
        {
            "category":"Building & Trades",
            "subcategory":"Landscaping Services",
            "type":"Services"
        }
    ],
    "sg:phone":"+1 302 792 0878",
    "sg:postcode":"19703",
    "sg:province":"DE",
    "sg:tags":[
        "landscape",
        "contractor"
    ],
    "wof:name":"Sunburst Landscape Co",
    "wof:placetype":"venue"
},
  "geometry": {"coordinates":[-75.460802,39.817717],"type":"Point"}
}