{
  "type": "Feature",
  "properties": {
    "iso:country":"US",
    "sg:address":"4737 Concord Pike",
    "sg:city":"Wilmington",
    "sg:classifiers":[
        {
            "category":"Shopping",
            "subcategory":"Shoes",
            "type":"Retail Goods"
        }
    ],
    "sg:phone":"+1 302 479 7535",
    "sg:postcode":"19803",
    "sg:province":"DE",
    "wof:name":"Payless Shoe Source",
    "wof:placetype":"venue"
},
  "geometry": {"coordinates":[-75.54853199999999,39.818338],"type":"Point"}
}