{
  "type": "Feature",
  "properties": {
    "iso:country":"US",
    "sg:address":"282 Quigley Blvd",
    "sg:city":"New Castle",
    "sg:classifiers":[
        {
            "category":"Wholesale",
            "subcategory":"Electrical",
            "type":"Manufacturing & Wholesale Goods"
        }
    ],
    "sg:phone":"+1 302 322 5401",
    "sg:postcode":"19720",
    "sg:province":"DE",
    "sg:tags":[
        "electronic",
        "parts",
        "component"
    ],
    "wof:name":"Electronics Exchange Corp",
    "wof:placetype":"venue"
},
  "geometry": {"coordinates":[-75.598085,39.659556],"type":"Point"}
}