{
  "type": "Feature",
  "properties": {
    "addr:full":"1013 Norman Eskridge Hwy Seaford DE 19973",
    "addr:housenumber":"1013",
    "addr:postcode":"19973",
    "addr:street":"Norman Eskridge Hwy",
    "iso:country":"US",
    "sg:address":"1013 Norman Eskridge Hwy",
    "sg:city":"Seaford",
    "sg:classifiers":[
        {
            "category":"Recreation",
            "subcategory":"Marina",
            "type":"Entertainment"
        }
    ],
    "sg:phone":"+1 302 629 0710",
    "sg:postcode":"19973",
    "sg:province":"DE",
    "sg:tags":[
        "operation"
    ],
    "wof:name":"Seaford Self Storage Inc",
    "wof:placetype":"venue"
},
  "geometry": {"coordinates":[-75.597902,38.65234],"type":"Point"}
}