{
  "type": "Feature",
  "properties": {
    "addr:full":"411 Prospect Ave Wilmington DE 19803",
    "addr:housenumber":"411",
    "addr:postcode":"19803",
    "addr:street":"Prospect Ave",
    "iso:country":"US",
    "sg:address":"411 Prospect Ave",
    "sg:city":"Wilmington",
    "sg:classifiers":[
        {
            "category":"Real Estate",
            "subcategory":"Real Estate Services",
            "type":"Services"
        }
    ],
    "sg:phone":"+1 302 478 1781",
    "sg:postcode":"19803",
    "sg:province":"DE",
    "wof:name":"Apsley Steven H Real Estate",
    "wof:placetype":"venue"
},
  "geometry": {"coordinates":[-75.543098,39.805099],"type":"Point"}
}