{
  "type": "Feature",
  "properties": {
    "iso:country":"US",
    "sg:address":"400 Mill St",
    "sg:city":"Bridgeville",
    "sg:classifiers":[
        {
            "category":"Social Services",
            "type":"Services"
        }
    ],
    "sg:phone":"+1 302 856 5350",
    "sg:postcode":"19933",
    "sg:province":"DE",
    "sg:tags":[
        "administrative"
    ],
    "wof:name":"Bridgeville State Services",
    "wof:placetype":"venue"
},
  "geometry": {"coordinates":[-75.60560599999999,38.743249],"type":"Point"}
}