{
  "type": "Feature",
  "properties": {
    "iso:country":"US",
    "sg:address":"1266 Sophers Row",
    "sg:city":"Magnolia",
    "sg:classifiers":[
        {
            "category":"Utilities",
            "subcategory":"Telephone",
            "type":"Services"
        },
        {
            "category":"Professional",
            "subcategory":"Business Services",
            "type":"Services"
        }
    ],
    "sg:phone":"+1 302 335 5730",
    "sg:postcode":"19962",
    "sg:province":"DE",
    "sg:tags":[
        "communications",
        "voice",
        "mail",
        "messaging"
    ],
    "wof:name":"Yoon's Martial Arts",
    "wof:placetype":"venue"
},
  "geometry": {"coordinates":[-75.475835,39.055548],"type":"Point"}
}