{
  "type": "Feature",
  "properties": {
    "addr:full":"4000 Concord Pike Wilmington DE 19803",
    "addr:housenumber":"4000",
    "addr:postcode":"19803",
    "addr:street":"Concord Pike",
    "iso:country":"US",
    "sg:address":"4000 Concord Pike",
    "sg:city":"Wilmington",
    "sg:classifiers":[
        {
            "category":"Professional",
            "type":"Services"
        }
    ],
    "sg:phone":"+1 302 478 3756",
    "sg:postcode":"19803",
    "sg:province":"DE",
    "wof:name":"Airrover Networks",
    "wof:placetype":"venue"
},
  "geometry": {"coordinates":[-75.549211,39.809205],"type":"Point"}
}