{
  "type": "Feature",
  "properties": {
    "addr:full":"530 S Dual Hwy Seaford DE 19973",
    "addr:housenumber":"530",
    "addr:postcode":"19973",
    "addr:street":"S Dual Hwy",
    "iso:country":"US",
    "sg:address":"530 S Dual Hwy",
    "sg:city":"Seaford",
    "sg:classifiers":[
        {
            "category":"Organizations",
            "subcategory":"Religious Organization",
            "type":"Services"
        }
    ],
    "sg:phone":"+1 302 629 9511",
    "sg:postcode":"19973",
    "sg:province":"DE",
    "wof:name":"Emmanuel Full Gospel",
    "wof:placetype":"venue"
},
  "geometry": {"coordinates":[-75.592877,38.63598],"type":"Point"}
}