{
  "type": "Feature",
  "properties": {
    "iso:country":"US",
    "sg:address":"1166 S Bay Rd",
    "sg:city":"Dover",
    "sg:classifiers":[
        {
            "category":"Retail",
            "subcategory":"Auto Rental",
            "type":"Services"
        }
    ],
    "sg:phone":"+1 302 678 0700",
    "sg:postcode":"19901",
    "sg:province":"DE",
    "sg:tags":[
        "truck",
        "rent",
        "operates"
    ],
    "wof:name":"J D Automotive",
    "wof:placetype":"venue"
},
  "geometry": {"coordinates":[-75.495789,39.138649],"type":"Point"}
}