{
  "type": "Feature",
  "properties": {
    "iso:country":"US",
    "sg:address":"2431 Pulaski Hwy ",
    "sg:city":"Newark",
    "sg:classifiers":[
        {
            "category":"Restaurant",
            "type":"Food & Drink"
        }
    ],
    "sg:menulink":"http://www.allmenus.com/de/central-pencader/81435-papa-johns-pizza/menu/",
    "sg:phone":"+1 302 738 2600",
    "sg:postcode":"19702",
    "sg:province":"DE",
    "sg:tags":[
        "american",
        "pizza"
    ],
    "wof:name":"Papa John's Pizza",
    "wof:placetype":"venue"
},
  "geometry": {"coordinates":[-75.74647299999999,39.605847],"type":"Point"}
}