{
  "type": "Feature",
  "properties": {
    "iso:country":"US",
    "sg:address":"1248 Capitol Trl",
    "sg:city":"Newark",
    "sg:classifiers":[
        {
            "category":"Retail",
            "subcategory":"Self-service Laundry",
            "type":"Services"
        }
    ],
    "sg:phone":"+1 302 266 9515",
    "sg:postcode":"19711",
    "sg:province":"DE",
    "sg:tags":[
        "coin"
    ],
    "wof:name":"Red Mill Laundromat",
    "wof:placetype":"venue"
},
  "geometry": {"coordinates":[-75.709532,39.697671],"type":"Point"}
}