{
  "type": "Feature",
  "properties": {
    "iso:country":"US",
    "sg:address":"198 Fairhill Dr",
    "sg:city":"Wilmington",
    "sg:classifiers":[
        {
            "category":"Professional",
            "subcategory":"Advertising",
            "type":"Services"
        }
    ],
    "sg:phone":"+1 302 235 1111",
    "sg:postcode":"19808",
    "sg:province":"DE",
    "sg:tags":[
        "mail",
        "mailing",
        "direct",
        "shipping"
    ],
    "wof:name":"Direct Mailing Service Inc",
    "wof:placetype":"venue"
},
  "geometry": {"coordinates":[-75.684551,39.754945],"type":"Point"}
}