{
  "type": "Feature",
  "properties": {
    "iso:country":"US",
    "sg:address":"1301 S State St",
    "sg:city":"Dover",
    "sg:classifiers":[
        {
            "category":"Home & Garden",
            "subcategory":"Building Materials",
            "type":"Retail Goods"
        },
        {
            "category":"Building & Trades",
            "subcategory":"Construction",
            "type":"Services"
        }
    ],
    "sg:phone":"+1 302 734 4446",
    "sg:postcode":"19901",
    "sg:province":"DE",
    "sg:tags":[
        "fence-sales",
        "fence",
        "contractor"
    ],
    "sg:website":"http://www.tocfencing.com",
    "wof:name":"Touch Of Class Fencing Of Delaware Inc.",
    "wof:placetype":"venue"
},
  "geometry": {"coordinates":[-75.522881,39.139999],"type":"Point"}
}