{
  "type": "Feature",
  "properties": {
    "iso:country":"US",
    "sg:address":"109 S John St",
    "sg:city":"Newport",
    "sg:classifiers":[
        {
            "category":"Manufacturing",
            "subcategory":"Metals",
            "type":"Manufacturing & Wholesale Goods"
        },
        {
            "category":"Building & Trades",
            "subcategory":"Construction",
            "type":"Services"
        }
    ],
    "sg:phone":"+1 302 998 2892",
    "sg:postcode":"19804",
    "sg:province":"DE",
    "sg:tags":[
        "installs",
        "fence"
    ],
    "wof:name":"Pioneer Fence Co Inc",
    "wof:placetype":"venue"
},
  "geometry": {"coordinates":[-75.610488,39.712048],"type":"Point"}
}