{
  "type": "Feature",
  "properties": {
    "iso:country":"US",
    "sg:address":"17507 S Dupont Hwy",
    "sg:city":"Harrington",
    "sg:classifiers":[
        {
            "category":"Manufacturing",
            "subcategory":"Paper Products",
            "type":"Manufacturing & Wholesale Goods"
        }
    ],
    "sg:phone":"+1 302 398 4211",
    "sg:postcode":"19952",
    "sg:province":"DE",
    "sg:tags":[
        "box"
    ],
    "sg:website":"www.templeinland.com",
    "wof:name":"Color-Box",
    "wof:placetype":"venue"
},
  "geometry": {"coordinates":[-75.56787,38.920271],"type":"Point"}
}