{
  "type": "Feature",
  "properties": {
    "iso:country":"US",
    "sg:address":"252 Greenview Dr",
    "sg:city":"Dover",
    "sg:classifiers":[
        {
            "category":"Building & Trades",
            "subcategory":"Construction",
            "type":"Services"
        }
    ],
    "sg:phone":"+1 302 697 9385",
    "sg:postcode":"19901",
    "sg:province":"DE",
    "sg:tags":[
        "contractor"
    ],
    "wof:name":"J & J Custom Builders Corp",
    "wof:placetype":"venue"
},
  "geometry": {"coordinates":[-75.5261,39.115799],"type":"Point"}
}