{
  "type": "Feature",
  "properties": {
    "iso:country":"US",
    "sg:address":"218 E Dupont Hwy",
    "sg:city":"Millsboro",
    "sg:classifiers":[
        {
            "category":"Professional",
            "subcategory":"Accounting & Tax Preparation",
            "type":"Services"
        }
    ],
    "sg:phone":"+1 302 934 6688",
    "sg:postcode":"19966",
    "sg:province":"DE",
    "sg:tags":[
        "accountant"
    ],
    "wof:name":"Robert M Hoyt & Co",
    "wof:placetype":"venue"
},
  "geometry": {"coordinates":[-75.291523,38.580823],"type":"Point"}
}