{
  "type": "Feature",
  "properties": {
    "iso:country":"US",
    "sg:address":"5 Co Rd 100",
    "sg:city":"Milford",
    "sg:classifiers":[
        {
            "category":"Real Estate",
            "subcategory":"Real Estate Operator",
            "type":"Services"
        }
    ],
    "sg:phone":"+1 302 422 0740",
    "sg:postcode":"19904",
    "sg:province":"DE",
    "sg:tags":[
        "apartment"
    ],
    "wof:name":"Silver Lake Estates Apartments",
    "wof:placetype":"venue"
},
  "geometry": {"coordinates":[-75.646642,39.172859],"type":"Point"}
}