{
  "type": "Feature",
  "properties": {
    "addr:full":"2216 Pennsylvania Ave Wilmington DE 19806",
    "addr:housenumber":"2216",
    "addr:postcode":"19806",
    "addr:street":"Pennsylvania Ave",
    "iso:country":"US",
    "sg:address":"2216 Pennsylvania Ave",
    "sg:city":"Wilmington",
    "sg:classifiers":[
        {
            "category":"Restaurant",
            "type":"Food & Drink"
        }
    ],
    "sg:phone":"+1 302 571 1492",
    "sg:postcode":"19806",
    "sg:province":"DE",
    "sg:tags":[
        "drinking",
        "eating"
    ],
    "sg:website":"www.columbusinn.com",
    "wof:name":"Columbus Inn",
    "wof:placetype":"venue"
},
  "geometry": {"coordinates":[-75.571349,39.758022],"type":"Point"}
}