{
  "type": "Feature",
  "properties": {
    "iso:country":"US",
    "sg:address":"12 Woodsway Rd",
    "sg:city":"Wilmington",
    "sg:classifiers":[
        {
            "category":"Building & Trades",
            "subcategory":"Construction",
            "type":"Services"
        }
    ],
    "sg:phone":"+1 302 791 7712",
    "sg:postcode":"19809",
    "sg:province":"DE",
    "sg:tags":[
        "house"
    ],
    "wof:name":"Sterling Builders",
    "wof:placetype":"venue"
},
  "geometry": {"coordinates":[-75.48378200000001,39.777652],"type":"Point"}
}