{
  "type": "Feature",
  "properties": {
    "iso:country":"US",
    "sg:address":"3 New Castle St",
    "sg:city":"Rehoboth Beach",
    "sg:classifiers":[
        {
            "category":"Health Services",
            "subcategory":"Doctor",
            "type":"Services"
        }
    ],
    "sg:phone":"+1 302 227 7271",
    "sg:postcode":"19971",
    "sg:province":"DE",
    "sg:tags":[
        "medical"
    ],
    "wof:name":"Frederick Goodwin Dr",
    "wof:placetype":"venue"
},
  "geometry": {"coordinates":[-75.07598299999999,38.711854],"type":"Point"}
}