{
  "type": "Feature",
  "properties": {
    "addr:full":"1 Moonwalker Rd Frederica DE 19946",
    "addr:housenumber":"1",
    "addr:postcode":"19946",
    "addr:street":"Moonwalker Rd",
    "iso:country":"US",
    "sg:address":"1 Moonwalker Rd",
    "sg:city":"Frederica",
    "sg:classifiers":[
        {
            "category":"Wholesale",
            "subcategory":"Durable Goods & Equipment",
            "type":"Manufacturing & Wholesale Goods"
        }
    ],
    "sg:phone":"+1 302 335 3911",
    "sg:postcode":"19946",
    "sg:province":"DE",
    "sg:tags":[
        "importer"
    ],
    "sg:website":"www.ilcdover.com",
    "wof:name":"ILC Dover Inc",
    "wof:placetype":"venue"
},
  "geometry": {"coordinates":[-75.488705,39.004208],"type":"Point"}
}