{
  "type": "Feature",
  "properties": {
    "addr:full":"927 S Chapel St Newark DE 19713",
    "addr:housenumber":"927",
    "addr:postcode":"19713",
    "addr:street":"S Chapel St",
    "iso:country":"US",
    "sg:address":"927 S Chapel St",
    "sg:city":"Newark",
    "sg:classifiers":[
        {
            "category":"Food & Beverages",
            "subcategory":"Groceries & Convenience Stores",
            "type":"Retail Goods"
        }
    ],
    "sg:phone":"+1 302 369 0690",
    "sg:postcode":"19713",
    "sg:province":"DE",
    "wof:name":"Dollar Land",
    "wof:placetype":"venue"
},
  "geometry": {"coordinates":[-75.734881,39.657888],"type":"Point"}
}