{
  "type": "Feature",
  "properties": {
    "addr:full":"29 Watergate Cir Selbyville DE 19975",
    "addr:housenumber":"29",
    "addr:postcode":"19975",
    "addr:street":"Watergate Cir",
    "iso:country":"US",
    "sg:address":"29 Watergate Cir",
    "sg:city":"Selbyville",
    "sg:classifiers":[
        {
            "category":"Professional",
            "subcategory":"Engineering",
            "type":"Services"
        }
    ],
    "sg:phone":"+1 302 436 2418",
    "sg:postcode":"19975",
    "sg:province":"DE",
    "sg:tags":[
        "consulting",
        "engineer"
    ],
    "wof:name":"Krh & Associates Inc",
    "wof:placetype":"venue"
},
  "geometry": {"coordinates":[-75.128917,38.453035],"type":"Point"}
}