{
  "type": "Feature",
  "properties": {
    "iso:country":"US",
    "sg:address":"85 Tidewaters",
    "sg:city":"Rehoboth Beach",
    "sg:classifiers":[
        {
            "category":"Health Services",
            "subcategory":"Doctor",
            "type":"Services"
        }
    ],
    "sg:phone":"+1 302 227 3051",
    "sg:postcode":"19971",
    "sg:province":"DE",
    "sg:tags":[
        "medical"
    ],
    "wof:name":"David Ehrenfeld Dr",
    "wof:placetype":"venue"
},
  "geometry": {"coordinates":[-75.085476,38.727228],"type":"Point"}
}