{
  "type": "Feature",
  "properties": {
    "iso:country":"US",
    "sg:address":"24994 Betts Ln",
    "sg:city":"Georgetown",
    "sg:classifiers":[
        {
            "category":"Wholesale",
            "subcategory":"Hardware",
            "type":"Manufacturing & Wholesale Goods"
        }
    ],
    "sg:phone":"+1 302 856 4330",
    "sg:postcode":"19947",
    "sg:province":"DE",
    "wof:name":"Rw Heating & Air Inc",
    "wof:placetype":"venue"
},
  "geometry": {"coordinates":[-75.35856699999999,38.645047],"type":"Point"}
}