{
  "type": "Feature",
  "properties": {
    "addr:full":"15 Boulden Cir New Castle DE 19720",
    "addr:housenumber":"15",
    "addr:postcode":"19720",
    "addr:street":"Boulden Cir",
    "iso:country":"US",
    "sg:address":"15 Boulden Cir",
    "sg:city":"New Castle",
    "sg:classifiers":[
        {
            "category":"Retail",
            "subcategory":"Auto Rental",
            "type":"Services"
        }
    ],
    "sg:phone":"+1 302 326 9300",
    "sg:postcode":"19720",
    "sg:province":"DE",
    "sg:tags":[
        "renting",
        "truck",
        "leasing"
    ],
    "wof:name":"Budget Truck Rental",
    "wof:placetype":"venue"
},
  "geometry": {"coordinates":[-75.573543,39.688978],"type":"Point"}
}