{
  "type": "Feature",
  "properties": {
    "iso:country":"US",
    "sg:address":"1661 S Dupont Hwy",
    "sg:city":"Dover",
    "sg:classifiers":[
        {
            "category":"Building & Trades",
            "subcategory":"Plumbing",
            "type":"Services"
        }
    ],
    "sg:phone":"+1 302 734 4311",
    "sg:postcode":"19901",
    "sg:province":"DE",
    "sg:tags":[
        "heating",
        "contractor"
    ],
    "wof:name":"Associates Contracting",
    "wof:placetype":"venue"
},
  "geometry": {"coordinates":[-75.52950300000001,39.129501],"type":"Point"}
}