{
  "type": "Feature",
  "properties": {
    "addr:full":"50 Garfield Ave Garfield DE 19720",
    "addr:housenumber":"50",
    "addr:postcode":"19720",
    "addr:street":"Garfield Ave",
    "iso:country":"US",
    "sg:address":"50 Garfield Ave",
    "sg:city":"Garfield",
    "sg:classifiers":[
        {
            "category":"Utilities",
            "subcategory":"Refuse",
            "type":"Services"
        }
    ],
    "sg:phone":"+1 973 641 9422",
    "sg:postcode":"19720",
    "sg:province":"DE",
    "sg:tags":[
        "garbage",
        "collection"
    ],
    "wof:name":"M & M Cleanout & Demoliton",
    "wof:placetype":"venue"
},
  "geometry": {"coordinates":[-75.58869,39.684643],"type":"Point"}
}