{
  "type": "Feature",
  "properties": {
    "addr:full":"49 Bancroft Mill Rd Wilmington DE 19806",
    "addr:housenumber":"49",
    "addr:postcode":"19806",
    "addr:street":"Bancroft Mill Rd",
    "iso:country":"US",
    "sg:address":"49 Bancroft Mill Rd",
    "sg:city":"Wilmington",
    "sg:classifiers":[
        {
            "category":"Real Estate",
            "subcategory":"Real Estate Operator",
            "type":"Services"
        }
    ],
    "sg:phone":"+1 302 654 9252",
    "sg:postcode":"19806",
    "sg:province":"DE",
    "sg:tags":[
        "apartment",
        "complex",
        "condominium"
    ],
    "wof:name":"Bancroft Mills Apartments",
    "wof:placetype":"venue"
},
  "geometry": {"coordinates":[-75.56470400000001,39.768587],"type":"Point"}
}