{
  "type": "Feature",
  "properties": {
    "iso:country":"US",
    "sg:address":"411 Valley Rd",
    "sg:city":"Newark",
    "sg:classifiers":[
        {
            "category":"Shopping",
            "subcategory":"Gifts & Souvenirs",
            "type":"Retail Goods"
        }
    ],
    "sg:phone":"+1 302 737 1039",
    "sg:postcode":"19711",
    "sg:province":"DE",
    "wof:name":"We Are Family Gift Boutique",
    "wof:placetype":"venue"
},
  "geometry": {"coordinates":[-75.78736499999999,39.683113],"type":"Point"}
}