{
  "type": "Feature",
  "properties": {
    "iso:country":"US",
    "sg:address":"2631 Creekwood Cir",
    "sg:city":"Millsboro",
    "sg:classifiers":[
        {
            "category":"Home & Garden",
            "subcategory":"Building Materials",
            "type":"Retail Goods"
        }
    ],
    "sg:phone":"+1 302 945 1005",
    "sg:postcode":"19966",
    "sg:province":"DE",
    "wof:name":"New Dimension Homes",
    "wof:placetype":"venue"
},
  "geometry": {"coordinates":[-75.169337,38.626951],"type":"Point"}
}