{
  "type": "Feature",
  "properties": {
    "addr:full":"209 W Laurel St Georgetown DE 19947",
    "addr:housenumber":"209",
    "addr:postcode":"19947",
    "addr:street":"W Laurel St",
    "iso:country":"US",
    "sg:address":"209 W Laurel St",
    "sg:city":"Georgetown",
    "sg:classifiers":[
        {
            "category":"Building & Trades",
            "subcategory":"Construction",
            "type":"Services"
        }
    ],
    "sg:phone":"+1 302 856 3832",
    "sg:postcode":"19947",
    "sg:province":"DE",
    "sg:tags":[
        "hanging",
        "contractor"
    ],
    "wof:name":"Layton Painting Al",
    "wof:placetype":"venue"
},
  "geometry": {"coordinates":[-75.390546,38.688043],"type":"Point"}
}