{
  "type": "Feature",
  "properties": {
    "iso:country":"US",
    "sg:address":"220 Mercury Rd",
    "sg:city":"Newark",
    "sg:classifiers":[
        {
            "category":"Real Estate",
            "subcategory":"Real Estate Services",
            "type":"Services"
        },
        {
            "category":"Real Estate",
            "subcategory":"Real Estate Agent",
            "type":"Services"
        }
    ],
    "sg:phone":"+1 302 239 4317",
    "sg:postcode":"19711",
    "sg:province":"DE",
    "sg:tags":[
        "management"
    ],
    "wof:name":"Hendrix",
    "wof:placetype":"venue"
},
  "geometry": {"coordinates":[-75.71470600000001,39.76017],"type":"Point"}
}