{
  "type": "Feature",
  "properties": {
    "addr:full":"3 Halsey Dr Wilmington DE 19807",
    "addr:housenumber":"3",
    "addr:postcode":"19807",
    "addr:street":"Halsey Dr",
    "iso:country":"US",
    "sg:address":"3 Halsey Dr",
    "sg:city":"Wilmington",
    "sg:classifiers":[
        {
            "category":"Professional",
            "type":"Services"
        }
    ],
    "sg:phone":"+1 302 658 0035",
    "sg:postcode":"19807",
    "sg:province":"DE",
    "wof:name":"Samuel C Terranova",
    "wof:placetype":"venue"
},
  "geometry": {"coordinates":[-75.604055,39.77534],"type":"Point"}
}