{
  "type": "Feature",
  "properties": {
    "iso:country":"US",
    "sg:address":"2812 Landon Dr",
    "sg:city":"Wilmington",
    "sg:classifiers":[
        {
            "category":"Professional",
            "subcategory":"Management & Consulting",
            "type":"Services"
        }
    ],
    "sg:phone":"+1 302 584 1592",
    "sg:postcode":"19810",
    "sg:province":"DE",
    "wof:name":"Bloom Consulting",
    "wof:placetype":"venue"
},
  "geometry": {"coordinates":[-75.5305,39.822919],"type":"Point"}
}