{
  "type": "Feature",
  "properties": {
    "addr:full":"928 Rockwell Rd Wilmington DE 19810",
    "addr:housenumber":"928",
    "addr:postcode":"19810",
    "addr:street":"Rockwell Rd",
    "iso:country":"US",
    "sg:address":"928 Rockwell Rd",
    "sg:city":"Wilmington",
    "sg:classifiers":[
        {
            "category":"Government",
            "subcategory":"Office",
            "type":"Public Place"
        }
    ],
    "sg:phone":"+1 302 345 2348",
    "sg:postcode":"19810",
    "sg:province":"DE",
    "sg:tags":[
        "waste",
        "management",
        "agency"
    ],
    "wof:name":"Watson Phillips",
    "wof:placetype":"venue"
},
  "geometry": {"coordinates":[-75.471172,39.819565],"type":"Point"}
}