{
  "type": "Feature",
  "properties": {
    "addr:full":"521 New Rd Lewes DE 19958",
    "addr:housenumber":"521",
    "addr:postcode":"19958",
    "addr:street":"New Rd",
    "iso:country":"US",
    "sg:address":"521 New Rd",
    "sg:city":"Lewes",
    "sg:classifiers":[
        {
            "category":"Professional",
            "type":"Services"
        }
    ],
    "sg:phone":"+1 302 645 4720",
    "sg:postcode":"19958",
    "sg:province":"DE",
    "wof:name":"Woodsmith",
    "wof:placetype":"venue"
},
  "geometry": {"coordinates":[-75.181512,38.755916],"type":"Point"}
}