{
  "type": "Feature",
  "properties": {
    "addr:full":"152 Berry Dr Wilmington DE 19808",
    "addr:housenumber":"152",
    "addr:postcode":"19808",
    "addr:street":"Berry Dr",
    "iso:country":"US",
    "sg:address":"152 Berry Dr",
    "sg:city":"Wilmington",
    "sg:classifiers":[
        {
            "category":"Manufacturing",
            "subcategory":"Buildings",
            "type":"Manufacturing & Wholesale Goods"
        },
        {
            "category":"Home & Garden",
            "subcategory":"Building Materials",
            "type":"Retail Goods"
        },
        {
            "category":"Building & Trades",
            "subcategory":"Construction",
            "type":"Services"
        }
    ],
    "sg:phone":"+1 302 733 0240",
    "sg:postcode":"19808",
    "sg:province":"DE",
    "sg:tags":[
        "industrial",
        "specialty",
        "builder",
        "heating",
        "system",
        "contractors-commercial",
        "contractor",
        "gazebo",
        "air conditioning",
        "patio"
    ],
    "wof:name":"Baltic Construction Inc",
    "wof:placetype":"venue"
},
  "geometry": {"coordinates":[-75.69130800000001,39.712697],"type":"Point"}
}