{
  "type": "Feature",
  "properties": {
    "iso:country":"US",
    "sg:address":"4 Ridgewood Dr",
    "sg:city":"Hockessin",
    "sg:classifiers":[
        {
            "category":"Building & Trades",
            "subcategory":"Construction",
            "type":"Services"
        }
    ],
    "sg:phone":"+1 302 239 5158",
    "sg:postcode":"19707",
    "sg:province":"DE",
    "sg:tags":[
        "hanging",
        "contractor"
    ],
    "wof:name":"Robinson E Painting",
    "wof:placetype":"venue"
},
  "geometry": {"coordinates":[-75.695599,39.759281],"type":"Point"}
}