{
  "type": "Feature",
  "properties": {
    "iso:country":"US",
    "sg:address":"5908 Judith Rd",
    "sg:city":"Clayton",
    "sg:classifiers":[
        {
            "category":"Manufacturing",
            "subcategory":"Retail Goods",
            "type":"Manufacturing & Wholesale Goods"
        }
    ],
    "sg:phone":"+1 302 653 8687",
    "sg:postcode":"19938",
    "sg:province":"DE",
    "sg:tags":[
        "product",
        "mfg"
    ],
    "wof:name":"Eastern Shore Lite Industries",
    "wof:placetype":"venue"
},
  "geometry": {"coordinates":[-75.67225500000001,39.21649],"type":"Point"}
}