{
  "type": "Feature",
  "properties": {
    "iso:country":"US",
    "sg:address":"508 Runnymeade Rd",
    "sg:city":"Hockessin",
    "sg:classifiers":[
        {
            "category":"Professional",
            "type":"Services"
        }
    ],
    "sg:phone":"+1 302 239 2936",
    "sg:postcode":"19707",
    "sg:province":"DE",
    "wof:name":"Cherie Congo",
    "wof:placetype":"venue"
},
  "geometry": {"coordinates":[-75.691118,39.771931],"type":"Point"}
}