{
  "type": "Feature",
  "properties": {
    "iso:country":"US",
    "sg:address":"102 Middleboro Rd",
    "sg:city":"Wilmington",
    "sg:classifiers":[
        {
            "category":"Social Services",
            "type":"Services"
        }
    ],
    "sg:phone":"+1 302 998 3577",
    "sg:postcode":"19804",
    "sg:province":"DE",
    "wof:name":"Bbbs of Delaware Inc",
    "wof:placetype":"venue"
},
  "geometry": {"coordinates":[-75.587177,39.722159],"type":"Point"}
}