{
  "type": "Feature",
  "properties": {
    "addr:full":"5 Atlantic Ave Ocean View DE 19970",
    "addr:housenumber":"5",
    "addr:postcode":"19970",
    "addr:street":"Atlantic Ave",
    "iso:country":"US",
    "sg:address":"5 Atlantic Ave",
    "sg:city":"Ocean View",
    "sg:classifiers":[
        {
            "category":"Home & Garden",
            "subcategory":"Carpets & Floor Coverings",
            "type":"Retail Goods"
        },
        {
            "category":"Home & Garden",
            "subcategory":"Furniture",
            "type":"Retail Goods"
        }
    ],
    "sg:phone":"+1 302 539 3004",
    "sg:postcode":"19970",
    "sg:province":"DE",
    "sg:tags":[
        "equipment",
        "kitchen",
        "cabinetry",
        "cabinet"
    ],
    "wof:name":"Kitchen N Cabinet Corner Inc",
    "wof:placetype":"venue"
},
  "geometry": {"coordinates":[-75.081221,38.542797],"type":"Point"}
}