{
  "type": "Feature",
  "properties": {
    "addr:full":"9 Sheffield Manor Dr Newark DE 19711",
    "addr:housenumber":"9",
    "addr:postcode":"19711",
    "addr:street":"Sheffield Manor Dr",
    "iso:country":"US",
    "sg:address":"9 Sheffield Manor Dr",
    "sg:city":"Newark",
    "sg:classifiers":[
        {
            "category":"Retail",
            "subcategory":"Laundry & Dry Cleaning",
            "type":"Services"
        }
    ],
    "sg:phone":"+1 302 454 1521",
    "sg:postcode":"19711",
    "sg:province":"DE",
    "sg:tags":[
        "upholstery",
        "restoration",
        "carpet"
    ],
    "wof:name":"Rainbow Carpet Care",
    "wof:placetype":"venue"
},
  "geometry": {"coordinates":[-75.691249,39.6984],"type":"Point"}
}