{
  "type": "Feature",
  "properties": {
    "iso:country":"US",
    "sg:address":"487 Brookfield Dr",
    "sg:city":"Dover",
    "sg:classifiers":[
        {
            "category":"Manufacturing",
            "subcategory":"Electronics",
            "type":"Manufacturing & Wholesale Goods"
        }
    ],
    "sg:phone":"+1 302 697 8411",
    "sg:postcode":"19901",
    "sg:province":"DE",
    "sg:tags":[
        "electronic",
        "component",
        "mfg"
    ],
    "wof:name":"Dedicated Circuits LLC",
    "wof:placetype":"venue"
},
  "geometry": {"coordinates":[-75.539828,39.091474],"type":"Point"}
}