{
  "type": "Feature",
  "properties": {
    "addr:full":"1201 N Market St Wilmington DE 19801",
    "addr:housenumber":"1201",
    "addr:postcode":"19801",
    "addr:street":"N Market St",
    "iso:country":"US",
    "sg:address":"1201 N Market St",
    "sg:city":"Wilmington",
    "sg:classifiers":[
        {
            "category":"Banks & Credit Unions",
            "subcategory":"Financial Services",
            "type":"Services"
        }
    ],
    "sg:phone":"+1 302 428 3300",
    "sg:postcode":"19801",
    "sg:province":"DE",
    "sg:tags":[
        "company",
        "bank",
        "holding"
    ],
    "wof:name":"Cbc Holding Inc",
    "wof:placetype":"venue"
},
  "geometry": {"coordinates":[-75.54606699999999,39.748169],"type":"Point"}
}