{
  "type": "Feature",
  "properties": {
    "addr:full":"2219 Concord Pike Wilmington DE 19803",
    "addr:housenumber":"2219",
    "addr:postcode":"19803",
    "addr:street":"Concord Pike",
    "iso:country":"US",
    "sg:address":"2219 Concord Pike",
    "sg:city":"Wilmington",
    "sg:classifiers":[
        {
            "category":"Professional",
            "type":"Services"
        }
    ],
    "sg:phone":"+1 302 654 4629",
    "sg:postcode":"19803",
    "sg:province":"DE",
    "wof:name":"Five Below",
    "wof:placetype":"venue"
},
  "geometry": {"coordinates":[-75.545913,39.786556],"type":"Point"}
}