{
  "type": "Feature",
  "properties": {
    "iso:country":"US",
    "sg:address":"17 E Moyer Dr",
    "sg:city":"Bear",
    "sg:classifiers":[
        {
            "category":"Wholesale",
            "subcategory":"Motor Vehicles",
            "type":"Manufacturing & Wholesale Goods"
        }
    ],
    "sg:phone":"+1 302 838 5298",
    "sg:postcode":"19701",
    "sg:province":"DE",
    "wof:name":"Timmel & Sons Inc",
    "wof:placetype":"venue"
},
  "geometry": {"coordinates":[-75.692446,39.59402],"type":"Point"}
}