{
  "type": "Feature",
  "properties": {
    "addr:full":"2205 N Market St Wilmington DE 19802",
    "addr:housenumber":"2205",
    "addr:postcode":"19802",
    "addr:street":"N Market St",
    "iso:country":"US",
    "sg:address":"2205 N Market St",
    "sg:city":"Wilmington",
    "sg:classifiers":[
        {
            "category":"Restaurant",
            "type":"Food & Drink"
        }
    ],
    "sg:phone":"+1 302 655 8587",
    "sg:postcode":"19802",
    "sg:province":"DE",
    "sg:tags":[
        "sandwich",
        "eating"
    ],
    "wof:name":"Quality Charcoal Subs & Steaks",
    "wof:placetype":"venue"
},
  "geometry": {"coordinates":[-75.53934700000001,39.752995],"type":"Point"}
}