{
  "type": "Feature",
  "properties": {
    "iso:country":"US",
    "sg:address":"581 Roberta Ave",
    "sg:city":"Dover",
    "sg:classifiers":[
        {
            "category":"Professional",
            "type":"Services"
        }
    ],
    "sg:phone":"+1 302 734 9478",
    "sg:postcode":"19901",
    "sg:province":"DE",
    "wof:name":"Roy Paul E Jr CMS",
    "wof:placetype":"venue"
},
  "geometry": {"coordinates":[-75.50038499999999,39.156089],"type":"Point"}
}