{
  "type": "Feature",
  "properties": {
    "addr:full":"42 Reads Way New Castle DE 19720",
    "addr:housenumber":"42",
    "addr:postcode":"19720",
    "addr:street":"Reads Way",
    "iso:country":"US",
    "sg:address":"42 Reads Way",
    "sg:city":"New Castle",
    "sg:classifiers":[
        {
            "category":"Banks & Credit Unions",
            "subcategory":"Bank",
            "type":"Services"
        }
    ],
    "sg:phone":"+1 302 324 5345",
    "sg:postcode":"19720",
    "sg:province":"DE",
    "sg:tags":[
        "banker",
        "mortgage"
    ],
    "wof:name":"Countrywide",
    "wof:placetype":"venue"
},
  "geometry": {"coordinates":[-75.61245,39.687919],"type":"Point"}
}