{
  "type": "Feature",
  "properties": {
    "addr:full":"1709 Concord Pike Wilmington DE 19803",
    "addr:housenumber":"1709",
    "addr:postcode":"19803",
    "addr:street":"Concord Pike",
    "iso:country":"US",
    "sg:address":"1709 Concord Pike",
    "sg:city":"Wilmington",
    "sg:classifiers":[
        {
            "category":"Communications",
            "subcategory":"Film & Video Production",
            "type":"Services"
        }
    ],
    "sg:phone":"+1 302 888 2737",
    "sg:postcode":"19803",
    "sg:province":"DE",
    "sg:tags":[
        "duplication",
        "tape"
    ],
    "wof:name":"Delaware Digital Video Factory",
    "wof:placetype":"venue"
},
  "geometry": {"coordinates":[-75.545795,39.785419],"type":"Point"}
}