{
  "type": "Feature",
  "properties": {
    "iso:country":"US",
    "sg:address":"1109 Willow Grove Rd",
    "sg:city":"Felton",
    "sg:classifiers":[
        {
            "category":"Utilities",
            "subcategory":"Electric",
            "type":"Services"
        }
    ],
    "sg:phone":"+1 302 284 0475",
    "sg:postcode":"19943",
    "sg:province":"DE",
    "sg:tags":[
        "energy"
    ],
    "wof:name":"Ogden Remediation Service",
    "wof:placetype":"venue"
},
  "geometry": {"coordinates":[-75.72309799999999,39.03294],"type":"Point"}
}