{
  "type": "Feature",
  "properties": {
    "iso:country":"US",
    "sg:address":"135 Ransom Ln",
    "sg:city":"Smyrna",
    "sg:classifiers":[
        {
            "category":"Organizations",
            "subcategory":"Religious Organization",
            "type":"Services"
        }
    ],
    "sg:phone":"+1 302 653 8279",
    "sg:postcode":"19977",
    "sg:province":"DE",
    "sg:tags":[
        "church"
    ],
    "wof:name":"St Polycarps Church",
    "wof:placetype":"venue"
},
  "geometry": {"coordinates":[-75.60983,39.294609],"type":"Point"}
}