{
  "type": "Feature",
  "properties": {
    "iso:country":"US",
    "sg:address":"29 Possum Park Mall",
    "sg:city":"Newark",
    "sg:classifiers":[
        {
            "category":"Retail",
            "subcategory":"Auto Repair",
            "type":"Services"
        }
    ],
    "sg:phone":"+1 302 738 5494",
    "sg:postcode":"19711",
    "sg:province":"DE",
    "sg:tags":[
        "automobile",
        "lubrication",
        "automotive"
    ],
    "wof:name":"Jiffy Lube",
    "wof:placetype":"venue"
},
  "geometry": {"coordinates":[-75.71732799999999,39.694337],"type":"Point"}
}