{
  "type": "Feature",
  "properties": {
    "addr:full":"230 Christiana Rd New Castle DE 19720",
    "addr:housenumber":"230",
    "addr:postcode":"19720",
    "addr:street":"Christiana Rd New",
    "iso:country":"US",
    "sg:address":"230 Christiana Rd",
    "sg:city":"New Castle",
    "sg:classifiers":[
        {
            "category":"Organizations",
            "subcategory":"Religious Organization",
            "type":"Services"
        }
    ],
    "sg:phone":"+1 302 322 4720",
    "sg:postcode":"19720",
    "sg:province":"DE",
    "wof:name":"Hope Lutheran Day Care Center",
    "wof:placetype":"venue"
},
  "geometry": {"coordinates":[-75.630764,39.663687],"type":"Point"}
}