{
  "type": "Feature",
  "properties": {
    "iso:country":"US",
    "sg:address":"5 S Walnut St",
    "sg:city":"Milford",
    "sg:classifiers":[
        {
            "category":"Building & Trades",
            "subcategory":"Cleaning & Sanitation",
            "type":"Services"
        }
    ],
    "sg:phone":"+1 302 839 0302",
    "sg:postcode":"19963",
    "sg:province":"DE",
    "sg:tags":[
        "maintenance"
    ],
    "wof:name":"Jens Cleaning",
    "wof:placetype":"venue"
},
  "geometry": {"coordinates":[-75.428403,38.912007],"type":"Point"}
}