{
  "type": "Feature",
  "properties": {
    "iso:country":"US",
    "sg:address":"412 N Governors Ave",
    "sg:city":"Dover",
    "sg:classifiers":[
        {
            "category":"Autos & Motor Vehicles",
            "subcategory":"Automobile Sales",
            "type":"Retail Goods"
        }
    ],
    "sg:phone":"+1 302 672 7980",
    "sg:postcode":"19904",
    "sg:province":"DE",
    "sg:tags":[
        "new",
        "car"
    ],
    "wof:name":"Kevin B Robeson",
    "wof:placetype":"venue"
},
  "geometry": {"coordinates":[-75.530514,39.167105],"type":"Point"}
}