{
  "type": "Feature",
  "properties": {
    "addr:full":"14878 Staytonville Rd Lincoln DE 19960",
    "addr:postcode":"14878;19960",
    "addr:street":"Staytonville Rd",
    "iso:country":"US",
    "sg:address":"14878 Staytonville Rd",
    "sg:city":"Lincoln",
    "sg:classifiers":[
        {
            "category":"Insurance",
            "subcategory":"Insurance Agent",
            "type":"Services"
        }
    ],
    "sg:phone":"+1 302 422 9639",
    "sg:postcode":"19960",
    "sg:province":"DE",
    "wof:name":"Thrivent Financial-Lutherans",
    "wof:placetype":"venue"
},
  "geometry": {"coordinates":[-75.480214,38.827071],"type":"Point"}
}