{
  "type": "Feature",
  "properties": {
    "addr:full":"233 Hibiscus Ter Magnolia DE 19962",
    "addr:housenumber":"233",
    "addr:postcode":"19962",
    "addr:street":"Hibiscus Ter",
    "iso:country":"US",
    "sg:address":"233 Hibiscus Ter",
    "sg:city":"Magnolia",
    "sg:classifiers":[
        {
            "category":"Shopping",
            "subcategory":"Computers & Home Electronics",
            "type":"Retail Goods"
        }
    ],
    "sg:phone":"+1 302 242 8304",
    "sg:postcode":"19962",
    "sg:province":"DE",
    "wof:name":"Complete Pcs of Delaware",
    "wof:placetype":"venue"
},
  "geometry": {"coordinates":[-75.500974,39.059573],"type":"Point"}
}