{
  "type": "Feature",
  "properties": {
    "addr:full":"17 Lamatan Rd Newark DE 19711",
    "addr:housenumber":"17",
    "addr:postcode":"19711",
    "addr:street":"Lamatan Rd",
    "iso:country":"US",
    "sg:address":"17 Lamatan Rd",
    "sg:city":"Newark",
    "sg:classifiers":[
        {
            "category":"Professional",
            "subcategory":"Accounting & Tax Preparation",
            "type":"Services"
        }
    ],
    "sg:phone":"+1 302 239 9166",
    "sg:postcode":"19711",
    "sg:province":"DE",
    "sg:tags":[
        "return"
    ],
    "wof:name":"A To Z Discount Taxes",
    "wof:placetype":"venue"
},
  "geometry": {"coordinates":[-75.74235299999999,39.757861],"type":"Point"}
}