{
  "type": "Feature",
  "properties": {
    "iso:country":"US",
    "sg:address":"97 Harvey Rd",
    "sg:city":"Claymont",
    "sg:classifiers":[
        {
            "category":"Food & Beverages",
            "subcategory":"Specialty",
            "type":"Retail Goods"
        }
    ],
    "sg:phone":"+1 302 798 7074",
    "sg:postcode":"19703",
    "sg:province":"DE",
    "sg:tags":[
        "american",
        "latin",
        "mexican",
        "product"
    ],
    "wof:name":"Las Cruces Mexican Store",
    "wof:placetype":"venue"
},
  "geometry": {"coordinates":[-75.468992,39.794764],"type":"Point"}
}