{
  "type": "Feature",
  "properties": {
    "addr:full":"2412 Greenleaf Dr Wilmington DE 19810",
    "addr:housenumber":"2412",
    "addr:postcode":"19810",
    "addr:street":"Greenleaf Dr",
    "iso:country":"US",
    "sg:address":"2412 Greenleaf Dr",
    "sg:city":"Wilmington",
    "sg:classifiers":[
        {
            "category":"Manufacturing",
            "subcategory":"Signs",
            "type":"Manufacturing & Wholesale Goods"
        }
    ],
    "sg:phone":"+1 302 598 5377",
    "sg:postcode":"19810",
    "sg:province":"DE",
    "sg:tags":[
        "specialty",
        "mfg"
    ],
    "wof:name":"Gatto Graphix LLC",
    "wof:placetype":"venue"
},
  "geometry": {"coordinates":[-75.50993699999999,39.825683],"type":"Point"}
}