{
  "type": "Feature",
  "properties": {
    "iso:country":"US",
    "sg:address":"25 W Main St",
    "sg:city":"Middletown",
    "sg:classifiers":[
        {
            "category":"Freight",
            "type":"Transportation"
        }
    ],
    "sg:phone":"+1 302 659 3449",
    "sg:postcode":"19709",
    "sg:province":"DE",
    "sg:tags":[
        "general"
    ],
    "wof:name":"Stewarts This That & More Stor",
    "wof:placetype":"venue"
},
  "geometry": {"coordinates":[-75.71719,39.449718],"type":"Point"}
}