{
  "type": "Feature",
  "properties": {
    "iso:country":"US",
    "sg:address":"103 S Dupont Blvd",
    "sg:city":"Smyrna",
    "sg:classifiers":[
        {
            "category":"Autos & Motor Vehicles",
            "subcategory":"Automobile Sales",
            "type":"Retail Goods"
        }
    ],
    "sg:phone":"+1 302 653 5193",
    "sg:postcode":"19977",
    "sg:province":"DE",
    "sg:tags":[
        "car",
        "dealer"
    ],
    "wof:name":"Solloway's Sales & Svc",
    "wof:placetype":"venue"
},
  "geometry": {"coordinates":[-75.60163799999999,39.300077],"type":"Point"}
}