{
  "type": "Feature",
  "properties": {
    "addr:full":"300 W Monroe St Millsboro DE 19966",
    "addr:housenumber":"300",
    "addr:postcode":"19966",
    "addr:street":"W Monroe St",
    "iso:country":"US",
    "sg:address":"300 W Monroe St",
    "sg:city":"Millsboro",
    "sg:classifiers":[
        {
            "category":"Professional",
            "subcategory":"Business Services",
            "type":"Services"
        }
    ],
    "sg:phone":"+1 302 934 7785",
    "sg:postcode":"19966",
    "sg:province":"DE",
    "sg:tags":[
        "repossessing"
    ],
    "wof:name":"Complete Auto Recovery Svc Inc",
    "wof:placetype":"venue"
},
  "geometry": {"coordinates":[-75.30290599999999,38.591716],"type":"Point"}
}