{
  "type": "Feature",
  "properties": {
    "iso:country":"US",
    "sg:address":"650 S Bay Rd",
    "sg:city":"Dover",
    "sg:classifiers":[
        {
            "category":"Banks & Credit Unions",
            "subcategory":"Bank",
            "type":"Services"
        }
    ],
    "sg:phone":"+1 302 730 1040",
    "sg:postcode":"19901",
    "sg:province":"DE",
    "sg:tags":[
        "cashing",
        "check"
    ],
    "wof:name":"Dover EZ Check Cashing",
    "wof:placetype":"venue"
},
  "geometry": {"coordinates":[-75.50773,39.154669],"type":"Point"}
}