{
  "type": "Feature",
  "properties": {
    "iso:country":"US",
    "sg:address":"2015 Concord Pike",
    "sg:city":"Wilmington",
    "sg:classifiers":[
        {
            "category":"Restaurant",
            "type":"Food & Drink"
        }
    ],
    "sg:phone":"+1 302 652 8910",
    "sg:postcode":"19803",
    "sg:province":"DE",
    "sg:website":"http://www.bennigans.com",
    "wof:name":"Bennigan's Grill & Tavern",
    "wof:placetype":"venue"
},
  "geometry": {"coordinates":[-75.546187,39.788131],"type":"Point"}
}