{
  "type": "Feature",
  "properties": {
    "addr:full":"1505 N Dupont Hwy New Castle DE 19720",
    "addr:housenumber":"1505",
    "addr:postcode":"19720",
    "addr:street":"N Dupont Hwy",
    "iso:country":"US",
    "sg:address":"1505 N Dupont Hwy",
    "sg:city":"New Castle",
    "sg:classifiers":[
        {
            "category":"Personal",
            "subcategory":"Beauty Salon",
            "type":"Services"
        }
    ],
    "sg:phone":"+1 302 328 2254",
    "sg:postcode":"19720",
    "sg:province":"DE",
    "sg:tags":[
        "shop"
    ],
    "wof:name":"Top Nails",
    "wof:placetype":"venue"
},
  "geometry": {"coordinates":[-75.58097600000001,39.691053],"type":"Point"}
}