{
  "type": "Feature",
  "properties": {
    "iso:country":"US",
    "sg:address":"102 E Laurel St",
    "sg:city":"Georgetown",
    "sg:classifiers":[
        {
            "category":"Organizations",
            "subcategory":"Religious Organization",
            "type":"Services"
        }
    ],
    "sg:phone":"+1 302 856 2414",
    "sg:postcode":"19947",
    "sg:province":"DE",
    "wof:name":"Wesley United Methodist Church",
    "wof:placetype":"venue"
},
  "geometry": {"coordinates":[-75.38484699999999,38.69245],"type":"Point"}
}