{
  "type": "Feature",
  "properties": {
    "iso:country":"US",
    "sg:address":"22300 Lewes Georgetown Hwy",
    "sg:city":"Georgetown",
    "sg:classifiers":[
        {
            "category":"Organizations",
            "subcategory":"Religious Organization",
            "type":"Services"
        }
    ],
    "sg:phone":"+1 302 856 3667",
    "sg:postcode":"19947",
    "sg:province":"DE",
    "wof:name":"Jehovahs Witnesses",
    "wof:placetype":"venue"
},
  "geometry": {"coordinates":[-75.34684,38.705237],"type":"Point"}
}