{
  "type": "Feature",
  "properties": {
    "addr:full":"2807 N Market St Wilmington DE 19802",
    "addr:housenumber":"2807",
    "addr:postcode":"19802",
    "addr:street":"N Market St",
    "iso:country":"US",
    "sg:address":"2807 N Market St",
    "sg:city":"Wilmington",
    "sg:classifiers":[
        {
            "category":"Banks & Credit Unions",
            "subcategory":"Bank",
            "type":"Services"
        }
    ],
    "sg:phone":"+1 302 764 9235",
    "sg:postcode":"19802",
    "sg:province":"DE",
    "sg:tags":[
        "depository",
        "banking"
    ],
    "wof:name":"Cash Connection",
    "wof:placetype":"venue"
},
  "geometry": {"coordinates":[-75.533252,39.75572],"type":"Point"}
}