{
  "type": "Feature",
  "properties": {
    "addr:full":"1601 Milltown Rd Wilmington DE 19808",
    "addr:housenumber":"1601",
    "addr:postcode":"19808",
    "addr:street":"Milltown Rd",
    "iso:country":"US",
    "sg:address":"1601 Milltown Rd",
    "sg:city":"Wilmington",
    "sg:classifiers":[
        {
            "category":"Shopping",
            "subcategory":"Shoes",
            "type":"Retail Goods"
        }
    ],
    "sg:phone":"+1 302 994 1210",
    "sg:postcode":"19808",
    "sg:province":"DE",
    "wof:name":"Red Wing Shoe Store",
    "wof:placetype":"venue"
},
  "geometry": {"coordinates":[-75.669051,39.729147],"type":"Point"}
}