{
  "type": "Feature",
  "properties": {
    "addr:full":"13350 Oak Branch Rd Delmar DE 19940",
    "addr:housenumber":"13350",
    "addr:postcode":"19940",
    "addr:street":"Oak Branch Rd",
    "iso:country":"US",
    "sg:address":"13350 Oak Branch Rd",
    "sg:city":"Delmar",
    "sg:classifiers":[
        {
            "category":"Organizations",
            "subcategory":"Religious Organization",
            "type":"Services"
        }
    ],
    "sg:phone":"+1 302 846 3962",
    "sg:postcode":"19940",
    "sg:province":"DE",
    "sg:tags":[
        "clergy"
    ],
    "wof:name":"Howard E Evans",
    "wof:placetype":"venue"
},
  "geometry": {"coordinates":[-75.517555,38.477669],"type":"Point"}
}