{
  "type": "Feature",
  "properties": {
    "iso:country":"US",
    "sg:address":"402 N Hall St",
    "sg:city":"Seaford",
    "sg:classifiers":[
        {
            "category":"Real Estate",
            "subcategory":"Real Estate Agent",
            "type":"Services"
        }
    ],
    "sg:phone":"+1 302 629 8333",
    "sg:postcode":"19973",
    "sg:province":"DE",
    "sg:tags":[
        "appraiser"
    ],
    "wof:name":"Huston Appraisal",
    "wof:placetype":"venue"
},
  "geometry": {"coordinates":[-75.621331,38.643482],"type":"Point"}
}