{
  "type": "Feature",
  "properties": {
    "iso:country":"US",
    "sg:address":"1783 Dixie Line Rd",
    "sg:city":"Elkton",
    "sg:classifiers":[
        {
            "category":"Shopping",
            "subcategory":"Hobbies, Toys, & Games",
            "type":"Retail Goods"
        }
    ],
    "sg:phone":"+1 410 620 7377",
    "sg:postcode":"21921",
    "sg:province":"MD",
    "sg:tags":[
        "equipment",
        "ceramic",
        "supply"
    ],
    "sg:website":"www.scenicartistry.com",
    "wof:name":"Ceramics Galore",
    "wof:placetype":"venue"
},
  "geometry": {"coordinates":[-75.787215,39.632263],"type":"Point"}
}