{
  "type": "Feature",
  "properties": {
    "addr:full":"105 N Dupont Hwy New Castle DE 19720",
    "addr:housenumber":"105",
    "addr:postcode":"19720",
    "addr:street":"N Dupont Hwy",
    "iso:country":"US",
    "sg:address":"105 N Dupont Hwy",
    "sg:city":"New Castle",
    "sg:classifiers":[
        {
            "category":"Insurance",
            "subcategory":"Insurance Agent",
            "type":"Services"
        }
    ],
    "sg:phone":"+1 302 322 0300",
    "sg:postcode":"19720",
    "sg:province":"DE",
    "wof:name":"Independent Financial Concepts",
    "wof:placetype":"venue"
},
  "geometry": {"coordinates":[-75.588279,39.682596],"type":"Point"}
}