{
  "type": "Feature",
  "properties": {
    "iso:country":"US",
    "sg:address":"1201 Yearsley Dr",
    "sg:city":"Dover",
    "sg:classifiers":[
        {
            "category":"Retail",
            "subcategory":"Funeral Services",
            "type":"Services"
        }
    ],
    "sg:phone":"+1 302 734 8219",
    "sg:postcode":"19904",
    "sg:province":"DE",
    "sg:tags":[
        "trade"
    ],
    "wof:name":"First Call Inc",
    "wof:placetype":"venue"
},
  "geometry": {"coordinates":[-75.534325,39.1414],"type":"Point"}
}