{
  "type": "Feature",
  "properties": {
    "iso:country":"US",
    "sg:address":"1235 Vernon Rd",
    "sg:city":"Harrington",
    "sg:classifiers":[
        {
            "category":"Building & Trades",
            "subcategory":"Plumbing",
            "type":"Services"
        }
    ],
    "sg:phone":"+1 302 398 6283",
    "sg:postcode":"19952",
    "sg:province":"DE",
    "sg:tags":[
        "conditioning",
        "air",
        "system",
        "contractor"
    ],
    "wof:name":"Randy Shahan & Sons",
    "wof:placetype":"venue"
},
  "geometry": {"coordinates":[-75.708551,38.89475],"type":"Point"}
}