{
  "type": "Feature",
  "properties": {
    "addr:full":"4748 Limestone Rd Wilmington DE 19808",
    "addr:housenumber":"4748",
    "addr:postcode":"19808",
    "addr:street":"Limestone Rd",
    "iso:country":"US",
    "sg:address":"4748 Limestone Rd",
    "sg:city":"Wilmington",
    "sg:classifiers":[
        {
            "category":"Banks & Credit Unions",
            "subcategory":"Investment Brokerage",
            "type":"Services"
        }
    ],
    "sg:phone":"+1 302 999 0588",
    "sg:postcode":"19808",
    "sg:province":"DE",
    "sg:tags":[
        "security"
    ],
    "wof:name":"Edward Jones 11395",
    "wof:placetype":"venue"
},
  "geometry": {"coordinates":[-75.695426,39.743394],"type":"Point"}
}