{
  "type": "Feature",
  "properties": {
    "iso:country":"US",
    "sg:address":"1718 Naamans Rd.",
    "sg:city":"Wilmington",
    "sg:classifiers":[
        {
            "category":"Food & Beverages",
            "subcategory":"Specialty",
            "type":"Retail Goods"
        }
    ],
    "sg:phone":"+1 302 529 0131",
    "sg:postcode":"19810",
    "sg:province":"DE",
    "sg:website":"www.phillysoftpretzelfactory.com",
    "wof:name":"Philly Pretzel Factory",
    "wof:placetype":"venue"
},
  "geometry": {"coordinates":[-75.488466,39.822844],"type":"Point"}
}