{
  "type": "Feature",
  "properties": {
    "iso:country":"US",
    "sg:address":"2202 London Way",
    "sg:city":"Newark",
    "sg:classifiers":[
        {
            "category":"Real Estate",
            "subcategory":"Real Estate Operator",
            "type":"Services"
        }
    ],
    "sg:phone":"+1 302 738 5225",
    "sg:postcode":"19713",
    "sg:province":"DE",
    "sg:tags":[
        "building",
        "apartment"
    ],
    "wof:name":"Elms Apartments",
    "wof:placetype":"venue"
},
  "geometry": {"coordinates":[-75.69478599999999,39.6729],"type":"Point"}
}