{
  "type": "Feature",
  "properties": {
    "iso:country":"US",
    "sg:address":"521 College Sq",
    "sg:city":"Newark",
    "sg:classifiers":[
        {
            "category":"Shopping",
            "subcategory":"Shoes",
            "type":"Retail Goods"
        }
    ],
    "sg:phone":"+1 302 368 7335",
    "sg:postcode":"19711",
    "sg:province":"DE",
    "wof:name":"Payless Shoe Source",
    "wof:placetype":"venue"
},
  "geometry": {"coordinates":[-75.73336,39.684268],"type":"Point"}
}