{
  "type": "Feature",
  "properties": {
    "iso:country":"US",
    "sg:address":"739 Old Wilmington Rd",
    "sg:city":"Hockessin",
    "sg:classifiers":[
        {
            "category":"Banks & Credit Unions",
            "subcategory":"Bank",
            "type":"Services"
        }
    ],
    "sg:phone":"+1 302 234 2482",
    "sg:postcode":"19707",
    "sg:province":"DE",
    "sg:tags":[
        "mortgage"
    ],
    "wof:name":"American Capital Mortgage",
    "wof:placetype":"venue"
},
  "geometry": {"coordinates":[-75.65959700000001,39.773377],"type":"Point"}
}