{
  "type": "Feature",
  "properties": {
    "iso:country":"US",
    "sg:address":"501 S Market St",
    "sg:city":"Wilmington",
    "sg:phone":"+1 302 658 5293",
    "sg:postcode":"19801",
    "sg:province":"DE",
    "sg:tags":[
        "oil"
    ],
    "wof:name":"Shellhorn & Hill Inc",
    "wof:placetype":"venue"
},
  "geometry": {"coordinates":[-75.55604,39.729939],"type":"Point"}
}