{
  "type": "Feature",
  "properties": {
    "iso:country":"US",
    "sg:address":"11351 S Dupont Hwy",
    "sg:city":"Felton",
    "sg:classifiers":[
        {
            "category":"Home & Garden",
            "subcategory":"Garden Supply",
            "type":"Retail Goods"
        }
    ],
    "sg:phone":"+1 302 284 9277",
    "sg:postcode":"19943",
    "sg:province":"DE",
    "sg:tags":[
        "lawn"
    ],
    "wof:name":"Felton Landscape",
    "wof:placetype":"venue"
},
  "geometry": {"coordinates":[-75.568783,39.007418],"type":"Point"}
}