{
  "type": "Feature",
  "properties": {
    "iso:country":"US",
    "sg:address":"412 Suburban Dr",
    "sg:city":"Newark",
    "sg:classifiers":[
        {
            "category":"Health Services",
            "subcategory":"Hospital",
            "type":"Services"
        }
    ],
    "sg:phone":"+1 302 378 3770",
    "sg:postcode":"19711",
    "sg:province":"DE",
    "sg:tags":[
        "sleep",
        "treatment",
        "disorders-information"
    ],
    "wof:name":"Christine Horan",
    "wof:placetype":"venue"
},
  "geometry": {"coordinates":[-75.77711499999999,39.666814],"type":"Point"}
}