{
  "type": "Feature",
  "properties": {
    "iso:country":"US",
    "sg:address":"3606 Silverside Rd",
    "sg:city":"Wilmington",
    "sg:classifiers":[
        {
            "category":"Shopping",
            "subcategory":"Optician",
            "type":"Retail Goods"
        }
    ],
    "sg:phone":"+1 302 479 9455",
    "sg:postcode":"19810",
    "sg:province":"DE",
    "sg:tags":[
        "eyewear"
    ],
    "sg:website":"www.brandywineopticians.org",
    "wof:name":"Brandywine Opticians",
    "wof:placetype":"venue"
},
  "geometry": {"coordinates":[-75.54630299999999,39.809101],"type":"Point"}
}