{
  "type": "Feature",
  "properties": {
    "iso:country":"US",
    "sg:address":"24635 Lewes Georgetown Hwy",
    "sg:city":"Georgetown",
    "sg:classifiers":[
        {
            "category":"Shopping",
            "type":"Retail Goods"
        }
    ],
    "sg:phone":"+1 302 856 2185",
    "sg:postcode":"19947",
    "sg:province":"DE",
    "sg:tags":[
        "pet",
        "shop"
    ],
    "wof:name":"Burns Tropical Fish & Pet Shop",
    "wof:placetype":"venue"
},
  "geometry": {"coordinates":[-75.316695,38.714186],"type":"Point"}
}