{
  "type": "Feature",
  "properties": {
    "iso:country":"US",
    "sg:address":"320 W 9th St",
    "sg:city":"Wilmington",
    "sg:classifiers":[
        {
            "category":"Manufacturing",
            "subcategory":"Printing",
            "type":"Manufacturing & Wholesale Goods"
        }
    ],
    "sg:phone":"+1 302 658 2003",
    "sg:postcode":"19801",
    "sg:province":"DE",
    "sg:tags":[
        "multimedia"
    ],
    "wof:name":"Studio 320 Multimedia",
    "wof:placetype":"venue"
},
  "geometry": {"coordinates":[-75.55132,39.745777],"type":"Point"}
}