{
  "type": "Feature",
  "properties": {
    "iso:country":"US",
    "sg:address":"32075 Melson Rd",
    "sg:city":"Delmar",
    "sg:classifiers":[
        {
            "category":"Building & Trades",
            "subcategory":"Construction",
            "type":"Services"
        }
    ],
    "sg:phone":"+1 410 896 3500",
    "sg:postcode":"21875",
    "sg:province":"DE",
    "sg:tags":[
        "home",
        "builder"
    ],
    "wof:name":"Tucker Homes",
    "wof:placetype":"venue"
},
  "geometry": {"coordinates":[-75.499836,38.44349],"type":"Point"}
}