{
  "type": "Feature",
  "properties": {
    "iso:country":"US",
    "sg:address":"4 Blackpool Way",
    "sg:city":"Rehoboth Beach",
    "sg:classifiers":[
        {
            "category":"Building & Trades",
            "subcategory":"Construction",
            "type":"Services"
        }
    ],
    "sg:phone":"+1 302 226 5328",
    "sg:postcode":"19971",
    "sg:province":"DE",
    "sg:tags":[
        "handyman"
    ],
    "wof:name":"Phillips Property Svc LLC",
    "wof:placetype":"venue"
},
  "geometry": {"coordinates":[-75.102698,38.699058],"type":"Point"}
}