{
  "type": "Feature",
  "properties": {
    "addr:full":"703 Chestnut St Milton DE 19968",
    "addr:housenumber":"703",
    "addr:postcode":"19968",
    "addr:street":"Chestnut St",
    "iso:country":"US",
    "sg:address":"703 Chestnut St",
    "sg:city":"Milton",
    "sg:classifiers":[
        {
            "category":"Shopping",
            "subcategory":"Hobbies, Toys, & Games",
            "type":"Retail Goods"
        }
    ],
    "sg:phone":"+1 302 856 3942",
    "sg:postcode":"19968",
    "sg:province":"DE",
    "sg:tags":[
        "craft"
    ],
    "wof:name":"Dogfish Head Craft Brewery",
    "wof:placetype":"venue"
},
  "geometry": {"coordinates":[-75.313305,38.769098],"type":"Point"}
}