{
  "type": "Feature",
  "properties": {
    "iso:country":"US",
    "sg:address":"23 Sommerset Ln",
    "sg:city":"Newark",
    "sg:classifiers":[
        {
            "category":"Home & Garden",
            "subcategory":"Carpets & Floor Coverings",
            "type":"Retail Goods"
        },
        {
            "category":"Building & Trades",
            "subcategory":"Construction",
            "type":"Services"
        }
    ],
    "sg:phone":"+1 302 234 9345",
    "sg:postcode":"19711",
    "sg:province":"DE",
    "sg:tags":[
        "tile",
        "dealer"
    ],
    "wof:name":"American Floor Covering Inc",
    "wof:placetype":"venue"
},
  "geometry": {"coordinates":[-75.73469900000001,39.746638],"type":"Point"}
}