{
  "type": "Feature",
  "properties": {
    "iso:country":"US",
    "sg:address":"2711 Centerville Rd",
    "sg:city":"Wilmington",
    "sg:classifiers":[
        {
            "category":"Professional",
            "subcategory":"Research",
            "type":"Services"
        }
    ],
    "sg:phone":"+1 302 436 5400",
    "sg:postcode":"19808",
    "sg:province":"DE",
    "sg:tags":[
        "biotechnology"
    ],
    "wof:name":"Sxinos Corporation",
    "wof:placetype":"venue"
},
  "geometry": {"coordinates":[-75.62527799999999,39.756113],"type":"Point"}
}