{
  "type": "Feature",
  "properties": {
    "iso:country":"US",
    "sg:address":"30 Germay Dr",
    "sg:city":"Wilmington",
    "sg:classifiers":[
        {
            "category":"Building & Trades",
            "subcategory":"Electrical",
            "type":"Services"
        }
    ],
    "sg:phone":"+1 302 428 6158",
    "sg:postcode":"19804",
    "sg:province":"DE",
    "sg:tags":[
        "electric",
        "contractor"
    ],
    "wof:name":"Georgetown Electric LTD",
    "wof:placetype":"venue"
},
  "geometry": {"coordinates":[-75.57705900000001,39.724563],"type":"Point"}
}