{
  "type": "Feature",
  "properties": {
    "iso:country":"US",
    "sg:address":"4407 Kennett Pike",
    "sg:city":"Wilmington",
    "sg:classifiers":[
        {
            "category":"Shopping",
            "subcategory":"Stationery & Office Supplies",
            "type":"Retail Goods"
        }
    ],
    "sg:phone":"+1 302 655 1299",
    "sg:postcode":"19807",
    "sg:province":"DE",
    "sg:tags":[
        "stationer"
    ],
    "wof:name":"Communiques",
    "wof:placetype":"venue"
},
  "geometry": {"coordinates":[-75.60434600000001,39.789966],"type":"Point"}
}