{
  "type": "Feature",
  "properties": {
    "addr:full":"365 Water St Wilmington DE 19804",
    "addr:housenumber":"365",
    "addr:postcode":"19804",
    "addr:street":"Water St",
    "iso:country":"US",
    "sg:address":"365 Water St",
    "sg:city":"Wilmington",
    "sg:classifiers":[
        {
            "category":"Restaurant",
            "type":"Food & Drink"
        }
    ],
    "sg:phone":"+1 302 998 0671",
    "sg:postcode":"19804",
    "sg:province":"DE",
    "sg:tags":[
        "eating"
    ],
    "wof:name":"Coffee Pause Co Inc",
    "wof:placetype":"venue"
},
  "geometry": {"coordinates":[-75.600701,39.71285],"type":"Point"}
}