{
  "type": "Feature",
  "properties": {
    "iso:country":"US",
    "sg:address":"200 Bellevue Pkwy",
    "sg:city":"Wilmington",
    "sg:classifiers":[
        {
            "category":"Wholesale",
            "subcategory":"Office Equipment",
            "type":"Manufacturing & Wholesale Goods"
        }
    ],
    "sg:phone":"+1 302 792 5100",
    "sg:postcode":"19809",
    "sg:province":"DE",
    "sg:tags":[
        "repair"
    ],
    "wof:name":"Xerox",
    "wof:placetype":"venue"
},
  "geometry": {"coordinates":[-75.490979,39.778794],"type":"Point"}
}