{
  "type": "Feature",
  "properties": {
    "iso:country":"US",
    "sg:address":"2 Mailly Ct",
    "sg:city":"Townsend",
    "sg:classifiers":[
        {
            "category":"Professional",
            "type":"Services"
        }
    ],
    "sg:phone":"+1 302 376 1737",
    "sg:postcode":"19734",
    "sg:province":"DE",
    "wof:name":"Jax Nuelear Inc",
    "wof:placetype":"venue"
},
  "geometry": {"coordinates":[-75.630957,39.432621],"type":"Point"}
}