{
  "type": "Feature",
  "properties": {
    "iso:country":"US",
    "sg:address":"9 E Loockerman St",
    "sg:city":"Dover",
    "sg:classifiers":[
        {
            "category":"Professional",
            "subcategory":"Business Services",
            "type":"Services"
        }
    ],
    "sg:phone":"+1 302 674 4089",
    "sg:postcode":"19901",
    "sg:province":"DE",
    "wof:name":"Nrai Service Center LLC",
    "wof:placetype":"venue"
},
  "geometry": {"coordinates":[-75.523515,39.158281],"type":"Point"}
}