{
  "type": "Feature",
  "properties": {
    "addr:full":"13 Robin Dr Hockessin DE 19707",
    "addr:housenumber":"13",
    "addr:postcode":"19707",
    "addr:street":"Robin Dr",
    "iso:country":"US",
    "sg:address":"13 Robin Dr",
    "sg:city":"Hockessin",
    "sg:classifiers":[
        {
            "category":"Manufacturing",
            "subcategory":"Tools & Machinery",
            "type":"Manufacturing & Wholesale Goods"
        }
    ],
    "sg:phone":"+1 302 239 6337",
    "sg:postcode":"19707",
    "sg:province":"DE",
    "sg:tags":[
        "equipment",
        "mfg",
        "lighting",
        "vehicle"
    ],
    "wof:name":"Dmg Clearance Inc",
    "wof:placetype":"venue"
},
  "geometry": {"coordinates":[-75.697146,39.778863],"type":"Point"}
}