{
  "type": "Feature",
  "properties": {
    "iso:country":"US",
    "sg:address":"3823 Evelyn Dr",
    "sg:city":"Wilmington",
    "sg:classifiers":[
        {
            "category":"Building & Trades",
            "subcategory":"Plumbing",
            "type":"Services"
        }
    ],
    "sg:phone":"+1 302 993 0834",
    "sg:postcode":"19808",
    "sg:province":"DE",
    "sg:tags":[
        "contractor",
        "system",
        "air conditioning"
    ],
    "wof:name":"Calvert Mechanical Systems",
    "wof:placetype":"venue"
},
  "geometry": {"coordinates":[-75.647413,39.736005],"type":"Point"}
}