{
  "type": "Feature",
  "properties": {
    "addr:full":"134 W Market St Lewes DE 19958",
    "addr:housenumber":"134",
    "addr:postcode":"19958",
    "addr:street":"W Market St",
    "iso:country":"US",
    "sg:address":"134 W Market St",
    "sg:city":"Lewes",
    "sg:classifiers":[
        {
            "category":"Restaurant",
            "type":"Food & Drink"
        }
    ],
    "sg:phone":"+1 302 644 7230",
    "sg:postcode":"19958",
    "sg:province":"DE",
    "wof:name":"Gilligan's Waterfront Rstrnt",
    "wof:placetype":"venue"
},
  "geometry": {"coordinates":[-75.139945,38.776008],"type":"Point"}
}