{
  "type": "Feature",
  "properties": {
    "iso:country":"US",
    "sg:address":"1570 N Dupont Hwy",
    "sg:city":"Dover",
    "sg:classifiers":[
        {
            "category":"Education",
            "subcategory":"Library",
            "type":"Public Place"
        }
    ],
    "sg:phone":"+1 302 674 8124",
    "sg:postcode":"19901",
    "sg:province":"DE",
    "wof:name":"Delaware Library Assoc",
    "wof:placetype":"venue"
},
  "geometry": {"coordinates":[-75.54607,39.192986],"type":"Point"}
}