{
  "type": "Feature",
  "properties": {
    "addr:full":"851 N Broad St Middletown DE 19709",
    "addr:housenumber":"851",
    "addr:postcode":"19709",
    "addr:street":"N Broad St",
    "iso:country":"US",
    "sg:address":"851 N Broad St",
    "sg:city":"Middletown",
    "sg:classifiers":[
        {
            "category":"Retail",
            "subcategory":"Car Wash",
            "type":"Services"
        }
    ],
    "sg:phone":"+1 302 376 7767",
    "sg:postcode":"19709",
    "sg:province":"DE",
    "sg:tags":[
        "carwash"
    ],
    "wof:name":"Middletown Car Wash",
    "wof:placetype":"venue"
},
  "geometry": {"coordinates":[-75.720293,39.460682],"type":"Point"}
}