{
  "type": "Feature",
  "properties": {
    "addr:full":"2205 Silverside Rd Ste 4 Wilmington DE 19810",
    "addr:housenumber":"2205",
    "addr:postcode":"19810",
    "addr:street":"Silverside Rd Ste 4",
    "iso:country":"US",
    "sg:address":"2205 Silverside Rd Ste 4",
    "sg:city":"Wilmington",
    "sg:classifiers":[
        {
            "category":"Professional",
            "subcategory":"Lawyer & Legal Services",
            "type":"Services"
        }
    ],
    "sg:phone":"+1 302 475 7790",
    "sg:postcode":"19810",
    "sg:province":"DE",
    "sg:tags":[
        "notary"
    ],
    "wof:name":"Hallstead Elaine R Ins",
    "wof:placetype":"venue"
},
  "geometry": {"coordinates":[-75.505898,39.8027],"type":"Point"}
}