{
  "type": "Feature",
  "properties": {
    "iso:country":"US",
    "sg:address":"6 Delaware Ave",
    "sg:city":"Rehoboth Beach",
    "sg:classifiers":[
        {
            "category":"Recreation",
            "subcategory":"Arcade",
            "type":"Entertainment"
        }
    ],
    "sg:phone":"+1 302 227 2785",
    "sg:postcode":"19971",
    "sg:province":"DE",
    "sg:tags":[
        "amusement",
        "devices"
    ],
    "wof:name":"Seaside Amusements Inc",
    "wof:placetype":"venue"
},
  "geometry": {"coordinates":[-75.07642,38.714786],"type":"Point"}
}