{
  "type": "Feature",
  "properties": {
    "iso:country":"US",
    "sg:address":"23738 Old Meadow Rd",
    "sg:city":"Seaford",
    "sg:classifiers":[
        {
            "category":"Food & Beverages",
            "subcategory":"Specialty",
            "type":"Retail Goods"
        },
        {
            "category":"Professional",
            "type":"Services"
        }
    ],
    "sg:phone":"+1 302 628 5447",
    "sg:postcode":"19973",
    "sg:province":"DE",
    "sg:tags":[
        "herb"
    ],
    "wof:name":"Itchita's Way",
    "wof:placetype":"venue"
},
  "geometry": {"coordinates":[-75.56546299999999,38.657965],"type":"Point"}
}