{
  "type": "Feature",
  "properties": {
    "iso:country":"US",
    "sg:address":"4300 Kennett Pike",
    "sg:city":"Wilmington",
    "sg:classifiers":[
        {
            "category":"Professional",
            "subcategory":"Management & Consulting",
            "type":"Services"
        }
    ],
    "sg:phone":"+1 302 656 7257",
    "sg:postcode":"19807",
    "sg:province":"DE",
    "sg:tags":[
        "consultant",
        "safety"
    ],
    "wof:name":"Hobbsco LTD",
    "wof:placetype":"venue"
},
  "geometry": {"coordinates":[-75.603329,39.787295],"type":"Point"}
}