{
  "type": "Feature",
  "properties": {
    "iso:country":"US",
    "sg:address":"98 Clinton St",
    "sg:city":"Delaware City",
    "sg:classifiers":[
        {
            "category":"Shopping",
            "subcategory":"Gifts & Souvenirs",
            "type":"Retail Goods"
        }
    ],
    "sg:phone":"+1 302 834 0138",
    "sg:postcode":"19706",
    "sg:province":"DE",
    "sg:tags":[
        "collectible"
    ],
    "wof:name":"T & T Collectables",
    "wof:placetype":"venue"
},
  "geometry": {"coordinates":[-75.589477,39.577774],"type":"Point"}
}