{
  "type": "Feature",
  "properties": {
    "addr:full":"913 Horsepond Rd Dover DE 19901",
    "addr:housenumber":"913",
    "addr:postcode":"19901",
    "addr:street":"Horsepond Rd",
    "iso:country":"US",
    "sg:address":"913 Horsepond Rd",
    "sg:city":"Dover",
    "sg:classifiers":[
        {
            "category":"Farming",
            "subcategory":"Livestock Farm",
            "type":"Manufacturing & Wholesale Goods"
        },
        {
            "category":"Wholesale",
            "subcategory":"Electrical",
            "type":"Manufacturing & Wholesale Goods"
        }
    ],
    "sg:phone":"+1 302 734 9250",
    "sg:postcode":"19901",
    "sg:province":"DE",
    "sg:tags":[
        "communication",
        "computer",
        "radio",
        "system",
        "electronic"
    ],
    "wof:name":"Magnum Electronics Inc",
    "wof:placetype":"venue"
},
  "geometry": {"coordinates":[-75.485184,39.149999],"type":"Point"}
}