{
  "type": "Feature",
  "properties": {
    "iso:country":"US",
    "sg:address":"340 S Market St",
    "sg:city":"Wilmington",
    "sg:classifiers":[
        {
            "category":"Restaurant",
            "type":"Food & Drink"
        }
    ],
    "sg:phone":"+1 302 652 5646",
    "sg:postcode":"19801",
    "sg:province":"DE",
    "wof:name":"Pharos Of Wilmington",
    "wof:placetype":"venue"
},
  "geometry": {"coordinates":[-75.556333,39.732802],"type":"Point"}
}