{
  "type": "Feature",
  "properties": {
    "iso:country":"US",
    "sg:address":"2300 Pennsylvania Ave",
    "sg:city":"Wilmington",
    "sg:classifiers":[
        {
            "category":"Real Estate",
            "subcategory":"Real Estate Operator",
            "type":"Services"
        }
    ],
    "sg:phone":"+1 302 654 7575",
    "sg:postcode":"19806",
    "sg:province":"DE",
    "sg:tags":[
        "building",
        "nonresidential"
    ],
    "wof:name":"Mrt Properties LLC",
    "wof:placetype":"venue"
},
  "geometry": {"coordinates":[-75.573144,39.75915],"type":"Point"}
}