{
  "type": "Feature",
  "properties": {
    "iso:country":"US",
    "sg:address":"1900 N Dupont Hwy",
    "sg:city":"New Castle",
    "sg:classifiers":[
        {
            "category":"Government",
            "subcategory":"Office",
            "type":"Public Place"
        }
    ],
    "sg:phone":"+1 302 577 4960",
    "sg:postcode":"19720",
    "sg:province":"DE",
    "wof:name":"Retired Senior Program",
    "wof:placetype":"venue"
},
  "geometry": {"coordinates":[-75.57189,39.700281],"type":"Point"}
}