{
  "type": "Feature",
  "properties": {
    "iso:country":"US",
    "sg:address":"303 N Bedford St",
    "sg:city":"Georgetown",
    "sg:classifiers":[
        {
            "category":"Professional",
            "subcategory":"Lawyer & Legal Services",
            "type":"Services"
        }
    ],
    "sg:phone":"+1 302 856 9021",
    "sg:postcode":"19947",
    "sg:province":"DE",
    "sg:tags":[
        "attorney"
    ],
    "sg:website":"www.davislawoff.com",
    "wof:name":"Henry Clay Davis III Pa",
    "wof:placetype":"venue"
},
  "geometry": {"coordinates":[-75.389985,38.693673],"type":"Point"}
}