{
  "type": "Feature",
  "properties": {
    "addr:full":"262 Chapman Rd Newark DE 19702",
    "addr:housenumber":"262",
    "addr:postcode":"19702",
    "addr:street":"Chapman Rd",
    "iso:country":"US",
    "sg:address":"262 Chapman Rd",
    "sg:city":"Newark",
    "sg:classifiers":[
        {
            "category":"Professional",
            "subcategory":"Detective & Security Services",
            "type":"Services"
        }
    ],
    "sg:phone":"+1 302 737 0420",
    "sg:postcode":"19702",
    "sg:province":"DE",
    "sg:tags":[
        "car"
    ],
    "wof:name":"Initial Security",
    "wof:placetype":"venue"
},
  "geometry": {"coordinates":[-75.675057,39.66788],"type":"Point"}
}