{
  "type": "Feature",
  "properties": {
    "addr:full":"121 Duke of York St Dover DE 19901",
    "addr:housenumber":"121",
    "addr:postcode":"19901",
    "addr:street":"Duke Of York St",
    "iso:country":"US",
    "sg:address":"121 Duke of York St",
    "sg:city":"Dover",
    "sg:classifiers":[
        {
            "category":"Education",
            "subcategory":"Library",
            "type":"Public Place"
        }
    ],
    "sg:phone":"+1 302 739 5318",
    "sg:postcode":"19901",
    "sg:province":"DE",
    "sg:tags":[
        "special",
        "interest"
    ],
    "wof:name":"Archives & Records",
    "wof:placetype":"venue"
},
  "geometry": {"coordinates":[-75.520984,39.157672],"type":"Point"}
}