{
  "type": "Feature",
  "properties": {
    "iso:country":"US",
    "sg:address":"140 Honora Dr",
    "sg:city":"Bear",
    "sg:classifiers":[
        {
            "category":"Building & Trades",
            "subcategory":"Plumbing",
            "type":"Services"
        }
    ],
    "sg:phone":"+1 302 376 6326",
    "sg:postcode":"19701",
    "sg:province":"DE",
    "sg:tags":[
        "plumbing",
        "contractor"
    ],
    "wof:name":"Garvey Plumbing",
    "wof:placetype":"venue"
},
  "geometry": {"coordinates":[-75.718416,39.572821],"type":"Point"}
}