{
  "type": "Feature",
  "properties": {
    "iso:country":"US",
    "sg:address":"143 Atlas Dr",
    "sg:city":"New Castle",
    "sg:classifiers":[
        {
            "category":"Autos & Motor Vehicles",
            "subcategory":"Boat Sales",
            "type":"Retail Goods"
        },
        {
            "category":"Professional",
            "type":"Services"
        }
    ],
    "sg:phone":"+1 302 777 7931",
    "sg:postcode":"19720",
    "sg:province":"DE",
    "sg:tags":[
        "equipment",
        "marine",
        "supply"
    ],
    "wof:name":"International Marine Developme",
    "wof:placetype":"venue"
},
  "geometry": {"coordinates":[-75.552753,39.688709],"type":"Point"}
}