{
  "type": "Feature",
  "properties": {
    "iso:country":"US",
    "sg:address":"4930 S Tupelo Turn",
    "sg:city":"Wilmington",
    "sg:classifiers":[
        {
            "category":"Wholesale",
            "subcategory":"Machinery & Supplies",
            "type":"Manufacturing & Wholesale Goods"
        }
    ],
    "sg:phone":"+1 302 239 2111",
    "sg:postcode":"19808",
    "sg:province":"DE",
    "sg:tags":[
        "equipment",
        "establishment"
    ],
    "wof:name":"Elements Beauty Supply Inc",
    "wof:placetype":"venue"
},
  "geometry": {"coordinates":[-75.706689,39.736979],"type":"Point"}
}