{
  "type": "Feature",
  "properties": {
    "iso:country":"US",
    "sg:address":"22237 Lewes Georgetown Hwy",
    "sg:city":"Georgetown",
    "sg:classifiers":[
        {
            "category":"Shopping",
            "type":"Retail Goods"
        }
    ],
    "sg:phone":"+1 302 854 9521",
    "sg:postcode":"19947",
    "sg:province":"DE",
    "sg:tags":[
        "merchandise",
        "monument"
    ],
    "wof:name":"Prestige Monuments & Mausoleum",
    "wof:placetype":"venue"
},
  "geometry": {"coordinates":[-75.34566599999999,38.7057],"type":"Point"}
}