{
  "type": "Feature",
  "properties": {
    "addr:full":"2615 Foulk Rd Wilmington DE 19810",
    "addr:housenumber":"2615",
    "addr:postcode":"19810",
    "addr:street":"Foulk Rd",
    "iso:country":"US",
    "sg:address":"2615 Foulk Rd",
    "sg:city":"Wilmington",
    "sg:classifiers":[
        {
            "category":"Professional",
            "type":"Services"
        }
    ],
    "sg:phone":"+1 302 475 3313",
    "sg:postcode":"19810",
    "sg:province":"DE",
    "sg:tags":[
        "organization",
        "religious"
    ],
    "wof:name":"Taylor Alfred Rev Res",
    "wof:placetype":"venue"
},
  "geometry": {"coordinates":[-75.499083,39.833133],"type":"Point"}
}