{
  "type": "Feature",
  "properties": {
    "iso:country":"US",
    "sg:address":"3201 Falcon Ln",
    "sg:city":"Wilmington",
    "sg:classifiers":[
        {
            "category":"Health Services",
            "subcategory":"Doctor",
            "type":"Services"
        }
    ],
    "sg:phone":"+1 302 239 1501",
    "sg:postcode":"19808",
    "sg:province":"DE",
    "sg:tags":[
        "medical"
    ],
    "wof:name":"Jeffrey J Stout Dr",
    "wof:placetype":"venue"
},
  "geometry": {"coordinates":[-75.686177,39.749997],"type":"Point"}
}