{
  "type": "Feature",
  "properties": {
    "addr:full":"9 E Loockerman St Dover DE 19901",
    "addr:housenumber":"9",
    "addr:postcode":"19901",
    "addr:street":"E Loockerman St",
    "iso:country":"US",
    "sg:address":"9 E Loockerman St",
    "sg:city":"Dover",
    "sg:classifiers":[
        {
            "category":"Social Services",
            "type":"Services"
        }
    ],
    "sg:phone":"+1 302 739 7150",
    "sg:postcode":"19901",
    "sg:province":"DE",
    "sg:tags":[
        "government"
    ],
    "wof:name":"Child Advocate Dept",
    "wof:placetype":"venue"
},
  "geometry": {"coordinates":[-75.523515,39.158281],"type":"Point"}
}