{
  "type": "Feature",
  "properties": {
    "addr:full":"4737 Concord Pike Wilmington DE 19803",
    "addr:housenumber":"4737",
    "addr:postcode":"19803",
    "addr:street":"Concord Pike",
    "iso:country":"US",
    "sg:address":"4737 Concord Pike",
    "sg:city":"Wilmington",
    "sg:classifiers":[
        {
            "category":"Shopping",
            "subcategory":"Clothing, Apparel, & Fashions",
            "type":"Retail Goods"
        },
        {
            "category":"Personal",
            "subcategory":"Shoe Repair & Shine",
            "type":"Services"
        },
        {
            "category":"Shopping",
            "subcategory":"Shoes",
            "type":"Retail Goods"
        }
    ],
    "sg:phone":"+1 302 478 5300",
    "sg:postcode":"19803",
    "sg:province":"DE",
    "sg:tags":[
        "dyer",
        "shoes-orthopedic",
        "store"
    ],
    "sg:website":"http://www.fastfeetshoerepair.com",
    "wof:name":"Fast Feet Shoe Repair Inc",
    "wof:placetype":"venue"
},
  "geometry": {"coordinates":[-75.546898,39.820999],"type":"Point"}
}