{
  "type": "Feature",
  "properties": {
    "addr:full":"3031 New Castle Ave New Castle DE 19720",
    "addr:housenumber":"3031",
    "addr:postcode":"19720",
    "addr:street":"New Castle Ave",
    "iso:country":"US",
    "sg:address":"3031 New Castle Ave",
    "sg:city":"New Castle",
    "sg:classifiers":[
        {
            "category":"Restaurant",
            "type":"Food & Drink"
        }
    ],
    "sg:phone":"+1 302 658 3278",
    "sg:postcode":"19720",
    "sg:province":"DE",
    "sg:tags":[
        "eating"
    ],
    "wof:name":"Fast Lane",
    "wof:placetype":"venue"
},
  "geometry": {"coordinates":[-75.552077,39.700676],"type":"Point"}
}