{
  "type": "Feature",
  "properties": {
    "iso:country":"US",
    "sg:address":"19 S Main St",
    "sg:city":"Selbyville",
    "sg:classifiers":[
        {
            "category":"Retail",
            "subcategory":"Auto Repair",
            "type":"Services"
        }
    ],
    "sg:phone":"+1 302 436 8013",
    "sg:postcode":"19975",
    "sg:province":"DE",
    "sg:tags":[
        "repairing",
        "automobile"
    ],
    "wof:name":"Hoban Service Ctr",
    "wof:placetype":"venue"
},
  "geometry": {"coordinates":[-75.224588,38.464885],"type":"Point"}
}