{
  "type": "Feature",
  "properties": {
    "addr:full":"1756 Skeeter Neck Rd Frederica DE 19946",
    "addr:housenumber":"1756",
    "addr:postcode":"19946",
    "addr:street":"Skeeter Neck Rd",
    "iso:country":"US",
    "sg:address":"1756 Skeeter Neck Rd",
    "sg:city":"Frederica",
    "sg:classifiers":[
        {
            "category":"Professional",
            "type":"Services"
        }
    ],
    "sg:phone":"+1 302 335 0812",
    "sg:postcode":"19946",
    "sg:province":"DE",
    "wof:name":"R H Eff Sgm",
    "wof:placetype":"venue"
},
  "geometry": {"coordinates":[-75.443552,39.036266],"type":"Point"}
}