{
  "type": "Feature",
  "properties": {
    "addr:full":"401 E Main St Ste A Middletown DE 19709",
    "addr:housenumber":"401",
    "addr:postcode":"19709",
    "addr:street":"E Main St Ste A",
    "iso:country":"US",
    "sg:address":"401 E Main St Ste A",
    "sg:city":"Middletown",
    "sg:classifiers":[
        {
            "category":"Health Services",
            "subcategory":"Optometrist",
            "type":"Services"
        },
        {
            "category":"Shopping",
            "subcategory":"Optician",
            "type":"Retail Goods"
        }
    ],
    "sg:phone":"+1 302 378 8818",
    "sg:postcode":"19709",
    "sg:province":"DE",
    "sg:tags":[
        "optical"
    ],
    "wof:name":"Middletown Eye Care Inc",
    "wof:placetype":"venue"
},
  "geometry": {"coordinates":[-75.70163700000001,39.45047],"type":"Point"}
}