{
  "type": "Feature",
  "properties": {
    "iso:country":"US",
    "sg:address":"3326 Altamont Dr",
    "sg:city":"Wilmington",
    "sg:classifiers":[
        {
            "category":"Social Services",
            "subcategory":"Child Care",
            "type":"Services"
        }
    ],
    "sg:phone":"+1 302 478 1274",
    "sg:postcode":"19810",
    "sg:province":"DE",
    "sg:tags":[
        "day"
    ],
    "wof:name":"Shermans Family Day Care Ctr",
    "wof:placetype":"venue"
},
  "geometry": {"coordinates":[-75.540965,39.825273],"type":"Point"}
}