{
  "type": "Feature",
  "properties": {
    "addr:full":"8014 Bay Rd Frederica DE 19946",
    "addr:housenumber":"8014",
    "addr:postcode":"19946",
    "addr:street":"Bay Rd",
    "iso:country":"US",
    "sg:address":"8014 Bay Rd",
    "sg:city":"Frederica",
    "sg:classifiers":[
        {
            "category":"Building & Trades",
            "subcategory":"Equipment Rental",
            "type":"Services"
        }
    ],
    "sg:phone":"+1 302 335 6300",
    "sg:postcode":"19946",
    "sg:province":"DE",
    "sg:website":"www.unitedrentals.com",
    "wof:name":"United Rentals",
    "wof:placetype":"venue"
},
  "geometry": {"coordinates":[-75.45740000000001,39.045439],"type":"Point"}
}