{
  "type": "Feature",
  "properties": {
    "iso:country":"US",
    "sg:address":"1511 Willow Grove Rd",
    "sg:city":"Felton",
    "sg:classifiers":[
        {
            "category":"Building & Trades",
            "subcategory":"Construction",
            "type":"Services"
        }
    ],
    "sg:phone":"+1 302 284 2936",
    "sg:postcode":"19943",
    "sg:province":"DE",
    "sg:tags":[
        "tile-contractors"
    ],
    "wof:name":"Macemcy Tile Installation",
    "wof:placetype":"venue"
},
  "geometry": {"coordinates":[-75.718266,39.033796],"type":"Point"}
}