{
  "type": "Feature",
  "properties": {
    "iso:country":"US",
    "sg:address":"507 W 9th St",
    "sg:city":"Wilmington",
    "sg:classifiers":[
        {
            "category":"Professional",
            "subcategory":"Lawyer & Legal Services",
            "type":"Services"
        }
    ],
    "sg:phone":"+1 302 655 5518",
    "sg:postcode":"19801",
    "sg:province":"DE",
    "sg:tags":[
        "referral",
        "for",
        "elderly"
    ],
    "wof:name":"Supportive Care Service Inc",
    "wof:placetype":"venue"
},
  "geometry": {"coordinates":[-75.552881,39.74657],"type":"Point"}
}