{
  "type": "Feature",
  "properties": {
    "iso:country":"US",
    "sg:address":"802 N West St",
    "sg:city":"Wilmington",
    "sg:classifiers":[
        {
            "category":"Banks & Credit Unions",
            "subcategory":"Financial Services",
            "type":"Services"
        }
    ],
    "sg:phone":"+1 302 428 0515",
    "sg:postcode":"19801",
    "sg:province":"DE",
    "sg:tags":[
        "company",
        "holding"
    ],
    "wof:name":"Corporate Holding Svc Inc",
    "wof:placetype":"venue"
},
  "geometry": {"coordinates":[-75.551383,39.745845],"type":"Point"}
}