{
  "type": "Feature",
  "properties": {
    "addr:full":"33 N Walnut St Milford DE 19963",
    "addr:housenumber":"33",
    "addr:postcode":"19963",
    "addr:street":"N Walnut St",
    "iso:country":"US",
    "sg:address":"33 N Walnut St",
    "sg:city":"Milford",
    "sg:classifiers":[
        {
            "category":"Banks & Credit Unions",
            "subcategory":"Investment Brokerage",
            "type":"Services"
        }
    ],
    "sg:phone":"+1 302 424 1185",
    "sg:postcode":"19963",
    "sg:province":"DE",
    "sg:tags":[
        "security"
    ],
    "wof:name":"Comprehensive Financial Svcs",
    "wof:placetype":"venue"
},
  "geometry": {"coordinates":[-75.428121,38.914239],"type":"Point"}
}