{
  "type": "Feature",
  "properties": {
    "addr:full":"1524 E Lebanon Rd Dover DE 19901",
    "addr:housenumber":"1524",
    "addr:postcode":"19901",
    "addr:street":"E Lebanon Rd",
    "iso:country":"US",
    "sg:address":"1524 E Lebanon Rd",
    "sg:city":"Dover",
    "sg:classifiers":[
        {
            "category":"Building & Trades",
            "subcategory":"Construction",
            "type":"Services"
        }
    ],
    "sg:phone":"+1 302 698 5402",
    "sg:postcode":"19901",
    "sg:province":"DE",
    "sg:tags":[
        "contractor"
    ],
    "wof:name":"Mid-Atlantic Dismantlement Corp",
    "wof:placetype":"venue"
},
  "geometry": {"coordinates":[-75.499143,39.123897],"type":"Point"}
}