{
  "type": "Feature",
  "properties": {
    "iso:country":"US",
    "sg:address":"721 N Broad St",
    "sg:city":"Middletown",
    "sg:classifiers":[
        {
            "category":"Shopping",
            "subcategory":"Hobbies, Toys, & Games",
            "type":"Retail Goods"
        }
    ],
    "sg:phone":"+1 302 378 9777",
    "sg:postcode":"19709",
    "sg:province":"DE",
    "sg:tags":[
        "craft"
    ],
    "wof:name":"Scrapbooking & More",
    "wof:placetype":"venue"
},
  "geometry": {"coordinates":[-75.719808,39.459391],"type":"Point"}
}