{
  "type": "Feature",
  "properties": {
    "iso:country":"US",
    "sg:address":"782 Kersey Rd",
    "sg:city":"Viola",
    "sg:classifiers":[
        {
            "category":"Retail",
            "subcategory":"Animal Services",
            "type":"Services"
        }
    ],
    "sg:phone":"+1 302 284 9788",
    "sg:postcode":"19979",
    "sg:province":"DE",
    "sg:tags":[
        "farm",
        "raw",
        "product",
        "material"
    ],
    "wof:name":"Sugar Creek Farm Inc",
    "wof:placetype":"venue"
},
  "geometry": {"coordinates":[-75.59440499999999,39.040695],"type":"Point"}
}