{
  "type": "Feature",
  "properties": {
    "iso:country":"US",
    "sg:address":"1702 Cherry St",
    "sg:city":"Wilmington",
    "sg:classifiers":[
        {
            "category":"Building & Trades",
            "subcategory":"Construction",
            "type":"Services"
        }
    ],
    "sg:phone":"+1 302 792 1822",
    "sg:postcode":"19809",
    "sg:province":"DE",
    "sg:tags":[
        "house"
    ],
    "wof:name":"David T Hollett Construction",
    "wof:placetype":"venue"
},
  "geometry": {"coordinates":[-75.474778,39.786371],"type":"Point"}
}