{
  "type": "Feature",
  "properties": {
    "iso:country":"US",
    "sg:address":"1014 White Birch Dr",
    "sg:city":"Newark",
    "sg:classifiers":[
        {
            "category":"Wholesale",
            "subcategory":"Chemicals & Plastics",
            "type":"Manufacturing & Wholesale Goods"
        }
    ],
    "sg:phone":"+1 302 366 1408",
    "sg:postcode":"19713",
    "sg:province":"DE",
    "sg:tags":[
        "water",
        "treatment"
    ],
    "wof:name":"Water-Tec Inc",
    "wof:placetype":"venue"
},
  "geometry": {"coordinates":[-75.77148200000001,39.644634],"type":"Point"}
}