{
  "type": "Feature",
  "properties": {
    "iso:country":"US",
    "sg:address":"3305 S Dupont Pkwy",
    "sg:city":"Townsend",
    "sg:classifiers":[
        {
            "category":"Retail",
            "subcategory":"Repair Shop",
            "type":"Services"
        }
    ],
    "sg:phone":"+1 302 378 7116",
    "sg:postcode":"19734",
    "sg:province":"DE",
    "sg:tags":[
        "reupholsters",
        "upholsterer",
        "furniture"
    ],
    "wof:name":"Charles Andrews Upholstery",
    "wof:placetype":"venue"
},
  "geometry": {"coordinates":[-75.66033899999999,39.43609],"type":"Point"}
}