{
  "type": "Feature",
  "properties": {
    "addr:full":"606 New Rd Wilmington DE 19805",
    "addr:housenumber":"606",
    "addr:postcode":"19805",
    "addr:street":"New Rd",
    "iso:country":"US",
    "sg:address":"606 New Rd",
    "sg:city":"Wilmington",
    "sg:classifiers":[
        {
            "category":"Organizations",
            "subcategory":"Religious Organization",
            "type":"Services"
        }
    ],
    "sg:phone":"+1 302 998 6365",
    "sg:postcode":"19805",
    "sg:province":"DE",
    "sg:tags":[
        "child",
        "day",
        "care"
    ],
    "wof:name":"Elsmere Presbyterian Church",
    "wof:placetype":"venue"
},
  "geometry": {"coordinates":[-75.59322,39.739923],"type":"Point"}
}