{
  "type": "Feature",
  "properties": {
    "addr:full":"12 S Main St Selbyville DE 19975",
    "addr:housenumber":"12",
    "addr:postcode":"19975",
    "addr:street":"S Main St",
    "iso:country":"US",
    "sg:address":"12 S Main St",
    "sg:city":"Selbyville",
    "sg:classifiers":[
        {
            "category":"Autos & Motor Vehicles",
            "subcategory":"Auto Supplies",
            "type":"Retail Goods"
        }
    ],
    "sg:phone":"+1 302 436 5114",
    "sg:postcode":"19975",
    "sg:province":"DE",
    "sg:tags":[
        "automobile",
        "parts"
    ],
    "wof:name":"Selbyville Auto Parts",
    "wof:placetype":"venue"
},
  "geometry": {"coordinates":[-75.220527,38.459309],"type":"Point"}
}