{
  "type": "Feature",
  "properties": {
    "iso:country":"US",
    "sg:address":"2751 Centerville Rd",
    "sg:city":"Wilmington",
    "sg:classifiers":[
        {
            "category":"Banks & Credit Unions",
            "subcategory":"Investment Brokerage",
            "type":"Services"
        }
    ],
    "sg:phone":"+1 302 994 6337",
    "sg:postcode":"19808",
    "sg:province":"DE",
    "sg:tags":[
        "security"
    ],
    "wof:name":"Hilliard Lyons Inc",
    "wof:placetype":"venue"
},
  "geometry": {"coordinates":[-75.624624,39.753755],"type":"Point"}
}