{
  "type": "Feature",
  "properties": {
    "iso:country":"US",
    "sg:address":"500 Union Church Rd",
    "sg:city":"Townsend",
    "sg:classifiers":[
        {
            "category":"Freight",
            "type":"Transportation"
        }
    ],
    "sg:phone":"+1 302 378 1664",
    "sg:postcode":"19734",
    "sg:province":"DE",
    "sg:tags":[
        "operator",
        "local",
        "trucking"
    ],
    "wof:name":"Ashs Equipment Rental Inc",
    "wof:placetype":"venue"
},
  "geometry": {"coordinates":[-75.65260600000001,39.386215],"type":"Point"}
}