{
  "type": "Feature",
  "properties": {
    "iso:country":"US",
    "sg:address":"2 E Main St",
    "sg:city":"Middletown",
    "sg:classifiers":[
        {
            "category":"Coffee & Tea",
            "type":"Food & Drink"
        },
        {
            "category":"Restaurant",
            "type":"Food & Drink"
        }
    ],
    "sg:phone":"+1 302 464 1144",
    "sg:postcode":"19709",
    "sg:province":"DE",
    "sg:tags":[
        "espresso"
    ],
    "wof:name":"Soul To Soul Cafe",
    "wof:placetype":"venue"
},
  "geometry": {"coordinates":[-75.71668200000001,39.449699],"type":"Point"}
}