{
  "type": "Feature",
  "properties": {
    "iso:country":"US",
    "sg:address":"500 Milton Dr",
    "sg:city":"Wilmington",
    "sg:classifiers":[
        {
            "category":"Professional",
            "subcategory":"Engineering",
            "type":"Services"
        }
    ],
    "sg:phone":"+1 302 765 2866",
    "sg:postcode":"19802",
    "sg:province":"DE",
    "wof:name":"Robert A Basye",
    "wof:placetype":"venue"
},
  "geometry": {"coordinates":[-75.525685,39.770752],"type":"Point"}
}