{
  "type": "Feature",
  "properties": {
    "addr:full":"313 S Dupont Pkwy Odessa DE 19709",
    "addr:housenumber":"313",
    "addr:postcode":"19709",
    "addr:street":"S Dupont Pkwy",
    "iso:country":"US",
    "sg:address":"313 S Dupont Pkwy",
    "sg:city":"Odessa",
    "sg:classifiers":[
        {
            "category":"Professional",
            "subcategory":"Management & Consulting",
            "type":"Services"
        }
    ],
    "sg:phone":"+1 302 696 6000",
    "sg:postcode":"19709",
    "sg:province":"DE",
    "sg:tags":[
        "consultant"
    ],
    "wof:name":"Nucar Consulting",
    "wof:placetype":"venue"
},
  "geometry": {"coordinates":[-75.660293,39.458864],"type":"Point"}
}