{
  "type": "Feature",
  "properties": {
    "iso:country":"US",
    "sg:address":"2213 Ogletown Rd",
    "sg:city":"Newark",
    "sg:classifiers":[
        {
            "category":"Retail",
            "subcategory":"Auto Repair",
            "type":"Services"
        }
    ],
    "sg:phone":"+1 302 733 7639",
    "sg:postcode":"19711",
    "sg:province":"DE",
    "sg:tags":[
        "repairing",
        "automobile",
        "automotive"
    ],
    "wof:name":"Calling All Cars",
    "wof:placetype":"venue"
},
  "geometry": {"coordinates":[-75.72258100000001,39.684785],"type":"Point"}
}