{
  "type": "Feature",
  "properties": {
    "iso:country":"US",
    "sg:address":"6343 Summit Bridge Rd",
    "sg:city":"Townsend",
    "sg:classifiers":[
        {
            "category":"Real Estate",
            "subcategory":"Real Estate Services",
            "type":"Services"
        },
        {
            "category":"Retail",
            "subcategory":"Laundry & Dry Cleaning",
            "type":"Services"
        },
        {
            "category":"Building & Trades",
            "subcategory":"Cleaning & Sanitation",
            "type":"Services"
        }
    ],
    "sg:phone":"+1 302 996 0210",
    "sg:postcode":"19734",
    "sg:province":"DE",
    "sg:tags":[
        "cleaner",
        "upholstery",
        "house",
        "rug",
        "maintenance",
        "cleaners-interior",
        "carpet"
    ],
    "wof:name":"Keep It Movin' Carpet & Furniture Cleaners",
    "wof:placetype":"venue"
},
  "geometry": {"coordinates":[-75.665932,39.381518],"type":"Point"}
}