{
  "type": "Feature",
  "properties": {
    "iso:country":"US",
    "sg:address":"5700 Kirkwood Hwy",
    "sg:city":"Wilmington",
    "sg:classifiers":[
        {
            "category":"Professional",
            "subcategory":"Engineering",
            "type":"Services"
        }
    ],
    "sg:phone":"+1 302 996 9500",
    "sg:postcode":"19808",
    "sg:province":"DE",
    "sg:tags":[
        "consulting",
        "structural",
        "engineer"
    ],
    "sg:website":"www.gredell.com",
    "wof:name":"Gredell & Associates",
    "wof:placetype":"venue"
},
  "geometry": {"coordinates":[-75.674108,39.714838],"type":"Point"}
}