{
  "type": "Feature",
  "properties": {
    "addr:full":"2502 Philadelphia Pike Claymont DE 19703",
    "addr:housenumber":"2502",
    "addr:postcode":"19703",
    "addr:street":"Philadelphia Pike",
    "iso:country":"US",
    "sg:address":"2502 Philadelphia Pike",
    "sg:city":"Claymont",
    "sg:classifiers":[
        {
            "category":"Personal",
            "subcategory":"Tattoo Parlor",
            "type":"Services"
        }
    ],
    "sg:phone":"+1 302 798 9020",
    "sg:postcode":"19703",
    "sg:province":"DE",
    "sg:tags":[
        "tattooing"
    ],
    "wof:name":"Fireball Tattoo Parlor",
    "wof:placetype":"venue"
},
  "geometry": {"coordinates":[-75.468796,39.793306],"type":"Point"}
}