{
  "type": "Feature",
  "properties": {
    "iso:country":"US",
    "sg:address":"17 Newland Ct",
    "sg:city":"Newark",
    "sg:classifiers":[
        {
            "category":"Building & Trades",
            "subcategory":"Landscaping Services",
            "type":"Services"
        }
    ],
    "sg:phone":"+1 302 738 4967",
    "sg:postcode":"19713",
    "sg:province":"DE",
    "wof:name":"Green Acres Lawn & Tree Svc",
    "wof:placetype":"venue"
},
  "geometry": {"coordinates":[-75.70974699999999,39.66131],"type":"Point"}
}