{
  "type": "Feature",
  "properties": {
    "iso:country":"US",
    "sg:address":"580 Lafferty Ln",
    "sg:city":"Dover",
    "sg:classifiers":[
        {
            "category":"Wholesale",
            "subcategory":"Construction Materials",
            "type":"Manufacturing & Wholesale Goods"
        }
    ],
    "sg:phone":"+1 302 678 1080",
    "sg:postcode":"19901",
    "sg:province":"DE",
    "sg:tags":[
        "roofing",
        "siding"
    ],
    "wof:name":"S G Williams Of Dover Inc",
    "wof:placetype":"venue"
},
  "geometry": {"coordinates":[-75.493623,39.145226],"type":"Point"}
}