{
  "type": "Feature",
  "properties": {
    "iso:country":"US",
    "sg:address":"118 E Ayre St",
    "sg:city":"Newport",
    "sg:classifiers":[
        {
            "category":"Retail",
            "subcategory":"Auto Repair",
            "type":"Services"
        }
    ],
    "sg:phone":"+1 302 998 5958",
    "sg:postcode":"19804",
    "sg:province":"DE",
    "sg:tags":[
        "shop",
        "automotive",
        "machine",
        "truck",
        "automobile"
    ],
    "sg:website":"www.americanautomotive.com",
    "wof:name":"American Automotive Service",
    "wof:placetype":"venue"
},
  "geometry": {"coordinates":[-75.607505,39.712887],"type":"Point"}
}