{
  "type": "Feature",
  "properties": {
    "addr:full":"228 W Loockerman St Dover DE 19904",
    "addr:housenumber":"228",
    "addr:postcode":"19904",
    "addr:street":"W Loockerman St",
    "iso:country":"US",
    "sg:address":"228 W Loockerman St",
    "sg:city":"Dover",
    "sg:classifiers":[
        {
            "category":"Professional",
            "type":"Services"
        }
    ],
    "sg:phone":"+1 302 734 9610",
    "sg:postcode":"19904",
    "sg:province":"DE",
    "wof:name":"Career Closet",
    "wof:placetype":"venue"
},
  "geometry": {"coordinates":[-75.527264,39.157511],"type":"Point"}
}