{
  "type": "Feature",
  "properties": {
    "iso:country":"US",
    "sg:address":"1202 Savannah Rd",
    "sg:city":"Lewes",
    "sg:classifiers":[
        {
            "category":"Home & Garden",
            "subcategory":"Home Furnishings",
            "type":"Retail Goods"
        }
    ],
    "sg:phone":"+1 302 645 5295",
    "sg:postcode":"19958",
    "sg:province":"DE",
    "sg:tags":[
        "repair"
    ],
    "wof:name":"Emick Upholstery",
    "wof:placetype":"venue"
},
  "geometry": {"coordinates":[-75.15274100000001,38.761372],"type":"Point"}
}