{
  "type": "Feature",
  "properties": {
    "addr:full":"311 Jessica Dr Middletown DE 19709",
    "addr:housenumber":"311",
    "addr:postcode":"19709",
    "addr:street":"Jessica Dr",
    "iso:country":"US",
    "sg:address":"311 Jessica Dr",
    "sg:city":"Middletown",
    "sg:classifiers":[
        {
            "category":"Professional",
            "subcategory":"Business Services",
            "type":"Services"
        }
    ],
    "sg:phone":"+1 302 378 9284",
    "sg:postcode":"19709",
    "sg:province":"DE",
    "wof:name":"Cvg Technical Solutions Llc",
    "wof:placetype":"venue"
},
  "geometry": {"coordinates":[-75.733897,39.534572],"type":"Point"}
}