{
  "type": "Feature",
  "properties": {
    "iso:country":"US",
    "sg:address":"4486 N Dupont Hwy",
    "sg:city":"Dover",
    "sg:classifiers":[
        {
            "category":"Home & Garden",
            "subcategory":"Building Materials",
            "type":"Retail Goods"
        }
    ],
    "sg:phone":"+1 302 678 3435",
    "sg:postcode":"19901",
    "sg:province":"DE",
    "wof:name":"Overhead Door Co Central De",
    "wof:placetype":"venue"
},
  "geometry": {"coordinates":[-75.57056900000001,39.210683],"type":"Point"}
}