{
  "type": "Feature",
  "properties": {
    "addr:full":"1604 Delaware Ave Wilmington DE 19806",
    "addr:housenumber":"1604",
    "addr:postcode":"19806",
    "addr:street":"Delaware Ave",
    "iso:country":"US",
    "sg:address":"1604 Delaware Ave",
    "sg:city":"Wilmington",
    "sg:classifiers":[
        {
            "category":"Professional",
            "subcategory":"Computer Services",
            "type":"Services"
        }
    ],
    "sg:phone":"+1 302 573 6909",
    "sg:postcode":"19806",
    "sg:province":"DE",
    "sg:website":"www.turn-keyservices.com",
    "wof:name":"Turn Key Svc",
    "wof:placetype":"venue"
},
  "geometry": {"coordinates":[-75.56250199999999,39.757887],"type":"Point"}
}