{
  "type": "Feature",
  "properties": {
    "iso:country":"US",
    "sg:address":"5600 Concord Pike",
    "sg:city":"Wilmington",
    "sg:classifiers":[
        {
            "category":"Shopping",
            "subcategory":"Mobile Phones",
            "type":"Retail Goods"
        }
    ],
    "sg:phone":"+1 302 478 4626",
    "sg:postcode":"19803",
    "sg:province":"DE",
    "sg:website":"www.gowireless.net",
    "wof:name":"Go Wireless",
    "wof:placetype":"venue"
},
  "geometry": {"coordinates":[-75.54325799999999,39.833546],"type":"Point"}
}