{
  "type": "Feature",
  "properties": {
    "iso:country":"US",
    "sg:address":"1805 Foulk Rd Ste H",
    "sg:city":"Wilmington",
    "sg:classifiers":[
        {
            "category":"Insurance",
            "subcategory":"Hazard Insurance",
            "type":"Services"
        },
        {
            "category":"Insurance",
            "subcategory":"Insurance Agent",
            "type":"Services"
        },
        {
            "category":"Insurance",
            "subcategory":"Life Insurance",
            "type":"Services"
        },
        {
            "category":"Insurance",
            "subcategory":"Title Insurance",
            "type":"Services"
        }
    ],
    "sg:phone":"+1 877 669 6877",
    "sg:postcode":"19810",
    "sg:province":"DE",
    "sg:tags":[
        "consultant",
        "homeowner",
        "auto",
        "property",
        "analyst",
        "casualty"
    ],
    "wof:name":"Nationwide Insurance- Brown Ins & Fin Serv Inc",
    "wof:placetype":"venue"
},
  "geometry": {"coordinates":[-75.51445,39.80904],"type":"Point"}
}