{
  "type": "Feature",
  "properties": {
    "addr:full":"307 Markus Ct Newark DE 19713",
    "addr:housenumber":"307",
    "addr:postcode":"19713",
    "addr:street":"Markus Ct",
    "iso:country":"US",
    "sg:address":"307 Markus Ct",
    "sg:city":"Newark",
    "sg:classifiers":[
        {
            "category":"Retail",
            "subcategory":"Repair Shop",
            "type":"Services"
        }
    ],
    "sg:phone":"+1 302 368 8760",
    "sg:postcode":"19713",
    "sg:province":"DE",
    "sg:tags":[
        "sharpening",
        "tool",
        "industrial",
        "grinding"
    ],
    "sg:website":"www.jagrinding.com",
    "wof:name":"J & A Grinding Inc",
    "wof:placetype":"venue"
},
  "geometry": {"coordinates":[-75.777323,39.657509],"type":"Point"}
}