{
  "type": "Feature",
  "properties": {
    "iso:country":"US",
    "sg:address":"16 Yew Rd",
    "sg:city":"Newark",
    "sg:classifiers":[
        {
            "category":"Building & Trades",
            "subcategory":"Cleaning & Sanitation",
            "type":"Services"
        }
    ],
    "sg:phone":"+1 302 455 1777",
    "sg:postcode":"19702",
    "sg:province":"DE",
    "sg:tags":[
        "janitor"
    ],
    "wof:name":"Grenn N Clean Inc",
    "wof:placetype":"venue"
},
  "geometry": {"coordinates":[-75.703451,39.627997],"type":"Point"}
}