{
  "type": "Feature",
  "properties": {
    "iso:country":"US",
    "sg:address":"83 Mahopac Dr",
    "sg:city":"Bear",
    "sg:classifiers":[
        {
            "category":"Personal",
            "type":"Services"
        }
    ],
    "sg:phone":"+1 302 838 0403",
    "sg:postcode":"19701",
    "sg:province":"DE",
    "sg:tags":[
        "control",
        "weight"
    ],
    "wof:name":"Herbalife Distributor",
    "wof:placetype":"venue"
},
  "geometry": {"coordinates":[-75.707661,39.619641],"type":"Point"}
}