{
  "type": "Feature",
  "properties": {
    "addr:full":"403 N Central Ave Laurel DE 19956",
    "addr:housenumber":"403",
    "addr:postcode":"19956",
    "addr:street":"N Central Ave",
    "iso:country":"US",
    "sg:address":"403 N Central Ave",
    "sg:city":"Laurel",
    "sg:classifiers":[
        {
            "category":"Restaurant",
            "type":"Food & Drink"
        }
    ],
    "sg:phone":"+1 302 875 4477",
    "sg:postcode":"19956",
    "sg:province":"DE",
    "sg:tags":[
        "pizza"
    ],
    "wof:name":"Pizza King",
    "wof:placetype":"venue"
},
  "geometry": {"coordinates":[-75.571793,38.560779],"type":"Point"}
}