{
  "type": "Feature",
  "properties": {
    "addr:full":"5 Church St Selbyville DE 19975",
    "addr:housenumber":"5",
    "addr:postcode":"19975",
    "addr:street":"Church St",
    "iso:country":"US",
    "sg:address":"5 Church St",
    "sg:city":"Selbyville",
    "sg:classifiers":[
        {
            "category":"Shopping",
            "subcategory":"Gifts & Souvenirs",
            "type":"Retail Goods"
        }
    ],
    "sg:phone":"+1 302 436 4824",
    "sg:postcode":"19975",
    "sg:province":"DE",
    "sg:tags":[
        "shop"
    ],
    "wof:name":"Gordon's Gifts",
    "wof:placetype":"venue"
},
  "geometry": {"coordinates":[-75.21971000000001,38.461011],"type":"Point"}
}