{
  "type": "Feature",
  "properties": {
    "iso:country":"US",
    "sg:address":"901 N Washington St",
    "sg:city":"Wilmington",
    "sg:classifiers":[
        {
            "category":"Professional",
            "subcategory":"Management & Consulting",
            "type":"Services"
        }
    ],
    "sg:phone":"+1 302 425 5274",
    "sg:postcode":"19801",
    "sg:province":"DE",
    "wof:name":"Lease Partners",
    "wof:placetype":"venue"
},
  "geometry": {"coordinates":[-75.551799,39.74717],"type":"Point"}
}