{
  "type": "Feature",
  "properties": {
    "addr:full":"5004 N Tupelo Turn Wilmington DE 19808",
    "addr:housenumber":"5004",
    "addr:postcode":"19808",
    "addr:street":"N Tupelo Turn",
    "iso:country":"US",
    "sg:address":"5004 N Tupelo Turn",
    "sg:city":"Wilmington",
    "sg:classifiers":[
        {
            "category":"Education",
            "subcategory":"Special Training",
            "type":"Public Place"
        }
    ],
    "sg:phone":"+1 302 239 3283",
    "sg:postcode":"19808",
    "sg:province":"DE",
    "wof:name":"Excelsior USA",
    "wof:placetype":"venue"
},
  "geometry": {"coordinates":[-75.70826,39.738796],"type":"Point"}
}