{
  "type": "Feature",
  "properties": {
    "addr:full":"4621 Sylvanus Dr Wilmington DE 19803",
    "addr:housenumber":"4621",
    "addr:postcode":"19803",
    "addr:street":"Sylvanus Dr",
    "iso:country":"US",
    "sg:address":"4621 Sylvanus Dr",
    "sg:city":"Wilmington",
    "sg:classifiers":[
        {
            "category":"Professional",
            "subcategory":"Computer Services",
            "type":"Services"
        }
    ],
    "sg:phone":"+1 302 762 3335",
    "sg:postcode":"19803",
    "sg:province":"DE",
    "sg:tags":[
        "related"
    ],
    "wof:name":"Neal Technological Enterprises",
    "wof:placetype":"venue"
},
  "geometry": {"coordinates":[-75.527299,39.77793],"type":"Point"}
}