{
  "type": "Feature",
  "properties": {
    "iso:country":"US",
    "sg:address":"33263 Melson Rd",
    "sg:city":"Delmar",
    "sg:classifiers":[
        {
            "category":"Building & Trades",
            "subcategory":"Construction",
            "type":"Services"
        }
    ],
    "sg:phone":"+1 410 896 3653",
    "sg:postcode":"21875",
    "sg:province":"DE",
    "sg:tags":[
        "concrete",
        "contractor"
    ],
    "wof:name":"Triple C",
    "wof:placetype":"venue"
},
  "geometry": {"coordinates":[-75.457572,38.440709],"type":"Point"}
}