{
  "type": "Feature",
  "properties": {
    "iso:country":"US",
    "sg:address":"14 Rehoboth Ave",
    "sg:city":"Rehoboth Beach",
    "sg:classifiers":[
        {
            "category":"Shopping",
            "subcategory":"Gifts & Souvenirs",
            "type":"Retail Goods"
        }
    ],
    "sg:phone":"+1 302 227 3017",
    "sg:postcode":"19971",
    "sg:province":"DE",
    "sg:tags":[
        "shop"
    ],
    "wof:name":"Imagination",
    "wof:placetype":"venue"
},
  "geometry": {"coordinates":[-75.07649600000001,38.716409],"type":"Point"}
}