{
  "type": "Feature",
  "properties": {
    "addr:full":"2215 Little Ln Wilmington DE 19810",
    "addr:housenumber":"2215",
    "addr:postcode":"19810",
    "addr:street":"Little Ln",
    "iso:country":"US",
    "sg:address":"2215 Little Ln",
    "sg:city":"Wilmington",
    "sg:classifiers":[
        {
            "category":"Professional",
            "subcategory":"Computer Services",
            "type":"Services"
        }
    ],
    "sg:phone":"+1 302 529 1516",
    "sg:postcode":"19810",
    "sg:province":"DE",
    "sg:tags":[
        "programming"
    ],
    "wof:name":"Faux Real",
    "wof:placetype":"venue"
},
  "geometry": {"coordinates":[-75.488029,39.812576],"type":"Point"}
}