{
  "type": "Feature",
  "properties": {
    "iso:country":"US",
    "sg:address":"33 Keenwick Rd",
    "sg:city":"Selbyville",
    "sg:classifiers":[
        {
            "category":"Social Services",
            "type":"Services"
        }
    ],
    "sg:phone":"+1 302 436 5868",
    "sg:postcode":"19975",
    "sg:province":"DE",
    "wof:name":"Abr Counseling Associates",
    "wof:placetype":"venue"
},
  "geometry": {"coordinates":[-75.087115,38.463445],"type":"Point"}
}