{
  "type": "Feature",
  "properties": {
    "iso:country":"US",
    "sg:address":"8 Devries Cir",
    "sg:city":"Lewes",
    "sg:classifiers":[
        {
            "category":"Professional",
            "subcategory":"Art Services",
            "type":"Services"
        }
    ],
    "sg:phone":"+1 302 645 6786",
    "sg:postcode":"19958",
    "sg:province":"DE",
    "sg:tags":[
        "commercial",
        "design"
    ],
    "wof:name":"Publishing Arts",
    "wof:placetype":"venue"
},
  "geometry": {"coordinates":[-75.146079,38.767026],"type":"Point"}
}