{
  "type": "Feature",
  "properties": {
    "iso:country":"US",
    "sg:address":"1679 S Dupont Hwy",
    "sg:city":"Dover",
    "sg:classifiers":[
        {
            "category":"Real Estate",
            "subcategory":"Real Estate Agent",
            "type":"Services"
        }
    ],
    "sg:phone":"+1 302 674 3832",
    "sg:postcode":"19901",
    "sg:province":"DE",
    "sg:tags":[
        "agency"
    ],
    "wof:name":"Century 21",
    "wof:placetype":"venue"
},
  "geometry": {"coordinates":[-75.529579,39.129135],"type":"Point"}
}