{
  "type": "Feature",
  "properties": {
    "iso:country":"US",
    "sg:address":"735 S Market St",
    "sg:city":"Wilmington",
    "sg:classifiers":[
        {
            "category":"Building & Trades",
            "subcategory":"Plumbing",
            "type":"Services"
        }
    ],
    "sg:phone":"+1 302 655 5652",
    "sg:postcode":"19801",
    "sg:province":"DE",
    "sg:tags":[
        "conditioning",
        "air",
        "system",
        "contractor"
    ],
    "wof:name":"Maichle's Heating & Air Cond",
    "wof:placetype":"venue"
},
  "geometry": {"coordinates":[-75.556151,39.731749],"type":"Point"}
}