{
  "type": "Feature",
  "properties": {
    "iso:country":"US",
    "sg:address":"31 Harbor Dr",
    "sg:city":"Claymont",
    "sg:classifiers":[
        {
            "category":"Recreation",
            "type":"Entertainment"
        }
    ],
    "sg:phone":"+1 302 798 9100",
    "sg:postcode":"19703",
    "sg:province":"DE",
    "sg:tags":[
        "club",
        "membership"
    ],
    "wof:name":"Harbor House Swim Club",
    "wof:placetype":"venue"
},
  "geometry": {"coordinates":[-75.45978100000001,39.79536],"type":"Point"}
}