{
  "type": "Feature",
  "properties": {
    "iso:country":"US",
    "sg:address":"4105 N Dupont Hwy",
    "sg:city":"Dover",
    "sg:classifiers":[
        {
            "category":"Restaurant",
            "type":"Food & Drink"
        }
    ],
    "sg:phone":"+1 302 736 3041",
    "sg:postcode":"19901",
    "sg:province":"DE",
    "sg:tags":[
        "out"
    ],
    "wof:name":"Glasgow Deli",
    "wof:placetype":"venue"
},
  "geometry": {"coordinates":[-75.566014,39.20753],"type":"Point"}
}