{
  "type": "Feature",
  "properties": {
    "iso:country":"US",
    "sg:address":"311 N Broad St",
    "sg:city":"Middletown",
    "sg:classifiers":[
        {
            "category":"Restaurant",
            "type":"Food & Drink"
        }
    ],
    "sg:menulink":"http://www.allmenus.com/de/middletown-odessa/105451-pats-family-restaurant/menu/",
    "sg:phone":"+1 302 378 4500",
    "sg:postcode":"19709",
    "sg:province":"DE",
    "sg:tags":[
        "american",
        "italian"
    ],
    "wof:name":"Pat's Family Restaurant",
    "wof:placetype":"venue"
},
  "geometry": {"coordinates":[-75.717455,39.452153],"type":"Point"}
}