{
  "type": "Feature",
  "properties": {
    "iso:country":"US",
    "sg:address":"1328 Garfield Dr",
    "sg:city":"Dover",
    "sg:classifiers":[
        {
            "category":"Wholesale",
            "subcategory":"Non-durable Goods",
            "type":"Manufacturing & Wholesale Goods"
        }
    ],
    "sg:phone":"+1 302 674 3705",
    "sg:postcode":"19901",
    "sg:province":"DE",
    "sg:tags":[
        "calendar"
    ],
    "wof:name":"Promotional Advertising Prods",
    "wof:placetype":"venue"
},
  "geometry": {"coordinates":[-75.514084,39.175502],"type":"Point"}
}