{
  "type": "Feature",
  "properties": {
    "iso:country":"US",
    "sg:address":"10 Country Ln",
    "sg:city":"Newark",
    "sg:classifiers":[
        {
            "category":"Professional",
            "subcategory":"Engineering",
            "type":"Services"
        }
    ],
    "sg:phone":"+1 302 455 0411",
    "sg:postcode":"19702",
    "sg:province":"DE",
    "wof:name":"Engineering Technologies",
    "wof:placetype":"venue"
},
  "geometry": {"coordinates":[-75.684883,39.640662],"type":"Point"}
}