{
  "type": "Feature",
  "properties": {
    "iso:country":"US",
    "sg:address":"4260 Mill Creek Rd",
    "sg:city":"Hockessin",
    "sg:classifiers":[
        {
            "category":"Professional",
            "subcategory":"Accounting & Tax Preparation",
            "type":"Services"
        }
    ],
    "sg:phone":"+1 302 235 1700",
    "sg:postcode":"19707",
    "sg:province":"DE",
    "sg:tags":[
        "public",
        "accountants-certified"
    ],
    "wof:name":"Lathrop, Judy K Cpa Pa",
    "wof:placetype":"venue"
},
  "geometry": {"coordinates":[-75.697407,39.780891],"type":"Point"}
}