{
  "type": "Feature",
  "properties": {
    "iso:country":"US",
    "sg:address":"2201 N Harrison St",
    "sg:city":"Wilmington",
    "sg:classifiers":[
        {
            "category":"Arena",
            "subcategory":"Sports Club",
            "type":"Entertainment"
        }
    ],
    "sg:phone":"+1 302 594 8108",
    "sg:postcode":"19802",
    "sg:province":"DE",
    "wof:name":"Mid Atlantic Rugby Football Un",
    "wof:placetype":"venue"
},
  "geometry": {"coordinates":[-75.544781,39.760191],"type":"Point"}
}