{
  "type": "Feature",
  "properties": {
    "iso:country":"US",
    "sg:address":"3301 Lancaster Pike",
    "sg:city":"Wilmington",
    "sg:classifiers":[
        {
            "category":"Restaurant",
            "type":"Food & Drink"
        }
    ],
    "sg:phone":"+1 302 652 4411",
    "sg:postcode":"19805",
    "sg:province":"DE",
    "wof:name":"Deerhead Hot Dogs",
    "wof:placetype":"venue"
},
  "geometry": {"coordinates":[-75.591043,39.753354],"type":"Point"}
}