{
  "type": "Feature",
  "properties": {
    "iso:country":"US",
    "sg:address":"15387 Pepperbox Rd",
    "sg:city":"Delmar",
    "sg:classifiers":[
        {
            "category":"Manufacturing",
            "subcategory":"Metals",
            "type":"Manufacturing & Wholesale Goods"
        }
    ],
    "sg:phone":"+1 302 875 1323",
    "sg:postcode":"19940",
    "sg:province":"DE",
    "sg:tags":[
        "installs",
        "fabricates",
        "balcony",
        "handrail"
    ],
    "wof:name":"Coastal Fabricating Inc",
    "wof:placetype":"venue"
},
  "geometry": {"coordinates":[-75.47933,38.483241],"type":"Point"}
}