{
  "type": "Feature",
  "properties": {
    "addr:full":"25 Port Royal Rd Ocean View DE 19970",
    "addr:housenumber":"25",
    "addr:postcode":"19970",
    "addr:street":"Port Royal Rd",
    "iso:country":"US",
    "sg:address":"25 Port Royal Rd",
    "sg:city":"Ocean View",
    "sg:classifiers":[
        {
            "category":"Travel",
            "subcategory":"Travel Agent",
            "type":"Entertainment"
        }
    ],
    "sg:phone":"+1 302 537 8320",
    "sg:postcode":"19970",
    "sg:province":"DE",
    "sg:tags":[
        "agency",
        "bureau"
    ],
    "wof:name":"Debra Christ",
    "wof:placetype":"venue"
},
  "geometry": {"coordinates":[-75.096768,38.546599],"type":"Point"}
}