{
  "type": "Feature",
  "properties": {
    "iso:country":"US",
    "sg:address":"409 Tatum Ave",
    "sg:city":"Wilmington",
    "sg:classifiers":[
        {
            "category":"Professional",
            "type":"Services"
        }
    ],
    "sg:phone":"+1 302 654 5680",
    "sg:postcode":"19805",
    "sg:province":"DE",
    "wof:name":"Jaclyn Milburn",
    "wof:placetype":"venue"
},
  "geometry": {"coordinates":[-75.59259400000001,39.745969],"type":"Point"}
}