{
  "type": "Feature",
  "properties": {
    "iso:country":"US",
    "sg:address":"3 Winston Ave",
    "sg:city":"Wilmington",
    "sg:classifiers":[
        {
            "category":"Restaurant",
            "type":"Food & Drink"
        }
    ],
    "sg:phone":"+1 302 652 9961",
    "sg:postcode":"19804",
    "sg:province":"DE",
    "sg:tags":[
        "eating"
    ],
    "wof:name":"Park Restaurant",
    "wof:placetype":"venue"
},
  "geometry": {"coordinates":[-75.588807,39.728787],"type":"Point"}
}