{
  "type": "Feature",
  "properties": {
    "iso:country":"US",
    "sg:address":"1812 Marsh Rd",
    "sg:city":"Wilmington",
    "sg:classifiers":[
        {
            "category":"Restaurant",
            "type":"Food & Drink"
        },
        {
            "category":"Food & Beverages",
            "subcategory":"Bakery",
            "type":"Retail Goods"
        }
    ],
    "sg:phone":"+1 302 529 7400",
    "sg:postcode":"19810",
    "sg:province":"DE",
    "sg:tags":[
        "sandwich",
        "pizza"
    ],
    "wof:name":"Romeo's Pizza & Restaurant",
    "wof:placetype":"venue"
},
  "geometry": {"coordinates":[-75.503899,39.803501],"type":"Point"}
}