{
  "type": "Feature",
  "properties": {
    "addr:full":"201 N Walnut St Wilmington DE 19801",
    "addr:housenumber":"201",
    "addr:postcode":"19801",
    "addr:street":"N Walnut St",
    "iso:country":"US",
    "sg:address":"201 N Walnut St",
    "sg:city":"Wilmington",
    "sg:classifiers":[
        {
            "category":"Banks & Credit Unions",
            "subcategory":"Investment Brokerage",
            "type":"Services"
        }
    ],
    "sg:phone":"+1 302 654 6162",
    "sg:postcode":"19801",
    "sg:province":"DE",
    "sg:tags":[
        "firm",
        "advisory",
        "management",
        "financial"
    ],
    "sg:website":"www.brandywineassetmgmtinc.com",
    "wof:name":"Brandywine Asset Management",
    "wof:placetype":"venue"
},
  "geometry": {"coordinates":[-75.549397,39.738157],"type":"Point"}
}