{
  "type": "Feature",
  "properties": {
    "addr:full":"4 Mill Park Ct Newark DE 19713",
    "addr:housenumber":"4",
    "addr:postcode":"19713",
    "addr:street":"Mill Park Ct",
    "iso:country":"US",
    "sg:address":"4 Mill Park Ct",
    "sg:city":"Newark",
    "sg:classifiers":[
        {
            "category":"Professional",
            "subcategory":"Business Services",
            "type":"Services"
        }
    ],
    "sg:phone":"+1 302 366 8992",
    "sg:postcode":"19713",
    "sg:province":"DE",
    "sg:tags":[
        "fund",
        "raising",
        "organization"
    ],
    "wof:name":"Ipi",
    "wof:placetype":"venue"
},
  "geometry": {"coordinates":[-75.698973,39.685589],"type":"Point"}
}