{
  "type": "Feature",
  "properties": {
    "iso:country":"US",
    "sg:address":"203 Atlantic Ave Ste 1",
    "sg:city":"Millville",
    "sg:classifiers":[
        {
            "category":"Health Services",
            "subcategory":"Doctor",
            "type":"Services"
        }
    ],
    "sg:phone":"+1 302 537 0793",
    "sg:postcode":"19967",
    "sg:province":"DE",
    "sg:tags":[
        "physician",
        "pediatrics-emergency",
        "pediatrics",
        "surgeons",
        "internal",
        "medicine",
        "surgeon"
    ],
    "wof:name":"Coastal Kid Watch",
    "wof:placetype":"venue"
},
  "geometry": {"coordinates":[-75.099846,38.545594],"type":"Point"}
}