{
  "type": "Feature",
  "properties": {
    "addr:full":"301 E Stein Hwy Seaford DE 19973",
    "addr:housenumber":"301",
    "addr:postcode":"19973",
    "addr:street":"E Stein Hwy",
    "iso:country":"US",
    "sg:address":"301 E Stein Hwy",
    "sg:city":"Seaford",
    "sg:phone":"+1 302 628 1400",
    "sg:postcode":"19973",
    "sg:province":"DE",
    "wof:name":"Subway",
    "wof:placetype":"venue"
},
  "geometry": {"coordinates":[-75.616951,38.646523],"type":"Point"}
}