{
  "type": "Feature",
  "properties": {
    "iso:country":"US",
    "sg:address":"76 Smyrna Ave",
    "sg:city":"Smyrna",
    "sg:classifiers":[
        {
            "category":"Personal",
            "subcategory":"Tanning Parlor",
            "type":"Services"
        }
    ],
    "sg:phone":"+1 302 653 6638",
    "sg:postcode":"19977",
    "sg:province":"DE",
    "sg:tags":[
        "salon"
    ],
    "wof:name":"Hot Locks Hair & Tanning",
    "wof:placetype":"venue"
},
  "geometry": {"coordinates":[-75.474109,39.332692],"type":"Point"}
}