{
  "type": "Feature",
  "properties": {
    "addr:full":"8 N Main St Magnolia DE 19938",
    "addr:housenumber":"8",
    "addr:postcode":"19938",
    "addr:street":"N Main St",
    "iso:country":"US",
    "sg:address":"8 N Main St",
    "sg:city":"Magnolia",
    "sg:classifiers":[
        {
            "category":"Government",
            "subcategory":"Post Office",
            "type":"Public Place"
        }
    ],
    "sg:phone":"+1 302 335 3609",
    "sg:postcode":"19938",
    "sg:province":"DE",
    "sg:tags":[
        "postal",
        "us"
    ],
    "wof:name":"US Post Office",
    "wof:placetype":"venue"
},
  "geometry": {"coordinates":[-75.66127400000001,39.228537],"type":"Point"}
}