{
  "type": "Feature",
  "properties": {
    "addr:full":"311 US Hwy 113 Millsboro DE 19966",
    "addr:housenumber":"311",
    "addr:postcode":"19966",
    "addr:street":"Us Hwy 113",
    "iso:country":"US",
    "sg:address":"311 US Hwy 113",
    "sg:city":"Millsboro",
    "sg:classifiers":[
        {
            "category":"Retail",
            "subcategory":"Auto Rental",
            "type":"Services"
        }
    ],
    "sg:phone":"+1 302 934 6600",
    "sg:postcode":"19966",
    "sg:province":"DE",
    "sg:tags":[
        "passenger",
        "car"
    ],
    "wof:name":"Rent Equip",
    "wof:placetype":"venue"
},
  "geometry": {"coordinates":[-75.302267,38.589894],"type":"Point"}
}