{
  "type": "Feature",
  "properties": {
    "iso:country":"US",
    "sg:address":"7 Rehoboth Beach Gardens",
    "sg:city":"Rehoboth Beach",
    "sg:classifiers":[
        {
            "category":"Real Estate",
            "subcategory":"Surveying",
            "type":"Services"
        }
    ],
    "sg:phone":"+1 302 227 7808",
    "sg:postcode":"19971",
    "sg:province":"DE",
    "sg:tags":[
        "surveyor"
    ],
    "wof:name":"Wingate & Eschenbach LLC",
    "wof:placetype":"venue"
},
  "geometry": {"coordinates":[-75.10137400000001,38.710691],"type":"Point"}
}