{
  "type": "Feature",
  "properties": {
    "iso:country":"US",
    "sg:address":"10 Lebanon Rd",
    "sg:city":"Dover",
    "sg:classifiers":[
        {
            "category":"Food & Beverages",
            "subcategory":"Groceries & Convenience Stores",
            "type":"Retail Goods"
        }
    ],
    "sg:phone":"+1 302 697 2587",
    "sg:postcode":"19901",
    "sg:province":"DE",
    "wof:name":"Shore Stop",
    "wof:placetype":"venue"
},
  "geometry": {"coordinates":[-75.516706,39.117653],"type":"Point"}
}