{
  "type": "Feature",
  "properties": {
    "iso:country":"US",
    "sg:address":"5209 W Woodmill Dr",
    "sg:city":"Wilmington",
    "sg:classifiers":[
        {
            "category":"Professional",
            "subcategory":"Research",
            "type":"Services"
        }
    ],
    "sg:phone":"+1 302 633 3300",
    "sg:postcode":"19808",
    "sg:province":"DE",
    "sg:tags":[
        "market",
        "analysis"
    ],
    "wof:name":"K C Assoc",
    "wof:placetype":"venue"
},
  "geometry": {"coordinates":[-75.672134,39.718086],"type":"Point"}
}