{
  "type": "Feature",
  "properties": {
    "iso:country":"US",
    "sg:address":"3316 Kirkwood Hwy",
    "sg:city":"Wilmington",
    "sg:classifiers":[
        {
            "category":"Manufacturing",
            "subcategory":"Furniture",
            "type":"Manufacturing & Wholesale Goods"
        },
        {
            "category":"Home & Garden",
            "subcategory":"Home Furnishings",
            "type":"Retail Goods"
        }
    ],
    "sg:phone":"+1 302 999 8800",
    "sg:postcode":"19808",
    "sg:province":"DE",
    "sg:tags":[
        "venetian",
        "blind",
        "drapery",
        "mfg"
    ],
    "wof:name":"Blind Factory Inc",
    "wof:placetype":"venue"
},
  "geometry": {"coordinates":[-75.63009700000001,39.736087],"type":"Point"}
}