{
  "type": "Feature",
  "properties": {
    "iso:country":"US",
    "sg:address":"161 Beechwood Ave",
    "sg:city":"Dover",
    "sg:classifiers":[
        {
            "category":"Professional",
            "type":"Services"
        }
    ],
    "sg:phone":"+1 302 736 9929",
    "sg:postcode":"19901",
    "sg:province":"DE",
    "wof:name":"Barrys Electronic Services",
    "wof:placetype":"venue"
},
  "geometry": {"coordinates":[-75.513553,39.131913],"type":"Point"}
}