{
  "type": "Feature",
  "properties": {
    "iso:country":"US",
    "sg:address":"2103 Capitol Trl",
    "sg:city":"Newark",
    "sg:classifiers":[
        {
            "category":"Building & Trades",
            "subcategory":"Construction",
            "type":"Services"
        }
    ],
    "sg:phone":"+1 302 737 4844",
    "sg:postcode":"19711",
    "sg:province":"DE",
    "sg:tags":[
        "house",
        "general",
        "contractor"
    ],
    "wof:name":"Grant Construction",
    "wof:placetype":"venue"
},
  "geometry": {"coordinates":[-75.686358,39.705871],"type":"Point"}
}