{
  "type": "Feature",
  "properties": {
    "iso:country":"US",
    "sg:address":"12774 Shawnee Rd",
    "sg:city":"Greenwood",
    "sg:classifiers":[
        {
            "category":"Mining & Drilling",
            "type":"Manufacturing & Wholesale Goods"
        }
    ],
    "sg:phone":"+1 302 349 5849",
    "sg:postcode":"19950",
    "sg:province":"DE",
    "sg:tags":[
        "construction"
    ],
    "wof:name":"Synergy Corporation",
    "wof:placetype":"venue"
},
  "geometry": {"coordinates":[-75.572529,38.808911],"type":"Point"}
}