{
  "type": "Feature",
  "properties": {
    "addr:full":"11 Black Walnut Ct Rehoboth Beach DE 19971",
    "addr:housenumber":"11",
    "addr:postcode":"19971",
    "addr:street":"Black Walnut Ct",
    "iso:country":"US",
    "sg:address":"11 Black Walnut Ct",
    "sg:city":"Rehoboth Beach",
    "sg:classifiers":[
        {
            "category":"Travel",
            "subcategory":"Travel Agent",
            "type":"Entertainment"
        }
    ],
    "sg:phone":"+1 302 227 9211",
    "sg:postcode":"19971",
    "sg:province":"DE",
    "sg:tags":[
        "agency"
    ],
    "wof:name":"Caribbean Cruise Lines",
    "wof:placetype":"venue"
},
  "geometry": {"coordinates":[-75.12268400000001,38.714465],"type":"Point"}
}