{
  "type": "Feature",
  "properties": {
    "addr:full":"913 Wilson Rd Wilmington DE 19803",
    "addr:housenumber":"913",
    "addr:postcode":"19803",
    "addr:street":"Wilson Rd",
    "iso:country":"US",
    "sg:address":"913 Wilson Rd",
    "sg:city":"Wilmington",
    "sg:classifiers":[
        {
            "category":"Organizations",
            "subcategory":"Religious Organization",
            "type":"Services"
        }
    ],
    "sg:phone":"+1 302 478 7574",
    "sg:postcode":"19803",
    "sg:province":"DE",
    "sg:tags":[
        "church"
    ],
    "sg:website":"www.stalbansde.org",
    "wof:name":"Saint Albans Episcopal Church",
    "wof:placetype":"venue"
},
  "geometry": {"coordinates":[-75.51413599999999,39.793783],"type":"Point"}
}