{
  "type": "Feature",
  "properties": {
    "addr:full":"44 Apple Run Magnolia DE 19962",
    "addr:housenumber":"44",
    "addr:postcode":"19962",
    "addr:street":"Apple Run",
    "iso:country":"US",
    "sg:address":"44 Apple Run",
    "sg:city":"Magnolia",
    "sg:classifiers":[
        {
            "category":"Bus Charters",
            "type":"Transportation"
        }
    ],
    "sg:phone":"+1 302 697 8681",
    "sg:postcode":"19962",
    "sg:province":"DE",
    "sg:tags":[
        "rental"
    ],
    "wof:name":"Robbins Bus Svc",
    "wof:placetype":"venue"
},
  "geometry": {"coordinates":[-75.530652,39.066148],"type":"Point"}
}