{
  "type": "Feature",
  "properties": {
    "iso:country":"US",
    "sg:address":"2032 New Castle Ave",
    "sg:city":"New Castle",
    "sg:classifiers":[
        {
            "category":"Health Services",
            "subcategory":"Health Practitioner",
            "type":"Services"
        }
    ],
    "sg:phone":"+1 302 654 1700",
    "sg:postcode":"19720",
    "sg:province":"DE",
    "sg:website":"www.prophysicaltherapy.com",
    "wof:name":"Pro Physical Therapy",
    "wof:placetype":"venue"
},
  "geometry": {"coordinates":[-75.556359,39.687892],"type":"Point"}
}