{
  "type": "Feature",
  "properties": {
    "iso:country":"US",
    "sg:address":"15 E Glenwood Ave",
    "sg:city":"Smyrna",
    "sg:classifiers":[
        {
            "category":"Restaurant",
            "type":"Food & Drink"
        }
    ],
    "sg:phone":"+1 302 653 3466",
    "sg:postcode":"19977",
    "sg:province":"DE",
    "wof:name":"Bridge Way Family Restaurant",
    "wof:placetype":"venue"
},
  "geometry": {"coordinates":[-75.610179,39.303605],"type":"Point"}
}