{
  "type": "Feature",
  "properties": {
    "iso:country":"US",
    "sg:address":"101 New Rd",
    "sg:city":"Wilmington",
    "sg:classifiers":[
        {
            "category":"Restaurant",
            "type":"Food & Drink"
        }
    ],
    "sg:phone":"+1 302 656 2010",
    "sg:postcode":"19805",
    "sg:province":"DE",
    "wof:name":"Mc Donald's",
    "wof:placetype":"venue"
},
  "geometry": {"coordinates":[-75.582916,39.741294],"type":"Point"}
}