{
  "type": "Feature",
  "properties": {
    "iso:country":"US",
    "sg:address":"461 Wyoming Rd",
    "sg:city":"Newark",
    "sg:classifiers":[
        {
            "category":"Wholesale",
            "subcategory":"Hardware",
            "type":"Manufacturing & Wholesale Goods"
        }
    ],
    "sg:phone":"+1 302 366 0400",
    "sg:postcode":"19711",
    "sg:province":"DE",
    "sg:tags":[
        "equipment",
        "energy",
        "solar"
    ],
    "wof:name":"Astropower Inc",
    "wof:placetype":"venue"
},
  "geometry": {"coordinates":[-75.73593200000001,39.678474],"type":"Point"}
}