{
  "type": "Feature",
  "properties": {
    "iso:country":"US",
    "sg:address":"1151 E Lebanon Rd Ste B",
    "sg:city":"Dover",
    "sg:classifiers":[
        {
            "category":"Food & Beverages",
            "subcategory":"Meat & Fish",
            "type":"Retail Goods"
        }
    ],
    "sg:phone":"+1 302 698 1015",
    "sg:postcode":"19901",
    "sg:province":"DE",
    "sg:tags":[
        "seafood",
        "market"
    ],
    "wof:name":"Reel Fresh Seafood Market & Grill",
    "wof:placetype":"venue"
},
  "geometry": {"coordinates":[-75.51222300000001,39.118458],"type":"Point"}
}