{
  "type": "Feature",
  "properties": {
    "addr:full":"282 N Bay Dr Dover DE 19901",
    "addr:housenumber":"282",
    "addr:postcode":"19901",
    "addr:street":"N Bay Dr",
    "iso:country":"US",
    "sg:address":"282 N Bay Dr",
    "sg:city":"Dover",
    "sg:classifiers":[
        {
            "category":"Building & Trades",
            "subcategory":"Construction",
            "type":"Services"
        }
    ],
    "sg:phone":"+1 302 735 1543",
    "sg:postcode":"19901",
    "sg:province":"DE",
    "sg:tags":[
        "roofing",
        "contractor"
    ],
    "wof:name":"Neverleak Roofing & Siding",
    "wof:placetype":"venue"
},
  "geometry": {"coordinates":[-75.402996,39.106794],"type":"Point"}
}