{
  "type": "Feature",
  "properties": {
    "iso:country":"US",
    "sg:address":"431 Savannah Rd",
    "sg:city":"Lewes",
    "sg:classifiers":[
        {
            "category":"Health Services",
            "subcategory":"Health Practitioner",
            "type":"Services"
        }
    ],
    "sg:phone":"+1 302 644 2773",
    "sg:postcode":"19958",
    "sg:province":"DE",
    "sg:tags":[
        "psychologist"
    ],
    "wof:name":"Elena Pardell PHD",
    "wof:placetype":"venue"
},
  "geometry": {"coordinates":[-75.142492,38.77107],"type":"Point"}
}