{
  "type": "Feature",
  "properties": {
    "iso:country":"US",
    "sg:address":"125 Causey Ave",
    "sg:city":"Milford",
    "sg:classifiers":[
        {
            "category":"Building & Trades",
            "subcategory":"Construction",
            "type":"Services"
        }
    ],
    "sg:phone":"+1 302 424 6744",
    "sg:postcode":"19963",
    "sg:province":"DE",
    "sg:tags":[
        "home",
        "improvement"
    ],
    "wof:name":"R C & D Emergency Home Repair",
    "wof:placetype":"venue"
},
  "geometry": {"coordinates":[-75.431391,38.911404],"type":"Point"}
}