{
  "type": "Feature",
  "properties": {
    "iso:country":"US",
    "sg:address":"211 Stone Crop Rd",
    "sg:city":"Wilmington",
    "sg:classifiers":[
        {
            "category":"Shopping",
            "subcategory":"Used Merchandise",
            "type":"Retail Goods"
        }
    ],
    "sg:phone":"+1 302 529 1178",
    "sg:postcode":"19810",
    "sg:province":"DE",
    "wof:name":"Harbar Antiques",
    "wof:placetype":"venue"
},
  "geometry": {"coordinates":[-75.501017,39.833349],"type":"Point"}
}