{
  "type": "Feature",
  "properties": {
    "addr:full":"104 West St Laurel DE 19956",
    "addr:housenumber":"104",
    "addr:postcode":"19956",
    "addr:street":"West St",
    "iso:country":"US",
    "sg:address":"104 West St",
    "sg:city":"Laurel",
    "sg:classifiers":[
        {
            "category":"Food & Beverages",
            "subcategory":"Groceries & Convenience Stores",
            "type":"Retail Goods"
        }
    ],
    "sg:phone":"+1 302 875 4446",
    "sg:postcode":"19956",
    "sg:province":"DE",
    "wof:name":"First Stop Inc",
    "wof:placetype":"venue"
},
  "geometry": {"coordinates":[-75.575335,38.555931],"type":"Point"}
}