{
  "type": "Feature",
  "properties": {
    "iso:country":"US",
    "sg:address":"423 Park Ave",
    "sg:city":"New Castle",
    "sg:classifiers":[
        {
            "category":"Building & Trades",
            "subcategory":"Cleaning & Sanitation",
            "type":"Services"
        }
    ],
    "sg:phone":"+1 302 322 8356",
    "sg:postcode":"19720",
    "sg:province":"DE",
    "sg:tags":[
        "janitor"
    ],
    "wof:name":"Ameri Clean Systems",
    "wof:placetype":"venue"
},
  "geometry": {"coordinates":[-75.605368,39.644338],"type":"Point"}
}