{
  "type": "Feature",
  "properties": {
    "addr:full":"5270 Baker Rd Bridgeville DE 19933",
    "addr:housenumber":"5270",
    "addr:postcode":"19933",
    "addr:street":"Baker Rd",
    "iso:country":"US",
    "sg:address":"5270 Baker Rd",
    "sg:city":"Bridgeville",
    "sg:classifiers":[
        {
            "category":"Professional",
            "type":"Services"
        }
    ],
    "sg:phone":"+1 302 628 8042",
    "sg:postcode":"19933",
    "sg:province":"DE",
    "wof:name":"Aire-Master of America",
    "wof:placetype":"venue"
},
  "geometry": {"coordinates":[-75.64693800000001,38.702064],"type":"Point"}
}