{
  "type": "Feature",
  "properties": {
    "iso:country":"US",
    "sg:address":"84 E Glenwood Ave",
    "sg:city":"Smyrna",
    "sg:classifiers":[
        {
            "category":"Shopping",
            "subcategory":"Department Store",
            "type":"Retail Goods"
        },
        {
            "category":"Shopping",
            "subcategory":"Discount & Variety Stores",
            "type":"Retail Goods"
        }
    ],
    "sg:phone":"+1 302 653 0834",
    "sg:postcode":"19977",
    "sg:province":"DE",
    "wof:name":"Roses Stores",
    "wof:placetype":"venue"
},
  "geometry": {"coordinates":[-75.60841000000001,39.305064],"type":"Point"}
}