{
  "type": "Feature",
  "properties": {
    "addr:full":"219 Old North Rd Camden DE 19934",
    "addr:housenumber":"219",
    "addr:postcode":"19934",
    "addr:street":"Old North Rd",
    "iso:country":"US",
    "sg:address":"219 Old North Rd",
    "sg:city":"Camden",
    "sg:classifiers":[
        {
            "category":"Education",
            "subcategory":"School",
            "type":"Public Place"
        }
    ],
    "sg:phone":"+1 302 697 2173",
    "sg:postcode":"19934",
    "sg:province":"DE",
    "wof:name":"Caesar Rodney School District Caesar Rodney District Office",
    "wof:placetype":"venue"
},
  "geometry": {"coordinates":[-75.54356300000001,39.118533],"type":"Point"}
}