{
  "type": "Feature",
  "properties": {
    "iso:country":"US",
    "sg:address":"500 S Dual Hwy",
    "sg:city":"Seaford",
    "sg:classifiers":[
        {
            "category":"Professional",
            "subcategory":"Advertising",
            "type":"Services"
        }
    ],
    "sg:phone":"+1 302 628 9334",
    "sg:postcode":"19973",
    "sg:province":"DE",
    "sg:tags":[
        "mailing",
        "shipping"
    ],
    "wof:name":"Mail Rooms",
    "wof:placetype":"venue"
},
  "geometry": {"coordinates":[-75.592884,38.636104],"type":"Point"}
}