{
  "type": "Feature",
  "properties": {
    "iso:country":"US",
    "sg:address":"201 S Maryland Ave",
    "sg:city":"Wilmington",
    "sg:classifiers":[
        {
            "category":"Professional",
            "subcategory":"Art Services",
            "type":"Services"
        }
    ],
    "sg:phone":"+1 302 994 7782",
    "sg:postcode":"19804",
    "sg:province":"DE",
    "sg:tags":[
        "communications",
        "graphic",
        "publishing",
        "desktop",
        "center"
    ],
    "sg:website":"www.technigraphicscorp.com",
    "wof:name":"Technigraphics Inc",
    "wof:placetype":"venue"
},
  "geometry": {"coordinates":[-75.58760599999999,39.727217],"type":"Point"}
}