{
  "type": "Feature",
  "properties": {
    "iso:country":"US",
    "sg:address":"2022 Harwyn Rd",
    "sg:city":"Wilmington",
    "sg:classifiers":[
        {
            "category":"Professional",
            "subcategory":"Employment Agencies",
            "type":"Services"
        }
    ],
    "sg:phone":"+1 302 529 1838",
    "sg:postcode":"19810",
    "sg:province":"DE",
    "sg:tags":[
        "nursing",
        "staffing"
    ],
    "wof:name":"Tedron Inc",
    "wof:placetype":"venue"
},
  "geometry": {"coordinates":[-75.50497,39.811949],"type":"Point"}
}