{
  "type": "Feature",
  "properties": {
    "iso:country":"US",
    "sg:address":"1217 Old Cooches Bridge Rd",
    "sg:city":"Newark",
    "sg:classifiers":[
        {
            "category":"Retail",
            "subcategory":"Car Wash",
            "type":"Services"
        }
    ],
    "sg:phone":"+1 302 456 3700",
    "sg:postcode":"19713",
    "sg:province":"DE",
    "sg:tags":[
        "polishing",
        "carwash",
        "washing"
    ],
    "wof:name":"Hitech Auto Detailing",
    "wof:placetype":"venue"
},
  "geometry": {"coordinates":[-75.74731,39.651716],"type":"Point"}
}