{
  "type": "Feature",
  "properties": {
    "iso:country":"US",
    "sg:address":"238 Tamarack Ave",
    "sg:city":"Wilmington",
    "sg:classifiers":[
        {
            "category":"Building & Trades",
            "subcategory":"Electrical",
            "type":"Services"
        }
    ],
    "sg:phone":"+1 302 994 9396",
    "sg:postcode":"19805",
    "sg:province":"DE",
    "sg:tags":[
        "electrical",
        "contractor"
    ],
    "wof:name":"Adamson Electric",
    "wof:placetype":"venue"
},
  "geometry": {"coordinates":[-75.599755,39.734377],"type":"Point"}
}