{
  "type": "Feature",
  "properties": {
    "addr:full":"2204 S Dupont Hwy Dover DE 19901",
    "addr:housenumber":"2204",
    "addr:postcode":"19901",
    "addr:street":"S Dupont Hwy",
    "iso:country":"US",
    "sg:address":"2204 S Dupont Hwy",
    "sg:city":"Dover",
    "sg:classifiers":[
        {
            "category":"Home & Garden",
            "subcategory":"Furniture",
            "type":"Retail Goods"
        },
        {
            "category":"Wholesale",
            "subcategory":"Furniture",
            "type":"Manufacturing & Wholesale Goods"
        }
    ],
    "sg:phone":"+1 302 697 1300",
    "sg:postcode":"19901",
    "sg:province":"DE",
    "sg:tags":[
        "sell"
    ],
    "wof:name":"Furniture & More Inc",
    "wof:placetype":"venue"
},
  "geometry": {"coordinates":[-75.53518099999999,39.118338],"type":"Point"}
}