{
  "type": "Feature",
  "properties": {
    "addr:full":"113 E Liberty St Harrington DE 19952",
    "addr:housenumber":"113",
    "addr:postcode":"19952",
    "addr:street":"E Liberty St",
    "iso:country":"US",
    "sg:address":"113 E Liberty St",
    "sg:city":"Harrington",
    "sg:classifiers":[
        {
            "category":"Personal",
            "subcategory":"Beauty Salon",
            "type":"Services"
        }
    ],
    "sg:phone":"+1 302 398 8018",
    "sg:postcode":"19952",
    "sg:province":"DE",
    "wof:name":"Plain Or Fancy Beauty Salon",
    "wof:placetype":"venue"
},
  "geometry": {"coordinates":[-75.57538099999999,38.925532],"type":"Point"}
}