{
  "type": "Feature",
  "properties": {
    "iso:country":"US",
    "sg:address":"78 E Glenwood Ave",
    "sg:city":"Smyrna",
    "sg:classifiers":[
        {
            "category":"Personal",
            "subcategory":"Beauty Salon",
            "type":"Services"
        }
    ],
    "sg:phone":"+1 302 653 1378",
    "sg:postcode":"19977",
    "sg:province":"DE",
    "sg:tags":[
        "manicure",
        "pedicure"
    ],
    "wof:name":"Center Nails",
    "wof:placetype":"venue"
},
  "geometry": {"coordinates":[-75.610022,39.303718],"type":"Point"}
}