{
  "type": "Feature",
  "properties": {
    "addr:full":"12 Salem Village Sq Newark DE 19713",
    "addr:housenumber":"12",
    "addr:postcode":"19713",
    "addr:street":"Salem Village Sq",
    "iso:country":"US",
    "sg:address":"12 Salem Village Sq",
    "sg:city":"Newark",
    "sg:classifiers":[
        {
            "category":"Education",
            "subcategory":"Dance Studio",
            "type":"Public Place"
        }
    ],
    "sg:phone":"+1 302 738 9292",
    "sg:postcode":"19713",
    "sg:province":"DE",
    "sg:tags":[
        "instruction",
        "dancing"
    ],
    "wof:name":"Jean Ferrill Dance Studio",
    "wof:placetype":"venue"
},
  "geometry": {"coordinates":[-75.69551800000001,39.667635],"type":"Point"}
}