{
  "type": "Feature",
  "properties": {
    "iso:country":"US",
    "sg:address":"900 N King St",
    "sg:city":"Wilmington",
    "sg:classifiers":[
        {
            "category":"Professional",
            "subcategory":"Employment Agencies",
            "type":"Services"
        }
    ],
    "sg:phone":"+1 302 472 0139",
    "sg:postcode":"19801",
    "sg:province":"DE",
    "sg:tags":[
        "consultant",
        "search",
        "executive"
    ],
    "wof:name":"De Army Natl Guard Recruiters",
    "wof:placetype":"venue"
},
  "geometry": {"coordinates":[-75.54695100000001,39.745205],"type":"Point"}
}