{
  "type": "Feature",
  "properties": {
    "addr:full":"42 New St Newark DE 19711",
    "addr:housenumber":"42",
    "addr:postcode":"19711",
    "addr:street":"New St",
    "iso:country":"US",
    "sg:address":"42 New St",
    "sg:city":"Newark",
    "sg:classifiers":[
        {
            "category":"Wholesale",
            "subcategory":"Electrical",
            "type":"Manufacturing & Wholesale Goods"
        }
    ],
    "sg:phone":"+1 302 737 1702",
    "sg:postcode":"19711",
    "sg:province":"DE",
    "sg:tags":[
        "electronic"
    ],
    "sg:website":"www.claycreekstudio.com",
    "wof:name":"Clay Creek Recording Studio",
    "wof:placetype":"venue"
},
  "geometry": {"coordinates":[-75.746342,39.685671],"type":"Point"}
}