{
  "type": "Feature",
  "properties": {
    "iso:country":"US",
    "sg:address":"2313 Concord Pike",
    "sg:city":"Wilmington",
    "sg:classifiers":[
        {
            "category":"Social Services",
            "subcategory":"Child Care",
            "type":"Services"
        },
        {
            "category":"Education",
            "subcategory":"Preschool",
            "type":"Public Place"
        },
        {
            "category":"Education",
            "subcategory":"School",
            "type":"Public Place"
        }
    ],
    "sg:phone":"+1 302 478 7114",
    "sg:postcode":"19803",
    "sg:province":"DE",
    "sg:tags":[
        "elementary",
        "day"
    ],
    "sg:website":"www.montessorilc.com",
    "wof:name":"Montessori Learning Centre",
    "wof:placetype":"venue"
},
  "geometry": {"coordinates":[-75.546997,39.793499],"type":"Point"}
}