{
  "type": "Feature",
  "properties": {
    "iso:country":"US",
    "sg:address":"1112 Dardel Dr",
    "sg:city":"Wilmington",
    "sg:classifiers":[
        {
            "category":"Professional",
            "subcategory":"Engineering",
            "type":"Services"
        }
    ],
    "sg:phone":"+1 302 478 7191",
    "sg:postcode":"19803",
    "sg:province":"DE",
    "wof:name":"Vance Professional Services",
    "wof:placetype":"venue"
},
  "geometry": {"coordinates":[-75.51664700000001,39.803795],"type":"Point"}
}