{
  "type": "Feature",
  "properties": {
    "addr:full":"102 Clayton St Dagsboro DE 19939",
    "addr:housenumber":"102",
    "addr:postcode":"19939",
    "addr:street":"Clayton St",
    "iso:country":"US",
    "sg:address":"102 Clayton St",
    "sg:city":"Dagsboro",
    "sg:classifiers":[
        {
            "category":"Government",
            "subcategory":"Post Office",
            "type":"Public Place"
        }
    ],
    "sg:phone":"+1 302 732 9404",
    "sg:postcode":"19939",
    "sg:province":"DE",
    "wof:name":"US Post Office",
    "wof:placetype":"venue"
},
  "geometry": {"coordinates":[-75.24559499999999,38.549198],"type":"Point"}
}