{
  "type": "Feature",
  "properties": {
    "iso:country":"US",
    "sg:address":"500 Delaware Ave Suite 1500",
    "sg:city":"Wilmington",
    "sg:classifiers":[
        {
            "category":"Professional",
            "subcategory":"Lawyer & Legal Services",
            "type":"Services"
        }
    ],
    "sg:phone":"+1 302 888 6870",
    "sg:postcode":"19801",
    "sg:province":"DE",
    "sg:tags":[
        "arbitration",
        "litigation",
        "attorney",
        "practice",
        "business",
        "mediation",
        "tort",
        "governmental",
        "plan",
        "law",
        "administrative",
        "insurance"
    ],
    "wof:name":"Semple, James W - Morris James Hitchens Williams",
    "wof:placetype":"venue"
},
  "geometry": {"coordinates":[-75.55135300000001,39.747799],"type":"Point"}
}