{
  "type": "Feature",
  "properties": {
    "addr:full":"304 N Union St Wilmington DE 19805",
    "addr:housenumber":"304",
    "addr:postcode":"19805",
    "addr:street":"N Union St",
    "iso:country":"US",
    "sg:address":"304 N Union St",
    "sg:city":"Wilmington",
    "sg:classifiers":[
        {
            "category":"Organizations",
            "subcategory":"Religious Organization",
            "type":"Services"
        }
    ],
    "sg:phone":"+1 302 656 5228",
    "sg:postcode":"19805",
    "sg:province":"DE",
    "wof:name":"Restoration Ministries",
    "wof:placetype":"venue"
},
  "geometry": {"coordinates":[-75.57295000000001,39.74921],"type":"Point"}
}