{
  "type": "Feature",
  "properties": {
    "iso:country":"US",
    "sg:address":"722 Philadelphia Pike",
    "sg:city":"Wilmington",
    "sg:classifiers":[
        {
            "category":"Professional",
            "type":"Services"
        }
    ],
    "sg:phone":"+1 302 765 2757",
    "sg:postcode":"19809",
    "sg:province":"DE",
    "wof:name":"Lucky Buddha",
    "wof:placetype":"venue"
},
  "geometry": {"coordinates":[-75.49902899999999,39.771247],"type":"Point"}
}