{
  "type": "Feature",
  "properties": {
    "iso:country":"US",
    "sg:address":"1511 N Dupont Hwy",
    "sg:city":"New Castle",
    "sg:classifiers":[
        {
            "category":"Restaurant",
            "type":"Food & Drink"
        }
    ],
    "sg:phone":"+1 302 322 1110",
    "sg:postcode":"19720",
    "sg:province":"DE",
    "sg:tags":[
        "eating"
    ],
    "wof:name":"La Chiquita Mexican Rest & Gr",
    "wof:placetype":"venue"
},
  "geometry": {"coordinates":[-75.581187,39.690877],"type":"Point"}
}