{
  "type": "Feature",
  "properties": {
    "iso:country":"US",
    "sg:address":"208 Lantana Dr",
    "sg:city":"Hockessin",
    "sg:classifiers":[
        {
            "category":"Shopping",
            "type":"Retail Goods"
        }
    ],
    "sg:phone":"+1 302 239 7460",
    "sg:postcode":"19707",
    "sg:province":"DE",
    "sg:tags":[
        "merchandise"
    ],
    "wof:name":"Big Picture Inc",
    "wof:placetype":"venue"
},
  "geometry": {"coordinates":[-75.71153,39.775192],"type":"Point"}
}