{
  "type": "Feature",
  "properties": {
    "iso:country":"US",
    "sg:address":"206 W 21st St",
    "sg:city":"Wilmington",
    "sg:classifiers":[
        {
            "category":"Professional",
            "subcategory":"Management & Consulting",
            "type":"Services"
        }
    ],
    "sg:phone":"+1 302 652 2235",
    "sg:postcode":"19802",
    "sg:province":"DE",
    "wof:name":"Edgar Consulting",
    "wof:placetype":"venue"
},
  "geometry": {"coordinates":[-75.542942,39.754984],"type":"Point"}
}