{
  "type": "Feature",
  "properties": {
    "iso:country":"US",
    "sg:address":"1504 Philadelphia Pike",
    "sg:city":"Wilmington",
    "sg:classifiers":[
        {
            "category":"Restaurant",
            "type":"Food & Drink"
        }
    ],
    "sg:phone":"+1 302 798 0559",
    "sg:postcode":"19809",
    "sg:province":"DE",
    "sg:website":"www.mammagiulia.com",
    "wof:name":"Mamma Giulia",
    "wof:placetype":"venue"
},
  "geometry": {"coordinates":[-75.479403,39.783852],"type":"Point"}
}