{
  "type": "Feature",
  "properties": {
    "iso:country":"US",
    "sg:address":"610 Thompson Station Rd",
    "sg:city":"Newark",
    "sg:classifiers":[
        {
            "category":"Professional",
            "subcategory":"Research",
            "type":"Services"
        }
    ],
    "sg:phone":"+1 302 454 8974",
    "sg:postcode":"19711",
    "sg:province":"DE",
    "sg:tags":[
        "environmental",
        "ecological"
    ],
    "wof:name":"Northeast Regional Probing Inc",
    "wof:placetype":"venue"
},
  "geometry": {"coordinates":[-75.754954,39.72841],"type":"Point"}
}