{
  "type": "Feature",
  "properties": {
    "addr:full":"248 S Dupont Hwy New Castle DE 19720",
    "addr:housenumber":"248",
    "addr:postcode":"19720",
    "addr:street":"S Dupont Hwy",
    "iso:country":"US",
    "sg:address":"248 S Dupont Hwy",
    "sg:city":"New Castle",
    "sg:classifiers":[
        {
            "category":"Home & Garden",
            "subcategory":"Building Materials",
            "type":"Retail Goods"
        }
    ],
    "sg:phone":"+1 302 322 3848",
    "sg:postcode":"19720",
    "sg:province":"DE",
    "sg:tags":[
        "lumber"
    ],
    "wof:name":"84 Lumber",
    "wof:placetype":"venue"
},
  "geometry": {"coordinates":[-75.61629499999999,39.65456],"type":"Point"}
}