{
  "type": "Feature",
  "properties": {
    "iso:country":"US",
    "sg:address":"20 W Loockerman St",
    "sg:city":"Dover",
    "sg:classifiers":[
        {
            "category":"Restaurant",
            "type":"Food & Drink"
        }
    ],
    "sg:phone":"+1 302 678 9650",
    "sg:postcode":"19904",
    "sg:province":"DE",
    "sg:tags":[
        "sandwich"
    ],
    "wof:name":"Angelo's Pizza Restaurant",
    "wof:placetype":"venue"
},
  "geometry": {"coordinates":[-75.52480300000001,39.1581],"type":"Point"}
}