{
  "type": "Feature",
  "properties": {
    "iso:country":"US",
    "sg:address":"1100 N King St",
    "sg:city":"Wilmington",
    "sg:classifiers":[
        {
            "category":"Utilities",
            "subcategory":"Telephone",
            "type":"Services"
        }
    ],
    "sg:phone":"+1 302 777 5046",
    "sg:postcode":"19801",
    "sg:province":"DE",
    "sg:tags":[
        "telecommunication"
    ],
    "wof:name":"Verizon Communications",
    "wof:placetype":"venue"
},
  "geometry": {"coordinates":[-75.545756,39.746966],"type":"Point"}
}