{
  "type": "Feature",
  "properties": {
    "addr:full":"98 Karlyn Dr New Castle DE 19720",
    "addr:housenumber":"98",
    "addr:postcode":"19720",
    "addr:street":"Karlyn Dr",
    "iso:country":"US",
    "sg:address":"98 Karlyn Dr",
    "sg:city":"New Castle",
    "sg:classifiers":[
        {
            "category":"Utilities",
            "subcategory":"Mobile Phone",
            "type":"Services"
        }
    ],
    "sg:phone":"+1 302 652 0616",
    "sg:postcode":"19720",
    "sg:province":"DE",
    "sg:tags":[
        "communication",
        "radiotelephone"
    ],
    "wof:name":"Twobright Wireless Inc",
    "wof:placetype":"venue"
},
  "geometry": {"coordinates":[-75.56251399999999,39.708411],"type":"Point"}
}