{
  "type": "Feature",
  "properties": {
    "iso:country":"US",
    "sg:address":"249 Old Churchmans Rd",
    "sg:city":"New Castle",
    "sg:classifiers":[
        {
            "category":"Manufacturing",
            "subcategory":"Tools & Machinery",
            "type":"Manufacturing & Wholesale Goods"
        }
    ],
    "sg:phone":"+1 302 322 0460",
    "sg:postcode":"19720",
    "sg:province":"DE",
    "sg:tags":[
        "laboratory",
        "design",
        "installation",
        "sales",
        "furniture"
    ],
    "wof:name":"L F Systems Corp",
    "wof:placetype":"venue"
},
  "geometry": {"coordinates":[-75.629486,39.682841],"type":"Point"}
}