{
  "type": "Feature",
  "properties": {
    "addr:full":"3412 Buttonwood St Dover DE 19901",
    "addr:housenumber":"3412",
    "addr:postcode":"19901",
    "addr:street":"Buttonwood St",
    "iso:country":"US",
    "sg:address":"3412 Buttonwood St",
    "sg:city":"Dover",
    "sg:classifiers":[
        {
            "category":"Professional",
            "subcategory":"Management & Consulting",
            "type":"Services"
        }
    ],
    "sg:phone":"+1 302 735 4918",
    "sg:postcode":"19901",
    "sg:province":"DE",
    "sg:tags":[
        "government",
        "contract",
        "residing"
    ],
    "wof:name":"Carla Headen",
    "wof:placetype":"venue"
},
  "geometry": {"coordinates":[-75.491124,39.121784],"type":"Point"}
}