{
  "type": "Feature",
  "properties": {
    "iso:country":"US",
    "sg:address":"21 N State St",
    "sg:city":"Dover",
    "sg:classifiers":[
        {
            "category":"Health Services",
            "subcategory":"Health Practitioner",
            "type":"Services"
        }
    ],
    "sg:phone":"+1 302 730 8200",
    "sg:postcode":"19901",
    "sg:province":"DE",
    "sg:tags":[
        "therapy",
        "physical"
    ],
    "wof:name":"West Side Physical Therapy",
    "wof:placetype":"venue"
},
  "geometry": {"coordinates":[-75.525724,39.161994],"type":"Point"}
}