{
  "type": "Feature",
  "properties": {
    "iso:country":"US",
    "sg:address":"1639 E Ayre St",
    "sg:city":"Newport",
    "sg:classifiers":[
        {
            "category":"Retail",
            "subcategory":"Auto Repair",
            "type":"Services"
        }
    ],
    "sg:phone":"+1 302 994 3901",
    "sg:postcode":"19804",
    "sg:province":"DE",
    "sg:tags":[
        "body",
        "automobile",
        "painting"
    ],
    "wof:name":"Car Care Auto Body",
    "wof:placetype":"venue"
},
  "geometry": {"coordinates":[-75.602227,39.713635],"type":"Point"}
}