{
  "type": "Feature",
  "properties": {
    "iso:country":"US",
    "sg:address":"312 N Broad St",
    "sg:city":"Middletown",
    "sg:classifiers":[
        {
            "category":"Personal",
            "subcategory":"Beauty Salon",
            "type":"Services"
        }
    ],
    "sg:phone":"+1 302 378 4405",
    "sg:postcode":"19709",
    "sg:province":"DE",
    "sg:tags":[
        "shop"
    ],
    "wof:name":"Professional Haircare By Appoi",
    "wof:placetype":"venue"
},
  "geometry": {"coordinates":[-75.717704,39.452688],"type":"Point"}
}