{
  "type": "Feature",
  "properties": {
    "iso:country":"US",
    "sg:address":"405 Foulk Rd",
    "sg:city":"Wilmington",
    "sg:classifiers":[
        {
            "category":"Social Services",
            "type":"Services"
        }
    ],
    "sg:phone":"+1 302 655 3953",
    "sg:postcode":"19803",
    "sg:province":"DE",
    "sg:tags":[
        "counselor",
        "marriage",
        "family"
    ],
    "wof:name":"Survivors Of Abuse In Recovery",
    "wof:placetype":"venue"
},
  "geometry": {"coordinates":[-75.542524,39.779554],"type":"Point"}
}