{
  "type": "Feature",
  "properties": {
    "addr:full":"244 Steeplechase Cir Wilmington DE 19808",
    "addr:housenumber":"244",
    "addr:postcode":"19808",
    "addr:street":"Steeplechase Cir",
    "iso:country":"US",
    "sg:address":"244 Steeplechase Cir",
    "sg:city":"Wilmington",
    "sg:classifiers":[
        {
            "category":"Professional",
            "type":"Services"
        },
        {
            "category":"Professional",
            "subcategory":"Business Services",
            "type":"Services"
        }
    ],
    "sg:phone":"+1 302 235 2008",
    "sg:postcode":"19808",
    "sg:province":"DE",
    "sg:tags":[
        "interior",
        "consultant",
        "design",
        "decorator"
    ],
    "wof:name":"Studio 244",
    "wof:placetype":"venue"
},
  "geometry": {"coordinates":[-75.68962999999999,39.75044],"type":"Point"}
}