{
  "type": "Feature",
  "properties": {
    "iso:country":"US",
    "sg:address":"501 Silverside Rd",
    "sg:city":"Wilmington",
    "sg:classifiers":[
        {
            "category":"Professional",
            "subcategory":"Business Services",
            "type":"Services"
        }
    ],
    "sg:phone":"+1 561 202 7618",
    "sg:postcode":"19809",
    "sg:province":"DE",
    "wof:name":"Cnn Technologies",
    "wof:placetype":"venue"
},
  "geometry": {"coordinates":[-75.48805900000001,39.79023],"type":"Point"}
}