{
  "type": "Feature",
  "properties": {
    "iso:country":"US",
    "sg:address":"4304 Berrytown Rd",
    "sg:city":"Camden Wyoming",
    "sg:classifiers":[
        {
            "category":"Building & Trades",
            "subcategory":"Construction",
            "type":"Services"
        }
    ],
    "sg:phone":"+1 302 697 0235",
    "sg:postcode":"19934",
    "sg:province":"DE",
    "sg:tags":[
        "masonry",
        "contractor"
    ],
    "wof:name":"J D & Sons Masonry & HM Imprvs",
    "wof:placetype":"venue"
},
  "geometry": {"coordinates":[-75.610714,39.065918],"type":"Point"}
}