{
  "type": "Feature",
  "properties": {
    "addr:full":"231 David Hall Rd Dover DE 19904",
    "addr:housenumber":"231",
    "addr:postcode":"19904",
    "addr:street":"David Hall Rd",
    "iso:country":"US",
    "sg:address":"231 David Hall Rd",
    "sg:city":"Dover",
    "sg:classifiers":[
        {
            "category":"Manufacturing",
            "subcategory":"Watercraft",
            "type":"Manufacturing & Wholesale Goods"
        }
    ],
    "sg:phone":"+1 302 678 5893",
    "sg:postcode":"19904",
    "sg:province":"DE",
    "wof:name":"Asm Enterprises",
    "wof:placetype":"venue"
},
  "geometry": {"coordinates":[-75.53373000000001,39.131564],"type":"Point"}
}