{
  "type": "Feature",
  "properties": {
    "iso:country":"US",
    "sg:address":"1201 N Market St",
    "sg:city":"Wilmington",
    "sg:classifiers":[
        {
            "category":"Banks & Credit Unions",
            "subcategory":"Bank",
            "type":"Services"
        }
    ],
    "sg:phone":"+1 302 984 4505",
    "sg:postcode":"19801",
    "sg:province":"DE",
    "wof:name":"Diamond State Fed Credit Union",
    "wof:placetype":"venue"
},
  "geometry": {"coordinates":[-75.54606699999999,39.748169],"type":"Point"}
}