{
  "type": "Feature",
  "properties": {
    "iso:country":"US",
    "sg:address":"601 Banyan Rd",
    "sg:city":"Newark",
    "sg:classifiers":[
        {
            "category":"Building & Trades",
            "subcategory":"Construction",
            "type":"Services"
        }
    ],
    "sg:phone":"+1 302 455 0769",
    "sg:postcode":"19713",
    "sg:province":"DE",
    "sg:tags":[
        "house",
        "general",
        "contractor"
    ],
    "wof:name":"Profound Construction Srv",
    "wof:placetype":"venue"
},
  "geometry": {"coordinates":[-75.714156,39.677863],"type":"Point"}
}