{
  "type": "Feature",
  "properties": {
    "iso:country":"US",
    "sg:address":"201 N Walnut St",
    "sg:city":"Wilmington",
    "sg:classifiers":[
        {
            "category":"Professional",
            "type":"Services"
        }
    ],
    "sg:phone":"+1 302 426 2660",
    "sg:postcode":"19801",
    "sg:province":"DE",
    "sg:tags":[
        "establishment"
    ],
    "wof:name":"TCG",
    "wof:placetype":"venue"
},
  "geometry": {"coordinates":[-75.549397,39.738157],"type":"Point"}
}