{
  "type": "Feature",
  "properties": {
    "addr:full":"910 S Chapel St Newark DE 19713",
    "addr:housenumber":"910",
    "addr:postcode":"19713",
    "addr:street":"S Chapel St",
    "iso:country":"US",
    "sg:address":"910 S Chapel St",
    "sg:city":"Newark",
    "sg:classifiers":[
        {
            "category":"Real Estate",
            "subcategory":"Real Estate Services",
            "type":"Services"
        },
        {
            "category":"Real Estate",
            "subcategory":"Real Estate Agent",
            "type":"Services"
        }
    ],
    "sg:phone":"+1 302 283 1800",
    "sg:postcode":"19713",
    "sg:province":"DE",
    "sg:tags":[
        "buyer",
        "management",
        "broker"
    ],
    "wof:name":"Diamond State Management Inc",
    "wof:placetype":"venue"
},
  "geometry": {"coordinates":[-75.735023,39.65836],"type":"Point"}
}