{
  "type": "Feature",
  "properties": {
    "addr:full":"7317 Hickman Rd Greenwood DE 19950",
    "addr:housenumber":"7317",
    "addr:postcode":"19950",
    "addr:street":"Hickman Rd",
    "iso:country":"US",
    "sg:address":"7317 Hickman Rd",
    "sg:city":"Greenwood",
    "sg:classifiers":[
        {
            "category":"Farming",
            "subcategory":"Farm",
            "type":"Manufacturing & Wholesale Goods"
        }
    ],
    "sg:phone":"+1 302 349 5342",
    "sg:postcode":"19950",
    "sg:province":"DE",
    "wof:name":"Richfield Farms Inc",
    "wof:placetype":"venue"
},
  "geometry": {"coordinates":[-75.61118,38.805315],"type":"Point"}
}