{
  "type": "Feature",
  "properties": {
    "addr:full":"3717 Philadelphia Pike Claymont DE 19703",
    "addr:housenumber":"3717",
    "addr:postcode":"19703",
    "addr:street":"Philadelphia Pike",
    "iso:country":"US",
    "sg:address":"3717 Philadelphia Pike",
    "sg:city":"Claymont",
    "sg:classifiers":[
        {
            "category":"Organizations",
            "subcategory":"Religious Organization",
            "type":"Services"
        }
    ],
    "sg:phone":"+1 302 798 6683",
    "sg:postcode":"19703",
    "sg:province":"DE",
    "sg:tags":[
        "church"
    ],
    "wof:name":"Church Of The Ascension",
    "wof:placetype":"venue"
},
  "geometry": {"coordinates":[-75.45343699999999,39.805035],"type":"Point"}
}