{
  "type": "Feature",
  "properties": {
    "iso:country":"US",
    "sg:address":"1 Stearrett Dr",
    "sg:city":"Newark",
    "sg:classifiers":[
        {
            "category":"Professional",
            "subcategory":"Management & Consulting",
            "type":"Services"
        }
    ],
    "sg:phone":"+1 302 738 2679",
    "sg:postcode":"19702",
    "sg:province":"DE",
    "sg:tags":[
        "consultant",
        "business"
    ],
    "wof:name":"American-African Services Inc",
    "wof:placetype":"venue"
},
  "geometry": {"coordinates":[-75.69588,39.63687],"type":"Point"}
}