{
  "type": "Feature",
  "properties": {
    "iso:country":"US",
    "sg:address":"202 Village Rd",
    "sg:city":"Wilmington",
    "sg:classifiers":[
        {
            "category":"Building & Trades",
            "subcategory":"Construction",
            "type":"Services"
        }
    ],
    "sg:phone":"+1 302 427 9114",
    "sg:postcode":"19805",
    "sg:province":"DE",
    "sg:tags":[
        "contractor"
    ],
    "wof:name":"Colemans General Contracting",
    "wof:placetype":"venue"
},
  "geometry": {"coordinates":[-75.59052,39.748327],"type":"Point"}
}