{
  "type": "Feature",
  "properties": {
    "iso:country":"US",
    "sg:address":"1203 Montgomery Rd",
    "sg:city":"Wilmington",
    "sg:classifiers":[
        {
            "category":"Shopping",
            "type":"Retail Goods"
        }
    ],
    "sg:phone":"+1 302 996 0389",
    "sg:postcode":"19805",
    "sg:province":"DE",
    "sg:tags":[
        "merchandise"
    ],
    "wof:name":"Pictures N Paintings",
    "wof:placetype":"venue"
},
  "geometry": {"coordinates":[-75.603646,39.744704],"type":"Point"}
}