{
  "type": "Feature",
  "properties": {
    "iso:country":"US",
    "sg:address":"65 Carver Rd",
    "sg:city":"Dover",
    "sg:classifiers":[
        {
            "category":"Education",
            "subcategory":"School",
            "type":"Public Place"
        }
    ],
    "sg:phone":"+1 302 672 1620",
    "sg:postcode":"19904",
    "sg:province":"DE",
    "wof:name":"William Henry Middle School",
    "wof:placetype":"venue"
},
  "geometry": {"coordinates":[-75.541915,39.16108],"type":"Point"}
}