{
  "type": "Feature",
  "properties": {
    "iso:country":"US",
    "sg:address":"47 S West St",
    "sg:city":"Dover",
    "sg:classifiers":[
        {
            "category":"Shopping",
            "subcategory":"Used Merchandise",
            "type":"Retail Goods"
        }
    ],
    "sg:phone":"+1 302 678 4626",
    "sg:postcode":"19904",
    "sg:province":"DE",
    "sg:tags":[
        "contractor",
        "supply"
    ],
    "wof:name":"Bay Contractors Supply Co",
    "wof:placetype":"venue"
},
  "geometry": {"coordinates":[-75.53277199999999,39.159188],"type":"Point"}
}