{
  "type": "Feature",
  "properties": {
    "addr:full":"74 E Main St Newark DE 19711",
    "addr:housenumber":"74",
    "addr:postcode":"19711",
    "addr:street":"E Main St",
    "iso:country":"US",
    "sg:address":"74 E Main St",
    "sg:city":"Newark",
    "sg:classifiers":[
        {
            "category":"Shopping",
            "subcategory":"Clothing, Apparel, & Fashions",
            "type":"Retail Goods"
        }
    ],
    "sg:phone":"+1 302 369 5440",
    "sg:postcode":"19711",
    "sg:province":"DE",
    "wof:name":"Stepping Out",
    "wof:placetype":"venue"
},
  "geometry": {"coordinates":[-75.75179199999999,39.683208],"type":"Point"}
}