{
  "type": "Feature",
  "properties": {
    "iso:country":"US",
    "sg:address":"1 Aig Ctr",
    "sg:city":"Wilmington",
    "sg:classifiers":[
        {
            "category":"Insurance",
            "subcategory":"Hazard Insurance",
            "type":"Services"
        }
    ],
    "sg:phone":"+1 302 252 4861",
    "sg:postcode":"19803",
    "sg:province":"DE",
    "sg:tags":[
        "commercial",
        "business"
    ],
    "wof:name":"Aig",
    "wof:placetype":"venue"
},
  "geometry": {"coordinates":[-75.544189,39.831287],"type":"Point"}
}