{
  "type": "Feature",
  "properties": {
    "iso:country":"US",
    "sg:address":"360 Fox Hunt Dr",
    "sg:city":"Bear",
    "sg:classifiers":[
        {
            "category":"Health Services",
            "subcategory":"Doctor",
            "type":"Services"
        }
    ],
    "sg:phone":"+1 302 832 3441",
    "sg:postcode":"19701",
    "sg:province":"DE",
    "sg:tags":[
        "gynecologist"
    ],
    "wof:name":"Pike Creek Assoc In Womenscare",
    "wof:placetype":"venue"
},
  "geometry": {"coordinates":[-75.712912,39.608149],"type":"Point"}
}