{
  "type": "Feature",
  "properties": {
    "iso:country":"US",
    "sg:address":"6280 Limestone Rd",
    "sg:city":"Hockessin",
    "sg:classifiers":[
        {
            "category":"Personal",
            "subcategory":"Beauty Salon",
            "type":"Services"
        }
    ],
    "sg:phone":"+1 302 239 0319",
    "sg:postcode":"19707",
    "sg:province":"DE",
    "sg:tags":[
        "shop",
        "tanning",
        "barber"
    ],
    "wof:name":"Advantage Hair Studio",
    "wof:placetype":"venue"
},
  "geometry": {"coordinates":[-75.71232500000001,39.772225],"type":"Point"}
}