{
  "type": "Feature",
  "properties": {
    "iso:country":"US",
    "sg:address":"1140 Alley Mill Rd",
    "sg:city":"Smyrna",
    "sg:classifiers":[
        {
            "category":"Building & Trades",
            "subcategory":"Landscaping Services",
            "type":"Services"
        }
    ],
    "sg:phone":"+1 302 653 0448",
    "sg:postcode":"19977",
    "sg:province":"DE",
    "sg:tags":[
        "ornamental",
        "tree",
        "shrub"
    ],
    "wof:name":"Greenspring Tree & Shrub Inc",
    "wof:placetype":"venue"
},
  "geometry": {"coordinates":[-75.66615899999999,39.320199],"type":"Point"}
}