{
  "type": "Feature",
  "properties": {
    "iso:country":"US",
    "sg:address":"107 Albe Dr",
    "sg:city":"Newark",
    "sg:classifiers":[
        {
            "category":"Freight",
            "type":"Transportation"
        }
    ],
    "sg:phone":"+1 302 455 0123",
    "sg:postcode":"19702",
    "sg:province":"DE",
    "sg:tags":[
        "storage",
        "commercial",
        "trucking",
        "operator",
        "local",
        "special"
    ],
    "wof:name":"Set Free Moving & Storage",
    "wof:placetype":"venue"
},
  "geometry": {"coordinates":[-75.713401,39.650767],"type":"Point"}
}