{
  "type": "Feature",
  "properties": {
    "iso:country":"US",
    "sg:address":"21 Keller Rd",
    "sg:city":"Newark",
    "sg:classifiers":[
        {
            "category":"Building & Trades",
            "subcategory":"Construction",
            "type":"Services"
        }
    ],
    "sg:phone":"+1 302 366 8746",
    "sg:postcode":"19713",
    "sg:province":"DE",
    "sg:tags":[
        "home",
        "remodeling",
        "family",
        "new"
    ],
    "wof:name":"Fenimore Construction Inc",
    "wof:placetype":"venue"
},
  "geometry": {"coordinates":[-75.73401,39.659041],"type":"Point"}
}