{
  "type": "Feature",
  "properties": {
    "iso:country":"US",
    "sg:address":"915 Waterlily Ln",
    "sg:city":"Middletown",
    "sg:classifiers":[
        {
            "category":"Building & Trades",
            "subcategory":"Construction",
            "type":"Services"
        }
    ],
    "sg:phone":"+1 302 322 1505",
    "sg:postcode":"19709",
    "sg:province":"DE",
    "sg:tags":[
        "builder",
        "repairer",
        "chimney"
    ],
    "wof:name":"Roger Rullo Brick Pointing",
    "wof:placetype":"venue"
},
  "geometry": {"coordinates":[-75.711894,39.517885],"type":"Point"}
}