{
  "type": "Feature",
  "properties": {
    "iso:country":"US",
    "sg:address":"222 Railroad Ave",
    "sg:city":"Dover",
    "sg:classifiers":[
        {
            "category":"Retail",
            "subcategory":"Repair Shop",
            "type":"Services"
        }
    ],
    "sg:phone":"+1 302 674 5354",
    "sg:postcode":"19904",
    "sg:province":"DE",
    "sg:tags":[
        "scooter",
        "motorcycle",
        "motor"
    ],
    "wof:name":"Wilford's Cycles Svc & Repair",
    "wof:placetype":"venue"
},
  "geometry": {"coordinates":[-75.53178800000001,39.156018],"type":"Point"}
}