{
  "type": "Feature",
  "properties": {
    "addr:full":"128 Lantana Dr Hockessin DE 19707",
    "addr:housenumber":"128",
    "addr:postcode":"19707",
    "addr:street":"Lantana Dr",
    "iso:country":"US",
    "sg:address":"128 Lantana Dr",
    "sg:city":"Hockessin",
    "sg:classifiers":[
        {
            "category":"Banks & Credit Unions",
            "subcategory":"Bank",
            "type":"Services"
        }
    ],
    "sg:phone":"+1 800 635 5662",
    "sg:postcode":"19707",
    "sg:province":"DE",
    "sg:tags":[
        "banking",
        "facility"
    ],
    "wof:name":"Mellon",
    "wof:placetype":"venue"
},
  "geometry": {"coordinates":[-75.71108099999999,39.774469],"type":"Point"}
}