{
  "type": "Feature",
  "properties": {
    "addr:full":"1800 Naamans Rd Wilmington DE 19810",
    "addr:housenumber":"1800",
    "addr:postcode":"19810",
    "addr:street":"Naamans Rd",
    "iso:country":"US",
    "sg:address":"1800 Naamans Rd",
    "sg:city":"Wilmington",
    "sg:classifiers":[
        {
            "category":"Sports & Exercise",
            "subcategory":"Gym",
            "type":"Entertainment"
        }
    ],
    "sg:phone":"+1 302 529 1865",
    "sg:postcode":"19810",
    "sg:province":"DE",
    "sg:tags":[
        "trainer",
        "club",
        "health",
        "studio",
        "gymnasium"
    ],
    "wof:name":"Kirkwood Fitness & Racquetball Clubs",
    "wof:placetype":"venue"
},
  "geometry": {"coordinates":[-75.489502,39.823002],"type":"Point"}
}