{
  "type": "Feature",
  "properties": {
    "iso:country":"US",
    "sg:address":"400 Stanton Christiana Rd",
    "sg:city":"Newark",
    "sg:classifiers":[
        {
            "category":"Professional",
            "subcategory":"Management & Consulting",
            "type":"Services"
        }
    ],
    "sg:phone":"+1 302 454 3190",
    "sg:postcode":"19702",
    "sg:province":"DE",
    "sg:tags":[
        "food"
    ],
    "wof:name":"Del-Tech Cafeteria",
    "wof:placetype":"venue"
},
  "geometry": {"coordinates":[-75.65448499999999,39.688643],"type":"Point"}
}