{
  "type": "Feature",
  "properties": {
    "iso:country":"US",
    "sg:address":"171 N Dupont Hwy",
    "sg:city":"Dover",
    "sg:classifiers":[
        {
            "category":"Travel",
            "subcategory":"Travel Agent",
            "type":"Entertainment"
        }
    ],
    "sg:phone":"+1 302 678 3747",
    "sg:postcode":"19901",
    "sg:province":"DE",
    "sg:tags":[
        "agency"
    ],
    "wof:name":"Gullivers Travel & Cruise Ctr",
    "wof:placetype":"venue"
},
  "geometry": {"coordinates":[-75.51653899999999,39.16635],"type":"Point"}
}