{
  "type": "Feature",
  "properties": {
    "iso:country":"US",
    "sg:address":"1401 Foulk Rd",
    "sg:city":"Wilmington",
    "sg:classifiers":[
        {
            "category":"Health Services",
            "subcategory":"Doctor",
            "type":"Services"
        }
    ],
    "sg:phone":"+1 302 478 1180",
    "sg:postcode":"19803",
    "sg:province":"DE",
    "sg:tags":[
        "practice",
        "family"
    ],
    "wof:name":"Brandywine Family Medicine",
    "wof:placetype":"venue"
},
  "geometry": {"coordinates":[-75.52619900000001,39.7929],"type":"Point"}
}