{
  "type": "Feature",
  "properties": {
    "iso:country":"US",
    "sg:address":"2501 Mc Cawber Dr",
    "sg:city":"Wilmington",
    "sg:classifiers":[
        {
            "category":"Building & Trades",
            "subcategory":"Plumbing",
            "type":"Services"
        }
    ],
    "sg:phone":"+1 302 998 3648",
    "sg:postcode":"19808",
    "sg:province":"DE",
    "sg:tags":[
        "plumbing",
        "heating",
        "contractor"
    ],
    "wof:name":"Del Campo Plumbing & Heating",
    "wof:placetype":"venue"
},
  "geometry": {"coordinates":[-75.659903,39.730992],"type":"Point"}
}