{
  "type": "Feature",
  "properties": {
    "addr:full":"2227 Centerville Rd Wilmington DE 19808",
    "addr:housenumber":"2227",
    "addr:postcode":"19808",
    "addr:street":"Centerville Rd",
    "iso:country":"US",
    "sg:address":"2227 Centerville Rd",
    "sg:city":"Wilmington",
    "sg:classifiers":[
        {
            "category":"Building & Trades",
            "subcategory":"Cleaning & Sanitation",
            "type":"Services"
        }
    ],
    "sg:phone":"+1 302 995 5633",
    "sg:postcode":"19808",
    "sg:province":"DE",
    "sg:tags":[
        "fireplace",
        "chimney"
    ],
    "wof:name":"Chimney Aid",
    "wof:placetype":"venue"
},
  "geometry": {"coordinates":[-75.62391100000001,39.745414],"type":"Point"}
}