{
  "type": "Feature",
  "properties": {
    "iso:country":"US",
    "sg:address":"1812 Foulk Rd",
    "sg:city":"Wilmington",
    "sg:classifiers":[
        {
            "category":"Professional",
            "subcategory":"Accounting & Tax Preparation",
            "type":"Services"
        }
    ],
    "sg:phone":"+1 302 475 2263",
    "sg:postcode":"19810",
    "sg:province":"DE",
    "sg:tags":[
        "bookkeeping",
        "general"
    ],
    "wof:name":"Top Notch Tax",
    "wof:placetype":"venue"
},
  "geometry": {"coordinates":[-75.511842,39.811755],"type":"Point"}
}