{
  "type": "Feature",
  "properties": {
    "addr:full":"2629 W 19th St Wilmington DE 19806",
    "addr:housenumber":"2629",
    "addr:postcode":"19806",
    "addr:street":"W 19Th St",
    "iso:country":"US",
    "sg:address":"2629 W 19th St",
    "sg:city":"Wilmington",
    "sg:classifiers":[
        {
            "category":"Organizations",
            "subcategory":"Religious Organization",
            "type":"Services"
        }
    ],
    "sg:phone":"+1 302 658 1807",
    "sg:postcode":"19806",
    "sg:province":"DE",
    "sg:tags":[
        "church"
    ],
    "wof:name":"Mt Salem United Methodist Chr",
    "wof:placetype":"venue"
},
  "geometry": {"coordinates":[-75.57410299999999,39.764992],"type":"Point"}
}