{
  "type": "Feature",
  "properties": {
    "addr:full":"1400 N French St Wilmington DE 19801",
    "addr:housenumber":"1400",
    "addr:postcode":"19801",
    "addr:street":"N French St",
    "iso:country":"US",
    "sg:address":"1400 N French St",
    "sg:city":"Wilmington",
    "sg:classifiers":[
        {
            "category":"Professional",
            "subcategory":"Secretarial Services",
            "type":"Services"
        }
    ],
    "sg:phone":"+1 302 734 3534",
    "sg:postcode":"19801",
    "sg:province":"DE",
    "sg:tags":[
        "convention",
        "court",
        "reporter"
    ],
    "sg:website":"www.corbettreporting.com",
    "wof:name":"Corbett & Assoc",
    "wof:placetype":"venue"
},
  "geometry": {"coordinates":[-75.54326399999999,39.748932],"type":"Point"}
}