{
  "type": "Feature",
  "properties": {
    "addr:full":"2302 Concord Pike Wilmington DE 19803",
    "addr:housenumber":"2302",
    "addr:postcode":"19803",
    "addr:street":"Concord Pike",
    "iso:country":"US",
    "sg:address":"2302 Concord Pike",
    "sg:city":"Wilmington",
    "sg:classifiers":[
        {
            "category":"Wholesale",
            "subcategory":"Electrical",
            "type":"Manufacturing & Wholesale Goods"
        }
    ],
    "sg:phone":"+1 302 656 5303",
    "sg:postcode":"19803",
    "sg:province":"DE",
    "sg:tags":[
        "electronic"
    ],
    "wof:name":"Audiovox Corporation",
    "wof:placetype":"venue"
},
  "geometry": {"coordinates":[-75.547065,39.793975],"type":"Point"}
}