{
  "type": "Feature",
  "properties": {
    "addr:full":"5716 Kennett Pike Wilmington DE 19807",
    "addr:housenumber":"5716",
    "addr:postcode":"19807",
    "addr:street":"Kennett Pike",
    "iso:country":"US",
    "sg:address":"5716 Kennett Pike",
    "sg:city":"Wilmington",
    "sg:classifiers":[
        {
            "category":"Building & Trades",
            "subcategory":"Construction",
            "type":"Services"
        }
    ],
    "sg:phone":"+1 302 254 5430",
    "sg:postcode":"19807",
    "sg:province":"DE",
    "sg:tags":[
        "contractor"
    ],
    "wof:name":"Clay Creek Tile Works Ltd",
    "wof:placetype":"venue"
},
  "geometry": {"coordinates":[-75.616491,39.82093],"type":"Point"}
}