{
  "type": "Feature",
  "properties": {
    "iso:country":"US",
    "sg:address":"102 Northwind Rd",
    "sg:city":"Bear",
    "sg:classifiers":[
        {
            "category":"Building & Trades",
            "subcategory":"Construction",
            "type":"Services"
        }
    ],
    "sg:phone":"+1 302 227 7283",
    "sg:postcode":"19701",
    "sg:province":"DE",
    "sg:tags":[
        "paving",
        "contractor"
    ],
    "wof:name":"Rock Bottom Paving Inc",
    "wof:placetype":"venue"
},
  "geometry": {"coordinates":[-75.64125,39.642099],"type":"Point"}
}