{
  "type": "Feature",
  "properties": {
    "addr:full":"2617 Carpenter Station Rd Wilmington DE 19810",
    "addr:housenumber":"2617",
    "addr:postcode":"19810",
    "addr:street":"Carpenter Station Rd",
    "iso:country":"US",
    "sg:address":"2617 Carpenter Station Rd",
    "sg:city":"Wilmington",
    "sg:classifiers":[
        {
            "category":"Farming",
            "subcategory":"Farm",
            "type":"Manufacturing & Wholesale Goods"
        }
    ],
    "sg:phone":"+1 302 475 4795",
    "sg:postcode":"19810",
    "sg:province":"DE",
    "wof:name":"Honeysuckle Farms LLC",
    "wof:placetype":"venue"
},
  "geometry": {"coordinates":[-75.464322,39.822949],"type":"Point"}
}