{
  "type": "Feature",
  "properties": {
    "iso:country":"US",
    "sg:address":"303 W 8th St",
    "sg:city":"Wilmington",
    "sg:classifiers":[
        {
            "category":"Manufacturing",
            "subcategory":"Printing",
            "type":"Manufacturing & Wholesale Goods"
        }
    ],
    "sg:phone":"+1 302 656 4432",
    "sg:postcode":"19801",
    "sg:province":"DE",
    "sg:tags":[
        "commercial"
    ],
    "wof:name":"Ace Printers",
    "wof:placetype":"venue"
},
  "geometry": {"coordinates":[-75.551875,39.744548],"type":"Point"}
}