{
  "type": "Feature",
  "properties": {
    "iso:country":"US",
    "sg:address":"641 State Hwy 1",
    "sg:city":"Lewes",
    "sg:classifiers":[
        {
            "category":"Shopping",
            "type":"Retail Goods"
        }
    ],
    "sg:phone":"+1 302 645 2287",
    "sg:postcode":"19958",
    "sg:province":"DE",
    "sg:tags":[
        "merchandise"
    ],
    "wof:name":"Skill Graphics Corp",
    "wof:placetype":"venue"
},
  "geometry": {"coordinates":[-75.202681,38.759917],"type":"Point"}
}