{
  "type": "Feature",
  "properties": {
    "iso:country":"US",
    "sg:address":"4799 Summit Bridge Rd",
    "sg:city":"Middletown",
    "sg:classifiers":[
        {
            "category":"Retail",
            "subcategory":"Auto Repair",
            "type":"Services"
        }
    ],
    "sg:phone":"+1 302 378 4301",
    "sg:postcode":"19709",
    "sg:province":"DE",
    "sg:tags":[
        "general"
    ],
    "wof:name":"Wallis Repair Inc",
    "wof:placetype":"venue"
},
  "geometry": {"coordinates":[-75.717455,39.48822],"type":"Point"}
}