{
  "type": "Feature",
  "properties": {
    "iso:country":"US",
    "sg:address":"400 W 9th St",
    "sg:city":"Wilmington",
    "sg:classifiers":[
        {
            "category":"Professional",
            "type":"Services"
        }
    ],
    "sg:phone":"+1 302 425 3740",
    "sg:postcode":"19801",
    "sg:province":"DE",
    "wof:name":"Ensyn",
    "wof:placetype":"venue"
},
  "geometry": {"coordinates":[-75.552393,39.746297],"type":"Point"}
}