{
  "type": "Feature",
  "properties": {
    "iso:country":"US",
    "sg:address":"107 Ruthar Dr",
    "sg:city":"Newark",
    "sg:classifiers":[
        {
            "category":"Wholesale",
            "subcategory":"Auto Parts",
            "type":"Manufacturing & Wholesale Goods"
        }
    ],
    "sg:phone":"+1 302 369 0505",
    "sg:postcode":"19711",
    "sg:province":"DE",
    "sg:tags":[
        "body",
        "automobile",
        "shop"
    ],
    "wof:name":"Kayfield Automotive Paints",
    "wof:placetype":"venue"
},
  "geometry": {"coordinates":[-75.690562,39.691706],"type":"Point"}
}