{
  "type": "Feature",
  "properties": {
    "addr:full":"14 Albe Dr Newark DE 19702",
    "addr:housenumber":"14",
    "addr:postcode":"19702",
    "addr:street":"Albe Dr",
    "iso:country":"US",
    "sg:address":"14 Albe Dr",
    "sg:city":"Newark",
    "sg:classifiers":[
        {
            "category":"Autos & Motor Vehicles",
            "subcategory":"Automobile Sales",
            "type":"Retail Goods"
        }
    ],
    "sg:phone":"+1 302 733 0551",
    "sg:postcode":"19702",
    "sg:province":"DE",
    "sg:tags":[
        "dealers-used",
        "car",
        "used",
        "cars-wholesale"
    ],
    "wof:name":"Trainee Autosales",
    "wof:placetype":"venue"
},
  "geometry": {"coordinates":[-75.715012,39.646732],"type":"Point"}
}