{
  "type": "Feature",
  "properties": {
    "addr:full":"27 Landers Ln New Castle DE 19720",
    "addr:housenumber":"27",
    "addr:postcode":"19720",
    "addr:street":"Landers Ln",
    "iso:country":"US",
    "sg:address":"27 Landers Ln",
    "sg:city":"New Castle",
    "sg:classifiers":[
        {
            "category":"Education",
            "subcategory":"School",
            "type":"Public Place"
        }
    ],
    "sg:phone":"+1 302 429 4073",
    "sg:postcode":"19720",
    "sg:province":"DE",
    "sg:tags":[
        "elementary"
    ],
    "wof:name":"Eisenburg Elementary School",
    "wof:placetype":"venue"
},
  "geometry": {"coordinates":[-75.559459,39.688991],"type":"Point"}
}