{
  "type": "Feature",
  "properties": {
    "iso:country":"US",
    "sg:address":"1327 Rodman Rd",
    "sg:city":"Wilmington",
    "sg:classifiers":[
        {
            "category":"Retail",
            "subcategory":"Portrait Studio",
            "type":"Services"
        }
    ],
    "sg:phone":"+1 302 275 9128",
    "sg:postcode":"19805",
    "sg:province":"DE",
    "sg:tags":[
        "photo"
    ],
    "wof:name":"Fsg Photography",
    "wof:placetype":"venue"
},
  "geometry": {"coordinates":[-75.584157,39.740964],"type":"Point"}
}