{
  "type": "Feature",
  "properties": {
    "iso:country":"US",
    "sg:address":"205 N Dupont Blvd",
    "sg:city":"Smyrna",
    "sg:classifiers":[
        {
            "category":"Autos & Motor Vehicles",
            "subcategory":"Automobile Sales",
            "type":"Retail Goods"
        }
    ],
    "sg:phone":"+1 302 653 6166",
    "sg:postcode":"19977",
    "sg:province":"DE",
    "sg:tags":[
        "car",
        "used",
        "dealer"
    ],
    "wof:name":"Colonial Motors Inc",
    "wof:placetype":"venue"
},
  "geometry": {"coordinates":[-75.605581,39.304872],"type":"Point"}
}