{
  "type": "Feature",
  "properties": {
    "addr:full":"29 Atlantic Ave Ocean View DE 19970",
    "addr:housenumber":"29",
    "addr:postcode":"19970",
    "addr:street":"Atlantic Ave",
    "iso:country":"US",
    "sg:address":"29 Atlantic Ave",
    "sg:city":"Ocean View",
    "sg:classifiers":[
        {
            "category":"Sports & Exercise",
            "subcategory":"Gym",
            "type":"Entertainment"
        }
    ],
    "sg:phone":"+1 302 541 4400",
    "sg:postcode":"19970",
    "sg:province":"DE",
    "sg:tags":[
        "club",
        "health",
        "studio",
        "gymnasium"
    ],
    "wof:name":"Curves For Women",
    "wof:placetype":"venue"
},
  "geometry": {"coordinates":[-75.08117,38.542781],"type":"Point"}
}