{
  "type": "Feature",
  "properties": {
    "addr:full":"221 E Flagstone Dr Newark DE 19702",
    "addr:housenumber":"221",
    "addr:postcode":"19702",
    "addr:street":"E Flagstone Dr",
    "iso:country":"US",
    "sg:address":"221 E Flagstone Dr",
    "sg:city":"Newark",
    "sg:classifiers":[
        {
            "category":"Professional",
            "subcategory":"Art Services",
            "type":"Services"
        }
    ],
    "sg:phone":"+1 302 369 9000",
    "sg:postcode":"19702",
    "sg:province":"DE",
    "sg:tags":[
        "photographer"
    ],
    "wof:name":"Patrick S Crowe Photographer",
    "wof:placetype":"venue"
},
  "geometry": {"coordinates":[-75.709322,39.634252],"type":"Point"}
}