{
  "type": "Feature",
  "properties": {
    "iso:country":"US",
    "sg:address":"902 Savannah Rd",
    "sg:city":"Lewes",
    "sg:classifiers":[
        {
            "category":"Professional",
            "subcategory":"Business Services",
            "type":"Services"
        }
    ],
    "sg:phone":"+1 302 644 2900",
    "sg:postcode":"19958",
    "sg:province":"DE",
    "sg:tags":[
        "profit",
        "fund",
        "raising",
        "organization"
    ],
    "wof:name":"Beebe Medical Foundation",
    "wof:placetype":"venue"
},
  "geometry": {"coordinates":[-75.146518,38.767424],"type":"Point"}
}