{
  "type": "Feature",
  "properties": {
    "iso:country":"US",
    "sg:address":"4 S Main St",
    "sg:city":"Selbyville",
    "sg:classifiers":[
        {
            "category":"Wholesale",
            "subcategory":"Drugs",
            "type":"Manufacturing & Wholesale Goods"
        }
    ],
    "sg:phone":"+1 302 436 7669",
    "sg:postcode":"19975",
    "sg:province":"DE",
    "sg:tags":[
        "pharmaceutical",
        "product"
    ],
    "sg:website":"www.snowbalm.com",
    "wof:name":"Snow Pharmaceutical Inc",
    "wof:placetype":"venue"
},
  "geometry": {"coordinates":[-75.220715,38.459642],"type":"Point"}
}