{
  "type": "Feature",
  "properties": {
    "addr:full":"123 Rehoboth Ave Rehoboth Beach DE 19971",
    "addr:housenumber":"123",
    "addr:postcode":"19971",
    "addr:street":"Rehoboth Ave",
    "iso:country":"US",
    "sg:address":"123 Rehoboth Ave",
    "sg:city":"Rehoboth Beach",
    "sg:classifiers":[
        {
            "category":"Restaurant",
            "type":"Food & Drink"
        }
    ],
    "sg:phone":"+1 302 226 0535",
    "sg:postcode":"19971",
    "sg:province":"DE",
    "sg:tags":[
        "eating"
    ],
    "wof:name":"Madison's Restaurant Inc",
    "wof:placetype":"venue"
},
  "geometry": {"coordinates":[-75.079815,38.71646],"type":"Point"}
}