{
  "type": "Feature",
  "properties": {
    "addr:full":"1 Greentree Dr Dover DE 19904",
    "addr:housenumber":"1",
    "addr:postcode":"19904",
    "addr:street":"Greentree Dr",
    "iso:country":"US",
    "sg:address":"1 Greentree Dr",
    "sg:city":"Dover",
    "sg:classifiers":[
        {
            "category":"Insurance",
            "subcategory":"Insurance Agent",
            "type":"Services"
        }
    ],
    "sg:phone":"+1 302 678 4200",
    "sg:postcode":"19904",
    "sg:province":"DE",
    "wof:name":"International Underwriters Ins",
    "wof:placetype":"venue"
},
  "geometry": {"coordinates":[-75.557411,39.160799],"type":"Point"}
}