{
  "type": "Feature",
  "properties": {
    "iso:country":"US",
    "sg:address":"2014 Baynard Blvd",
    "sg:city":"Wilmington",
    "sg:classifiers":[
        {
            "category":"Real Estate",
            "subcategory":"Architect",
            "type":"Services"
        }
    ],
    "sg:phone":"+1 302 652 2552",
    "sg:postcode":"19802",
    "sg:province":"DE",
    "sg:tags":[
        "architectural"
    ],
    "wof:name":"William E Pelham AIA",
    "wof:placetype":"venue"
},
  "geometry": {"coordinates":[-75.54488499999999,39.757218],"type":"Point"}
}