{
  "type": "Feature",
  "properties": {
    "iso:country":"US",
    "sg:address":"78 W Merchant St",
    "sg:city":"Newark",
    "sg:classifiers":[
        {
            "category":"Manufacturing",
            "subcategory":"Printing",
            "type":"Manufacturing & Wholesale Goods"
        }
    ],
    "sg:phone":"+1 973 344 8545",
    "sg:postcode":"19731",
    "sg:province":"DE",
    "sg:tags":[
        "periodical"
    ],
    "wof:name":"Black Press Clipping Bur Div",
    "wof:placetype":"venue"
},
  "geometry": {"coordinates":[-75.57852200000001,39.515955],"type":"Point"}
}