{
  "type": "Feature",
  "properties": {
    "addr:full":"15 Stone Crop Rd Wilmington DE 19810",
    "addr:housenumber":"15",
    "addr:postcode":"19810",
    "addr:street":"Stone Crop Rd",
    "iso:country":"US",
    "sg:address":"15 Stone Crop Rd",
    "sg:city":"Wilmington",
    "sg:classifiers":[
        {
            "category":"Education",
            "subcategory":"Special Training",
            "type":"Public Place"
        }
    ],
    "sg:phone":"+1 302 475 4913",
    "sg:postcode":"19810",
    "sg:province":"DE",
    "sg:tags":[
        "instruction",
        "music"
    ],
    "wof:name":"Music Room",
    "wof:placetype":"venue"
},
  "geometry": {"coordinates":[-75.50712900000001,39.827982],"type":"Point"}
}