{
  "type": "Feature",
  "properties": {
    "addr:full":"721 E State St Millsboro DE 19966",
    "addr:housenumber":"721",
    "addr:postcode":"19966",
    "addr:street":"E State St",
    "iso:country":"US",
    "sg:address":"721 E State St",
    "sg:city":"Millsboro",
    "sg:classifiers":[
        {
            "category":"Retail",
            "subcategory":"Auto Repair",
            "type":"Services"
        }
    ],
    "sg:phone":"+1 302 934 9552",
    "sg:postcode":"19966",
    "sg:province":"DE",
    "sg:tags":[
        "body",
        "repairing",
        "automobile",
        "removal",
        "dent",
        "painting"
    ],
    "wof:name":"Djs Auto Body",
    "wof:placetype":"venue"
},
  "geometry": {"coordinates":[-75.290993,38.59165],"type":"Point"}
}