{
  "type": "Feature",
  "properties": {
    "iso:country":"US",
    "sg:address":"740 S New St",
    "sg:city":"Dover",
    "sg:classifiers":[
        {
            "category":"Health Services",
            "subcategory":"Doctor",
            "type":"Services"
        }
    ],
    "sg:phone":"+1 302 736 1320",
    "sg:postcode":"19904",
    "sg:province":"DE",
    "sg:tags":[
        "physician",
        "surgeon",
        "urologist"
    ],
    "sg:website":"www.urologyassociatesofdover.com",
    "wof:name":"Urology Associates of Dover PA",
    "wof:placetype":"venue"
},
  "geometry": {"coordinates":[-75.52619900000001,39.1497],"type":"Point"}
}