{
  "type": "Feature",
  "properties": {
    "addr:full":"239 Pavin Ct Newark DE 19702",
    "addr:housenumber":"239",
    "addr:postcode":"19702",
    "addr:street":"Pavin Ct",
    "iso:country":"US",
    "sg:address":"239 Pavin Ct",
    "sg:city":"Newark",
    "sg:classifiers":[
        {
            "category":"Professional",
            "type":"Services"
        }
    ],
    "sg:phone":"+1 302 369 3844",
    "sg:postcode":"19702",
    "sg:province":"DE",
    "wof:name":"Andres R Chindemi",
    "wof:placetype":"venue"
},
  "geometry": {"coordinates":[-75.74903399999999,39.623177],"type":"Point"}
}