{
  "type": "Feature",
  "properties": {
    "iso:country":"US",
    "sg:address":"13209 Seashore Hwy",
    "sg:city":"Georgetown",
    "sg:classifiers":[
        {
            "category":"Restaurant",
            "type":"Food & Drink"
        }
    ],
    "sg:phone":"+1 302 629 9120",
    "sg:postcode":"19947",
    "sg:province":"DE",
    "wof:name":"Skip Jack's Restaurant",
    "wof:placetype":"venue"
},
  "geometry": {"coordinates":[-75.497778,38.699119],"type":"Point"}
}