{
  "type": "Feature",
  "properties": {
    "iso:country":"US",
    "sg:address":"11 Crenshaw Dr",
    "sg:city":"Wilmington",
    "sg:classifiers":[
        {
            "category":"Professional",
            "subcategory":"Accounting & Tax Preparation",
            "type":"Services"
        }
    ],
    "sg:phone":"+1 302 529 0965",
    "sg:postcode":"19810",
    "sg:province":"DE",
    "wof:name":"William F Facciolo CPA",
    "wof:placetype":"venue"
},
  "geometry": {"coordinates":[-75.510262,39.816438],"type":"Point"}
}