{
  "type": "Feature",
  "properties": {
    "iso:country":"US",
    "sg:address":"205 Milford Dr",
    "sg:city":"Middletown",
    "sg:classifiers":[
        {
            "category":"Building & Trades",
            "subcategory":"Construction",
            "type":"Services"
        }
    ],
    "sg:phone":"+1 302 378 7073",
    "sg:postcode":"19709",
    "sg:province":"DE",
    "sg:tags":[
        "house"
    ],
    "wof:name":"Conte Constructin Co",
    "wof:placetype":"venue"
},
  "geometry": {"coordinates":[-75.659834,39.504351],"type":"Point"}
}