{
  "type": "Feature",
  "properties": {
    "iso:country":"US",
    "sg:address":"12 Parkway Cir",
    "sg:city":"New Castle",
    "sg:classifiers":[
        {
            "category":"Retail",
            "subcategory":"Self-service Laundry",
            "type":"Services"
        }
    ],
    "sg:phone":"+1 302 328 0228",
    "sg:postcode":"19720",
    "sg:province":"DE",
    "wof:name":"Laundry Basket",
    "wof:placetype":"venue"
},
  "geometry": {"coordinates":[-75.611869,39.663051],"type":"Point"}
}