{
  "type": "Feature",
  "properties": {
    "iso:country":"US",
    "sg:address":"7503 Lancaster Pike",
    "sg:city":"Hockessin",
    "sg:classifiers":[
        {
            "category":"Health Services",
            "subcategory":"Chiropractor",
            "type":"Services"
        }
    ],
    "sg:phone":"+1 302 234 1115",
    "sg:postcode":"19707",
    "sg:province":"DE",
    "wof:name":"Corrective Chiropractic",
    "wof:placetype":"venue"
},
  "geometry": {"coordinates":[-75.700774,39.790219],"type":"Point"}
}