{
  "type": "Feature",
  "properties": {
    "addr:full":"29 Leader Dr Newark DE 19713",
    "addr:housenumber":"29",
    "addr:postcode":"19713",
    "addr:street":"Leader Dr",
    "iso:country":"US",
    "sg:address":"29 Leader Dr",
    "sg:city":"Newark",
    "sg:classifiers":[
        {
            "category":"Home & Garden",
            "subcategory":"Furniture",
            "type":"Retail Goods"
        }
    ],
    "sg:phone":"+1 302 684 4442",
    "sg:postcode":"19713",
    "sg:province":"DE",
    "wof:name":"J & J Brick Barn Home Furnishn",
    "wof:placetype":"venue"
},
  "geometry": {"coordinates":[-75.716353,39.680764],"type":"Point"}
}