{
  "type": "Feature",
  "properties": {
    "addr:full":"4555 Kirkwood Hwy Wilmington DE 19808",
    "addr:housenumber":"4555",
    "addr:postcode":"19808",
    "addr:street":"Kirkwood Hwy",
    "iso:country":"US",
    "sg:address":"4555 Kirkwood Hwy",
    "sg:city":"Wilmington",
    "sg:classifiers":[
        {
            "category":"Recreation",
            "type":"Entertainment"
        },
        {
            "category":"Shopping",
            "subcategory":"Books",
            "type":"Retail Goods"
        }
    ],
    "sg:phone":"+1 302 994 3156",
    "sg:postcode":"19808",
    "sg:province":"DE",
    "sg:tags":[
        "dealer"
    ],
    "wof:name":"Books & Tobaccos Inc",
    "wof:placetype":"venue"
},
  "geometry": {"coordinates":[-75.655956,39.725007],"type":"Point"}
}