{
  "type": "Feature",
  "properties": {
    "addr:full":"523 Capitol Trl Newark DE 19711",
    "addr:housenumber":"523",
    "addr:postcode":"19711",
    "addr:street":"Capitol Trl",
    "iso:country":"US",
    "sg:address":"523 Capitol Trl",
    "sg:city":"Newark",
    "sg:classifiers":[
        {
            "category":"Health Services",
            "subcategory":"Doctor",
            "type":"Services"
        }
    ],
    "sg:phone":"+1 302 575 8040",
    "sg:postcode":"19711",
    "sg:province":"DE",
    "sg:tags":[
        "physician",
        "surgeon"
    ],
    "wof:name":"St Francis Ctr Of Hope",
    "wof:placetype":"venue"
},
  "geometry": {"coordinates":[-75.72484,39.692256],"type":"Point"}
}