{
  "type": "Feature",
  "properties": {
    "iso:country":"US",
    "sg:address":"1604 E Ayre St",
    "sg:city":"Wilmington",
    "sg:classifiers":[
        {
            "category":"Building & Trades",
            "subcategory":"Electrical",
            "type":"Services"
        },
        {
            "category":"Building & Trades",
            "subcategory":"Construction",
            "type":"Services"
        }
    ],
    "sg:phone":"+1 302 994 3371",
    "sg:postcode":"19804",
    "sg:province":"DE",
    "sg:tags":[
        "installation",
        "contractor"
    ],
    "wof:name":"3 D Installations",
    "wof:placetype":"venue"
},
  "geometry": {"coordinates":[-75.60247099999999,39.713432],"type":"Point"}
}