{
  "type": "Feature",
  "properties": {
    "addr:full":"612 S Dual Hwy Seaford DE 19973",
    "addr:housenumber":"612",
    "addr:postcode":"19973",
    "addr:street":"S Dual Hwy",
    "iso:country":"US",
    "sg:address":"612 S Dual Hwy",
    "sg:city":"Seaford",
    "sg:classifiers":[
        {
            "category":"Professional",
            "subcategory":"Accounting & Tax Preparation",
            "type":"Services"
        }
    ],
    "sg:phone":"+1 302 629 9840",
    "sg:postcode":"19973",
    "sg:province":"DE",
    "sg:tags":[
        "return",
        "filing"
    ],
    "wof:name":"H & R Block Tax Svc",
    "wof:placetype":"venue"
},
  "geometry": {"coordinates":[-75.592855,38.635639],"type":"Point"}
}