{
  "type": "Feature",
  "properties": {
    "addr:full":"9 Chesmar Plz Newark DE 19713",
    "addr:housenumber":"9",
    "addr:postcode":"19713",
    "addr:street":"Chesmar Plz",
    "iso:country":"US",
    "sg:address":"9 Chesmar Plz",
    "sg:city":"Newark",
    "sg:classifiers":[
        {
            "category":"Wholesale",
            "subcategory":"Auto Parts",
            "type":"Manufacturing & Wholesale Goods"
        }
    ],
    "sg:phone":"+1 302 368 1644",
    "sg:postcode":"19713",
    "sg:province":"DE",
    "sg:tags":[
        "automobile",
        "supply",
        "automotive"
    ],
    "sg:website":"http://brakeserviceco.com",
    "wof:name":"Brake Service Co Inc",
    "wof:placetype":"venue"
},
  "geometry": {"coordinates":[-75.727626,39.662283],"type":"Point"}
}