{
  "type": "Feature",
  "properties": {
    "iso:country":"US",
    "sg:address":"1266 Middletown Warwick Rd",
    "sg:city":"Middletown",
    "sg:classifiers":[
        {
            "category":"Building & Trades",
            "subcategory":"Cleaning & Sanitation",
            "type":"Services"
        }
    ],
    "sg:phone":"+1 302 376 8633",
    "sg:postcode":"19709",
    "sg:province":"DE",
    "sg:tags":[
        "house"
    ],
    "wof:name":"Maid 4U",
    "wof:placetype":"venue"
},
  "geometry": {"coordinates":[-75.764639,39.418259],"type":"Point"}
}