{
  "type": "Feature",
  "properties": {
    "addr:full":"26 S Market St Seaford DE 19973",
    "addr:housenumber":"26",
    "addr:postcode":"19973",
    "addr:street":"S Market St",
    "iso:country":"US",
    "sg:address":"26 S Market St",
    "sg:city":"Seaford",
    "sg:classifiers":[
        {
            "category":"Real Estate",
            "subcategory":"Developer",
            "type":"Services"
        }
    ],
    "sg:phone":"+1 302 628 8600",
    "sg:postcode":"19973",
    "sg:province":"DE",
    "wof:name":"Blades Economic Development Corp",
    "wof:placetype":"venue"
},
  "geometry": {"coordinates":[-75.610079,38.635822],"type":"Point"}
}