{
  "type": "Feature",
  "properties": {
    "addr:full":"3628 Concord Pike Wilmington DE 19803",
    "addr:housenumber":"3628",
    "addr:postcode":"19803",
    "addr:street":"Concord Pike",
    "iso:country":"US",
    "sg:address":"3628 Concord Pike",
    "sg:city":"Wilmington",
    "sg:classifiers":[
        {
            "category":"Home & Garden",
            "subcategory":"Furniture",
            "type":"Retail Goods"
        }
    ],
    "sg:phone":"+1 302 477 0999",
    "sg:postcode":"19803",
    "sg:province":"DE",
    "sg:tags":[
        "store"
    ],
    "sg:website":"www.visitsimplyhome.com",
    "wof:name":"Simply Home",
    "wof:placetype":"venue"
},
  "geometry": {"coordinates":[-75.54836299999999,39.803979],"type":"Point"}
}