{
  "type": "Feature",
  "properties": {
    "addr:full":"245 S Dupont Blvd Smyrna DE 19977",
    "addr:housenumber":"245",
    "addr:postcode":"19977",
    "addr:street":"S Dupont Blvd",
    "iso:country":"US",
    "sg:address":"245 S Dupont Blvd",
    "sg:city":"Smyrna",
    "sg:classifiers":[
        {
            "category":"Personal",
            "subcategory":"Barber",
            "type":"Services"
        }
    ],
    "sg:phone":"+1 302 653 9008",
    "sg:postcode":"19977",
    "sg:province":"DE",
    "sg:tags":[
        "shop"
    ],
    "wof:name":"Hair Designs By Tracy",
    "wof:placetype":"venue"
},
  "geometry": {"coordinates":[-75.600143,39.297588],"type":"Point"}
}