{
  "type": "Feature",
  "properties": {
    "addr:full":"147 Dodge Dr Smyrna DE 19977",
    "addr:housenumber":"147",
    "addr:postcode":"19977",
    "addr:street":"Dodge Dr",
    "iso:country":"US",
    "sg:address":"147 Dodge Dr",
    "sg:city":"Smyrna",
    "sg:classifiers":[
        {
            "category":"Professional",
            "subcategory":"Computer Services",
            "type":"Services"
        }
    ],
    "sg:phone":"+1 302 653 7305",
    "sg:postcode":"19977",
    "sg:province":"DE",
    "sg:tags":[
        "consultant",
        "designer"
    ],
    "wof:name":"Micro Tek",
    "wof:placetype":"venue"
},
  "geometry": {"coordinates":[-75.592448,39.246564],"type":"Point"}
}