{
  "type": "Feature",
  "properties": {
    "iso:country":"US",
    "sg:address":"844 N King St",
    "sg:city":"Wilmington",
    "sg:classifiers":[
        {
            "category":"Government",
            "subcategory":"Office",
            "type":"Public Place"
        }
    ],
    "sg:phone":"+1 302 573 6364",
    "sg:postcode":"19801",
    "sg:province":"DE",
    "sg:tags":[
        "federal"
    ],
    "wof:name":"US General Svc Adm",
    "wof:placetype":"venue"
},
  "geometry": {"coordinates":[-75.54781,39.743711],"type":"Point"}
}