{
  "type": "Feature",
  "properties": {
    "addr:full":"2036 Foulk Rd Wilmington DE 19810",
    "addr:housenumber":"2036",
    "addr:postcode":"19810",
    "addr:street":"Foulk Rd",
    "iso:country":"US",
    "sg:address":"2036 Foulk Rd",
    "sg:city":"Wilmington",
    "sg:classifiers":[
        {
            "category":"Health Services",
            "subcategory":"Dentist",
            "type":"Services"
        }
    ],
    "sg:phone":"+1 302 475 7640",
    "sg:postcode":"19810",
    "sg:province":"DE",
    "sg:tags":[
        "pediatric"
    ],
    "wof:name":"Maher Rachel A DMD",
    "wof:placetype":"venue"
},
  "geometry": {"coordinates":[-75.509697,39.814301],"type":"Point"}
}