{
  "type": "Feature",
  "properties": {
    "iso:country":"US",
    "sg:address":"1450 Eagles Nest Rd",
    "sg:city":"Smyrna",
    "sg:classifiers":[
        {
            "category":"Building & Trades",
            "subcategory":"Construction",
            "type":"Services"
        }
    ],
    "sg:phone":"+1 302 653 4189",
    "sg:postcode":"19977",
    "sg:province":"DE",
    "sg:tags":[
        "residential"
    ],
    "wof:name":"D&K Construction",
    "wof:placetype":"venue"
},
  "geometry": {"coordinates":[-75.596981,39.355521],"type":"Point"}
}