{
  "type": "Feature",
  "properties": {
    "addr:full":"14 Phyllis Dr Newark DE 19711",
    "addr:housenumber":"14",
    "addr:postcode":"19711",
    "addr:street":"Phyllis Dr",
    "iso:country":"US",
    "sg:address":"14 Phyllis Dr",
    "sg:city":"Newark",
    "sg:classifiers":[
        {
            "category":"Social Services",
            "subcategory":"Child Care",
            "type":"Services"
        }
    ],
    "sg:phone":"+1 302 737 3006",
    "sg:postcode":"19711",
    "sg:province":"DE",
    "sg:tags":[
        "day"
    ],
    "wof:name":"Aunt Pats Day Care",
    "wof:placetype":"venue"
},
  "geometry": {"coordinates":[-75.69875500000001,39.698215],"type":"Point"}
}