{
  "type": "Feature",
  "properties": {
    "addr:full":"124 Christiana Rd Newark DE 19702",
    "addr:housenumber":"124",
    "addr:postcode":"19702",
    "addr:street":"Christiana Rd",
    "iso:country":"US",
    "sg:address":"124 Christiana Rd",
    "sg:city":"Newark",
    "sg:classifiers":[
        {
            "category":"Shopping",
            "subcategory":"Pharmacy",
            "type":"Retail Goods"
        }
    ],
    "sg:phone":"+1 302 366 7432",
    "sg:postcode":"19702",
    "sg:province":"DE",
    "sg:website":"www.cvs.com",
    "wof:name":"CVS Pharmacy",
    "wof:placetype":"venue"
},
  "geometry": {"coordinates":[-75.65887499999999,39.663491],"type":"Point"}
}