{
  "type": "Feature",
  "properties": {
    "iso:country":"US",
    "sg:address":"314 S State St",
    "sg:city":"Dover",
    "sg:classifiers":[
        {
            "category":"Professional",
            "subcategory":"Lawyer & Legal Services",
            "type":"Services"
        }
    ],
    "sg:phone":"+1 302 264 9780",
    "sg:postcode":"19904",
    "sg:province":"DE",
    "sg:tags":[
        "divorce",
        "law",
        "family"
    ],
    "sg:website":"yiengstlaw.com",
    "wof:name":"Law Office of Laura A. Yiengst",
    "wof:placetype":"venue"
},
  "geometry": {"coordinates":[-75.523976,39.156839],"type":"Point"}
}