{
  "type": "Feature",
  "properties": {
    "addr:full":"2803 N Washington St Wilmington DE 19802",
    "addr:housenumber":"2803",
    "addr:postcode":"19802",
    "addr:street":"N Washington St",
    "iso:country":"US",
    "sg:address":"2803 N Washington St",
    "sg:city":"Wilmington",
    "sg:classifiers":[
        {
            "category":"Professional",
            "type":"Services"
        }
    ],
    "sg:phone":"+1 302 761 9294",
    "sg:postcode":"19802",
    "sg:province":"DE",
    "wof:name":"Wendy L Congo",
    "wof:placetype":"venue"
},
  "geometry": {"coordinates":[-75.53534000000001,39.75857],"type":"Point"}
}