{
  "type": "Feature",
  "properties": {
    "iso:country":"US",
    "sg:address":"1200 Capitol Trl",
    "sg:city":"Newark",
    "sg:classifiers":[
        {
            "category":"Personal",
            "subcategory":"Beauty Salon",
            "type":"Services"
        }
    ],
    "sg:phone":"+1 302 292 3511",
    "sg:postcode":"19711",
    "sg:province":"DE",
    "sg:tags":[
        "treatment",
        "skin"
    ],
    "wof:name":"Trilogy Salon & Day Spa",
    "wof:placetype":"venue"
},
  "geometry": {"coordinates":[-75.711853,39.696834],"type":"Point"}
}