{
  "type": "Feature",
  "properties": {
    "addr:full":"3044 New Castle Ave New Castle DE 19720",
    "addr:housenumber":"3044",
    "addr:postcode":"19720",
    "addr:street":"New Castle Ave",
    "iso:country":"US",
    "sg:address":"3044 New Castle Ave",
    "sg:city":"New Castle",
    "sg:classifiers":[
        {
            "category":"Restaurant",
            "type":"Food & Drink"
        }
    ],
    "sg:phone":"+1 302 658 8999",
    "sg:postcode":"19720",
    "sg:province":"DE",
    "wof:name":"Gordon's Pizza",
    "wof:placetype":"venue"
},
  "geometry": {"coordinates":[-75.550875,39.703614],"type":"Point"}
}