{
  "type": "Feature",
  "properties": {
    "iso:country":"US",
    "sg:address":"3301 Concord Pike Ste B",
    "sg:city":"Wilmington",
    "sg:classifiers":[
        {
            "category":"Retail",
            "subcategory":"Laundry & Dry Cleaning",
            "type":"Services"
        }
    ],
    "sg:phone":"+1 302 478 1487",
    "sg:postcode":"19803",
    "sg:province":"DE",
    "wof:name":"Towne & Country Cleaners Inc",
    "wof:placetype":"venue"
},
  "geometry": {"coordinates":[-75.54789700000001,39.801201],"type":"Point"}
}