{
  "type": "Feature",
  "properties": {
    "addr:full":"3482 Judith Rd Dover DE 19904",
    "addr:housenumber":"3482",
    "addr:postcode":"19904",
    "addr:street":"Judith Rd",
    "iso:country":"US",
    "sg:address":"3482 Judith Rd",
    "sg:city":"Dover",
    "sg:classifiers":[
        {
            "category":"Farming",
            "subcategory":"Livestock Farm",
            "type":"Manufacturing & Wholesale Goods"
        }
    ],
    "sg:phone":"+1 302 492 8636",
    "sg:postcode":"19904",
    "sg:province":"DE",
    "sg:tags":[
        "hog",
        "or",
        "feedlot"
    ],
    "wof:name":"Sandy Hill Farms",
    "wof:placetype":"venue"
},
  "geometry": {"coordinates":[-75.671628,39.17945],"type":"Point"}
}