{
  "type": "Feature",
  "properties": {
    "iso:country":"US",
    "sg:address":"2225 Naamans Rd",
    "sg:city":"Wilmington",
    "sg:classifiers":[
        {
            "category":"Building & Trades",
            "subcategory":"Plumbing",
            "type":"Services"
        }
    ],
    "sg:phone":"+1 302 475 7846",
    "sg:postcode":"19810",
    "sg:province":"DE",
    "sg:tags":[
        "contractor"
    ],
    "sg:website":"www.moonplumbing.com",
    "wof:name":"Moon Plumbing Services Inc",
    "wof:placetype":"venue"
},
  "geometry": {"coordinates":[-75.508499,39.826],"type":"Point"}
}