{
  "type": "Feature",
  "properties": {
    "addr:full":"37 Nanticoke Dr Seaford DE 19973",
    "addr:housenumber":"37",
    "addr:postcode":"19973",
    "addr:street":"Nanticoke Dr",
    "iso:country":"US",
    "sg:address":"37 Nanticoke Dr",
    "sg:city":"Seaford",
    "sg:classifiers":[
        {
            "category":"Building & Trades",
            "subcategory":"Plumbing",
            "type":"Services"
        }
    ],
    "sg:phone":"+1 302 628 4220",
    "sg:postcode":"19973",
    "sg:province":"DE",
    "sg:tags":[
        "conditioning",
        "air",
        "system",
        "contractor"
    ],
    "wof:name":"Lifetime Heating & AC",
    "wof:placetype":"venue"
},
  "geometry": {"coordinates":[-75.58455600000001,38.641029],"type":"Point"}
}