{
  "type": "Feature",
  "properties": {
    "iso:country":"US",
    "sg:address":"20915 US Hwy 13",
    "sg:city":"Seaford",
    "sg:classifiers":[
        {
            "category":"Manufacturing",
            "subcategory":"Glass & Minerals",
            "type":"Manufacturing & Wholesale Goods"
        }
    ],
    "sg:phone":"+1 302 628 9933",
    "sg:postcode":"19973",
    "sg:province":"DE",
    "sg:tags":[
        "optical",
        "mfg"
    ],
    "wof:name":"Design Technology",
    "wof:placetype":"venue"
},
  "geometry": {"coordinates":[-75.58954799999999,38.694981],"type":"Point"}
}