{
  "type": "Feature",
  "properties": {
    "iso:country":"US",
    "sg:address":"9859 Middleford Rd",
    "sg:city":"Seaford",
    "sg:classifiers":[
        {
            "category":"Social Services",
            "subcategory":"Child Care",
            "type":"Services"
        }
    ],
    "sg:phone":"+1 302 629 3687",
    "sg:postcode":"19973",
    "sg:province":"DE",
    "sg:tags":[
        "day"
    ],
    "wof:name":"O Day Family Day Care Center",
    "wof:placetype":"venue"
},
  "geometry": {"coordinates":[-75.571971,38.661437],"type":"Point"}
}