{
  "type": "Feature",
  "properties": {
    "iso:country":"US",
    "sg:address":"9 Ivy Hall",
    "sg:city":"Newark",
    "sg:classifiers":[
        {
            "category":"Building & Trades",
            "subcategory":"Construction",
            "type":"Services"
        }
    ],
    "sg:phone":"+1 302 292 1104",
    "sg:postcode":"19711",
    "sg:province":"DE",
    "sg:tags":[
        "hanging",
        "contractor"
    ],
    "wof:name":"D C H Inc",
    "wof:placetype":"venue"
},
  "geometry": {"coordinates":[-75.703147,39.717271],"type":"Point"}
}