{
  "type": "Feature",
  "properties": {
    "iso:country":"US",
    "sg:address":"200 Continental Dr",
    "sg:city":"Newark",
    "sg:classifiers":[
        {
            "category":"Banks & Credit Unions",
            "subcategory":"Investment Brokerage",
            "type":"Services"
        },
        {
            "category":"Banks & Credit Unions",
            "subcategory":"Bank",
            "type":"Services"
        }
    ],
    "sg:phone":"+1 302 292 2524",
    "sg:postcode":"19713",
    "sg:province":"DE",
    "sg:tags":[
        "loan",
        "short",
        "term",
        "financing"
    ],
    "wof:name":"Campbell Finance Corporation",
    "wof:placetype":"venue"
},
  "geometry": {"coordinates":[-75.660782,39.685627],"type":"Point"}
}