{
  "type": "Feature",
  "properties": {
    "iso:country":"US",
    "sg:address":"409 Salt Pond Rd",
    "sg:city":"Bethany Beach",
    "sg:classifiers":[
        {
            "category":"Professional",
            "subcategory":"Business Services",
            "type":"Services"
        }
    ],
    "sg:phone":"+1 302 841 3204",
    "sg:postcode":"19930",
    "sg:province":"DE",
    "wof:name":"Property Solutions LLC",
    "wof:placetype":"venue"
},
  "geometry": {"coordinates":[-75.067548,38.552914],"type":"Point"}
}