{
  "type": "Feature",
  "properties": {
    "iso:country":"US",
    "sg:address":"721 Ferry Cut Off St",
    "sg:city":"New Castle",
    "sg:classifiers":[
        {
            "category":"Food & Beverages",
            "subcategory":"Groceries & Convenience Stores",
            "type":"Retail Goods"
        },
        {
            "category":"Restaurant",
            "type":"Food & Drink"
        }
    ],
    "sg:phone":"+1 302 322 6006",
    "sg:postcode":"19720",
    "sg:province":"DE",
    "sg:tags":[
        "delicatessen"
    ],
    "wof:name":"New Castle Deli",
    "wof:placetype":"venue"
},
  "geometry": {"coordinates":[-75.56696700000001,39.66347],"type":"Point"}
}