{
  "type": "Feature",
  "properties": {
    "iso:country":"US",
    "sg:address":"5 Caxton Dr",
    "sg:city":"New Castle",
    "sg:classifiers":[
        {
            "category":"Building & Trades",
            "subcategory":"Construction",
            "type":"Services"
        }
    ],
    "sg:phone":"+1 302 328 2964",
    "sg:postcode":"19720",
    "sg:province":"DE",
    "sg:tags":[
        "hanging",
        "contractor"
    ],
    "wof:name":"A & N Painting",
    "wof:placetype":"venue"
},
  "geometry": {"coordinates":[-75.637367,39.673178],"type":"Point"}
}