{
  "type": "Feature",
  "properties": {
    "addr:full":"10 Radnor Rd Newark DE 19713",
    "addr:housenumber":"10",
    "addr:postcode":"19713",
    "addr:street":"Radnor Rd",
    "iso:country":"US",
    "sg:address":"10 Radnor Rd",
    "sg:city":"Newark",
    "sg:classifiers":[
        {
            "category":"Organizations",
            "subcategory":"Religious Organization",
            "type":"Services"
        }
    ],
    "sg:phone":"+1 302 738 5907",
    "sg:postcode":"19713",
    "sg:province":"DE",
    "wof:name":"Agape Fellowship Church",
    "wof:placetype":"venue"
},
  "geometry": {"coordinates":[-75.704858,39.67815],"type":"Point"}
}