{
  "type": "Feature",
  "properties": {
    "iso:country":"US",
    "sg:address":"14 Wesley Ave",
    "sg:city":"Frankford",
    "sg:classifiers":[
        {
            "category":"Wholesale",
            "subcategory":"Construction Materials",
            "type":"Manufacturing & Wholesale Goods"
        }
    ],
    "sg:phone":"+1 302 245 7547",
    "sg:postcode":"19945",
    "sg:province":"DE",
    "sg:tags":[
        "fence"
    ],
    "wof:name":"First State Vinyl Railing",
    "wof:placetype":"venue"
},
  "geometry": {"coordinates":[-75.149061,38.54476],"type":"Point"}
}